Workbook
Name AIR: 'BoA - Conventional'!$AIR$4
Name BOAIR: 'BoA - Conventional'!$AIR$4
Name CAPR: 'Wells - Conventional'!$C$5
Name CIR: 'Wells - Conventional'!$C$4
Name CP: 'Wells - Conventional'!$C$6
Name IR: #REF!
Name WIR: 'Wells - Conventional'!$C$4

Sheet Result
C7: 30-year Conforming Conventional | D7: Interest Rate | E7: Points | F7: 1-Point Rate
C8: Bank of America | D8: ='BoA - Conventional'!C4 -> 0.03875 | E8: ='BoA - Conventional'!F7 -> 0.020248436 | F8: ='BoA - Conventional'!I4 -> 0.041312109
C9: Chase | D9: ='Chase - Conventional'!C4 -> 0.04125 | E9: ='Chase - Conventional'!F7 -> 0.0099947928 | F9: ='Chase - Conventional'!I4 -> 0.041248698
C10: Quicken | D10: ='Quicken - Conventional'!C4 -> 0.0375 | E10: ='Quicken - Conventional'!F7 -> 0.027134923 | F10: ='Quicken - Conventional'!I4 -> 0.041783731
C11: Wells Fargo | D11: =CIR -> 0.04 | E11: ='Wells - Conventional'!F9 -> 0.019441773 | F11: ='Wells - Conventional'!I4 -> 0.042360443
C12: Average | D12: =AVERAGE(D8:D11) -> 0.039375 | E12: =AVERAGE(E8:E11) -> 0.019204981 | F12: =AVERAGE(F8:F11) -> 0.041676245

Sheet Wells - Conventional
B2: Input | E2: Intermediate Calculation | H2: Result
B4: Interest Rates | C4: 0.04 | E4: Loan Amount for APR | F4: =((CIR/12*(1+CIR/12)^360)/((1+CIR/12)^360-1)*((1+CAPR/12)^360-1)/(CAPR/12*(1+CAPR/12)^360))*CP -> 198869.65 | H4: 1-point rate | I4: =CIR-(1%-F9)/4 -> 0.042360443
B5: APR | C5: 0.04047 | E5: Points for APR | F5: =1-F4/CP -> 0.0056517728
B6: Loan Amount | C6: 200000 | E6: Points for APR(as Discount Points) | F6: =1-((CIR/12*(1+CIR/12)^360)/((1+CIR/12)^360-1)*((1+CAPR/12)^360-1)/(CAPR/12*(1+CAPR/12)^360)) -> 0.0056517728
B7: Closing costs | C7: 2758
B8: Points | C8: n/a | E8: Origination Points | F8: =C7/CP -> 0.01379
E9: Total Points | F9: =F6+F8 -> 0.019441773
B13: No need to calculate numbers in the gray area

Sheet BoA - Conventional
B2: Input | E2: Intermediate Calculation | H2: Result
B4: Interest Rates | C4: 0.03875 | E4: Points for APR | F4: =1-((C4/12*(1+C4/12)^360)/((1+C4/12)^360-1)*((1+C5/12)^360-1)/(C5/12*(1+C5/12)^360)) -> 0.020248436 | H4: 1-point rate | I4: =C4-(1%-F7)/4 -> 0.041312109
B5: APR | C5: 0.04044 | E5: Discount Point | F5: =C8 -> 0.00893
B6: Loan Amount | C6: 200000 | E6: Origination Points | F6: =F4-C8 -> 0.011318436
B7: Closing costs | C7: n/a | E7: Total Points | F7: =F5+F6 -> 0.020248436
B8: Points | C8: 0.00893
B13: No need to calculate numbers in the gray area

Sheet Chase - Conventional
B2: Input | E2: Intermediate Calculation | H2: Result
B4: Interest Rates | C4: 0.04125 | E4: Points for APR | F4: =1-((C4/12*(1+C4/12)^360)/((1+C4/12)^360-1)*((1+C5/12)^360-1)/(C5/12*(1+C5/12)^360)) -> 0.0099947928 | H4: 1-point rate | I4: =C4-(1%-F7)/4 -> 0.041248698
B5: APR | C5: 0.04209 | E5: Discount Point | F5: =C8 -> 0.01
B6: Loan Amount | C6: 215000 | E6: Origination Points | F6: =F4-C8 -> -5.2071876e-06
B7: Closing costs | C7: n/a | E7: Total Points | F7: =F5+F6 -> 0.0099947928
B8: Points | C8: 0.01
B13: No need to calculate numbers in the gray area

Sheet Quicken - Conventional
B2: Input | E2: Intermediate Calculation | H2: Result
B4: Interest Rates | C4: 0.0375 | E4: Points for APR | F4: =1-((C4/12*(1+C4/12)^360)/((1+C4/12)^360-1)*((1+C5/12)^360-1)/(C5/12*(1+C5/12)^360)) -> 0.027134923 | H4: 1-point rate | I4: =C4-(1%-F7)/4 -> 0.041783731
B5: APR | C5: 0.03976 | E5: Discount Point | F5: =C8 -> 0.01
B6: Loan Amount | C6: 200000 | E6: Origination Points | F6: =F4-C8 -> 0.017134923
B7: Closing costs | C7: n/a | E7: Total Points | F7: =F5+F6 -> 0.027134923
B8: Points | C8: 0.01
B13: No need to calculate numbers in the gray area
