Workbook
Name AIR: #REF!
Name AIR: 'Wells - Jumbo conformin'!$AIR$4
Name AIR: 'Wells - Jumbo Non-conforming'!$AIR$4
Name AIR: 'BoA - Conventional'!$AIR$4
Name BOAIR: #REF!
Name BOAIR: 'Wells - Jumbo conformin'!$AIR$4
Name BOAIR: 'Wells - Jumbo Non-conforming'!$AIR$4
Name BOAIR: 'BoA - Conventional'!$AIR$4
Name CAPR: #REF!
Name CAPR: 'Wells - Conventional'!$C$5
Name CIR: #REF!
Name CIR: 'Wells - Conventional'!$C$4
Name CP: #REF!
Name CP: 'Wells - Conventional'!$C$6
Name IR: #REF!
Name IR: #REF!
Name IR: #REF!
Name IR: #REF!
Name WIR: #REF!
Name WIR: 'Wells - Conventional'!$C$4

Sheet Result
C7: 30-year Conforming Conventional | D7: Interest Rate | G7: APR | J7: Discount Points | K7: Origination Points | L7: Total Points | M7: 1-Point Rate | N7: Servicing Spread | O7: 1D Rate Chg (bps) | P7: 1D SS Chg (bps) | Q7: 1wk Rate Chg (bps) | R7: 1wk SS Chg (bps)
C8: Bank of America | D8: ='BoA - Conventional'!C4 -> 0.04 | G8: ='BoA - Conventional'!C5 -> 0.0417 | J8: ='BoA - Conventional'!F5 -> 0.00713 | K8: ='BoA - Conventional'!F6 -> 0.013089891 | L8: ='BoA - Conventional'!F7 -> 0.020219891 | M8: ='BoA - Conventional'!I4 -> 0.042554973 | N8: =M8-D$24 -> 0.014212973 | O8: =(M8-'Historic Result'!C5)*100*100 -> 8.597817 | P8: =(N8-'Historic Result'!D5)*100*100 -> 1.5972193 | Q8: =(M8-'Historic Result'!E5)*100*100 -> 8.597817 | R8: =(N8-'Historic Result'!F5)*100*100 -> 1.5972193
C9: Chase | D9: ='Chase - Conventional'!C4 -> 0.04125 | G9: ='Chase - Conventional'!C5 -> 0.04219 | J9: n/a | K9: n/a | L9: ='Chase - Conventional'!F7 -> 0.011174724 | M9: ='Chase - Conventional'!I4 -> 0.041543681 | N9: =M9-D$24 -> 0.013201682 | O9: =(M9-'Historic Result'!C6)*100*100 -> -3.2018873 | P9: =(N9-'Historic Result'!D6)*100*100 -> -10.202485 | Q9: =(M9-'Historic Result'!E6)*100*100 -> -3.2018873 | R9: =(N9-'Historic Result'!F6)*100*100 -> -10.202485
C10: Quicken | D10: ='Quicken - Conventional'!C4 -> 0.0375 | G10: ='Quicken - Conventional'!C5 -> 0.04008 | J10: ='Quicken - Conventional'!F5 -> 0.0225 | K10: ='Quicken - Conventional'!F6 -> 0.0083887869 | L10: ='Quicken - Conventional'!F7 -> 0.030888787 | M10: ='Quicken - Conventional'!I4 -> 0.042722197 | N10: =M10-D$24 -> 0.014380197 | O10: =(M10-'Historic Result'!C7)*100*100 -> 6.1526132 | P10: =(N10-'Historic Result'!D7)*100*100 -> -0.8479846 | Q10: =(M10-'Historic Result'!E7)*100*100 -> 6.1526132 | R10: =(N10-'Historic Result'!F7)*100*100 -> -0.8479846
C11: Wells Fargo | D11: =CIR -> 0.04125 | G11: =CAPR -> 0.04147 | J11: ='Wells - Conventional'!F6 -> 0.0026321592 | K11: ='Wells - Conventional'!F8 -> 0.00884 | L11: ='Wells - Conventional'!F9 -> 0.011472159 | M11: ='Wells - Conventional'!I4 -> 0.04161804 | N11: =M11-D$24 -> 0.01327604 | O11: =(M11-'Historic Result'!C8)*100*100 -> -13.838802 | P11: =(N11-'Historic Result'!D8)*100*100 -> -20.839399 | Q11: =(M11-'Historic Result'!E8)*100*100 -> -13.838802 | R11: =(N11-'Historic Result'!F8)*100*100 -> -20.839399
C12: Average | D12: =AVERAGE(D8:D11) -> 0.04 | G12: =AVERAGE(G8:I11) -> 0.04136 | J12: =AVERAGE(J8:J11) -> 0.010754053 | K12: =AVERAGE(K8:K11) -> 0.010106226 | L12: =AVERAGE(L8:L11) -> 0.01843889 | M12: =AVERAGE(M8:M11) -> 0.042109723 | N12: =M12-D$24 -> 0.013767723 | O12: =AVERAGE(O8:O11) -> -0.57256466 | P12: =AVERAGE(P8:P11) -> -7.5731624 | Q12: =AVERAGE(Q8:Q11) -> -0.57256466 | R12: =AVERAGE(R8:R11) -> -7.5731624
C13: 30-year Jumbo Conforming | D13: Interest Rate | G13: APR
C14: Wells Fargo | D14: ='Wells - Jumbo conformin'!C4 -> 0.04125 | G14: ='Wells - Jumbo conformin'!C5 -> 0.04148 | J14: ='Wells - Jumbo conformin'!F5 -> 0.0027515577 | K14: ='Wells - Jumbo conformin'!F6 -> 0.007204 | L14: ='Wells - Jumbo conformin'!F7 -> 0.0099555577 | M14: ='Wells - Jumbo conformin'!I4 -> 0.041238889 | N14: =M14-D$24 -> 0.01289689 | O14: =(M14-'Historic Result'!C11)*100*100 -> 10.435171 | P14: =(N14-'Historic Result'!D11)*100*100 -> 3.4345733 | Q14: =(M14-'Historic Result'!E11)*100*100 -> 10.435171 | R14: =(N14-'Historic Result'!F11)*100*100 -> 3.4345733
C15: 30-year Jumbo Non-Conforming | D15: Interest Rate | G15: APR
C16: Wells Fargo | D16: ='Wells - Jumbo Non-conforming'!C4 -> 0.04125 | G16: ='Wells - Jumbo Non-conforming'!C5 -> 0.04125 | J16: ='Wells - Jumbo Non-conforming'!F5 -> 0 | K16: ='Wells - Jumbo Non-conforming'!F6 -> 0.0016826667 | L16: ='Wells - Jumbo Non-conforming'!F7 -> 0.0016826667 | M16: ='Wells - Jumbo Non-conforming'!I4 -> 0.039170667 | N16: =M16-D$24 -> 0.010828667 | O16: =(M16-'Historic Result'!C13)*100*100 -> 0.24190298 | P16: =(N16-'Historic Result'!D13)*100*100 -> -6.7586948 | Q16: =(M16-'Historic Result'!E13)*100*100 -> 0.24190298 | R16: =(N16-'Historic Result'!F13)*100*100 -> -6.7586948
C17: 30-year FHA | D17: Base Rate | F17: UFMIP | H17: Ann. MIP
C18: Wells Fargo | D18: 0.03875 | F18: 0.0175 | H18: 0.0085 | J18: 0 | K18: 0.01387 | L18: 0.01387 | M18: 0.0397175 | N18: =M18-D25 -> 0.0126435 | O18: =(M18-'Historic Result'!C15)*100*100 -> 0 | P18: =(N18-'Historic Result'!D15)*100*100 -> -3.2742455 | Q18: =(M18-'Historic Result'!E15)*100*100 -> 0 | R18: =(N18-'Historic Result'!F15)*100*100 -> -3.2742455
C22: Current Coupon
C23: Type | D23: Rate
C24: FNMA 30-Year | D24: ='Input Data'!P2/100 -> 0.028341999
C25: GNMA 30-Year | D25: ='Input Data'!P3/100 -> 0.027074

Sheet BoA - Conventional
B2: Input | E2: Intermediate Calculation | H2: Result
B4: Interest Rates | C4: ='Input Data'!E8/100 -> 0.04 | E4: Points for APR | F4: =1-((C4/12*(1+C4/12)^360)/((1+C4/12)^360-1)*((1+C5/12)^360-1)/(C5/12*(1+C5/12)^360)) -> 0.020219891 | H4: 1-point rate | I4: =C4-(1%-F7)/4 -> 0.042554973
B5: APR | C5: ='Input Data'!G8/100 -> 0.0417 | E5: Discount Point | F5: =C8 -> 0.00713
B6: Loan Amount | C6: 200000 | E6: Origination Points | F6: =F4-C8 -> 0.013089891 | H6: One formula for AA Software | I6: =C4-(0.01-(1-((C4/12*(1+C4/12)^360)/((1+C4/12)^360-1)*((1+C5/12)^360-1)/(C5/12*(1+C5/12)^360))))/4 -> 0.042554973
B7: Closing costs | C7: n/a | E7: Total Points | F7: =F5+F6 -> 0.020219891
B8: Points | C8: ='Input Data'!F8/100 -> 0.00713
B13: No need to calculate numbers in the gray area

Sheet Chase - Conventional
B2: Input | E2: Intermediate Calculation | H2: Result
B4: Interest Rates | C4: ='Input Data'!E9/100 -> 0.04125 | E4: Points for APR | F4: =1-((C4/12*(1+C4/12)^360)/((1+C4/12)^360-1)*((1+C5/12)^360-1)/(C5/12*(1+C5/12)^360)) -> 0.011174724 | H4: 1-point rate | I4: =C4-(1%-F7)/4 -> 0.041543681
B5: APR | C5: ='Input Data'!G9/100 -> 0.04219 | E5: Discount Point | F5: =C8 -> 0.01125
B6: Loan Amount | C6: 215000 | E6: Origination Points | F6: =F4-C8 -> -7.5276357e-05 | H6: One formula for AA Software | I6: =C4-(0.01-(1-((C4/12*(1+C4/12)^360)/((1+C4/12)^360-1)*((1+C5/12)^360-1)/(C5/12*(1+C5/12)^360))))/4 -> 0.041543681
B7: Closing costs | C7: n/a | E7: Total Points | F7: =F5+F6 -> 0.011174724
B8: Points | C8: ='Input Data'!F9/100 -> 0.01125
B13: No need to calculate numbers in the gray area

Sheet Quicken - Conventional
B2: Input | E2: Intermediate Calculation | H2: Result
B4: Interest Rates | C4: ='Input Data'!E7/100 -> 0.0375 | E4: Points for APR | F4: =1-((C4/12*(1+C4/12)^360)/((1+C4/12)^360-1)*((1+C5/12)^360-1)/(C5/12*(1+C5/12)^360)) -> 0.030888787 | H4: 1-point rate | I4: =C4-(1%-F7)/4 -> 0.042722197
B5: APR | C5: ='Input Data'!G7/100 -> 0.04008 | E5: Discount Point | F5: =C8 -> 0.0225
B6: Loan Amount | C6: 200000 | E6: Origination Points | F6: =F4-C8 -> 0.0083887869 | H6: One formula for AA Software | I6: =C4-(0.01-(1-((C4/12*(1+C4/12)^360)/((1+C4/12)^360-1)*((1+C5/12)^360-1)/(C5/12*(1+C5/12)^360))))/4 -> 0.042722197
B7: Closing costs | C7: n/a | E7: Total Points | F7: =F5+F6 -> 0.030888787
B8: Points | C8: ='Input Data'!F7/100 -> 0.0225
B13: No need to calculate numbers in the gray area

Sheet Wells - Conventional
B2: Input | E2: Intermediate Calculation | H2: Result
B4: Interest Rates | C4: ='Input Data'!E3/100 -> 0.04125 | E4: Loan Amount for APR | F4: =((CIR/12*(1+CIR/12)^360)/((1+CIR/12)^360-1)*((1+CAPR/12)^360-1)/(CAPR/12*(1+CAPR/12)^360))*CP -> 199473.57 | H4: 1-point rate | I4: =CIR-(1%-F9)/4 -> 0.04161804
B5: APR | C5: ='Input Data'!G3/100 -> 0.04147 | E5: Points for APR | F5: =1-F4/CP -> 0.0026321592
B6: Loan Amount | C6: ='Input Data'!I3 -> 200000 | E6: Points for APR(as Discount Points) | F6: =1-((CIR/12*(1+CIR/12)^360)/((1+CIR/12)^360-1)*((1+CAPR/12)^360-1)/(CAPR/12*(1+CAPR/12)^360)) -> 0.0026321592 | H6: One formula for AA Software | I6: =CIR-(0.01-(1-((CIR/12*(1+CIR/12)^360)/((1+CIR/12)^360-1)*((1+CAPR/12)^360-1)/(CAPR/12*(1+CAPR/12)^360)) + C7/CP))/4 -> 0.04161804
B7: Closing costs | C7: ='Input Data'!H3 -> 1768
B8: Points | C8: n/a | E8: Origination Points | F8: =C7/CP -> 0.00884
E9: Total Points | F9: =F6+F8 -> 0.011472159
B13: No need to calculate numbers in the gray area

Sheet Wells - Jumbo conformin
B2: Input | E2: Intermediate Calculation | H2: Result
B4: Interest Rates | C4: ='Input Data'!E4/100 -> 0.04125 | E4: Points for APR | F4: =1-((C4/12*(1+C4/12)^360)/((1+C4/12)^360-1)*((1+C5/12)^360-1)/(C5/12*(1+C5/12)^360)) -> 0.0027515577 | H4: 1-point rate | I4: =C4-(1%-F7)/4 -> 0.041238889
B5: APR | C5: ='Input Data'!G4/100 -> 0.04148 | E5: Discount Point | F5: =F4 -> 0.0027515577
B6: Loan Amount | C6: ='Input Data'!I4 -> 500000 | E6: Origination Points | F6: =C7/C6 -> 0.007204 | H6: One formula for AA Software | I6: =C4-(0.01-(1-((C4/12*(1+C4/12)^360)/((1+C4/12)^360-1)*((1+C5/12)^360-1)/(C5/12*(1+C5/12)^360)) + C7/C6))/4 -> 0.041238889
B7: Closing costs | C7: ='Input Data'!H4 -> 3602 | E7: Total Points | F7: =F5+F6 -> 0.0099555577
B8: Points | C8: n/a
B13: No need to calculate numbers in the gray area

Sheet Wells - Jumbo Non-conforming
B2: Input | E2: Intermediate Calculation | H2: Result
B4: Interest Rates | C4: ='Input Data'!E5/100 -> 0.04125 | E4: Points for APR | F4: =1-((C4/12*(1+C4/12)^360)/((1+C4/12)^360-1)*((1+C5/12)^360-1)/(C5/12*(1+C5/12)^360)) -> 0 | H4: 1-point rate | I4: =C4-(1%-F7)/4 -> 0.039170667
B5: APR | C5: ='Input Data'!G5/100 -> 0.04125 | E5: Discount Point | F5: =F4 -> 0
B6: Loan Amount | C6: ='Input Data'!I5 -> 750000 | E6: Origination Points | F6: =C7/C6 -> 0.0016826667 | H6: One formula for AA Software | I6: =C4-(0.01-(1-((C4/12*(1+C4/12)^360)/((1+C4/12)^360-1)*((1+C5/12)^360-1)/(C5/12*(1+C5/12)^360)) + C7/C6))/4 -> 0.039170667
B7: Closing costs | C7: ='Input Data'!H5 -> 1262 | E7: Total Points | F7: =F5+F6 -> 0.0016826667
B8: Points | C8: n/a
B13: No need to calculate numbers in the gray area

Sheet Wells - FHA
B2: Input | E2: Intermediate Calculation | H2: Result
B4: Interest Rates | C4: ='Input Data'!E2/100 -> 0.03875 | E4: UFMIP | F4: =C5/C6 -> 0.0175 | H4: 1-point rate | I4: =C4-(1%-F7)/4 -> 0.04003625
B5: Upfront Mortgage Insurance Premium | C5: ='Input Data'!J2 -> 3500 | E5: Discount Point | F5: =C8 -> 0
B6: Loan Amount | C6: ='Input Data'!I2 -> 200000 | E6: Origination Points | F6: =C7/C6-F4 -> 0.015145
B7: Closing costs | C7: ='Input Data'!H2 -> 6529 | E7: Total Points | F7: =F5+F6 -> 0.015145
B8: Points | C8: 0
E9: Closing Costs | F9: =C7/C6 -> 0.032645
B13: No need to calculate numbers in the gray area

Sheet Input Data
B1: Date | C1: OriginatorNAme | D1: RateType | E1: Rate | F1: Points | G1: APR | H1: Closing Cost | I1: Loan Amount | J1: Upfront MIP
B2: 20150303 | C2: Wells Fargo | D2: 30YrConformingFHA | E2: 3.875 | F2: =1 -> 1 | G2: 4.905 | H2: 6529 | I2: 200000 | J2: 3500 | O2: FNMA 30-Year | P2: 2.8341999
B3: 20150303 | C3: Wells Fargo | D3: 30YrConformingConventional | E3: 4.125 | F3: =1 -> 1 | G3: 4.147 | H3: 1768 | I3: 200000 | O3: GNMA 30-Year | P3: 2.7074
B4: 20150303 | C4: Wells Fargo | D4: 30YrJumboConforming | E4: 4.125 | F4: =1 -> 1 | G4: 4.148 | H4: 3602 | I4: 500000
B5: 20150303 | C5: Wells Fargo | D5: 30YrJumboNonConforming | E5: 4.125 | F5: =1 -> 1 | G5: 4.125 | H5: 1262 | I5: 750000
B6: 20150303 | C6: Quicken | D6: 30YrConformingFHA | E6: 3.375 | F6: 2.25 | G6: 4.27
B7: 20150303 | C7: Quicken | D7: 30-year Conforming Conventional | E7: 3.75 | F7: 2.25 | G7: 4.008
B8: 20150303 | C8: Bank of America | D8: 30YrConformingConventional | E8: 4 | F8: 0.713 | G8: 4.17
B9: 20150303 | C9: Chase | D9: 30YrConformingConventional | E9: 4.125 | F9: 1.125 | G9: 4.219

Sheet Historic Result
C3: 1D | E3: 1W
B4: 30-year Conforming Conventional | C4: 1-Point Rate | D4: Servicing Spread | E4: 1-Point Rate | F4: Servicing Spread
B5: Bank of America | C5: 0.041695191 | D5: 0.014053251 | E5: 0.041695191 | F5: 0.014053251
B6: Chase | C6: 0.04186387 | D6: 0.01422193 | E6: 0.04186387 | F6: 0.01422193
B7: Quicken | C7: 0.042106935 | D7: 0.014464996 | E7: 0.042106935 | F7: 0.014464996
B8: Wells Fargo | C8: 0.04300192 | D8: 0.01535998 | E8: 0.04300192 | F8: 0.01535998
B9: Average | C9: 0.042166979 | D9: 0.014525039 | E9: 0.042166979 | F9: 0.014525039
B10: 30-year Jumbo Conforming | C10: 1-Point Rate | D10: Servicing Spread | E10: 1-Point Rate | F10: Servicing Spread
B11: Wells Fargo | C11: 0.040195372 | D11: 0.012553433 | E11: 0.040195372 | F11: 0.012553433
B12: 30-year Jumbo Non-Conforming | C12: 1-Point Rate | D12: Servicing Spread | E12: 1-Point Rate | F12: Servicing Spread
B13: Wells Fargo | C13: 0.039146476 | D13: 0.011504537 | E13: 0.039146476 | F13: 0.011504537
B14: 30-year FHA | C14: 1D Chg (bps) | D14: Servicing Spread | E14: 1D Chg (bps) | F14: Servicing Spread
B15: Wells Fargo | C15: 0.0397175 | D15: 0.012970924 | E15: 0.0397175 | F15: 0.012970924
