Workbook
Name temp: Input!$C$3:$E$1179
Name temp_1: Pivot!$C$3:$D$102
Name temp_6: Input!$N$3:$O$102
Name temp_7: Input!$J$3:$K$102
Name temp_8: Input!$R$3:$S$102

Sheet Result
D3: Total | E3: Top 10 | F3: Top 5 | G3: Top 1 | H3: N/A | I3: Remaining | L3: Top 10 | M3: Top 5 | N3: Top 1 | O3: N/A | P3: Remaining
C4: =Pivot!C4 -> 39083 | D4: =VLOOKUP(C4,Input!J$4:$K$102,2,0) -> 4.7181483e+10 | E4: =VLOOKUP(C4,Pivot!G22:H141,2,0) -> 3.0025184e+10 | F4: =VLOOKUP(C4,Pivot!K22:L141,2,0) -> 2.4746999e+10 | G4: =VLOOKUP(C4,Pivot!O22:P141,2,0) -> 9008075393 | H4: =VLOOKUP(C4,Input!$N$3:$O$102,2,0) -> 1.8054911e+09 | I4: =VLOOKUP(C4,Input!temp_8,2,0) -> 9.2902344e+08 | K4: =Pivot!C4 -> 39083 | L4: =E4/$D4 -> 0.63637644 | M4: =F4/$D4 -> 0.52450659 | N4: =G4/$D4 -> 0.19092396 | O4: =H4/$D4 -> 0.038266943 | P4: =I4/$D4 -> 0.019690425
C5: =Pivot!C5 -> 39114 | D5: =VLOOKUP(C5,Input!J$4:$K$102,2,0) -> 5.0773443e+10 | E5: =VLOOKUP(C5,Pivot!G23:H142,2,0) -> 3.0108179e+10 | F5: =VLOOKUP(C5,Pivot!K23:L142,2,0) -> 2.3003135e+10 | G5: =VLOOKUP(C5,Pivot!O23:P142,2,0) -> 8625817045 | H5: =VLOOKUP(C5,Input!$N$3:$O$102,2,0) -> 1.6799903e+09 | I5: =VLOOKUP(C5,Input!temp_8,2,0) -> 668892203 | K5: =Pivot!C5 -> 39114 | L5: =E5/$D5 -> 0.59299069 | M5: =F5/$D5 -> 0.45305446 | N5: =G5/$D5 -> 0.16988836 | O5: =H5/$D5 -> 0.033087973 | P5: =I5/$D5 -> 0.013174056
C6: =Pivot!C6 -> 39142 | D6: =VLOOKUP(C6,Input!J$4:$K$102,2,0) -> 4.6084431e+10 | E6: =VLOOKUP(C6,Pivot!G24:H143,2,0) -> 2.8183297e+10 | F6: =VLOOKUP(C6,Pivot!K24:L143,2,0) -> 2.1409134e+10 | G6: =VLOOKUP(C6,Pivot!O24:P143,2,0) -> 7241357422 | H6: =VLOOKUP(C6,Input!$N$3:$O$102,2,0) -> 1.6727128e+09 | I6: =VLOOKUP(C6,Input!temp_8,2,0) -> 7.5401117e+08 | K6: =Pivot!C6 -> 39142 | L6: =E6/$D6 -> 0.61155789 | M6: =F6/$D6 -> 0.46456327 | N6: =G6/$D6 -> 0.1571324 | O6: =H6/$D6 -> 0.036296701 | P6: =I6/$D6 -> 0.016361516
C7: =Pivot!C7 -> 39173 | D7: =VLOOKUP(C7,Input!J$4:$K$102,2,0) -> 5.0957712e+10 | E7: =VLOOKUP(C7,Pivot!G25:H144,2,0) -> 3.1533332e+10 | F7: =VLOOKUP(C7,Pivot!K25:L144,2,0) -> 2.533764e+10 | G7: =VLOOKUP(C7,Pivot!O25:P144,2,0) -> 8.4357953e+09 | H7: =VLOOKUP(C7,Input!$N$3:$O$102,2,0) -> 1.5829348e+09 | I7: =VLOOKUP(C7,Input!temp_8,2,0) -> 6.8427019e+08 | K7: =Pivot!C7 -> 39173 | L7: =E7/$D7 -> 0.61881373 | M7: =F7/$D7 -> 0.49722877 | N7: =G7/$D7 -> 0.16554502 | O7: =H7/$D7 -> 0.031063694 | P7: =I7/$D7 -> 0.013428197
C8: =Pivot!C8 -> 39203 | D8: =VLOOKUP(C8,Input!J$4:$K$102,2,0) -> 5.2257218e+10 | E8: =VLOOKUP(C8,Pivot!G26:H145,2,0) -> 3.6317977e+10 | F8: =VLOOKUP(C8,Pivot!K26:L145,2,0) -> 2.7080728e+10 | G8: =VLOOKUP(C8,Pivot!O26:P145,2,0) -> 8.7570316e+09 | H8: =VLOOKUP(C8,Input!$N$3:$O$102,2,0) -> 2.7729062e+09 | I8: =VLOOKUP(C8,Input!temp_8,2,0) -> 7.9461413e+08 | K8: =Pivot!C8 -> 39203 | L8: =E8/$D8 -> 0.69498489 | M8: =F8/$D8 -> 0.51821986 | N8: =G8/$D8 -> 0.16757554 | O8: =H8/$D8 -> 0.053062644 | P8: =I8/$D8 -> 0.015205825
C9: =Pivot!C9 -> 39234 | D9: =VLOOKUP(C9,Input!J$4:$K$102,2,0) -> 6.0994804e+10 | E9: =VLOOKUP(C9,Pivot!G27:H146,2,0) -> 2.0208581e+09 | F9: =VLOOKUP(C9,Pivot!K27:L146,2,0) -> 1640096016 | G9: =VLOOKUP(C9,Pivot!O27:P146,2,0) -> 529500000 | H9: =VLOOKUP(C9,Input!$N$3:$O$102,2,0) -> 2.7963526e+09 | I9: =VLOOKUP(C9,Input!temp_8,2,0) -> 7.1313849e+08 | K9: =Pivot!C9 -> 39234 | L9: =E9/$D9 -> 0.033131643 | M9: =F9/$D9 -> 0.02688911 | N9: =G9/$D9 -> 0.0086810673 | O9: =H9/$D9 -> 0.045845751 | P9: =I9/$D9 -> 0.011691791
C10: =Pivot!C10 -> 39264 | D10: =VLOOKUP(C10,Input!J$4:$K$102,2,0) -> 6.3564232e+10 | E10: =VLOOKUP(C10,Pivot!G28:H147,2,0) -> 1.9142144e+09 | F10: =VLOOKUP(C10,Pivot!K28:L147,2,0) -> 1.3451641e+09 | G10: =VLOOKUP(C10,Pivot!O28:P147,2,0) -> 5.874024e+08 | H10: =VLOOKUP(C10,Input!$N$3:$O$102,2,0) -> 2.979152e+09 | I10: =VLOOKUP(C10,Input!temp_8,2,0) -> 9.7079402e+08 | K10: =Pivot!C10 -> 39264 | L10: =E10/$D10 -> 0.030114647 | M10: =F10/$D10 -> 0.02116228 | N10: =G10/$D10 -> 0.009241084 | O10: =H10/$D10 -> 0.046868371 | P10: =I10/$D10 -> 0.015272646
C11: =Pivot!C11 -> 39295 | D11: =VLOOKUP(C11,Input!J$4:$K$102,2,0) -> 6.3574228e+10 | E11: =VLOOKUP(C11,Pivot!G29:H148,2,0) -> 3.6163125e+10 | F11: =VLOOKUP(C11,Pivot!K29:L148,2,0) -> 2.6896586e+10 | G11: =VLOOKUP(C11,Pivot!O29:P148,2,0) -> 7.9703835e+09 | H11: =VLOOKUP(C11,Input!$N$3:$O$102,2,0) -> 3.267541e+09 | I11: =VLOOKUP(C11,Input!temp_8,2,0) -> 7.1026208e+08 | K11: =Pivot!C11 -> 39295 | L11: =E11/$D11 -> 0.56883309 | M11: =F11/$D11 -> 0.42307373 | N11: =G11/$D11 -> 0.1253713 | O11: =H11/$D11 -> 0.051397258 | P11: =I11/$D11 -> 0.01117217
C12: =Pivot!C12 -> 39326 | D12: =VLOOKUP(C12,Input!J$4:$K$102,2,0) -> 5.6268903e+10 | E12: =VLOOKUP(C12,Pivot!G30:H149,2,0) -> 3.9727851e+10 | F12: =VLOOKUP(C12,Pivot!K30:L149,2,0) -> 3.1387724e+10 | G12: =VLOOKUP(C12,Pivot!O30:P149,2,0) -> 1.1906421e+10 | H12: =VLOOKUP(C12,Input!$N$3:$O$102,2,0) -> 2.5758234e+09 | I12: =VLOOKUP(C12,Input!temp_8,2,0) -> 7.790342e+08 | K12: =Pivot!C12 -> 39326 | L12: =E12/$D12 -> 0.70603564 | M12: =F12/$D12 -> 0.55781652 | N12: =G12/$D12 -> 0.2115986 | O12: =H12/$D12 -> 0.045777032 | P12: =I12/$D12 -> 0.013844844
C13: =Pivot!C13 -> 39356 | D13: =VLOOKUP(C13,Input!J$4:$K$102,2,0) -> 5.9150818e+10 | E13: =VLOOKUP(C13,Pivot!G31:H150,2,0) -> 3.4611208e+10 | F13: =VLOOKUP(C13,Pivot!K31:L150,2,0) -> 2.5266525e+10 | G13: =VLOOKUP(C13,Pivot!O31:P150,2,0) -> 7.6112336e+09 | H13: =VLOOKUP(C13,Input!$N$3:$O$102,2,0) -> 2.5699712e+09 | I13: =VLOOKUP(C13,Input!temp_8,2,0) -> 7.0701634e+08 | K13: =Pivot!C13 -> 39356 | L13: =E13/$D13 -> 0.5851349 | M13: =F13/$D13 -> 0.42715428 | N13: =G13/$D13 -> 0.12867504 | O13: =H13/$D13 -> 0.043447771 | P13: =I13/$D13 -> 0.011952774
C14: =Pivot!C14 -> 39387 | D14: =VLOOKUP(C14,Input!J$4:$K$102,2,0) -> 5.4956654e+10 | E14: =VLOOKUP(C14,Pivot!G32:H151,2,0) -> 3.8426582e+10 | F14: =VLOOKUP(C14,Pivot!K32:L151,2,0) -> 2.7917519e+10 | G14: =VLOOKUP(C14,Pivot!O32:P151,2,0) -> 9251362639 | H14: =VLOOKUP(C14,Input!$N$3:$O$102,2,0) -> 2.0604413e+09 | I14: =VLOOKUP(C14,Input!temp_8,2,0) -> 7.1463558e+08 | K14: =Pivot!C14 -> 39387 | L14: =E14/$D14 -> 0.69921618 | M14: =F14/$D14 -> 0.50799161 | N14: =G14/$D14 -> 0.16833926 | O14: =H14/$D14 -> 0.037492118 | P14: =I14/$D14 -> 0.013003622
C15: =Pivot!C15 -> 39417 | D15: =VLOOKUP(C15,Input!J$4:$K$102,2,0) -> 5.4697321e+10 | E15: =VLOOKUP(C15,Pivot!G33:H152,2,0) -> 4.5838565e+10 | F15: =VLOOKUP(C15,Pivot!K33:L152,2,0) -> 3.534814e+10 | G15: =VLOOKUP(C15,Pivot!O33:P152,2,0) -> 1.2421827e+10 | H15: =VLOOKUP(C15,Input!$N$3:$O$102,2,0) -> 2.6422772e+09 | I15: =VLOOKUP(C15,Input!temp_8,2,0) -> 6.3213746e+08 | K15: =Pivot!C15 -> 39417 | L15: =E15/$D15 -> 0.8380404 | M15: =F15/$D15 -> 0.64624993 | N15: =G15/$D15 -> 0.2271012 | O15: =H15/$D15 -> 0.04830725 | P15: =I15/$D15 -> 0.011557009
... C32: =Pivot!C32 -> 39934 | D32: =VLOOKUP(C32,Input!J$4:$K$102,2,0) -> 4.1425622e+10 | E32: =VLOOKUP(C32,Pivot!G50:H169,2,0) -> 5.9246266e+10 | F32: =VLOOKUP(C32,Pivot!K50:L169,2,0) -> 4.861435e+10 | G32: =VLOOKUP(C32,Pivot!O50:P169,2,0) -> 1.6377154e+10 | H32: =VLOOKUP(C32,Input!$N$3:$O$102,2,0) -> 1.4916254e+10 | I32: =VLOOKUP(C32,Input!temp_8,2,0) -> 5.1348512e+08 | K32: =Pivot!C32 -> 39934 | L32: =E32/$D32 -> 1.4301841 | M32: =F32/$D32 -> 1.1735334 | N32: =G32/$D32 -> 0.39533875 | O32: =H32/$D32 -> 0.36007314 | P32: =I32/$D32 -> 0.012395351
B33: =D33+H33 -> 1.2605633e+11 | C33: =Pivot!C33 -> 39965 | D33: =VLOOKUP(C33,Input!J$4:$K$102,2,0) -> 5.4510214e+10 | E33: =VLOOKUP(C33,Pivot!G51:H170,2,0) -> 6.254832e+10 | F33: =VLOOKUP(C33,Pivot!K51:L170,2,0) -> 5.0633929e+10 | G33: =VLOOKUP(C33,Pivot!O51:P170,2,0) -> 1.8556307e+10 | H33: =VLOOKUP(C33,Input!$N$3:$O$102,2,0) -> 7.1546121e+10 | I33: =VLOOKUP(C33,Input!temp_8,2,0) -> 7.5091474e+08 | K33: =Pivot!C33 -> 39965 | L33: =E33/$D33 -> 1.1474606 | M33: =F33/$D33 -> 0.92888883 | N33: =G33/$D33 -> 0.3404189 | O33: =H33/$D33 -> 1.3125269 | P33: =I33/$D33 -> 0.01377567
C34: =Pivot!C34 -> 39995 | D34: =VLOOKUP(C34,Input!J$4:$K$102,2,0) -> 7.933665e+10 | E34: =VLOOKUP(C34,Pivot!G52:H171,2,0) -> 4.7492473e+10 | F34: =VLOOKUP(C34,Pivot!K52:L171,2,0) -> 4.0903264e+10 | G34: =VLOOKUP(C34,Pivot!O52:P171,2,0) -> 1.778028e+10 | H34: =VLOOKUP(C34,Input!$N$3:$O$102,2,0) -> 4.8580167e+10 | I34: =VLOOKUP(C34,Input!temp_8,2,0) -> 1.1450267e+09 | K34: =Pivot!C34 -> 39995 | L34: =E34/$D34 -> 0.5986196 | M34: =F34/$D34 -> 0.51556581 | N34: =G34/$D34 -> 0.22411181 | O34: =H34/$D34 -> 0.61232945 | P34: =I34/$D34 -> 0.014432507
C35: =Pivot!C35 -> 40026 | D35: =VLOOKUP(C35,Input!J$4:$K$102,2,0) -> 6.1794829e+10 | E35: =VLOOKUP(C35,Pivot!G53:H172,2,0) -> 3.5622456e+10 | F35: =VLOOKUP(C35,Pivot!K53:L172,2,0) -> 3.0196349e+10 | G35: =VLOOKUP(C35,Pivot!O53:P172,2,0) -> 1.3559469e+10 | H35: =VLOOKUP(C35,Input!$N$3:$O$102,2,0) -> 1.6641693e+10 | I35: =VLOOKUP(C35,Input!temp_8,2,0) -> 1.0225149e+09 | K35: =Pivot!C35 -> 40026 | L35: =E35/$D35 -> 0.57646338 | M35: =F35/$D35 -> 0.48865496 | N35: =G35/$D35 -> 0.21942725 | O35: =H35/$D35 -> 0.2693056 | P35: =I35/$D35 -> 0.016546933
C36: =Pivot!C36 -> 40057 | D36: =VLOOKUP(C36,Input!J$4:$K$102,2,0) -> 4.5832557e+10 | E36: =VLOOKUP(C36,Pivot!G54:H173,2,0) -> 2.9845785e+10 | F36: =VLOOKUP(C36,Pivot!K54:L173,2,0) -> 2.5413967e+10 | G36: =VLOOKUP(C36,Pivot!O54:P173,2,0) -> 9.7112614e+09 | H36: =VLOOKUP(C36,Input!$N$3:$O$102,2,0) -> 1.3851899e+10 | I36: =VLOOKUP(C36,Input!temp_8,2,0) -> 1.0994973e+09 | K36: =Pivot!C36 -> 40057 | L36: =E36/$D36 -> 0.65119179 | M36: =F36/$D36 -> 0.55449594 | N36: =G36/$D36 -> 0.21188566 | O36: =H36/$D36 -> 0.30222837 | P36: =I36/$D36 -> 0.023989439
C37: =Pivot!C37 -> 40087 | D37: =VLOOKUP(C37,Input!J$4:$K$102,2,0) -> 4.3788862e+10 | E37: =VLOOKUP(C37,Pivot!G55:H174,2,0) -> 1.8050213e+10 | F37: =VLOOKUP(C37,Pivot!K55:L174,2,0) -> 1.5113924e+10 | G37: =VLOOKUP(C37,Pivot!O55:P174,2,0) -> 7.2112824e+09 | H37: =VLOOKUP(C37,Input!$N$3:$O$102,2,0) -> 1.2597169e+10 | I37: =VLOOKUP(C37,Input!temp_8,2,0) -> 7.1926646e+08 | K37: =Pivot!C37 -> 40087 | L37: =E37/$D37 -> 0.41221013 | M37: =F37/$D37 -> 0.34515453 | N37: =G37/$D37 -> 0.16468303 | O37: =H37/$D37 -> 0.28767975 | P37: =I37/$D37 -> 0.016425786
C38: =Pivot!C38 -> 40118 | D38: =VLOOKUP(C38,Input!J$4:$K$102,2,0) -> 3.0442712e+10 | E38: =VLOOKUP(C38,Pivot!G56:H175,2,0) -> 2.1036922e+10 | F38: =VLOOKUP(C38,Pivot!K56:L175,2,0) -> 1.7714705e+10 | G38: =VLOOKUP(C38,Pivot!O56:P175,2,0) -> 7.75127e+09 | H38: =VLOOKUP(C38,Input!$N$3:$O$102,2,0) -> 7.0659361e+09 | I38: =VLOOKUP(C38,Input!temp_8,2,0) -> 7.5240953e+08 | K38: =Pivot!C38 -> 40118 | L38: =E38/$D38 -> 0.6910331 | M38: =F38/$D38 -> 0.58190299 | N38: =G38/$D38 -> 0.25461825 | O38: =H38/$D38 -> 0.232106 | P38: =I38/$D38 -> 0.024715588
C39: =Pivot!C39 -> 40148 | D39: =VLOOKUP(C39,Input!J$4:$K$102,2,0) -> 3.0141102e+10 | E39: =VLOOKUP(C39,Pivot!G57:H176,2,0) -> 2.7010035e+10 | F39: =VLOOKUP(C39,Pivot!K57:L176,2,0) -> 2.2935301e+10 | G39: =VLOOKUP(C39,Pivot!O57:P176,2,0) -> 1.1583901e+10 | H39: =VLOOKUP(C39,Input!$N$3:$O$102,2,0) -> 6.3677379e+09 | I39: =VLOOKUP(C39,Input!temp_8,2,0) -> 5.9108656e+08 | K39: =Pivot!C39 -> 40148 | L39: =E39/$D39 -> 0.89611967 | M39: =F39/$D39 -> 0.76093106 | N39: =G39/$D39 -> 0.38432241 | O39: =H39/$D39 -> 0.21126427 | P39: =I39/$D39 -> 0.019610649
C40: =Pivot!C40 -> 40179 | D40: =VLOOKUP(C40,Input!J$4:$K$102,2,0) -> 3.9433551e+10 | E40: =VLOOKUP(C40,Pivot!G58:H177,2,0) -> 2.3918184e+10 | F40: =VLOOKUP(C40,Pivot!K58:L177,2,0) -> 2.085892e+10 | G40: =VLOOKUP(C40,Pivot!O58:P177,2,0) -> 9.9788493e+09 | H40: =VLOOKUP(C40,Input!$N$3:$O$102,2,0) -> 7.787527e+09 | I40: =VLOOKUP(C40,Input!temp_8,2,0) -> 7.2213822e+08 | K40: =Pivot!C40 -> 40179 | L40: =E40/$D40 -> 0.606544 | M40: =F40/$D40 -> 0.52896376 | N40: =G40/$D40 -> 0.2530548 | O40: =H40/$D40 -> 0.1974848 | P40: =I40/$D40 -> 0.018312787
C41: =Pivot!C41 -> 40210 | D41: =VLOOKUP(C41,Input!J$4:$K$102,2,0) -> 3.1932663e+10 | E41: =VLOOKUP(C41,Pivot!G59:H178,2,0) -> 2.521946e+10 | F41: =VLOOKUP(C41,Pivot!K59:L178,2,0) -> 2.27325e+10 | G41: =VLOOKUP(C41,Pivot!O59:P178,2,0) -> 9.807431e+09 | H41: =VLOOKUP(C41,Input!$N$3:$O$102,2,0) -> 7.3132766e+09 | I41: =VLOOKUP(C41,Input!temp_8,2,0) -> 7.3011418e+08 | K41: =Pivot!C41 -> 40210 | L41: =E41/$D41 -> 0.78977002 | M41: =F41/$D41 -> 0.71188864 | N41: =G41/$D41 -> 0.3071285 | O41: =H41/$D41 -> 0.22902182 | P41: =I41/$D41 -> 0.022864181
C42: =Pivot!C42 -> 40238 | D42: =VLOOKUP(C42,Input!J$4:$K$102,2,0) -> 3.5237291e+10 | E42: =VLOOKUP(C42,Pivot!G60:H179,2,0) -> 1.8730251e+10 | F42: =VLOOKUP(C42,Pivot!K60:L179,2,0) -> 1.6626538e+10 | G42: =VLOOKUP(C42,Pivot!O60:P179,2,0) -> 7.7521484e+09 | H42: =VLOOKUP(C42,Input!$N$3:$O$102,2,0) -> 5.5133079e+09 | I42: =VLOOKUP(C42,Input!temp_8,2,0) -> 8.2270018e+08 | K42: =Pivot!C42 -> 40238 | L42: =E42/$D42 -> 0.53154628 | M42: =F42/$D42 -> 0.47184497 | N42: =G42/$D42 -> 0.21999842 | O42: =H42/$D42 -> 0.15646231 | P42: =I42/$D42 -> 0.02334743
C43: =Pivot!C43 -> 40269 | D43: =VLOOKUP(C43,Input!J$4:$K$102,2,0) -> 3.0111044e+10 | E43: =VLOOKUP(C43,Pivot!G61:H180,2,0) -> 2.1401297e+10 | F43: =VLOOKUP(C43,Pivot!K61:L180,2,0) -> 1.8926472e+10 | G43: =VLOOKUP(C43,Pivot!O61:P180,2,0) -> 8.7598562e+09 | H43: =VLOOKUP(C43,Input!$N$3:$O$102,2,0) -> 4.3841867e+09 | I43: =VLOOKUP(C43,Input!temp_8,2,0) -> 6.3190681e+08 | K43: =Pivot!C43 -> 40269 | L43: =E43/$D43 -> 0.71074577 | M43: =F43/$D43 -> 0.62855583 | N43: =G43/$D43 -> 0.29091838 | O43: =H43/$D43 -> 0.14560062 | P43: =I43/$D43 -> 0.020985882
C44: =Pivot!C44 -> 40299 | D44: =VLOOKUP(C44,Input!J$4:$K$102,2,0) -> 2.9683096e+10 | E44: =VLOOKUP(C44,Pivot!G62:H181,2,0) -> 2.2794601e+10 | F44: =VLOOKUP(C44,Pivot!K62:L181,2,0) -> 1.9737345e+10 | G44: =VLOOKUP(C44,Pivot!O62:P181,2,0) -> 7.9831172e+09 | H44: =VLOOKUP(C44,Input!$N$3:$O$102,2,0) -> 4.8786661e+09 | I44: =VLOOKUP(C44,Input!temp_8,2,0) -> 5.6034352e+08 | K44: =Pivot!C44 -> 40299 | L44: =E44/$D44 -> 0.76793206 | M44: =F44/$D44 -> 0.66493553 | N44: =G44/$D44 -> 0.2689449 | O44: =H44/$D44 -> 0.1643584 | P44: =I44/$D44 -> 0.01887753
C45: =Pivot!C45 -> 40330 | D45: =VLOOKUP(C45,Input!J$4:$K$102,2,0) -> 2.9388182e+10 | E45: =VLOOKUP(C45,Pivot!G63:H182,2,0) -> 2.6357644e+10 | F45: =VLOOKUP(C45,Pivot!K63:L182,2,0) -> 2.3095751e+10 | G45: =VLOOKUP(C45,Pivot!O63:P182,2,0) -> 8.1596999e+09 | H45: =VLOOKUP(C45,Input!$N$3:$O$102,2,0) -> 4.255467e+09 | I45: =VLOOKUP(C45,Input!temp_8,2,0) -> 7.0140741e+08 | K45: =Pivot!C45 -> 40330 | L45: =E45/$D45 -> 0.896879 | M45: =F45/$D45 -> 0.78588565 | N45: =G45/$D45 -> 0.27765242 | O45: =H45/$D45 -> 0.14480198 | P45: =I45/$D45 -> 0.023866989
... C102: =Pivot!C102 -> 42064 | D102: =VLOOKUP(C102,Input!J$4:$K$102,2,0) -> 2.1020607e+10 | E102: =VLOOKUP(C102,Pivot!G120:H239,2,0) -> 1.1103072e+10 | F102: =VLOOKUP(C102,Pivot!K120:L239,2,0) -> 8.8444623e+09 | G102: =VLOOKUP(C102,Pivot!O120:P239,2,0) -> 4009024386 | H102: =VLOOKUP(C102,Input!$N$3:$O$102,2,0) -> 1.471834e+10 | I102: =VLOOKUP(C102,Input!temp_8,2,0) -> 9.8696934e+08 | K102: =Pivot!C102 -> 42064 | L102: =E102/$D102 -> 0.52819937 | M102: =F102/$D102 -> 0.42075199 | N102: =G102/$D102 -> 0.19071877 | O102: =H102/$D102 -> 0.70018622 | P102: =I102/$D102 -> 0.046952465

Sheet Pivot
K1: Rank | L1: (Multiple Items) | O1: Rank | P1: 1
C2: Total | G2: Top Ten | K2: Top Five | O2: Top One
C3: asOf | D3: TotalBalance | G3: Row Labels | H3: Sum of TotalBalance | K3: Row Labels | L3: Sum of TotalBalance | O3: Row Labels | P3: Sum of TotalBalance
C4: 39083 | D4: 3.5508272e+10 | G4: 38504 | H4: 19413121 | K4: 38504 | L4: 17670874 | O4: 38504 | P4: 9487254
C5: 39114 | D5: 3.5209528e+10 | G5: 38534 | H5: 10883226 | K5: 38534 | L5: 8575678 | O5: 38534 | P5: 4500722
C6: 39142 | D6: 3.2600805e+10 | G6: 38565 | H6: 1.6235539e+08 | K6: 38565 | L6: 1.5625708e+08 | O6: 38565 | P6: 79158664
C7: 39173 | D7: 3.8660093e+10 | G7: 38596 | H7: 116005289 | K7: 38596 | L7: 106953756 | O7: 38596 | P7: 56552979
C8: 39203 | D8: 4.3308374e+10 | G8: 38626 | H8: 1.7701127e+08 | K8: 38626 | L8: 1.7396893e+08 | O8: 38626 | P8: 89226904
C9: 39234 | D9: 2.1709736e+09 | G9: 38657 | H9: 45939105 | K9: 38657 | L9: 40249664 | O9: 38657 | P9: 19726775
C10: 39264 | D10: 2.6570081e+09 | G10: 38687 | H10: 167073886 | K10: 38687 | L10: 161351206 | O10: 38687 | P10: 123617884
C11: 39295 | D11: 4.3995399e+10 | G11: 38718 | H11: 409581706 | K11: 38718 | L11: 409234045 | O11: 38718 | P11: 405272994
C12: 39326 | D12: 4.9111821e+10 | G12: 38749 | H12: 47420821 | K12: 38749 | L12: 43567861 | O12: 38749 | P12: 18989706
C13: 39356 | D13: 4.1062455e+10 | G13: 38777 | H13: 57815428 | K13: 38777 | L13: 44990671 | O13: 38777 | P13: 16635495
C14: 39387 | D14: 4.4732737e+10 | G14: 38808 | H14: 1.4320683e+08 | K14: 38808 | L14: 1.0562871e+08 | O14: 38808 | P14: 41797459
C15: 39417 | D15: 5.1707189e+10 | G15: 38838 | H15: 168814422 | K15: 38838 | L15: 117134068 | O15: 38838 | P15: 30826920
... C102: 42064 | D102: 1.7165686e+10 | G102: 41487 | H102: 3.5770897e+10 | K102: 41487 | L102: 2.7875192e+10 | O102: 41487 | P102: 1.6043755e+10
G103: 41518 | H103: 2.8474516e+10 | K103: 41518 | L103: 2.3217758e+10 | O103: 41518 | P103: 1.2954392e+10
G104: 41548 | H104: 2.1846439e+10 | K104: 41548 | L104: 1.662235e+10 | O104: 41548 | P104: 9.1489415e+09
G105: 41579 | H105: 1.9735518e+10 | K105: 41579 | L105: 1.5129674e+10 | O105: 41579 | P105: 7.2779801e+09
G106: 41609 | H106: 1.7148937e+10 | K106: 41609 | L106: 1.2929027e+10 | O106: 41609 | P106: 6.588451e+09
G107: 41640 | H107: 1.1561109e+10 | K107: 41640 | L107: 8.9674971e+09 | O107: 41640 | P107: 3.1057026e+09
G108: 41671 | H108: 1.3447219e+10 | K108: 41671 | L108: 1.0862979e+10 | O108: 41671 | P108: 4.2289775e+09
G109: 41699 | H109: 9.8601102e+09 | K109: 41699 | L109: 7.6019885e+09 | O109: 41699 | P109: 2.7717457e+09
G110: 41730 | H110: 1.2276304e+10 | K110: 41730 | L110: 9.0175735e+09 | O110: 41730 | P110: 3.2819376e+09
G111: 41760 | H111: 1.0540782e+10 | K111: 41760 | L111: 7.5119552e+09 | O111: 41760 | P111: 3.7013763e+09
G112: 41791 | H112: 1.3048715e+10 | K112: 41791 | L112: 9.6984172e+09 | O112: 41791 | P112: 4.1196641e+09
G113: 41821 | H113: 1.4180444e+10 | K113: 41821 | L113: 1.0365357e+10 | O113: 41821 | P113: 4.4048467e+09
G114: 41852 | H114: 1.3791298e+10 | K114: 41852 | L114: 1.0185764e+10 | O114: 41852 | P114: 4.3510128e+09
... G121: 42064 | H121: 1.1103072e+10 | K121: 42064 | L121: 8.8444623e+09 | O121: 42064 | P121: 4009024386
G122: Grand Total | H122: 3.055236e+12 | K122: Grand Total | L122: 2.4817667e+12 | O122: Grand Total | P122: 1.0076484e+12

Sheet Input
J2: Total | N2: N/A | R2: Remaining
B3: asOf | C3: servicerName | D3: TotalBalance | E3: Rank | J3: asOf | K3: TotalBalance | N3: asOf | O3: TotalBalance | R3: asOf | S3: TotalBalance
B4: 38504 | C4: CITI | D4: 9487254 | E4: 1 | J4: 39083 | K4: 4.7181483e+10 | N4: 39083 | O4: 1.8054911e+09 | R4: 39083 | S4: 9.2902344e+08
B5: 38504 | C5: PHH | D5: 2584090 | E5: 2 | J5: 39114 | K5: 5.0773443e+10 | N5: 39114 | O5: 1.6799903e+09 | R5: 39114 | S5: 668892203
B6: 38504 | C6: BANK OF AMERICA | D6: 2473153 | E6: 3 | J6: 39142 | K6: 4.6084431e+10 | N6: 39142 | O6: 1.6727128e+09 | R6: 39142 | S6: 7.5401117e+08
B7: 38504 | C7: CWB | D7: 2473153 | E7: 3 | J7: 39173 | K7: 5.0957712e+10 | N7: 39173 | O7: 1.5829348e+09 | R7: 39173 | S7: 6.8427019e+08
B8: 38504 | C8: US BANK | D8: 653224 | E8: 5 | J8: 39203 | K8: 5.2257218e+10 | N8: 39203 | O8: 2.7729062e+09 | R8: 39203 | S8: 7.9461413e+08
B9: 38504 | C9: OHIO SAVINGS BANK | D9: 527391.33 | E9: 6 | J9: 39234 | K9: 6.0994804e+10 | N9: 39234 | O9: 2.7963526e+09 | R9: 39234 | S9: 7.1313849e+08
B10: 38504 | C10: CENTRAL MORTGAGE | D10: 344406.07 | E10: 7 | J10: 39264 | K10: 6.3564232e+10 | N10: 39264 | O10: 2.979152e+09 | R10: 39264 | S10: 9.7079402e+08
B11: 38504 | C11: OPTEUM GROUP | D11: 329248.45 | E11: 8 | J11: 39295 | K11: 6.3574228e+10 | N11: 39295 | O11: 3.267541e+09 | R11: 39295 | S11: 7.1026208e+08
B12: 38504 | C12: FLAGSTAR | D12: 315400 | E12: 9 | J12: 39326 | K12: 5.6268903e+10 | N12: 39326 | O12: 2.5758234e+09 | R12: 39326 | S12: 7.790342e+08
B13: 38504 | C13: WELLS FARGO | D13: 225801.62 | E13: 10 | J13: 39356 | K13: 5.9150818e+10 | N13: 39356 | O13: 2.5699712e+09 | R13: 39356 | S13: 7.0701634e+08
B14: 38534 | C14: BANK OF AMERICA | D14: 2250361 | E14: 1 | J14: 39387 | K14: 5.4956654e+10 | N14: 39387 | O14: 2.0604413e+09 | R14: 39387 | S14: 7.1463558e+08
B15: 38534 | C15: CWB | D15: 2250361 | E15: 1 | J15: 39417 | K15: 5.4697321e+10 | N15: 39417 | O15: 2.6422772e+09 | R15: 39417 | S15: 6.3213746e+08
... B102: 38808 | C102: WELLS FARGO | D102: 13371004 | E102: 3 | J102: 42064 | K102: 2.1020607e+10 | N102: 42064 | O102: 1.471834e+10 | R102: 42064 | S102: 9.8696934e+08
B103: 38808 | C103: RED MORTGAGE CAPITAL, INC. | D103: 13000000 | E103: 4
B104: 38808 | C104: WACHOVIA | D104: 12884249 | E104: 5
B105: 38808 | C105: AMERICAN PROPERTY FINANCING INC. | D105: 10000000 | E105: 6
B106: 38808 | C106: ARBOR | D106: 8533433 | E106: 7
B107: 38808 | C107: DB MORTGAGE SERVICES, LLC | D107: 8371000 | E107: 8
B108: 38808 | C108: PRUDENTIAL MULTIFAMILY MORTGAGE INC. | D108: 5809000 | E108: 9
B109: 38808 | C109: PHH | D109: 4864686 | E109: 10
B110: 38838 | C110: PRUDENTIAL MULTIFAMILY MORTGAGE INC. | D110: 30826920 | E110: 1
B111: 38838 | C111: CHASE | D111: 23268574 | E111: 2
B112: 38838 | C112: WAMU | D112: 23268574 | E112: 2
B113: 38838 | C113: COLUMN GUARANTEED LLC | D113: 20500000 | E113: 4
B114: 38838 | C114: DB MORTGAGE SERVICES, LLC | D114: 19270000 | E114: 5
... B1179: 42064 | C1179: FRANKLIN AMERICAN MORTGAGE COMPANY | D1179: 395566598 | E1179: 10
