Workbook

Sheet Sheet1
A1: LoanId | B1: asOf | C1: servicer | D1: Current Coupon | E1: current RPB | F1: loan Age | G1: rem Term | H1: adj Rem Term | I1: mat Dt | J1: delinqStatus | K1: loan Mod Flag | L1: zeroBalanceCode | M1: asOfZeroBalance | N1: Last Paid Installment Date | O1: Foreclosure Date | P1: Disposition Date | Q1: Foreclosure Costs | R1: Property Preserve And Repair Cost | S1: Asset Recovery Cost | T1: Misc Holding Expense And Credits | U1: Associated Tax for Holding Property | V1: NetSaleProceeds | W1: CreditEnhancementProceeds | X1: RepurchaseMakeWholeProceeds | Y1: OtherForecloseProceeds
A2: 109313766616 | B2: 37803 | D2: 8.625 | E2: 69818.57 | F2: 40 | G2: 321 | I2: 47574 | J2: 0 | K2: Y
A3: 109313766616 | B3: 37834 | D3: 8.625 | E3: 69818.57 | F3: 41 | G3: 320 | I3: 47574 | J3: 1 | K3: Y
A4: 109313766616 | B4: 37865 | D4: 8.625 | E4: 69818.57 | F4: 42 | G4: 319 | I4: 47574 | J4: 2 | K4: Y
A5: 109313766616 | B5: 37895 | D5: 8.625 | E5: 69818.57 | F5: 43 | G5: 318 | I5: 47574 | J5: 3 | K5: Y
A6: 109313766616 | B6: 37926 | D6: 8.625 | E6: 69818.57 | F6: 44 | G6: 317 | I6: 47574 | J6: 4 | K6: Y
A7: 109313766616 | B7: 37956 | D7: 8.625 | E7: 69818.57 | F7: 45 | G7: 316 | I7: 47574 | J7: 5 | K7: Y
A8: 109313766616 | B8: 37987 | D8: 8.625 | E8: 69818.57 | F8: 46 | G8: 315 | H8: 0 | I8: 47574 | J8: X | K8: Y | L8: 9 | M8: 37987 | N8: 37803 | O8: 37987 | P8: 38292 | Q8: 1798 | R8: 2366 | S8: -129 | T8: 1316 | U8: 29948 | V8: 51672
Q9: Expenses | R9: Expenses | S9: Expenses | T9: NonMI Recoveries | U9: Expense | V9: NetSaleProceeds | W9: MI Recoveries
A20: LoanId | B20: asOf | C20: servicer | D20: CurrentCoupon | E20: currentRPB | F20: loanAge | G20: remTerm | H20: adjRemTerm | I20: matDt | J20: msa | K20: delinqStatus | L20: loanModFlag | M20: zeroBalanceCode | N20: asOfZeroBalance | O20: LastPaidInstallmentDate | P20: ForeclosureDate | Q20: DispositionDate | R20: ForeclosureCosts | S20: PropertyPreserveAndRepairCost | T20: AssetRecoveryCost | U20: MiscHoldingExpenseAndCredits | V20: AssociatedTaxforHoldingProperty | W20: NetSaleProceeds | X20: CreditEnhancementProceeds | Y20: RepurchaseMakeWholeProceeds | Z20: OtherForecloseProceeds
A21: 109313766616 | B21: 37987 | D21: 8.625 | E21: 69818.57 | F21: 46 | G21: 315 | H21: 0 | I21: 47574 | J21: 0 | K21: X | L21: Y | M21: 9 | N21: 37987 | O21: 37803 | P21: 37987 | Q21: 38292 | R21: 1798 | S21: 2366 | T21: -129 | U21: 1316 | V21: 29948 | W21: 51672
A26: LoanId | B26: asOf | C26: servicer | D26: CurrentCoupon | E26: currentRPB | F26: loanAge | G26: remTerm | H26: adjRemTerm | I26: matDt | J26: msa | K26: delinqStatus | L26: loanModFlag | M26: zeroBalanceCode | N26: asOfZeroBalance | O26: LastPaidInstallmentDate | P26: ForeclosureDate | Q26: DispositionDate | R26: ForeclosureCosts | S26: PropertyPreserveAndRepairCost | T26: AssetRecoveryCost | U26: MiscHoldingExpenseAndCredits | V26: AssociatedTaxforHoldingProperty | W26: NetSaleProceeds | X26: CreditEnhancementProceeds | Y26: RepurchaseMakeWholeProceeds | Z26: OtherForecloseProceeds | AA26: Proceeds
A27: 109313766616 | B27: 37987 | D27: 8.625 | E27: 69818.57 | F27: 46 | G27: 315 | H27: 0 | I27: 47574 | J27: 0 | K27: X | L27: Y | M27: 9 | N27: 37987 | O27: 37803 | P27: 37987 | Q27: 38292 | R27: 1798 | S27: 2366 | T27: -129 | U27: 1316 | V27: 29948 | W27: 51672

Sheet Statistical
A2: Year | B2: 2000 | C2: 2001 | D2: 2002 | E2: 2003 | F2: 2004 | G2: 2005 | H2: 2006 | I2: 2007 | J2: 2008 | K2: 2009 | L2: 2010 | M2: 2011 | N2: 2012 | O2: 2013 | P2: 2014 | U2: Loan Count
A3: EXPENSES | V3: FHL | W3: FNM
A4: Delinquent Interest | B4: 0.045644944 | C4: 0.077126885 | D4: 0.086539642 | E4: 0.088162106 | F4: 0.08879892 | G4: 0.092340888 | H4: 0.096726046 | I4: 0.089745739 | J4: 0.081043535 | K4: 0.075122103 | L4: 0.082118553 | M4: 0.093235643 | N4: 0.097621192 | O4: 0.12027512 | P4: 0.15259221 | Q4: 0.1 | U4: Performance | V4: 17432 | W4: 21945 | X4: =V4+W4 -> 39377
A5: Total Liquidition Expenses | B5: 0.031864091 | C5: 0.05533699 | D5: 0.062819814 | E5: 0.066668059 | F5: 0.068511218 | G5: 0.085485507 | H5: 0.09797658 | I5: 0.091319163 | J5: 0.071926825 | K5: 0.055779328 | L5: 0.060133363 | M5: 0.070368792 | N5: 0.082928928 | O5: 0.1076057 | P5: 0.14100999 | Q5: 0.08 | U5: FC | V5: 153 | W5: 120 | X5: =V5+W5 -> 273
A6: Foreclosure | B6: 0.012203585 | C6: 0.023258731 | D6: 0.029110359 | E6: 0.031405709 | F6: 0.030785428 | G6: 0.036736405 | H6: 0.041229213 | I6: 0.038797789 | J6: 0.029626221 | K6: 0.021622909 | L6: 0.023602931 | M6: 0.024930145 | N6: 0.027622286 | O6: 0.034410589 | P6: 0.044163473 | Q6: 0.03 | U6: REO | V6: 286 | W6: 350 | X6: =V6+W6 -> 636
A7: Property Preserve And Repair | B7: 0.0080454636 | C7: 0.018413373 | D7: 0.014410713 | E7: 0.014457053 | F7: 0.01618162 | G7: 0.023391342 | H7: 0.027456008 | I7: 0.023540438 | J7: 0.017229908 | K7: 0.012159839 | L7: 0.012143922 | M7: 0.015384889 | N7: 0.017649913 | O7: 0.023263442 | P7: 0.033064194 | Q7: =AVERAGE(B7:P7) -> 0.018452808 | V7: =V5+V6 -> 439 | W7: =W5+W6 -> 470 | X7: =V7+W7 -> 909
A8: Asset Recovery | B8: 0.0063824624 | C8: 0.0047965122 | D8: 0.0052771551 | E8: 0.0046752971 | F8: 0.003846333 | G8: 0.0053432915 | H8: 0.0053785281 | I8: 0.0043639566 | J8: 0.0040010978 | K8: 0.004158921 | L8: 0.0051922756 | M8: 0.0066898518 | N8: 0.0079684527 | O8: 0.0090135819 | P8: 0.0094037956 | Q8: =AVERAGE(B8:P8) -> 0.0057661008
A9: Misc Holding Expenses | B9: 0.0018126094 | C9: 0.001518431 | D9: 0.0033383348 | E9: 0.0034372199 | F9: 0.0034841025 | G9: 0.0035357066 | H9: 0.0040830841 | I9: 0.0034528508 | J9: 0.0021330949 | K9: 0.0023614857 | L9: 0.0031423244 | M9: 0.0051684332 | N9: 0.0079103464 | O9: 0.01229339 | P9: 0.018173217 | Q9: =AVERAGE(B9:P9) -> 0.0050563087
A10: Associated Tax | B10: 0.0034199712 | C10: 0.0073499426 | D10: 0.010683252 | E10: 0.01269278 | F10: 0.014213734 | G10: 0.016478762 | H10: 0.019829747 | I10: 0.021164128 | J10: 0.018936504 | K10: 0.015476173 | L10: 0.01605191 | M10: 0.018195473 | N10: 0.02177793 | O10: 0.028624696 | P10: 0.036205309 | Q10: =AVERAGE(B10:P10) -> 0.017406687
A11: Total Cost | B11: =B4+B5+1 -> 1.077509 | C11: =C4+C5+1 -> 1.1324639 | D11: =D4+D5+1 -> 1.1493595 | E11: =E4+E5+1 -> 1.1548302 | F11: =F4+F5+1 -> 1.1573101 | G11: =G4+G5+1 -> 1.1778264 | H11: =H4+H5+1 -> 1.1947026 | I11: =I4+I5+1 -> 1.1810649 | ... P11: =P4+P5+1 -> 1.2936022 | Q11: 1.18
A13: PROCEEDS
A14: Net Sale Proceeds | B14: 1.0143553 | C14: 0.76002322 | D14: 0.79609159 | E14: 0.76611289 | F14: 0.77841624 | G14: 0.79395329 | H14: 0.77848654 | I14: 0.76467226 | J14: 0.71425569 | K14: 0.63162663 | L14: 0.62015037 | M14: 0.58822992 | N14: 0.63741597 | O14: 0.71243535 | P14: 0.74440157 | Q14: 0.66
A15: Credit Enhancement | B15: 0.069843576 | C15: 0.16004382 | D15: 0.16355638 | E15: 0.15797621 | F15: 0.15277552 | G15: 0.15204054 | H15: 0.16093875 | I15: 0.1422654 | J15: 0.11117143 | K15: 0.094229818 | L15: 0.079078359 | M15: 0.070483801 | N15: 0.070255495 | O15: 0.068462719 | P15: 0.06813012 | Q15: 0.08
A16: Repurchase Make Whole | B16: 0 | C16: 0.15059481 | D16: 0.11942038 | E16: 0.13027452 | F16: 0.10284814 | G16: 0.078162962 | H16: 0.048421078 | I16: 0.034494707 | J16: 0.043219649 | K16: 0.077981874 | L16: 0.086555175 | M16: 0.078887009 | N16: 0.04882204 | O16: 0.026431466 | P16: 0.0084919502 | Q16: 0.06
A17: Other | B17: 0.0032629443 | C17: 0.038464937 | D17: 0.037679942 | E17: 0.041566184 | F17: 0.050495457 | G17: 0.051560185 | H17: 0.054605612 | I17: 0.045006523 | J17: 0.01837519 | K17: 0.0077761945 | L17: 0.0082850071 | M17: 0.012673218 | N17: 0.013589347 | O17: 0.015658651 | P17: 0.018155664 | Q17: 0.02
A18: Total Proceeds | B18: 1.0874618 | C18: 1.1091268 | D18: 1.1167483 | E18: 1.0959298 | F18: 1.0845354 | G18: 1.075717 | H18: 1.042452 | I18: 0.98643889 | J18: 0.88702195 | K18: 0.81161451 | L18: 0.79406892 | M18: 0.75027394 | N18: 0.77008285 | O18: 0.82298819 | P18: 0.83917931 | Q18: 0.82
A19: Severity | B19: =B11-B18 -> -0.00995277 | C19: =C11-C18 -> 0.023337085 | D19: =D11-D18 -> 0.032611169 | E19: =E11-E18 -> 0.05890036 | F19: =F11-F18 -> 0.072774781 | G19: =G11-G18 -> 0.10210942 | H19: =H11-H18 -> 0.15225064 | I19: =I11-I18 -> 0.19462601 | ... P19: =P11-P18 -> 0.4544229 | Q19: 0.366
B20: =B19*B36/1000000 -> -0.078615245 | C20: =C19*C36/1000000 -> 3.2310129 | D20: =D19*D36/1000000 -> 16.37444 | E20: =E19*E36/1000000 -> 60.507242 | F20: =F19*F36/1000000 -> 97.063168 | G20: =G19*G36/1000000 -> 124.98115 | H20: =H19*H36/1000000 -> 189.20903 | I20: =I19*I36/1000000 -> 300.30012 | ... P20: =P19*P36/1000000 -> 2782.762
A35: Year | B35: 2000 | C35: 2001 | D35: 2002 | E35: 2003 | F35: 2004 | G35: 2005 | H35: 2006 | I35: 2007 | J35: 2008 | K35: 2009 | L35: 2010 | M35: 2011 | N35: 2012 | O35: 2013 | P35: 2014
A36: sum(LoanLevelHistMonthlyPerformData.currentRPB) | B36: 7898830.7 | C36: 1.3844972e+08 | D36: 5.0211141e+08 | E36: 1.0272814e+09 | F36: 1.3337473e+09 | G36: 1.2239923e+09 | H36: 1.242747e+09 | I36: 1.5429599e+09 | J36: 2.9510611e+09 | K36: 6.6909993e+09 | L36: 1.4632611e+10 | M36: 1.4366886e+10 | N36: 1.3116468e+10 | O36: 9.1541122e+09 | P36: 6.1237274e+09
A38: ForeclosureCostsPct | B38: 191117 | C38: 4141074 | D38: 16207312 | E38: 32765112 | F38: 45757759 | G38: 50513596 | H38: 50674017 | I38: 54197867 | J38: 79143909 | K38: 162221641 | L38: 383233344 | M38: 357931404 | N38: 384310530 | O38: 308319125 | P38: 117894107
A39: PropertyPreserveAndRepairCostPct | B39: 184302 | C39: 2804611 | D39: 8081090 | E39: 16395200 | F39: 28881005 | G39: 34008250 | H39: 31725557 | I39: 32735411 | J39: 48621027 | K39: 99061516 | L39: 240476692 | M39: 230632664 | N39: 244531636 | O39: 206092653 | P39: 65177166
A40: AssetRecoveryCostPct | B40: 43070 | C40: 959627 | D40: 2925246 | E40: 4146674 | F40: 6281274 | G40: 7510651 | H40: 6128685 | I40: 6565751 | J40: 11947449 | K40: 32442561 | L40: 88880505 | M40: 99675202 | N40: 108306692 | O40: 79311827 | P40: 23829913
A41: MiscHoldingExpenseAndCreditsPct | B41: 22580 | C41: 358585 | D41: 1894153 | E41: 3884287 | F41: 4972521 | G41: 4541696 | H41: 5472148 | I41: 3802848 | J41: 7047544 | K41: 22736993 | L41: 64541779 | M41: 85578183 | N41: 126126073 | O41: 120325359 | P41: 50338289
A42: AssociatedTaxforHoldingPropertyPct | B42: 60756 | C42: 1436742 | D42: 6292821 | E42: 14555914 | F42: 21721430 | G42: 24274928 | H42: 27925354 | I42: 32860251 | J42: 56098522 | K42: 115983231 | L42: 285735507 | M42: 268429870 | N42: 308419143 | O42: 244457739 | P42: 91732167
A43: Expenses | B43: 312689 | C43: 4738301 | D43: 16911440 | E43: 29774966 | F43: 49226864 | G43: 63713096 | H43: 58879034 | I43: 60165723 | J43: 92295411 | K43: 199301896 | L43: 578197779 | M43: 623453354 | N43: 715637165 | O43: 541395087 | P43: 167837441
A45: NetSaleProceedsPct | B45: 5530161 | C45: 100179716 | D45: 377265471 | E45: 769361961 | F45: 1039478922 | G45: 962210784 | H45: 951765677 | I45: 1098965797 | J45: 1914379189 | K45: 4128195908 | L45: 8788434504 | M45: 8753887069 | N45: 8706073066 | O45: 6184298820 | P45: 2373058371
A46: CreditEnhancementProceedsPct | B46: 1241356 | C46: 24495186 | D46: 82133605 | E46: 163215364 | F46: 209838629 | G46: 190880687 | H46: 187008422 | I46: 194952683 | J46: 308544425 | K46: 583255253 | L46: 1129924589 | M46: 947267121 | N46: 905355437 | O46: 590589176 | P46: 198182018
A47: RepurchaseMakeWholeProceedsPct | B47: 1615157 | C47: 23307366 | D47: 70642032 | E47: 130790916 | F47: 119279554 | G47: 67677116 | H47: 42369388 | I47: 64934457 | J47: 190618952 | K47: 632418943 | L47: 1351873621 | M47: 875577036 | N47: 464818949 | O47: 105373972 | P47: 9117224
A48: OtherForecloseProceedsPct | B48: 86167 | C48: 5749999 | D48: 18288344 | E48: 47170736 | F48: 59984066 | G48: 61974203 | H48: 62600474 | I48: 54922627 | J48: 40778452 | K48: 55169367 | L48: 163863038 | M48: 211399538 | N48: 169469766 | O48: 121556378 | P48: 46859084
A49: Proceeds | B49: 676478 | C49: 5063343 | D49: 15039885 | E49: 27357946 | F49: 23218434 | G49: 13508766 | H49: 11204364 | I49: 9537348 | J49: 78851773 | K49: 259324298 | L49: 424432525 | M49: 278636797 | N49: 159866537 | O49: 28970597 | P49: 1888966
A54: Year | B54: Interest | C54: ForeclosureCostsPct | D54: PropertyPreserveAndRepairCostPct | E54: AssetRecoveryCostPct | F54: MiscHoldingExpenseAndCreditsPct | G54: AssociatedTaxforHoldingPropertyPct | H54: Expenses | I54: NetSaleProceedsPct | J54: CreditEnhancementProceedsPct | K54: RepurchaseMakeWholeProceedsPct | L54: OtherForecloseProceedsPct | M54: Proceeds
A55: 2000 | B55: 0.045644944 | C55: 0.012203585 | D55: 0.0080454636 | E55: 0.0063824624 | F55: 0.0018126094 | G55: 0.0034199712 | H55: 0.031864091 | I55: 1.0143553 | J55: 0.069843576 | K55: 0 | L55: 0.0032629443 | M55: 1.0874618
A56: 2001 | B56: 0.077126885 | C56: 0.023258731 | D56: 0.018413373 | E56: 0.0047965122 | F56: 0.001518431 | G56: 0.0073499426 | H56: 0.05533699 | I56: 0.76002322 | J56: 0.16004382 | K56: 0.15059481 | L56: 0.038464937 | M56: 1.1091268
A57: 2002 | B57: 0.086539642 | C57: 0.029110359 | D57: 0.014410713 | E57: 0.0052771551 | F57: 0.0033383348 | G57: 0.010683252 | H57: 0.062819814 | I57: 0.79609159 | J57: 0.16355638 | K57: 0.11942038 | L57: 0.037679942 | M57: 1.1167483
A58: 2003 | B58: 0.088162106 | C58: 0.031405709 | D58: 0.014457053 | E58: 0.0046752971 | F58: 0.0034372199 | G58: 0.01269278 | H58: 0.066668059 | I58: 0.76611289 | J58: 0.15797621 | K58: 0.13027452 | L58: 0.041566184 | M58: 1.0959298
A59: 2004 | B59: 0.08879892 | C59: 0.030785428 | D59: 0.01618162 | E59: 0.003846333 | F59: 0.0034841025 | G59: 0.014213734 | H59: 0.068511218 | I59: 0.77841624 | J59: 0.15277552 | K59: 0.10284814 | L59: 0.050495457 | M59: 1.0845354
A60: 2005 | B60: 0.092340888 | C60: 0.036736405 | D60: 0.023391342 | E60: 0.0053432915 | F60: 0.0035357066 | G60: 0.016478762 | H60: 0.085485507 | I60: 0.79395329 | J60: 0.15204054 | K60: 0.078162962 | L60: 0.051560185 | M60: 1.075717
A61: 2006 | B61: 0.096726046 | C61: 0.041229213 | D61: 0.027456008 | E61: 0.0053785281 | F61: 0.0040830841 | G61: 0.019829747 | H61: 0.09797658 | I61: 0.77848654 | J61: 0.16093875 | K61: 0.048421078 | L61: 0.054605612 | M61: 1.042452
A62: 2007 | B62: 0.089745739 | C62: 0.038797789 | D62: 0.023540438 | E62: 0.0043639566 | F62: 0.0034528508 | G62: 0.021164128 | H62: 0.091319163 | I62: 0.76467226 | J62: 0.1422654 | K62: 0.034494707 | L62: 0.045006523 | M62: 0.98643889
A63: 2008 | B63: 0.081043535 | C63: 0.029626221 | D63: 0.017229908 | E63: 0.0040010978 | F63: 0.0021330949 | G63: 0.018936504 | H63: 0.071926825 | I63: 0.71425569 | J63: 0.11117143 | K63: 0.043219649 | L63: 0.01837519 | M63: 0.88702195
A64: 2009 | B64: 0.075122103 | C64: 0.021622909 | D64: 0.012159839 | E64: 0.004158921 | F64: 0.0023614857 | G64: 0.015476173 | H64: 0.055779328 | I64: 0.63162663 | J64: 0.094229818 | K64: 0.077981874 | L64: 0.0077761945 | M64: 0.81161451
A65: 2010 | B65: 0.082118553 | C65: 0.023602931 | D65: 0.012143922 | E65: 0.0051922756 | F65: 0.0031423244 | G65: 0.01605191 | H65: 0.060133363 | I65: 0.62015037 | J65: 0.079078359 | K65: 0.086555175 | L65: 0.0082850071 | M65: 0.79406892
A66: 2011 | B66: 0.093235643 | C66: 0.024930145 | D66: 0.015384889 | E66: 0.0066898518 | F66: 0.0051684332 | G66: 0.018195473 | H66: 0.070368792 | I66: 0.58822992 | J66: 0.070483801 | K66: 0.078887009 | L66: 0.012673218 | M66: 0.75027394
... A69: 2014 | B69: 0.15259221 | C69: 0.044163473 | D69: 0.033064194 | E69: 0.0094037956 | F69: 0.018173217 | G69: 0.036205309 | H69: 0.14100999 | I69: 0.74440157 | J69: 0.06813012 | K69: 0.0084919502 | L69: 0.018155664 | M69: 0.83917931

Sheet Total
A1: dispositiondate | B1: Interest | C1: ForeclosureCostsPct | D1: PropertyPreserveAndRepairCostPct | E1: AssetRecoveryCostPct | F1: MiscHoldingExpenseAndCreditsPct | G1: AssociatedTaxforHoldingPropertyPct | H1: Expenses | J1: NetSaleProceedsPct | K1: CreditEnhancementProceedsPct | L1: RepurchaseMakeWholeProceedsPct | M1: OtherForecloseProceedsPct | N1: Proceeds | O1: Proceeds | P1: Severity | T1: FHL | V1: FNMA
A2: 36770 | B2: 0.044129954 | C2: 0.0046020586 | D2: 0 | E2: 0 | F2: 0 | G2: 0 | H2: 0.0046020586 | I2: =B2+H2+1 -> 1.048732 | J2: 1.0526067 | K2: 0 | L2: 0 | M2: 0 | N2: 1.0526067 | O2: 1.1972648 | P2: =I2-O2 -> -0.14853281 | T2: Actural | U2: Estim | V2: Actual
A3: 36831 | B3: 0.043370685 | C3: 0.018381869 | D3: 0.015644467 | E3: 0.010539377 | F3: 0.0027272727 | G3: 0.0064775893 | H3: 0.053770575 | I3: =B3+H3+1 -> 1.0971413 | J3: 0.9986199 | K3: 0.11206888 | L3: 0 | M3: 0.0053203343 | N3: 1.1160091 | O3: 1.1018724 | P3: =I3-O3 -> -0.0047311135 | S3: 36526 | T3: 0 | U3: -0.025202227 | V3: =VLOOKUP(S3,A:P,16,0) -> #N/A
A4: 36861 | B4: 0.055 | C4: 0.0096361134 | D4: 0.0023448826 | E4: 0.0071273028 | F4: 0.0027725208 | G4: 0.001482479 | H4: 0.023363299 | I4: =B4+H4+1 -> 1.0783633 | J4: 0.98405957 | K4: 0.087181168 | L4: 0 | M4: 0.0038344889 | N4: 1.0750752 | O4: 1.1149449 | P4: =I4-O4 -> -0.03658158 | S4: 36557 | T4: 0.029483169 | U4: 0.29370823 | V4: =VLOOKUP(S4,A:P,16,0) -> #N/A
A5: 36892 | B5: 0.063505736 | C5: 0.014186798 | D5: 0.0071557571 | E5: 0.0065072345 | F5: -0.00041009516 | G5: 0.0074448045 | H5: 0.034884499 | I5: =B5+H5+1 -> 1.0983902 | J5: 0.85286735 | K5: 0.16719411 | L5: 0.042707119 | M5: 0.00057736117 | N5: 1.0633459 | O5: 1.1219672 | P5: =I5-O5 -> -0.023576945 | S5: 36586 | T5: 0.00047097972 | U5: 0.052109176 | V5: =VLOOKUP(S5,A:P,16,0) -> #N/A
A6: 36923 | B6: 0.061097626 | C6: 0.01084847 | D6: 0.013088261 | E6: 0.0012204788 | F6: -0.00035048584 | G6: 0.0075914404 | H6: 0.032398165 | I6: =B6+H6+1 -> 1.0934958 | J6: 0.76645447 | K6: 0.0603126 | L6: 0.078106496 | M6: 0.17513923 | N6: 1.0800128 | O6: 1.145623 | P6: =I6-O6 -> -0.052127162 | S6: 36617 | T6: 0.045120999 | U6: 0.10898449 | V6: =VLOOKUP(S6,A:P,16,0) -> #N/A
A7: 36951 | B7: 0.073558562 | C7: 0.017528084 | D7: 0.01707944 | E7: 0.0019322267 | F7: 0.0029477266 | G7: 0.0076186297 | H7: 0.047106107 | I7: =B7+H7+1 -> 1.1206647 | J7: 0.81168713 | K7: 0.15395178 | L7: 0.11402002 | M7: 0.033789174 | N7: 1.1134481 | O7: 1.1601957 | P7: =I7-O7 -> -0.039531038 | S7: 36647 | T7: 0.013876271 | U7: 0.046184785 | V7: =VLOOKUP(S7,A:P,16,0) -> #N/A
A8: 36982 | B8: 0.065513945 | C8: 0.01840928 | D8: 0.0086977176 | E8: 0.0048787866 | F8: -9.138339e-05 | G8: 0.0073704218 | H8: 0.039264822 | I8: =B8+H8+1 -> 1.1047788 | J8: 0.69332322 | K8: 0.22139575 | L8: 0.18430847 | M8: 0.0031300409 | N8: 1.1021575 | O8: 1.1406252 | P8: =I8-O8 -> -0.035846427 | S8: 36678 | T8: 0.029666311 | U8: 0.17814182 | V8: =VLOOKUP(S8,A:P,16,0) -> #N/A
A9: 37012 | B9: 0.070216614 | C9: 0.020135836 | D9: 0.024928087 | E9: 0.0028169478 | F9: 0.0020572953 | G9: 0.0076301498 | H9: 0.057568316 | I9: =B9+H9+1 -> 1.1277849 | J9: 0.85544817 | K9: 0.14064849 | L9: 0.11303433 | M9: 0.011061389 | N9: 1.1201924 | O9: 1.0876175 | P9: =I9-O9 -> 0.040167458 | S9: 36708 | T9: 0.021487661 | U9: 0.1281643 | V9: =VLOOKUP(S9,A:P,16,0) -> #N/A
A10: 37043 | B10: 0.073447771 | C10: 0.021387666 | D10: 0.013008769 | E10: 0.0036166073 | F10: 0.00037465537 | G10: 0.006141382 | H10: 0.04452908 | I10: =B10+H10+1 -> 1.1179769 | J10: 0.77418331 | K10: 0.13567768 | L10: 0.15552047 | M10: 0.035299175 | N10: 1.1006806 | O10: 1.1148062 | P10: =I10-O10 -> 0.003170685 | S10: 36739 | T10: 0.020187618 | U10: 0.089225365 | V10: =VLOOKUP(S10,A:P,16,0) -> #N/A
A11: 37073 | B11: 0.074491023 | C11: 0.018838419 | D11: 0.015283745 | E11: 0.0044614985 | F11: 0.0011984071 | G11: 0.0062111729 | H11: 0.045993243 | I11: =B11+H11+1 -> 1.1204843 | J11: 0.7541403 | K11: 0.20097792 | L11: 0.13134686 | M11: 0.0086431283 | N11: 1.0951082 | O11: 1.1121202 | P11: =I11-O11 -> 0.0083640343 | S11: 36770 | T11: 0.018294944 | U11: 0.056410352 | V11: =VLOOKUP(S11,A:P,16,0) -> -0.14853281
A12: 37104 | B12: 0.069184435 | C12: 0.02724743 | D12: 0.012095495 | E12: 0.0047807393 | F12: 0.0016730831 | G12: 0.0060450447 | H12: 0.051841792 | I12: =B12+H12+1 -> 1.1210262 | J12: 0.75211645 | K12: 0.15840547 | L12: 0.10490816 | M12: 0.075276306 | N12: 1.0907064 | O12: 1.1417744 | P12: =I12-O12 -> -0.020748191 | S12: 36800 | T12: 0.018924636 | U12: 0.025583014 | V12: =VLOOKUP(S12,A:P,16,0) -> #N/A
A13: 37135 | B13: 0.083641215 | C13: 0.021652646 | D13: 0.01434458 | E13: 0.0051814941 | F13: 0.0021753198 | G13: 0.007749701 | H13: 0.051103741 | I13: =B13+H13+1 -> 1.134745 | J13: 0.76171386 | K13: 0.14439402 | L13: 0.15531906 | M13: 0.039033657 | N13: 1.1004606 | O13: 1.1348414 | P13: =I13-O13 -> -9.649216e-05 | S13: 36831 | T13: 0.032175582 | U13: 0.063431994 | V13: =VLOOKUP(S13,A:P,16,0) -> -0.0047311135
A14: 37165 | B14: 0.082321213 | C14: 0.02497844 | D14: 0.016744077 | E14: 0.0057476189 | F14: 0.0021140902 | G14: 0.0066820133 | H14: 0.056266239 | I14: =B14+H14+1 -> 1.1385875 | J14: 0.72025257 | K14: 0.15112229 | L14: 0.20839846 | M14: 0.0416662 | N14: 1.1214395 | O14: 1.1102609 | P14: =I14-O14 -> 0.028326589 | S14: 36861 | T14: 0.054973311 | U14: 0.1642641 | V14: =VLOOKUP(S14,A:P,16,0) -> -0.03658158
... A172: 41974 | B172: 0.167088 | C172: 0.048305421 | D172: 0.041584889 | E172: 0.01010701 | F172: 0.020852587 | G172: 0.040384463 | H172: 0.16123437 | I172: =B172+H172+1 -> 1.3283224 | J172: 0.752585 | K172: 0.064254126 | L172: 0.0044963046 | M172: 0.018486646 | N172: 0.83982208 | O172: 0.85453104 | P172: =I172-O172 -> 0.47379133 | S172: 41671 | T172: 0.53622668 | U172: 0.49936245 | V172: =VLOOKUP(S172,A:P,16,0) -> 0.41918064
A173: 41944 | B173: 0.11575233 | C173: 0.024339527 | D173: 0.0044050199 | E173: 0.0052162 | F173: 0.013573931 | G173: 0.029243441 | H173: 0.076778118 | I173: =B173+H173+1 -> 1.1925305 | J173: =B173+H173+1 -> 1.1925305 | K173: 0.82041994 | L173: 0.039462865 | M173: 0.0011831116 | N173: 0.0089298684 | O173: 0.86999578 | P173: =I173-O173 -> 0.32253467 | S173: 41699 | T173: 0.52510059 | U173: 0.49017286 | V173: =VLOOKUP(S173,A:P,16,0) -> 0.43061916
A174: 41974 | B174: 0.11142558 | C174: 0.023839986 | D174: 0.0026431704 | E174: 0.0049754557 | F174: 0.010409596 | G174: 0.028925838 | H174: 0.070794046 | I174: =B174+H174+1 -> 1.1822196 | J174: =B174+H174+1 -> 1.1822196 | K174: 0.82984566 | L174: 0.042270704 | M174: 0 | N174: 0.0093742942 | O174: 0.88149066 | P174: =I174-O174 -> 0.30072897 | S174: 41730 | T174: 0.53007323 | U174: 0.49068919 | V174: =VLOOKUP(S174,A:P,16,0) -> 0.42343612
A175: 42005 | B175: 0.10318172 | C175: 0.05365969 | D175: 0.026877676 | E175: 0 | F175: 0.014850294 | G175: 0.030316307 | H175: 0.12570397 | I175: =B175+H175+1 -> 1.2288857 | J175: =B175+H175+1 -> 1.2288857 | K175: 0.7033105 | L175: 0.10401468 | M175: 0 | N175: 0.011262082 | O175: 0.81858725 | P175: =I175-O175 -> 0.41029844 | S175: 41760 | T175: 0.53400349 | U175: 0.48796122 | V175: =VLOOKUP(S175,A:P,16,0) -> 0.43617623
A176: 42036 | B176: 0.12567916 | C176: 0.049141781 | D176: 0.021579814 | E176: 0.015449271 | F176: 0.0095615501 | G176: 0.015240922 | H176: 0.11097334 | I176: =B176+H176+1 -> 1.2366525 | J176: =B176+H176+1 -> 1.2366525 | K176: 0.87309138 | L176: 0.014861698 | M176: 0 | N176: 0.018253732 | O176: 0.90620681 | P176: =I176-O176 -> 0.33044569 | S176: 41791 | T176: 0.56045607 | U176: 0.48876552 | V176: =VLOOKUP(S176,A:P,16,0) -> 0.44850285
A177: 42064 | B177: 0.12448688 | C177: 0.042394086 | D177: 0.048303048 | E177: 0.012381789 | F177: 0.0035205625 | G177: 0.023437552 | H177: 0.13003704 | I177: =B177+H177+1 -> 1.2545239 | J177: =B177+H177+1 -> 1.2545239 | K177: 0.80709283 | L177: 0.046001056 | M177: 0 | N177: 0.060218457 | O177: 0.91331234 | P177: =I177-O177 -> 0.34121158 | S177: 41821 | T177: 0.5994286 | U177: 0.49269073 | V177: =VLOOKUP(S177,A:P,16,0) -> 0.44265097
S178: 41852 | T178: 0.59640021 | U178: 0.5286428 | V178: =VLOOKUP(S178,A:P,16,0) -> 0.46289637
T179: 0.73373296 | U179: 0.49507167 | V179: =VLOOKUP(S179,A:P,16,0) -> #N/A

Sheet Combined
K1: Interest | O1: MI | S1: expenses | W1: Non-MI | AA1: Total | AE1: Base Loss
A2: lossDate | B2: interest | C2: miRecoveries | D2: nonMIRecoveries | E2: expenses | F2: netSaleProceeds | G2: ActuralSeverity | K2: FHL | L2: FNMA | O2: FHL | P2: FNMA | S2: FHL | T2: FNMA | W2: FHL | X2: FNMA | AA2: FHL | AB2: FNMA | AE2: FHL | AF2: FNMA
A3: 36892 | B3: 0.067081483 | C3: 0.18105061 | D3: 0.18105061 | E3: -0.050292646 | F3: 0.61083333 | G3: 0.036380463 | J3: 36892 | K3: =VLOOKUP(J3,A:G,2,0) -> 0.067081483 | L3: =VLOOKUP(J3,Total!A:P,2,0) -> 0.063505736 | N3: =J3 -> 36892 | O3: =VLOOKUP(J3,A:G,3,0) -> 0.18105061 | P3: =VLOOKUP(J3,Total!A:P,11,0) -> 0.16719411 | R3: =N3 -> 36892 | S3: =-VLOOKUP(J3,A:G,5,0) -> 0.050292646 | T3: =VLOOKUP(J3,Total!A:P,8,0) -> 0.034884499 | V3: =R3 -> 36892 | W3: =VLOOKUP(J3,A:G,4,0) -> 0.18105061 | X3: =VLOOKUP(J3,Total!A:P,12,0)+VLOOKUP(J3,Total!A:P,13,0) -> 0.04328448 | Z3: =V3 -> 36892 | AA3: =VLOOKUP(J3,A:G,7,0) -> 0.036380463 | AB3: =VLOOKUP(J3,Total!A:P,16,0) -> -0.023576945 | AD3: =Z3 -> 36892 | AE3: =AA3+O3+W3-K3-S3 -> 0.28110755 | AF3: =AB3+P3+X3-L3-T3 -> 0.08851141
A4: 36923 | B4: 0.06846882 | C4: 0.15625382 | D4: 0.15625382 | E4: -0.053613517 | F4: 0.70074551 | G4: 0.033402912 | J4: 36923 | K4: =VLOOKUP(J4,A:G,2,0) -> 0.06846882 | L4: =VLOOKUP(J4,Total!A:P,2,0) -> 0.061097626 | N4: =J4 -> 36923 | O4: =VLOOKUP(J4,A:G,3,0) -> 0.15625382 | P4: =VLOOKUP(J4,Total!A:P,11,0) -> 0.0603126 | R4: =N4 -> 36923 | S4: =-VLOOKUP(J4,A:G,5,0) -> 0.053613517 | T4: =VLOOKUP(J4,Total!A:P,8,0) -> 0.032398165 | V4: =R4 -> 36923 | W4: =VLOOKUP(J4,A:G,4,0) -> 0.15625382 | X4: =VLOOKUP(J4,Total!A:P,12,0)+VLOOKUP(J4,Total!A:P,13,0) -> 0.25324572 | Z4: =V4 -> 36923 | AA4: =VLOOKUP(J4,A:G,7,0) -> 0.033402912 | AB4: =VLOOKUP(J4,Total!A:P,16,0) -> -0.052127162 | AD4: =Z4 -> 36923 | AE4: =AA4+O4+W4-K4-S4 -> 0.22382822 | AF4: =AB4+P4+X4-L4-T4 -> 0.16793537
A5: 36951 | B5: 0.072709305 | C5: 0.20269618 | D5: 0.20269618 | E5: -0.046337984 | F5: 0.73603751 | G5: 0.042661984 | J5: 36951 | K5: =VLOOKUP(J5,A:G,2,0) -> 0.072709305 | L5: =VLOOKUP(J5,Total!A:P,2,0) -> 0.073558562 | N5: =J5 -> 36951 | O5: =VLOOKUP(J5,A:G,3,0) -> 0.20269618 | P5: =VLOOKUP(J5,Total!A:P,11,0) -> 0.15395178 | R5: =N5 -> 36951 | S5: =-VLOOKUP(J5,A:G,5,0) -> 0.046337984 | T5: =VLOOKUP(J5,Total!A:P,8,0) -> 0.047106107 | V5: =R5 -> 36951 | W5: =VLOOKUP(J5,A:G,4,0) -> 0.20269618 | X5: =VLOOKUP(J5,Total!A:P,12,0)+VLOOKUP(J5,Total!A:P,13,0) -> 0.14780919 | Z5: =V5 -> 36951 | AA5: =VLOOKUP(J5,A:G,7,0) -> 0.042661984 | AB5: =VLOOKUP(J5,Total!A:P,16,0) -> -0.039531038 | AD5: =Z5 -> 36951 | AE5: =AA5+O5+W5-K5-S5 -> 0.32900705 | AF5: =AB5+P5+X5-L5-T5 -> 0.14156526
A6: 36982 | B6: 0.076695836 | C6: 0.17730268 | D6: 0.17730268 | E6: -0.057232241 | F6: 0.75394763 | G6: 0.022597555 | J6: 36982 | K6: =VLOOKUP(J6,A:G,2,0) -> 0.076695836 | L6: =VLOOKUP(J6,Total!A:P,2,0) -> 0.065513945 | N6: =J6 -> 36982 | O6: =VLOOKUP(J6,A:G,3,0) -> 0.17730268 | P6: =VLOOKUP(J6,Total!A:P,11,0) -> 0.22139575 | R6: =N6 -> 36982 | S6: =-VLOOKUP(J6,A:G,5,0) -> 0.057232241 | T6: =VLOOKUP(J6,Total!A:P,8,0) -> 0.039264822 | V6: =R6 -> 36982 | W6: =VLOOKUP(J6,A:G,4,0) -> 0.17730268 | X6: =VLOOKUP(J6,Total!A:P,12,0)+VLOOKUP(J6,Total!A:P,13,0) -> 0.18743852 | Z6: =V6 -> 36982 | AA6: =VLOOKUP(J6,A:G,7,0) -> 0.022597555 | AB6: =VLOOKUP(J6,Total!A:P,16,0) -> -0.035846427 | AD6: =Z6 -> 36982 | AE6: =AA6+O6+W6-K6-S6 -> 0.24327484 | AF6: =AB6+P6+X6-L6-T6 -> 0.26820907
A7: 37012 | B7: 0.07391983 | C7: 0.19891039 | D7: 0.19891039 | E7: -0.048647285 | F7: 0.68920607 | G7: 0.011923887 | J7: 37012 | K7: =VLOOKUP(J7,A:G,2,0) -> 0.07391983 | L7: =VLOOKUP(J7,Total!A:P,2,0) -> 0.070216614 | N7: =J7 -> 37012 | O7: =VLOOKUP(J7,A:G,3,0) -> 0.19891039 | P7: =VLOOKUP(J7,Total!A:P,11,0) -> 0.14064849 | R7: =N7 -> 37012 | S7: =-VLOOKUP(J7,A:G,5,0) -> 0.048647285 | T7: =VLOOKUP(J7,Total!A:P,8,0) -> 0.057568316 | V7: =R7 -> 37012 | W7: =VLOOKUP(J7,A:G,4,0) -> 0.19891039 | X7: =VLOOKUP(J7,Total!A:P,12,0)+VLOOKUP(J7,Total!A:P,13,0) -> 0.12409572 | Z7: =V7 -> 37012 | AA7: =VLOOKUP(J7,A:G,7,0) -> 0.011923887 | AB7: =VLOOKUP(J7,Total!A:P,16,0) -> 0.040167458 | AD7: =Z7 -> 37012 | AE7: =AA7+O7+W7-K7-S7 -> 0.28717756 | AF7: =AB7+P7+X7-L7-T7 -> 0.17712674
A8: 37043 | B8: 0.073619748 | C8: 0.15205841 | D8: 0.15205841 | E8: -0.051385241 | F8: 0.76410792 | G8: 0.021925473 | J8: 37043 | K8: =VLOOKUP(J8,A:G,2,0) -> 0.073619748 | L8: =VLOOKUP(J8,Total!A:P,2,0) -> 0.073447771 | N8: =J8 -> 37043 | O8: =VLOOKUP(J8,A:G,3,0) -> 0.15205841 | P8: =VLOOKUP(J8,Total!A:P,11,0) -> 0.13567768 | R8: =N8 -> 37043 | S8: =-VLOOKUP(J8,A:G,5,0) -> 0.051385241 | T8: =VLOOKUP(J8,Total!A:P,8,0) -> 0.04452908 | V8: =R8 -> 37043 | W8: =VLOOKUP(J8,A:G,4,0) -> 0.15205841 | X8: =VLOOKUP(J8,Total!A:P,12,0)+VLOOKUP(J8,Total!A:P,13,0) -> 0.19081964 | Z8: =V8 -> 37043 | AA8: =VLOOKUP(J8,A:G,7,0) -> 0.021925473 | AB8: =VLOOKUP(J8,Total!A:P,16,0) -> 0.003170685 | AD8: =Z8 -> 37043 | AE8: =AA8+O8+W8-K8-S8 -> 0.2010373 | AF8: =AB8+P8+X8-L8-T8 -> 0.21169116
A9: 37073 | B9: 0.073445 | C9: 0.1382431 | D9: 0.1382431 | E9: -0.056009229 | F9: 0.76048545 | G9: 0.06729369 | J9: 37073 | K9: =VLOOKUP(J9,A:G,2,0) -> 0.073445 | L9: =VLOOKUP(J9,Total!A:P,2,0) -> 0.074491023 | N9: =J9 -> 37073 | O9: =VLOOKUP(J9,A:G,3,0) -> 0.1382431 | P9: =VLOOKUP(J9,Total!A:P,11,0) -> 0.20097792 | R9: =N9 -> 37073 | S9: =-VLOOKUP(J9,A:G,5,0) -> 0.056009229 | T9: =VLOOKUP(J9,Total!A:P,8,0) -> 0.045993243 | V9: =R9 -> 37073 | W9: =VLOOKUP(J9,A:G,4,0) -> 0.1382431 | X9: =VLOOKUP(J9,Total!A:P,12,0)+VLOOKUP(J9,Total!A:P,13,0) -> 0.13998999 | Z9: =V9 -> 37073 | AA9: =VLOOKUP(J9,A:G,7,0) -> 0.06729369 | AB9: =VLOOKUP(J9,Total!A:P,16,0) -> 0.0083640343 | AD9: =Z9 -> 37073 | AE9: =AA9+O9+W9-K9-S9 -> 0.21432566 | AF9: =AB9+P9+X9-L9-T9 -> 0.22884768
A10: 37104 | B10: 0.077184686 | C10: 0.14921991 | D10: 0.14921991 | E10: -0.055780747 | F10: 0.70501326 | G10: 0.061930282 | J10: 37104 | K10: =VLOOKUP(J10,A:G,2,0) -> 0.077184686 | L10: =VLOOKUP(J10,Total!A:P,2,0) -> 0.069184435 | N10: =J10 -> 37104 | O10: =VLOOKUP(J10,A:G,3,0) -> 0.14921991 | P10: =VLOOKUP(J10,Total!A:P,11,0) -> 0.15840547 | R10: =N10 -> 37104 | S10: =-VLOOKUP(J10,A:G,5,0) -> 0.055780747 | T10: =VLOOKUP(J10,Total!A:P,8,0) -> 0.051841792 | V10: =R10 -> 37104 | W10: =VLOOKUP(J10,A:G,4,0) -> 0.14921991 | X10: =VLOOKUP(J10,Total!A:P,12,0)+VLOOKUP(J10,Total!A:P,13,0) -> 0.18018447 | Z10: =V10 -> 37104 | AA10: =VLOOKUP(J10,A:G,7,0) -> 0.061930282 | AB10: =VLOOKUP(J10,Total!A:P,16,0) -> -0.020748191 | AD10: =Z10 -> 37104 | AE10: =AA10+O10+W10-K10-S10 -> 0.22740467 | AF10: =AB10+P10+X10-L10-T10 -> 0.19681552
A11: 37135 | B11: 0.080731526 | C11: 0.12618147 | D11: 0.12618147 | E11: -0.057501692 | F11: 0.66189533 | G11: 0.054134333 | J11: 37135 | K11: =VLOOKUP(J11,A:G,2,0) -> 0.080731526 | L11: =VLOOKUP(J11,Total!A:P,2,0) -> 0.083641215 | N11: =J11 -> 37135 | O11: =VLOOKUP(J11,A:G,3,0) -> 0.12618147 | P11: =VLOOKUP(J11,Total!A:P,11,0) -> 0.14439402 | R11: =N11 -> 37135 | S11: =-VLOOKUP(J11,A:G,5,0) -> 0.057501692 | T11: =VLOOKUP(J11,Total!A:P,8,0) -> 0.051103741 | V11: =R11 -> 37135 | W11: =VLOOKUP(J11,A:G,4,0) -> 0.12618147 | X11: =VLOOKUP(J11,Total!A:P,12,0)+VLOOKUP(J11,Total!A:P,13,0) -> 0.19435271 | Z11: =V11 -> 37135 | AA11: =VLOOKUP(J11,A:G,7,0) -> 0.054134333 | AB11: =VLOOKUP(J11,Total!A:P,16,0) -> -9.649216e-05 | AD11: =Z11 -> 37135 | AE11: =AA11+O11+W11-K11-S11 -> 0.16826406 | AF11: =AB11+P11+X11-L11-T11 -> 0.20390528
A12: 37165 | B12: 0.07963713 | C12: 0.13274911 | D12: 0.13274911 | E12: -0.053992403 | F12: 0.6889086 | G12: 0.063367516 | J12: 37165 | K12: =VLOOKUP(J12,A:G,2,0) -> 0.07963713 | L12: =VLOOKUP(J12,Total!A:P,2,0) -> 0.082321213 | N12: =J12 -> 37165 | O12: =VLOOKUP(J12,A:G,3,0) -> 0.13274911 | P12: =VLOOKUP(J12,Total!A:P,11,0) -> 0.15112229 | R12: =N12 -> 37165 | S12: =-VLOOKUP(J12,A:G,5,0) -> 0.053992403 | T12: =VLOOKUP(J12,Total!A:P,8,0) -> 0.056266239 | V12: =R12 -> 37165 | W12: =VLOOKUP(J12,A:G,4,0) -> 0.13274911 | X12: =VLOOKUP(J12,Total!A:P,12,0)+VLOOKUP(J12,Total!A:P,13,0) -> 0.25006466 | Z12: =V12 -> 37165 | AA12: =VLOOKUP(J12,A:G,7,0) -> 0.063367516 | AB12: =VLOOKUP(J12,Total!A:P,16,0) -> 0.028326589 | AD12: =Z12 -> 37165 | AE12: =AA12+O12+W12-K12-S12 -> 0.19523621 | AF12: =AB12+P12+X12-L12-T12 -> 0.29092609
A13: 37196 | B13: 0.084809798 | C13: 0.11718486 | D13: 0.11718486 | E13: -0.062849905 | F13: 0.78301811 | G13: 0.090237871 | J13: 37196 | K13: =VLOOKUP(J13,A:G,2,0) -> 0.084809798 | L13: =VLOOKUP(J13,Total!A:P,2,0) -> 0.081691858 | N13: =J13 -> 37196 | O13: =VLOOKUP(J13,A:G,3,0) -> 0.11718486 | P13: =VLOOKUP(J13,Total!A:P,11,0) -> 0.16696237 | R13: =N13 -> 37196 | S13: =-VLOOKUP(J13,A:G,5,0) -> 0.062849905 | T13: =VLOOKUP(J13,Total!A:P,8,0) -> 0.05202268 | V13: =R13 -> 37196 | W13: =VLOOKUP(J13,A:G,4,0) -> 0.11718486 | X13: =VLOOKUP(J13,Total!A:P,12,0)+VLOOKUP(J13,Total!A:P,13,0) -> 0.19480291 | Z13: =V13 -> 37196 | AA13: =VLOOKUP(J13,A:G,7,0) -> 0.090237871 | AB13: =VLOOKUP(J13,Total!A:P,16,0) -> -0.019875818 | AD13: =Z13 -> 37196 | AE13: =AA13+O13+W13-K13-S13 -> 0.17694789 | AF13: =AB13+P13+X13-L13-T13 -> 0.20817492
A14: 37226 | B14: 0.084472034 | C14: 0.13388614 | D14: 0.13388614 | E14: -0.063592646 | F14: 0.69890077 | G14: 0.073543569 | J14: 37226 | K14: =VLOOKUP(J14,A:G,2,0) -> 0.084472034 | L14: =VLOOKUP(J14,Total!A:P,2,0) -> 0.081993014 | N14: =J14 -> 37226 | O14: =VLOOKUP(J14,A:G,3,0) -> 0.13388614 | P14: =VLOOKUP(J14,Total!A:P,11,0) -> 0.16160833 | R14: =N14 -> 37226 | S14: =-VLOOKUP(J14,A:G,5,0) -> 0.063592646 | T14: =VLOOKUP(J14,Total!A:P,8,0) -> 0.083101635 | V14: =R14 -> 37226 | W14: =VLOOKUP(J14,A:G,4,0) -> 0.13388614 | X14: =VLOOKUP(J14,Total!A:P,12,0)+VLOOKUP(J14,Total!A:P,13,0) -> 0.20050206 | Z14: =V14 -> 37226 | AA14: =VLOOKUP(J14,A:G,7,0) -> 0.073543569 | AB14: =VLOOKUP(J14,Total!A:P,16,0) -> 0.035839587 | AD14: =Z14 -> 37226 | AE14: =AA14+O14+W14-K14-S14 -> 0.19325116 | AF14: =AB14+P14+X14-L14-T14 -> 0.23285533
... A35: 37865 | B35: 0.087868288 | C35: 0.15230435 | D35: 0.15230435 | E35: -0.069105729 | F35: 0.72136773 | G35: 0.096701435 | J35: 37865 | K35: =VLOOKUP(J35,A:G,2,0) -> 0.087868288 | L35: =VLOOKUP(J35,Total!A:P,2,0) -> 0.086182645 | N35: =J35 -> 37865 | O35: =VLOOKUP(J35,A:G,3,0) -> 0.15230435 | P35: =VLOOKUP(J35,Total!A:P,11,0) -> 0.16284233 | R35: =N35 -> 37865 | S35: =-VLOOKUP(J35,A:G,5,0) -> 0.069105729 | T35: =VLOOKUP(J35,Total!A:P,8,0) -> 0.064692377 | V35: =R35 -> 37865 | W35: =VLOOKUP(J35,A:G,4,0) -> 0.15230435 | X35: =VLOOKUP(J35,Total!A:P,12,0)+VLOOKUP(J35,Total!A:P,13,0) -> 0.18703095 | Z35: =V35 -> 37865 | AA35: =VLOOKUP(J35,A:G,7,0) -> 0.096701435 | AB35: =VLOOKUP(J35,Total!A:P,16,0) -> 0.06484937 | AD35: =Z35 -> 37865 | AE35: =AA35+O35+W35-K35-S35 -> 0.24433612 | AF35: =AB35+P35+X35-L35-T35 -> 0.26384763
A36: 37895 | B36: 0.088726217 | C36: 0.13949027 | D36: 0.13949027 | E36: -0.075871471 | F36: 0.75159773 | G36: 0.10420448 | J36: 37895 | K36: =VLOOKUP(J36,A:G,2,0) -> 0.088726217 | L36: =VLOOKUP(J36,Total!A:P,2,0) -> 0.089428215 | N36: =J36 -> 37895 | O36: =VLOOKUP(J36,A:G,3,0) -> 0.13949027 | P36: =VLOOKUP(J36,Total!A:P,11,0) -> 0.1485461 | R36: =N36 -> 37895 | S36: =-VLOOKUP(J36,A:G,5,0) -> 0.075871471 | T36: =VLOOKUP(J36,Total!A:P,8,0) -> 0.063413361 | V36: =R36 -> 37895 | W36: =VLOOKUP(J36,A:G,4,0) -> 0.13949027 | X36: =VLOOKUP(J36,Total!A:P,12,0)+VLOOKUP(J36,Total!A:P,13,0) -> 0.19044737 | Z36: =V36 -> 37895 | AA36: =VLOOKUP(J36,A:G,7,0) -> 0.10420448 | AB36: =VLOOKUP(J36,Total!A:P,16,0) -> 0.070809144 | AD36: =Z36 -> 37895 | AE36: =AA36+O36+W36-K36-S36 -> 0.21858733 | AF36: =AB36+P36+X36-L36-T36 -> 0.25696104 | AQ36: 1
A37: 37926 | B37: 0.090423627 | C37: 0.15011951 | D37: 0.15011951 | E37: -0.075831398 | F37: 0.73920822 | G37: 0.1134664 | J37: 37926 | K37: =VLOOKUP(J37,A:G,2,0) -> 0.090423627 | L37: =VLOOKUP(J37,Total!A:P,2,0) -> 0.087281355 | N37: =J37 -> 37926 | O37: =VLOOKUP(J37,A:G,3,0) -> 0.15011951 | P37: =VLOOKUP(J37,Total!A:P,11,0) -> 0.14959091 | R37: =N37 -> 37926 | S37: =-VLOOKUP(J37,A:G,5,0) -> 0.075831398 | T37: =VLOOKUP(J37,Total!A:P,8,0) -> 0.065686461 | V37: =R37 -> 37926 | W37: =VLOOKUP(J37,A:G,4,0) -> 0.15011951 | X37: =VLOOKUP(J37,Total!A:P,12,0)+VLOOKUP(J37,Total!A:P,13,0) -> 0.18585613 | Z37: =V37 -> 37926 | AA37: =VLOOKUP(J37,A:G,7,0) -> 0.1134664 | AB37: =VLOOKUP(J37,Total!A:P,16,0) -> 0.074315517 | AD37: =Z37 -> 37926 | AE37: =AA37+O37+W37-K37-S37 -> 0.24745039 | AF37: =AB37+P37+X37-L37-T37 -> 0.25679474
A38: 37956 | B38: 0.087757125 | C38: 0.14372469 | D38: 0.14372469 | E38: -0.07515191 | F38: 0.6968052 | G38: 0.10098621 | J38: 37956 | K38: =VLOOKUP(J38,A:G,2,0) -> 0.087757125 | L38: =VLOOKUP(J38,Total!A:P,2,0) -> 0.090162471 | N38: =J38 -> 37956 | O38: =VLOOKUP(J38,A:G,3,0) -> 0.14372469 | P38: =VLOOKUP(J38,Total!A:P,11,0) -> 0.15671454 | R38: =N38 -> 37956 | S38: =-VLOOKUP(J38,A:G,5,0) -> 0.07515191 | T38: =VLOOKUP(J38,Total!A:P,8,0) -> 0.075293664 | V38: =R38 -> 37956 | W38: =VLOOKUP(J38,A:G,4,0) -> 0.14372469 | X38: =VLOOKUP(J38,Total!A:P,12,0)+VLOOKUP(J38,Total!A:P,13,0) -> 0.19364597 | Z38: =V38 -> 37956 | AA38: =VLOOKUP(J38,A:G,7,0) -> 0.10098621 | AB38: =VLOOKUP(J38,Total!A:P,16,0) -> 0.078714369 | AD38: =Z38 -> 37956 | AE38: =AA38+O38+W38-K38-S38 -> 0.22552655 | AF38: =AB38+P38+X38-L38-T38 -> 0.26361875
A39: 37987 | B39: 0.090019954 | C39: 0.13729706 | D39: 0.13729706 | E39: -0.068800976 | F39: 0.64135671 | G39: 0.11534898 | J39: 37987 | K39: =VLOOKUP(J39,A:G,2,0) -> 0.090019954 | L39: =VLOOKUP(J39,Total!A:P,2,0) -> 0.086899541 | N39: =J39 -> 37987 | O39: =VLOOKUP(J39,A:G,3,0) -> 0.13729706 | P39: =VLOOKUP(J39,Total!A:P,11,0) -> 0.13780819 | R39: =N39 -> 37987 | S39: =-VLOOKUP(J39,A:G,5,0) -> 0.068800976 | T39: =VLOOKUP(J39,Total!A:P,8,0) -> 0.064205061 | V39: =R39 -> 37987 | W39: =VLOOKUP(J39,A:G,4,0) -> 0.13729706 | X39: =VLOOKUP(J39,Total!A:P,12,0)+VLOOKUP(J39,Total!A:P,13,0) -> 0.18580336 | Z39: =V39 -> 37987 | AA39: =VLOOKUP(J39,A:G,7,0) -> 0.11534898 | AB39: =VLOOKUP(J39,Total!A:P,16,0) -> 0.068608017 | AD39: =Z39 -> 37987 | AE39: =AA39+O39+W39-K39-S39 -> 0.23112216 | AF39: =AB39+P39+X39-L39-T39 -> 0.24111496
A40: 38018 | B40: 0.088321416 | C40: 0.15465018 | D40: 0.15465018 | E40: -0.071449254 | F40: 0.6907308 | G40: 0.10821171 | J40: 38018 | K40: =VLOOKUP(J40,A:G,2,0) -> 0.088321416 | L40: =VLOOKUP(J40,Total!A:P,2,0) -> 0.089969621 | N40: =J40 -> 38018 | O40: =VLOOKUP(J40,A:G,3,0) -> 0.15465018 | P40: =VLOOKUP(J40,Total!A:P,11,0) -> 0.1696073 | R40: =N40 -> 38018 | S40: =-VLOOKUP(J40,A:G,5,0) -> 0.071449254 | T40: =VLOOKUP(J40,Total!A:P,8,0) -> 0.068126547 | V40: =R40 -> 38018 | W40: =VLOOKUP(J40,A:G,4,0) -> 0.15465018 | X40: =VLOOKUP(J40,Total!A:P,12,0)+VLOOKUP(J40,Total!A:P,13,0) -> 0.16573804 | Z40: =V40 -> 38018 | AA40: =VLOOKUP(J40,A:G,7,0) -> 0.10821171 | AB40: =VLOOKUP(J40,Total!A:P,16,0) -> 0.061965097 | AD40: =Z40 -> 38018 | AE40: =AA40+O40+W40-K40-S40 -> 0.25774141 | AF40: =AB40+P40+X40-L40-T40 -> 0.23921427
A41: 38047 | B41: 0.088812242 | C41: 0.13570561 | D41: 0.13570561 | E41: -0.070261719 | F41: 0.65779498 | G41: 0.098655299 | J41: 38047 | K41: =VLOOKUP(J41,A:G,2,0) -> 0.088812242 | L41: =VLOOKUP(J41,Total!A:P,2,0) -> 0.089471668 | N41: =J41 -> 38047 | O41: =VLOOKUP(J41,A:G,3,0) -> 0.13570561 | P41: =VLOOKUP(J41,Total!A:P,11,0) -> 0.15180676 | R41: =N41 -> 38047 | S41: =-VLOOKUP(J41,A:G,5,0) -> 0.070261719 | T41: =VLOOKUP(J41,Total!A:P,8,0) -> 0.068208159 | V41: =R41 -> 38047 | W41: =VLOOKUP(J41,A:G,4,0) -> 0.13570561 | X41: =VLOOKUP(J41,Total!A:P,12,0)+VLOOKUP(J41,Total!A:P,13,0) -> 0.17339854 | Z41: =V41 -> 38047 | AA41: =VLOOKUP(J41,A:G,7,0) -> 0.098655299 | AB41: =VLOOKUP(J41,Total!A:P,16,0) -> 0.060293668 | AD41: =Z41 -> 38047 | AE41: =AA41+O41+W41-K41-S41 -> 0.21099256 | AF41: =AB41+P41+X41-L41-T41 -> 0.22781914
A42: 38078 | B42: 0.089065439 | C42: 0.14060228 | D42: 0.14060228 | E42: -0.077240692 | F42: 0.72545137 | G42: 0.12127312 | J42: 38078 | K42: =VLOOKUP(J42,A:G,2,0) -> 0.089065439 | L42: =VLOOKUP(J42,Total!A:P,2,0) -> 0.086854601 | N42: =J42 -> 38078 | O42: =VLOOKUP(J42,A:G,3,0) -> 0.14060228 | P42: =VLOOKUP(J42,Total!A:P,11,0) -> 0.15471126 | R42: =N42 -> 38078 | S42: =-VLOOKUP(J42,A:G,5,0) -> 0.077240692 | T42: =VLOOKUP(J42,Total!A:P,8,0) -> 0.066884863 | V42: =R42 -> 38078 | W42: =VLOOKUP(J42,A:G,4,0) -> 0.14060228 | X42: =VLOOKUP(J42,Total!A:P,12,0)+VLOOKUP(J42,Total!A:P,13,0) -> 0.15014582 | Z42: =V42 -> 38078 | AA42: =VLOOKUP(J42,A:G,7,0) -> 0.12127312 | AB42: =VLOOKUP(J42,Total!A:P,16,0) -> 0.07723368 | AD42: =Z42 -> 38078 | AE42: =AA42+O42+W42-K42-S42 -> 0.23617155 | AF42: =AB42+P42+X42-L42-T42 -> 0.2283513
A43: 38108 | B43: 0.090233695 | C43: 0.15755851 | D43: 0.15755851 | E43: -0.077462396 | F43: 0.74622404 | G43: 0.11596033 | J43: 38108 | K43: =VLOOKUP(J43,A:G,2,0) -> 0.090233695 | L43: =VLOOKUP(J43,Total!A:P,2,0) -> 0.088791304 | N43: =J43 -> 38108 | O43: =VLOOKUP(J43,A:G,3,0) -> 0.15755851 | P43: =VLOOKUP(J43,Total!A:P,11,0) -> 0.14149724 | R43: =N43 -> 38108 | S43: =-VLOOKUP(J43,A:G,5,0) -> 0.077462396 | T43: =VLOOKUP(J43,Total!A:P,8,0) -> 0.068711333 | V43: =R43 -> 38108 | W43: =VLOOKUP(J43,A:G,4,0) -> 0.15755851 | X43: =VLOOKUP(J43,Total!A:P,12,0)+VLOOKUP(J43,Total!A:P,13,0) -> 0.14958184 | Z43: =V43 -> 38108 | AA43: =VLOOKUP(J43,A:G,7,0) -> 0.11596033 | AB43: =VLOOKUP(J43,Total!A:P,16,0) -> 0.07842801 | AD43: =Z43 -> 38108 | AE43: =AA43+O43+W43-K43-S43 -> 0.26338126 | AF43: =AB43+P43+X43-L43-T43 -> 0.21200445
A44: 38139 | B44: 0.090645353 | C44: 0.15595011 | D44: 0.15595011 | E44: -0.076800637 | F44: 0.73188296 | G44: 0.11835581 | J44: 38139 | K44: =VLOOKUP(J44,A:G,2,0) -> 0.090645353 | L44: =VLOOKUP(J44,Total!A:P,2,0) -> 0.087070609 | N44: =J44 -> 38139 | O44: =VLOOKUP(J44,A:G,3,0) -> 0.15595011 | P44: =VLOOKUP(J44,Total!A:P,11,0) -> 0.14501538 | R44: =N44 -> 38139 | S44: =-VLOOKUP(J44,A:G,5,0) -> 0.076800637 | T44: =VLOOKUP(J44,Total!A:P,8,0) -> 0.065361633 | V44: =R44 -> 38139 | W44: =VLOOKUP(J44,A:G,4,0) -> 0.15595011 | X44: =VLOOKUP(J44,Total!A:P,12,0)+VLOOKUP(J44,Total!A:P,13,0) -> 0.16269749 | Z44: =V44 -> 38139 | AA44: =VLOOKUP(J44,A:G,7,0) -> 0.11835581 | AB44: =VLOOKUP(J44,Total!A:P,16,0) -> 0.07941364 | AD44: =Z44 -> 38139 | AE44: =AA44+O44+W44-K44-S44 -> 0.26281003 | AF44: =AB44+P44+X44-L44-T44 -> 0.23469426
A45: 38169 | B45: 0.085457894 | C45: 0.12836352 | D45: 0.12836352 | E45: -0.076938935 | F45: 0.76472439 | G45: 0.11814033 | J45: 38169 | K45: =VLOOKUP(J45,A:G,2,0) -> 0.085457894 | L45: =VLOOKUP(J45,Total!A:P,2,0) -> 0.087441521 | N45: =J45 -> 38169 | O45: =VLOOKUP(J45,A:G,3,0) -> 0.12836352 | P45: =VLOOKUP(J45,Total!A:P,11,0) -> 0.16887105 | R45: =N45 -> 38169 | S45: =-VLOOKUP(J45,A:G,5,0) -> 0.076938935 | T45: =VLOOKUP(J45,Total!A:P,8,0) -> 0.071414218 | V45: =R45 -> 38169 | W45: =VLOOKUP(J45,A:G,4,0) -> 0.12836352 | X45: =VLOOKUP(J45,Total!A:P,12,0)+VLOOKUP(J45,Total!A:P,13,0) -> 0.12730289 | Z45: =V45 -> 38169 | AA45: =VLOOKUP(J45,A:G,7,0) -> 0.11814033 | AB45: =VLOOKUP(J45,Total!A:P,16,0) -> 0.087241837 | AD45: =Z45 -> 38169 | AE45: =AA45+O45+W45-K45-S45 -> 0.21247054 | AF45: =AB45+P45+X45-L45-T45 -> 0.22456004
A46: 38200 | B46: 0.091238331 | C46: 0.14740192 | D46: 0.14740192 | E46: -0.077380772 | F46: 0.73743988 | G46: 0.11972959 | J46: 38200 | K46: =VLOOKUP(J46,A:G,2,0) -> 0.091238331 | L46: =VLOOKUP(J46,Total!A:P,2,0) -> 0.087469715 | N46: =J46 -> 38200 | O46: =VLOOKUP(J46,A:G,3,0) -> 0.14740192 | P46: =VLOOKUP(J46,Total!A:P,11,0) -> 0.16018615 | R46: =N46 -> 38200 | S46: =-VLOOKUP(J46,A:G,5,0) -> 0.077380772 | T46: =VLOOKUP(J46,Total!A:P,8,0) -> 0.065515033 | V46: =R46 -> 38200 | W46: =VLOOKUP(J46,A:G,4,0) -> 0.14740192 | X46: =VLOOKUP(J46,Total!A:P,12,0)+VLOOKUP(J46,Total!A:P,13,0) -> 0.14072519 | Z46: =V46 -> 38200 | AA46: =VLOOKUP(J46,A:G,7,0) -> 0.11972959 | AB46: =VLOOKUP(J46,Total!A:P,16,0) -> 0.080920836 | AD46: =Z46 -> 38200 | AE46: =AA46+O46+W46-K46-S46 -> 0.24591432 | AF46: =AB46+P46+X46-L46-T46 -> 0.22884743
A47: 38231 | B47: 0.087752971 | C47: 0.15879026 | D47: 0.15879026 | E47: -0.081175101 | F47: 0.73736847 | G47: 0.12761567 | J47: 38231 | K47: =VLOOKUP(J47,A:G,2,0) -> 0.087752971 | L47: =VLOOKUP(J47,Total!A:P,2,0) -> 0.090837395 | N47: =J47 -> 38231 | O47: =VLOOKUP(J47,A:G,3,0) -> 0.15879026 | P47: =VLOOKUP(J47,Total!A:P,11,0) -> 0.14284928 | R47: =N47 -> 38231 | S47: =-VLOOKUP(J47,A:G,5,0) -> 0.081175101 | T47: =VLOOKUP(J47,Total!A:P,8,0) -> 0.065195866 | V47: =R47 -> 38231 | W47: =VLOOKUP(J47,A:G,4,0) -> 0.15879026 | X47: =VLOOKUP(J47,Total!A:P,12,0)+VLOOKUP(J47,Total!A:P,13,0) -> 0.16153641 | Z47: =V47 -> 38231 | AA47: =VLOOKUP(J47,A:G,7,0) -> 0.12761567 | AB47: =VLOOKUP(J47,Total!A:P,16,0) -> 0.070586303 | AD47: =Z47 -> 38231 | AE47: =AA47+O47+W47-K47-S47 -> 0.27626812 | AF47: =AB47+P47+X47-L47-T47 -> 0.21893873
A48: 38261 | B48: 0.088020713 | C48: 0.14616576 | D48: 0.14616576 | E48: -0.080090983 | F48: 0.67308226 | G48: 0.11347599 | J48: 38261 | K48: =VLOOKUP(J48,A:G,2,0) -> 0.088020713 | L48: =VLOOKUP(J48,Total!A:P,2,0) -> 0.089777394 | N48: =J48 -> 38261 | O48: =VLOOKUP(J48,A:G,3,0) -> 0.14616576 | P48: =VLOOKUP(J48,Total!A:P,11,0) -> 0.15753269 | R48: =N48 -> 38261 | S48: =-VLOOKUP(J48,A:G,5,0) -> 0.080090983 | T48: =VLOOKUP(J48,Total!A:P,8,0) -> 0.071639978 | V48: =R48 -> 38261 | W48: =VLOOKUP(J48,A:G,4,0) -> 0.14616576 | X48: =VLOOKUP(J48,Total!A:P,12,0)+VLOOKUP(J48,Total!A:P,13,0) -> 0.15080175 | Z48: =V48 -> 38261 | AA48: =VLOOKUP(J48,A:G,7,0) -> 0.11347599 | AB48: =VLOOKUP(J48,Total!A:P,16,0) -> 0.085221352 | AD48: =Z48 -> 38261 | AE48: =AA48+O48+W48-K48-S48 -> 0.23769582 | AF48: =AB48+P48+X48-L48-T48 -> 0.23213842
... A164: 41791 | B164: 0.15713851 | C164: 0.056635312 | D164: 0.056635312 | E164: -0.15832221 | F164: 0.67641346 | G164: 0.55945876 | J164: 41791 | K164: =VLOOKUP(J164,A:G,2,0) -> 0.15713851 | L164: =VLOOKUP(J164,Total!A:P,2,0) -> 0.15109386 | N164: =J164 -> 41791 | O164: =VLOOKUP(J164,A:G,3,0) -> 0.056635312 | P164: =VLOOKUP(J164,Total!A:P,11,0) -> 0.068409344 | R164: =N164 -> 41791 | S164: =-VLOOKUP(J164,A:G,5,0) -> 0.15832221 | T164: =VLOOKUP(J164,Total!A:P,8,0) -> 0.1408829 | V164: =R164 -> 41791 | W164: =VLOOKUP(J164,A:G,4,0) -> 0.056635312 | X164: =VLOOKUP(J164,Total!A:P,12,0)+VLOOKUP(J164,Total!A:P,13,0) -> 0.0238118 | Z164: =V164 -> 41791 | AA164: =VLOOKUP(J164,A:G,7,0) -> 0.55945876 | AB164: =VLOOKUP(J164,Total!A:P,16,0) -> 0.44850285 | AD164: =Z164 -> 41791 | AE164: =AA164+O164+W164-K164-S164 -> 0.35726867 | AF164: =AB164+P164+X164-L164-T164 -> 0.24874723
A165: 41821 | B165: 0.15936983 | C165: 0.042308069 | D165: 0.042308069 | E165: -0.15071274 | F165: 0.64500453 | G165: 0.5988897
A166: 41852 | B166: 0.1747027 | C166: 0.030881373 | D166: 0.030881373 | E166: -0.12245575 | F166: 0.65771784 | G166: 0.59591163
A167: 41883 | B167: 0.16475491 | C167: 0.041673738 | D167: 0.041673738 | E167: -0.12239302 | F167: 0.49708521 | G167: 0.73304407

Sheet FC
B1: Interest | C1: ForeclosureCostsPct | D1: PropertyPreserveAndRepairCostPct | E1: AssetRecoveryCostPct | F1: MiscHoldingExpenseAndCreditsPct | G1: AssociatedTaxforHoldingPropertyPct | H1: Expenses | I1: NetSaleProceedsPct | J1: CreditEnhancementProceedsPct | K1: RepurchaseMakeWholeProceedsPct | L1: OtherForecloseProceedsPct | M1: Proceeds | N1: Severity | P1: lossDate | Q1: interest | R1: miRecoveries | S1: nonMIRecoveries | T1: expenses | U1: netSaleProceeds | V1: ActuralSeverity | Z1: Interest | AD1: MI | AH1: expenses | AL1: Non-MI | AP1: Total
A2: 36770 | B2: 0.044129954 | C2: 0.0046020586 | D2: 0 | E2: 0 | F2: 0 | G2: 0 | H2: 0.0046020586 | I2: 1.0526067 | J2: 0 | K2: 0 | L2: 0 | M2: 1.0526067 | N2: =B2+H2+1-M2 -> -0.0038746715 | P2: 36434 | Q2: 0.037872361 | R2: 0.024505321 | S2: 0.024505321 | T2: -0.011084216 | Z2: FHL | AA2: FNMA | AD2: FHL | AE2: FNMA | AH2: FHL | AI2: FNMA | AL2: FHL | AM2: FNMA | AP2: FHL | AQ2: FNMA
A3: 36831 | B3: 0.0275 | C3: 0 | D3: 0 | E3: 0.0046511628 | F3: -0.0013162791 | G3: 0 | H3: 0.0033348837 | I3: 1.014986 | J3: 0.0090837209 | K3: 0 | L3: 0.00075348837 | M3: 1.0248233 | N3: =B3+H3+1-M3 -> 0.0060116279 | P3: 36465 | Q3: 0.0325 | R3: 0.058627103 | S3: 0.058627103 | T3: -0.01735443 | Y3: 36557 | Z3: =VLOOKUP(Y3,P:V,2,0) -> 0.028507229 | AA3: =VLOOKUP(Y3,A:N,2,0) -> #N/A | AC3: 36557 | AD3: =VLOOKUP(Y3,P:V,3,0) -> 0.031453293 | AE3: =VLOOKUP(Y3,A:N,10,0) -> #N/A | AG3: 36557 | AH3: =-VLOOKUP(Y3,P:V,5,0) -> 0.0045568616 | AI3: =VLOOKUP(Y3,A:N,8,0) -> #N/A | AK3: 36557 | AL3: =VLOOKUP(Y3,P:V,4,0) -> 0.031453293 | AM3: =VLOOKUP(Y3,A:N,11,0)+VLOOKUP(Y3,A:N,12,0) -> #N/A | AO3: 36557 | AP3: =VLOOKUP(Y3,P:V,7,0) -> 5.6932038e-08 | AQ3: =VLOOKUP(Y3,A:N,14,0) -> #N/A
A4: 36861 | B4: 0.055 | C4: 0.0096361134 | D4: 0.0023448826 | E4: 0.0071273028 | F4: 0.0027725208 | G4: 0.001482479 | H4: 0.023363299 | I4: 0.98405957 | J4: 0.087181168 | K4: 0 | L4: 0.0038344889 | M4: 1.0750752 | N4: =B4+H4+1-M4 -> 0.0032880682 | P4: 36495 | Q4: 0.02731786 | R4: 0.11839948 | S4: 0.11839948 | T4: -0.021279083 | Y4: 36586 | Z4: =VLOOKUP(Y4,P:V,2,0) -> 0.04455445 | AA4: =VLOOKUP(Y4,A:N,2,0) -> #N/A | AC4: 36586 | AD4: =VLOOKUP(Y4,P:V,3,0) -> 0.084914844 | AE4: =VLOOKUP(Y4,A:N,10,0) -> #N/A | AG4: 36586 | AH4: =-VLOOKUP(Y4,P:V,5,0) -> 0.015703286 | AI4: =VLOOKUP(Y4,A:N,8,0) -> #N/A | AK4: 36586 | AL4: =VLOOKUP(Y4,P:V,4,0) -> 0.084914844 | AM4: =VLOOKUP(Y4,A:N,11,0)+VLOOKUP(Y4,A:N,12,0) -> #N/A | AO4: 36586 | AP4: =VLOOKUP(Y4,P:V,7,0) -> 0.0041902826 | AQ4: =VLOOKUP(Y4,A:N,14,0) -> #N/A
A5: 36892 | B5: 0.047935436 | C5: 0.0033171601 | D5: 0.00067736966 | E5: 0.005575059 | F5: -0.003448174 | G5: 0.0049144145 | H5: 0.011035829 | I5: 0.96171997 | J5: 0.1052822 | K5: 0 | L5: 0 | M5: 1.0670022 | N5: =B5+H5+1-M5 -> -0.0080309083 | P5: 36526 | Q5: 0.028735889 | R5: 0.10319416 | S5: 0.10319416 | T5: -0.013510922 | U5: 0.93758211 | V5: 6.1266478e-09 | Y5: 36617 | Z5: =VLOOKUP(Y5,P:V,2,0) -> 0.043194315 | AA5: =VLOOKUP(Y5,A:N,2,0) -> #N/A | AC5: 36617 | AD5: =VLOOKUP(Y5,P:V,3,0) -> 0.044691468 | AE5: =VLOOKUP(Y5,A:N,10,0) -> #N/A | AG5: 36617 | AH5: =-VLOOKUP(Y5,P:V,5,0) -> 0.019638595 | AI5: =VLOOKUP(Y5,A:N,8,0) -> #N/A | AK5: 36617 | AL5: =VLOOKUP(Y5,P:V,4,0) -> 0.044691468 | AM5: =VLOOKUP(Y5,A:N,11,0)+VLOOKUP(Y5,A:N,12,0) -> #N/A | AO5: 36617 | AP5: =VLOOKUP(Y5,P:V,7,0) -> 0.067339586 | AQ5: =VLOOKUP(Y5,A:N,14,0) -> #N/A
A6: 36923 | B6: 0.051101429 | C6: 0.0020433162 | D6: 0 | E6: 0.00012401079 | F6: -0.0013564873 | G6: 0 | H6: 0.00081083978 | I6: 0.73311554 | J6: 0 | K6: 0 | L6: 0.32021303 | M6: 1.0533286 | N6: =B6+H6+1-M6 -> -0.001416301 | P6: 36557 | Q6: 0.028507229 | R6: 0.031453293 | S6: 0.031453293 | T6: -0.0045568616 | U6: 0.9809073 | V6: 5.6932038e-08 | Y6: 36647 | Z6: =VLOOKUP(Y6,P:V,2,0) -> 0.044340743 | AA6: =VLOOKUP(Y6,A:N,2,0) -> #N/A | AC6: 36647 | AD6: =VLOOKUP(Y6,P:V,3,0) -> 0.073383258 | AE6: =VLOOKUP(Y6,A:N,10,0) -> #N/A | AG6: 36647 | AH6: =-VLOOKUP(Y6,P:V,5,0) -> 0.013328806 | AI6: =VLOOKUP(Y6,A:N,8,0) -> #N/A | AK6: 36647 | AL6: =VLOOKUP(Y6,P:V,4,0) -> 0.073383258 | AM6: =VLOOKUP(Y6,A:N,11,0)+VLOOKUP(Y6,A:N,12,0) -> #N/A | AO6: 36647 | AP6: =VLOOKUP(Y6,P:V,7,0) -> 0.0051575716 | AQ6: =VLOOKUP(Y6,A:N,14,0) -> #N/A
A7: 36951 | B7: 0.054557557 | C7: 0.0054913195 | D7: 0.00014411268 | E7: 0.0025063074 | F7: 0.00027193435 | G7: 0.0016290998 | H7: 0.010042774 | I7: 1.0470813 | J7: 0.034939178 | K7: 0 | L7: 0.0018070476 | M7: 1.0838276 | N7: =B7+H7+1-M7 -> -0.019227244 | P7: 36586 | Q7: 0.04455445 | R7: 0.084914844 | S7: 0.084914844 | T7: -0.015703286 | U7: 0.96907232 | V7: 0.0041902826 | Y7: 36678 | Z7: =VLOOKUP(Y7,P:V,2,0) -> 0.045407847 | AA7: =VLOOKUP(Y7,A:N,2,0) -> #N/A | AC7: 36678 | AD7: =VLOOKUP(Y7,P:V,3,0) -> 0.080169137 | AE7: =VLOOKUP(Y7,A:N,10,0) -> #N/A | AG7: 36678 | AH7: =-VLOOKUP(Y7,P:V,5,0) -> 0.015019502 | AI7: =VLOOKUP(Y7,A:N,8,0) -> #N/A | AK7: 36678 | AL7: =VLOOKUP(Y7,P:V,4,0) -> 0.080169137 | AM7: =VLOOKUP(Y7,A:N,11,0)+VLOOKUP(Y7,A:N,12,0) -> #N/A | AO7: 36678 | AP7: =VLOOKUP(Y7,P:V,7,0) -> 0.072817607 | AQ7: =VLOOKUP(Y7,A:N,14,0) -> #N/A
A8: 36982 | B8: 0.040534155 | C8: 0.0072808934 | D8: 0 | E8: 0.0052900654 | F8: -0.0013048828 | G8: 0.002562155 | H8: 0.013828231 | I8: 0.91620848 | J8: 0.13268366 | K8: 0 | L8: 0.00016311035 | M8: 1.0490552 | N8: =B8+H8+1-M8 -> 0.0053071415 | P8: 36617 | Q8: 0.043194315 | R8: 0.044691468 | S8: 0.044691468 | T8: -0.019638595 | U8: 0.9450777 | V8: 0.067339586 | Y8: 36708 | Z8: =VLOOKUP(Y8,P:V,2,0) -> 0.041810539 | AA8: =VLOOKUP(Y8,A:N,2,0) -> #N/A | AC8: 36708 | AD8: =VLOOKUP(Y8,P:V,3,0) -> 0.0067870463 | AE8: =VLOOKUP(Y8,A:N,10,0) -> #N/A | AG8: 36708 | AH8: =-VLOOKUP(Y8,P:V,5,0) -> 0.0069777018 | AI8: =VLOOKUP(Y8,A:N,8,0) -> #N/A | AK8: 36708 | AL8: =VLOOKUP(Y8,P:V,4,0) -> 0.0067870463 | AM8: =VLOOKUP(Y8,A:N,11,0)+VLOOKUP(Y8,A:N,12,0) -> #N/A | AO8: 36708 | AP8: =VLOOKUP(Y8,P:V,7,0) -> 0.007480477 | AQ8: =VLOOKUP(Y8,A:N,14,0) -> #N/A
A9: 37012 | B9: 0.051094253 | C9: 0.012129221 | D9: 0.00011807276 | E9: 0.0044080498 | F9: -0.00014641022 | G9: 0.0076841753 | H9: 0.024193109 | I9: 0.99565407 | J9: 0.065464262 | K9: 0.0076715809 | L9: 0.0020961851 | M9: 1.0708861 | N9: =B9+H9+1-M9 -> 0.0044012618 | P9: 36647 | Q9: 0.044340743 | R9: 0.073383258 | S9: 0.073383258 | T9: -0.013328806 | U9: 0.97734778 | V9: 0.0051575716 | Y9: 36739 | Z9: =VLOOKUP(Y9,P:V,2,0) -> 0.037035506 | AA9: =VLOOKUP(Y9,A:N,2,0) -> #N/A | AC9: 36739 | AD9: =VLOOKUP(Y9,P:V,3,0) -> 0.083448407 | AE9: =VLOOKUP(Y9,A:N,10,0) -> #N/A | AG9: 36739 | AH9: =-VLOOKUP(Y9,P:V,5,0) -> 0.015103354 | AI9: =VLOOKUP(Y9,A:N,8,0) -> #N/A | AK9: 36739 | AL9: =VLOOKUP(Y9,P:V,4,0) -> 0.083448407 | AM9: =VLOOKUP(Y9,A:N,11,0)+VLOOKUP(Y9,A:N,12,0) -> #N/A | AO9: 36739 | AP9: =VLOOKUP(Y9,P:V,7,0) -> 0.064310738 | AQ9: =VLOOKUP(Y9,A:N,14,0) -> #N/A
A10: 37043 | B10: 0.053189327 | C10: 0.0060913243 | D10: 0 | E10: 0.0045008981 | F10: 0.00037330498 | G10: 0.002991341 | H10: 0.013956868 | I10: 0.88925248 | J10: 0.042008654 | K10: 0 | L10: 0.13418884 | M10: 1.06545 | N10: =B10+H10+1-M10 -> 0.0016962189 | P10: 36678 | Q10: 0.045407847 | R10: 0.080169137 | S10: 0.080169137 | T10: -0.015019502 | U10: 0.90458556 | V10: 0.072817607 | Y10: 36770 | Z10: =VLOOKUP(Y10,P:V,2,0) -> 0.035177554 | AA10: =VLOOKUP(Y10,A:N,2,0) -> 0.044129954 | AC10: 36770 | AD10: =VLOOKUP(Y10,P:V,3,0) -> 0.10003842 | AE10: =VLOOKUP(Y10,A:N,10,0) -> 0 | AG10: 36770 | AH10: =-VLOOKUP(Y10,P:V,5,0) -> 0.011246553 | AI10: =VLOOKUP(Y10,A:N,8,0) -> 0.0046020586 | AK10: 36770 | AL10: =VLOOKUP(Y10,P:V,4,0) -> 0.10003842 | AM10: =VLOOKUP(Y10,A:N,11,0)+VLOOKUP(Y10,A:N,12,0) -> 0 | AO10: 36770 | AP10: =VLOOKUP(Y10,P:V,7,0) -> 0.01572328 | AQ10: =VLOOKUP(Y10,A:N,14,0) -> -0.0038746715
A11: 37073 | B11: 0.049343684 | C11: 0.0090052601 | D11: 0.0006271992 | E11: 0.0051616394 | F11: 0.00051016203 | G11: 0.0015911053 | H11: 0.016895366 | I11: 0.9779284 | J11: 0.067728511 | K11: 0.008696162 | L11: 0.00066621159 | M11: 1.0550193 | N11: =B11+H11+1-M11 -> 0.011219767 | P11: 36708 | Q11: 0.041810539 | R11: 0.0067870463 | S11: 0.0067870463 | T11: -0.0069777018 | U11: 1.0315424 | V11: 0.007480477 | Y11: 36800 | Z11: =VLOOKUP(Y11,P:V,2,0) -> 0.046182747 | AA11: =VLOOKUP(Y11,A:N,2,0) -> #N/A | AC11: 36800 | AD11: =VLOOKUP(Y11,P:V,3,0) -> 0.074782627 | AE11: =VLOOKUP(Y11,A:N,10,0) -> #N/A | AG11: 36800 | AH11: =-VLOOKUP(Y11,P:V,5,0) -> 0.010006783 | AI11: =VLOOKUP(Y11,A:N,8,0) -> #N/A | AK11: 36800 | AL11: =VLOOKUP(Y11,P:V,4,0) -> 0.074782627 | AM11: =VLOOKUP(Y11,A:N,11,0)+VLOOKUP(Y11,A:N,12,0) -> #N/A | AO11: 36800 | AP11: =VLOOKUP(Y11,P:V,7,0) -> -0.0015436133 | AQ11: =VLOOKUP(Y11,A:N,14,0) -> #N/A
A12: 37104 | B12: 0.052684828 | C12: 0.0088165347 | D12: 0.00059504171 | E12: 0.0048061061 | F12: 0.0013674516 | G12: 0.0044281021 | H12: 0.020013236 | I12: 0.93753132 | J12: 0.090020275 | K12: 0.0078625608 | L12: 0.0089828412 | M12: 1.044397 | N12: =B12+H12+1-M12 -> 0.028301068 | P12: 36739 | Q12: 0.037035506 | R12: 0.083448407 | S12: 0.083448407 | T12: -0.015103354 | U12: 0.897679 | V12: 0.064310738 | Y12: 36831 | Z12: =VLOOKUP(Y12,P:V,2,0) -> 0.04344528 | AA12: =VLOOKUP(Y12,A:N,2,0) -> 0.0275 | AC12: 36831 | AD12: =VLOOKUP(Y12,P:V,3,0) -> 0.10252697 | AE12: =VLOOKUP(Y12,A:N,10,0) -> 0.0090837209 | AG12: 36831 | AH12: =-VLOOKUP(Y12,P:V,5,0) -> 0.033513045 | AI12: =VLOOKUP(Y12,A:N,8,0) -> 0.0033348837 | AK12: 36831 | AL12: =VLOOKUP(Y12,P:V,4,0) -> 0.10252697 | AM12: =VLOOKUP(Y12,A:N,11,0)+VLOOKUP(Y12,A:N,12,0) -> 0.00075348837 | AO12: 36831 | AP12: =VLOOKUP(Y12,P:V,7,0) -> 0.030278267 | AQ12: =VLOOKUP(Y12,A:N,14,0) -> 0.0060116279
A13: 37135 | B13: 0.043909285 | C13: 0.0038946081 | D13: 0.00022456244 | E13: 0.0036963542 | F13: 0.0016461649 | G13: 0.00096402121 | H13: 0.010425711 | I13: 0.94124644 | J13: 0.085172119 | K13: 0.0014610653 | L13: 0.00156536 | M13: 1.029445 | N13: =B13+H13+1-M13 -> 0.024890011 | P13: 36770 | Q13: 0.035177554 | R13: 0.10003842 | S13: 0.10003842 | T13: -0.011246553 | U13: 0.92793581 | V13: 0.01572328 | Y13: 36861 | Z13: =VLOOKUP(Y13,P:V,2,0) -> 0.041650472 | AA13: =VLOOKUP(Y13,A:N,2,0) -> 0.055 | AC13: 36861 | AD13: =VLOOKUP(Y13,P:V,3,0) -> 0.10886305 | AE13: =VLOOKUP(Y13,A:N,10,0) -> 0.087181168 | AG13: 36861 | AH13: =-VLOOKUP(Y13,P:V,5,0) -> 0.023715566 | AI13: =VLOOKUP(Y13,A:N,8,0) -> 0.023363299 | AK13: 36861 | AL13: =VLOOKUP(Y13,P:V,4,0) -> 0.10886305 | AM13: =VLOOKUP(Y13,A:N,11,0)+VLOOKUP(Y13,A:N,12,0) -> 0.0038344889 | AO13: 36861 | AP13: =VLOOKUP(Y13,P:V,7,0) -> 0.012636552 | AQ13: =VLOOKUP(Y13,A:N,14,0) -> 0.0032880682
A14: 37165 | B14: 0.053365177 | C14: 0.0065443844 | D14: 6.2819674e-05 | E14: 0.002227648 | F14: -0.0016417766 | G14: 0.0040391714 | H14: 0.011232247 | I14: 0.92146438 | J14: 0.045946577 | K14: 0.060687815 | L14: 0.037139793 | M14: 1.0652386 | N14: =B14+H14+1-M14 -> -0.00064113714 | P14: 36800 | Q14: 0.046182747 | R14: 0.074782627 | S14: 0.074782627 | T14: -0.010006783 | U14: 0.9648617 | V14: -0.0015436133 | Y14: 36892 | Z14: =VLOOKUP(Y14,P:V,2,0) -> 0.036827345 | AA14: =VLOOKUP(Y14,A:N,2,0) -> 0.047935436 | AC14: 36892 | AD14: =VLOOKUP(Y14,P:V,3,0) -> 0.042253928 | AE14: =VLOOKUP(Y14,A:N,10,0) -> 0.1052822 | AG14: 36892 | AH14: =-VLOOKUP(Y14,P:V,5,0) -> 0.010461183 | AI14: =VLOOKUP(Y14,A:N,8,0) -> 0.011035829 | AK14: 36892 | AL14: =VLOOKUP(Y14,P:V,4,0) -> 0.042253928 | AM14: =VLOOKUP(Y14,A:N,11,0)+VLOOKUP(Y14,A:N,12,0) -> 0 | AO14: 36892 | AP14: =VLOOKUP(Y14,P:V,7,0) -> 0.033547024 | AQ14: =VLOOKUP(Y14,A:N,14,0) -> -0.0080309083
A15: 37196 | B15: 0.058115063 | C15: 0.0090273558 | D15: 0.00021686473 | E15: 0.0036650139 | F15: -0.0033217893 | G15: 0.0050532373 | H15: 0.014640682 | I15: 0.98597433 | J15: 0.066655832 | K15: 0.0061057541 | L15: 0.0097808884 | M15: 1.0685168 | N15: =B15+H15+1-M15 -> 0.0042389397 | P15: 36831 | Q15: 0.04344528 | R15: 0.10252697 | S15: 0.10252697 | T15: -0.033513045 | U15: 0.92172157 | V15: 0.030278267 | Y15: 36923 | Z15: =VLOOKUP(Y15,P:V,2,0) -> 0.042129878 | AA15: =VLOOKUP(Y15,A:N,2,0) -> 0.051101429 | AC15: 36923 | AD15: =VLOOKUP(Y15,P:V,3,0) -> 0.055779109 | AE15: =VLOOKUP(Y15,A:N,10,0) -> 0 | AG15: 36923 | AH15: =-VLOOKUP(Y15,P:V,5,0) -> 0.023132487 | AI15: =VLOOKUP(Y15,A:N,8,0) -> 0.00081083978 | AK15: 36923 | AL15: =VLOOKUP(Y15,P:V,4,0) -> 0.055779109 | AM15: =VLOOKUP(Y15,A:N,11,0)+VLOOKUP(Y15,A:N,12,0) -> 0.32021303 | AO15: 36923 | AP15: =VLOOKUP(Y15,P:V,7,0) -> 0.036254786 | AQ15: =VLOOKUP(Y15,A:N,14,0) -> -0.001416301
A16: 37226 | B16: 0.049023505 | C16: 0.0080321208 | D16: 0.00016519895 | E16: 0.0041916151 | F16: -0.0015972519 | G16: 0.0066474084 | H16: 0.017439091 | I16: 0.94590206 | J16: 0.092434483 | K16: 0.0078294439 | L16: 0.0023739336 | M16: 1.0485399 | N16: =B16+H16+1-M16 -> 0.017922678 | P16: 36861 | Q16: 0.041650472 | R16: 0.10886305 | S16: 0.10886305 | T16: -0.023715566 | U16: 0.94026127 | V16: 0.012636552 | Y16: 36951 | Z16: =VLOOKUP(Y16,P:V,2,0) -> 0.05267806 | AA16: =VLOOKUP(Y16,A:N,2,0) -> 0.054557557 | AC16: 36951 | AD16: =VLOOKUP(Y16,P:V,3,0) -> 0.081185882 | AE16: =VLOOKUP(Y16,A:N,10,0) -> 0.034939178 | AG16: 36951 | AH16: =-VLOOKUP(Y16,P:V,5,0) -> 0.016607764 | AI16: =VLOOKUP(Y16,A:N,8,0) -> 0.010042774 | AK16: 36951 | AL16: =VLOOKUP(Y16,P:V,4,0) -> 0.081185882 | AM16: =VLOOKUP(Y16,A:N,11,0)+VLOOKUP(Y16,A:N,12,0) -> 0.0018070476 | AO16: 36951 | AP16: =VLOOKUP(Y16,P:V,7,0) -> 0.01752654 | AQ16: =VLOOKUP(Y16,A:N,14,0) -> -0.019227244
... A31: 37681 | B31: 0.05739125 | C31: 0.0090062906 | D31: 0.00037050241 | E31: 0.0035886236 | F31: 0.0012815368 | G31: 0.0066657446 | H31: 0.020912698 | I31: 0.98339747 | J31: 0.056992715 | K31: 0.021795174 | L31: 0.0033267931 | M31: 1.0655122 | N31: =B31+H31+1-M31 -> 0.012791793 | P31: 37316 | Q31: 0.051418156 | R31: 0.059203934 | S31: 0.059203934 | T31: -0.015676473 | U31: 0.99287948 | V31: 0.0035551744 | Y31: 37408 | Z31: =VLOOKUP(Y31,P:V,2,0) -> 0.055774215 | AA31: =VLOOKUP(Y31,A:N,2,0) -> 0.068733294 | AC31: 37408 | AD31: =VLOOKUP(Y31,P:V,3,0) -> 0.058322281 | AE31: =VLOOKUP(Y31,A:N,10,0) -> 0.055312859 | AG31: 37408 | AH31: =-VLOOKUP(Y31,P:V,5,0) -> 0.01436111 | AI31: =VLOOKUP(Y31,A:N,8,0) -> 0.025800588 | AK31: 37408 | AL31: =VLOOKUP(Y31,P:V,4,0) -> 0.058322281 | AM31: =VLOOKUP(Y31,A:N,11,0)+VLOOKUP(Y31,A:N,12,0) -> 0.0028313854 | AO31: 37408 | AP31: =VLOOKUP(Y31,P:V,7,0) -> 0.047092549 | AQ31: =VLOOKUP(Y31,A:N,14,0) -> 0.027852893
A32: 37712 | B32: 0.060843517 | C32: 0.012785382 | D32: 0.00022274357 | E32: 0.0031141089 | F32: 0.0017637519 | G32: 0.0071899936 | H32: 0.02507598 | I32: 1.0063281 | J32: 0.064250312 | K32: 0.005574379 | L32: 0.012508462 | M32: 1.0886612 | N32: =B32+H32+1-M32 -> -0.0027417166 | P32: 37347 | Q32: 0.050753805 | R32: 0.053559872 | S32: 0.053559872 | T32: -0.013986064 | U32: 0.97774309 | V32: 0.026960012 | Y32: 37438 | Z32: =VLOOKUP(Y32,P:V,2,0) -> 0.064228838 | AA32: =VLOOKUP(Y32,A:N,2,0) -> 0.05258209 | AC32: 37438 | AD32: =VLOOKUP(Y32,P:V,3,0) -> 0.061502033 | AE32: =VLOOKUP(Y32,A:N,10,0) -> 0.053505671 | AG32: 37438 | AH32: =-VLOOKUP(Y32,P:V,5,0) -> 0.0093406287 | AI32: =VLOOKUP(Y32,A:N,8,0) -> 0.017857582 | AK32: 37438 | AL32: =VLOOKUP(Y32,P:V,4,0) -> 0.061502033 | AM32: =VLOOKUP(Y32,A:N,11,0)+VLOOKUP(Y32,A:N,12,0) -> 0.02687012 | AO32: 37438 | AP32: =VLOOKUP(Y32,P:V,7,0) -> 0.03460423 | AQ32: =VLOOKUP(Y32,A:N,14,0) -> 0.0052774186 | BJ32: 1
A33: 37742 | B33: 0.060312239 | C33: 0.010782701 | D33: 0.00043997329 | E33: 0.0040447345 | F33: -0.0014779076 | G33: 0.0063922313 | H33: 0.020181732 | I33: 0.9896175 | J33: 0.059840087 | K33: 6.9074056e-05 | L33: 0.018447149 | M33: 1.0679738 | N33: =B33+H33+1-M33 -> 0.012520157 | P33: 37377 | Q33: 0.051384537 | R33: 0.062957393 | S33: 0.062957393 | T33: -0.015006765 | U33: 0.95999704 | V33: 0.024979744 | Y33: 37469 | Z33: =VLOOKUP(Y33,P:V,2,0) -> 0.059208263 | AA33: =VLOOKUP(Y33,A:N,2,0) -> 0.054235463 | AC33: 37469 | AD33: =VLOOKUP(Y33,P:V,3,0) -> 0.076931178 | AE33: =VLOOKUP(Y33,A:N,10,0) -> 0.078988418 | AG33: 37469 | AH33: =-VLOOKUP(Y33,P:V,5,0) -> 0.016259689 | AI33: =VLOOKUP(Y33,A:N,8,0) -> 0.026381228 | AK33: 37469 | AL33: =VLOOKUP(Y33,P:V,4,0) -> 0.076931178 | AM33: =VLOOKUP(Y33,A:N,11,0)+VLOOKUP(Y33,A:N,12,0) -> 0.015698798 | AO33: 37469 | AP33: =VLOOKUP(Y33,P:V,7,0) -> 0.031921768 | AQ33: =VLOOKUP(Y33,A:N,14,0) -> 0.021477074
A34: 37773 | B34: 0.057111076 | C34: 0.01226596 | D34: 0.00064349319 | E34: 0.0025561364 | F34: -0.00031153289 | G34: 0.0057591405 | H34: 0.020913197 | I34: 1.0060679 | J34: 0.041715038 | K34: 0.013165609 | L34: 0.0073940555 | M34: 1.0683426 | N34: =B34+H34+1-M34 -> 0.0096816282 | P34: 37408 | Q34: 0.055774215 | R34: 0.058322281 | S34: 0.058322281 | T34: -0.01436111 | U34: 0.96015292 | V34: 0.047092549 | Y34: 37500 | Z34: =VLOOKUP(Y34,P:V,2,0) -> 0.052083544 | AA34: =VLOOKUP(Y34,A:N,2,0) -> 0.058796769 | AC34: 37500 | AD34: =VLOOKUP(Y34,P:V,3,0) -> 0.060093232 | AE34: =VLOOKUP(Y34,A:N,10,0) -> 0.045380459 | AG34: 37500 | AH34: =-VLOOKUP(Y34,P:V,5,0) -> 0.0170678 | AI34: =VLOOKUP(Y34,A:N,8,0) -> 0.020915833 | AK34: 37500 | AL34: =VLOOKUP(Y34,P:V,4,0) -> 0.060093232 | AM34: =VLOOKUP(Y34,A:N,11,0)+VLOOKUP(Y34,A:N,12,0) -> 0.0061055829 | AO34: 37500 | AP34: =VLOOKUP(Y34,P:V,7,0) -> 0.015626211 | AQ34: =VLOOKUP(Y34,A:N,14,0) -> 0.017394958
A35: 37803 | B35: 0.056170971 | C35: 0.0096002832 | D35: 0.00058399397 | E35: 0.0032333373 | F35: -0.00097411114 | G35: 0.0071477055 | H35: 0.019591209 | I35: 0.99395295 | J35: 0.050447231 | K35: 2.4751628e-05 | L35: 0.0024108217 | M35: 1.0468358 | N35: =B35+H35+1-M35 -> 0.028926423 | P35: 37438 | Q35: 0.064228838 | R35: 0.061502033 | S35: 0.061502033 | T35: -0.0093406287 | U35: 0.95924814 | V35: 0.03460423 | Y35: 37530 | Z35: =VLOOKUP(Y35,P:V,2,0) -> 0.051062549 | AA35: =VLOOKUP(Y35,A:N,2,0) -> 0.052794707 | AC35: 37530 | AD35: =VLOOKUP(Y35,P:V,3,0) -> 0.058583726 | AE35: =VLOOKUP(Y35,A:N,10,0) -> 0.039939859 | AG35: 37530 | AH35: =-VLOOKUP(Y35,P:V,5,0) -> 0.0069790739 | AI35: =VLOOKUP(Y35,A:N,8,0) -> 0.017322432 | AK35: 37530 | AL35: =VLOOKUP(Y35,P:V,4,0) -> 0.058583726 | AM35: =VLOOKUP(Y35,A:N,11,0)+VLOOKUP(Y35,A:N,12,0) -> 0.014893748 | AO35: 37530 | AP35: =VLOOKUP(Y35,P:V,7,0) -> 0.048170396 | AQ35: =VLOOKUP(Y35,A:N,14,0) -> 0.016157077
A36: 37834 | B36: 0.056027395 | C36: 0.013522402 | D36: 0.00022206481 | E36: 0.0027561142 | F36: 0.00095682138 | G36: 0.0046213988 | H36: 0.022078801 | I36: 0.88271868 | J36: 0.047716199 | K36: 0.11775353 | L36: 0.0048792092 | M36: 1.0530676 | N36: =B36+H36+1-M36 -> 0.025038581 | P36: 37469 | Q36: 0.059208263 | R36: 0.076931178 | S36: 0.076931178 | T36: -0.016259689 | U36: 0.96046006 | V36: 0.031921768 | Y36: 37561 | Z36: =VLOOKUP(Y36,P:V,2,0) -> 0.056778499 | AA36: =VLOOKUP(Y36,A:N,2,0) -> 0.053493761 | AC36: 37561 | AD36: =VLOOKUP(Y36,P:V,3,0) -> 0.05583369 | AE36: =VLOOKUP(Y36,A:N,10,0) -> 0.050064816 | AG36: 37561 | AH36: =-VLOOKUP(Y36,P:V,5,0) -> 0.017723485 | AI36: =VLOOKUP(Y36,A:N,8,0) -> 0.015470853 | AK36: 37561 | AL36: =VLOOKUP(Y36,P:V,4,0) -> 0.05583369 | AM36: =VLOOKUP(Y36,A:N,11,0)+VLOOKUP(Y36,A:N,12,0) -> 0.029882571 | AO36: 37561 | AP36: =VLOOKUP(Y36,P:V,7,0) -> 0.040475924 | AQ36: =VLOOKUP(Y36,A:N,14,0) -> 0.02220817
A37: 37865 | B37: 0.05687355 | C37: 0.012032461 | D37: 0.00048027375 | E37: 0.0032286874 | F37: 0.00044328379 | G37: 0.0047691053 | H37: 0.020953811 | I37: 0.94078143 | J37: 0.068135508 | K37: 0.041913687 | L37: 0.0073972339 | M37: 1.0582279 | N37: =B37+H37+1-M37 -> 0.019599501 | P37: 37500 | Q37: 0.052083544 | R37: 0.060093232 | S37: 0.060093232 | T37: -0.0170678 | U37: 0.97053146 | V37: 0.015626211 | Y37: 37591 | Z37: =VLOOKUP(Y37,P:V,2,0) -> 0.052193501 | AA37: =VLOOKUP(Y37,A:N,2,0) -> 0.061729303 | AC37: 37591 | AD37: =VLOOKUP(Y37,P:V,3,0) -> 0.070087657 | AE37: =VLOOKUP(Y37,A:N,10,0) -> 0.087192598 | AG37: 37591 | AH37: =-VLOOKUP(Y37,P:V,5,0) -> 0.014574144 | AI37: =VLOOKUP(Y37,A:N,8,0) -> 0.026978609 | AK37: 37591 | AL37: =VLOOKUP(Y37,P:V,4,0) -> 0.070087657 | AM37: =VLOOKUP(Y37,A:N,11,0)+VLOOKUP(Y37,A:N,12,0) -> 0.012160914 | AO37: 37591 | AP37: =VLOOKUP(Y37,P:V,7,0) -> 0.022538262 | AQ37: =VLOOKUP(Y37,A:N,14,0) -> -0.00037809558
A38: 37895 | B38: 0.064546724 | C38: 0.01818535 | D38: 0.00051873415 | E38: 0.0029879062 | F38: -0.0008371575 | G38: 0.0068415495 | H38: 0.027696382 | I38: 0.97102891 | J38: 0.06631571 | K38: 0.011156452 | L38: 0.033717404 | M38: 1.0822185 | N38: =B38+H38+1-M38 -> 0.01002463 | P38: 37530 | Q38: 0.051062549 | R38: 0.058583726 | S38: 0.058583726 | T38: -0.0069790739 | U38: 0.92081655 | V38: 0.048170396 | Y38: 37622 | Z38: =VLOOKUP(Y38,P:V,2,0) -> 0.052693853 | AA38: =VLOOKUP(Y38,A:N,2,0) -> 0.058546508 | AC38: 37622 | AD38: =VLOOKUP(Y38,P:V,3,0) -> 0.051219089 | AE38: =VLOOKUP(Y38,A:N,10,0) -> 0.056793697 | AG38: 37622 | AH38: =-VLOOKUP(Y38,P:V,5,0) -> 0.014514215 | AI38: =VLOOKUP(Y38,A:N,8,0) -> 0.028995692 | AK38: 37622 | AL38: =VLOOKUP(Y38,P:V,4,0) -> 0.051219089 | AM38: =VLOOKUP(Y38,A:N,11,0)+VLOOKUP(Y38,A:N,12,0) -> 0.016475157 | AO38: 37622 | AP38: =VLOOKUP(Y38,P:V,7,0) -> 0.043383042 | AQ38: =VLOOKUP(Y38,A:N,14,0) -> 0.02157015
A39: 37926 | B39: 0.058001613 | C39: 0.015101548 | D39: 0.00030484765 | E39: 0.0026501309 | F39: -0.00072695945 | G39: 0.0058468198 | H39: 0.023176387 | I39: 0.84386431 | J39: 0.043416991 | K39: 0.14599055 | L39: 0.014345925 | M39: 1.0476178 | N39: =B39+H39+1-M39 -> 0.03356022 | P39: 37561 | Q39: 0.056778499 | R39: 0.05583369 | S39: 0.05583369 | T39: -0.017723485 | U39: 0.96890064 | V39: 0.040475924 | Y39: 37653 | Z39: =VLOOKUP(Y39,P:V,2,0) -> 0.058334266 | AA39: =VLOOKUP(Y39,A:N,2,0) -> 0.054348348 | AC39: 37653 | AD39: =VLOOKUP(Y39,P:V,3,0) -> 0.055233917 | AE39: =VLOOKUP(Y39,A:N,10,0) -> 0.071143739 | AG39: 37653 | AH39: =-VLOOKUP(Y39,P:V,5,0) -> 0.016872378 | AI39: =VLOOKUP(Y39,A:N,8,0) -> 0.026456515 | AK39: 37653 | AL39: =VLOOKUP(Y39,P:V,4,0) -> 0.055233917 | AM39: =VLOOKUP(Y39,A:N,11,0)+VLOOKUP(Y39,A:N,12,0) -> 0.029556459 | AO39: 37653 | AP39: =VLOOKUP(Y39,P:V,7,0) -> 0.034565037 | AQ39: =VLOOKUP(Y39,A:N,14,0) -> 0.017790068
A40: 37956 | B40: 0.060825361 | C40: 0.012970019 | D40: 0.00032849038 | E40: 0.003101723 | F40: 5.3184156e-05 | G40: 0.0066373168 | H40: 0.023090733 | I40: 0.98313654 | J40: 0.056320787 | K40: 0.02247821 | L40: 0.0026732036 | M40: 1.0646087 | N40: =B40+H40+1-M40 -> 0.01930735 | P40: 37591 | Q40: 0.052193501 | R40: 0.070087657 | S40: 0.070087657 | T40: -0.014574144 | U40: 0.94039574 | V40: 0.022538262 | Y40: 37681 | Z40: =VLOOKUP(Y40,P:V,2,0) -> 0.056849175 | AA40: =VLOOKUP(Y40,A:N,2,0) -> 0.05739125 | AC40: 37681 | AD40: =VLOOKUP(Y40,P:V,3,0) -> 0.043892006 | AE40: =VLOOKUP(Y40,A:N,10,0) -> 0.056992715 | AG40: 37681 | AH40: =-VLOOKUP(Y40,P:V,5,0) -> 0.014200444 | AI40: =VLOOKUP(Y40,A:N,8,0) -> 0.020912698 | AK40: 37681 | AL40: =VLOOKUP(Y40,P:V,4,0) -> 0.043892006 | AM40: =VLOOKUP(Y40,A:N,11,0)+VLOOKUP(Y40,A:N,12,0) -> 0.025121967 | AO40: 37681 | AP40: =VLOOKUP(Y40,P:V,7,0) -> 0.053538498 | AQ40: =VLOOKUP(Y40,A:N,14,0) -> 0.012791793
A41: 37987 | B41: 0.061756027 | C41: 0.013311599 | D41: 0.00034050549 | E41: 0.0039425023 | F41: 0.00058617697 | G41: 0.0085128013 | H41: 0.026693585 | I41: 0.98642733 | J41: 0.056336649 | K41: 0.0062395197 | L41: 0.0155921 | M41: 1.0645956 | N41: =B41+H41+1-M41 -> 0.02385401 | P41: 37622 | Q41: 0.052693853 | R41: 0.051219089 | S41: 0.051219089 | T41: -0.014514215 | U41: 0.96097013 | V41: 0.043383042 | Y41: 37712 | Z41: =VLOOKUP(Y41,P:V,2,0) -> 0.051332782 | AA41: =VLOOKUP(Y41,A:N,2,0) -> 0.060843517 | AC41: 37712 | AD41: =VLOOKUP(Y41,P:V,3,0) -> 0.075240238 | AE41: =VLOOKUP(Y41,A:N,10,0) -> 0.064250312 | AG41: 37712 | AH41: =-VLOOKUP(Y41,P:V,5,0) -> 0.017101464 | AI41: =VLOOKUP(Y41,A:N,8,0) -> 0.02507598 | AK41: 37712 | AL41: =VLOOKUP(Y41,P:V,4,0) -> 0.075240238 | AM41: =VLOOKUP(Y41,A:N,11,0)+VLOOKUP(Y41,A:N,12,0) -> 0.018082841 | AO41: 37712 | AP41: =VLOOKUP(Y41,P:V,7,0) -> 0.024902151 | AQ41: =VLOOKUP(Y41,A:N,14,0) -> -0.0027417166
A42: 38018 | B42: 0.057340996 | C42: 0.014171493 | D42: 0.00068282833 | E42: 0.0025849482 | F42: -0.00045296533 | G42: 0.0076763649 | H42: 0.024662669 | I42: 0.96662801 | J42: 0.077522796 | K42: 0.00023857522 | L42: 0.02189365 | M42: 1.066283 | N42: =B42+H42+1-M42 -> 0.015720631 | P42: 37653 | Q42: 0.058334266 | R42: 0.055233917 | S42: 0.055233917 | T42: -0.016872378 | U42: 0.96894002 | V42: 0.034565037 | Y42: 37742 | Z42: =VLOOKUP(Y42,P:V,2,0) -> 0.053851237 | AA42: =VLOOKUP(Y42,A:N,2,0) -> 0.060312239 | AC42: 37742 | AD42: =VLOOKUP(Y42,P:V,3,0) -> 0.062386257 | AE42: =VLOOKUP(Y42,A:N,10,0) -> 0.059840087 | AG42: 37742 | AH42: =-VLOOKUP(Y42,P:V,5,0) -> 0.013955327 | AI42: =VLOOKUP(Y42,A:N,8,0) -> 0.020181732 | AK42: 37742 | AL42: =VLOOKUP(Y42,P:V,4,0) -> 0.062386257 | AM42: =VLOOKUP(Y42,A:N,11,0)+VLOOKUP(Y42,A:N,12,0) -> 0.018516223 | AO42: 37742 | AP42: =VLOOKUP(Y42,P:V,7,0) -> 0.026850148 | AQ42: =VLOOKUP(Y42,A:N,14,0) -> 0.012520157
A43: 38047 | B43: 0.062570811 | C43: 0.013281356 | D43: 0.00047832607 | E43: 0.0027994923 | F43: -0.00027854587 | G43: 0.0088863397 | H43: 0.025166968 | I43: 0.89014801 | J43: 0.058571521 | K43: 0.095274894 | L43: 0.0078917378 | M43: 1.0518862 | N43: =B43+H43+1-M43 -> 0.035851611 | P43: 37681 | Q43: 0.056849175 | R43: 0.043892006 | S43: 0.043892006 | T43: -0.014200444 | U43: 0.96570543 | V43: 0.053538498 | Y43: 37773 | Z43: =VLOOKUP(Y43,P:V,2,0) -> 0.057728506 | AA43: =VLOOKUP(Y43,A:N,2,0) -> 0.057111076 | AC43: 37773 | AD43: =VLOOKUP(Y43,P:V,3,0) -> 0.063750978 | AE43: =VLOOKUP(Y43,A:N,10,0) -> 0.041715038 | AG43: 37773 | AH43: =-VLOOKUP(Y43,P:V,5,0) -> 0.025431498 | AI43: =VLOOKUP(Y43,A:N,8,0) -> 0.020913197 | AK43: 37773 | AL43: =VLOOKUP(Y43,P:V,4,0) -> 0.063750978 | AM43: =VLOOKUP(Y43,A:N,11,0)+VLOOKUP(Y43,A:N,12,0) -> 0.020559665 | AO43: 37773 | AP43: =VLOOKUP(Y43,P:V,7,0) -> 0.048517949 | AQ43: =VLOOKUP(Y43,A:N,14,0) -> 0.0096816282
A44: 38078 | B44: 0.056943243 | C44: 0.018386353 | D44: 0.00071777512 | E44: 0.0028115865 | F44: -0.00013375625 | G44: 0.0078492377 | H44: 0.029631196 | I44: 0.99948026 | J44: 0.05569752 | K44: 0.0078287985 | L44: 0.0094552574 | M44: 1.0724618 | N44: =B44+H44+1-M44 -> 0.014112603 | P44: 37712 | Q44: 0.051332782 | R44: 0.075240238 | S44: 0.075240238 | T44: -0.017101464 | U44: 0.9526092 | V44: 0.024902151 | Y44: 37803 | Z44: =VLOOKUP(Y44,P:V,2,0) -> 0.055020275 | AA44: =VLOOKUP(Y44,A:N,2,0) -> 0.056170971 | AC44: 37803 | AD44: =VLOOKUP(Y44,P:V,3,0) -> 0.062693112 | AE44: =VLOOKUP(Y44,A:N,10,0) -> 0.050447231 | AG44: 37803 | AH44: =-VLOOKUP(Y44,P:V,5,0) -> 0.019507175 | AI44: =VLOOKUP(Y44,A:N,8,0) -> 0.019591209 | AK44: 37803 | AL44: =VLOOKUP(Y44,P:V,4,0) -> 0.062693112 | AM44: =VLOOKUP(Y44,A:N,11,0)+VLOOKUP(Y44,A:N,12,0) -> 0.0024355733 | AO44: 37803 | AP44: =VLOOKUP(Y44,P:V,7,0) -> 0.040566189 | AQ44: =VLOOKUP(Y44,A:N,14,0) -> 0.028926423
... A170: 41913 | B170: 0.11054177 | C170: 0.023311182 | D170: 0.0020870435 | E170: 0.0050207714 | F170: 0.01165467 | G170: 0.027690666 | H170: 0.069764332 | I170: 0.81138887 | J170: 0.04793721 | K170: 0 | L170: 0.010878273 | M170: 0.87020435 | N170: =B170+H170+1-M170 -> 0.31010175 | P170: 41548 | Q170: 0.10214546 | R170: 0.053812091 | S170: 0.053812091 | T170: -0.05750974 | U170: 0.70355493 | V170: 0.38517328 | Y170: 41640 | Z170: =VLOOKUP(Y170,P:V,2,0) -> 0.12078379 | AA170: =VLOOKUP(Y170,A:N,2,0) -> 0.090893838 | AC170: 41640 | AD170: =VLOOKUP(Y170,P:V,3,0) -> 0.034665692 | AE170: =VLOOKUP(Y170,A:N,10,0) -> 0.053468062 | AG170: 41640 | AH170: =-VLOOKUP(Y170,P:V,5,0) -> 0.073187066 | AI170: =VLOOKUP(Y170,A:N,8,0) -> 0.057011878 | AK170: 41640 | AL170: =VLOOKUP(Y170,P:V,4,0) -> 0.034665692 | AM170: =VLOOKUP(Y170,A:N,11,0)+VLOOKUP(Y170,A:N,12,0) -> 0.0103836 | AO170: 41640 | AP170: =VLOOKUP(Y170,P:V,7,0) -> 0.41849085 | AQ170: =VLOOKUP(Y170,A:N,14,0) -> 0.28234051
A171: 41944 | B171: 0.11006132 | C171: 0.022451085 | D171: 0.0018644583 | E171: 0.005387555 | F171: 0.014015354 | G171: 0.029031976 | H171: 0.072750429 | I171: 0.80264365 | J171: 0.034985434 | K171: 0 | L171: 0.0084276509 | M171: 0.84605674 | P171: 41579 | Q171: 0.099495115 | R171: 0.058232831 | S171: 0.058232831 | T171: -0.055389498 | U171: 0.70500681 | V171: 0.36947712 | Y171: 41671 | Z171: =VLOOKUP(Y171,P:V,2,0) -> 0.11658109 | AA171: =VLOOKUP(Y171,A:N,2,0) -> 0.10153615 | AC171: 41671 | AD171: =VLOOKUP(Y171,P:V,3,0) -> 0.040750477 | AE171: =VLOOKUP(Y171,A:N,10,0) -> 0.058522048 | AG171: 41671 | AH171: =-VLOOKUP(Y171,P:V,5,0) -> 0.070689842 | AI171: =VLOOKUP(Y171,A:N,8,0) -> 0.058295448 | AK171: 41671 | AL171: =VLOOKUP(Y171,P:V,4,0) -> 0.040750477 | AM171: =VLOOKUP(Y171,A:N,11,0)+VLOOKUP(Y171,A:N,12,0) -> 0.011039381 | AO171: 41671 | AP171: =VLOOKUP(Y171,P:V,7,0) -> 0.41837057 | AQ171: =VLOOKUP(Y171,A:N,14,0) -> 0.29311196
A172: 41974 | B172: 0.11034188 | C172: 0.021829243 | D172: 0.001378519 | E172: 0.0052728247 | F172: 0.0097011051 | G172: 0.028876845 | H172: 0.067058537 | I172: 0.79559221 | J172: 0.042019179 | K172: 0 | L172: 0.0093022815 | M172: 0.84691367 | P172: 41609 | Q172: 0.10501461 | R172: 0.051825808 | S172: 0.051825808 | T172: -0.060758016 | U172: 0.7073013 | V172: 0.38833396 | Y172: 41699 | Z172: =VLOOKUP(Y172,P:V,2,0) -> 0.11483861 | AA172: =VLOOKUP(Y172,A:N,2,0) -> 0.097234264 | AC172: 41699 | AD172: =VLOOKUP(Y172,P:V,3,0) -> 0.034148414 | AE172: =VLOOKUP(Y172,A:N,10,0) -> 0.052480299 | AG172: 41699 | AH172: =-VLOOKUP(Y172,P:V,5,0) -> 0.070824396 | AI172: =VLOOKUP(Y172,A:N,8,0) -> 0.062325544 | AK172: 41699 | AL172: =VLOOKUP(Y172,P:V,4,0) -> 0.034148414 | AM172: =VLOOKUP(Y172,A:N,11,0)+VLOOKUP(Y172,A:N,12,0) -> 0.012330508 | AO172: 41699 | AP172: =VLOOKUP(Y172,P:V,7,0) -> 0.40934538 | AQ172: =VLOOKUP(Y172,A:N,14,0) -> 0.28998539
P173: 41640 | Q173: 0.12078379 | R173: 0.034665692 | S173: 0.034665692 | T173: -0.073187066 | U173: 0.719865 | V173: 0.41849085 | Y173: 41730 | Z173: =VLOOKUP(Y173,P:V,2,0) -> 0.12229385 | AA173: =VLOOKUP(Y173,A:N,2,0) -> 0.095751159 | AC173: 41730 | AD173: =VLOOKUP(Y173,P:V,3,0) -> 0.037077895 | AE173: =VLOOKUP(Y173,A:N,10,0) -> 0.050936761 | AG173: 41730 | AH173: =-VLOOKUP(Y173,P:V,5,0) -> 0.070142065 | AI173: =VLOOKUP(Y173,A:N,8,0) -> 0.060059104 | AK173: 41730 | AL173: =VLOOKUP(Y173,P:V,4,0) -> 0.037077895 | AM173: =VLOOKUP(Y173,A:N,11,0)+VLOOKUP(Y173,A:N,12,0) -> 0.0092588334 | AO173: 41730 | AP173: =VLOOKUP(Y173,P:V,7,0) -> 0.44820744 | AQ173: =VLOOKUP(Y173,A:N,14,0) -> 0.29622187
P174: 41671 | Q174: 0.11658109 | R174: 0.040750477 | S174: 0.040750477 | T174: -0.070689842 | U174: 0.71135843 | V174: 0.41837057 | Y174: 41760 | Z174: =VLOOKUP(Y174,P:V,2,0) -> 0.12464585 | AA174: =VLOOKUP(Y174,A:N,2,0) -> 0.089671336 | AC174: 41760 | AD174: =VLOOKUP(Y174,P:V,3,0) -> 0.032512436 | AE174: =VLOOKUP(Y174,A:N,10,0) -> 0.050093888 | AG174: 41760 | AH174: =-VLOOKUP(Y174,P:V,5,0) -> 0.066364094 | AI174: =VLOOKUP(Y174,A:N,8,0) -> 0.059926609 | AK174: 41760 | AL174: =VLOOKUP(Y174,P:V,4,0) -> 0.032512436 | AM174: =VLOOKUP(Y174,A:N,11,0)+VLOOKUP(Y174,A:N,12,0) -> 0.0090293262 | AO174: 41760 | AP174: =VLOOKUP(Y174,P:V,7,0) -> 0.47595753 | AQ174: =VLOOKUP(Y174,A:N,14,0) -> 0.27166726
P175: 41699 | Q175: 0.11483861 | R175: 0.034148414 | S175: 0.034148414 | T175: -0.070824396 | U175: 0.72116469 | V175: 0.40934538 | Y175: 41791 | Z175: =VLOOKUP(Y175,P:V,2,0) -> 0.13125443 | AA175: =VLOOKUP(Y175,A:N,2,0) -> 0.097921127 | AC175: 41791 | AD175: =VLOOKUP(Y175,P:V,3,0) -> 0.024337517 | AE175: =VLOOKUP(Y175,A:N,10,0) -> 0.057657428 | AG175: 41791 | AH175: =-VLOOKUP(Y175,P:V,5,0) -> 0.057733084 | AI175: =VLOOKUP(Y175,A:N,8,0) -> 0.065786915 | AK175: 41791 | AL175: =VLOOKUP(Y175,P:V,4,0) -> 0.024337517 | AM175: =VLOOKUP(Y175,A:N,11,0)+VLOOKUP(Y175,A:N,12,0) -> 0.013571762 | AO175: 41791 | AP175: =VLOOKUP(Y175,P:V,7,0) -> 0.55013773 | AQ175: =VLOOKUP(Y175,A:N,14,0) -> 0.2659552
P176: 41730 | Q176: 0.12229385 | R176: 0.037077895 | S176: 0.037077895 | T176: -0.070142065 | U176: 0.68967411 | V176: 0.44820744 | Y176: 41821 | Z176: =VLOOKUP(Y176,P:V,2,0) -> 0.13640862 | AA176: =VLOOKUP(Y176,A:N,2,0) -> 0.10490905 | AC176: 41821 | AD176: =VLOOKUP(Y176,P:V,3,0) -> 0.0089674927 | AE176: =VLOOKUP(Y176,A:N,10,0) -> 0.051535774 | AG176: 41821 | AH176: =-VLOOKUP(Y176,P:V,5,0) -> 0.040988347 | AI176: =VLOOKUP(Y176,A:N,8,0) -> 0.06795539 | AK176: 41821 | AL176: =VLOOKUP(Y176,P:V,4,0) -> 0.0089674927 | AM176: =VLOOKUP(Y176,A:N,11,0)+VLOOKUP(Y176,A:N,12,0) -> 0.011851702 | AO176: 41821 | AP176: =VLOOKUP(Y176,P:V,7,0) -> 0.64508192 | AQ176: =VLOOKUP(Y176,A:N,14,0) -> 0.28202616
P177: 41760 | Q177: 0.12464585 | R177: 0.032512436 | S177: 0.032512436 | T177: -0.066364094 | U177: 0.66948002 | V177: 0.47595753 | Y177: 41852 | Z177: =VLOOKUP(Y177,P:V,2,0) -> 0.17628704 | AA177: =VLOOKUP(Y177,A:N,2,0) -> 0.10372223 | AC177: 41852 | AD177: =VLOOKUP(Y177,P:V,3,0) -> 0.0023777292 | AE177: =VLOOKUP(Y177,A:N,10,0) -> 0.058715471 | AG177: 41852 | AH177: =-VLOOKUP(Y177,P:V,5,0) -> 0.064936174 | AI177: =VLOOKUP(Y177,A:N,8,0) -> 0.06653966 | AK177: 41852 | AL177: =VLOOKUP(Y177,P:V,4,0) -> 0.0023777292 | AM177: =VLOOKUP(Y177,A:N,11,0)+VLOOKUP(Y177,A:N,12,0) -> 0.011484943 | AO177: 41852 | AP177: =VLOOKUP(Y177,P:V,7,0) -> 0.6123816 | AQ177: =VLOOKUP(Y177,A:N,14,0) -> 0.27873383
P178: 41791 | Q178: 0.13125443 | R178: 0.024337517 | S178: 0.024337517 | T178: -0.057733084 | U178: 0.60227769 | V178: 0.55013773 | Y178: 41883 | Z178: =VLOOKUP(Y178,P:V,2,0) -> 0.13317228 | AA178: =VLOOKUP(Y178,A:N,2,0) -> 0.10462629 | AC178: 41883 | AD178: =VLOOKUP(Y178,P:V,3,0) -> 0.0035302767 | AE178: =VLOOKUP(Y178,A:N,10,0) -> 0.053078965 | AG178: 41883 | AH178: =-VLOOKUP(Y178,P:V,5,0) -> 0.0052285781 | AI178: =VLOOKUP(Y178,A:N,8,0) -> 0.073753561 | AK178: 41883 | AL178: =VLOOKUP(Y178,P:V,4,0) -> 0.0035302767 | AM178: =VLOOKUP(Y178,A:N,11,0)+VLOOKUP(Y178,A:N,12,0) -> 0.011111103 | AO178: 41883 | AP178: =VLOOKUP(Y178,P:V,7,0) -> 0.90807762 | AQ178: =VLOOKUP(Y178,A:N,14,0) -> 0.28936554
P179: 41821 | Q179: 0.13640862 | R179: 0.0089674927 | S179: 0.0089674927 | T179: -0.040988347 | U179: 0.51482431 | V179: 0.64508192
P180: 41852 | Q180: 0.17628704 | R180: 0.0023777292 | S180: 0.0023777292 | T180: -0.064936174 | U180: 0.62452831 | V180: 0.6123816
P181: 41883 | Q181: 0.13317228 | R181: 0.0035302767 | S181: 0.0035302767 | T181: -0.0052285781 | U181: 0.22284706 | V181: 0.90807762

Sheet REO
B1: Interest | C1: ForeclosureCostsPct | D1: PropertyPreserveAndRepairCostPct | E1: AssetRecoveryCostPct | F1: MiscHoldingExpenseAndCreditsPct | G1: AssociatedTaxforHoldingPropertyPct | H1: Expenses | I1: NetSaleProceedsPct | J1: CreditEnhancementProceedsPct | K1: RepurchaseMakeWholeProceedsPct | L1: OtherForecloseProceedsPct | M1: Proceeds | N1: Severity | P1: lossDate | Q1: interest | R1: miRecoveries | S1: nonMIRecoveries | T1: expenses | U1: netSaleProceeds | V1: ActuralSeverity | Z1: Interest | AD1: MI | AH1: expenses | AL1: Non-MI | AP1: Total
A2: 36831 | B2: 0.062337873 | C2: 0.040350195 | D2: 0.034341301 | E2: 0.017576431 | F2: 0.0075597554 | G2: 0.014219011 | H2: 0.11404669 | I2: 0.97906059 | J2: 0.2351473 | K2: 0 | L2: 0.01077821 | M2: 1.2249861 | N2: =B2+H2+1-M2 -> -0.048601538 | P2: 36557 | Q2: 0.04875 | R2: 0.12835754 | S2: 0.12835754 | T2: -0.031992065 | U2: 0.87529913 | V2: 0.064115157 | Z2: FHL | AA2: FNMA | AD2: FHL | AE2: FNMA | AH2: FHL | AI2: FNMA | AL2: FHL | AM2: FNMA | AP2: FHL | AQ2: FNMA
A3: 36892 | B3: 0.0690672 | C3: 0.01806926 | D3: 0.0094697341 | E3: 0.0068401928 | F3: 0.00067505833 | G3: 0.0083486196 | H3: 0.043402865 | I3: 0.81398692 | J3: 0.18930806 | K3: 0.057961424 | L3: 0.0007835854 | M3: 1.06204 | N3: =B3+H3+1-M3 -> 0.050430074 | P3: 36586 | Q3: 0.06375 | R3: 0.32150512 | S3: 0.32150512 | T3: -0.043225825 | U3: 0 | V3: -0.029329644 | Y3: 36557 | Z3: =VLOOKUP(Y3,P:V,2,0) -> 0.04875 | AA3: =VLOOKUP(Y3,A:N,2,0) -> #N/A | AC3: 36557 | AD3: =VLOOKUP(Y3,P:V,3,0) -> 0.12835754 | AE3: =VLOOKUP(Y3,A:N,10,0) -> #N/A | AG3: 36557 | AH3: =-VLOOKUP(Y3,P:V,5,0) -> 0.031992065 | AI3: =VLOOKUP(Y3,A:N,8,0) -> #N/A | AK3: 36557 | AL3: =VLOOKUP(Y3,P:V,4,0) -> 0.12835754 | AM3: =VLOOKUP(Y3,A:N,11,0)+VLOOKUP(Y3,A:N,12,0) -> #N/A | AO3: 36557 | AP3: =VLOOKUP(Y3,P:V,7,0) -> 0.064115157 | AQ3: =VLOOKUP(Y3,A:N,14,0) -> #N/A
A4: 36923 | B4: 0.072999391 | C4: 0.021332144 | D4: 0.028671528 | E4: 0.0025259657 | F4: 0.00084728886 | G4: 0.016630031 | H4: 0.070006958 | I4: 0.80614878 | J4: 0.13212254 | K4: 0.17110238 | L4: 0.0024101166 | M4: 1.1117838 | N4: =B4+H4+1-M4 -> 0.03122253 | P4: 36617 | Q4: 0.069298967 | R4: 0.42094216 | S4: 0.42094216 | T4: -0.05880357 | U4: 0.40582229 | V4: -0.020734916 | Y4: 36586 | Z4: =VLOOKUP(Y4,P:V,2,0) -> 0.06375 | AA4: =VLOOKUP(Y4,A:N,2,0) -> #N/A | AC4: 36586 | AD4: =VLOOKUP(Y4,P:V,3,0) -> 0.32150512 | AE4: =VLOOKUP(Y4,A:N,10,0) -> #N/A | AG4: 36586 | AH4: =-VLOOKUP(Y4,P:V,5,0) -> 0.043225825 | AI4: =VLOOKUP(Y4,A:N,8,0) -> #N/A | AK4: 36586 | AL4: =VLOOKUP(Y4,P:V,4,0) -> 0.32150512 | AM4: =VLOOKUP(Y4,A:N,11,0)+VLOOKUP(Y4,A:N,12,0) -> #N/A | AO4: 36586 | AP4: =VLOOKUP(Y4,P:V,7,0) -> -0.029329644 | AQ4: =VLOOKUP(Y4,A:N,14,0) -> #N/A
A5: 36951 | B5: 0.082358961 | C5: 0.023102964 | D5: 0.02492311 | E5: 0.0016663387 | F5: 0.0041870314 | G5: 0.010392706 | H5: 0.064272151 | I5: 0.70266327 | J5: 0.20907298 | K5: 0.16682888 | L5: 0.048601835 | M5: 1.127167 | N5: =B5+H5+1-M5 -> 0.019464148 | P5: 36647 | Q5: 0.052799457 | R5: 0.85562108 | S5: 0.85562108 | T5: -0.084116315 | U5: 0.20357422 | V5: 0.074791498 | Y5: 36617 | Z5: =VLOOKUP(Y5,P:V,2,0) -> 0.069298967 | AA5: =VLOOKUP(Y5,A:N,2,0) -> #N/A | AC5: 36617 | AD5: =VLOOKUP(Y5,P:V,3,0) -> 0.42094216 | AE5: =VLOOKUP(Y5,A:N,10,0) -> #N/A | AG5: 36617 | AH5: =-VLOOKUP(Y5,P:V,5,0) -> 0.05880357 | AI5: =VLOOKUP(Y5,A:N,8,0) -> #N/A | AK5: 36617 | AL5: =VLOOKUP(Y5,P:V,4,0) -> 0.42094216 | AM5: =VLOOKUP(Y5,A:N,11,0)+VLOOKUP(Y5,A:N,12,0) -> #N/A | AO5: 36617 | AP5: =VLOOKUP(Y5,P:V,7,0) -> -0.020734916 | AQ5: =VLOOKUP(Y5,A:N,14,0) -> #N/A
A6: 36982 | B6: 0.079712161 | C6: 0.024734522 | D6: 0.013641397 | E6: 0.0046450206 | F6: 0.00059835523 | G6: 0.010103383 | H6: 0.053722678 | I6: 0.5666379 | J6: 0.27181865 | K6: 0.28906722 | L6: 0.0048164088 | M6: 1.1323402 | N6: =B6+H6+1-M6 -> 0.0010946676 | P6: 36678 | Q6: 0.064524493 | R6: 0.3021859 | S6: 0.3021859 | T6: -0.11830933 | U6: 0.6529669 | V6: -0.01251395 | Y6: 36647 | Z6: =VLOOKUP(Y6,P:V,2,0) -> 0.052799457 | AA6: =VLOOKUP(Y6,A:N,2,0) -> #N/A | AC6: 36647 | AD6: =VLOOKUP(Y6,P:V,3,0) -> 0.85562108 | AE6: =VLOOKUP(Y6,A:N,10,0) -> #N/A | AG6: 36647 | AH6: =-VLOOKUP(Y6,P:V,5,0) -> 0.084116315 | AI6: =VLOOKUP(Y6,A:N,8,0) -> #N/A | AK6: 36647 | AL6: =VLOOKUP(Y6,P:V,4,0) -> 0.85562108 | AM6: =VLOOKUP(Y6,A:N,11,0)+VLOOKUP(Y6,A:N,12,0) -> #N/A | AO6: 36647 | AP6: =VLOOKUP(Y6,P:V,7,0) -> 0.074791498 | AQ6: =VLOOKUP(Y6,A:N,14,0) -> #N/A
A7: 37012 | B7: 0.079575096 | C7: 0.024054273 | D7: 0.037070107 | E7: 0.0020382626 | F7: 0.0031357887 | G7: 0.0076037097 | H7: 0.073902141 | I7: 0.7868314 | J7: 0.17744365 | K7: 0.16459886 | L7: 0.01544896 | M7: 1.1443229 | N7: =B7+H7+1-M7 -> 0.0091543663 | P7: 36708 | Q7: 0.070398776 | R7: 0.30766611 | S7: 0.30766611 | T7: -0.054116056 | U7: 0.75598429 | V7: 0.028489967 | Y7: 36678 | Z7: =VLOOKUP(Y7,P:V,2,0) -> 0.064524493 | AA7: =VLOOKUP(Y7,A:N,2,0) -> #N/A | AC7: 36678 | AD7: =VLOOKUP(Y7,P:V,3,0) -> 0.3021859 | AE7: =VLOOKUP(Y7,A:N,10,0) -> #N/A | AG7: 36678 | AH7: =-VLOOKUP(Y7,P:V,5,0) -> 0.11830933 | AI7: =VLOOKUP(Y7,A:N,8,0) -> #N/A | AK7: 36678 | AL7: =VLOOKUP(Y7,P:V,4,0) -> 0.3021859 | AM7: =VLOOKUP(Y7,A:N,11,0)+VLOOKUP(Y7,A:N,12,0) -> #N/A | AO7: 36678 | AP7: =VLOOKUP(Y7,P:V,7,0) -> -0.01251395 | AQ7: =VLOOKUP(Y7,A:N,14,0) -> #N/A
A8: 37043 | B8: 0.079033858 | C8: 0.025605497 | D8: 0.016595822 | E8: 0.0033727719 | F8: 0.00037502773 | G8: 0.0070099779 | H8: 0.052959097 | I8: 0.74245401 | J8: 0.16150609 | K8: 0.19840386 | L8: 0.0080312246 | M8: 1.1103952 | N8: =B8+H8+1-M8 -> 0.021597774 | P8: 36739 | Q8: 0.071546122 | R8: 0.16560305 | S8: 0.16560305 | T8: -0.050254484 | U8: 0.46366627 | V8: -0.01475706 | Y8: 36708 | Z8: =VLOOKUP(Y8,P:V,2,0) -> 0.070398776 | AA8: =VLOOKUP(Y8,A:N,2,0) -> #N/A | AC8: 36708 | AD8: =VLOOKUP(Y8,P:V,3,0) -> 0.30766611 | AE8: =VLOOKUP(Y8,A:N,10,0) -> #N/A | AG8: 36708 | AH8: =-VLOOKUP(Y8,P:V,5,0) -> 0.054116056 | AI8: =VLOOKUP(Y8,A:N,8,0) -> #N/A | AK8: 36708 | AL8: =VLOOKUP(Y8,P:V,4,0) -> 0.30766611 | AM8: =VLOOKUP(Y8,A:N,11,0)+VLOOKUP(Y8,A:N,12,0) -> #N/A | AO8: 36708 | AP8: =VLOOKUP(Y8,P:V,7,0) -> 0.028489967 | AQ8: =VLOOKUP(Y8,A:N,14,0) -> #N/A
A9: 37073 | B9: 0.085281662 | C9: 0.023057795 | D9: 0.02157282 | E9: 0.0041610704 | F9: 0.0014937308 | G9: 0.0081936284 | H9: 0.058479045 | I9: 0.65811357 | J9: 0.25815479 | K9: 0.18397587 | L9: 0.012065997 | M9: 1.1123102 | N9: =B9+H9+1-M9 -> 0.031450482 | P9: 36770 | Q9: 0.069357313 | R9: 0.30551444 | S9: 0.30551444 | T9: -0.063405957 | U9: 0.56078821 | V9: 0.019582273 | Y9: 36739 | Z9: =VLOOKUP(Y9,P:V,2,0) -> 0.071546122 | AA9: =VLOOKUP(Y9,A:N,2,0) -> #N/A | AC9: 36739 | AD9: =VLOOKUP(Y9,P:V,3,0) -> 0.16560305 | AE9: =VLOOKUP(Y9,A:N,10,0) -> #N/A | AG9: 36739 | AH9: =-VLOOKUP(Y9,P:V,5,0) -> 0.050254484 | AI9: =VLOOKUP(Y9,A:N,8,0) -> #N/A | AK9: 36739 | AL9: =VLOOKUP(Y9,P:V,4,0) -> 0.16560305 | AM9: =VLOOKUP(Y9,A:N,11,0)+VLOOKUP(Y9,A:N,12,0) -> #N/A | AO9: 36739 | AP9: =VLOOKUP(Y9,P:V,7,0) -> -0.01475706 | AQ9: =VLOOKUP(Y9,A:N,14,0) -> #N/A
A10: 37104 | B10: 0.078236843 | C10: 0.037359428 | D10: 0.018405148 | E10: 0.0047668219 | F10: 0.0018407659 | G10: 0.0069321703 | H10: 0.069304334 | I10: 0.65038972 | J10: 0.19592458 | K10: 0.15815163 | L10: 0.11164781 | M10: 1.1161137 | N10: =B10+H10+1-M10 -> 0.03142743 | P10: 36800 | Q10: 0.075878094 | R10: 0.24335548 | S10: 0.24335548 | T10: -0.062116451 | U10: 0.52078368 | V10: 0.031258205 | Y10: 36770 | Z10: =VLOOKUP(Y10,P:V,2,0) -> 0.069357313 | AA10: =VLOOKUP(Y10,A:N,2,0) -> #N/A | AC10: 36770 | AD10: =VLOOKUP(Y10,P:V,3,0) -> 0.30551444 | AE10: =VLOOKUP(Y10,A:N,10,0) -> #N/A | AG10: 36770 | AH10: =-VLOOKUP(Y10,P:V,5,0) -> 0.063405957 | AI10: =VLOOKUP(Y10,A:N,8,0) -> #N/A | AK10: 36770 | AL10: =VLOOKUP(Y10,P:V,4,0) -> 0.30551444 | AM10: =VLOOKUP(Y10,A:N,11,0)+VLOOKUP(Y10,A:N,12,0) -> #N/A | AO10: 36770 | AP10: =VLOOKUP(Y10,P:V,7,0) -> 0.019582273 | AQ10: =VLOOKUP(Y10,A:N,14,0) -> #N/A
A11: 37135 | B11: 0.091358307 | C11: 0.025101771 | D11: 0.017087096 | E11: 0.0054699513 | F11: 0.002278097 | G11: 0.0090676766 | H11: 0.059004593 | I11: 0.72684344 | J11: 0.15589662 | K11: 0.18520274 | L11: 0.046311086 | M11: 1.1142539 | N11: =B11+H11+1-M11 -> 0.036109018 | P11: 36831 | Q11: 0.074752987 | R11: 0.25182566 | S11: 0.25182566 | T11: -0.061491359 | U11: 0.62072968 | V11: 0.033229807 | Y11: 36800 | Z11: =VLOOKUP(Y11,P:V,2,0) -> 0.075878094 | AA11: =VLOOKUP(Y11,A:N,2,0) -> #N/A | AC11: 36800 | AD11: =VLOOKUP(Y11,P:V,3,0) -> 0.24335548 | AE11: =VLOOKUP(Y11,A:N,10,0) -> #N/A | AG11: 36800 | AH11: =-VLOOKUP(Y11,P:V,5,0) -> 0.062116451 | AI11: =VLOOKUP(Y11,A:N,8,0) -> #N/A | AK11: 36800 | AL11: =VLOOKUP(Y11,P:V,4,0) -> 0.24335548 | AM11: =VLOOKUP(Y11,A:N,11,0)+VLOOKUP(Y11,A:N,12,0) -> #N/A | AO11: 36800 | AP11: =VLOOKUP(Y11,P:V,7,0) -> 0.031258205 | AQ11: =VLOOKUP(Y11,A:N,14,0) -> #N/A
A12: 37165 | B12: 0.090941628 | C12: 0.030466388 | D12: 0.021710204 | E12: 0.006795539 | F12: 0.0032322381 | G12: 0.0074688058 | H12: 0.069673175 | I12: 0.6603504 | J12: 0.18243384 | K12: 0.25237295 | L12: 0.043013743 | M12: 1.1381709 | N12: =B12+H12+1-M12 -> 0.022443865 | P12: 36861 | Q12: 0.075288062 | R12: 0.14859924 | S12: 0.14859924 | T12: -0.061677914 | U12: 0.62828729 | V12: 0.075490456 | Y12: 36831 | Z12: =VLOOKUP(Y12,P:V,2,0) -> 0.074752987 | AA12: =VLOOKUP(Y12,A:N,2,0) -> 0.062337873 | AC12: 36831 | AD12: =VLOOKUP(Y12,P:V,3,0) -> 0.25182566 | AE12: =VLOOKUP(Y12,A:N,10,0) -> 0.2351473 | AG12: 36831 | AH12: =-VLOOKUP(Y12,P:V,5,0) -> 0.061491359 | AI12: =VLOOKUP(Y12,A:N,8,0) -> 0.11404669 | AK12: 36831 | AL12: =VLOOKUP(Y12,P:V,4,0) -> 0.25182566 | AM12: =VLOOKUP(Y12,A:N,11,0)+VLOOKUP(Y12,A:N,12,0) -> 0.01077821 | AO12: 36831 | AP12: =VLOOKUP(Y12,P:V,7,0) -> 0.033229807 | AQ12: =VLOOKUP(Y12,A:N,14,0) -> -0.048601538
A13: 37196 | B13: 0.091738939 | C13: 0.033511278 | D13: 0.018271743 | E13: 0.0049105811 | F13: 0.002694215 | G13: 0.0085649298 | H13: 0.067952748 | I13: 0.65963723 | J13: 0.20970727 | K13: 0.21502263 | L13: 0.056024146 | M13: 1.1403913 | N13: =B13+H13+1-M13 -> 0.019300408 | P13: 36892 | Q13: 0.075700018 | R13: 0.22058979 | S13: 0.22058979 | T13: -0.061639485 | U13: 0.50933133 | V13: 0.037187628 | Y13: 36861 | Z13: =VLOOKUP(Y13,P:V,2,0) -> 0.075288062 | AA13: =VLOOKUP(Y13,A:N,2,0) -> #N/A | AC13: 36861 | AD13: =VLOOKUP(Y13,P:V,3,0) -> 0.14859924 | AE13: =VLOOKUP(Y13,A:N,10,0) -> #N/A | AG13: 36861 | AH13: =-VLOOKUP(Y13,P:V,5,0) -> 0.061677914 | AI13: =VLOOKUP(Y13,A:N,8,0) -> #N/A | AK13: 36861 | AL13: =VLOOKUP(Y13,P:V,4,0) -> 0.14859924 | AM13: =VLOOKUP(Y13,A:N,11,0)+VLOOKUP(Y13,A:N,12,0) -> #N/A | AO13: 36861 | AP13: =VLOOKUP(Y13,P:V,7,0) -> 0.075490456 | AQ13: =VLOOKUP(Y13,A:N,14,0) -> #N/A
A14: 37226 | B14: 0.089358634 | C14: 0.030112926 | D14: 0.047920529 | E14: 0.0066452823 | F14: 0.0030917821 | G14: 0.010000589 | H14: 0.097771108 | I14: 0.71839513 | J14: 0.17706225 | K14: 0.19860106 | L14: 0.044415063 | M14: 1.1384735 | N14: =B14+H14+1-M14 -> 0.048656235 | P14: 36923 | Q14: 0.086374846 | R14: 0.22455964 | S14: 0.22455964 | T14: -0.074335462 | U14: 0.54453254 | V14: 0.031464121 | Y14: 36892 | Z14: =VLOOKUP(Y14,P:V,2,0) -> 0.075700018 | AA14: =VLOOKUP(Y14,A:N,2,0) -> 0.0690672 | AC14: 36892 | AD14: =VLOOKUP(Y14,P:V,3,0) -> 0.22058979 | AE14: =VLOOKUP(Y14,A:N,10,0) -> 0.18930806 | AG14: 36892 | AH14: =-VLOOKUP(Y14,P:V,5,0) -> 0.061639485 | AI14: =VLOOKUP(Y14,A:N,8,0) -> 0.043402865 | AK14: 36892 | AL14: =VLOOKUP(Y14,P:V,4,0) -> 0.22058979 | AM14: =VLOOKUP(Y14,A:N,11,0)+VLOOKUP(Y14,A:N,12,0) -> 0.058745009 | AO14: 36892 | AP14: =VLOOKUP(Y14,P:V,7,0) -> 0.037187628 | AQ14: =VLOOKUP(Y14,A:N,14,0) -> 0.050430074
... A23: 37500 | B23: 0.09630358 | C23: 0.034690348 | D23: 0.019622107 | E23: 0.0046654788 | F23: 0.0047863995 | G23: 0.01159775 | H23: 0.075362084 | I23: 0.74305471 | J23: 0.187929 | K23: 0.14789167 | L23: 0.03289998 | M23: 1.1117754 | N23: =B23+H23+1-M23 -> 0.059890305 | P23: 37196 | Q23: 0.097345433 | R23: 0.14346107 | S23: 0.14346107 | T23: -0.084835535 | U23: 0.73457107 | V23: 0.089220673 | Y23: 37165 | Z23: =VLOOKUP(Y23,P:V,2,0) -> 0.090651097 | AA23: =VLOOKUP(Y23,A:N,2,0) -> 0.090941628 | AC23: 37165 | AD23: =VLOOKUP(Y23,P:V,3,0) -> 0.16475264 | AE23: =VLOOKUP(Y23,A:N,10,0) -> 0.18243384 | AG23: 37165 | AH23: =-VLOOKUP(Y23,P:V,5,0) -> 0.070374898 | AI23: =VLOOKUP(Y23,A:N,8,0) -> 0.069673175 | AK23: 37165 | AL23: =VLOOKUP(Y23,P:V,4,0) -> 0.16475264 | AM23: =VLOOKUP(Y23,A:N,11,0)+VLOOKUP(Y23,A:N,12,0) -> 0.2953867 | AO23: 37165 | AP23: =VLOOKUP(Y23,P:V,7,0) -> 0.070812168 | AQ23: =VLOOKUP(Y23,A:N,14,0) -> 0.022443865
A24: 37530 | B24: 0.098699431 | C24: 0.036775377 | D24: 0.018052109 | E24: 0.0055582122 | F24: 0.0049945772 | G24: 0.012039129 | H24: 0.077419404 | I24: 0.74938175 | J24: 0.19858797 | K24: 0.15590861 | L24: 0.035340276 | M24: 1.1392186 | N24: =B24+H24+1-M24 -> 0.036900226 | P24: 37226 | Q24: 0.094388606 | R24: 0.16248996 | S24: 0.16248996 | T24: -0.074646348 | U24: 0.60175962 | V24: 0.085889213 | Y24: 37196 | Z24: =VLOOKUP(Y24,P:V,2,0) -> 0.097345433 | AA24: =VLOOKUP(Y24,A:N,2,0) -> 0.091738939 | AC24: 37196 | AD24: =VLOOKUP(Y24,P:V,3,0) -> 0.14346107 | AE24: =VLOOKUP(Y24,A:N,10,0) -> 0.20970727 | AG24: 37196 | AH24: =-VLOOKUP(Y24,P:V,5,0) -> 0.084835535 | AI24: =VLOOKUP(Y24,A:N,8,0) -> 0.067952748 | AK24: 37196 | AL24: =VLOOKUP(Y24,P:V,4,0) -> 0.14346107 | AM24: =VLOOKUP(Y24,A:N,11,0)+VLOOKUP(Y24,A:N,12,0) -> 0.27104678 | AO24: 37196 | AP24: =VLOOKUP(Y24,P:V,7,0) -> 0.089220673 | AQ24: =VLOOKUP(Y24,A:N,14,0) -> 0.019300408 | BF24: 1
A25: 37561 | B25: 0.094732216 | C25: 0.034537619 | D25: 0.018652768 | E25: 0.0045379711 | F25: 0.0035223485 | G25: 0.014148417 | H25: 0.075399124 | I25: 0.71598955 | J25: 0.19963008 | K25: 0.1507467 | L25: 0.066792889 | M25: 1.1331592 | N25: =B25+H25+1-M25 -> 0.036972132 | P25: 37257 | Q25: 0.092143358 | R25: 0.13199034 | S25: 0.13199034 | T25: -0.078982393 | U25: 0.71399767 | V25: 0.092632648 | Y25: 37226 | Z25: =VLOOKUP(Y25,P:V,2,0) -> 0.094388606 | AA25: =VLOOKUP(Y25,A:N,2,0) -> 0.089358634 | AC25: 37226 | AD25: =VLOOKUP(Y25,P:V,3,0) -> 0.16248996 | AE25: =VLOOKUP(Y25,A:N,10,0) -> 0.17706225 | AG25: 37226 | AH25: =-VLOOKUP(Y25,P:V,5,0) -> 0.074646348 | AI25: =VLOOKUP(Y25,A:N,8,0) -> 0.097771108 | AK25: 37226 | AL25: =VLOOKUP(Y25,P:V,4,0) -> 0.16248996 | AM25: =VLOOKUP(Y25,A:N,11,0)+VLOOKUP(Y25,A:N,12,0) -> 0.24301612 | AO25: 37226 | AP25: =VLOOKUP(Y25,P:V,7,0) -> 0.085889213 | AQ25: =VLOOKUP(Y25,A:N,14,0) -> 0.048656235
A26: 37591 | B26: 0.093027142 | C26: 0.032424421 | D26: 0.017573942 | E26: 0.0051661686 | F26: 0.0043045753 | G26: 0.013522086 | H26: 0.072991193 | I26: 0.77050414 | J26: 0.18220516 | K26: 0.14164347 | L26: 0.029594281 | M26: 1.1239471 | N26: =B26+H26+1-M26 -> 0.042071282 | P26: 37288 | Q26: 0.091875612 | R26: 0.17381646 | S26: 0.17381646 | T26: -0.076945384 | U26: 0.71297672 | V26: 0.084698029 | Y26: 37257 | Z26: =VLOOKUP(Y26,P:V,2,0) -> 0.092143358 | AA26: =VLOOKUP(Y26,A:N,2,0) -> 0.097383211 | AC26: 37257 | AD26: =VLOOKUP(Y26,P:V,3,0) -> 0.13199034 | AE26: =VLOOKUP(Y26,A:N,10,0) -> 0.20667945 | AG26: 37257 | AH26: =-VLOOKUP(Y26,P:V,5,0) -> 0.078982393 | AI26: =VLOOKUP(Y26,A:N,8,0) -> 0.088211583 | AK26: 37257 | AL26: =VLOOKUP(Y26,P:V,4,0) -> 0.13199034 | AM26: =VLOOKUP(Y26,A:N,11,0)+VLOOKUP(Y26,A:N,12,0) -> 0.32370373 | AO26: 37257 | AP26: =VLOOKUP(Y26,P:V,7,0) -> 0.092632648 | AQ26: =VLOOKUP(Y26,A:N,14,0) -> 0.033640741
A27: 37622 | B27: 0.097419911 | C27: 0.040749156 | D27: 0.016961007 | E27: 0.0051932994 | F27: 0.0056919153 | G27: 0.013334125 | H27: 0.081929503 | I27: 0.69290201 | J27: 0.20000193 | K27: 0.17011005 | L27: 0.062161308 | M27: 1.1251753 | N27: =B27+H27+1-M27 -> 0.054174114 | P27: 37316 | Q27: 0.094031959 | R27: 0.22046988 | S27: 0.22046988 | T27: -0.080547162 | U27: 0.6611473 | V27: 0.091376148 | Y27: 37288 | Z27: =VLOOKUP(Y27,P:V,2,0) -> 0.091875612 | AA27: =VLOOKUP(Y27,A:N,2,0) -> 0.096002164 | AC27: 37288 | AD27: =VLOOKUP(Y27,P:V,3,0) -> 0.17381646 | AE27: =VLOOKUP(Y27,A:N,10,0) -> 0.24000651 | AG27: 37288 | AH27: =-VLOOKUP(Y27,P:V,5,0) -> 0.076945384 | AI27: =VLOOKUP(Y27,A:N,8,0) -> 0.098232929 | AK27: 37288 | AL27: =VLOOKUP(Y27,P:V,4,0) -> 0.17381646 | AM27: =VLOOKUP(Y27,A:N,11,0)+VLOOKUP(Y27,A:N,12,0) -> 0.16754759 | AO27: 37288 | AP27: =VLOOKUP(Y27,P:V,7,0) -> 0.084698029 | AQ27: =VLOOKUP(Y27,A:N,14,0) -> 0.04892843
A28: 37653 | B28: 0.094840673 | C28: 0.03670639 | D28: 0.018004198 | E28: 0.0089939149 | F28: 0.0047706996 | G28: 0.016304793 | H28: 0.084779996 | I28: 0.73339626 | J28: 0.2207231 | K28: 0.13296836 | L28: 0.02966599 | M28: 1.1167537 | N28: =B28+H28+1-M28 -> 0.062866962 | P28: 37347 | Q28: 0.09664752 | R28: 0.19003674 | S28: 0.19003674 | T28: -0.08395408 | U28: 0.68603333 | V28: 0.081119427 | Y28: 37316 | Z28: =VLOOKUP(Y28,P:V,2,0) -> 0.094031959 | AA28: =VLOOKUP(Y28,A:N,2,0) -> 0.095026824 | AC28: 37316 | AD28: =VLOOKUP(Y28,P:V,3,0) -> 0.22046988 | AE28: =VLOOKUP(Y28,A:N,10,0) -> 0.17079696 | AG28: 37316 | AH28: =-VLOOKUP(Y28,P:V,5,0) -> 0.080547162 | AI28: =VLOOKUP(Y28,A:N,8,0) -> 0.065236185 | AK28: 37316 | AL28: =VLOOKUP(Y28,P:V,4,0) -> 0.22046988 | AM28: =VLOOKUP(Y28,A:N,11,0)+VLOOKUP(Y28,A:N,12,0) -> 0.22585596 | AO28: 37316 | AP28: =VLOOKUP(Y28,P:V,7,0) -> 0.091376148 | AQ28: =VLOOKUP(Y28,A:N,14,0) -> 0.023601919
A29: 37681 | B29: 0.095779157 | C29: 0.033905946 | D29: 0.016528034 | E29: 0.0051958095 | F29: 0.0043609834 | G29: 0.015562218 | H29: 0.075552991 | I29: 0.75517788 | J29: 0.18441207 | K29: 0.14475221 | L29: 0.03633725 | M29: 1.1206794 | N29: =B29+H29+1-M29 -> 0.050652733 | P29: 37377 | Q29: 0.095342703 | R29: 0.2352029 | S29: 0.2352029 | T29: -0.088447898 | U29: 0.71224782 | V29: 0.10370711 | Y29: 37347 | Z29: =VLOOKUP(Y29,P:V,2,0) -> 0.09664752 | AA29: =VLOOKUP(Y29,A:N,2,0) -> 0.096828909 | AC29: 37347 | AD29: =VLOOKUP(Y29,P:V,3,0) -> 0.19003674 | AE29: =VLOOKUP(Y29,A:N,10,0) -> 0.19422416 | AG29: 37347 | AH29: =-VLOOKUP(Y29,P:V,5,0) -> 0.08395408 | AI29: =VLOOKUP(Y29,A:N,8,0) -> 0.067459038 | AK29: 37347 | AL29: =VLOOKUP(Y29,P:V,4,0) -> 0.19003674 | AM29: =VLOOKUP(Y29,A:N,11,0)+VLOOKUP(Y29,A:N,12,0) -> 0.21802265 | AO29: 37347 | AP29: =VLOOKUP(Y29,P:V,7,0) -> 0.081119427 | AQ29: =VLOOKUP(Y29,A:N,14,0) -> 0.02973795
A30: 37712 | B30: 0.097603685 | C30: 0.040477915 | D30: 0.017183458 | E30: 0.0053458087 | F30: 0.0030993456 | G30: 0.014707748 | H30: 0.080814276 | I30: 0.70588106 | J30: 0.20549128 | K30: 0.14768224 | L30: 0.046156943 | M30: 1.1052115 | N30: =B30+H30+1-M30 -> 0.073206441 | P30: 37408 | Q30: 0.093979781 | R30: 0.15296662 | S30: 0.15296662 | T30: -0.085630486 | U30: 0.70025462 | V30: 0.06247337 | Y30: 37377 | Z30: =VLOOKUP(Y30,P:V,2,0) -> 0.095342703 | AA30: =VLOOKUP(Y30,A:N,2,0) -> 0.091497061 | AC30: 37377 | AD30: =VLOOKUP(Y30,P:V,3,0) -> 0.2352029 | AE30: =VLOOKUP(Y30,A:N,10,0) -> 0.18867197 | AG30: 37377 | AH30: =-VLOOKUP(Y30,P:V,5,0) -> 0.088447898 | AI30: =VLOOKUP(Y30,A:N,8,0) -> 0.06758598 | AK30: 37377 | AL30: =VLOOKUP(Y30,P:V,4,0) -> 0.2352029 | AM30: =VLOOKUP(Y30,A:N,11,0)+VLOOKUP(Y30,A:N,12,0) -> 0.17442508 | AO30: 37377 | AP30: =VLOOKUP(Y30,P:V,7,0) -> 0.10370711 | AQ30: =VLOOKUP(Y30,A:N,14,0) -> 0.042958827
A31: 37742 | B31: 0.096424702 | C31: 0.04100936 | D31: 0.018251177 | E31: 0.0049562576 | F31: 0.0043691886 | G31: 0.014582712 | H31: 0.083168695 | I31: 0.74958191 | J31: 0.19094668 | K31: 0.13583566 | L31: 0.044426776 | M31: 1.120791 | N31: =B31+H31+1-M31 -> 0.058802378 | P31: 37438 | Q31: 0.097684253 | R31: 0.18526928 | S31: 0.18526928 | T31: -0.083421637 | U31: 0.70460338 | V31: 0.09250024 | Y31: 37408 | Z31: =VLOOKUP(Y31,P:V,2,0) -> 0.093979781 | AA31: =VLOOKUP(Y31,A:N,2,0) -> 0.092552909 | AC31: 37408 | AD31: =VLOOKUP(Y31,P:V,3,0) -> 0.15296662 | AE31: =VLOOKUP(Y31,A:N,10,0) -> 0.18321223 | AG31: 37408 | AH31: =-VLOOKUP(Y31,P:V,5,0) -> 0.085630486 | AI31: =VLOOKUP(Y31,A:N,8,0) -> 0.072737008 | AK31: 37408 | AL31: =VLOOKUP(Y31,P:V,4,0) -> 0.15296662 | AM31: =VLOOKUP(Y31,A:N,11,0)+VLOOKUP(Y31,A:N,12,0) -> 0.21214007 | AO31: 37408 | AP31: =VLOOKUP(Y31,P:V,7,0) -> 0.06247337 | AQ31: =VLOOKUP(Y31,A:N,14,0) -> 0.022435434
A32: 37773 | B32: 0.095980528 | C32: 0.032698867 | D32: 0.015805399 | E32: 0.0046463332 | F32: 0.0037641613 | G32: 0.01339999 | H32: 0.07031475 | I32: 0.72490965 | J32: 0.17304423 | K32: 0.16860564 | L32: 0.045979702 | M32: 1.1125392 | N32: =B32+H32+1-M32 -> 0.053756056 | P32: 37469 | Q32: 0.099353926 | R32: 0.19273438 | S32: 0.19273438 | T32: -0.084097465 | U32: 0.65810318 | V32: 0.1039882 | Y32: 37438 | Z32: =VLOOKUP(Y32,P:V,2,0) -> 0.097684253 | AA32: =VLOOKUP(Y32,A:N,2,0) -> 0.095463533 | AC32: 37438 | AD32: =VLOOKUP(Y32,P:V,3,0) -> 0.18526928 | AE32: =VLOOKUP(Y32,A:N,10,0) -> 0.19516214 | AG32: 37438 | AH32: =-VLOOKUP(Y32,P:V,5,0) -> 0.083421637 | AI32: =VLOOKUP(Y32,A:N,8,0) -> 0.072560416 | AK32: 37438 | AL32: =VLOOKUP(Y32,P:V,4,0) -> 0.18526928 | AM32: =VLOOKUP(Y32,A:N,11,0)+VLOOKUP(Y32,A:N,12,0) -> 0.19647086 | AO32: 37438 | AP32: =VLOOKUP(Y32,P:V,7,0) -> 0.09250024 | AQ32: =VLOOKUP(Y32,A:N,14,0) -> 0.040806568
A33: 37803 | B33: 0.097198068 | C33: 0.0336266 | D33: 0.021742754 | E33: 0.0043583764 | F33: 0.0043488271 | G33: 0.013407248 | H33: 0.077483805 | I33: 0.72461605 | J33: 0.18606159 | K33: 0.14421786 | L33: 0.040687739 | M33: 1.0955832 | N33: =B33+H33+1-M33 -> 0.079098635 | P33: 37500 | Q33: 0.098950253 | R33: 0.20414717 | S33: 0.20414717 | T33: -0.092322013 | U33: 0.69162983 | V33: 0.093244375 | Y33: 37469 | Z33: =VLOOKUP(Y33,P:V,2,0) -> 0.099353926 | AA33: =VLOOKUP(Y33,A:N,2,0) -> 0.098718605 | AC33: 37469 | AD33: =VLOOKUP(Y33,P:V,3,0) -> 0.19273438 | AE33: =VLOOKUP(Y33,A:N,10,0) -> 0.20135427 | AG33: 37469 | AH33: =-VLOOKUP(Y33,P:V,5,0) -> 0.084097465 | AI33: =VLOOKUP(Y33,A:N,8,0) -> 0.074638086 | AK33: 37469 | AL33: =VLOOKUP(Y33,P:V,4,0) -> 0.19273438 | AM33: =VLOOKUP(Y33,A:N,11,0)+VLOOKUP(Y33,A:N,12,0) -> 0.18353875 | AO33: 37469 | AP33: =VLOOKUP(Y33,P:V,7,0) -> 0.1039882 | AQ33: =VLOOKUP(Y33,A:N,14,0) -> 0.042313393
A34: 37834 | B34: 0.095584103 | C34: 0.035686587 | D34: 0.018510366 | E34: 0.004211156 | F34: 0.0034909987 | G34: 0.014113175 | H34: 0.076012282 | I34: 0.71882159 | J34: 0.17079296 | K34: 0.17107178 | L34: 0.035384047 | M34: 1.0960704 | N34: =B34+H34+1-M34 -> 0.075526006 | P34: 37530 | Q34: 0.098997578 | R34: 0.16858537 | S34: 0.16858537 | T34: -0.087021885 | U34: 0.70123051 | V34: 0.11276998 | Y34: 37500 | Z34: =VLOOKUP(Y34,P:V,2,0) -> 0.098950253 | AA34: =VLOOKUP(Y34,A:N,2,0) -> 0.09630358 | AC34: 37500 | AD34: =VLOOKUP(Y34,P:V,3,0) -> 0.20414717 | AE34: =VLOOKUP(Y34,A:N,10,0) -> 0.187929 | AG34: 37500 | AH34: =-VLOOKUP(Y34,P:V,5,0) -> 0.092322013 | AI34: =VLOOKUP(Y34,A:N,8,0) -> 0.075362084 | AK34: 37500 | AL34: =VLOOKUP(Y34,P:V,4,0) -> 0.20414717 | AM34: =VLOOKUP(Y34,A:N,11,0)+VLOOKUP(Y34,A:N,12,0) -> 0.18079165 | AO34: 37500 | AP34: =VLOOKUP(Y34,P:V,7,0) -> 0.093244375 | AQ34: =VLOOKUP(Y34,A:N,14,0) -> 0.059890305
A35: 37865 | B35: 0.094151908 | C35: 0.033980108 | D35: 0.01779074 | E35: 0.0073414593 | F35: 0.0044333641 | G35: 0.013039401 | H35: 0.076585072 | I35: 0.69091416 | J35: 0.1885935 | K35: 0.16523007 | L35: 0.059247519 | M35: 1.1039852 | N35: =B35+H35+1-M35 -> 0.066751732 | P35: 37561 | Q35: 0.097595287 | R35: 0.19821838 | S35: 0.19821838 | T35: -0.087093979 | U35: 0.62580363 | V35: 0.099507748 | Y35: 37530 | Z35: =VLOOKUP(Y35,P:V,2,0) -> 0.098997578 | AA35: =VLOOKUP(Y35,A:N,2,0) -> 0.098699431 | AC35: 37530 | AD35: =VLOOKUP(Y35,P:V,3,0) -> 0.16858537 | AE35: =VLOOKUP(Y35,A:N,10,0) -> 0.19858797 | AG35: 37530 | AH35: =-VLOOKUP(Y35,P:V,5,0) -> 0.087021885 | AI35: =VLOOKUP(Y35,A:N,8,0) -> 0.077419404 | AK35: 37530 | AL35: =VLOOKUP(Y35,P:V,4,0) -> 0.16858537 | AM35: =VLOOKUP(Y35,A:N,11,0)+VLOOKUP(Y35,A:N,12,0) -> 0.19124889 | AO35: 37530 | AP35: =VLOOKUP(Y35,P:V,7,0) -> 0.11276998 | AQ35: =VLOOKUP(Y35,A:N,14,0) -> 0.036900226
A36: 37895 | B36: 0.094983666 | C36: 0.031747143 | D36: 0.018446292 | E36: 0.0035254289 | F36: 0.0045889813 | G36: 0.013080276 | H36: 0.071388121 | I36: 0.68347489 | J36: 0.16690621 | K36: 0.1756454 | L36: 0.047305107 | M36: 1.0733316 | N36: =B36+H36+1-M36 -> 0.093040176 | P36: 37591 | Q36: 0.098142376 | R36: 0.19051084 | S36: 0.19051084 | T36: -0.084176588 | U36: 0.67300196 | V36: 0.10785837 | Y36: 37561 | Z36: =VLOOKUP(Y36,P:V,2,0) -> 0.097595287 | AA36: =VLOOKUP(Y36,A:N,2,0) -> 0.094732216 | AC36: 37561 | AD36: =VLOOKUP(Y36,P:V,3,0) -> 0.19821838 | AE36: =VLOOKUP(Y36,A:N,10,0) -> 0.19963008 | AG36: 37561 | AH36: =-VLOOKUP(Y36,P:V,5,0) -> 0.087093979 | AI36: =VLOOKUP(Y36,A:N,8,0) -> 0.075399124 | AK36: 37561 | AL36: =VLOOKUP(Y36,P:V,4,0) -> 0.19821838 | AM36: =VLOOKUP(Y36,A:N,11,0)+VLOOKUP(Y36,A:N,12,0) -> 0.21753958 | AO36: 37561 | AP36: =VLOOKUP(Y36,P:V,7,0) -> 0.099507748 | AQ36: =VLOOKUP(Y36,A:N,14,0) -> 0.036972132
... A170: 41974 | B170: 0.17856827 | C170: 0.053661799 | D170: 0.049719013 | E170: 0.011085011 | F170: 0.023108635 | G170: 0.042712562 | H170: 0.18028702 | I170: 0.74388424 | J170: 0.068752464 | K170: 0.005405949 | L170: 0.020344728 | M170: 0.83838738 | N170: =B170+H170+1-M170 -> 0.52046791 | P170: 41671 | Q170: 0.16121224 | R170: 0.075422176 | S170: 0.075422176 | T170: -0.22058314 | U170: 0.68249206 | V170: 0.58537785 | Y170: 41640 | Z170: =VLOOKUP(Y170,P:V,2,0) -> 0.16187093 | AA170: =VLOOKUP(Y170,A:N,2,0) -> 0.15472478 | AC170: 41640 | AD170: =VLOOKUP(Y170,P:V,3,0) -> 0.073360752 | AE170: =VLOOKUP(Y170,A:N,10,0) -> 0.071319314 | AG170: 41640 | AH170: =-VLOOKUP(Y170,P:V,5,0) -> 0.22196046 | AI170: =VLOOKUP(Y170,A:N,8,0) -> 0.14523075 | AK170: 41640 | AL170: =VLOOKUP(Y170,P:V,4,0) -> 0.073360752 | AM170: =VLOOKUP(Y170,A:N,11,0)+VLOOKUP(Y170,A:N,12,0) -> 0.035154126 | AO170: 41640 | AP170: =VLOOKUP(Y170,P:V,7,0) -> 0.57761247 | AQ170: =VLOOKUP(Y170,A:N,14,0) -> 0.48996754
P171: 41699 | Q171: 0.16066696 | R171: 0.072687428 | S171: 0.072687428 | T171: -0.22502422 | U171: 0.71423242 | V171: 0.56670827 | Y171: 41671 | Z171: =VLOOKUP(Y171,P:V,2,0) -> 0.16121224 | AA171: =VLOOKUP(Y171,A:N,2,0) -> 0.15413006 | AC171: 41671 | AD171: =VLOOKUP(Y171,P:V,3,0) -> 0.075422176 | AE171: =VLOOKUP(Y171,A:N,10,0) -> 0.073936663 | AG171: 41671 | AH171: =-VLOOKUP(Y171,P:V,5,0) -> 0.22058314 | AI171: =VLOOKUP(Y171,A:N,8,0) -> 0.14316323 | AK171: 41671 | AL171: =VLOOKUP(Y171,P:V,4,0) -> 0.075422176 | AM171: =VLOOKUP(Y171,A:N,11,0)+VLOOKUP(Y171,A:N,12,0) -> 0.03215315 | AO171: 41671 | AP171: =VLOOKUP(Y171,P:V,7,0) -> 0.58537785 | AQ171: =VLOOKUP(Y171,A:N,14,0) -> 0.47127288
P172: 41730 | Q172: 0.16525642 | R172: 0.072536125 | S172: 0.072536125 | T172: -0.22518758 | U172: 0.71643672 | V172: 0.56344112 | Y172: 41699 | Z172: =VLOOKUP(Y172,P:V,2,0) -> 0.16066696 | AA172: =VLOOKUP(Y172,A:N,2,0) -> 0.15678633 | AC172: 41699 | AD172: =VLOOKUP(Y172,P:V,3,0) -> 0.072687428 | AE172: =VLOOKUP(Y172,A:N,10,0) -> 0.070560538 | AG172: 41699 | AH172: =-VLOOKUP(Y172,P:V,5,0) -> 0.22502422 | AI172: =VLOOKUP(Y172,A:N,8,0) -> 0.14703553 | AK172: 41699 | AL172: =VLOOKUP(Y172,P:V,4,0) -> 0.072687428 | AM172: =VLOOKUP(Y172,A:N,11,0)+VLOOKUP(Y172,A:N,12,0) -> 0.035447667 | AO172: 41699 | AP172: =VLOOKUP(Y172,P:V,7,0) -> 0.56670827 | AQ172: =VLOOKUP(Y172,A:N,14,0) -> 0.4803714
P173: 41760 | Q173: 0.16878781 | R173: 0.066614757 | S173: 0.066614757 | T173: -0.22042268 | U173: 0.72916131 | V173: 0.56272838 | Y173: 41730 | Z173: =VLOOKUP(Y173,P:V,2,0) -> 0.16525642 | AA173: =VLOOKUP(Y173,A:N,2,0) -> 0.15826173 | AC173: 41730 | AD173: =VLOOKUP(Y173,P:V,3,0) -> 0.072536125 | AE173: =VLOOKUP(Y173,A:N,10,0) -> 0.072297019 | AG173: 41730 | AH173: =-VLOOKUP(Y173,P:V,5,0) -> 0.22518758 | AI173: =VLOOKUP(Y173,A:N,8,0) -> 0.15046163 | AK173: 41730 | AL173: =VLOOKUP(Y173,P:V,4,0) -> 0.072536125 | AM173: =VLOOKUP(Y173,A:N,11,0)+VLOOKUP(Y173,A:N,12,0) -> 0.034133111 | AO173: 41730 | AP173: =VLOOKUP(Y173,P:V,7,0) -> 0.56344112 | AQ173: =VLOOKUP(Y173,A:N,14,0) -> 0.47877019
P174: 41791 | Q174: 0.17270617 | R174: 0.076060427 | S174: 0.076060427 | T174: -0.2188203 | U174: 0.72100151 | V174: 0.56506478 | Y174: 41760 | Z174: =VLOOKUP(Y174,P:V,2,0) -> 0.16878781 | AA174: =VLOOKUP(Y174,A:N,2,0) -> 0.16297189 | AC174: 41760 | AD174: =VLOOKUP(Y174,P:V,3,0) -> 0.066614757 | AE174: =VLOOKUP(Y174,A:N,10,0) -> 0.068493537 | AG174: 41760 | AH174: =-VLOOKUP(Y174,P:V,5,0) -> 0.22042268 | AI174: =VLOOKUP(Y174,A:N,8,0) -> 0.15456936 | AK174: 41760 | AL174: =VLOOKUP(Y174,P:V,4,0) -> 0.066614757 | AM174: =VLOOKUP(Y174,A:N,11,0)+VLOOKUP(Y174,A:N,12,0) -> 0.027923944 | AO174: 41760 | AP174: =VLOOKUP(Y174,P:V,7,0) -> 0.56272838 | AQ174: =VLOOKUP(Y174,A:N,14,0) -> 0.48354858
P175: 41821 | Q175: 0.1733223 | R175: 0.0625676 | S175: 0.0625676 | T175: -0.2173872 | U175: 0.72410905 | V175: 0.57082082 | Y175: 41791 | Z175: =VLOOKUP(Y175,P:V,2,0) -> 0.17270617 | AA175: =VLOOKUP(Y175,A:N,2,0) -> 0.16407419 | AC175: 41791 | AD175: =VLOOKUP(Y175,P:V,3,0) -> 0.076060427 | AE175: =VLOOKUP(Y175,A:N,10,0) -> 0.071034061 | AG175: 41791 | AH175: =-VLOOKUP(Y175,P:V,5,0) -> 0.2188203 | AI175: =VLOOKUP(Y175,A:N,8,0) -> 0.15921504 | AK175: 41791 | AL175: =VLOOKUP(Y175,P:V,4,0) -> 0.076060427 | AM175: =VLOOKUP(Y175,A:N,11,0)+VLOOKUP(Y175,A:N,12,0) -> 0.026311559 | AO175: 41791 | AP175: =VLOOKUP(Y175,P:V,7,0) -> 0.56506478 | AQ175: =VLOOKUP(Y175,A:N,14,0) -> 0.48268935
P176: 41852 | Q176: 0.17256507 | R176: 0.069339056 | S176: 0.069339056 | T176: -0.2000623 | U176: 0.7024978 | V176: 0.57369001 | Y176: 41821 | Z176: =VLOOKUP(Y176,P:V,2,0) -> 0.1733223 | AA176: =VLOOKUP(Y176,A:N,2,0) -> 0.1664112 | AC176: 41821 | AD176: =VLOOKUP(Y176,P:V,3,0) -> 0.0625676 | AE176: =VLOOKUP(Y176,A:N,10,0) -> 0.071561413 | AG176: 41821 | AH176: =-VLOOKUP(Y176,P:V,5,0) -> 0.2173872 | AI176: =VLOOKUP(Y176,A:N,8,0) -> 0.16398074 | AK176: 41821 | AL176: =VLOOKUP(Y176,P:V,4,0) -> 0.0625676 | AM176: =VLOOKUP(Y176,A:N,11,0)+VLOOKUP(Y176,A:N,12,0) -> 0.029415469 | AO176: 41821 | AP176: =VLOOKUP(Y176,P:V,7,0) -> 0.57082082 | AQ176: =VLOOKUP(Y176,A:N,14,0) -> 0.48767936
P177: 41883 | Q177: 0.18397048 | R177: 0.064881066 | S177: 0.064881066 | T177: -0.19367846 | U177: 0.66393778 | V177: 0.62654978 | Y177: 41852 | Z177: =VLOOKUP(Y177,P:V,2,0) -> 0.17256507 | AA177: =VLOOKUP(Y177,A:N,2,0) -> 0.1742196 | AC177: 41852 | AD177: =VLOOKUP(Y177,P:V,3,0) -> 0.069339056 | AE177: =VLOOKUP(Y177,A:N,10,0) -> 0.075334091 | AG177: 41852 | AH177: =-VLOOKUP(Y177,P:V,5,0) -> 0.2000623 | AI177: =VLOOKUP(Y177,A:N,8,0) -> 0.17155864 | AK177: 41852 | AL177: =VLOOKUP(Y177,P:V,4,0) -> 0.069339056 | AM177: =VLOOKUP(Y177,A:N,11,0)+VLOOKUP(Y177,A:N,12,0) -> 0.03436326 | AO177: 41852 | AP177: =VLOOKUP(Y177,P:V,7,0) -> 0.57369001 | AQ177: =VLOOKUP(Y177,A:N,14,0) -> 0.50991557
Y178: 41883 | Z178: =VLOOKUP(Y178,P:V,2,0) -> 0.18397048 | AA178: =VLOOKUP(Y178,A:N,2,0) -> 0.17287536 | AC178: 41883 | AD178: =VLOOKUP(Y178,P:V,3,0) -> 0.064881066 | AE178: =VLOOKUP(Y178,A:N,10,0) -> 0.075574333 | AG178: 41883 | AH178: =-VLOOKUP(Y178,P:V,5,0) -> 0.19367846 | AI178: =VLOOKUP(Y178,A:N,8,0) -> 0.16876695 | AK178: 41883 | AL178: =VLOOKUP(Y178,P:V,4,0) -> 0.064881066 | AM178: =VLOOKUP(Y178,A:N,11,0)+VLOOKUP(Y178,A:N,12,0) -> 0.026680392 | AO178: 41883 | AP178: =VLOOKUP(Y178,P:V,7,0) -> 0.62654978 | AQ178: =VLOOKUP(Y178,A:N,14,0) -> 0.51819777
