Workbook

Sheet Distribution of data
A1: count() | B1: bucket | I1: count() | J1: tag | K1: loansize | L1: fico | M1: lien | N1: invest | O1: cltv | P1: state | Q1: asOf | R1: Ticker | S1: Orig Date | T1: wala | U1: TPO | V1: butnout | X1: burnout adj
A2: 1096925 | B2: 'Done' | C2: <= 417 >= 740 no lien no invest cltv <= 80
A3: 466351 | B3: 'FICO' | I3: =SUM('Burnout 2013 Corres+CW'!AR3:AR36) -> 3951976 | J3: Burnout | K3: (175,417] | L3: [740,860] | M3: no | N3: no | O3: (0,80] | P3: not in ('NY','PR') | Q3: [20120101,20130401] | R3: All 4 | S3: post HARP | U3: CORRES, CASHWINDOW | V3: [0,2000]
A4: 230769 | B4: '2nd Lien' | I4: =SUM('Burnout 2013 Corres+CW'!AR123:AR134) -> 104779 | J4: Burnout | K4: (175,417] | L4: [740,860] | M4: no | N4: no | O4: (0,80] | P4: not in ('NY','PR') | Q4: [20120101,20130401] | R4: All 4 | S4: post HARP | U4: CORRES, CASHWINDOW | V4: (2000,4000]
A5: 144409 | B5: 'INV' | I5: =SUM('Burnout 2013 Corres+CW'!AR184:AR189) -> 2518 | J5: Burnout | K5: (175,417] | L5: [740,860] | M5: no | N5: no | O5: (0,80] | P5: not in ('NY','PR') | Q5: [20120101,20130401] | R5: All 4 | S5: post HARP | U5: CORRES, CASHWINDOW | V5: (4000,6000]
A6: 124596 | B6: 'CLTV' | I6: =SUM('Burnout 2013 Broker'!AR3:AR35) -> 960295 | J6: Burnout | K6: (175,417] | L6: [740,860] | M6: no | N6: no | O6: (0,80] | P6: not in ('NY','PR') | Q6: [20120101,20130401] | R6: All 4 | S6: post HARP | U6: Broker | V6: [0,2000]
A7: 57525 | B7: 'Jumbo' | I7: =SUM('Burnout 2013 Broker'!AR123:AR133) -> 29518 | J7: Burnout | K7: (175,417] | L7: [740,860] | M7: no | N7: no | O7: (0,80] | P7: not in ('NY','PR') | Q7: [20120101,20130401] | R7: All 4 | S7: post HARP | U7: Broker | V7: (2000,4000]
A8: 2 | B8: 'Not Done' | I8: =SUM('Burnout 2013 Broker'!AR184:AR189) -> 686 | J8: Burnout | K8: (175,417] | L8: [740,860] | M8: no | N8: no | O8: (0,80] | P8: not in ('NY','PR') | Q8: [20120101,20130401] | R8: All 4 | S8: post HARP | U8: Broker | V8: (4000,6000]
I9: =SUM('Burnout 2013 NonCW'!AR3:AR36) -> 2402977 | J9: Burnout | K9: (175,417] | L9: [740,860] | M9: no | N9: no | O9: (0,80] | P9: not in ('NY','PR') | Q9: [20120101,20130401] | R9: All 4 | S9: post HARP | U9: NonCashWindow | V9: [0,2000]
A10: =SUM(A2:A8) -> 2120577 | B10: total | I10: =SUM('Burnout 2013 NonCW'!AR123:AR134) -> 136528 | J10: Burnout | K10: (175,417] | L10: [740,860] | M10: no | N10: no | O10: (0,80] | P10: not in ('NY','PR') | Q10: [20120101,20130401] | R10: All 4 | S10: post HARP | U10: NonCashWindow | V10: (2000,4000] | X10: 1.15
I11: =SUM('Burnout 2013 NonCW'!AR195:AR201) -> 3921 | J11: Burnout | K11: (175,417] | L11: [740,860] | M11: no | N11: no | O11: (0,80] | P11: not in ('NY','PR') | Q11: [20120101,20130401] | R11: All 4 | S11: post HARP | U11: NonCashWindow | V11: (4000,6000]

Sheet Baseline
A1: WALA [12,24) | C1: CORRES+CASHWINDOW | F1: low media | AS1: tover | AT1: cash | AW1: refi
A2: modelId | B2: SFACTOR_PREPAY_TRACKING_CPR | C2: PREPAY_CPR1 | D2: PREPAY_TRACKING_CPR1 | E2: PREPAY_SMM1 | F2: PREPAY_TRACKING_SMM1 | G2: PCT_LOANTYPE | H2: _ORIGNOTERATE | I2: _ZEROSATO | J2: _SATO | K2: _REFI_INCENTIVE_Fixed | L2: _Fixed_cost | M2: _LOANAGE | N2: _LTV | O2: _CLTV | P2: _AVG_LOANSIZE_SCHAMBALANCE | Q2: _WACLS | R2: _FICO | S2: PCT_ISSECONDLIEN | T2: _OrigCombLTV | U2: PCT_SVC | V2: PCT_TPO | W2: PCT_GEO | X2: PCT_LOANPURPOSE | Y2: PCT_OCC | Z2: curtailsmm | AA2: defaultsmm | AB2: toverSmm | AC2: cashoutSmm | AD2: refiSmm | AE2: cumHPA | AF2: cumHPA05Pct | AG2: cumHPA15Pct | AH2: cumHPA20Pct | AI2: cumHPA25Pct | AJ2: cumHPA30Pct | AK2: cumHPA35Pct | AL2: cumHPA40Pct | AM2: adjtoverSmm | AN2: adjRefiSmm | AO2: groupByColumn | AP2: curve | AQ2: Balance | AR2: LoanCount | AS2: PCT_BROKER | AT2: PCT_CORRES | AU2: PCT_NonRETAIL | AV2: PCT_RETAIL | AW2: PCT_CashWindow | AX2: PCT_NonCashWindow
A3: 97 | B3: 0.98839691 | C3: 96.635073 | D3: 13.068622 | E3: 0.24621417 | F3: 0.011603087 | G3: 0 | H3: 3.4287964 | I3: 3.9170498 | J3: -60.571903 | K3: -108.57802 | L3: 100 | M3: 13.372006 | N3: 76.773096 | O3: 12.785692 | P3: 34194.875 | Q3: 31481.298 | R3: 792.65593 | S3: 0 | T3: 0 | U3: 0.060023573 | V3: 0.43037133 | W3: 0 | X3: 0.060023573 | Y3: 0 | Z3: 0.0055161513 | AA3: 1.2412019e-05 | AB3: 0.0060745137 | AC3: 0 | AD3: 0 | AE3: 0.059792222 | AF3: 0.39695938 | AG3: 1 | AH3: 1 | AI3: 1 | AJ3: 1 | AK3: 1 | AL3: 1 | AM3: 0 | AN3: 0 | AO3: 04:-125--100 | AP3: =-125--100 -> -25 | AQ3: 188887.79 | AR3: 6 | AS3: 0 | AT3: 56.962867 | AU3: 56.962867 | AV3: 43.037133 | AW3: 43.037133 | AX3: 0
A4: 97 | B4: 0.98844184 | C4: 49.843412 | D4: 13.021188 | E4: 0.055879709 | F4: 0.011558155 | G4: 0 | H4: 3.4420778 | I4: 3.9164769 | J4: -59.517626 | K4: -81.597641 | L4: 68.465589 | M4: 14.548948 | N4: 71.385986 | O4: 24.934341 | P4: 117969.24 | Q4: 40852.783 | R4: 786.04463 | S4: 0 | T4: 0 | U4: 0.027485084 | V4: 0.68664472 | W4: 0 | X4: 0.058346254 | Y4: 0 | Z4: 0.0043983283 | AA4: 3.4939807e-05 | AB4: 0.007099851 | AC4: 3.07944e-06 | AD4: 2.1947121e-05 | AE4: 0.092113583 | AF4: 0.20636363 | AG4: 0.92741588 | AH4: 1 | AI4: 1 | AJ4: 1 | AK4: 1 | AL4: 1 | AM4: 0 | AN4: 0 | AO4: 05:-100--75 | AP4: =-100--75 -> -25 | AQ4: 6005359.1 | AR4: 147 | AS4: 0 | AT4: 31.335528 | AU4: 31.335528 | AV4: 68.664472 | AW4: 68.664472 | AX4: 0
A5: 97 | B5: 0.99124721 | C5: 38.81742 | D5: 10.012176 | E5: 0.040115492 | F5: 0.0087527875 | G5: 0 | H5: 3.4962707 | I5: 3.8952664 | J5: -53.707825 | K5: -57.582086 | L5: 45.414254 | M5: 15.142775 | N5: 73.296276 | O5: 43.30325 | P5: 173908.24 | Q5: 63191.424 | R5: 782.07674 | S5: 0 | T5: 0 | U5: 0.054816654 | V5: 0.72447447 | W5: 0 | X5: 0.21958318 | Y5: 0 | Z5: 0.0023777527 | AA5: 3.843875e-05 | AB5: 0.0061975188 | AC5: 2.517301e-06 | AD5: 0.00013654951 | AE5: 0.087867306 | AF5: 0.19207694 | AG5: 0.95406742 | AH5: 0.99472364 | AI5: 1 | AJ5: 1 | AK5: 1 | AL5: 1 | AM5: 0 | AN5: 0 | AO5: 06:-75--50 | AP5: =-75--50 -> -25 | AQ5: 43286126 | AR5: 685 | AS5: 0 | AT5: 27.552553 | AU5: 27.552553 | AV5: 72.447447 | AW5: 72.447447 | AX5: 0
A6: 97 | B6: 0.99390274 | C6: 9.3616256 | D6: 7.0762609 | E6: 0.0081575869 | F6: 0.0060972558 | G6: 0 | H6: 3.4645783 | I6: 3.9281772 | J6: -54.768892 | K6: -31.153905 | L6: 18.985438 | M6: 14.446285 | N6: 73.016693 | O6: 63.087717 | P6: 251793.26 | Q6: 201489.6 | R6: 781.12105 | S6: 0 | T6: 0 | U6: 0.05384346 | V6: 0.61549503 | W6: 0 | X6: 0.51591271 | Y6: 0 | Z6: 0.00053383381 | AA6: 3.2372878e-05 | AB6: 0.0050501465 | AC6: 9.784867e-07 | AD6: 0.00047990951 | AE6: 0.08095162 | AF6: 0.19860855 | AG6: 0.95610793 | AH6: 0.99846457 | AI6: 1 | AJ6: 1 | AK6: 1 | AL6: 1 | AM6: 0 | AN6: 0 | AO6: 07:-50--25 | AP6: =-50--25 -> -25 | AQ6: 1.3604578e+09 | AR6: 6752 | AS6: 0 | AT6: 38.450497 | AU6: 38.450497 | AV6: 61.549503 | AW6: 61.549503 | AX6: 0
A7: 97 | B7: 0.99378325 | C7: 7.416952 | D7: 7.2102337 | E7: 0.0064014336 | F7: 0.006216748 | G7: 0 | H7: 3.524119 | I7: 3.9299141 | J7: -48.414066 | K7: -22.221985 | L7: 16.498899 | M7: 14.36346 | N7: 73.1865 | O7: 65.100598 | P7: 268436.49 | Q7: 239394.87 | R7: 780.93529 | S7: 0 | T7: 0 | U7: 0.068865837 | V7: 0.6104547 | W7: 0 | X7: 0.5618934 | Y7: 0 | Z7: 0.00040143177 | AA7: 3.2732743e-05 | AB7: 0.0049308652 | AC7: 7.3330338e-07 | AD7: 0.00085097056 | AE7: 0.08062327 | AF7: 0.16681883 | AG7: 0.96699982 | AH7: 0.99933097 | AI7: 1 | AJ7: 1 | AK7: 1 | AL7: 1 | AM7: 0 | AN7: 0 | AO7: 08-1:-25--20 | AP7: =-25--20 -> -5 | AQ7: 1.5658819e+09 | AR7: 6541 | AS7: 0 | AT7: 38.95453 | AU7: 38.95453 | AV7: 61.04547 | AW7: 61.04547 | AX7: 0
A8: 97 | B8: 0.99345355 | C8: 4.8879394 | D8: 7.5789684 | E8: 0.0041674922 | F8: 0.0065464462 | G8: 0 | H8: 3.5557883 | I8: 3.9208747 | J8: -45.581681 | K8: -17.210662 | L8: 15.961582 | M8: 14.483489 | N8: 71.60487 | O8: 63.81283 | P8: 272723.21 | Q8: 249028.12 | R8: 781.78181 | S8: 0 | T8: 0 | U8: 0.078276983 | V8: 0.60553234 | W8: 0 | X8: 0.54899391 | Y8: 0 | Z8: 0.00038737513 | AA8: 3.3488465e-05 | AB8: 0.0050609118 | AC8: 9.2107342e-07 | AD8: 0.0010637355 | AE8: 0.082238649 | AF8: 0.16530941 | AG8: 0.96394511 | AH8: 0.99885027 | AI8: 1 | AJ8: 1 | AK8: 1 | AL8: 1 | AM8: 0 | AN8: 0 | AO8: 08-2:-20--15 | AP8: =-20--15 -> -5 | AQ8: 2.7221264e+09 | AR8: 10931 | AS8: 0 | AT8: 39.446766 | AU8: 39.446766 | AV8: 60.553234 | AW8: 60.553234 | AX8: 0
A9: 97 | B9: 0.99328989 | C9: 8.259733 | D9: 7.7615092 | E9: 0.0071583219 | F9: 0.0067101086 | G9: 0 | H9: 3.5954185 | I9: 3.9147199 | J9: -41.886543 | K9: -12.281778 | L9: 15.428091 | M9: 14.550842 | N9: 72.17644 | O9: 64.441153 | P9: 279936.8 | Q9: 258280.9 | R9: 781.46676 | S9: 0 | T9: 0 | U9: 0.087735292 | V9: 0.60964009 | W9: 0 | X9: 0.54254679 | Y9: 0 | Z9: 0.00037560677 | AA9: 3.3985792e-05 | AB9: 0.0050442272 | AC9: 1.084469e-06 | AD9: 0.0012551902 | AE9: 0.083439747 | AF9: 0.14859681 | AG9: 0.96165329 | AH9: 0.99909455 | AI9: 1 | AJ9: 1 | AK9: 1 | AL9: 1 | AM9: 0 | AN9: 0 | AO9: 08-3:-15--10 | AP9: =-15--10 -> -5 | AQ9: 4.5837111e+09 | AR9: 17747 | AS9: 0 | AT9: 39.035991 | AU9: 39.035991 | AV9: 60.964009 | AW9: 60.964009 | AX9: 0
A10: 97 | B10: 0.99296879 | C10: 7.9191916 | D10: 8.1186917 | E10: 0.0068517227 | F10: 0.007031212 | G10: 0 | H10: 3.6231364 | I10: 3.8984104 | J10: -39.585383 | K10: -7.4062628 | L10: 15.296341 | M10: 14.911876 | N10: 71.109777 | O10: 63.291883 | P10: 281675.24 | Q10: 260533.88 | R10: 781.48996 | S10: 0 | T10: 0 | U10: 0.091236558 | V10: 0.60130514 | W10: 0 | X10: 0.55636662 | Y10: 0 | Z10: 0.00037442918 | AA10: 3.4860008e-05 | AB10: 0.0051831359 | AC10: 1.5032299e-06 | AD10: 0.0014372692 | AE10: 0.086115169 | AF10: 0.14110782 | AG10: 0.95021425 | AH10: 0.99893123 | AI10: 1 | AJ10: 1 | AK10: 1 | AL10: 1 | AM10: 0 | AN10: 0 | AO10: 08-4:-10--5 | AP10: =-10--5 -> -5 | AQ10: 6.6326715e+09 | AR10: 25458 | AS10: 0 | AT10: 39.869486 | AU10: 39.869486 | AV10: 60.130514 | AW10: 60.130514 | AX10: 0
A11: 97 | B11: 0.99281459 | C11: 8.6514849 | D11: 8.2897601 | E11: 0.0075123203 | F11: 0.0071854061 | G11: 0 | H11: 3.6551722 | I11: 3.8826854 | J11: -36.811228 | K11: -2.3916674 | L11: 15.050831 | M11: 15.210302 | N11: 71.233243 | O11: 63.416485 | P11: 286027.38 | Q11: 264953.55 | R11: 781.41774 | S11: 0 | T11: 0 | U11: 0.092835681 | V11: 0.59536817 | W11: 0 | X11: 0.56119432 | Y11: 0 | Z11: 0.00037069367 | AA11: 3.581818e-05 | AB11: 0.0051417377 | AC11: 1.8486999e-06 | AD11: 0.0016352936 | AE11: 0.087190228 | AF11: 0.13675479 | AG11: 0.95105333 | AH11: 0.99888108 | AI11: 1 | AJ11: 1 | AK11: 1 | AL11: 1 | AM11: 0 | AN11: 0 | AO11: 08:-25-0 | AP11: =-25-0 -> -25 | AQ11: 9.7982474e+09 | AR11: 36981 | AS11: 0 | AT11: 40.463183 | AU11: 40.463183 | AV11: 59.536817 | AW11: 59.536817 | AX11: 0
A12: 97 | B12: 0.99252654 | C12: 9.6587779 | D12: 8.6085537 | E12: 0.0084289694 | F12: 0.0074734586 | G12: 0 | H12: 3.6936876 | I12: 3.8737928 | J12: -33.806205 | K12: 2.6121767 | L12: 15.059416 | M12: 15.398367 | N12: 71.20197 | O12: 63.30499 | P12: 284835.16 | Q12: 264994.1 | R12: 781.44475 | S12: 0 | T12: 0 | U12: 0.099676388 | V12: 0.6006954 | W12: 0 | X12: 0.56479509 | Y12: 0 | Z12: 0.0003703554 | AA12: 3.6686619e-05 | AB12: 0.0052090767 | AC12: 3.0870021e-06 | AD12: 0.0018542384 | AE12: 0.089425468 | AF12: 0.1246349 | AG12: 0.94265683 | AH12: 0.99742834 | AI12: 1 | AJ12: 1 | AK12: 1 | AL12: 1 | AM12: 0 | AN12: 0 | AO12: 09-1:0-5 | AP12: 0-5 | AQ12: 1.2626439e+10 | AR12: 47648 | AS12: 0 | AT12: 39.93046 | AU12: 39.93046 | AV12: 60.06954 | AW12: 60.06954 | AX12: 0
A13: 97 | B13: 0.99219486 | C13: 11.895024 | D13: 8.9743772 | E13: 0.010497939 | F13: 0.0078051429 | G13: 0 | H13: 3.7178014 | I13: 3.8530514 | J13: -32.195354 | K13: 7.6142859 | L13: 14.558583 | M13: 15.821745 | N13: 70.946759 | O13: 62.934601 | P13: 293115.39 | Q13: 274145.15 | R13: 781.38453 | S13: 0 | T13: 0 | U13: 0.1010385 | V13: 0.60196444 | W13: 0 | X13: 0.55814045 | Y13: 0 | Z13: 0.00037043941 | AA13: 3.8612944e-05 | AB13: 0.0052327257 | AC13: 4.0688358e-06 | AD13: 0.0021592816 | AE13: 0.091144609 | AF13: 0.12017603 | AG13: 0.93715128 | AH13: 0.99640248 | AI13: 1 | AJ13: 1 | AK13: 1 | AL13: 1 | AM13: 0 | AN13: 0 | AO13: 09-2:5-10 | AP13: 43230 | AQ13: 1.600432e+10 | AR13: 58379 | AS13: 0 | AT13: 39.803556 | AU13: 39.803556 | AV13: 60.196444 | AW13: 60.196444 | AX13: 0
A14: 97 | B14: 0.99187172 | C14: 13.619226 | D14: 9.3294821 | E14: 0.012126299 | F14: 0.0081282798 | G14: 0 | H14: 3.7551712 | I14: 3.8414164 | J14: -29.577044 | K14: 12.555816 | L14: 14.66393 | M14: 16.07843 | N14: 70.781193 | O14: 62.654426 | P14: 292854.45 | Q14: 272182.21 | R14: 781.20433 | S14: 0 | T14: 0 | U14: 0.11061444 | V14: 0.5989312 | W14: 0 | X14: 0.57020664 | Y14: 0 | Z14: 0.00037059973 | AA14: 4.1935797e-05 | AB14: 0.005219016 | AC14: 5.8672202e-06 | AD14: 0.0024908466 | AE14: 0.093267643 | AF14: 0.11238082 | AG14: 0.92893431 | AH14: 0.99520282 | AI14: 1 | AJ14: 1 | AK14: 1 | AL14: 1 | AM14: 0 | AN14: 0 | AO14: 09-3:10-15 | AP14: 43388 | AQ14: 1.7351616e+10 | AR14: 63750 | AS14: 0 | AT14: 40.10688 | AU14: 40.10688 | AV14: 59.89312 | AW14: 59.89312 | AX14: 0
A15: 97 | B15: 0.99145545 | C15: 12.96156 | D15: 9.7850591 | E15: 0.011501704 | F15: 0.008544547 | G15: 0 | H15: 3.793177 | I15: 3.8307621 | J15: -27.475239 | K15: 17.559079 | L15: 14.863894 | M15: 16.339959 | N15: 70.435491 | O15: 62.357252 | P15: 287175.28 | Q15: 268515.14 | R15: 781.17369 | S15: 0 | T15: 0 | U15: 0.11020424 | V15: 0.59692517 | W15: 0 | X15: 0.55869535 | Y15: 0 | Z15: 0.00037026406 | AA15: 4.4001409e-05 | AB15: 0.0052680609 | AC15: 7.3344628e-06 | AD15: 0.0028548717 | AE15: 0.093673786 | AF15: 0.1216746 | AG15: 0.92555841 | AH15: 0.99393651 | AI15: 1 | AJ15: 1 | AK15: 1 | AL15: 1 | AM15: 0 | AN15: 0 | AO15: 09-4:15-20 | AP15: 15-20 | AQ15: 1.900926e+10 | AR15: 70794 | AS15: 0 | AT15: 40.307483 | AU15: 40.307483 | AV15: 59.692517 | AW15: 59.692517 | AX15: 0
A16: 97 | B16: 0.99104263 | C16: 14.637116 | D16: 10.234797 | E16: 0.013101649 | F16: 0.0089573731 | G16: 0 | H16: 3.8324935 | I16: 3.8215182 | J16: -25.058838 | K16: 22.492715 | L16: 14.619027 | M16: 16.595066 | N16: 72.560471 | O16: 64.111066 | P16: 291993.22 | Q16: 273045.97 | R16: 780.70105 | S16: 0 | T16: 0 | U16: 0.11739366 | V16: 0.59923875 | W16: 0 | X16: 0.53772358 | Y16: 0 | Z16: 0.00037045613 | AA16: 4.7841729e-05 | AB16: 0.0052312754 | AC16: 9.0230904e-06 | AD16: 0.0032987623 | AE16: 0.095232533 | AF16: 0.10930375 | AG16: 0.92375779 | AH16: 0.99317013 | AI16: 1 | AJ16: 1 | AK16: 1 | AL16: 1 | AM16: 0 | AN16: 0 | AO16: 09:0-25 | AP16: 0-25 | AQ16: 2.13724e+10 | AR16: 78274 | AS16: 0 | AT16: 40.076125 | AU16: 40.076125 | AV16: 59.923875 | AW16: 59.923875 | AX16: 0
A17: 97 | B17: 0.99054164 | C17: 14.604826 | D17: 10.777818 | E17: 0.013070546 | F17: 0.009458361 | G17: 0 | H17: 3.8802513 | I17: 3.8260683 | J17: -23.149488 | K17: 27.497283 | L17: 14.783174 | M17: 16.760813 | N17: 71.002037 | O17: 62.66057 | P17: 290042.05 | Q17: 270022.6 | R17: 780.65055 | S17: 0 | T17: 0 | U17: 0.12762314 | V17: 0.60434038 | W17: 0 | X17: 0.54144113 | Y17: 0 | Z17: 0.00037040792 | AA17: 5.2756991e-05 | AB17: 0.0052657744 | AC17: 1.1995207e-05 | AD17: 0.003757412 | AE17: 0.096874647 | AF17: 0.10769357 | AG17: 0.91569525 | AH17: 0.99057482 | AI17: 1 | AJ17: 1 | AK17: 1 | AL17: 1 | AM17: 0 | AN17: 0 | AO17: 10-1:25-30 | AP17: 25-30 | AQ17: 2.1784883e+10 | AR17: 80678 | AS17: 0 | AT17: 39.565962 | AU17: 39.565962 | AV17: 60.434038 | AW17: 60.434038 | AX17: 0
A18: 97 | B18: 0.9900634 | C18: 17.054965 | D18: 11.293377 | E18: 0.015461887 | F18: 0.0099366049 | G18: 0 | H18: 3.9333662 | I18: 3.8273207 | J18: -21.054766 | K18: 32.544834 | L18: 14.719492 | M18: 16.945081 | N18: 72.455906 | O18: 63.979812 | P18: 289962.49 | Q18: 271195.83 | R18: 780.30113 | S18: 0 | T18: 0 | U18: 0.13215231 | V18: 0.60288165 | W18: 0 | X18: 0.50110059 | Y18: 0 | Z18: 0.00036949258 | AA18: 5.8408594e-05 | AB18: 0.0052867022 | AC18: 1.4083395e-05 | AD18: 0.0042079037 | AE18: 0.096559649 | AF18: 0.10969443 | AG18: 0.91444607 | AH18: 0.98982817 | AI18: 1 | AJ18: 1 | AK18: 1 | AL18: 1 | AM18: 0 | AN18: 0 | AO18: 10-2:30-35 | AP18: 30-35 | AQ18: 2.3345622e+10 | AR18: 86084 | AS18: 0 | AT18: 39.711835 | AU18: 39.711835 | AV18: 60.288165 | AW18: 60.288165 | AX18: 0
A19: 97 | B19: 0.98956159 | C19: 17.472775 | D19: 11.831396 | E19: 0.01587612 | F19: 0.010438409 | G19: 0 | H19: 3.9887988 | I19: 3.8342699 | J19: -18.859196 | K19: 37.532819 | L19: 14.890849 | M19: 17.238109 | N19: 73.129167 | O19: 64.378678 | P19: 287507.92 | Q19: 268087.65 | R19: 780.22666 | S19: 0 | T19: 0 | U19: 0.14165558 | V19: 0.59860947 | W19: 0 | X19: 0.48035418 | Y19: 0 | Z19: 0.00037065483 | AA19: 6.2691e-05 | AB19: 0.0053581156 | AC19: 1.8733744e-05 | AD19: 0.004628199 | AE19: 0.099074579 | AF19: 0.098689398 | AG19: 0.90334815 | AH19: 0.98636649 | AI19: 1 | AJ19: 1 | AK19: 1 | AL19: 1 | AM19: 0 | AN19: 0 | AO19: 10-3:35-40 | AP19: 35-40 | AQ19: 2.3599756e+10 | AR19: 88030 | AS19: 0 | AT19: 40.139053 | AU19: 40.139053 | AV19: 59.860947 | AW19: 59.860947 | AX19: 0
A20: 97 | B20: 0.98904609 | C20: 19.256804 | D20: 12.380986 | E20: 0.017666787 | F20: 0.010953911 | G20: 0 | H20: 4.0333097 | I20: 3.832988 | J20: -16.933643 | K20: 42.527555 | L20: 15.030478 | M20: 17.424412 | N20: 72.829279 | O20: 64.077189 | P20: 283449.61 | Q20: 265599.94 | R20: 779.89642 | S20: 0 | T20: 0 | U20: 0.14429394 | V20: 0.59294043 | W20: 0 | X20: 0.4624459 | Y20: 0 | Z20: 0.00036993666 | AA20: 6.5548211e-05 | AB20: 0.005443187 | AC20: 2.5274335e-05 | AD20: 0.0050499501 | AE20: 0.10018495 | AF20: 0.1043867 | AG20: 0.89247886 | AH20: 0.9818066 | AI20: 1 | AJ20: 1 | AK20: 1 | AL20: 1 | AM20: 0 | AN20: 0 | AO20: 10-4:40-45 | AP20: 40-45 | AQ20: 2.3903729e+10 | AR20: 89999 | AS20: 0 | AT20: 40.704451 | AU20: 40.704451 | AV20: 59.295549 | AW20: 59.295549 | AX20: 0
A21: 97 | B21: 0.98854525 | C21: 21.38762 | D21: 12.91193 | E21: 0.019853684 | F21: 0.011454745 | G21: 0 | H21: 4.0756897 | I21: 3.8275303 | J21: -14.680369 | K21: 47.487928 | L21: 14.784285 | M21: 17.649351 | N21: 74.412996 | O21: 65.367046 | P21: 289059.93 | Q21: 270029.11 | R21: 779.61414 | S21: 0 | T21: 0 | U21: 0.14711552 | V21: 0.58810781 | W21: 0 | X21: 0.44142328 | Y21: 0 | Z21: 0.00036961207 | AA21: 6.8708407e-05 | AB21: 0.0054225893 | AC21: 3.2519154e-05 | AD21: 0.0055613017 | AE21: 0.10202995 | AF21: 0.097177046 | AG21: 0.88462842 | AH21: 0.97743111 | AI21: 1 | AJ21: 1 | AK21: 1 | AL21: 1 | AM21: 0 | AN21: 0 | AO21: 10:25-50 | AP21: 25-50 | AQ21: 2.5012257e+10 | AR21: 92628 | AS21: 0 | AT21: 41.188502 | AU21: 41.188502 | AV21: 58.811498 | AW21: 58.811498 | AX21: 0
A22: 97 | B22: 0.98797844 | C22: 21.844648 | D22: 13.509266 | E22: 0.020329809 | F22: 0.012021565 | G22: 0 | H22: 4.1162904 | I22: 3.8250034 | J22: -12.697177 | K22: 52.465594 | L22: 15.01716 | M22: 17.858718 | N22: 73.733427 | O22: 64.600006 | P22: 283932.11 | Q22: 265847.61 | R22: 779.4181 | S22: 0 | T22: 0 | U22: 0.14961168 | V22: 0.5771239 | W22: 0 | X22: 0.45869187 | Y22: 0 | Z22: 0.00037027866 | AA22: 6.9688069e-05 | AB22: 0.0054943338 | AC22: 4.4868516e-05 | AD22: 0.0060423809 | AE22: 0.10498919 | AF22: 0.093444582 | AG22: 0.86841661 | AH22: 0.96867738 | AI22: 1 | AJ22: 1 | AK22: 1 | AL22: 1 | AM22: 0 | AN22: 0 | AO22: 11-1:50-55 | AP22: 50-55 | AQ22: 2.339778e+10 | AR22: 88012 | AS22: 0 | AT22: 42.286845 | AU22: 42.286845 | AV22: 57.713155 | AW22: 57.713155 | AX22: 0
A23: 97 | B23: 0.98733231 | C23: 25.082143 | D23: 14.1856 | E23: 0.023777577 | F23: 0.012667694 | G23: 0 | H23: 4.1452802 | I23: 3.811939 | J23: -10.28406 | K23: 57.480826 | L23: 14.438664 | M23: 17.856393 | N23: 74.381849 | O23: 65.11985 | P23: 293108.98 | Q23: 276498.8 | R23: 778.95854 | S23: 0 | T23: 0 | U23: 0.15108265 | V23: 0.57695188 | W23: 0 | X23: 0.46632902 | Y23: 0 | Z23: 0.00036919673 | AA23: 7.2425856e-05 | AB23: 0.0054649508 | AC23: 5.5520356e-05 | AD23: 0.0067055855 | AE23: 0.10656911 | AF23: 0.083564264 | AG23: 0.86605027 | AH23: 0.9624726 | AI23: 1 | AJ23: 1 | AK23: 1 | AL23: 1 | AM23: 0 | AN23: 0 | AO23: 11-2:55-60 | AP23: 55-60 | AQ23: 2.2377877e+10 | AR23: 80933 | AS23: 0 | AT23: 42.304014 | AU23: 42.304014 | AV23: 57.695986 | AW23: 57.695986 | AX23: 0
A24: 97 | B24: 0.98672236 | C24: 25.678761 | D24: 14.819605 | E24: 0.02442781 | F24: 0.013277638 | G24: 0 | H24: 4.1715759 | I24: 3.8064635 | J24: -7.9445009 | K24: 62.390237 | L24: 14.296382 | M24: 18.025439 | N24: 74.543544 | O24: 65.017459 | P24: 297842.77 | Q24: 279246.36 | R24: 778.6258 | S24: 0 | T24: 0 | U24: 0.1655487 | V24: 0.58941463 | W24: 0 | X24: 0.49759965 | Y24: 0 | Z24: 0.00036918747 | AA24: 7.6977537e-05 | AB24: 0.0054438374 | AC24: 6.7859739e-05 | AD24: 0.0073197602 | AE24: 0.11036 | AF24: 0.068871881 | AG24: 0.85240549 | AH24: 0.95461999 | AI24: 1 | AJ24: 1 | AK24: 1 | AL24: 1 | AM24: 0 | AN24: 0 | AO24: 11-3:60-65 | AP24: 60-65 | AQ24: 1.7494505e+10 | AR24: 62649 | AS24: 0 | AT24: 41.055489 | AU24: 41.055489 | AV24: 58.944511 | AW24: 58.944511 | AX24: 0
A25: 97 | B25: 0.98614148 | C25: 25.732334 | D25: 15.419403 | E25: 0.024486431 | F25: 0.013858515 | G25: 0 | H25: 4.2076933 | I25: 3.8090937 | J25: -5.0515423 | K25: 67.437798 | L25: 14.773111 | M25: 18.14047 | N25: 75.050091 | O25: 65.386412 | P25: 287814.41 | Q25: 270237.23 | R25: 777.84026 | S25: 0 | T25: 0 | U25: 0.17876355 | V25: 0.59239971 | W25: 0 | X25: 0.51347696 | Y25: 0 | Z25: 0.0003685446 | AA25: 8.2212533e-05 | AB25: 0.0055341895 | AC25: 7.917242e-05 | AD25: 0.0077943809 | AE25: 0.11240211 | AF25: 0.071716434 | AG25: 0.83279078 | AH25: 0.94929456 | AI25: 1 | AJ25: 1 | AK25: 1 | AL25: 1 | AM25: 0 | AN25: 0 | AO25: 11-4:65-70 | AP25: 65-70 | AQ25: 1.3415387e+10 | AR25: 49643 | AS25: 0 | AT25: 40.760029 | AU25: 40.760029 | AV25: 59.239971 | AW25: 59.239971 | AX25: 0
A26: 97 | B26: 0.98548019 | C26: 28.913425 | D26: 16.097522 | E26: 0.028038717 | F26: 0.014519809 | G26: 0 | H26: 4.2395864 | I26: 3.8105994 | J26: -2.3814145 | K26: 72.406061 | L26: 14.570543 | M26: 18.278509 | N26: 77.971379 | O26: 67.791666 | P26: 291264.86 | Q26: 274004.12 | R26: 777.26793 | S26: 0 | T26: 0 | U26: 0.17551211 | V26: 0.57909797 | W26: 0 | X26: 0.49760423 | Y26: 0 | Z26: 0.00036876269 | AA26: 8.875363e-05 | AB26: 0.0055168837 | AC26: 8.5784378e-05 | AD26: 0.0084596096 | AE26: 0.11453738 | AF26: 0.059446717 | AG26: 0.82399413 | AH26: 0.94859901 | AI26: 1 | AJ26: 1 | AK26: 1 | AL26: 1 | AM26: 0 | AN26: 0 | AO26: 11:50-75 | AP26: 50-75 | AQ26: 1.1261843e+10 | AR26: 41101 | AS26: 0 | AT26: 42.090203 | AU26: 42.090203 | AV26: 57.909797 | AW26: 57.909797 | AX26: 0
... A32: 97 | B32: 0.96171818 | C32: 94.051204 | D32: 37.40006 | E32: 0.20955967 | F32: 0.038281819 | G32: 0 | H32: 5.1176123 | I32: 3.8034605 | J32: 72.032955 | K32: 203.70254 | L32: 15.29575 | M32: 22.005306 | N32: 91.060496 | O32: 74.911131 | P32: 287554.11 | Q32: 261070.33 | R32: 771.00948 | S32: 0 | T32: 0 | U32: 0.063892119 | V32: 0.6831468 | W32: 0 | X32: 0.351038 | Y32: 0 | Z32: 0.00036019193 | AA32: 0.00057121596 | AB32: 0.0062610961 | AC32: 0.0012560033 | AD32: 0.029833294 | AE32: 0.18245448 | AF32: 0 | AG32: 0.18677956 | AH32: 0.55165766 | AI32: 1 | AJ32: 1 | AK32: 1 | AL32: 1 | AM32: 0 | AN32: 0 | AO32: 17:200-225 | AP32: 200-225 | AQ32: 3916055 | AR32: 15 | AS32: 0 | AT32: 31.68532 | AU32: 31.68532 | AV32: 68.31468 | AW32: 68.31468 | AX32: 0
F36: high media
A37: modelId | B37: SFACTOR_PREPAY_TRACKING_CPR | C37: PREPAY_CPR1 | D37: PREPAY_TRACKING_CPR1 | E37: PREPAY_SMM1 | F37: PREPAY_TRACKING_SMM1 | G37: PCT_LOANTYPE | H37: _ORIGNOTERATE | I37: _ZEROSATO | J37: _SATO | K37: _REFI_INCENTIVE_Fixed | L37: _Fixed_cost | M37: _LOANAGE | N37: _LTV | O37: _CLTV | P37: _AVG_LOANSIZE_SCHAMBALANCE | Q37: _WACLS | R37: _FICO | S37: PCT_ISSECONDLIEN | T37: _OrigCombLTV | U37: PCT_SVC | V37: PCT_TPO | W37: PCT_GEO | X37: PCT_LOANPURPOSE | Y37: PCT_OCC | Z37: curtailsmm | AA37: defaultsmm | AB37: toverSmm | AC37: cashoutSmm | AD37: refiSmm | AE37: cumHPA | AF37: cumHPA05Pct | AG37: cumHPA15Pct | AH37: cumHPA20Pct | AI37: cumHPA25Pct | AJ37: cumHPA30Pct | AK37: cumHPA35Pct | AL37: cumHPA40Pct | AM37: adjtoverSmm | AN37: adjRefiSmm | AO37: groupByColumn | AP37: curve | AQ37: Balance | AR37: LoanCount | AS37: PCT_BROKER | AT37: PCT_CORRES | AU37: PCT_NonRETAIL | AV37: PCT_RETAIL | AW37: PCT_CashWindow | AX37: PCT_NonCashWindow
A38: 96 | B38: 0.98839691 | C38: 96.635073 | D38: 13.068622 | E38: 0.24621417 | F38: 0.011603087 | G38: 0 | H38: 3.4287964 | I38: 3.9170498 | J38: -60.571903 | K38: -108.57802 | L38: 100 | M38: 13.372006 | N38: 76.773096 | O38: 12.785692 | P38: 34194.875 | Q38: 31481.298 | R38: 792.65593 | S38: 0 | T38: 0 | U38: 0.060023573 | V38: 0.43037133 | W38: 0 | X38: 0.060023573 | Y38: 0 | Z38: 0.0055161513 | AA38: 1.2412019e-05 | AB38: 0.0060745137 | AC38: 0 | AD38: 0 | AE38: 0.059792222 | AF38: 0.39695938 | AG38: 1 | AH38: 1 | AI38: 1 | AJ38: 1 | AK38: 1 | AL38: 1 | AM38: 0 | AN38: 0 | AO38: 04:-125--100 | AP38: =-125--100 -> -25 | AQ38: 188887.79 | AR38: 6 | AS38: 0 | AT38: 56.962867 | AU38: 56.962867 | AV38: 43.037133 | AW38: 43.037133 | AX38: 0
A39: 96 | B39: 0.98826771 | C39: 49.843412 | D39: 13.204884 | E39: 0.055879709 | F39: 0.011732287 | G39: 0 | H39: 3.4420778 | I39: 3.9164769 | J39: -59.517626 | K39: -81.597641 | L39: 68.465589 | M39: 14.548948 | N39: 71.385986 | O39: 24.934341 | P39: 117969.24 | Q39: 40852.783 | R39: 786.04463 | S39: 0 | T39: 0 | U39: 0.027485084 | V39: 0.68664472 | W39: 0 | X39: 0.058346254 | Y39: 0 | Z39: 0.0043983283 | AA39: 3.4939807e-05 | AB39: 0.007099851 | AC39: 3.07944e-06 | AD39: 0.00019607821 | AE39: 0.092113583 | AF39: 0.20636363 | AG39: 0.92741588 | AH39: 1 | AI39: 1 | AJ39: 1 | AK39: 1 | AL39: 1 | AM39: 0 | AN39: 0 | AO39: 05:-100--75 | AP39: =-100--75 -> -25 | AQ39: 6005359.1 | AR39: 147 | AS39: 0 | AT39: 31.335528 | AU39: 31.335528 | AV39: 68.664472 | AW39: 68.664472 | AX39: 0
A40: 96 | B40: 0.99029962 | C40: 38.81742 | D40: 11.039063 | E40: 0.040115492 | F40: 0.0097003799 | G40: 0 | H40: 3.4962707 | I40: 3.8952664 | J40: -53.707825 | K40: -57.582086 | L40: 45.414254 | M40: 15.142775 | N40: 73.296276 | O40: 43.30325 | P40: 173908.24 | Q40: 63191.424 | R40: 782.07674 | S40: 0 | T40: 0 | U40: 0.054816654 | V40: 0.72447447 | W40: 0 | X40: 0.21958318 | Y40: 0 | Z40: 0.0023777527 | AA40: 3.843875e-05 | AB40: 0.0061975188 | AC40: 2.517301e-06 | AD40: 0.0010841412 | AE40: 0.087867306 | AF40: 0.19207694 | AG40: 0.95406742 | AH40: 0.99472364 | AI40: 1 | AJ40: 1 | AK40: 1 | AL40: 1 | AM40: 0 | AN40: 0 | AO40: 06:-75--50 | AP40: =-75--50 -> -25 | AQ40: 43286126 | AR40: 685 | AS40: 0 | AT40: 27.552553 | AU40: 27.552553 | AV40: 72.447447 | AW40: 72.447447 | AX40: 0
A41: 96 | B41: 0.99020777 | C41: 9.3616256 | D41: 11.138029 | E41: 0.0081575869 | F41: 0.0097922328 | G41: 0 | H41: 3.4645783 | I41: 3.9281772 | J41: -54.768892 | K41: -31.153905 | L41: 18.985438 | M41: 14.446285 | N41: 73.016693 | O41: 63.087717 | P41: 251793.26 | Q41: 201489.6 | R41: 781.12105 | S41: 0 | T41: 0 | U41: 0.05384346 | V41: 0.61549503 | W41: 0 | X41: 0.51591271 | Y41: 0 | Z41: 0.00053383381 | AA41: 3.2372878e-05 | AB41: 0.0050501465 | AC41: 9.784867e-07 | AD41: 0.0041748865 | AE41: 0.08095162 | AF41: 0.19860855 | AG41: 0.95610793 | AH41: 0.99846457 | AI41: 1 | AJ41: 1 | AK41: 1 | AL41: 1 | AM41: 0 | AN41: 0 | AO41: 07:-50--25 | AP41: =-50--25 -> -25 | AQ41: 1.3604578e+09 | AR41: 6752 | AS41: 0 | AT41: 38.450497 | AU41: 38.450497 | AV41: 61.549503 | AW41: 61.549503 | AX41: 0
A42: 96 | B42: 0.98750826 | C42: 7.416952 | D42: 14.001907 | E42: 0.0064014336 | F42: 0.012491744 | G42: 0 | H42: 3.524119 | I42: 3.9299141 | J42: -48.414066 | K42: -22.221985 | L42: 16.498899 | M42: 14.36346 | N42: 73.1865 | O42: 65.100598 | P42: 268436.49 | Q42: 239394.87 | R42: 780.93529 | S42: 0 | T42: 0 | U42: 0.068865837 | V42: 0.6104547 | W42: 0 | X42: 0.5618934 | Y42: 0 | Z42: 0.00040143177 | AA42: 3.2732743e-05 | AB42: 0.0049308652 | AC42: 7.3330338e-07 | AD42: 0.007125967 | AE42: 0.08062327 | AF42: 0.16681883 | AG42: 0.96699982 | AH42: 0.99933097 | AI42: 1 | AJ42: 1 | AK42: 1 | AL42: 1 | AM42: 0 | AN42: 0 | AO42: 08-1:-25--20 | AP42: =-25--20 -> -5 | AQ42: 1.5658819e+09 | AR42: 6541 | AS42: 0 | AT42: 38.95453 | AU42: 38.95453 | AV42: 61.04547 | AW42: 61.04547 | AX42: 0
A43: 96 | B43: 0.98587441 | C43: 4.8879394 | D43: 15.693878 | E43: 0.0041674922 | F43: 0.014125593 | G43: 0 | H43: 3.5557883 | I43: 3.9208747 | J43: -45.581681 | K43: -17.210662 | L43: 15.961582 | M43: 14.483489 | N43: 71.60487 | O43: 63.81283 | P43: 272723.21 | Q43: 249028.12 | R43: 781.78181 | S43: 0 | T43: 0 | U43: 0.078276983 | V43: 0.60553234 | W43: 0 | X43: 0.54899391 | Y43: 0 | Z43: 0.00038737513 | AA43: 3.3488465e-05 | AB43: 0.0050609118 | AC43: 9.2107342e-07 | AD43: 0.0086428822 | AE43: 0.082238649 | AF43: 0.16530941 | AG43: 0.96394511 | AH43: 0.99885027 | AI43: 1 | AJ43: 1 | AK43: 1 | AL43: 1 | AM43: 0 | AN43: 0 | AO43: 08-2:-20--15 | AP43: =-20--15 -> -5 | AQ43: 2.7221264e+09 | AR43: 10931 | AS43: 0 | AT43: 39.446766 | AU43: 39.446766 | AV43: 60.553234 | AW43: 60.553234 | AX43: 0
A44: 96 | B44: 0.98462513 | C44: 8.259733 | D44: 16.966955 | E44: 0.0071583219 | F44: 0.015374875 | G44: 0 | H44: 3.5954185 | I44: 3.9147199 | J44: -41.886543 | K44: -12.281778 | L44: 15.428091 | M44: 14.550842 | N44: 72.17644 | O44: 64.441153 | P44: 279936.8 | Q44: 258280.9 | R44: 781.46676 | S44: 0 | T44: 0 | U44: 0.087735292 | V44: 0.60964009 | W44: 0 | X44: 0.54254679 | Y44: 0 | Z44: 0.00037560677 | AA44: 3.3985792e-05 | AB44: 0.0050442272 | AC44: 1.084469e-06 | AD44: 0.009919956 | AE44: 0.083439747 | AF44: 0.14859681 | AG44: 0.96165329 | AH44: 0.99909455 | AI44: 1 | AJ44: 1 | AK44: 1 | AL44: 1 | AM44: 0 | AN44: 0 | AO44: 08-3:-15--10 | AP44: =-15--10 -> -5 | AQ44: 4.5837111e+09 | AR44: 17747 | AS44: 0 | AT44: 39.035991 | AU44: 39.035991 | AV44: 60.964009 | AW44: 60.964009 | AX44: 0
A45: 96 | B45: 0.98330492 | C45: 7.9191916 | D45: 18.29314 | E45: 0.0068517227 | F45: 0.016695085 | G45: 0 | H45: 3.6231364 | I45: 3.8984104 | J45: -39.585383 | K45: -7.4062628 | L45: 15.296341 | M45: 14.911876 | N45: 71.109777 | O45: 63.291883 | P45: 281675.24 | Q45: 260533.88 | R45: 781.48996 | S45: 0 | T45: 0 | U45: 0.091236558 | V45: 0.60130514 | W45: 0 | X45: 0.55636662 | Y45: 0 | Z45: 0.00037442918 | AA45: 3.4860008e-05 | AB45: 0.0051831359 | AC45: 1.5032299e-06 | AD45: 0.011101142 | AE45: 0.086115169 | AF45: 0.14110782 | AG45: 0.95021425 | AH45: 0.99893123 | AI45: 1 | AJ45: 1 | AK45: 1 | AL45: 1 | AM45: 0 | AN45: 0 | AO45: 08-4:-10--5 | AP45: =-10--5 -> -5 | AQ45: 6.6326715e+09 | AR45: 25458 | AS45: 0 | AT45: 39.869486 | AU45: 39.869486 | AV45: 60.130514 | AW45: 60.130514 | AX45: 0
A46: 96 | B46: 0.98219018 | C46: 8.6514849 | D46: 19.397773 | E46: 0.0075123203 | F46: 0.017809822 | G46: 0 | H46: 3.6551722 | I46: 3.8826854 | J46: -36.811228 | K46: -2.3916674 | L46: 15.050831 | M46: 15.210302 | N46: 71.233243 | O46: 63.416485 | P46: 286027.38 | Q46: 264953.55 | R46: 781.41774 | S46: 0 | T46: 0 | U46: 0.092835681 | V46: 0.59536817 | W46: 0 | X46: 0.56119432 | Y46: 0 | Z46: 0.00037069367 | AA46: 3.581818e-05 | AB46: 0.0051417377 | AC46: 1.8486999e-06 | AD46: 0.012259709 | AE46: 0.087190228 | AF46: 0.13675479 | AG46: 0.95105333 | AH46: 0.99888108 | AI46: 1 | AJ46: 1 | AK46: 1 | AL46: 1 | AM46: 0 | AN46: 0 | AO46: 08:-25-0 | AP46: =-25-0 -> -25 | AQ46: 9.7982474e+09 | AR46: 36981 | AS46: 0 | AT46: 40.463183 | AU46: 40.463183 | AV46: 59.536817 | AW46: 59.536817 | AX46: 0
A47: 96 | B47: 0.98105311 | C47: 9.6587779 | D47: 20.510416 | E47: 0.0084289694 | F47: 0.01894689 | G47: 0 | H47: 3.6936876 | I47: 3.8737928 | J47: -33.806205 | K47: 2.6121767 | L47: 15.059416 | M47: 15.398367 | N47: 71.20197 | O47: 63.30499 | P47: 284835.16 | Q47: 264994.1 | R47: 781.44475 | S47: 0 | T47: 0 | U47: 0.099676388 | V47: 0.6006954 | W47: 0 | X47: 0.56479509 | Y47: 0 | Z47: 0.0003703554 | AA47: 3.6686619e-05 | AB47: 0.0052090767 | AC47: 3.0870021e-06 | AD47: 0.01332767 | AE47: 0.089425468 | AF47: 0.1246349 | AG47: 0.94265683 | AH47: 0.99742834 | AI47: 1 | AJ47: 1 | AK47: 1 | AL47: 1 | AM47: 0 | AN47: 0 | AO47: 09-1:0-5 | AP47: 0-5 | AQ47: 1.2626439e+10 | AR47: 47648 | AS47: 0 | AT47: 39.93046 | AU47: 39.93046 | AV47: 60.06954 | AW47: 60.06954 | AX47: 0
A48: 96 | B48: 0.97970182 | C48: 11.895024 | D48: 21.814361 | E48: 0.010497939 | F48: 0.020298177 | G48: 0 | H48: 3.7178014 | I48: 3.8530514 | J48: -32.195354 | K48: 7.6142859 | L48: 14.558583 | M48: 15.821745 | N48: 70.946759 | O48: 62.934601 | P48: 293115.39 | Q48: 274145.15 | R48: 781.38453 | S48: 0 | T48: 0 | U48: 0.1010385 | V48: 0.60196444 | W48: 0 | X48: 0.55814045 | Y48: 0 | Z48: 0.00037043941 | AA48: 3.8612944e-05 | AB48: 0.0052327257 | AC48: 4.0688358e-06 | AD48: 0.014652316 | AE48: 0.091144609 | AF48: 0.12017603 | AG48: 0.93715128 | AH48: 0.99640248 | AI48: 1 | AJ48: 1 | AK48: 1 | AL48: 1 | AM48: 0 | AN48: 0 | AO48: 09-2:5-10 | AP48: 43230 | AQ48: 1.600432e+10 | AR48: 58379 | AS48: 0 | AT48: 39.803556 | AU48: 39.803556 | AV48: 60.196444 | AW48: 60.196444 | AX48: 0
A49: 96 | B49: 0.97859541 | C49: 13.619226 | D49: 22.867381 | E49: 0.012126299 | F49: 0.021404593 | G49: 0 | H49: 3.7551712 | I49: 3.8414164 | J49: -29.577044 | K49: 12.555816 | L49: 14.66393 | M49: 16.07843 | N49: 70.781193 | O49: 62.654426 | P49: 292854.45 | Q49: 272182.21 | R49: 781.20433 | S49: 0 | T49: 0 | U49: 0.11061444 | V49: 0.5989312 | W49: 0 | X49: 0.57020664 | Y49: 0 | Z49: 0.00037059973 | AA49: 4.1935797e-05 | AB49: 0.005219016 | AC49: 5.8672202e-06 | AD49: 0.01576716 | AE49: 0.093267643 | AF49: 0.11238082 | AG49: 0.92893431 | AH49: 0.99520282 | AI49: 1 | AJ49: 1 | AK49: 1 | AL49: 1 | AM49: 0 | AN49: 0 | AO49: 09-3:10-15 | AP49: 43388 | AQ49: 1.7351616e+10 | AR49: 63750 | AS49: 0 | AT49: 40.10688 | AU49: 40.10688 | AV49: 59.89312 | AW49: 59.89312 | AX49: 0
A50: 96 | B50: 0.97748281 | C50: 12.96156 | D50: 23.913156 | E50: 0.011501704 | F50: 0.022517185 | G50: 0 | H50: 3.793177 | I50: 3.8307621 | J50: -27.475239 | K50: 17.559079 | L50: 14.863894 | M50: 16.339959 | N50: 70.435491 | O50: 62.357252 | P50: 287175.28 | Q50: 268515.14 | R50: 781.17369 | S50: 0 | T50: 0 | U50: 0.11020424 | V50: 0.59692517 | W50: 0 | X50: 0.55869535 | Y50: 0 | Z50: 0.00037026406 | AA50: 4.4001409e-05 | AB50: 0.0052680609 | AC50: 7.3344628e-06 | AD50: 0.01682751 | AE50: 0.093673786 | AF50: 0.1216746 | AG50: 0.92555841 | AH50: 0.99393651 | AI50: 1 | AJ50: 1 | AK50: 1 | AL50: 1 | AM50: 0 | AN50: 0 | AO50: 09-4:15-20 | AP50: 15-20 | AQ50: 1.900926e+10 | AR50: 70794 | AS50: 0 | AT50: 40.307483 | AU50: 40.307483 | AV50: 59.692517 | AW50: 59.692517 | AX50: 0
A51: 96 | B51: 0.97607821 | C51: 14.637116 | D51: 25.214844 | E51: 0.013101649 | F51: 0.023921791 | G51: 0 | H51: 3.8324935 | I51: 3.8215182 | J51: -25.058838 | K51: 22.492715 | L51: 14.619027 | M51: 16.595066 | N51: 72.560471 | O51: 64.111066 | P51: 291993.22 | Q51: 273045.97 | R51: 780.70105 | S51: 0 | T51: 0 | U51: 0.11739366 | V51: 0.59923875 | W51: 0 | X51: 0.53772358 | Y51: 0 | Z51: 0.00037045613 | AA51: 4.7841729e-05 | AB51: 0.0052312754 | AC51: 9.0230904e-06 | AD51: 0.01826318 | AE51: 0.095232533 | AF51: 0.10930375 | AG51: 0.92375779 | AH51: 0.99317013 | AI51: 1 | AJ51: 1 | AK51: 1 | AL51: 1 | AM51: 0 | AN51: 0 | AO51: 09:0-25 | AP51: 0-25 | AQ51: 2.13724e+10 | AR51: 78274 | AS51: 0 | AT51: 40.076125 | AU51: 40.076125 | AV51: 59.923875 | AW51: 59.923875 | AX51: 0
A52: 96 | B52: 0.97456952 | C52: 14.604826 | D52: 26.590227 | E52: 0.013070546 | F52: 0.025430483 | G52: 0 | H52: 3.8802513 | I52: 3.8260683 | J52: -23.149488 | K52: 27.497283 | L52: 14.783174 | M52: 16.760813 | N52: 71.002037 | O52: 62.66057 | P52: 290042.05 | Q52: 270022.6 | R52: 780.65055 | S52: 0 | T52: 0 | U52: 0.12762314 | V52: 0.60434038 | W52: 0 | X52: 0.54144113 | Y52: 0 | Z52: 0.00037040792 | AA52: 5.2756991e-05 | AB52: 0.0052657744 | AC52: 1.1995207e-05 | AD52: 0.019729534 | AE52: 0.096874647 | AF52: 0.10769357 | AG52: 0.91569525 | AH52: 0.99057482 | AI52: 1 | AJ52: 1 | AK52: 1 | AL52: 1 | AM52: 0 | AN52: 0 | AO52: 10-1:25-30 | AP52: 25-30 | AQ52: 2.1784883e+10 | AR52: 80678 | AS52: 0 | AT52: 39.565962 | AU52: 39.565962 | AV52: 60.434038 | AW52: 60.434038 | AX52: 0
A53: 96 | B53: 0.97308134 | C53: 17.054965 | D53: 27.924156 | E53: 0.015461887 | F53: 0.02691866 | G53: 0 | H53: 3.9333662 | I53: 3.8273207 | J53: -21.054766 | K53: 32.544834 | L53: 14.719492 | M53: 16.945081 | N53: 72.455906 | O53: 63.979812 | P53: 289962.49 | Q53: 271195.83 | R53: 780.30113 | S53: 0 | T53: 0 | U53: 0.13215231 | V53: 0.60288165 | W53: 0 | X53: 0.50110059 | Y53: 0 | Z53: 0.00036949258 | AA53: 5.8408594e-05 | AB53: 0.0052867022 | AC53: 1.4083395e-05 | AD53: 0.021189958 | AE53: 0.096559649 | AF53: 0.10969443 | AG53: 0.91444607 | AH53: 0.98982817 | AI53: 1 | AJ53: 1 | AK53: 1 | AL53: 1 | AM53: 0 | AN53: 0 | AO53: 10-2:30-35 | AP53: 30-35 | AQ53: 2.3345622e+10 | AR53: 86084 | AS53: 0 | AT53: 39.711835 | AU53: 39.711835 | AV53: 60.288165 | AW53: 60.288165 | AX53: 0
A54: 96 | B54: 0.97160054 | C54: 17.472775 | D54: 29.229387 | E54: 0.01587612 | F54: 0.028399462 | G54: 0 | H54: 3.9887988 | I54: 3.8342699 | J54: -18.859196 | K54: 37.532819 | L54: 14.890849 | M54: 17.238109 | N54: 73.129167 | O54: 64.378678 | P54: 287507.92 | Q54: 268087.65 | R54: 780.22666 | S54: 0 | T54: 0 | U54: 0.14165558 | V54: 0.59860947 | W54: 0 | X54: 0.48035418 | Y54: 0 | Z54: 0.00037065483 | AA54: 6.2691e-05 | AB54: 0.0053581156 | AC54: 1.8733744e-05 | AD54: 0.022589252 | AE54: 0.099074579 | AF54: 0.098689398 | AG54: 0.90334815 | AH54: 0.98636649 | AI54: 1 | AJ54: 1 | AK54: 1 | AL54: 1 | AM54: 0 | AN54: 0 | AO54: 10-3:35-40 | AP54: 35-40 | AQ54: 2.3599756e+10 | AR54: 88030 | AS54: 0 | AT54: 40.139053 | AU54: 40.139053 | AV54: 59.860947 | AW54: 59.860947 | AX54: 0
A55: 96 | B55: 0.97008146 | C55: 19.256804 | D55: 30.545808 | E55: 0.017666787 | F55: 0.029918539 | G55: 0 | H55: 4.0333097 | I55: 3.832988 | J55: -16.933643 | K55: 42.527555 | L55: 15.030478 | M55: 17.424412 | N55: 72.829279 | O55: 64.077189 | P55: 283449.61 | Q55: 265599.94 | R55: 779.89642 | S55: 0 | T55: 0 | U55: 0.14429394 | V55: 0.59294043 | W55: 0 | X55: 0.4624459 | Y55: 0 | Z55: 0.00036993666 | AA55: 6.5548211e-05 | AB55: 0.005443187 | AC55: 2.5274335e-05 | AD55: 0.024014578 | AE55: 0.10018495 | AF55: 0.1043867 | AG55: 0.89247886 | AH55: 0.9818066 | AI55: 1 | AJ55: 1 | AK55: 1 | AL55: 1 | AM55: 0 | AN55: 0 | AO55: 10-4:40-45 | AP55: 40-45 | AQ55: 2.3903729e+10 | AR55: 89999 | AS55: 0 | AT55: 40.704451 | AU55: 40.704451 | AV55: 59.295549 | AW55: 59.295549 | AX55: 0
A56: 96 | B56: 0.96827652 | C56: 21.38762 | D56: 32.080766 | E56: 0.019853684 | F56: 0.031723485 | G56: 0 | H56: 4.0756897 | I56: 3.8275303 | J56: -14.680369 | K56: 47.487928 | L56: 14.784285 | M56: 17.649351 | N56: 74.412996 | O56: 65.367046 | P56: 289059.93 | Q56: 270029.11 | R56: 779.61414 | S56: 0 | T56: 0 | U56: 0.14711552 | V56: 0.58810781 | W56: 0 | X56: 0.44142328 | Y56: 0 | Z56: 0.00036961207 | AA56: 6.8708407e-05 | AB56: 0.0054225893 | AC56: 3.2519154e-05 | AD56: 0.025830041 | AE56: 0.10202995 | AF56: 0.097177046 | AG56: 0.88462842 | AH56: 0.97743111 | AI56: 1 | AJ56: 1 | AK56: 1 | AL56: 1 | AM56: 0 | AN56: 0 | AO56: 10:25-50 | AP56: 25-50 | AQ56: 2.5012257e+10 | AR56: 92628 | AS56: 0 | AT56: 41.188502 | AU56: 41.188502 | AV56: 58.811498 | AW56: 58.811498 | AX56: 0
A57: 96 | B57: 0.96659665 | C57: 21.844648 | D57: 33.48135 | E57: 0.020329809 | F57: 0.03340335 | G57: 0 | H57: 4.1162904 | I57: 3.8250034 | J57: -12.697177 | K57: 52.465594 | L57: 15.01716 | M57: 17.858718 | N57: 73.733427 | O57: 64.600006 | P57: 283932.11 | Q57: 265847.61 | R57: 779.4181 | S57: 0 | T57: 0 | U57: 0.14961168 | V57: 0.5771239 | W57: 0 | X57: 0.45869187 | Y57: 0 | Z57: 0.00037027866 | AA57: 6.9688069e-05 | AB57: 0.0054943338 | AC57: 4.4868516e-05 | AD57: 0.027424166 | AE57: 0.10498919 | AF57: 0.093444582 | AG57: 0.86841661 | AH57: 0.96867738 | AI57: 1 | AJ57: 1 | AK57: 1 | AL57: 1 | AM57: 0 | AN57: 0 | AO57: 11-1:50-55 | AP57: 50-55 | AQ57: 2.339778e+10 | AR57: 88012 | AS57: 0 | AT57: 42.286845 | AU57: 42.286845 | AV57: 57.713155 | AW57: 57.713155 | AX57: 0
A58: 96 | B58: 0.96432906 | C58: 25.082143 | D58: 35.32997 | E58: 0.023777577 | F58: 0.035670938 | G58: 0 | H58: 4.1452802 | I58: 3.811939 | J58: -10.28406 | K58: 57.480826 | L58: 14.438664 | M58: 17.856393 | N58: 74.381849 | O58: 65.11985 | P58: 293108.98 | Q58: 276498.8 | R58: 778.95854 | S58: 0 | T58: 0 | U58: 0.15108265 | V58: 0.57695188 | W58: 0 | X58: 0.46632902 | Y58: 0 | Z58: 0.00036919673 | AA58: 7.2425856e-05 | AB58: 0.0054649508 | AC58: 5.5520356e-05 | AD58: 0.029708829 | AE58: 0.10656911 | AF58: 0.083564264 | AG58: 0.86605027 | AH58: 0.9624726 | AI58: 1 | AJ58: 1 | AK58: 1 | AL58: 1 | AM58: 0 | AN58: 0 | AO58: 11-2:55-60 | AP58: 55-60 | AQ58: 2.2377877e+10 | AR58: 80933 | AS58: 0 | AT58: 42.304014 | AU58: 42.304014 | AV58: 57.695986 | AW58: 57.695986 | AX58: 0
A59: 96 | B59: 0.96240407 | C59: 25.678761 | D59: 36.862204 | E59: 0.02442781 | F59: 0.037595929 | G59: 0 | H59: 4.1715759 | I59: 3.8064635 | J59: -7.9445009 | K59: 62.390237 | L59: 14.296382 | M59: 18.025439 | N59: 74.543544 | O59: 65.017459 | P59: 297842.77 | Q59: 279246.36 | R59: 778.6258 | S59: 0 | T59: 0 | U59: 0.1655487 | V59: 0.58941463 | W59: 0 | X59: 0.49759965 | Y59: 0 | Z59: 0.00036918747 | AA59: 7.6977537e-05 | AB59: 0.0054438374 | AC59: 6.7859739e-05 | AD59: 0.031638052 | AE59: 0.11036 | AF59: 0.068871881 | AG59: 0.85240549 | AH59: 0.95461999 | AI59: 1 | AJ59: 1 | AK59: 1 | AL59: 1 | AM59: 0 | AN59: 0 | AO59: 11-3:60-65 | AP59: 60-65 | AQ59: 1.7494505e+10 | AR59: 62649 | AS59: 0 | AT59: 41.055489 | AU59: 41.055489 | AV59: 58.944511 | AW59: 58.944511 | AX59: 0
A60: 96 | B60: 0.96112263 | C60: 25.732334 | D60: 37.863662 | E60: 0.024486431 | F60: 0.038877367 | G60: 0 | H60: 4.2076933 | I60: 3.8090937 | J60: -5.0515423 | K60: 67.437798 | L60: 14.773111 | M60: 18.14047 | N60: 75.050091 | O60: 65.386412 | P60: 287814.41 | Q60: 270237.23 | R60: 777.84026 | S60: 0 | T60: 0 | U60: 0.17876355 | V60: 0.59239971 | W60: 0 | X60: 0.51347696 | Y60: 0 | Z60: 0.0003685446 | AA60: 8.2212533e-05 | AB60: 0.0055341895 | AC60: 7.917242e-05 | AD60: 0.032813233 | AE60: 0.11240211 | AF60: 0.071716434 | AG60: 0.83279078 | AH60: 0.94929456 | AI60: 1 | AJ60: 1 | AK60: 1 | AL60: 1 | AM60: 0 | AN60: 0 | AO60: 11-4:65-70 | AP60: 65-70 | AQ60: 1.3415387e+10 | AR60: 49643 | AS60: 0 | AT60: 40.760029 | AU60: 40.760029 | AV60: 59.239971 | AW60: 59.239971 | AX60: 0
A61: 96 | B61: 0.95927331 | C61: 28.913425 | D61: 39.283279 | E61: 0.028038717 | F61: 0.040726695 | G61: 0 | H61: 4.2395864 | I61: 3.8105994 | J61: -2.3814145 | K61: 72.406061 | L61: 14.570543 | M61: 18.278509 | N61: 77.971379 | O61: 67.791666 | P61: 291264.86 | Q61: 274004.12 | R61: 777.26793 | S61: 0 | T61: 0 | U61: 0.17551211 | V61: 0.57909797 | W61: 0 | X61: 0.49760423 | Y61: 0 | Z61: 0.00036876269 | AA61: 8.875363e-05 | AB61: 0.0055168837 | AC61: 8.5784378e-05 | AD61: 0.034666495 | AE61: 0.11453738 | AF61: 0.059446717 | AG61: 0.82399413 | AH61: 0.94859901 | AI61: 1 | AJ61: 1 | AK61: 1 | AL61: 1 | AM61: 0 | AN61: 0 | AO61: 11:50-75 | AP61: 50-75 | AQ61: 1.1261843e+10 | AR61: 41101 | AS61: 0 | AT61: 42.090203 | AU61: 42.090203 | AV61: 57.909797 | AW61: 57.909797 | AX61: 0
... A67: 96 | B67: 0.94546126 | C67: 94.051204 | D67: 48.981833 | E67: 0.20955967 | F67: 0.054538742 | G67: 0 | H67: 5.1176123 | I67: 3.8034605 | J67: 72.032955 | K67: 203.70254 | L67: 15.29575 | M67: 22.005306 | N67: 91.060496 | O67: 74.911131 | P67: 287554.11 | Q67: 261070.33 | R67: 771.00948 | S67: 0 | T67: 0 | U67: 0.063892119 | V67: 0.6831468 | W67: 0 | X67: 0.351038 | Y67: 0 | Z67: 0.00036019193 | AA67: 0.00057121596 | AB67: 0.0062610961 | AC67: 0.0012560033 | AD67: 0.046090215 | AE67: 0.18245448 | AF67: 0 | AG67: 0.18677956 | AH67: 0.55165766 | AI67: 1 | AJ67: 1 | AK67: 1 | AL67: 1 | AM67: 0 | AN67: 0 | AO67: 17:200-225 | AP67: 200-225 | AQ67: 3916055 | AR67: 15 | AS67: 0 | AT67: 31.68532 | AU67: 31.68532 | AV67: 68.31468 | AW67: 68.31468 | AX67: 0
O69: pct high media | P69: pct low media
K70: turn | L70: cash | M70: refi | O70: 0.4 | P70: =1-O70 -> 0.6
A71: incentive | B71: =AQ2 -> Balance | C71: =AO2 -> groupByColumn | D71: =E2 -> PREPAY_SMM1 | E71: =F2 -> PREPAY_TRACKING_SMM1 | F71: ratio | G71: =C2 -> PREPAY_CPR1 | H71: =D2 -> PREPAY_TRACKING_CPR1 | I71: high media cpr | K71: adj | L71: adj | M71: adj | O71: high media refi | P71: low media refi | Q71: interpolate refi | S71: mdl_smm | T71: mdl_cpr | U71: ratio
A72: =K3 -> -108.57802 | B72: =AQ3/1000000000 -> 0.00018888779 | C72: =AO3 -> 04:-125--100 | D72: =E3 -> 0.24621417 | E72: =Z3+AA3+AB3+AC3+AD3 -> 0.011603077 | F72: =D72/E72 -> 21.21973 | G72: =(1-(1-D72)^12)*100 -> 96.635073 | H72: =(1-(1-E72)^12)*100 -> 13.068611 | I72: =(1-(1-SUM(Z38,AA38,AB38,AC38,AD38*M72))^12)*100 -> 13.068611 | K72: =VLOOKUP($C72,'Refi Adj'!$B$2:$E$32,2,0) -> 1 | L72: =VLOOKUP($C72,'Refi Adj'!$B$2:$E$32,3,0) -> 1 | M72: =VLOOKUP($C72,'Refi Adj'!$B$2:$E$32,4,0) -> 1 | O72: =AD38*M72 -> 0 | P72: =AD3 -> 0 | Q72: =(O72*$O$70+P72*$P$70) -> 0 | S72: =Z3+AA3+AB3*K72+AC3*L72+Q72 -> 0.011603077 | T72: =100*(1-(1-S72)^12) -> 13.068611 | U72: =D72/S72 -> 21.21973
A73: =K4 -> -81.597641 | B73: =AQ4/1000000000 -> 0.0060053591 | C73: =AO4 -> 05:-100--75 | D73: =E4 -> 0.055879709 | E73: =Z4+AA4+AB4+AC4+AD4 -> 0.011558146 | F73: =D73/E73 -> 4.8346604 | G73: =(1-(1-D73)^12)*100 -> 49.843412 | H73: =(1-(1-E73)^12)*100 -> 13.021178 | I73: =(1-(1-SUM(Z39,AA39,AB39,AC39,AD39*M73))^12)*100 -> 13.204874 | K73: =VLOOKUP($C73,'Refi Adj'!$B$2:$E$32,2,0) -> 1 | L73: =VLOOKUP($C73,'Refi Adj'!$B$2:$E$32,3,0) -> 1 | M73: =VLOOKUP($C73,'Refi Adj'!$B$2:$E$32,4,0) -> 1 | O73: =AD39*M73 -> 0.00019607821 | P73: =AD4 -> 2.1947121e-05 | Q73: =(O73*$O$70+P73*$P$70) -> 9.1599557e-05 | S73: =Z4+AA4+AB4*K73+AC4*L73+Q73 -> 0.011627798 | T73: =100*(1-(1-S73)^12) -> 13.094699 | U73: =D73/S73 -> 4.8056999
A74: =K5 -> -57.582086 | B74: =AQ5/1000000000 -> 0.043286126 | C74: =AO5 -> 06:-75--50 | D74: =E5 -> 0.040115492 | E74: =Z5+AA5+AB5+AC5+AD5 -> 0.008752777 | F74: =D74/E74 -> 4.5831731 | G74: =(1-(1-D74)^12)*100 -> 38.81742 | H74: =(1-(1-E74)^12)*100 -> 10.012165 | I74: =(1-(1-SUM(Z40,AA40,AB40,AC40,AD40*M74))^12)*100 -> 10.452943 | K74: =VLOOKUP($C74,'Refi Adj'!$B$2:$E$32,2,0) -> 1 | L74: =VLOOKUP($C74,'Refi Adj'!$B$2:$E$32,3,0) -> 1 | M74: =VLOOKUP($C74,'Refi Adj'!$B$2:$E$32,4,0) -> 0.5 | O74: =AD40*M74 -> 0.00054207061 | P74: =AD5 -> 0.00013654951 | Q74: =(O74*$O$70+P74*$P$70) -> 0.00029875795 | S74: =Z5+AA5+AB5*K74+AC5*L74+Q74 -> 0.0089149854 | T74: =100*(1-(1-S74)^12) -> 10.188714 | U74: =D74/S74 -> 4.4997821
A75: =K6 -> -31.153905 | B75: =AQ6/1000000000 -> 1.3604578 | C75: =AO6 -> 07:-50--25 | D75: =E6 -> 0.0081575869 | E75: =Z6+AA6+AB6+AC6+AD6 -> 0.0060972412 | F75: =D75/E75 -> 1.3379144 | G75: =(1-(1-D75)^12)*100 -> 9.3616256 | H75: =(1-(1-E75)^12)*100 -> 7.0762446 | I75: =(1-(1-SUM(Z41,AA41,AB41,AC41,AD41*M75))^12)*100 -> 8.8638206 | K75: =VLOOKUP($C75,'Refi Adj'!$B$2:$E$32,2,0) -> 1 | L75: =VLOOKUP($C75,'Refi Adj'!$B$2:$E$32,3,0) -> 1 | M75: =VLOOKUP($C75,'Refi Adj'!$B$2:$E$32,4,0) -> 0.5 | O75: =AD41*M75 -> 0.0020874433 | P75: =AD6 -> 0.00047990951 | Q75: =(O75*$O$70+P75*$P$70) -> 0.001122923 | S75: =Z6+AA6+AB6*K75+AC6*L75+Q75 -> 0.0067402547 | T75: =100*(1-(1-S75)^12) -> 7.7950965 | U75: =D75/S75 -> 1.2102787
A76: =K7 -> -22.221985 | B76: =AQ7/1000000000 -> 1.5658819 | C76: =AO7 -> 08-1:-25--20 | D76: =E7 -> 0.0064014336 | E76: =Z7+AA7+AB7+AC7+AD7 -> 0.0062167335 | F76: =D76/E76 -> 1.0297102 | G76: =(1-(1-D76)^12)*100 -> 7.416952 | H76: =(1-(1-E76)^12)*100 -> 7.2102175 | I76: =(1-(1-SUM(Z42,AA42,AB42,AC42,AD42*M76))^12)*100 -> 10.281125 | K76: =VLOOKUP($C76,'Refi Adj'!$B$2:$E$32,2,0) -> 1 | L76: =VLOOKUP($C76,'Refi Adj'!$B$2:$E$32,3,0) -> 1 | M76: =VLOOKUP($C76,'Refi Adj'!$B$2:$E$32,4,0) -> 0.51 | O76: =AD42*M76 -> 0.0036342432 | P76: =AD7 -> 0.00085097056 | Q76: =(O76*$O$70+P76*$P$70) -> 0.0019642796 | S76: =Z7+AA7+AB7*K76+AC7*L76+Q76 -> 0.0073300426 | T76: =100*(1-(1-S76)^12) -> 8.4499595 | U76: =D76/S76 -> 0.87331466
A77: =K8 -> -17.210662 | B77: =AQ8/1000000000 -> 2.7221264 | C77: =AO8 -> 08-2:-20--15 | D77: =E8 -> 0.0041674922 | E77: =Z8+AA8+AB8+AC8+AD8 -> 0.006546432 | F77: =D77/E77 -> 0.63660513 | G77: =(1-(1-D77)^12)*100 -> 4.8879394 | H77: =(1-(1-E77)^12)*100 -> 7.5789524 | I77: =(1-(1-SUM(Z43,AA43,AB43,AC43,AD43*M77))^12)*100 -> 11.336793 | K77: =VLOOKUP($C77,'Refi Adj'!$B$2:$E$32,2,0) -> 1 | L77: =VLOOKUP($C77,'Refi Adj'!$B$2:$E$32,3,0) -> 1 | M77: =VLOOKUP($C77,'Refi Adj'!$B$2:$E$32,4,0) -> 0.52 | O77: =AD43*M77 -> 0.0044942988 | P77: =AD8 -> 0.0010637355 | Q77: =(O77*$O$70+P77*$P$70) -> 0.0024359608 | S77: =Z8+AA8+AB8*K77+AC8*L77+Q77 -> 0.0079186573 | T77: =100*(1-(1-S77)^12) -> 9.0992666 | U77: =D77/S77 -> 0.52628773
A78: =K9 -> -12.281778 | B78: =AQ9/1000000000 -> 4.5837111 | C78: =AO9 -> 08-3:-15--10 | D78: =E9 -> 0.0071583219 | E78: =Z9+AA9+AB9+AC9+AD9 -> 0.0067100944 | F78: =D78/E78 -> 1.066799 | G78: =(1-(1-D78)^12)*100 -> 8.259733 | H78: =(1-(1-E78)^12)*100 -> 7.7614933 | I78: =(1-(1-SUM(Z44,AA44,AB44,AC44,AD44*M78))^12)*100 -> 12.123984 | K78: =VLOOKUP($C78,'Refi Adj'!$B$2:$E$32,2,0) -> 1 | L78: =VLOOKUP($C78,'Refi Adj'!$B$2:$E$32,3,0) -> 1 | M78: =VLOOKUP($C78,'Refi Adj'!$B$2:$E$32,4,0) -> 0.53 | O78: =AD44*M78 -> 0.0052575767 | P78: =AD9 -> 0.0012551902 | Q78: =(O78*$O$70+P78*$P$70) -> 0.0028561448 | S78: =Z9+AA9+AB9*K78+AC9*L78+Q78 -> 0.008311049 | T78: =100*(1-(1-S78)^12) -> 9.52977 | U78: =D78/S78 -> 0.86130185
A79: =K10 -> -7.4062628 | B79: =AQ10/1000000000 -> 6.6326715 | C79: =AO10 -> 08-4:-10--5 | D79: =E10 -> 0.0068517227 | E79: =Z10+AA10+AB10+AC10+AD10 -> 0.0070311975 | F79: =D79/E79 -> 0.9744745 | G79: =(1-(1-D79)^12)*100 -> 7.9191916 | H79: =(1-(1-E79)^12)*100 -> 8.1186756 | I79: =(1-(1-SUM(Z45,AA45,AB45,AC45,AD45*M79))^12)*100 -> 13.053273 | K79: =VLOOKUP($C79,'Refi Adj'!$B$2:$E$32,2,0) -> 1 | L79: =VLOOKUP($C79,'Refi Adj'!$B$2:$E$32,3,0) -> 1 | M79: =VLOOKUP($C79,'Refi Adj'!$B$2:$E$32,4,0) -> 0.54 | O79: =AD45*M79 -> 0.0059946168 | P79: =AD10 -> 0.0014372692 | Q79: =(O79*$O$70+P79*$P$70) -> 0.0032602082 | S79: =Z10+AA10+AB10*K79+AC10*L79+Q79 -> 0.0088541365 | T79: =100*(1-(1-S79)^12) -> 10.122523 | U79: =D79/S79 -> 0.77384425
A80: =K11 -> -2.3916674 | B80: =AQ11/1000000000 -> 9.7982474 | C80: =AO11 -> 08:-25-0 | D80: =E11 -> 0.0075123203 | E80: =Z11+AA11+AB11+AC11+AD11 -> 0.0071853918 | F80: =D80/E80 -> 1.045499 | G80: =(1-(1-D80)^12)*100 -> 8.6514849 | H80: =(1-(1-E80)^12)*100 -> 8.2897443 | I80: =(1-(1-SUM(Z46,AA46,AB46,AC46,AD46*M80))^12)*100 -> 13.793918 | K80: =VLOOKUP($C80,'Refi Adj'!$B$2:$E$32,2,0) -> 1 | L80: =VLOOKUP($C80,'Refi Adj'!$B$2:$E$32,3,0) -> 1 | M80: =VLOOKUP($C80,'Refi Adj'!$B$2:$E$32,4,0) -> 0.55 | O80: =AD46*M80 -> 0.0067428401 | P80: =AD11 -> 0.0016352936 | Q80: =(O80*$O$70+P80*$P$70) -> 0.0036783122 | S80: =Z11+AA11+AB11*K80+AC11*L80+Q80 -> 0.0092284104 | T80: =100*(1-(1-S80)^12) -> 10.52895 | U80: =D80/S80 -> 0.81404272
A81: =K12 -> 2.6121767 | B81: =AQ12/1000000000 -> 12.626439 | C81: =AO12 -> 09-1:0-5 | D81: =E12 -> 0.0084289694 | E81: =Z12+AA12+AB12+AC12+AD12 -> 0.0074734442 | F81: =D81/E81 -> 1.1278561 | G81: =(1-(1-D81)^12)*100 -> 9.6587779 | H81: =(1-(1-E81)^12)*100 -> 8.6085378 | I81: =(1-(1-SUM(Z47,AA47,AB47,AC47,AD47*M81))^12)*100 -> 15.169262 | K81: =VLOOKUP($C81,'Refi Adj'!$B$2:$E$32,2,0) -> 1 | L81: =VLOOKUP($C81,'Refi Adj'!$B$2:$E$32,3,0) -> 1 | M81: =VLOOKUP($C81,'Refi Adj'!$B$2:$E$32,4,0) -> 0.6 | O81: =AD47*M81 -> 0.007996602 | P81: =AD12 -> 0.0018542384 | Q81: =(O81*$O$70+P81*$P$70) -> 0.0043111838 | S81: =Z12+AA12+AB12*K81+AC12*L81+Q81 -> 0.0099303896 | T81: =100*(1-(1-S81)^12) -> 11.286694 | U81: =D81/S81 -> 0.84880551
A82: =K13 -> 7.6142859 | B82: =AQ13/1000000000 -> 16.00432 | C82: =AO13 -> 09-2:5-10 | D82: =E13 -> 0.010497939 | E82: =Z13+AA13+AB13+AC13+AD13 -> 0.0078051285 | F82: =D82/E82 -> 1.3450053 | G82: =(1-(1-D82)^12)*100 -> 11.895024 | H82: =(1-(1-E82)^12)*100 -> 8.9743613 | I82: =(1-(1-SUM(Z48,AA48,AB48,AC48,AD48*M82))^12)*100 -> 16.759244 | K82: =VLOOKUP($C82,'Refi Adj'!$B$2:$E$32,2,0) -> 1 | L82: =VLOOKUP($C82,'Refi Adj'!$B$2:$E$32,3,0) -> 1 | M82: =VLOOKUP($C82,'Refi Adj'!$B$2:$E$32,4,0) -> 0.65 | O82: =AD48*M82 -> 0.0095240055 | P82: =AD13 -> 0.0021592816 | Q82: =(O82*$O$70+P82*$P$70) -> 0.0051051711 | S82: =Z13+AA13+AB13*K82+AC13*L82+Q82 -> 0.010751018 | T82: =100*(1-(1-S82)^12) -> 12.165053 | U82: =D82/S82 -> 0.97646
A83: =K14 -> 12.555816 | B83: =AQ14/1000000000 -> 17.351616 | C83: =AO14 -> 09-3:10-15 | D83: =E14 -> 0.012126299 | E83: =Z14+AA14+AB14+AC14+AD14 -> 0.0081282653 | F83: =D83/E83 -> 1.491868 | G83: =(1-(1-D83)^12)*100 -> 13.619226 | H83: =(1-(1-E83)^12)*100 -> 9.3294662 | I83: =(1-(1-SUM(Z49,AA49,AB49,AC49,AD49*M83))^12)*100 -> 18.272543 | K83: =VLOOKUP($C83,'Refi Adj'!$B$2:$E$32,2,0) -> 1 | L83: =VLOOKUP($C83,'Refi Adj'!$B$2:$E$32,3,0) -> 1 | M83: =VLOOKUP($C83,'Refi Adj'!$B$2:$E$32,4,0) -> 0.7 | O83: =AD49*M83 -> 0.011037012 | P83: =AD14 -> 0.0024908466 | Q83: =(O83*$O$70+P83*$P$70) -> 0.0059093128 | S83: =Z14+AA14+AB14*K83+AC14*L83+Q83 -> 0.011546731 | T83: =100*(1-(1-S83)^12) -> 13.009124 | U83: =D83/S83 -> 1.0501932
... A99: =K30 -> 158.33425 | B99: =AQ30/1000000000 -> 0.4446183 | C99: =AO30 -> 15:150-175 | D99: =E30 -> 0.059426937 | E99: =Z30+AA30+AB30+AC30+AD30 -> 0.030452091 | F99: =D99/E99 -> 1.9514895 | G99: =(1-(1-D99)^12)*100 -> 52.05863 | H99: =(1-(1-E99)^12)*100 -> 31.002828 | I99: =(1-(1-SUM(Z65,AA65,AB65,AC65,AD65*M99))^12)*100 -> 47.772882 | K99: =VLOOKUP($C99,'Refi Adj'!$B$2:$E$32,2,0) -> 1 | L99: =VLOOKUP($C99,'Refi Adj'!$B$2:$E$32,3,0) -> 1 | M99: =VLOOKUP($C99,'Refi Adj'!$B$2:$E$32,4,0) -> 0.9 | O99: =AD65*M99 -> 0.045051077 | P99: =AD30 -> 0.02281146 | Q99: =(O99*$O$70+P99*$P$70) -> 0.031707307 | S99: =Z30+AA30+AB30*K99+AC30*L99+Q99 -> 0.039347938 | T99: =100*(1-(1-S99)^12) -> 38.227748 | U99: =D99/S99 -> 1.5102935
A103: WALA [12,24) | C103: BROKER | F103: low media | AS103: tover | AT103: cash | AW103: refi
A104: modelId | B104: SFACTOR_PREPAY_TRACKING_CPR | C104: PREPAY_CPR1 | D104: PREPAY_TRACKING_CPR1 | E104: PREPAY_SMM1 | F104: PREPAY_TRACKING_SMM1 | G104: PCT_LOANTYPE | H104: _ORIGNOTERATE | I104: _ZEROSATO | J104: _SATO | K104: _REFI_INCENTIVE_Fixed | L104: _Fixed_cost | M104: _LOANAGE | N104: _LTV | O104: _CLTV | P104: _AVG_LOANSIZE_SCHAMBALANCE | Q104: _WACLS | R104: _FICO | S104: PCT_ISSECONDLIEN | T104: _OrigCombLTV | U104: PCT_SVC | V104: PCT_TPO | W104: PCT_GEO | X104: PCT_LOANPURPOSE | Y104: PCT_OCC | Z104: curtailsmm | AA104: defaultsmm | AB104: toverSmm | AC104: cashoutSmm | AD104: refiSmm | AE104: cumHPA | AF104: cumHPA05Pct | AG104: cumHPA15Pct | AH104: cumHPA20Pct | AI104: cumHPA25Pct | AJ104: cumHPA30Pct | AK104: cumHPA35Pct | AL104: cumHPA40Pct | AM104: adjtoverSmm | AN104: adjRefiSmm | AO104: groupByColumn | AP104: curve | AQ104: Balance | AR104: LoanCount | AS104: PCT_BROKER | AT104: PCT_CORRES | AU104: PCT_NonRETAIL | AV104: PCT_RETAIL | AW104: PCT_CashWindow | AX104: PCT_NonCashWindow
A105: 97 | B105: 0.98717805 | C105: 51.093738 | D105: 14.346354 | E105: 0.057863769 | F105: 0.012821955 | G105: 0 | H105: 3.5 | I105: 3.9641177 | J105: -46.82088 | K105: -104.38193 | L105: 100 | M105: 14.479647 | N105: 70 | O105: 9.101893 | P105: 31499.593 | Q105: 31447.485 | R105: 813 | S105: 0 | T105: 0 | U105: 0 | V105: 0 | W105: 0 | X105: 0 | Y105: 0 | Z105: 0.0073728503 | AA105: 4.3457552e-05 | AB105: 0.0054056319 | AC105: 0 | AD105: 0 | AE105: 0.065095111 | AF105: 0 | AG105: 1 | AH105: 1 | AI105: 1 | AJ105: 1 | AK105: 1 | AL105: 1 | AM105: 0 | AN105: 0 | AO105: 04:-125--100 | AP105: =-125--100 -> -25 | AQ105: 62894.97 | AR105: 2 | AS105: 100 | AT105: 0 | AU105: 100 | AV105: 0 | AW105: 0 | AX105: 0
A106: 97 | B106: 0.98521581 | C106: 14.946386 | D106: 16.367236 | E106: 0.013400106 | F106: 0.014784194 | G106: 0 | H106: 3.608228 | I106: 3.8845445 | J106: -39.278372 | K106: -84.523744 | L106: 97.152158 | M106: 15.147705 | N106: 80.018452 | O106: 8.1523317 | P106: 30663.842 | Q106: 26200.371 | R106: 804.43112 | S106: 0 | T106: 0 | U106: 0 | V106: 0 | W106: 0 | X106: 0 | Y106: 0 | Z106: 0.006721237 | AA106: 2.8119532e-05 | AB106: 0.0080348285 | AC106: 0 | AD106: 0 | AE106: 0.09654619 | AF106: 0 | AG106: 1 | AH106: 1 | AI106: 1 | AJ106: 1 | AK106: 1 | AL106: 1 | AM106: 0 | AN106: 0 | AO106: 05:-100--75 | AP106: =-100--75 -> -25 | AQ106: 707410.03 | AR106: 27 | AS106: 100 | AT106: 0 | AU106: 100 | AV106: 0 | AW106: 0 | AX106: 0
A107: 97 | B107: 0.99081351 | C107: 18.096062 | D107: 10.483514 | E107: 0.016497658 | F107: 0.0091864916 | G107: 0 | H107: 3.4613011 | I107: 3.9059607 | J107: -55.632561 | K107: -57.377777 | L107: 48.596687 | M107: 14.375749 | N107: 70.045544 | O107: 39.201412 | P107: 171695.99 | Q107: 59778.38 | R107: 781.89644 | S107: 0 | T107: 0 | U107: 0.18247199 | V107: 0 | W107: 0 | X107: 0.57703133 | Y107: 0 | Z107: 0.0026065179 | AA107: 3.0473938e-05 | AB107: 0.0065425673 | AC107: 6.9220064e-06 | AD107: 0 | AE107: 0.098877051 | AF107: 0.18485074 | AG107: 0.87192065 | AH107: 1 | AI107: 1 | AJ107: 1 | AK107: 1 | AL107: 1 | AM107: 0 | AN107: 0 | AO107: 06:-75--50 | AP107: =-75--50 -> -25 | AQ107: 4363821.7 | AR107: 73 | AS107: 100 | AT107: 0 | AU107: 100 | AV107: 0 | AW107: 0 | AX107: 0
A108: 97 | B108: 0.99371972 | C108: 4.3036058 | D108: 7.2813929 | E108: 0.0036590864 | F108: 0.0062802802 | G108: 0 | H108: 3.4453894 | I108: 3.925779 | J108: -56.57836 | K108: -31.114896 | L108: 17.359003 | M108: 14.460238 | N108: 69.817493 | O108: 60.987955 | P108: 265956.18 | Q108: 221964.68 | R108: 780.78902 | S108: 0 | T108: 0 | U108: 0.26399512 | V108: 0 | W108: 0 | X108: 0.63616984 | Y108: 0 | Z108: 0.00045874415 | AA108: 3.3580202e-05 | AB108: 0.0052362435 | AC108: 2.0813514e-06 | AD108: 0.00054961612 | AE108: 0.088177657 | AF108: 0.12789084 | AG108: 0.9395086 | AH108: 0.99912392 | AI108: 1 | AJ108: 1 | AK108: 1 | AL108: 1 | AM108: 0 | AN108: 0 | AO108: 07:-50--25 | AP108: =-50--25 -> -25 | AQ108: 1.6980298e+08 | AR108: 765 | AS108: 100 | AT108: 0 | AU108: 100 | AV108: 0 | AW108: 0 | AX108: 0
A109: 97 | B109: 0.99340685 | C109: 9.3546473 | D109: 7.6310972 | E109: 0.0081512235 | F109: 0.0065931536 | G109: 0 | H109: 3.513882 | I109: 3.9421493 | J109: -48.996049 | K109: -22.229761 | L109: 14.788359 | M109: 14.356613 | N109: 71.651334 | O109: 63.350334 | P109: 294036.64 | Q109: 268956.39 | R109: 780.79442 | S109: 0 | T109: 0 | U109: 0.38598226 | V109: 0 | W109: 0 | X109: 0.70046037 | Y109: 0 | Z109: 0.00037936105 | AA109: 3.9222507e-05 | AB109: 0.0051312787 | AC109: 9.4363457e-07 | AD109: 0.001042333 | AE109: 0.091495907 | AF109: 0.11819208 | AG109: 0.94190371 | AH109: 0.99858 | AI109: 1 | AJ109: 1 | AK109: 1 | AL109: 1 | AM109: 0 | AN109: 0 | AO109: 08-1:-25--20 | AP109: =-25--20 -> -5 | AQ109: 2.7971465e+08 | AR109: 1040 | AS109: 100 | AT109: 0 | AU109: 100 | AV109: 0 | AW109: 0 | AX109: 0
A110: 97 | B110: 0.99310934 | C110: 6.3762958 | D110: 7.9625004 | E110: 0.0054755032 | F110: 0.0068906571 | G110: 0 | H110: 3.5419733 | I110: 3.9369234 | J110: -46.111295 | K110: -17.09629 | L110: 14.336892 | M110: 14.480167 | N110: 67.370985 | O110: 59.748077 | P110: 300547.54 | Q110: 277965.94 | R110: 781.83322 | S110: 0 | T110: 0 | U110: 0.36754756 | V110: 0 | W110: 0 | X110: 0.73746029 | Y110: 0 | Z110: 0.00037098606 | AA110: 3.7428242e-05 | AB110: 0.0051694196 | AC110: 1.2743154e-06 | AD110: 0.001311534 | AE110: 0.092634214 | AF110: 0.10942349 | AG110: 0.92712821 | AH110: 0.99703861 | AI110: 1 | AJ110: 1 | AK110: 1 | AL110: 1 | AM110: 0 | AN110: 0 | AO110: 08-2:-20--15 | AP110: =-20--15 -> -5 | AQ110: 5.6732849e+08 | AR110: 2041 | AS110: 100 | AT110: 0 | AU110: 100 | AV110: 0 | AW110: 0 | AX110: 0
A111: 97 | B111: 0.99286804 | C111: 10.582111 | D111: 8.2305017 | E111: 0.0092774814 | F111: 0.0071319631 | G111: 0 | H111: 3.5865162 | I111: 3.9275357 | J111: -42.271619 | K111: -12.256696 | L111: 13.993727 | M111: 14.57794 | N111: 69.522343 | O111: 61.743513 | P111: 304068.02 | Q111: 284638.85 | R111: 781.40849 | S111: 0 | T111: 0 | U111: 0.32304257 | V111: 0 | W111: 0 | X111: 0.72316379 | Y111: 0 | Z111: 0.00036858221 | AA111: 3.7570907e-05 | AB111: 0.0051978837 | AC111: 1.8038783e-06 | AD111: 0.0015261079 | AE111: 0.093150695 | AF111: 0.093081842 | AG111: 0.93741737 | AH111: 0.9986889 | AI111: 1 | AJ111: 1 | AK111: 1 | AL111: 1 | AM111: 0 | AN111: 0 | AO111: 08-3:-15--10 | AP111: =-15--10 -> -5 | AQ111: 9.6008685e+08 | AR111: 3373 | AS111: 100 | AT111: 0 | AU111: 100 | AV111: 0 | AW111: 0 | AX111: 0
A112: 97 | B112: 0.99248716 | C112: 9.2241763 | D112: 8.6520563 | E112: 0.0080323332 | F112: 0.0075128376 | G112: 0 | H112: 3.6105569 | I112: 3.9098078 | J112: -40.343517 | K112: -7.4527448 | L112: 13.853094 | M112: 14.999495 | N112: 67.471238 | O112: 59.733141 | P112: 307262.75 | Q112: 287755.53 | R112: 781.79494 | S112: 0 | T112: 0 | U112: 0.28637138 | V112: 0 | W112: 0 | X112: 0.72878788 | Y112: 0 | Z112: 0.00036754879 | AA112: 3.8319379e-05 | AB112: 0.0053630769 | AC112: 2.5850055e-06 | AD112: 0.0017412928 | AE112: 0.095958295 | AF112: 0.084816308 | AG112: 0.93269664 | AH112: 0.99827066 | AI112: 1 | AJ112: 1 | AK112: 1 | AL112: 1 | AM112: 0 | AN112: 0 | AO112: 08-4:-10--5 | AP112: =-10--5 -> -5 | AQ112: 1.5095655e+09 | AR112: 5246 | AS112: 100 | AT112: 0 | AU112: 100 | AV112: 0 | AW112: 0 | AX112: 0
A113: 97 | B113: 0.9922933 | C113: 9.472374 | D113: 8.8659395 | E113: 0.0082586354 | F113: 0.0077066976 | G113: 0 | H113: 3.6389092 | I113: 3.8902957 | J113: -38.093674 | K113: -2.4416225 | L113: 13.613078 | M113: 15.348969 | N113: 67.730737 | O113: 59.905591 | P113: 312221.39 | Q113: 292946.11 | R113: 781.20772 | S113: 0 | T113: 0 | U113: 0.26810644 | V113: 0 | W113: 0 | X113: 0.72810249 | Y113: 0 | Z113: 0.00036582089 | AA113: 3.8897981e-05 | AB113: 0.0053178106 | AC113: 2.8809183e-06 | AD113: 0.0019812726 | AE113: 0.096502525 | AF113: 0.077194887 | AG113: 0.93772656 | AH113: 0.99772433 | AI113: 1 | AJ113: 1 | AK113: 1 | AL113: 1 | AM113: 0 | AN113: 0 | AO113: 08:-25-0 | AP113: =-25-0 -> -25 | AQ113: 2.2193597e+09 | AR113: 7576 | AS113: 100 | AT113: 0 | AU113: 100 | AV113: 0 | AW113: 0 | AX113: 0
A114: 97 | B114: 0.99197634 | C114: 15.393161 | D114: 9.2146516 | E114: 0.013833022 | F114: 0.0080236601 | G114: 0 | H114: 3.6729898 | I114: 3.875255 | J114: -35.426086 | K114: 2.5942211 | L114: 13.720368 | M114: 15.735454 | N114: 67.889186 | O114: 59.896447 | P114: 309762.47 | Q114: 290905.56 | R114: 781.35176 | S114: 0 | T114: 0 | U114: 0.27440132 | V114: 0 | W114: 0 | X114: 0.73132601 | Y114: 0 | Z114: 0.00036572817 | AA114: 4.0387583e-05 | AB114: 0.0053689263 | AC114: 5.5813747e-06 | AD114: 0.0022430222 | AE114: 0.09983964 | AF114: 0.073680052 | AG114: 0.92019325 | AH114: 0.99207841 | AI114: 1 | AJ114: 1 | AK114: 1 | AL114: 1 | AM114: 0 | AN114: 0 | AO114: 09-1:0-5 | AP114: 0-5 | AQ114: 2.7164761e+09 | AR114: 9338 | AS114: 100 | AT114: 0 | AU114: 100 | AV114: 0 | AW114: 0 | AX114: 0
A115: 97 | B115: 0.99159782 | C115: 19.374143 | D115: 9.6294845 | E115: 0.01778583 | F115: 0.00840218 | G115: 0 | H115: 3.7018031 | I115: 3.8523687 | J115: -33.608499 | K115: 7.5978709 | L115: 13.555931 | M115: 16.153041 | N115: 68.349284 | O115: 60.209078 | P115: 312318.42 | Q115: 294443.2 | R115: 780.75008 | S115: 0 | T115: 0 | U115: 0.25445129 | V115: 0 | W115: 0 | X115: 0.71538394 | Y115: 0 | Z115: 0.00036549654 | AA115: 4.1631701e-05 | AB115: 0.0054127244 | AC115: 5.8972403e-06 | AD115: 0.0025764157 | AE115: 0.10079002 | AF115: 0.072350374 | AG115: 0.9232549 | AH115: 0.99228221 | AI115: 1 | AJ115: 1 | AK115: 1 | AL115: 1 | AM115: 0 | AN115: 0 | AO115: 09-2:5-10 | AP115: 43230 | AQ115: 3.400819e+09 | AR115: 11550 | AS115: 100 | AT115: 0 | AU115: 100 | AV115: 0 | AW115: 0 | AX115: 0
A116: 97 | B116: 0.99121162 | C116: 21.536671 | D116: 10.050948 | E116: 0.020008684 | F116: 0.0087883846 | G116: 0 | H116: 3.7336879 | I116: 3.8353194 | J116: -31.218814 | K116: 12.584783 | L116: 13.542286 | M116: 16.428454 | N116: 68.213845 | O116: 59.996082 | P116: 312667.75 | Q116: 294763.93 | R116: 780.5621 | S116: 0 | T116: 0 | U116: 0.22768863 | V116: 0 | W116: 0 | X116: 0.71399457 | Y116: 0 | Z116: 0.0003660012 | AA116: 4.402875e-05 | AB116: 0.0053939823 | AC116: 7.3101587e-06 | AD116: 0.0029770477 | AE116: 0.10205526 | AF116: 0.067915561 | AG116: 0.92503791 | AH116: 0.99162116 | AI116: 1 | AJ116: 1 | AK116: 1 | AL116: 1 | AM116: 0 | AN116: 0 | AO116: 09-3:10-15 | AP116: 43388 | AQ116: 3.7317114e+09 | AR116: 12660 | AS116: 100 | AT116: 0 | AU116: 100 | AV116: 0 | AW116: 0 | AX116: 0
A117: 97 | B117: 0.99076024 | C117: 22.102074 | D117: 10.541252 | E117: 0.020599117 | F117: 0.0092397639 | G117: 0 | H117: 3.7702088 | I117: 3.8263271 | J117: -28.959175 | K117: 17.500116 | L117: 13.734289 | M117: 16.664463 | N117: 67.006822 | O117: 58.877311 | P117: 309456.95 | Q117: 290646.95 | R117: 780.42452 | S117: 0 | T117: 0 | U117: 0.22507981 | V117: 0 | W117: 0 | X117: 0.70941174 | Y117: 0 | Z117: 0.00036583592 | AA117: 4.5257751e-05 | AB117: 0.0054132137 | AC117: 9.1615113e-06 | AD117: 0.0034062805 | AE117: 0.10338482 | AF117: 0.071025376 | AG117: 0.92095469 | AH117: 0.99022255 | AI117: 1 | AJ117: 1 | AK117: 1 | AL117: 1 | AM117: 0 | AN117: 0 | AO117: 09-4:15-20 | AP117: 15-20 | AQ117: 3.8533973e+09 | AR117: 13258 | AS117: 100 | AT117: 0 | AU117: 100 | AV117: 0 | AW117: 0 | AX117: 0
A118: 97 | B118: 0.99029671 | C118: 22.682516 | D118: 11.0422 | E118: 0.021209356 | F118: 0.0097032905 | G118: 0 | H118: 3.8240921 | I118: 3.8203738 | J118: -25.925004 | K118: 22.488531 | L118: 13.878578 | M118: 16.730959 | N118: 71.299152 | O118: 62.700504 | P118: 305355.71 | Q118: 287632.39 | R118: 779.57653 | S118: 0 | T118: 0 | U118: 0.23416701 | V118: 0 | W118: 0 | X118: 0.63976586 | Y118: 0 | Z118: 0.00036540967 | AA118: 4.9480737e-05 | AB118: 0.0054207146 | AC118: 1.2126789e-05 | AD118: 0.0038555443 | AE118: 0.10276232 | AF118: 0.076715892 | AG118: 0.9201677 | AH118: 0.98817962 | AI118: 1 | AJ118: 1 | AK118: 1 | AL118: 1 | AM118: 0 | AN118: 0 | AO118: 09:0-25 | AP118: 0-25 | AQ118: 3.9753672e+09 | AR118: 13821 | AS118: 100 | AT118: 0 | AU118: 100 | AV118: 0 | AW118: 0 | AX118: 0
A119: 97 | B119: 0.9897309 | C119: 26.052643 | D119: 11.650207 | E119: 0.024837734 | F119: 0.010269103 | G119: 0 | H119: 3.8611126 | I119: 3.8194515 | J119: -24.704015 | K119: 27.484782 | L119: 13.867262 | M119: 16.93715 | N119: 68.706809 | O119: 60.315487 | P119: 307000.71 | Q119: 287869.18 | R119: 779.88715 | S119: 0 | T119: 0 | U119: 0.24312876 | V119: 0 | W119: 0 | X119: 0.64958666 | Y119: 0 | Z119: 0.00036641857 | AA119: 5.1789911e-05 | AB119: 0.0054098708 | AC119: 1.5751935e-05 | AD119: 0.0044252573 | AE119: 0.10434004 | AF119: 0.074891196 | AG119: 0.91372197 | AH119: 0.98287059 | AI119: 1 | AJ119: 1 | AK119: 1 | AL119: 1 | AM119: 0 | AN119: 0 | AO119: 10-1:25-30 | AP119: 25-30 | AQ119: 4.0989693e+09 | AR119: 14239 | AS119: 100 | AT119: 0 | AU119: 100 | AV119: 0 | AW119: 0 | AX119: 0
A120: 97 | B120: 0.98919367 | C120: 22.490237 | D120: 12.223966 | E120: 0.021006743 | F120: 0.010806328 | G120: 0 | H120: 3.917368 | I120: 3.8193358 | J120: -21.934467 | K120: 32.518647 | L120: 13.956175 | M120: 16.961322 | N120: 70.695176 | O120: 62.147245 | P120: 304453.94 | Q120: 286030.89 | R120: 778.75186 | S120: 0 | T120: 0 | U120: 0.24836269 | V120: 0 | W120: 0 | X120: 0.60559435 | Y120: 0 | Z120: 0.0003663531 | AA120: 5.7775307e-05 | AB120: 0.0054354146 | AC120: 1.7110415e-05 | AD120: 0.0049296603 | AE120: 0.10319738 | AF120: 0.085516319 | AG120: 0.91107805 | AH120: 0.98361541 | AI120: 1 | AJ120: 1 | AK120: 1 | AL120: 1 | AM120: 0 | AN120: 0 | AO120: 10-2:30-35 | AP120: 30-35 | AQ120: 4.1094058e+09 | AR120: 14367 | AS120: 100 | AT120: 0 | AU120: 100 | AV120: 0 | AW120: 0 | AX120: 0
A121: 97 | B121: 0.98867766 | C121: 28.073637 | D121: 12.771855 | E121: 0.027086996 | F121: 0.011322343 | G121: 0 | H121: 3.9727196 | I121: 3.8255135 | J121: -20.034866 | K121: 37.512332 | L121: 14.136359 | M121: 17.193102 | N121: 71.539239 | O121: 62.764266 | P121: 300857.72 | Q121: 282400.24 | R121: 778.6284 | S121: 0 | T121: 0 | U121: 0.25340714 | V121: 0 | W121: 0 | X121: 0.56893055 | Y121: 0 | Z121: 0.00036740263 | AA121: 6.282134e-05 | AB121: 0.0054848605 | AC121: 2.0901031e-05 | AD121: 0.0053863426 | AE121: 0.10447481 | AF121: 0.080848158 | AG121: 0.90455391 | AH121: 0.98152931 | AI121: 1 | AJ121: 1 | AK121: 1 | AL121: 1 | AM121: 0 | AN121: 0 | AO121: 10-3:35-40 | AP121: 35-40 | AQ121: 3.9584041e+09 | AR121: 14017 | AS121: 100 | AT121: 0 | AU121: 100 | AV121: 0 | AW121: 0 | AX121: 0
A122: 97 | B122: 0.98813403 | C122: 28.188409 | D122: 13.345671 | E122: 0.027216462 | F122: 0.011865972 | G122: 0 | H122: 4.0172408 | I122: 3.8247546 | J122: -18.502891 | K122: 42.505752 | L122: 14.36766 | M122: 17.298542 | N122: 70.978622 | O122: 62.304937 | P122: 295678.37 | Q122: 277858.85 | R122: 778.43385 | S122: 0 | T122: 0 | U122: 0.2710462 | V122: 0 | W122: 0 | X122: 0.54695527 | Y122: 0 | Z122: 0.00036657336 | AA122: 6.4844544e-05 | AB122: 0.0055490251 | AC122: 2.757674e-05 | AD122: 0.0058579376 | AE122: 0.10491807 | AF122: 0.09065585 | AG122: 0.89679488 | AH122: 0.97711292 | AI122: 1 | AJ122: 1 | AK122: 1 | AL122: 1 | AM122: 0 | AN122: 0 | AO122: 10-4:40-45 | AP122: 40-45 | AQ122: 3.860293e+09 | AR122: 13893 | AS122: 100 | AT122: 0 | AU122: 100 | AV122: 0 | AW122: 0 | AX122: 0
A123: 97 | B123: 0.98758905 | C123: 27.031938 | D123: 13.917436 | E123: 0.025920505 | F123: 0.012410949 | G123: 0 | H123: 4.0612882 | I123: 3.8182088 | J123: -15.771314 | K123: 47.461827 | L123: 14.179633 | M123: 17.458233 | N123: 73.222494 | O123: 64.178052 | P123: 300122.87 | Q123: 281545.65 | R123: 778.26481 | S123: 0 | T123: 0 | U123: 0.28966431 | V123: 0 | W123: 0 | X123: 0.51534085 | Y123: 0 | Z123: 0.00036689699 | AA123: 6.9321491e-05 | AB123: 0.0055216338 | AC123: 3.4076194e-05 | AD123: 0.006419006 | AE123: 0.10653619 | AF123: 0.082188735 | AG123: 0.88760885 | AH123: 0.97488923 | AI123: 1 | AJ123: 1 | AK123: 1 | AL123: 1 | AM123: 0 | AN123: 0 | AO123: 10:25-50 | AP123: 25-50 | AQ123: 3.9489593e+09 | AR123: 14026 | AS123: 100 | AT123: 0 | AU123: 100 | AV123: 0 | AW123: 0 | AX123: 0
A124: 97 | B124: 0.98696551 | C124: 29.634233 | D124: 14.567378 | E124: 0.028863854 | F124: 0.013034486 | G124: 0 | H124: 4.1003164 | I124: 3.8168106 | J124: -14.200618 | K124: 52.451012 | L124: 14.42263 | M124: 17.651874 | N124: 71.682711 | O124: 62.656962 | P124: 295482.63 | Q124: 276804.9 | R124: 778.19195 | S124: 0 | T124: 0 | U124: 0.29163471 | V124: 0 | W124: 0 | X124: 0.53942584 | Y124: 0 | Z124: 0.00036722608 | AA124: 6.8901375e-05 | AB124: 0.0055799862 | AC124: 4.267464e-05 | AD124: 0.0069756828 | AE124: 0.10880778 | AF124: 0.072614864 | AG124: 0.87931908 | AH124: 0.96952068 | AI124: 1 | AJ124: 1 | AK124: 1 | AL124: 1 | AM124: 0 | AN124: 0 | AO124: 11-1:50-55 | AP124: 50-55 | AQ124: 3.4658742e+09 | AR124: 12521 | AS124: 100 | AT124: 0 | AU124: 100 | AV124: 0 | AW124: 0 | AX124: 0
A125: 97 | B125: 0.98629664 | C125: 34.135848 | D125: 15.259571 | E125: 0.034199501 | F125: 0.013703357 | G125: 0 | H125: 4.134622 | I125: 3.8069629 | J125: -11.414417 | K125: 57.46557 | L125: 14.024441 | M125: 17.606136 | N125: 73.524392 | O125: 64.241333 | P125: 301926.45 | Q125: 284664.89 | R125: 777.6874 | S125: 0 | T125: 0 | U125: 0.31006981 | V125: 0 | W125: 0 | X125: 0.52602402 | Y125: 0 | Z125: 0.00036593884 | AA125: 7.1819514e-05 | AB125: 0.0055331355 | AC125: 5.4440638e-05 | AD125: 0.0076780079 | AE125: 0.10983005 | AF125: 0.069941609 | AG125: 0.86764495 | AH125: 0.96112622 | AI125: 1 | AJ125: 1 | AK125: 1 | AL125: 1 | AM125: 0 | AN125: 0 | AO125: 11-2:55-60 | AP125: 55-60 | AQ125: 3.1794221e+09 | AR125: 11169 | AS125: 100 | AT125: 0 | AU125: 100 | AV125: 0 | AW125: 0 | AX125: 0
A126: 97 | B126: 0.98565188 | C126: 33.963543 | D126: 15.92195 | E126: 0.033989203 | F126: 0.014348125 | G126: 0 | H126: 4.1641574 | I126: 3.8010371 | J126: -8.8362461 | K126: 62.397341 | L126: 13.924157 | M126: 17.810219 | N126: 74.443821 | O126: 64.926923 | P126: 305289.4 | Q126: 286718.82 | R126: 777.4596 | S126: 0 | T126: 0 | U126: 0.31728515 | V126: 0 | W126: 0 | X126: 0.53426942 | Y126: 0 | Z126: 0.00036670849 | AA126: 7.8171417e-05 | AB126: 0.0054875739 | AC126: 6.5222706e-05 | AD126: 0.0083504334 | AE126: 0.11213021 | AF126: 0.063305209 | AG126: 0.8609546 | AH126: 0.95390789 | AI126: 1 | AJ126: 1 | AK126: 1 | AL126: 1 | AM126: 0 | AN126: 0 | AO126: 11-3:60-65 | AP126: 60-65 | AQ126: 2.5506507e+09 | AR126: 8896 | AS126: 100 | AT126: 0 | AU126: 100 | AV126: 0 | AW126: 0 | AX126: 0
A127: 97 | B127: 0.98504114 | C127: 32.364874 | D127: 16.544991 | E127: 0.032061661 | F127: 0.014958864 | G127: 0 | H127: 4.1962927 | I127: 3.8040842 | J127: -6.2745947 | K127: 67.458497 | L127: 14.386665 | M127: 17.868395 | N127: 74.769419 | O127: 65.162384 | P127: 295170.68 | Q127: 277506.24 | R127: 776.63757 | S127: 0 | T127: 0 | U127: 0.32492011 | V127: 0 | W127: 0 | X127: 0.53117384 | Y127: 0 | Z127: 0.00036633725 | AA127: 8.1664755e-05 | AB127: 0.0055632693 | AC127: 7.1146965e-05 | AD127: 0.0088764303 | AE127: 0.11300142 | AF127: 0.061907497 | AG127: 0.84554838 | AH127: 0.95520817 | AI127: 1 | AJ127: 1 | AK127: 1 | AL127: 1 | AM127: 0 | AN127: 0 | AO127: 11-4:65-70 | AP127: 65-70 | AQ127: 1.8567943e+09 | AR127: 6691 | AS127: 100 | AT127: 0 | AU127: 100 | AV127: 0 | AW127: 0 | AX127: 0
A128: 97 | B128: 0.98430655 | C128: 32.755563 | D128: 17.288771 | E128: 0.032528834 | F128: 0.015693455 | G128: 0 | H128: 4.225392 | I128: 3.8067612 | J128: -3.3116473 | K128: 72.403715 | L128: 14.236678 | M128: 17.908482 | N128: 78.9946 | O128: 68.621471 | P128: 297441.43 | Q128: 280429.91 | R128: 775.71806 | S128: 0 | T128: 0 | U128: 0.34152839 | V128: 0 | W128: 0 | X128: 0.51176166 | Y128: 0 | Z128: 0.00036633966 | AA128: 8.8245576e-05 | AB128: 0.0055680157 | AC128: 8.1831751e-05 | AD128: 0.0095890067 | AE128: 0.11640522 | AF128: 0.050382067 | AG128: 0.81694746 | AH128: 0.95327366 | AI128: 1 | AJ128: 1 | AK128: 1 | AL128: 1 | AM128: 0 | AN128: 0 | AO128: 11:50-75 | AP128: 50-75 | AQ128: 1.5112368e+09 | AR128: 5389 | AS128: 100 | AT128: 0 | AU128: 100 | AV128: 0 | AW128: 0 | AX128: 0
... A132: 97 | B132: 0.96714625 | C132: 48.305524 | D132: 33.026063 | E132: 0.053500597 | F132: 0.03285375 | G132: 0 | H132: 4.7387345 | I132: 3.8090134 | J132: 36.351428 | K132: 158.04327 | L132: 14.788747 | M132: 21.723605 | N132: 93.526999 | O132: 76.332455 | P132: 284456.04 | Q132: 269990.25 | R132: 764.542 | S132: 0 | T132: 0 | U132: 0.44724081 | V132: 0 | W132: 0 | X132: 0.20675656 | Y132: 0 | Z132: 0.00037300835 | AA132: 0.00026788372 | AB132: 0.0067066792 | AC132: 0.00076686368 | AD132: 0.024739296 | AE132: 0.18380824 | AF132: 0 | AG132: 0.24101444 | AH132: 0.60775903 | AI132: 1 | AJ132: 1 | AK132: 1 | AL132: 1 | AM132: 0 | AN132: 0 | AO132: 15:150-175 | AP132: 150-175 | AQ132: 79647123 | AR132: 295 | AS132: 100 | AT132: 0 | AU132: 100 | AV132: 0 | AW132: 0 | AX132: 0
F136: high media
A137: modelId | B137: SFACTOR_PREPAY_TRACKING_CPR | C137: PREPAY_CPR1 | D137: PREPAY_TRACKING_CPR1 | E137: PREPAY_SMM1 | F137: PREPAY_TRACKING_SMM1 | G137: PCT_LOANTYPE | H137: _ORIGNOTERATE | I137: _ZEROSATO | J137: _SATO | K137: _REFI_INCENTIVE_Fixed | L137: _Fixed_cost | M137: _LOANAGE | N137: _LTV | O137: _CLTV | P137: _AVG_LOANSIZE_SCHAMBALANCE | Q137: _WACLS | R137: _FICO | S137: PCT_ISSECONDLIEN | T137: _OrigCombLTV | U137: PCT_SVC | V137: PCT_TPO | W137: PCT_GEO | X137: PCT_LOANPURPOSE | Y137: PCT_OCC | Z137: curtailsmm | AA137: defaultsmm | AB137: toverSmm | AC137: cashoutSmm | AD137: refiSmm | AE137: cumHPA | AF137: cumHPA05Pct | AG137: cumHPA15Pct | AH137: cumHPA20Pct | AI137: cumHPA25Pct | AJ137: cumHPA30Pct | AK137: cumHPA35Pct | AL137: cumHPA40Pct | AM137: adjtoverSmm | AN137: adjRefiSmm | AO137: groupByColumn | AP137: curve | AQ137: Balance | AR137: LoanCount | AS137: PCT_BROKER | AT137: PCT_CORRES | AU137: PCT_NonRETAIL | AV137: PCT_RETAIL | AW137: PCT_CashWindow | AX137: PCT_NonCashWindow
A138: 96 | B138: 0.98717805 | C138: 51.093738 | D138: 14.346354 | E138: 0.057863769 | F138: 0.012821955 | G138: 0 | H138: 3.5 | I138: 3.9641177 | J138: -46.82088 | K138: -104.38193 | L138: 100 | M138: 14.479647 | N138: 70 | O138: 9.101893 | P138: 31499.593 | Q138: 31447.485 | R138: 813 | S138: 0 | T138: 0 | U138: 0 | V138: 0 | W138: 0 | X138: 0 | Y138: 0 | Z138: 0.0073728503 | AA138: 4.3457552e-05 | AB138: 0.0054056319 | AC138: 0 | AD138: 0 | AE138: 0.065095111 | AF138: 0 | AG138: 1 | AH138: 1 | AI138: 1 | AJ138: 1 | AK138: 1 | AL138: 1 | AM138: 0 | AN138: 0 | AO138: 04:-125--100 | AP138: =-125--100 -> -25 | AQ138: 62894.97 | AR138: 2 | AS138: 100 | AT138: 0 | AU138: 100 | AV138: 0 | AW138: 0 | AX138: 0
...

Sheet Burnout 2013 Corres+Cashwindow_
A1: burnout 0-2000 | C1: CORRES+CASHWINDOW | F1: low media | AS1: tover | AT1: cash | AW1: refi
A2: modelId | B2: SFACTOR_PREPAY_TRACKING_CPR | C2: PREPAY_CPR1 | D2: PREPAY_TRACKING_CPR1 | E2: PREPAY_SMM1 | F2: PREPAY_TRACKING_SMM1 | G2: PCT_LOANTYPE | H2: _ORIGNOTERATE | I2: _ZEROSATO | J2: _SATO | K2: _REFI_INCENTIVE_Fixed | L2: _Fixed_cost | M2: _LOANAGE | N2: _LTV | O2: _CLTV | P2: _AVG_LOANSIZE_SCHAMBALANCE | Q2: _WACLS | R2: _FICO | S2: PCT_ISSECONDLIEN | T2: _OrigCombLTV | U2: PCT_SVC | V2: PCT_TPO | W2: PCT_GEO | X2: PCT_LOANPURPOSE | Y2: PCT_OCC | Z2: curtailsmm | AA2: defaultsmm | AB2: toverSmm | AC2: cashoutSmm | AD2: refiSmm | AE2: cumHPA | AF2: cumHPA05Pct | AG2: cumHPA15Pct | AH2: cumHPA20Pct | AI2: cumHPA25Pct | AJ2: cumHPA30Pct | AK2: cumHPA35Pct | AL2: cumHPA40Pct | AM2: adjtoverSmm | AN2: adjRefiSmm | AO2: groupByColumn | AP2: curve | AQ2: Balance | AR2: LoanCount | AS2: PCT_BROKER | AT2: PCT_CORRES | AU2: PCT_NonRETAIL | AV2: PCT_RETAIL | AW2: PCT_CashWindow | AX2: PCT_NonCashWindow | AY2: _Burnout_Fixed
A3: 97 | B3: 0.99833297 | C3: 0.26130405 | D3: 1.9821991 | E3: 0.0002180146 | F3: 0.0016670325 | G3: 0 | H3: 3.25 | I3: 3.7357636 | J3: -40.509727 | K3: -155.50095 | L3: 14.562552 | M3: 3.2725683 | N3: 80 | O3: 77.654292 | P3: 291131.11 | Q3: 274125.36 | R3: 774.19702 | S3: 0 | T3: 0 | U3: 0 | V3: 0.45074387 | W3: 0 | X3: 0 | Y3: 0 | Z3: 0.0001606861 | AA3: 5.3411715e-06 | AB3: 0.001500988 | AC3: 0 | AD3: 0 | AE3: 0.024554217 | AF3: 1 | AG3: 1 | AH3: 1 | AI3: 1 | AJ3: 1 | AK3: 1 | AL3: 1 | AM3: 0 | AN3: 0 | AO3: 02:-175--150 | AP3: =-175--150 -> -25 | AQ3: 822376.09 | AR3: 3 | AS3: 0 | AT3: 54.925613 | AU3: 54.925613 | AV3: 45.074387 | AW3: 45.074387 | AX3: 0 | AY3: 0
A4: 97 | B4: 0.99842362 | C4: 0.16230364 | D4: 1.8753433 | E4: 0.00013535375 | F4: 0.0015763819 | G4: 0 | H4: 3.5272566 | I4: 3.8043425 | J4: -22.033008 | K4: -133.73728 | L4: 15.318144 | M4: 4.2985068 | N4: 78.869899 | O4: 77.21009 | P4: 278644.18 | Q4: 260629.58 | R4: 780.52698 | S4: 0 | T4: 0 | U4: 0.044210759 | V4: 0.62073294 | W4: 0 | X4: 0.4786667 | Y4: 0 | Z4: 0.00021594279 | AA4: 1.9980674e-05 | AB4: 0.001338924 | AC4: 0 | AD4: 1.5205842e-06 | AE4: 0.013634735 | AF4: 0.95578924 | AG4: 1 | AH4: 1 | AI4: 1 | AJ4: 1 | AK4: 1 | AL4: 1 | AM4: 0 | AN4: 0 | AO4: 03:-150--125 | AP4: =-150--125 -> -25 | AQ4: 5994480.4 | AR4: 23 | AS4: 0 | AT4: 37.926706 | AU4: 37.926706 | AV4: 62.073294 | AW4: 62.073294 | AX4: 0 | AY4: 0
A5: 97 | B5: 0.9980806 | C5: 0.18121177 | D5: 2.2791191 | E5: 0.00015113537 | F5: 0.0019193993 | G5: 0 | H5: 3.6597934 | I5: 3.8379448 | J5: -23.588857 | K5: -109.75521 | L5: 15.30596 | M5: 4.9024314 | N5: 79.067811 | O5: 77.25009 | P5: 287089.08 | Q5: 248393.64 | R5: 779.35781 | S5: 0 | T5: 0 | U5: 0.066477551 | V5: 0.5786861 | W5: 0 | X5: 0.66174794 | Y5: 0 | Z5: 0.00026488139 | AA5: 2.0234425e-05 | AB5: 0.0014553005 | AC5: 0 | AD5: 0.00017896852 | AE5: 0.010841057 | AF5: 0.97253224 | AG5: 1 | AH5: 1 | AI5: 1 | AJ5: 1 | AK5: 1 | AL5: 1 | AM5: 0 | AN5: 0 | AO5: 04:-125--100 | AP5: =-125--100 -> -25 | AQ5: 24342577 | AR5: 98 | AS5: 0 | AT5: 42.13139 | AU5: 42.13139 | AV5: 57.86861 | AW5: 57.86861 | AX5: 0 | AY5: 0
A6: 97 | B6: 0.99802284 | C6: 3.6078533 | D6: 2.3469599 | E6: 0.0030574376 | F6: 0.0019771593 | G6: 0 | H6: 3.2951592 | I6: 3.8031731 | J6: -51.130374 | K6: -82.887944 | L6: 16.468467 | M6: 4.5559092 | N6: 78.442481 | O6: 76.520646 | P6: 264670.5 | Q6: 238741.99 | R6: 779.20984 | S6: 0 | T6: 0 | U6: 0.021720415 | V6: 0.72115303 | W6: 0 | X6: 0.55872654 | Y6: 0 | Z6: 0.00028078566 | AA6: 1.604513e-05 | AB6: 0.0014023499 | AC6: 0 | AD6: 0.00027796719 | AE6: 0.012095997 | AF6: 0.97058986 | AG6: 1 | AH6: 1 | AI6: 1 | AJ6: 1 | AK6: 1 | AL6: 1 | AM6: 0 | AN6: 0 | AO6: 05:-100--75 | AP6: =-100--75 -> -25 | AQ6: 1.9147108e+08 | AR6: 802 | AS6: 0 | AT6: 27.884697 | AU6: 27.884697 | AV6: 72.115303 | AW6: 72.115303 | AX6: 0 | AY6: 0.020677368
A7: 97 | B7: 0.99829917 | C7: 2.5251789 | D7: 2.0220101 | E7: 0.0021290709 | F7: 0.0017008291 | G7: 0 | H7: 3.4176098 | I7: 3.8696585 | J7: -46.76069 | K7: -57.590534 | L7: 16.353256 | M7: 4.4696039 | N7: 77.304998 | O7: 75.810597 | P7: 264339.53 | Q7: 242223.69 | R7: 780.28507 | S7: 0 | T7: 0 | U7: 0.047430635 | V7: 0.53831607 | W7: 0 | X7: 0.53935504 | Y7: 0 | Z7: 0.00023385913 | AA7: 1.8005624e-05 | AB7: 0.0013467223 | AC7: 0 | AD7: 0.00010223164 | AE7: 0.0099080295 | AF7: 0.97156969 | AG7: 0.99997862 | AH7: 1 | AI7: 1 | AJ7: 1 | AK7: 1 | AL7: 1 | AM7: 0 | AN7: 0 | AO7: 06:-75--50 | AP7: =-75--50 -> -25 | AQ7: 2.0998372e+09 | AR7: 8669 | AS7: 0 | AT7: 46.168393 | AU7: 46.168393 | AV7: 53.831607 | AW7: 53.831607 | AX7: 0 | AY7: 0.033571794
A8: 97 | B8: 0.99793548 | C8: 2.2766196 | D8: 2.4494838 | E8: 0.001917272 | F8: 0.0020645182 | G8: 0 | H8: 3.6403841 | I8: 3.9312025 | J8: -37.175533 | K8: -33.319482 | L8: 15.413077 | M8: 4.7861354 | N8: 74.92019 | O8: 73.22133 | P8: 278474.32 | Q8: 258664.79 | R8: 781.87721 | S8: 0 | T8: 0 | U8: 0.095435758 | V8: 0.39247208 | W8: 0 | X8: 0.62046666 | Y8: 0 | Z8: 0.0002312847 | AA8: 2.1392131e-05 | AB8: 0.0015898255 | AC8: 4.7241305e-09 | AD8: 0.00022199631 | AE8: 0.014420522 | AF8: 0.93978349 | AG8: 0.9998606 | AH8: 0.99999508 | AI8: 0.99999664 | AJ8: 1 | AK8: 1 | AL8: 1 | AM8: 0 | AN8: 0 | AO8: 07:-50--25 | AP8: =-50--25 -> -25 | AQ8: 2.2563329e+10 | AR8: 87230 | AS8: 0 | AT8: 60.752792 | AU8: 60.752792 | AV8: 39.247208 | AW8: 39.247208 | AX8: 0 | AY8: 0.024667824
A9: 97 | B9: 0.99751193 | C9: 2.9023812 | D9: 2.9451661 | E9: 0.0024514348 | F9: 0.002488072 | G9: 0 | H9: 3.706346 | I9: 3.9369143 | J9: -33.716192 | K9: -22.334933 | L9: 14.857801 | M9: 5.0207812 | N9: 71.926174 | O9: 70.058762 | P9: 288330.77 | Q9: 268583.17 | R9: 782.78234 | S9: 0 | T9: 0 | U9: 0.1044504 | V9: 0.36785414 | W9: 0 | X9: 0.70138515 | Y9: 0 | Z9: 0.0002396446 | AA9: 2.201004e-05 | AB9: 0.0017620538 | AC9: 5.5977508e-09 | AD9: 0.00046434322 | AE9: 0.017770583 | AF9: 0.90284197 | AG9: 0.99985315 | AH9: 0.99997747 | AI9: 1 | AJ9: 1 | AK9: 1 | AL9: 1 | AM9: 0 | AN9: 0 | AO9: 08-1:-25--20 | AP9: =-25--20 -> -5 | AQ9: 1.2758775e+10 | AR9: 47504 | AS9: 0 | AT9: 63.214586 | AU9: 63.214586 | AV9: 36.785414 | AW9: 36.785414 | AX9: 0 | AY9: 0.028662294
A10: 97 | B10: 0.99729572 | C10: 3.2032131 | D10: 3.1973015 | E10: 0.0027093552 | F10: 0.0027042798 | G10: 0 | H10: 3.7392656 | I10: 3.9359698 | J10: -32.212527 | K10: -17.367272 | L10: 14.50223 | M10: 5.200665 | N10: 70.594399 | O10: 68.707242 | P10: 295249.41 | Q10: 274993.91 | R10: 783.20152 | S10: 0 | T10: 0 | U10: 0.10321728 | V10: 0.36824829 | W10: 0 | X10: 0.72838232 | Y10: 0 | Z10: 0.00024584604 | AA10: 2.3257115e-05 | AB10: 0.0018292368 | AC10: 5.1401836e-09 | AD10: 0.00060591994 | AE10: 0.018369623 | AF10: 0.89009889 | AG10: 0.99978465 | AH10: 0.99997442 | AI10: 1 | AJ10: 1 | AK10: 1 | AL10: 1 | AM10: 0 | AN10: 0 | AO10: 08-2:-20--15 | AP10: =-20--15 -> -5 | AQ10: 17092521430 | AR10: 62156 | AS10: 0 | AT10: 63.175171 | AU10: 63.175171 | AV10: 36.824829 | AW10: 36.824829 | AX10: 0 | AY10: 0.041647693
A11: 97 | B11: 0.99703313 | C11: 4.5170378 | D11: 3.5027179 | E11: 0.0038444545 | F11: 0.0029668687 | G11: 0 | H11: 3.763594 | I11: 3.9206934 | J11: -30.353496 | K11: -12.402038 | L11: 14.443703 | M11: 5.5812302 | N11: 69.030042 | O11: 67.08445 | P11: 296549.13 | Q11: 276032.09 | R11: 783.22658 | S11: 0 | T11: 0 | U11: 0.094269616 | V11: 0.3601719 | W11: 0 | X11: 0.7388216 | Y11: 0 | Z11: 0.00025529552 | AA11: 2.5119771e-05 | AB11: 0.0019324644 | AC11: 4.9397321e-09 | AD11: 0.00075396938 | AE11: 0.019124926 | AF11: 0.8740921 | AG11: 0.99968867 | AH11: 0.99997655 | AI11: 1 | AJ11: 1 | AK11: 1 | AL11: 1 | AM11: 0 | AN11: 0 | AO11: 08-3:-15--10 | AP11: =-15--10 -> -5 | AQ11: 2.0836834e+10 | AR11: 75487 | AS11: 0 | AT11: 63.98281 | AU11: 63.98281 | AV11: 36.01719 | AW11: 36.01719 | AX11: 0 | AY11: 0.33634651
A12: 97 | B12: 0.99679391 | C12: 5.5688374 | D12: 3.7801851 | E12: 0.0047635395 | F12: 0.0032060889 | G12: 0 | H12: 3.7981737 | I12: 3.9037512 | J12: -27.922121 | K12: -7.4908218 | L12: 14.421523 | M12: 5.9852692 | N12: 69.510003 | O12: 67.501154 | P12: 297178.13 | Q12: 276508.02 | R12: 783.02563 | S12: 0 | T12: 0 | U12: 0.083687209 | V12: 0.35376725 | W12: 0 | X12: 0.7433794 | Y12: 0 | Z12: 0.00026209042 | AA12: 2.6911623e-05 | AB12: 0.0020148024 | AC12: 7.2078782e-09 | AD12: 0.00090226268 | AE12: 0.019365974 | AF12: 0.85335759 | AG12: 0.99948205 | AH12: 0.99998624 | AI12: 1 | AJ12: 1 | AK12: 1 | AL12: 1 | AM12: 0 | AN12: 0 | AO12: 08-4:-10--5 | AP12: =-10--5 -> -5 | AQ12: 2.3515901e+10 | AR12: 85046 | AS12: 0 | AT12: 64.623275 | AU12: 64.623275 | AV12: 35.376725 | AW12: 35.376725 | AX12: 0 | AY12: 1.6271224
A13: 97 | B13: 0.99653298 | C13: 7.1644601 | D13: 4.0820002 | E13: 0.0061759041 | F13: 0.00346702 | G13: 0 | H13: 3.8170273 | I13: 3.8825951 | J13: -26.300375 | K13: -2.4075089 | L13: 14.189775 | M13: 6.3344277 | N13: 68.355222 | O13: 66.29816 | P13: 301559.68 | Q13: 280888.12 | R13: 783.0112 | S13: 0 | T13: 0 | U13: 0.072013208 | V13: 0.34742339 | W13: 0 | X13: 0.74814443 | Y13: 0 | Z13: 0.00027086981 | AA13: 2.8370681e-05 | AB13: 0.0020925006 | AC13: 8.6823745e-09 | AD13: 0.0010752557 | AE13: 0.020306574 | AF13: 0.83709037 | AG13: 0.9991445 | AH13: 0.99998979 | AI13: 0.99999753 | AJ13: 1 | AK13: 1 | AL13: 1 | AM13: 0 | AN13: 0 | AO13: 08:-25-0 | AP13: =-25-0 -> -25 | AQ13: 2.7364682e+10 | AR13: 97422 | AS13: 0 | AT13: 65.257661 | AU13: 65.257661 | AV13: 34.742339 | AW13: 34.742339 | AX13: 0 | AY13: 3.8281215
A14: 97 | B14: 0.99620234 | C14: 8.8521007 | D14: 4.4632021 | E14: 0.0076941417 | F14: 0.0037976618 | G14: 0 | H14: 3.8637792 | I14: 3.8745511 | J14: -24.547966 | K14: 2.5749501 | L14: 14.34917 | M14: 6.9661342 | N14: 69.504712 | O14: 67.290785 | P14: 299077.72 | Q14: 278046.68 | R14: 782.79281 | S14: 0 | T14: 0 | U14: 0.059893911 | V14: 0.34156872 | W14: 0 | X14: 0.74353845 | Y14: 0 | Z14: 0.00028202297 | AA14: 3.183605e-05 | AB14: 0.0021957464 | AC14: 1.8329034e-08 | AD14: 0.0012880237 | AE14: 0.020230836 | AF14: 0.82736883 | AG14: 0.99877998 | AH14: 0.99996516 | AI14: 1 | AJ14: 1 | AK14: 1 | AL14: 1 | AM14: 0 | AN14: 0 | AO14: 09-1:0-5 | AP14: 0-5 | AQ14: 2.8507014e+10 | AR14: 102526 | AS14: 0 | AT14: 65.843128 | AU14: 65.843128 | AV14: 34.156872 | AW14: 34.156872 | AX14: 0 | AY14: 6.5534176
A15: 97 | B15: 0.995818 | C15: 10.904271 | D15: 4.9045654 | E15: 0.0095754262 | F15: 0.0041819996 | G15: 0 | H15: 3.9014199 | I15: 3.864134 | J15: -23.498066 | K15: 7.540442 | L15: 14.609501 | M15: 7.6447099 | N15: 68.92636 | O15: 66.691838 | P15: 293821.84 | Q15: 273049.64 | R15: 782.7708 | S15: 0 | T15: 0 | U15: 0.056353209 | V15: 0.3349724 | W15: 0 | X15: 0.74153986 | Y15: 0 | Z15: 0.000294315 | AA15: 3.5237191e-05 | AB15: 0.0023060552 | AC15: 4.8883762e-08 | AD15: 0.0015463292 | AE15: 0.019958804 | AF15: 0.81921162 | AG15: 0.99804752 | AH15: 0.99991392 | AI15: 0.99998862 | AJ15: 1 | AK15: 1 | AL15: 1 | AM15: 0 | AN15: 0 | AO15: 09-2:5-10 | AP15: 43230 | AQ15: 3.0239974e+10 | AR15: 110749 | AS15: 0 | AT15: 66.50276 | AU15: 66.50276 | AV15: 33.49724 | AW15: 33.49724 | AX15: 0 | AY15: 11.31499
A16: 97 | B16: 0.9952584 | C16: 14.002827 | D16: 5.5438582 | E16: 0.012492625 | F16: 0.0047416036 | G16: 0 | H16: 3.9578852 | I16: 3.8699165 | J16: -22.980733 | K16: 12.527276 | L16: 14.707416 | M16: 8.6019845 | N16: 69.31381 | O16: 66.948659 | P16: 292211.26 | Q16: 271327.41 | R16: 782.55568 | S16: 0 | T16: 0 | U16: 0.048480184 | V16: 0.32608776 | W16: 0 | X16: 0.74323334 | Y16: 0 | Z16: 0.00030836331 | AA16: 3.9228681e-05 | AB16: 0.0024557607 | AC16: 1.2838962e-07 | AD16: 0.0019381086 | AE16: 0.019745186 | AF16: 0.81163826 | AG16: 0.9967414 | AH16: 0.99972331 | AI16: 0.99995143 | AJ16: 1 | AK16: 1 | AL16: 1 | AM16: 0 | AN16: 0 | AO16: 09-3:10-15 | AP16: 43388 | AQ16: 3.4873712e+10 | AR16: 128530 | AS16: 0 | AT16: 67.38927 | AU16: 67.38927 | AV16: 32.61073 | AW16: 32.61073 | AX16: 0 | AY16: 19.077563
A17: 97 | B17: 0.99463567 | C17: 17.244109 | D17: 6.2506293 | E17: 0.015649174 | F17: 0.0053643298 | G17: 0 | H17: 4.0147816 | I17: 3.8798009 | J17: -22.760576 | K17: 17.528626 | L17: 14.725807 | M17: 9.7205173 | N17: 69.437098 | O17: 66.990268 | P17: 291290.28 | Q17: 271047.98 | R17: 782.6742 | S17: 0 | T17: 0 | U17: 0.042086768 | V17: 0.31382781 | W17: 0 | X17: 0.75251585 | Y17: 0 | Z17: 0.00032247629 | AA17: 4.3168092e-05 | AB17: 0.0025730807 | AC17: 2.5216964e-07 | AD17: 0.0024253388 | AE17: 0.018708914 | AF17: 0.80916352 | AG17: 0.99408256 | AH17: 0.99968214 | AI17: 0.99994157 | AJ17: 1 | AK17: 1 | AL17: 1 | AM17: 0 | AN17: 0 | AO17: 09-4:15-20 | AP17: 15-20 | AQ17: 3.8504534e+10 | AR17: 142058 | AS17: 0 | AT17: 68.614687 | AU17: 68.614687 | AV17: 31.385313 | AW17: 31.385313 | AX17: 0 | AY17: 32.921262
A18: 97 | B18: 0.99397648 | C18: 21.069423 | D18: 6.9935008 | E18: 0.019523686 | F18: 0.0060235197 | G18: 0 | H18: 4.043684 | I18: 3.8720952 | J18: -22.362804 | K18: 22.543948 | L18: 14.47741 | M18: 10.47453 | N18: 67.823588 | O18: 65.233278 | P18: 296099.13 | Q18: 275599.6 | R18: 782.70335 | S18: 0 | T18: 0 | U18: 0.040518232 | V18: 0.31265171 | W18: 0 | X18: 0.75911106 | Y18: 0 | Z18: 0.00033241406 | AA18: 4.5092679e-05 | AB18: 0.0026704932 | AC18: 5.2559592e-07 | AD18: 0.0029749807 | AE18: 0.020591337 | AF18: 0.79097261 | AG18: 0.99085171 | AH18: 0.99938978 | AI18: 0.999863 | AJ18: 1 | AK18: 1 | AL18: 1 | AM18: 0 | AN18: 0 | AO18: 09:0-25 | AP18: 0-25 | AQ18: 4.2866486e+10 | AR18: 155539 | AS18: 0 | AT18: 68.733949 | AU18: 68.733949 | AV18: 31.266051 | AW18: 31.266051 | AX18: 0 | AY18: 51.265645
A19: 97 | B19: 0.99334906 | C19: 23.063402 | D19: 7.6955562 | E19: 0.021612081 | F19: 0.0066509423 | G19: 0 | H19: 4.080554 | I19: 3.8625394 | J19: -21.393001 | K19: 27.523059 | L19: 14.579448 | M19: 11.278876 | N19: 68.399355 | O19: 65.529784 | P19: 294526.49 | Q19: 273743.06 | R19: 782.53593 | S19: 0 | T19: 0 | U19: 0.038080922 | V19: 0.31095846 | W19: 0 | X19: 0.75527821 | Y19: 0 | Z19: 0.00034120649 | AA19: 4.8394569e-05 | AB19: 0.002743361 | AC19: 8.3452158e-07 | AD19: 0.0035171324 | AE19: 0.022744783 | AF19: 0.77371183 | AG19: 0.98435998 | AH19: 0.99926501 | AI19: 0.99978341 | AJ19: 1 | AK19: 1 | AL19: 1 | AM19: 0 | AN19: 0 | AO19: 10-1:25-30 | AP19: 25-30 | AQ19: 4.3570041e+10 | AR19: 159164 | AS19: 0 | AT19: 68.902598 | AU19: 68.902598 | AV19: 31.097402 | AW19: 31.097402 | AX19: 0 | AY19: 73.319059
A20: 97 | B20: 0.99276784 | C20: 25.027503 | D20: 8.3415774 | E20: 0.023718264 | F20: 0.0072321641 | G20: 0 | H20: 4.1027406 | I20: 3.8402996 | J20: -20.75564 | K20: 32.511491 | L20: 14.592738 | M20: 11.839008 | N20: 68.156254 | O20: 65.177773 | P20: 293515.87 | Q20: 273384.45 | R20: 782.6238 | S20: 0 | T20: 0 | U20: 0.036990865 | V20: 0.31948025 | W20: 0 | X20: 0.75414459 | Y20: 0 | Z20: 0.00034765967 | AA20: 5.1752209e-05 | AB20: 0.0027994829 | AC20: 1.3959302e-06 | AD20: 0.0040318601 | AE20: 0.024530157 | AF20: 0.75628599 | AG20: 0.97965777 | AH20: 0.99872128 | AI20: 0.99974782 | AJ20: 1 | AK20: 1 | AL20: 1 | AM20: 0 | AN20: 0 | AO20: 10-2:30-35 | AP20: 30-35 | AQ20: 4.3981817e+10 | AR20: 160879 | AS20: 0 | AT20: 68.048233 | AU20: 68.048233 | AV20: 31.951767 | AW20: 31.951767 | AX20: 0 | AY20: 94.54859
A21: 97 | B21: 0.99209712 | C21: 27.830949 | D21: 9.0819204 | E21: 0.026813857 | F21: 0.0079028825 | G21: 0 | H21: 4.1348421 | I21: 3.827725 | J21: -20.038956 | K21: 37.477156 | L21: 14.487705 | M21: 12.607813 | N21: 67.879502 | O21: 64.682708 | P21: 295895.42 | Q21: 275423.54 | R21: 782.57786 | S21: 0 | T21: 0 | U21: 0.033245687 | V21: 0.31884608 | W21: 0 | X21: 0.74620281 | Y21: 0 | Z21: 0.0003534843 | AA21: 5.6024627e-05 | AB21: 0.0028690502 | AC21: 1.6527383e-06 | AD21: 0.0046226575 | AE21: 0.026445154 | AF21: 0.73125549 | AG21: 0.97947389 | AH21: 0.99839829 | AI21: 0.99967124 | AJ21: 1 | AK21: 1 | AL21: 1 | AM21: 0 | AN21: 0 | AO21: 10-3:35-40 | AP21: 35-40 | AQ21: 4.4207957e+10 | AR21: 160509 | AS21: 0 | AT21: 68.114534 | AU21: 68.114534 | AV21: 31.885466 | AW21: 31.885466 | AX21: 0 | AY21: 118.1742
A22: 97 | B22: 0.99144967 | C22: 31.45781 | D22: 9.7913692 | E22: 0.030986491 | F22: 0.0085503261 | G22: 0 | H22: 4.1831056 | I22: 3.8234898 | J22: -19.308467 | K22: 42.441471 | L22: 14.535832 | M22: 13.466146 | N22: 68.134365 | O22: 64.854192 | P22: 295673.58 | Q22: 274474.32 | R22: 782.37062 | S22: 0 | T22: 0 | U22: 0.029554947 | V22: 0.31628243 | W22: 0 | X22: 0.73742217 | Y22: 0 | Z22: 0.00035962518 | AA22: 6.1795145e-05 | AB22: 0.0029245869 | AC22: 2.2833316e-06 | AD22: 0.0052020225 | AE22: 0.026782477 | AF22: 0.72475109 | AG22: 0.97632537 | AH22: 0.99778689 | AI22: 0.9997711 | AJ22: 1 | AK22: 1 | AL22: 1 | AM22: 0 | AN22: 0 | AO22: 10-4:40-45 | AP22: 40-45 | AQ22: 4.0881577e+10 | AR22: 148945 | AS22: 0 | AT22: 68.371757 | AU22: 68.371757 | AV22: 31.628243 | AW22: 31.628243 | AX22: 0 | AY22: 144.31374
A23: 97 | B23: 0.99072239 | C23: 33.304222 | D23: 10.58225 | E23: 0.033189121 | F23: 0.0092776097 | G23: 0 | H23: 4.2389415 | I23: 3.8269869 | J23: -18.56358 | K23: 47.518166 | L23: 14.521738 | M23: 14.59814 | N23: 67.828227 | O23: 64.551916 | P23: 295745.68 | Q23: 274652.3 | R23: 782.20509 | S23: 0 | T23: 0 | U23: 0.023834157 | V23: 0.30543286 | W23: 0 | X23: 0.72540982 | Y23: 0 | Z23: 0.00036543652 | AA23: 6.9434013e-05 | AB23: 0.0030125581 | AC23: 2.5641522e-06 | AD23: 0.0058276038 | AE23: 0.0254136 | AF23: 0.72717763 | AG23: 0.97756361 | AH23: 0.99767709 | AI23: 0.9998045 | AJ23: 1 | AK23: 1 | AL23: 1 | AM23: 0 | AN23: 0 | AO23: 10:25-50 | AP23: 25-50 | AQ23: 3.919096e+10 | AR23: 142693 | AS23: 0 | AT23: 69.456714 | AU23: 69.456714 | AV23: 30.543286 | AW23: 30.543286 | AX23: 0 | AY23: 174.12595
A24: 97 | B24: 0.99008101 | C24: 33.412905 | D24: 11.274432 | E24: 0.033320507 | F24: 0.0099189865 | G24: 0 | H24: 4.3180088 | I24: 3.8417096 | J24: -17.463033 | K24: 52.504461 | L24: 14.887496 | M24: 16.089802 | N24: 69.557278 | O24: 66.210126 | P24: 289074.81 | Q24: 268000.81 | R24: 781.78016 | S24: 0 | T24: 0 | U24: 0.019533417 | V24: 0.29306856 | W24: 0 | X24: 0.70769 | Y24: 0 | Z24: 0.00037173065 | AA24: 8.2806942e-05 | AB24: 0.0031134834 | AC24: 2.6524879e-06 | AD24: 0.0063482996 | AE24: 0.021343834 | AF24: 0.74321936 | AG24: 0.97898505 | AH24: 0.99781394 | AI24: 0.99980767 | AJ24: 1 | AK24: 1 | AL24: 1 | AM24: 0 | AN24: 0 | AO24: 11-1:50-55 | AP24: 50-55 | AQ24: 3.5465887e+10 | AR24: 132335 | AS24: 0 | AT24: 70.693144 | AU24: 70.693144 | AV24: 29.306856 | AW24: 29.306856 | AX24: 0 | AY24: 205.96089
A25: 97 | B25: 0.98941934 | C25: 35.483123 | D25: 11.983369 | E25: 0.035861457 | F25: 0.01058066 | G25: 0 | H25: 4.3828476 | I25: 3.8523699 | J25: -17.323485 | K25: 57.483953 | L25: 15.128447 | M25: 17.615636 | N25: 69.370722 | O25: 66.117421 | P25: 284722.57 | Q25: 263601.22 | R25: 781.65219 | S25: 0 | T25: 0 | U25: 0.016827545 | V25: 0.27475101 | W25: 0 | X25: 0.70253618 | Y25: 0 | Z25: 0.00037826165 | AA25: 9.7685403e-05 | AB25: 0.0031965205 | AC25: 3.2926443e-06 | AD25: 0.0069048864 | AE25: 0.017894567 | AF25: 0.76065412 | AG25: 0.97939804 | AH25: 0.9974502 | AI25: 0.99959005 | AJ25: 1 | AK25: 1 | AL25: 1 | AM25: 0 | AN25: 0 | AO25: 11-2:55-60 | AP25: 55-60 | AQ25: 3.4266578e+10 | AR25: 129994 | AS25: 0 | AT25: 72.524899 | AU25: 72.524899 | AV25: 27.475101 | AW25: 27.475101 | AX25: 0 | AY25: 247.53419
A26: 97 | B26: 0.98867875 | C26: 36.916194 | D26: 12.770695 | E26: 0.037664536 | F26: 0.011321247 | G26: 0 | H26: 4.4570138 | I26: 3.873694 | J26: -17.37229 | K26: 62.493872 | L26: 15.300089 | M26: 19.219581 | N26: 69.640995 | O26: 66.478468 | P26: 281394.51 | Q26: 260887.2 | R26: 781.25669 | S26: 0 | T26: 0 | U26: 0.015796997 | V26: 0.25155199 | W26: 0 | X26: 0.69517778 | Y26: 0 | Z26: 0.00038188402 | AA26: 0.00011628449 | AB26: 0.003282456 | AC26: 3.3856391e-06 | AD26: 0.0075372228 | AE26: 0.012960875 | AF26: 0.77964598 | AG26: 0.98196677 | AH26: 0.99752558 | AI26: 0.99960562 | AJ26: 1 | AK26: 1 | AL26: 1 | AM26: 0 | AN26: 0 | AO26: 11-3:60-65 | AP26: 60-65 | AQ26: 3.5359608e+10 | AR26: 135536 | AS26: 0 | AT26: 74.844801 | AU26: 74.844801 | AV26: 25.155199 | AW26: 25.155199 | AX26: 0 | AY26: 297.70248
A27: 97 | B27: 0.98805992 | C27: 37.34521 | D27: 13.423621 | E27: 0.038211625 | F27: 0.011940076 | G27: 0 | H27: 4.5265381 | I27: 3.8931776 | J27: -17.357444 | K27: 67.507788 | L27: 15.524625 | M27: 20.507183 | N27: 69.628969 | O27: 66.643585 | P27: 277328.62 | Q27: 257076.01 | R27: 781.11713 | S27: 0 | T27: 0 | U27: 0.016723574 | V27: 0.23597175 | W27: 0 | X27: 0.69099868 | Y27: 0 | Z27: 0.00038698645 | AA27: 0.00013357149 | AB27: 0.0033189158 | AC27: 3.9252188e-06 | AD27: 0.0080966625 | AE27: 0.007362507 | AF27: 0.80371152 | AG27: 0.98172644 | AH27: 0.99727104 | AI27: 0.99956676 | AJ27: 1 | AK27: 1 | AL27: 1 | AM27: 0 | AN27: 0 | AO27: 11-4:65-70 | AP27: 65-70 | AQ27: 3.6614566e+10 | AR27: 142427 | AS27: 0 | AT27: 76.402825 | AU27: 76.402825 | AV27: 23.597175 | AW27: 23.597175 | AX27: 0 | AY27: 353.87949
A28: 97 | B28: 0.98724113 | C28: 38.800417 | D28: 14.280642 | E28: 0.040093265 | F28: 0.012758865 | G28: 0 | H28: 4.5629607 | I28: 3.8915188 | J28: -17.338162 | K28: 72.521817 | L28: 15.200947 | M28: 21.458715 | N28: 68.415455 | O28: 65.44972 | P28: 282548.22 | Q28: 262505.17 | R28: 781.02953 | S28: 0 | T28: 0 | U28: 0.016188388 | V28: 0.22642586 | W28: 0 | X28: 0.69552406 | Y28: 0 | Z28: 0.00038991503 | AA28: 0.00014459484 | AB28: 0.0033562306 | AC28: 4.5622395e-06 | AD28: 0.0088635481 | AE28: 0.0062719663 | AF28: 0.79883958 | AG28: 0.98129144 | AH28: 0.99689562 | AI28: 0.99964418 | AJ28: 1 | AK28: 1 | AL28: 1 | AM28: 0 | AN28: 0 | AO28: 11:50-75 | AP28: 50-75 | AQ28: 3.9348475e+10 | AR28: 149896 | AS28: 0 | AT28: 77.357414 | AU28: 77.357414 | AV28: 22.642586 | AW28: 22.642586 | AX28: 0 | AY28: 414.10153
... A36: 97 | B36: 0.96185187 | C36: 84.603245 | D36: 37.295557 | E36: 0.14437047 | F36: 0.038148132 | G36: 0 | H36: 5.75 | I36: 4.1387574 | J36: 54.4553 | K36: 254.14738 | L36: 23.888925 | M36: 31.426217 | N36: 95 | O36: 57.497761 | P36: 170045.7 | Q36: 166421.72 | R36: 782 | S36: 0 | T36: 0 | U36: 0 | V36: 0 | W36: 0 | X36: 0 | Y36: 0 | Z36: 0.0016004217 | AA36: 0.0016422781 | AB36: 0.0061079827 | AC36: 0 | AD36: 0.028797429 | AE36: -0.06000343 | AF36: 1 | AG36: 1 | AH36: 1 | AI36: 1 | AJ36: 1 | AK36: 1 | AL36: 1 | AM36: 0 | AN36: 0 | AO36: 999:>= 250 | AP36: >= 250 | AQ36: 332843.44 | AR36: 2 | AS36: 0 | AT36: 100 | AU36: 100 | AV36: 0 | AW36: 0 | AX36: 0 | AY36: 1089.0234
F40: high media
A41: modelId | B41: SFACTOR_PREPAY_TRACKING_CPR | C41: PREPAY_CPR1 | D41: PREPAY_TRACKING_CPR1 | E41: PREPAY_SMM1 | F41: PREPAY_TRACKING_SMM1 | G41: PCT_LOANTYPE | H41: _ORIGNOTERATE | I41: _ZEROSATO | J41: _SATO | K41: _REFI_INCENTIVE_Fixed | L41: _Fixed_cost | M41: _LOANAGE | N41: _LTV | O41: _CLTV | P41: _AVG_LOANSIZE_SCHAMBALANCE | Q41: _WACLS | R41: _FICO | S41: PCT_ISSECONDLIEN | T41: _OrigCombLTV | U41: PCT_SVC | V41: PCT_TPO | W41: PCT_GEO | X41: PCT_LOANPURPOSE | Y41: PCT_OCC | Z41: curtailsmm | AA41: defaultsmm | AB41: toverSmm | AC41: cashoutSmm | AD41: refiSmm | AE41: cumHPA | AF41: cumHPA05Pct | AG41: cumHPA15Pct | AH41: cumHPA20Pct | AI41: cumHPA25Pct | AJ41: cumHPA30Pct | AK41: cumHPA35Pct | AL41: cumHPA40Pct | AM41: adjtoverSmm | AN41: adjRefiSmm | AO41: groupByColumn | AP41: curve | AQ41: Balance | AR41: LoanCount | AS41: PCT_BROKER | AT41: PCT_CORRES | AU41: PCT_NonRETAIL | AV41: PCT_RETAIL | AW41: PCT_CashWindow | AX41: PCT_NonCashWindow | AY41: _Burnout_Fixed
A42: 96 | B42: 0.99833297 | C42: 0.26130405 | D42: 1.9821991 | E42: 0.0002180146 | F42: 0.0016670325 | G42: 0 | H42: 3.25 | I42: 3.7357636 | J42: -40.509727 | K42: -155.50095 | L42: 14.562552 | M42: 3.2725683 | N42: 80 | O42: 77.654292 | P42: 291131.11 | Q42: 274125.36 | R42: 774.19702 | S42: 0 | T42: 0 | U42: 0 | V42: 0.45074387 | W42: 0 | X42: 0 | Y42: 0 | Z42: 0.0001606861 | AA42: 5.3411715e-06 | AB42: 0.001500988 | AC42: 0 | AD42: 0 | AE42: 0.024554217 | AF42: 1 | AG42: 1 | AH42: 1 | AI42: 1 | AJ42: 1 | AK42: 1 | AL42: 1 | AM42: 0 | AN42: 0 | AO42: 02:-175--150 | AP42: =-175--150 -> -25 | AQ42: 822376.09 | AR42: 3 | AS42: 0 | AT42: 54.925613 | AU42: 54.925613 | AV42: 45.074387 | AW42: 45.074387 | AX42: 0 | AY42: 0
A43: 96 | B43: 0.99840708 | C43: 0.16230364 | D43: 1.8948401 | E43: 0.00013535375 | F43: 0.0015929152 | G43: 0 | H43: 3.5272566 | I43: 3.8043425 | J43: -22.033008 | K43: -133.73728 | L43: 15.318144 | M43: 4.2985068 | N43: 78.869899 | O43: 77.21009 | P43: 278644.18 | Q43: 260629.58 | R43: 780.52698 | S43: 0 | T43: 0 | U43: 0.044210759 | V43: 0.62073294 | W43: 0 | X43: 0.4786667 | Y43: 0 | Z43: 0.00021594279 | AA43: 1.9980674e-05 | AB43: 0.001338924 | AC43: 0 | AD43: 1.8054137e-05 | AE43: 0.013634735 | AF43: 0.95578924 | AG43: 1 | AH43: 1 | AI43: 1 | AJ43: 1 | AK43: 1 | AL43: 1 | AM43: 0 | AN43: 0 | AO43: 03:-150--125 | AP43: =-150--125 -> -25 | AQ43: 5994480.4 | AR43: 23 | AS43: 0 | AT43: 37.926706 | AU43: 37.926706 | AV43: 62.073294 | AW43: 62.073294 | AX43: 0 | AY43: 0
A44: 96 | B44: 0.99672241 | C44: 0.18121177 | D44: 3.8629782 | E44: 0.00015113537 | F44: 0.0032775921 | G44: 0 | H44: 3.6597934 | I44: 3.8379448 | J44: -23.588857 | K44: -109.75521 | L44: 15.30596 | M44: 4.9024314 | N44: 79.067811 | O44: 77.25009 | P44: 287089.08 | Q44: 248393.64 | R44: 779.35781 | S44: 0 | T44: 0 | U44: 0.066477551 | V44: 0.5786861 | W44: 0 | X44: 0.66174794 | Y44: 0 | Z44: 0.00026488139 | AA44: 2.0234425e-05 | AB44: 0.0014553005 | AC44: 0 | AD44: 0.0015371609 | AE44: 0.010841057 | AF44: 0.97253224 | AG44: 1 | AH44: 1 | AI44: 1 | AJ44: 1 | AK44: 1 | AL44: 1 | AM44: 0 | AN44: 0 | AO44: 04:-125--100 | AP44: =-125--100 -> -25 | AQ44: 24342577 | AR44: 98 | AS44: 0 | AT44: 42.13139 | AU44: 42.13139 | AV44: 57.86861 | AW44: 57.86861 | AX44: 0 | AY44: 0
A45: 96 | B45: 0.9963176 | C45: 3.6078533 | D45: 4.330471 | E45: 0.0030574376 | F45: 0.0036823982 | G45: 0 | H45: 3.2951592 | I45: 3.8031731 | J45: -51.130374 | K45: -82.887944 | L45: 16.468467 | M45: 4.5559092 | N45: 78.442481 | O45: 76.520646 | P45: 264670.5 | Q45: 238741.99 | R45: 779.20984 | S45: 0 | T45: 0 | U45: 0.021720415 | V45: 0.72115303 | W45: 0 | X45: 0.55872654 | Y45: 0 | Z45: 0.00028078566 | AA45: 1.604513e-05 | AB45: 0.0014023499 | AC45: 0 | AD45: 0.0019832061 | AE45: 0.012095997 | AF45: 0.97058986 | AG45: 1 | AH45: 1 | AI45: 1 | AJ45: 1 | AK45: 1 | AL45: 1 | AM45: 0 | AN45: 0 | AO45: 05:-100--75 | AP45: =-100--75 -> -25 | AQ45: 1.9147108e+08 | AR45: 802 | AS45: 0 | AT45: 27.884697 | AU45: 27.884697 | AV45: 72.115303 | AW45: 72.115303 | AX45: 0 | AY45: 0.020677368
A46: 96 | B46: 0.9978104 | C46: 2.5251789 | D46: 2.5961107 | E46: 0.0021290709 | F46: 0.002189603 | G46: 0 | H46: 3.4176098 | I46: 3.8696585 | J46: -46.76069 | K46: -57.590534 | L46: 16.353256 | M46: 4.4696039 | N46: 77.304998 | O46: 75.810597 | P46: 264339.53 | Q46: 242223.69 | R46: 780.28507 | S46: 0 | T46: 0 | U46: 0.047430635 | V46: 0.53831607 | W46: 0 | X46: 0.53935504 | Y46: 0 | Z46: 0.00023385913 | AA46: 1.8005624e-05 | AB46: 0.0013467223 | AC46: 0 | AD46: 0.00059100512 | AE46: 0.0099080295 | AF46: 0.97156969 | AG46: 0.99997862 | AH46: 1 | AI46: 1 | AJ46: 1 | AK46: 1 | AL46: 1 | AM46: 0 | AN46: 0 | AO46: 06:-75--50 | AP46: =-75--50 -> -25 | AQ46: 2.0998372e+09 | AR46: 8669 | AS46: 0 | AT46: 46.168393 | AU46: 46.168393 | AV46: 53.831607 | AW46: 53.831607 | AX46: 0 | AY46: 0.033571794
A47: 96 | B47: 0.99625689 | C47: 2.2766196 | D47: 4.4004004 | E47: 0.001917272 | F47: 0.0037431066 | G47: 0 | H47: 3.6403841 | I47: 3.9312025 | J47: -37.175533 | K47: -33.319482 | L47: 15.413077 | M47: 4.7861354 | N47: 74.92019 | O47: 73.22133 | P47: 278474.32 | Q47: 258664.79 | R47: 781.87721 | S47: 0 | T47: 0 | U47: 0.095435758 | V47: 0.39247208 | W47: 0 | X47: 0.62046666 | Y47: 0 | Z47: 0.0002312847 | AA47: 2.1392131e-05 | AB47: 0.0015898255 | AC47: 4.7241305e-09 | AD47: 0.0019005847 | AE47: 0.014420522 | AF47: 0.93978349 | AG47: 0.9998606 | AH47: 0.99999508 | AI47: 0.99999664 | AJ47: 1 | AK47: 1 | AL47: 1 | AM47: 0 | AN47: 0 | AO47: 07:-50--25 | AP47: =-50--25 -> -25 | AQ47: 2.2563329e+10 | AR47: 87230 | AS47: 0 | AT47: 60.752792 | AU47: 60.752792 | AV47: 39.247208 | AW47: 39.247208 | AX47: 0 | AY47: 0.024667824
A48: 96 | B48: 0.99410145 | C48: 2.9023812 | D48: 6.8530878 | E48: 0.0024514348 | F48: 0.0058985547 | G48: 0 | H48: 3.706346 | I48: 3.9369143 | J48: -33.716192 | K48: -22.334933 | L48: 14.857801 | M48: 5.0207812 | N48: 71.926174 | O48: 70.058762 | P48: 288330.77 | Q48: 268583.17 | R48: 782.78234 | S48: 0 | T48: 0 | U48: 0.1044504 | V48: 0.36785414 | W48: 0 | X48: 0.70138515 | Y48: 0 | Z48: 0.0002396446 | AA48: 2.201004e-05 | AB48: 0.0017620538 | AC48: 5.5977508e-09 | AD48: 0.0038748259 | AE48: 0.017770583 | AF48: 0.90284197 | AG48: 0.99985315 | AH48: 0.99997747 | AI48: 1 | AJ48: 1 | AK48: 1 | AL48: 1 | AM48: 0 | AN48: 0 | AO48: 08-1:-25--20 | AP48: =-25--20 -> -5 | AQ48: 1.2758775e+10 | AR48: 47504 | AS48: 0 | AT48: 63.214586 | AU48: 63.214586 | AV48: 36.785414 | AW48: 36.785414 | AX48: 0 | AY48: 0.028662294
A49: 96 | B49: 0.9929889 | C49: 3.2032131 | D49: 8.0963596 | E49: 0.0027093552 | F49: 0.0070111021 | G49: 0 | H49: 3.7392656 | I49: 3.9359698 | J49: -32.212527 | K49: -17.367272 | L49: 14.50223 | M49: 5.200665 | N49: 70.594399 | O49: 68.707242 | P49: 295249.41 | Q49: 274993.91 | R49: 783.20152 | S49: 0 | T49: 0 | U49: 0.10321728 | V49: 0.36824829 | W49: 0 | X49: 0.72838232 | Y49: 0 | Z49: 0.00024584604 | AA49: 2.3257115e-05 | AB49: 0.0018292368 | AC49: 5.1401836e-09 | AD49: 0.0049127422 | AE49: 0.018369623 | AF49: 0.89009889 | AG49: 0.99978465 | AH49: 0.99997442 | AI49: 1 | AJ49: 1 | AK49: 1 | AL49: 1 | AM49: 0 | AN49: 0 | AO49: 08-2:-20--15 | AP49: =-20--15 -> -5 | AQ49: 17092521430 | AR49: 62156 | AS49: 0 | AT49: 63.175171 | AU49: 63.175171 | AV49: 36.824829 | AW49: 36.824829 | AX49: 0 | AY49: 0.041647693
A50: 96 | B50: 0.99183844 | C50: 4.5170378 | D50: 9.3659791 | E50: 0.0038444545 | F50: 0.0081615569 | G50: 0 | H50: 3.763594 | I50: 3.9206934 | J50: -30.353496 | K50: -12.402038 | L50: 14.443703 | M50: 5.5812302 | N50: 69.030042 | O50: 67.08445 | P50: 296549.13 | Q50: 276032.09 | R50: 783.22658 | S50: 0 | T50: 0 | U50: 0.094269616 | V50: 0.3601719 | W50: 0 | X50: 0.7388216 | Y50: 0 | Z50: 0.00025529552 | AA50: 2.5119771e-05 | AB50: 0.0019324644 | AC50: 4.9397321e-09 | AD50: 0.0059486576 | AE50: 0.019124926 | AF50: 0.8740921 | AG50: 0.99968867 | AH50: 0.99997655 | AI50: 1 | AJ50: 1 | AK50: 1 | AL50: 1 | AM50: 0 | AN50: 0 | AO50: 08-3:-15--10 | AP50: =-15--10 -> -5 | AQ50: 2.0836834e+10 | AR50: 75487 | AS50: 0 | AT50: 63.98281 | AU50: 63.98281 | AV50: 36.01719 | AW50: 36.01719 | AX50: 0 | AY50: 0.33634651
A51: 96 | B51: 0.99073648 | C51: 5.5688374 | D51: 10.566985 | E51: 0.0047635395 | F51: 0.0092635161 | G51: 0 | H51: 3.7981737 | I51: 3.9037512 | J51: -27.922121 | K51: -7.4908218 | L51: 14.421523 | M51: 5.9852692 | N51: 69.510003 | O51: 67.501154 | P51: 297178.13 | Q51: 276508.02 | R51: 783.02563 | S51: 0 | T51: 0 | U51: 0.083687209 | V51: 0.35376725 | W51: 0 | X51: 0.7433794 | Y51: 0 | Z51: 0.00026209042 | AA51: 2.6911623e-05 | AB51: 0.0020148024 | AC51: 7.2078782e-09 | AD51: 0.0069596899 | AE51: 0.019365974 | AF51: 0.85335759 | AG51: 0.99948205 | AH51: 0.99998624 | AI51: 1 | AJ51: 1 | AK51: 1 | AL51: 1 | AM51: 0 | AN51: 0 | AO51: 08-4:-10--5 | AP51: =-10--5 -> -5 | AQ51: 2.3515901e+10 | AR51: 85046 | AS51: 0 | AT51: 64.623275 | AU51: 64.623275 | AV51: 35.376725 | AW51: 35.376725 | AX51: 0 | AY51: 1.6271224
A52: 96 | B52: 0.98955811 | C52: 7.1644601 | D52: 11.835114 | E52: 0.0061759041 | F52: 0.010441886 | G52: 0 | H52: 3.8170273 | I52: 3.8825951 | J52: -26.300375 | K52: -2.4075089 | L52: 14.189775 | M52: 6.3344277 | N52: 68.355222 | O52: 66.29816 | P52: 301559.68 | Q52: 280888.12 | R52: 783.0112 | S52: 0 | T52: 0 | U52: 0.072013208 | V52: 0.34742339 | W52: 0 | X52: 0.74814443 | Y52: 0 | Z52: 0.00027086981 | AA52: 2.8370681e-05 | AB52: 0.0020925006 | AC52: 8.6823745e-09 | AD52: 0.0080501214 | AE52: 0.020306574 | AF52: 0.83709037 | AG52: 0.9991445 | AH52: 0.99998979 | AI52: 0.99999753 | AJ52: 1 | AK52: 1 | AL52: 1 | AM52: 0 | AN52: 0 | AO52: 08:-25-0 | AP52: =-25-0 -> -25 | AQ52: 2.7364682e+10 | AR52: 97422 | AS52: 0 | AT52: 65.257661 | AU52: 65.257661 | AV52: 34.742339 | AW52: 34.742339 | AX52: 0 | AY52: 3.8281215
A53: 96 | B53: 0.98824066 | C53: 8.8521007 | D53: 13.233387 | E53: 0.0076941417 | F53: 0.011759336 | G53: 0 | H53: 3.8637792 | I53: 3.8745511 | J53: -24.547966 | K53: 2.5749501 | L53: 14.34917 | M53: 6.9661342 | N53: 69.504712 | O53: 67.290785 | P53: 299077.72 | Q53: 278046.68 | R53: 782.79281 | S53: 0 | T53: 0 | U53: 0.059893911 | V53: 0.34156872 | W53: 0 | X53: 0.74353845 | Y53: 0 | Z53: 0.00028202297 | AA53: 3.183605e-05 | AB53: 0.0021957464 | AC53: 1.8329034e-08 | AD53: 0.0092496976 | AE53: 0.020230836 | AF53: 0.82736883 | AG53: 0.99877998 | AH53: 0.99996516 | AI53: 1 | AJ53: 1 | AK53: 1 | AL53: 1 | AM53: 0 | AN53: 0 | AO53: 09-1:0-5 | AP53: 0-5 | AQ53: 2.8507014e+10 | AR53: 102526 | AS53: 0 | AT53: 65.843128 | AU53: 65.843128 | AV53: 34.156872 | AW53: 34.156872 | AX53: 0 | AY53: 6.5534176
A54: 96 | B54: 0.98687262 | C54: 10.904271 | D54: 14.66382 | E54: 0.0095754262 | F54: 0.013127381 | G54: 0 | H54: 3.9014199 | I54: 3.864134 | J54: -23.498066 | K54: 7.540442 | L54: 14.609501 | M54: 7.6447099 | N54: 68.92636 | O54: 66.691838 | P54: 293821.84 | Q54: 273049.64 | R54: 782.7708 | S54: 0 | T54: 0 | U54: 0.056353209 | V54: 0.3349724 | W54: 0 | X54: 0.74153986 | Y54: 0 | Z54: 0.000294315 | AA54: 3.5237191e-05 | AB54: 0.0023060552 | AC54: 4.8883762e-08 | AD54: 0.01049171 | AE54: 0.019958804 | AF54: 0.81921162 | AG54: 0.99804752 | AH54: 0.99991392 | AI54: 0.99998862 | AJ54: 1 | AK54: 1 | AL54: 1 | AM54: 0 | AN54: 0 | AO54: 09-2:5-10 | AP54: 43230 | AQ54: 3.0239974e+10 | AR54: 110749 | AS54: 0 | AT54: 66.50276 | AU54: 66.50276 | AV54: 33.49724 | AW54: 33.49724 | AX54: 0 | AY54: 11.31499
A55: 96 | B55: 0.9849319 | C55: 14.002827 | D55: 16.655984 | E55: 0.012492625 | F55: 0.015068104 | G55: 0 | H55: 3.9578852 | I55: 3.8699165 | J55: -22.980733 | K55: 12.527276 | L55: 14.707416 | M55: 8.6019845 | N55: 69.31381 | O55: 66.948659 | P55: 292211.26 | Q55: 271327.41 | R55: 782.55568 | S55: 0 | T55: 0 | U55: 0.048480184 | V55: 0.32608776 | W55: 0 | X55: 0.74323334 | Y55: 0 | Z55: 0.00030836331 | AA55: 3.9228681e-05 | AB55: 0.0024557607 | AC55: 1.2838962e-07 | AD55: 0.012264609 | AE55: 0.019745186 | AF55: 0.81163826 | AG55: 0.9967414 | AH55: 0.99972331 | AI55: 0.99995143 | AJ55: 1 | AK55: 1 | AL55: 1 | AM55: 0 | AN55: 0 | AO55: 09-3:10-15 | AP55: 43388 | AQ55: 3.4873712e+10 | AR55: 128530 | AS55: 0 | AT55: 67.38927 | AU55: 67.38927 | AV55: 32.61073 | AW55: 32.61073 | AX55: 0 | AY55: 19.077563
A56: 96 | B56: 0.98276911 | C56: 17.244109 | D56: 18.825807 | E56: 0.015649174 | F56: 0.017230888 | G56: 0 | H56: 4.0147816 | I56: 3.8798009 | J56: -22.760576 | K56: 17.528626 | L56: 14.725807 | M56: 9.7205173 | N56: 69.437098 | O56: 66.990268 | P56: 291290.28 | Q56: 271047.98 | R56: 782.6742 | S56: 0 | T56: 0 | U56: 0.042086768 | V56: 0.31382781 | W56: 0 | X56: 0.75251585 | Y56: 0 | Z56: 0.00032247629 | AA56: 4.3168092e-05 | AB56: 0.0025730807 | AC56: 2.5216964e-07 | AD56: 0.014291897 | AE56: 0.018708914 | AF56: 0.80916352 | AG56: 0.99408256 | AH56: 0.99968214 | AI56: 0.99994157 | AJ56: 1 | AK56: 1 | AL56: 1 | AM56: 0 | AN56: 0 | AO56: 09-4:15-20 | AP56: 15-20 | AQ56: 3.8504534e+10 | AR56: 142058 | AS56: 0 | AT56: 68.614687 | AU56: 68.614687 | AV56: 31.385313 | AW56: 31.385313 | AX56: 0 | AY56: 32.921262
A57: 96 | B57: 0.98050079 | C57: 21.069423 | D57: 21.045778 | E57: 0.019523686 | F57: 0.019499214 | G57: 0 | H57: 4.043684 | I57: 3.8720952 | J57: -22.362804 | K57: 22.543948 | L57: 14.47741 | M57: 10.47453 | N57: 67.823588 | O57: 65.233278 | P57: 296099.13 | Q57: 275599.6 | R57: 782.70335 | S57: 0 | T57: 0 | U57: 0.040518232 | V57: 0.31265171 | W57: 0 | X57: 0.75911106 | Y57: 0 | Z57: 0.00033241406 | AA57: 4.5092679e-05 | AB57: 0.0026704932 | AC57: 5.2559592e-07 | AD57: 0.016450675 | AE57: 0.020591337 | AF57: 0.79097261 | AG57: 0.99085171 | AH57: 0.99938978 | AI57: 0.999863 | AJ57: 1 | AK57: 1 | AL57: 1 | AM57: 0 | AN57: 0 | AO57: 09:0-25 | AP57: 0-25 | AQ57: 4.2866486e+10 | AR57: 155539 | AS57: 0 | AT57: 68.733949 | AU57: 68.733949 | AV57: 31.266051 | AW57: 31.266051 | AX57: 0 | AY57: 51.265645
A58: 96 | B58: 0.97841116 | C58: 23.063402 | D58: 23.04147 | E58: 0.021612081 | F58: 0.021588842 | G58: 0 | H58: 4.080554 | I58: 3.8625394 | J58: -21.393001 | K58: 27.523059 | L58: 14.579448 | M58: 11.278876 | N58: 68.399355 | O58: 65.529784 | P58: 294526.49 | Q58: 273743.06 | R58: 782.53593 | S58: 0 | T58: 0 | U58: 0.038080922 | V58: 0.31095846 | W58: 0 | X58: 0.75527821 | Y58: 0 | Z58: 0.00034120649 | AA58: 4.8394569e-05 | AB58: 0.002743361 | AC58: 8.3452158e-07 | AD58: 0.018455032 | AE58: 0.022744783 | AF58: 0.77371183 | AG58: 0.98435998 | AH58: 0.99926501 | AI58: 0.99978341 | AJ58: 1 | AK58: 1 | AL58: 1 | AM58: 0 | AN58: 0 | AO58: 10-1:25-30 | AP58: 25-30 | AQ58: 4.3570041e+10 | AR58: 159164 | AS58: 0 | AT58: 68.902598 | AU58: 68.902598 | AV58: 31.097402 | AW58: 31.097402 | AX58: 0 | AY58: 73.319059
A59: 96 | B59: 0.97649386 | C59: 25.027503 | D59: 24.831788 | E59: 0.023718264 | F59: 0.023506137 | G59: 0 | H59: 4.1027406 | I59: 3.8402996 | J59: -20.75564 | K59: 32.511491 | L59: 14.592738 | M59: 11.839008 | N59: 68.156254 | O59: 65.177773 | P59: 293515.87 | Q59: 273384.45 | R59: 782.6238 | S59: 0 | T59: 0 | U59: 0.036990865 | V59: 0.31948025 | W59: 0 | X59: 0.75414459 | Y59: 0 | Z59: 0.00034765967 | AA59: 5.1752209e-05 | AB59: 0.0027994829 | AC59: 1.3959302e-06 | AD59: 0.020305833 | AE59: 0.024530157 | AF59: 0.75628599 | AG59: 0.97965777 | AH59: 0.99872128 | AI59: 0.99974782 | AJ59: 1 | AK59: 1 | AL59: 1 | AM59: 0 | AN59: 0 | AO59: 10-2:30-35 | AP59: 30-35 | AQ59: 4.3981817e+10 | AR59: 160879 | AS59: 0 | AT59: 68.048233 | AU59: 68.048233 | AV59: 31.951767 | AW59: 31.951767 | AX59: 0 | AY59: 94.54859
A60: 96 | B60: 0.97414941 | C60: 27.830949 | D60: 26.969069 | E60: 0.026813857 | F60: 0.025850594 | G60: 0 | H60: 4.1348421 | I60: 3.827725 | J60: -20.038956 | K60: 37.477156 | L60: 14.487705 | M60: 12.607813 | N60: 67.879502 | O60: 64.682708 | P60: 295895.42 | Q60: 275423.54 | R60: 782.57786 | S60: 0 | T60: 0 | U60: 0.033245687 | V60: 0.31884608 | W60: 0 | X60: 0.74620281 | Y60: 0 | Z60: 0.0003534843 | AA60: 5.6024627e-05 | AB60: 0.0028690502 | AC60: 1.6527383e-06 | AD60: 0.022570369 | AE60: 0.026445154 | AF60: 0.73125549 | AG60: 0.97947389 | AH60: 0.99839829 | AI60: 0.99967124 | AJ60: 1 | AK60: 1 | AL60: 1 | AM60: 0 | AN60: 0 | AO60: 10-3:35-40 | AP60: 35-40 | AQ60: 4.4207957e+10 | AR60: 160509 | AS60: 0 | AT60: 68.114534 | AU60: 68.114534 | AV60: 31.885466 | AW60: 31.885466 | AX60: 0 | AY60: 118.1742
A61: 96 | B61: 0.97190419 | C61: 31.45781 | D61: 28.963514 | E61: 0.030986491 | F61: 0.028095807 | G61: 0 | H61: 4.1831056 | I61: 3.8234898 | J61: -19.308467 | K61: 42.441471 | L61: 14.535832 | M61: 13.466146 | N61: 68.134365 | O61: 64.854192 | P61: 295673.58 | Q61: 274474.32 | R61: 782.37062 | S61: 0 | T61: 0 | U61: 0.029554947 | V61: 0.31628243 | W61: 0 | X61: 0.73742217 | Y61: 0 | Z61: 0.00035962518 | AA61: 6.1795145e-05 | AB61: 0.0029245869 | AC61: 2.2833316e-06 | AD61: 0.024747503 | AE61: 0.026782477 | AF61: 0.72475109 | AG61: 0.97632537 | AH61: 0.99778689 | AI61: 0.9997711 | AJ61: 1 | AK61: 1 | AL61: 1 | AM61: 0 | AN61: 0 | AO61: 10-4:40-45 | AP61: 40-45 | AQ61: 4.0881577e+10 | AR61: 148945 | AS61: 0 | AT61: 68.371757 | AU61: 68.371757 | AV61: 31.628243 | AW61: 31.628243 | AX61: 0 | AY61: 144.31374
A62: 96 | B62: 0.96949188 | C62: 33.304222 | D62: 31.050664 | E62: 0.033189121 | F62: 0.030508124 | G62: 0 | H62: 4.2389415 | I62: 3.8269869 | J62: -18.56358 | K62: 47.518166 | L62: 14.521738 | M62: 14.59814 | N62: 67.828227 | O62: 64.551916 | P62: 295745.68 | Q62: 274652.3 | R62: 782.20509 | S62: 0 | T62: 0 | U62: 0.023834157 | V62: 0.30543286 | W62: 0 | X62: 0.72540982 | Y62: 0 | Z62: 0.00036543652 | AA62: 6.9434013e-05 | AB62: 0.0030125581 | AC62: 2.5641522e-06 | AD62: 0.027058118 | AE62: 0.0254136 | AF62: 0.72717763 | AG62: 0.97756361 | AH62: 0.99767709 | AI62: 0.9998045 | AJ62: 1 | AK62: 1 | AL62: 1 | AM62: 0 | AN62: 0 | AO62: 10:25-50 | AP62: 25-50 | AQ62: 3.919096e+10 | AR62: 142693 | AS62: 0 | AT62: 69.456714 | AU62: 69.456714 | AV62: 30.543286 | AW62: 30.543286 | AX62: 0 | AY62: 174.12595
A63: 96 | B63: 0.96762603 | C63: 33.412905 | D63: 32.626278 | E63: 0.033320507 | F63: 0.032373966 | G63: 0 | H63: 4.3180088 | I63: 3.8417096 | J63: -17.463033 | K63: 52.504461 | L63: 14.887496 | M63: 16.089802 | N63: 69.557278 | O63: 66.210126 | P63: 289074.81 | Q63: 268000.81 | R63: 781.78016 | S63: 0 | T63: 0 | U63: 0.019533417 | V63: 0.29306856 | W63: 0 | X63: 0.70769 | Y63: 0 | Z63: 0.00037173065 | AA63: 8.2806942e-05 | AB63: 0.0031134834 | AC63: 2.6524879e-06 | AD63: 0.028803279 | AE63: 0.021343834 | AF63: 0.74321936 | AG63: 0.97898505 | AH63: 0.99781394 | AI63: 0.99980767 | AJ63: 1 | AK63: 1 | AL63: 1 | AM63: 0 | AN63: 0 | AO63: 11-1:50-55 | AP63: 50-55 | AQ63: 3.5465887e+10 | AR63: 132335 | AS63: 0 | AT63: 70.693144 | AU63: 70.693144 | AV63: 29.306856 | AW63: 29.306856 | AX63: 0 | AY63: 205.96089
A64: 96 | B64: 0.96572974 | C64: 35.483123 | D64: 34.193728 | E64: 0.035861457 | F64: 0.034270257 | G64: 0 | H64: 4.3828476 | I64: 3.8523699 | J64: -17.323485 | K64: 57.483953 | L64: 15.128447 | M64: 17.615636 | N64: 69.370722 | O64: 66.117421 | P64: 284722.57 | Q64: 263601.22 | R64: 781.65219 | S64: 0 | T64: 0 | U64: 0.016827545 | V64: 0.27475101 | W64: 0 | X64: 0.70253618 | Y64: 0 | Z64: 0.00037826165 | AA64: 9.7685403e-05 | AB64: 0.0031965205 | AC64: 3.2926443e-06 | AD64: 0.030594483 | AE64: 0.017894567 | AF64: 0.76065412 | AG64: 0.97939804 | AH64: 0.9974502 | AI64: 0.99959005 | AJ64: 1 | AK64: 1 | AL64: 1 | AM64: 0 | AN64: 0 | AO64: 11-2:55-60 | AP64: 55-60 | AQ64: 3.4266578e+10 | AR64: 129994 | AS64: 0 | AT64: 72.524899 | AU64: 72.524899 | AV64: 27.475101 | AW64: 27.475101 | AX64: 0 | AY64: 247.53419
A65: 96 | B65: 0.96365242 | C65: 36.916194 | D65: 35.872398 | E65: 0.037664536 | F65: 0.036347579 | G65: 0 | H65: 4.4570138 | I65: 3.873694 | J65: -17.37229 | K65: 62.493872 | L65: 15.300089 | M65: 19.219581 | N65: 69.640995 | O65: 66.478468 | P65: 281394.51 | Q65: 260887.2 | R65: 781.25669 | S65: 0 | T65: 0 | U65: 0.015796997 | V65: 0.25155199 | W65: 0 | X65: 0.69517778 | Y65: 0 | Z65: 0.00038188402 | AA65: 0.00011628449 | AB65: 0.003282456 | AC65: 3.3856391e-06 | AD65: 0.032563555 | AE65: 0.012960875 | AF65: 0.77964598 | AG65: 0.98196677 | AH65: 0.99752558 | AI65: 0.99960562 | AJ65: 1 | AK65: 1 | AL65: 1 | AM65: 0 | AN65: 0 | AO65: 11-3:60-65 | AP65: 60-65 | AQ65: 3.5359608e+10 | AR65: 135536 | AS65: 0 | AT65: 74.844801 | AU65: 74.844801 | AV65: 25.155199 | AW65: 25.155199 | AX65: 0 | AY65: 297.70248
A66: 96 | B66: 0.96208002 | C66: 37.34521 | D66: 37.116842 | E66: 0.038211625 | F66: 0.037919981 | G66: 0 | H66: 4.5265381 | I66: 3.8931776 | J66: -17.357444 | K66: 67.507788 | L66: 15.524625 | M66: 20.507183 | N66: 69.628969 | O66: 66.643585 | P66: 277328.62 | Q66: 257076.01 | R66: 781.11713 | S66: 0 | T66: 0 | U66: 0.016723574 | V66: 0.23597175 | W66: 0 | X66: 0.69099868 | Y66: 0 | Z66: 0.00038698645 | AA66: 0.00013357149 | AB66: 0.0033189158 | AC66: 3.9252188e-06 | AD66: 0.034076568 | AE66: 0.007362507 | AF66: 0.80371152 | AG66: 0.98172644 | AH66: 0.99727104 | AI66: 0.99956676 | AJ66: 1 | AK66: 1 | AL66: 1 | AM66: 0 | AN66: 0 | AO66: 11-4:65-70 | AP66: 65-70 | AQ66: 3.6614566e+10 | AR66: 142427 | AS66: 0 | AT66: 76.402825 | AU66: 76.402825 | AV66: 23.597175 | AW66: 23.597175 | AX66: 0 | AY66: 353.87949
A67: 96 | B67: 0.95981028 | C67: 38.800417 | D67: 38.874173 | E67: 0.040093265 | F67: 0.040189724 | G67: 0 | H67: 4.5629607 | I67: 3.8915188 | J67: -17.338162 | K67: 72.521817 | L67: 15.200947 | M67: 21.458715 | N67: 68.415455 | O67: 65.44972 | P67: 282548.22 | Q67: 262505.17 | R67: 781.02953 | S67: 0 | T67: 0 | U67: 0.016188388 | V67: 0.22642586 | W67: 0 | X67: 0.69552406 | Y67: 0 | Z67: 0.00038991503 | AA67: 0.00014459484 | AB67: 0.0033562306 | AC67: 4.5622395e-06 | AD67: 0.036294407 | AE67: 0.0062719663 | AF67: 0.79883958 | AG67: 0.98129144 | AH67: 0.99689562 | AI67: 0.99964418 | AJ67: 1 | AK67: 1 | AL67: 1 | AM67: 0 | AN67: 0 | AO67: 11:50-75 | AP67: 50-75 | AQ67: 3.9348475e+10 | AR67: 149896 | AS67: 0 | AT67: 77.357414 | AU67: 77.357414 | AV67: 22.642586 | AW67: 22.642586 | AX67: 0 | AY67: 414.10153
... A75: 96 | B75: 0.94271986 | C75: 84.603245 | D75: 50.728943 | E75: 0.14437047 | F75: 0.057280139 | G75: 0 | H75: 5.75 | I75: 4.1387574 | J75: 54.4553 | K75: 254.14738 | L75: 23.888925 | M75: 31.426217 | N75: 95 | O75: 57.497761 | P75: 170045.7 | Q75: 166421.72 | R75: 782 | S75: 0 | T75: 0 | U75: 0 | V75: 0 | W75: 0 | X75: 0 | Y75: 0 | Z75: 0.0016004217 | AA75: 0.0016422781 | AB75: 0.0061079827 | AC75: 0 | AD75: 0.047929433 | AE75: -0.06000343 | AF75: 1 | AG75: 1 | AH75: 1 | AI75: 1 | AJ75: 1 | AK75: 1 | AL75: 1 | AM75: 0 | AN75: 0 | AO75: 999:>= 250 | AP75: >= 250 | AQ75: 332843.44 | AR75: 2 | AS75: 0 | AT75: 100 | AU75: 100 | AV75: 0 | AW75: 0 | AX75: 0 | AY75: 1089.0234
O79: pct high media | P79: pct low media
K80: turn | L80: cash | M80: refi | O80: 1 | P80: =1-O80 -> 0
A81: incentive | B81: =AQ2 -> Balance | C81: =AO2 -> groupByColumn | D81: =E2 -> PREPAY_SMM1 | E81: =F2 -> PREPAY_TRACKING_SMM1 | F81: ratio | G81: =C2 -> PREPAY_CPR1 | H81: =D2 -> PREPAY_TRACKING_CPR1 | I81: high media cpr | K81: adj | L81: adj | M81: adj | O81: high media refi | P81: low media refi | Q81: interpolate refi | S81: mdl_smm | T81: mdl_cpr | U81: ratio
A82: =K3 -> -155.50095 | B82: =AQ3/1000000000 -> 0.00082237609 | C82: =AO3 -> 02:-175--150 | D82: =E3 -> 0.0002180146 | E82: =Z3+AA3+AB3+AC3+AD3 -> 0.0016670152 | F82: =D82/E82 -> 0.13078141 | G82: =(1-(1-D82)^12)*100 -> 0.26130405 | H82: =(1-(1-E82)^12)*100 -> 1.9821788 | I82: =(1-(1-SUM(Z42,AA42,AB42,AC42,AD42*M82))^12)*100 -> 1.9821788 | K82: =VLOOKUP($C82,'Refi Adj'!$B$2:$E$32,2,0) -> 1 | L82: =VLOOKUP($C82,'Refi Adj'!$B$2:$E$32,3,0) -> 1 | M82: =VLOOKUP($C82,'Refi Adj'!$B$2:$E$32,4,0) -> 1 | O82: =AD42*M82 -> 0 | P82: =AD3 -> 0 | Q82: =(O82*$O$80+P82*$P$80) -> 0 | S82: =Z3+AA3+AB3*K82+AC3*L82+Q82 -> 0.0016670152 | T82: =100*(1-(1-S82)^12) -> 1.9821788 | U82: =D82/S82 -> 0.13078141
A83: =K4 -> -133.73728 | B83: =AQ4/1000000000 -> 0.0059944804 | C83: =AO4 -> 03:-150--125 | D83: =E4 -> 0.00013535375 | E83: =Z4+AA4+AB4+AC4+AD4 -> 0.001576368 | F83: =D83/E83 -> 0.085864308 | G83: =(1-(1-D83)^12)*100 -> 0.16230364 | H83: =(1-(1-E83)^12)*100 -> 1.8753269 | I83: =(1-(1-SUM(Z43,AA43,AB43,AC43,AD43*M83))^12)*100 -> 1.8948241 | K83: =VLOOKUP($C83,'Refi Adj'!$B$2:$E$32,2,0) -> 1 | L83: =VLOOKUP($C83,'Refi Adj'!$B$2:$E$32,3,0) -> 1 | M83: =VLOOKUP($C83,'Refi Adj'!$B$2:$E$32,4,0) -> 1 | O83: =AD43*M83 -> 1.8054137e-05 | P83: =AD4 -> 1.5205842e-06 | Q83: =(O83*$O$80+P83*$P$80) -> 1.8054137e-05 | S83: =Z4+AA4+AB4*K83+AC4*L83+Q83 -> 0.0015929016 | T83: =100*(1-(1-S83)^12) -> 1.8948241 | U83: =D83/S83 -> 0.084973078
A84: =K5 -> -109.75521 | B84: =AQ5/1000000000 -> 0.024342577 | C84: =AO5 -> 04:-125--100 | D84: =E5 -> 0.00015113537 | E84: =Z5+AA5+AB5+AC5+AD5 -> 0.0019193848 | F84: =D84/E84 -> 0.078741569 | G84: =(1-(1-D84)^12)*100 -> 0.18121177 | H84: =(1-(1-E84)^12)*100 -> 2.2791021 | I84: =(1-(1-SUM(Z44,AA44,AB44,AC44,AD44*M84))^12)*100 -> 3.862961 | K84: =VLOOKUP($C84,'Refi Adj'!$B$2:$E$32,2,0) -> 1 | L84: =VLOOKUP($C84,'Refi Adj'!$B$2:$E$32,3,0) -> 1 | M84: =VLOOKUP($C84,'Refi Adj'!$B$2:$E$32,4,0) -> 1 | O84: =AD44*M84 -> 0.0015371609 | P84: =AD5 -> 0.00017896852 | Q84: =(O84*$O$80+P84*$P$80) -> 0.0015371609 | S84: =Z5+AA5+AB5*K84+AC5*L84+Q84 -> 0.0032775772 | T84: =100*(1-(1-S84)^12) -> 3.862961 | U84: =D84/S84 -> 0.046111919
A85: =K6 -> -82.887944 | B85: =AQ6/1000000000 -> 0.19147108 | C85: =AO6 -> 05:-100--75 | D85: =E6 -> 0.0030574376 | E85: =Z6+AA6+AB6+AC6+AD6 -> 0.0019771479 | F85: =D85/E85 -> 1.5463879 | G85: =(1-(1-D85)^12)*100 -> 3.6078533 | H85: =(1-(1-E85)^12)*100 -> 2.3469466 | I85: =(1-(1-SUM(Z45,AA45,AB45,AC45,AD45*M85))^12)*100 -> 4.3304579 | K85: =VLOOKUP($C85,'Refi Adj'!$B$2:$E$32,2,0) -> 1 | L85: =VLOOKUP($C85,'Refi Adj'!$B$2:$E$32,3,0) -> 1 | M85: =VLOOKUP($C85,'Refi Adj'!$B$2:$E$32,4,0) -> 1 | O85: =AD45*M85 -> 0.0019832061 | P85: =AD6 -> 0.00027796719 | Q85: =(O85*$O$80+P85*$P$80) -> 0.0019832061 | S85: =Z6+AA6+AB6*K85+AC6*L85+Q85 -> 0.0036823868 | T85: =100*(1-(1-S85)^12) -> 4.3304579 | U85: =D85/S85 -> 0.83028692
A86: =K7 -> -57.590534 | B86: =AQ7/1000000000 -> 2.0998372 | C86: =AO7 -> 06:-75--50 | D86: =E7 -> 0.0021290709 | E86: =Z7+AA7+AB7+AC7+AD7 -> 0.0017008187 | F86: =D86/E86 -> 1.2517918 | G86: =(1-(1-D86)^12)*100 -> 2.5251789 | H86: =(1-(1-E86)^12)*100 -> 2.0219979 | I86: =(1-(1-SUM(Z46,AA46,AB46,AC46,AD46*M86))^12)*100 -> 2.2493784 | K86: =VLOOKUP($C86,'Refi Adj'!$B$2:$E$32,2,0) -> 1 | L86: =VLOOKUP($C86,'Refi Adj'!$B$2:$E$32,3,0) -> 1 | M86: =VLOOKUP($C86,'Refi Adj'!$B$2:$E$32,4,0) -> 0.5 | O86: =AD46*M86 -> 0.00029550256 | P86: =AD7 -> 0.00010223164 | Q86: =(O86*$O$80+P86*$P$80) -> 0.00029550256 | S86: =Z7+AA7+AB7*K86+AC7*L86+Q86 -> 0.0018940896 | T86: =100*(1-(1-S86)^12) -> 2.2493784 | U86: =D86/S86 -> 1.1240603
A87: =K8 -> -33.319482 | B87: =AQ8/1000000000 -> 22.563329 | C87: =AO8 -> 07:-50--25 | D87: =E8 -> 0.001917272 | E87: =Z8+AA8+AB8+AC8+AD8 -> 0.0020645034 | F87: =D87/E87 -> 0.92868436 | G87: =(1-(1-D87)^12)*100 -> 2.2766196 | H87: =(1-(1-E87)^12)*100 -> 2.4494664 | I87: =(1-(1-SUM(Z47,AA47,AB47,AC47,AD47*M87))^12)*100 -> 3.3003573 | K87: =VLOOKUP($C87,'Refi Adj'!$B$2:$E$32,2,0) -> 1 | L87: =VLOOKUP($C87,'Refi Adj'!$B$2:$E$32,3,0) -> 1 | M87: =VLOOKUP($C87,'Refi Adj'!$B$2:$E$32,4,0) -> 0.5 | O87: =AD47*M87 -> 0.00095029235 | P87: =AD8 -> 0.00022199631 | Q87: =(O87*$O$80+P87*$P$80) -> 0.00095029235 | S87: =Z8+AA8+AB8*K87+AC8*L87+Q87 -> 0.0027927994 | T87: =100*(1-(1-S87)^12) -> 3.3003573 | U87: =D87/S87 -> 0.68650544
A88: =K9 -> -22.334933 | B88: =AQ9/1000000000 -> 12.758775 | C88: =AO9 -> 08-1:-25--20 | D88: =E9 -> 0.0024514348 | E88: =Z9+AA9+AB9+AC9+AD9 -> 0.0024880572 | F88: =D88/E88 -> 0.98528072 | G88: =(1-(1-D88)^12)*100 -> 2.9023812 | H88: =(1-(1-E88)^12)*100 -> 2.9451488 | I88: =(1-(1-SUM(Z48,AA48,AB48,AC48,AD48*M88))^12)*100 -> 4.6956521 | K88: =VLOOKUP($C88,'Refi Adj'!$B$2:$E$32,2,0) -> 1 | L88: =VLOOKUP($C88,'Refi Adj'!$B$2:$E$32,3,0) -> 1 | M88: =VLOOKUP($C88,'Refi Adj'!$B$2:$E$32,4,0) -> 0.51 | O88: =AD48*M88 -> 0.0019761612 | P88: =AD9 -> 0.00046434322 | Q88: =(O88*$O$80+P88*$P$80) -> 0.0019761612 | S88: =Z9+AA9+AB9*K88+AC9*L88+Q88 -> 0.0039998752 | T88: =100*(1-(1-S88)^12) -> 4.6956521 | U88: =D88/S88 -> 0.61287782
A89: =K10 -> -17.367272 | B89: =AQ10/1000000000 -> 17.092521 | C89: =AO10 -> 08-2:-20--15 | D89: =E10 -> 0.0027093552 | E89: =Z10+AA10+AB10+AC10+AD10 -> 0.0027042651 | F89: =D89/E89 -> 1.0018822 | G89: =(1-(1-D89)^12)*100 -> 3.2032131 | H89: =(1-(1-E89)^12)*100 -> 3.1972844 | I89: =(1-(1-SUM(Z49,AA49,AB49,AC49,AD49*M89))^12)*100 -> 5.4428676 | K89: =VLOOKUP($C89,'Refi Adj'!$B$2:$E$32,2,0) -> 1 | L89: =VLOOKUP($C89,'Refi Adj'!$B$2:$E$32,3,0) -> 1 | M89: =VLOOKUP($C89,'Refi Adj'!$B$2:$E$32,4,0) -> 0.52 | O89: =AD49*M89 -> 0.002554626 | P89: =AD10 -> 0.00060591994 | Q89: =(O89*$O$80+P89*$P$80) -> 0.002554626 | S89: =Z10+AA10+AB10*K89+AC10*L89+Q89 -> 0.0046529711 | T89: =100*(1-(1-S89)^12) -> 5.4428676 | U89: =D89/S89 -> 0.58228498
A90: =K11 -> -12.402038 | B90: =AQ11/1000000000 -> 20.836834 | C90: =AO11 -> 08-3:-15--10 | D90: =E11 -> 0.0038444545 | E90: =Z11+AA11+AB11+AC11+AD11 -> 0.002966854 | F90: =D90/E90 -> 1.2958017 | G90: =(1-(1-D90)^12)*100 -> 4.5170378 | H90: =(1-(1-E90)^12)*100 -> 3.5027009 | I90: =(1-(1-SUM(Z50,AA50,AB50,AC50,AD50*M90))^12)*100 -> 6.2521487 | K90: =VLOOKUP($C90,'Refi Adj'!$B$2:$E$32,2,0) -> 1 | L90: =VLOOKUP($C90,'Refi Adj'!$B$2:$E$32,3,0) -> 1 | M90: =VLOOKUP($C90,'Refi Adj'!$B$2:$E$32,4,0) -> 0.53 | O90: =AD50*M90 -> 0.0031527885 | P90: =AD11 -> 0.00075396938 | Q90: =(O90*$O$80+P90*$P$80) -> 0.0031527885 | S90: =Z11+AA11+AB11*K90+AC11*L90+Q90 -> 0.0053656732 | T90: =100*(1-(1-S90)^12) -> 6.2521487 | U90: =D90/S90 -> 0.71649062
A91: =K12 -> -7.4908218 | B91: =AQ12/1000000000 -> 23.515901 | C91: =AO12 -> 08-4:-10--5 | D91: =E12 -> 0.0047635395 | E91: =Z12+AA12+AB12+AC12+AD12 -> 0.0032060743 | F91: =D91/E91 -> 1.4857857 | G91: =(1-(1-D91)^12)*100 -> 5.5688374 | H91: =(1-(1-E91)^12)*100 -> 3.7801682 | I91: =(1-(1-SUM(Z51,AA51,AB51,AC51,AD51*M91))^12)*100 -> 7.0367484 | K91: =VLOOKUP($C91,'Refi Adj'!$B$2:$E$32,2,0) -> 1 | L91: =VLOOKUP($C91,'Refi Adj'!$B$2:$E$32,3,0) -> 1 | M91: =VLOOKUP($C91,'Refi Adj'!$B$2:$E$32,4,0) -> 0.54 | O91: =AD51*M91 -> 0.0037582325 | P91: =AD12 -> 0.00090226268 | Q91: =(O91*$O$80+P91*$P$80) -> 0.0037582325 | S91: =Z12+AA12+AB12*K91+AC12*L91+Q91 -> 0.0060620441 | T91: =100*(1-(1-S91)^12) -> 7.0367484 | U91: =D91/S91 -> 0.78579755
A92: =K13 -> -2.4075089 | B92: =AQ13/1000000000 -> 27.364682 | C92: =AO13 -> 08:-25-0 | D92: =E13 -> 0.0061759041 | E92: =Z13+AA13+AB13+AC13+AD13 -> 0.0034670055 | F92: =D92/E92 -> 1.7813367 | G92: =(1-(1-D92)^12)*100 -> 7.1644601 | H92: =(1-(1-E92)^12)*100 -> 4.0819835 | I92: =(1-(1-SUM(Z52,AA52,AB52,AC52,AD52*M92))^12)*100 -> 7.8831303 | K92: =VLOOKUP($C92,'Refi Adj'!$B$2:$E$32,2,0) -> 1 | L92: =VLOOKUP($C92,'Refi Adj'!$B$2:$E$32,3,0) -> 1 | M92: =VLOOKUP($C92,'Refi Adj'!$B$2:$E$32,4,0) -> 0.55 | O92: =AD52*M92 -> 0.0044275668 | P92: =AD13 -> 0.0010752557 | Q92: =(O92*$O$80+P92*$P$80) -> 0.0044275668 | S92: =Z13+AA13+AB13*K92+AC13*L92+Q92 -> 0.0068193166 | T92: =100*(1-(1-S92)^12) -> 7.8831303 | U92: =D92/S92 -> 0.90564854
A93: =K14 -> 2.5749501 | B93: =AQ14/1000000000 -> 28.507014 | C93: =AO14 -> 09-1:0-5 | D93: =E14 -> 0.0076941417 | E93: =Z14+AA14+AB14+AC14+AD14 -> 0.0037976475 | F93: =D93/E93 -> 2.0260284 | G93: =(1-(1-D93)^12)*100 -> 8.8521007 | H93: =(1-(1-E93)^12)*100 -> 4.4631856 | I93: =(1-(1-SUM(Z53,AA53,AB53,AC53,AD53*M93))^12)*100 -> 9.2539411 | K93: =VLOOKUP($C93,'Refi Adj'!$B$2:$E$32,2,0) -> 1 | L93: =VLOOKUP($C93,'Refi Adj'!$B$2:$E$32,3,0) -> 1 | M93: =VLOOKUP($C93,'Refi Adj'!$B$2:$E$32,4,0) -> 0.6 | O93: =AD53*M93 -> 0.0055498186 | P93: =AD14 -> 0.0012880237 | Q93: =(O93*$O$80+P93*$P$80) -> 0.0055498186 | S93: =Z14+AA14+AB14*K93+AC14*L93+Q93 -> 0.0080594423 | T93: =100*(1-(1-S93)^12) -> 9.2539411 | U93: =D93/S93 -> 0.95467421
... A112: =K33 -> 182.01779 | B112: =AQ33/1000000000 -> 1.5924065 | C112: =AO33 -> 16:175-200 | D112: =E33 -> 0.043174796 | E112: =Z33+AA33+AB33+AC33+AD33 -> 0.03546063 | F112: =D112/E112 -> 1.2175417 | G112: =(1-(1-D112)^12)*100 -> 41.116817 | H112: =(1-(1-E112)^12)*100 -> 35.160522 | I112: =(1-(1-SUM(Z72,AA72,AB72,AC72,AD72*M112))^12)*100 -> #N/A | K112: =VLOOKUP($C112,'Refi Adj'!$B$2:$E$32,2,0) -> #N/A | L112: =VLOOKUP($C112,'Refi Adj'!$B$2:$E$32,3,0) -> #N/A | M112: =VLOOKUP($C112,'Refi Adj'!$B$2:$E$32,4,0) -> #N/A | O112: =AD72*M112 -> #N/A | P112: =AD33 -> 0.030439068 | Q112: =(O112*$O$80+P112*$P$80) -> #N/A | S112: =Z33+AA33+AB33*K112+AC33*L112+Q112 -> #N/A | T112: =100*(1-(1-S112)^12) -> #N/A | U112: =D112/S112 -> #N/A
A120: burnout 2000-4000 | C120: CORRES+CASHWINDOW | F120: low media | AS120: tover | AT120: cash | AW120: refi
A121: modelId | B121: SFACTOR_PREPAY_TRACKING_CPR | C121: PREPAY_CPR1 | D121: PREPAY_TRACKING_CPR1 | E121: PREPAY_SMM1 | F121: PREPAY_TRACKING_SMM1 | G121: PCT_LOANTYPE | H121: _ORIGNOTERATE | I121: _ZEROSATO | J121: _SATO | K121: _REFI_INCENTIVE_Fixed | L121: _Fixed_cost | M121: _LOANAGE | N121: _LTV | O121: _CLTV | P121: _AVG_LOANSIZE_SCHAMBALANCE | Q121: _WACLS | R121: _FICO | S121: PCT_ISSECONDLIEN | T121: _OrigCombLTV | U121: PCT_SVC | V121: PCT_TPO | W121: PCT_GEO | X121: PCT_LOANPURPOSE | Y121: PCT_OCC | Z121: curtailsmm | AA121: defaultsmm | AB121: toverSmm | AC121: cashoutSmm | AD121: refiSmm | AE121: cumHPA | AF121: cumHPA05Pct | AG121: cumHPA15Pct | AH121: cumHPA20Pct | AI121: cumHPA25Pct | AJ121: cumHPA30Pct | AK121: cumHPA35Pct | AL121: cumHPA40Pct | AM121: adjtoverSmm | AN121: adjRefiSmm | AO121: groupByColumn | AP121: curve | AQ121: Balance | AR121: LoanCount | AS121: PCT_BROKER | AT121: PCT_CORRES | AU121: PCT_NonRETAIL | AV121: PCT_RETAIL | AW121: PCT_CashWindow | AX121: PCT_NonCashWindow | AY121: _Burnout_Fixed
A122: 97 | B122: 0.98205364 | C122: 0 | D122: 19.532131 | E122: 0 | F122: 0.017946363 | G122: 0 | H122: 5.0073042 | I122: 3.8587571 | J122: -7.7679575 | K122: 45.850297 | L122: 100 | M122: 38.235944 | N122: 54.294378 | O122: 6.1854485 | P122: 28883.502 | Q122: 26580.115 | R122: 778.29217 | S122: 0 | T122: 0 | U122: 0 | V122: 0.35281111 | W122: 0 | X122: 0 | Y122: 0 | Z122: 0.010364355 | AA122: 0.00041857955 | AB122: 0.0069299003 | AC122: 0 | AD122: 0.00023351775 | AE122: -0.064847236 | AF122: 1 | AG122: 1 | AH122: 1 | AI122: 1 | AJ122: 1 | AK122: 1 | AL122: 1 | AM122: 0 | AN122: 0 | AO122: 10:25-50 | AP122: 25-50 | AQ122: 53160.23 | AR122: 2 | AS122: 0 | AT122: 64.718889 | AU122: 64.718889 | AV122: 35.281111 | AW122: 35.281111 | AX122: 0 | AY122: 2048.3802
A123: 97 | B123: 0.97712858 | C123: 0 | D123: 24.243379 | E123: 0 | F123: 0.02287142 | G123: 0 | H123: 5.25 | I123: 3.889063 | J123: 15.3495 | K123: 58.82 | L123: 100 | M123: 36 | N123: 53 | O123: 2.17 | P123: 16446.75 | Q123: 16446.75 | R123: 788 | S123: 0 | T123: 0 | U123: 0 | V123: 1 | W123: 0 | X123: 0 | Y123: 0 | Z123: 0.01409106 | AA123: 0.00059012 | AB123: 0.00803485 | AC123: 0 | AD123: 0.00015538 | AE123: -0.03670308 | AF123: 1 | AG123: 1 | AH123: 1 | AI123: 1 | AJ123: 1 | AK123: 1 | AL123: 1 | AM123: 0 | AN123: 0 | AO123: 11-2:55-60 | AP123: 55-60 | AQ123: 16446.75 | AR123: 1 | AS123: 0 | AT123: 0 | AU123: 0 | AV123: 100 | AW123: 100 | AX123: 0 | AY123: 2114.96
A124: 97 | B124: 0.98826511 | C124: 0 | D124: 13.207628 | E124: 0 | F124: 0.01173489 | G124: 0 | H124: 5 | I124: 4.153825 | J124: -14.4812 | K124: 65.92 | L124: 17.18 | M124: 26 | N124: 95 | O124: 79.18 | P124: 232170.07 | Q124: 232170.07 | R124: 770 | S124: 0 | T124: 0 | U124: 0 | V124: 0 | W124: 0 | X124: 1 | Y124: 0 | Z124: 0.000803 | AA124: 0.00029903 | AB124: 0.00352274 | AC124: 0 | AD124: 0.00711012 | AE124: -0.026023842 | AF124: 1 | AG124: 1 | AH124: 1 | AI124: 1 | AJ124: 1 | AK124: 1 | AL124: 1 | AM124: 0 | AN124: 0 | AO124: 11-4:65-70 | AP124: 65-70 | AQ124: 232170.07 | AR124: 1 | AS124: 0 | AT124: 100 | AU124: 100 | AV124: 0 | AW124: 0 | AX124: 0 | AY124: 2007.21
A125: 97 | B125: 0.98596422 | C125: 31.735277 | D125: 15.601667 | E125: 0.03131399 | F125: 0.014035779 | G125: 0 | H125: 4.9804384 | I125: 4.091103 | J125: -2.4334577 | K125: 71.878078 | L125: 29.082251 | M125: 31.443908 | N125: 84.8672 | O125: 64.273713 | P125: 231308.59 | Q125: 89953.178 | R125: 771.59719 | S125: 0 | T125: 0 | U125: 0 | V125: 0.052587469 | W125: 0 | X125: 0.2750431 | Y125: 0 | Z125: 0.0021991697 | AA125: 0.00021787542 | AB125: 0.0046047121 | AC125: 0 | AD125: 0.0070140027 | AE125: -0.00058853978 | AF125: 0.94565019 | AG125: 1 | AH125: 1 | AI125: 1 | AJ125: 1 | AK125: 1 | AL125: 1 | AM125: 0 | AN125: 0 | AO125: 11:50-75 | AP125: 50-75 | AQ125: 989484.96 | AR125: 11 | AS125: 0 | AT125: 94.741253 | AU125: 94.741253 | AV125: 5.2587469 | AW125: 5.2587469 | AX125: 0 | AY125: 2085.515
A126: 97 | B126: 0.98503278 | C126: 75.12402 | D126: 16.55349 | E126: 0.10947042 | F126: 0.014967224 | G126: 0 | H126: 5.0874263 | I126: 3.8991322 | J126: 4.6528775 | K126: 92.496268 | L126: 46.922884 | M126: 34.635219 | N126: 79.346614 | O126: 48.924294 | P126: 163922.03 | Q126: 63864.502 | R126: 775.13984 | S126: 0 | T126: 0 | U126: 0 | V126: 0.34323436 | W126: 0 | X126: 0.35260476 | Y126: 0 | Z126: 0.0035263312 | AA126: 0.00044628965 | AB126: 0.0051085608 | AC126: 2.3829555e-05 | AD126: 0.0058621989 | AE126: 0.013044208 | AF126: 0.84861557 | AG126: 0.98179977 | AH126: 0.98179977 | AI126: 0.99703064 | AJ126: 1 | AK126: 1 | AL126: 1 | AM126: 0 | AN126: 0 | AO126: 12:75-100 | AP126: 75-100 | AQ126: 6514179.2 | AR126: 102 | AS126: 0 | AT126: 65.676564 | AU126: 65.676564 | AV126: 34.323436 | AW126: 34.323436 | AX126: 0 | AY126: 2232.8266
A127: 97 | B127: 0.98333708 | C127: 41.152211 | D127: 18.261067 | E127: 0.043222737 | F127: 0.016662925 | G127: 0 | H127: 5.1566289 | I127: 3.8626142 | J127: 7.4998933 | K127: 117.34231 | L127: 30.356748 | M127: 36.270305 | N127: 79.198829 | O127: 56.200871 | P127: 182615.02 | Q127: 124724.04 | R127: 777.94792 | S127: 0 | T127: 0 | U127: 0.012453106 | V127: 0.35469302 | W127: 0 | X127: 0.45074758 | Y127: 0 | Z127: 0.0016673738 | AA127: 0.00051598676 | AB127: 0.0049197501 | AC127: 5.0875095e-06 | AD127: 0.0095547115 | AE127: -0.0087515521 | AF127: 0.81499604 | AG127: 0.99409153 | AH127: 1 | AI127: 1 | AJ127: 1 | AK127: 1 | AL127: 1 | AM127: 0 | AN127: 0 | AO127: 13:100-125 | AP127: 100-125 | AQ127: 53132442 | AR127: 426 | AS127: 0 | AT127: 64.530698 | AU127: 64.530698 | AV127: 35.469302 | AW127: 35.469302 | AX127: 0 | AY127: 2251.1841
A128: 97 | B128: 0.97705967 | C128: 42.593394 | D128: 24.307461 | E128: 0.045197628 | F128: 0.022940325 | G128: 0 | H128: 5.1459985 | I128: 3.8623083 | J128: 5.740604 | K128: 140.2459 | L128: 15.573586 | M128: 35.983076 | N128: 61.597253 | O128: 58.063223 | P128: 281106.92 | Q128: 256245.2 | R128: 779.24518 | S128: 0 | T128: 0 | U128: 0.029072545 | V128: 0.33035966 | W128: 0 | X128: 0.75179069 | Y128: 0 | Z128: 0.00046621189 | AA128: 0.00047582512 | AB128: 0.004217646 | AC128: 8.1820362e-06 | AD128: 0.017772445 | AE128: -0.0072979565 | AF128: 0.78579818 | AG128: 0.98693773 | AH128: 0.99693465 | AI128: 0.99949472 | AJ128: 1 | AK128: 1 | AL128: 1 | AM128: 0 | AN128: 0 | AO128: 14:125-150 | AP128: 125-150 | AQ128: 5.3719244e+09 | AR128: 20964 | AS128: 0 | AT128: 66.964034 | AU128: 66.964034 | AV128: 33.035966 | AW128: 33.035966 | AX128: 0 | AY128: 2205.188
A129: 97 | B129: 0.97391044 | C129: 44.106171 | D129: 27.183757 | E129: 0.047320131 | F129: 0.026089558 | G129: 0 | H129: 5.2439505 | I129: 3.7219745 | J129: 13.954143 | K129: 162.73199 | L129: 15.914148 | M129: 36.169459 | N129: 65.351666 | O129: 61.873933 | P129: 271939.59 | Q129: 250869.37 | R129: 778.43785 | S129: 0 | T129: 0 | U129: 0.025079781 | V129: 0.32896083 | W129: 0 | X129: 0.72400655 | Y129: 0 | Z129: 0.00044736572 | AA129: 0.00065345172 | AB129: 0.0039919848 | AC129: 8.1232066e-06 | AD129: 0.020988617 | AE129: -0.006308962 | AF129: 0.84009366 | AG129: 0.98653978 | AH129: 0.99740946 | AI129: 0.99926471 | AJ129: 1 | AK129: 1 | AL129: 1 | AM129: 0 | AN129: 0 | AO129: 15:150-175 | AP129: 150-175 | AQ129: 1.3676897e+10 | AR129: 54518 | AS129: 0 | AT129: 67.103917 | AU129: 67.103917 | AV129: 32.896083 | AW129: 32.896083 | AX129: 0 | AY129: 2425.0502
A130: 97 | B130: 0.969186 | C130: 41.525582 | D130: 31.311254 | E130: 0.043730086 | F130: 0.030813999 | G130: 0 | H130: 5.3866835 | I130: 3.6742414 | J130: 28.739009 | K130: 184.21087 | L130: 15.40641 | M130: 37.638587 | N130: 69.217315 | O130: 64.848874 | P130: 279528.26 | Q130: 259154.72 | R130: 777.53518 | S130: 0 | T130: 0 | U130: 0.029845573 | V130: 0.3002845 | W130: 0 | X130: 0.67116565 | Y130: 0 | Z130: 0.00044682849 | AA130: 0.00085731119 | AB130: 0.0037609579 | AC130: 1.7450145e-05 | AD130: 0.025731436 | AE130: 0.0047000378 | AF130: 0.79385594 | AG130: 0.98041365 | AH130: 0.99450896 | AI130: 0.99807633 | AJ130: 1 | AK130: 1 | AL130: 1 | AM130: 0 | AN130: 0 | AO130: 16:175-200 | AP130: 175-200 | AQ130: 6.403454e+09 | AR130: 24709 | AS130: 0 | AT130: 69.97155 | AU130: 69.97155 | AV130: 30.02845 | AW130: 30.02845 | AX130: 0 | AY130: 2860.1967
A131: 97 | B131: 0.96660881 | C131: 37.052644 | D131: 33.471305 | E131: 0.03783817 | F131: 0.033391187 | G131: 0 | H131: 5.4948867 | I131: 3.6704199 | J131: 41.263997 | K131: 208.14902 | L131: 15.672694 | M131: 37.422384 | N131: 78.959214 | O131: 71.656854 | P131: 274574.82 | Q131: 254761.15 | R131: 775.65877 | S131: 0 | T131: 0 | U131: 0.022791785 | V131: 0.26346594 | W131: 0 | X131: 0.48218657 | Y131: 0 | Z131: 0.00044560604 | AA131: 0.00099275164 | AB131: 0.0038411009 | AC131: 7.6864767e-05 | AD131: 0.028034848 | AE131: 0.037903055 | AF131: 0.63450754 | AG131: 0.91546238 | AH131: 0.97599908 | AI131: 0.99078252 | AJ131: 1 | AK131: 1 | AL131: 1 | AM131: 0 | AN131: 0 | AO131: 17:200-225 | AP131: 200-225 | AQ131: 9.1612111e+08 | AR131: 3596 | AS131: 0 | AT131: 73.653406 | AU131: 73.653406 | AV131: 26.346594 | AW131: 26.346594 | AX131: 0 | AY131: 3108.4242
A132: 97 | B132: 0.9665913 | C132: 34.341607 | D132: 33.485771 | E132: 0.034451291 | F132: 0.033408703 | G132: 0 | H132: 5.4921254 | I132: 3.6556027 | J132: 42.368549 | K132: 232.20992 | L132: 15.296587 | M132: 35.803612 | N132: 86.981576 | O132: 75.157305 | P132: 281144.61 | Q132: 261019.52 | R132: 778.15278 | S132: 0 | T132: 0 | U132: 0.010950428 | V132: 0.2138923 | W132: 0 | X132: 0.24164737 | Y132: 0 | Z132: 0.00045418908 | AA132: 0.0010867688 | AB132: 0.0039097386 | AC132: 0.0003660817 | AD132: 0.027591909 | AE132: 0.089261421 | AF132: 0.42925329 | AG132: 0.72155098 | AH132: 0.83787515 | AI132: 0.98175486 | AJ132: 1 | AK132: 1 | AL132: 1 | AM132: 0 | AN132: 0 | AO132: 18:225-250 | AP132: 225-250 | AQ132: 1.1328247e+08 | AR132: 434 | AS132: 0 | AT132: 78.61077 | AU132: 78.61077 | AV132: 21.38923 | AW132: 21.38923 | AX132: 0 | AY132: 3264.9183
A133: 97 | B133: 0.96856619 | C133: 86.528924 | D133: 31.836539 | E133: 0.15384448 | F133: 0.031433814 | G133: 0 | H133: 5.3898897 | I133: 3.6359111 | J133: 35.222488 | K133: 254.97824 | L133: 13.977084 | M133: 36.520121 | N133: 90.915794 | O133: 75.934593 | P133: 300055.07 | Q133: 285614.64 | R133: 776.66317 | S133: 0 | T133: 0 | U133: 0 | V133: 0.31513296 | W133: 0 | X133: 0.24730728 | Y133: 0 | Z133: 0.00050009394 | AA133: 0.00067034081 | AB133: 0.0038426656 | AC133: 0.0002304585 | AD133: 0.026190237 | AE133: 0.11049626 | AF133: 0.36306355 | AG133: 0.45685609 | AH133: 0.93049475 | AI133: 1 | AJ133: 1 | AK133: 1 | AL133: 1 | AM133: 0 | AN133: 0 | AO133: 999:>= 250 | AP133: >= 250 | AQ133: 4284219.7 | AR133: 15 | AS133: 0 | AT133: 68.486704 | AU133: 68.486704 | AV133: 31.513296 | AW133: 31.513296 | AX133: 0 | AY133: 3735.8626
F137: high media
A138: modelId | B138: SFACTOR_PREPAY_TRACKING_CPR | C138: PREPAY_CPR1 | D138: PREPAY_TRACKING_CPR1 | E138: PREPAY_SMM1 | F138: PREPAY_TRACKING_SMM1 | G138: PCT_LOANTYPE | H138: _ORIGNOTERATE | I138: _ZEROSATO | J138: _SATO | K138: _REFI_INCENTIVE_Fixed | L138: _Fixed_cost | M138: _LOANAGE | N138: _LTV | O138: _CLTV | P138: _AVG_LOANSIZE_SCHAMBALANCE | Q138: _WACLS | R138: _FICO | S138: PCT_ISSECONDLIEN | T138: _OrigCombLTV | U138: PCT_SVC | V138: PCT_TPO | W138: PCT_GEO | X138: PCT_LOANPURPOSE | Y138: PCT_OCC | Z138: curtailsmm | AA138: defaultsmm | AB138: toverSmm | AC138: cashoutSmm | AD138: refiSmm | AE138: cumHPA | AF138: cumHPA05Pct | AG138: cumHPA15Pct | AH138: cumHPA20Pct | AI138: cumHPA25Pct | AJ138: cumHPA30Pct | AK138: cumHPA35Pct | AL138: cumHPA40Pct | AM138: adjtoverSmm | AN138: adjRefiSmm | AO138: groupByColumn | AP138: curve | AQ138: Balance | AR138: LoanCount | AS138: PCT_BROKER | AT138: PCT_CORRES | AU138: PCT_NonRETAIL | AV138: PCT_RETAIL | AW138: PCT_CashWindow | AX138: PCT_NonCashWindow | AY138: _Burnout_Fixed
A139: 96 | B139: 0.98119233 | C139: 0 | D139: 20.374945 | E139: 0 | F139: 0.018807668 | G139: 0 | H139: 5.0073042 | I139: 3.8587571 | J139: -7.7679575 | K139: 45.850297 | L139: 100 | M139: 38.235944 | N139: 54.294378 | O139: 6.1854485 | P139: 28883.502 | Q139: 26580.115 | R139: 778.29217 | S139: 0 | T139: 0 | U139: 0 | V139: 0.35281111 | W139: 0 | X139: 0 | Y139: 0 | Z139: 0.010364355 | AA139: 0.00041857955 | AB139: 0.0069299003 | AC139: 0 | AD139: 0.0010948165 | AE139: -0.064847236 | AF139: 1 | AG139: 1 | AH139: 1 | AI139: 1 | AJ139: 1 | AK139: 1 | AL139: 1 | AM139: 0 | AN139: 0 | AO139: 10:25-50 | AP139: 25-50 | AQ139: 53160.23 | AR139: 2 | AS139: 0 | AT139: 64.718889 | AU139: 64.718889 | AV139: 35.281111 | AW139: 35.281111 | AX139: 0 | AY139: 2048.3802
A140: 96 | B140: 0.97659979 | C140: 0 | D140: 24.733882 | E140: 0 | F140: 0.02340021 | G140: 0 | H140: 5.25 | I140: 3.889063 | J140: 15.3495 | K140: 58.82 | L140: 100 | M140: 36 | N140: 53 | O140: 2.17 | P140: 16446.75 | Q140: 16446.75 | R140: 788 | S140: 0 | T140: 0 | U140: 0 | V140: 1 | W140: 0 | X140: 0 | Y140: 0 | Z140: 0.01409106 | AA140: 0.00059012 | AB140: 0.00803485 | AC140: 0 | AD140: 0.00068418 | AE140: -0.03670308 | AF140: 1 | AG140: 1 | AH140: 1 | AI140: 1 | AJ140: 1 | AK140: 1 | AL140: 1 | AM140: 0 | AN140: 0 | AO140: 11-2:55-60 | AP140: 55-60 | AQ140: 16446.75 | AR140: 1 | AS140: 0 | AT140: 0 | AU140: 0 | AV140: 100 | AW140: 100 | AX140: 0 | AY140: 2114.96
A141: 96 | B141: 0.96519015 | C141: 0 | D141: 34.633599 | E141: 0 | F141: 0.03480985 | G141: 0 | H141: 5 | I141: 4.153825 | J141: -14.4812 | K141: 65.92 | L141: 17.18 | M141: 26 | N141: 95 | O141: 79.18 | P141: 232170.07 | Q141: 232170.07 | R141: 770 | S141: 0 | T141: 0 | U141: 0 | V141: 0 | W141: 0 | X141: 1 | Y141: 0 | Z141: 0.000803 | AA141: 0.00029903 | AB141: 0.00352274 | AC141: 0 | AD141: 0.03018507 | AE141: -0.026023842 | AF141: 1 | AG141: 1 | AH141: 1 | AI141: 1 | AJ141: 1 | AK141: 1 | AL141: 1 | AM141: 0 | AN141: 0 | AO141: 11-4:65-70 | AP141: 65-70 | AQ141: 232170.07 | AR141: 1 | AS141: 0 | AT141: 100 | AU141: 100 | AV141: 0 | AW141: 0 | AX141: 0 | AY141: 2007.21
A142: 96 | B142: 0.96416655 | C142: 31.735277 | D142: 35.46063 | E142: 0.03131399 | F142: 0.035833451 | G142: 0 | H142: 4.9804384 | I142: 4.091103 | J142: -2.4334577 | K142: 71.878078 | L142: 29.082251 | M142: 31.443908 | N142: 84.8672 | O142: 64.273713 | P142: 231308.59 | Q142: 89953.178 | R142: 771.59719 | S142: 0 | T142: 0 | U142: 0 | V142: 0.052587469 | W142: 0 | X142: 0.2750431 | Y142: 0 | Z142: 0.0021991697 | AA142: 0.00021787542 | AB142: 0.0046047121 | AC142: 0 | AD142: 0.028811681 | AE142: -0.00058853978 | AF142: 0.94565019 | AG142: 1 | AH142: 1 | AI142: 1 | AJ142: 1 | AK142: 1 | AL142: 1 | AM142: 0 | AN142: 0 | AO142: 11:50-75 | AP142: 50-75 | AQ142: 989484.96 | AR142: 11 | AS142: 0 | AT142: 94.741253 | AU142: 94.741253 | AV142: 5.2587469 | AW142: 5.2587469 | AX142: 0 | AY142: 2085.515
A143: 96 | B143: 0.96999665 | C143: 75.12402 | D143: 30.618636 | E143: 0.10947042 | F143: 0.030003346 | G143: 0 | H143: 5.0874263 | I143: 3.8991322 | J143: 4.6528775 | K143: 92.496268 | L143: 46.922884 | M143: 34.635219 | N143: 79.346614 | O143: 48.924294 | P143: 163922.03 | Q143: 63864.502 | R143: 775.13984 | S143: 0 | T143: 0 | U143: 0 | V143: 0.34323436 | W143: 0 | X143: 0.35260476 | Y143: 0 | Z143: 0.0035263312 | AA143: 0.00044628965 | AB143: 0.0051085608 | AC143: 2.3829555e-05 | AD143: 0.020898321 | AE143: 0.013044208 | AF143: 0.84861557 | AG143: 0.98179977 | AH143: 0.98179977 | AI143: 0.99703064 | AJ143: 1 | AK143: 1 | AL143: 1 | AM143: 0 | AN143: 0 | AO143: 12:75-100 | AP143: 75-100 | AQ143: 6514179.2 | AR143: 102 | AS143: 0 | AT143: 65.676564 | AU143: 65.676564 | AV143: 34.323436 | AW143: 34.323436 | AX143: 0 | AY143: 2232.8266
A144: 96 | B144: 0.96482394 | C144: 41.152211 | D144: 34.93059 | E144: 0.043222737 | F144: 0.035176057 | G144: 0 | H144: 5.1566289 | I144: 3.8626142 | J144: 7.4998933 | K144: 117.34231 | L144: 30.356748 | M144: 36.270305 | N144: 79.198829 | O144: 56.200871 | P144: 182615.02 | Q144: 124724.04 | R144: 777.94792 | S144: 0 | T144: 0 | U144: 0.012453106 | V144: 0.35469302 | W144: 0 | X144: 0.45074758 | Y144: 0 | Z144: 0.0016673738 | AA144: 0.00051598676 | AB144: 0.0049197501 | AC144: 5.0875095e-06 | AD144: 0.028067843 | AE144: -0.0087515521 | AF144: 0.81499604 | AG144: 0.99409153 | AH144: 1 | AI144: 1 | AJ144: 1 | AK144: 1 | AL144: 1 | AM144: 0 | AN144: 0 | AO144: 13:100-125 | AP144: 100-125 | AQ144: 53132442 | AR144: 426 | AS144: 0 | AT144: 64.530698 | AU144: 64.530698 | AV144: 35.469302 | AW144: 35.469302 | AX144: 0 | AY144: 2251.1841
A145: 96 | B145: 0.94982991 | C145: 42.593394 | D145: 46.07997 | E145: 0.045197628 | F145: 0.050170085 | G145: 0 | H145: 5.1459985 | I145: 3.8623083 | J145: 5.740604 | K145: 140.2459 | L145: 15.573586 | M145: 35.983076 | N145: 61.597253 | O145: 58.063223 | P145: 281106.92 | Q145: 256245.2 | R145: 779.24518 | S145: 0 | T145: 0 | U145: 0.029072545 | V145: 0.33035966 | W145: 0 | X145: 0.75179069 | Y145: 0 | Z145: 0.00046621189 | AA145: 0.00047582512 | AB145: 0.004217646 | AC145: 8.1820362e-06 | AD145: 0.045002205 | AE145: -0.0072979565 | AF145: 0.78579818 | AG145: 0.98693773 | AH145: 0.99693465 | AI145: 0.99949472 | AJ145: 1 | AK145: 1 | AL145: 1 | AM145: 0 | AN145: 0 | AO145: 14:125-150 | AP145: 125-150 | AQ145: 5.3719244e+09 | AR145: 20964 | AS145: 0 | AT145: 66.964034 | AU145: 66.964034 | AV145: 33.035966 | AW145: 33.035966 | AX145: 0 | AY145: 2205.188
A146: 96 | B146: 0.95046077 | C146: 44.106171 | D146: 45.648645 | E146: 0.047320131 | F146: 0.049539226 | G146: 0 | H146: 5.2439505 | I146: 3.7219745 | J146: 13.954143 | K146: 162.73199 | L146: 15.914148 | M146: 36.169459 | N146: 65.351666 | O146: 61.873933 | P146: 271939.59 | Q146: 250869.37 | R146: 778.43785 | S146: 0 | T146: 0 | U146: 0.025079781 | V146: 0.32896083 | W146: 0 | X146: 0.72400655 | Y146: 0 | Z146: 0.00044736572 | AA146: 0.00065345172 | AB146: 0.0039919848 | AC146: 8.1232066e-06 | AD146: 0.044438285 | AE146: -0.006308962 | AF146: 0.84009366 | AG146: 0.98653978 | AH146: 0.99740946 | AI146: 0.99926471 | AJ146: 1 | AK146: 1 | AL146: 1 | AM146: 0 | AN146: 0 | AO146: 15:150-175 | AP146: 150-175 | AQ146: 1.3676897e+10 | AR146: 54518 | AS146: 0 | AT146: 67.103917 | AU146: 67.103917 | AV146: 32.896083 | AW146: 32.896083 | AX146: 0 | AY146: 2425.0502
A147: 96 | B147: 0.95094104 | C147: 41.525582 | D147: 45.318164 | E147: 0.043730086 | F147: 0.049058961 | G147: 0 | H147: 5.3866835 | I147: 3.6742414 | J147: 28.739009 | K147: 184.21087 | L147: 15.40641 | M147: 37.638587 | N147: 69.217315 | O147: 64.848874 | P147: 279528.26 | Q147: 259154.72 | R147: 777.53518 | S147: 0 | T147: 0 | U147: 0.029845573 | V147: 0.3002845 | W147: 0 | X147: 0.67116565 | Y147: 0 | Z147: 0.00044682849 | AA147: 0.00085731119 | AB147: 0.0037609579 | AC147: 1.7450145e-05 | AD147: 0.043976398 | AE147: 0.0047000378 | AF147: 0.79385594 | AG147: 0.98041365 | AH147: 0.99450896 | AI147: 0.99807633 | AJ147: 1 | AK147: 1 | AL147: 1 | AM147: 0 | AN147: 0 | AO147: 16:175-200 | AP147: 175-200 | AQ147: 6.403454e+09 | AR147: 24709 | AS147: 0 | AT147: 69.97155 | AU147: 69.97155 | AV147: 30.02845 | AW147: 30.02845 | AX147: 0 | AY147: 2860.1967
A148: 96 | B148: 0.95098783 | C148: 37.052644 | D148: 45.285869 | E148: 0.03783817 | F148: 0.049012171 | G148: 0 | H148: 5.4948867 | I148: 3.6704199 | J148: 41.263997 | K148: 208.14902 | L148: 15.672694 | M148: 37.422384 | N148: 78.959214 | O148: 71.656854 | P148: 274574.82 | Q148: 254761.15 | R148: 775.65877 | S148: 0 | T148: 0 | U148: 0.022791785 | V148: 0.26346594 | W148: 0 | X148: 0.48218657 | Y148: 0 | Z148: 0.00044560604 | AA148: 0.00099275164 | AB148: 0.0038411009 | AC148: 7.6864767e-05 | AD148: 0.043655832 | AE148: 0.037903055 | AF148: 0.63450754 | AG148: 0.91546238 | AH148: 0.97599908 | AI148: 0.99078252 | AJ148: 1 | AK148: 1 | AL148: 1 | AM148: 0 | AN148: 0 | AO148: 17:200-225 | AP148: 200-225 | AQ148: 9.1612111e+08 | AR148: 3596 | AS148: 0 | AT148: 73.653406 | AU148: 73.653406 | AV148: 26.346594 | AW148: 26.346594 | AX148: 0 | AY148: 3108.4242
...

Sheet Actual
A1: WALA [12,24) | C1: BROKER
A2: modelId | B2: SFACTOR_PREPAY_TRACKING_CPR | C2: PREPAY_CPR1 | D2: PREPAY_TRACKING_CPR1 | E2: PREPAY_SMM1 | F2: PREPAY_TRACKING_SMM1 | G2: PCT_LOANTYPE | H2: _ORIGNOTERATE | I2: _ZEROSATO | J2: _SATO | K2: _REFI_INCENTIVE_Fixed | L2: _Fixed_cost | M2: _LOANAGE | N2: _LTV | O2: _CLTV | P2: _AVG_LOANSIZE_SCHAMBALANCE | Q2: _WACLS | R2: _FICO | S2: PCT_ISSECONDLIEN | T2: _OrigCombLTV | U2: PCT_SVC | V2: PCT_TPO | W2: PCT_GEO | X2: PCT_LOANPURPOSE | Y2: PCT_OCC | Z2: curtailsmm | AA2: defaultsmm | AB2: toverSmm | AC2: cashoutSmm | AD2: refiSmm | AE2: cumHPA | AF2: cumHPA05Pct | AG2: cumHPA15Pct | AH2: cumHPA20Pct | AI2: cumHPA25Pct | AJ2: cumHPA30Pct | AK2: cumHPA35Pct | AL2: cumHPA40Pct | AM2: adjtoverSmm | AN2: adjRefiSmm | AO2: groupByColumn | AP2: curve | AQ2: Balance | AR2: LoanCount | AS2: PCT_BROKER | AT2: PCT_CORRES | AU2: PCT_NonRETAIL | AV2: PCT_RETAIL | AW2: PCT_CashWindow | AX2: PCT_NonCashWindow
A3: 4.3 | B3: 0.99354299 | C3: 3.4433222 | D3: 7.4790735 | E3: 0.0029157422 | F3: 0.0064570079 | G3: 0 | H3: 3.9622665 | I3: 4.1506701 | J3: -55.102824 | K3: -57.170377 | L3: 18.591369 | M3: 15.604608 | N3: 77.726934 | O3: 75.492093 | P3: 267072.12 | Q3: 193404.05 | R3: 774.87434 | S3: 0 | T3: 0 | U3: 0.089424414 | V3: 0 | W3: 0 | X3: 0.58543282 | Y3: 0 | Z3: 0.00067107958 | AA3: 7.5421688e-05 | AB3: 0.0025087098 | AC3: 2.9446125e-08 | AD3: 0.0032017562 | AE3: -0.025268185 | AF3: 0.99001879 | AG3: 0.99720024 | AH3: 1 | AI3: 1 | AJ3: 1 | AK3: 1 | AL3: 1 | AM3: 0 | AN3: 0 | AO3: 06:-75--50 | AP3: =-75--50 -> -25 | AQ3: 22048061 | AR3: 114 | AS3: 100 | AT3: 0 | AU3: 100 | AV3: 0 | AW3: 0 | AX3: 0
A4: 4.3 | B4: 0.9934404 | C4: 2.6756426 | D4: 7.5936475 | E4: 0.0022575225 | F4: 0.0065595963 | G4: 0 | H4: 3.91998 | I4: 4.1424648 | J4: -57.659948 | K4: -32.594271 | L4: 14.98906 | M4: 15.424298 | N4: 73.798811 | O4: 72.801415 | P4: 293064.03 | Q4: 263371.78 | R4: 784.82056 | S4: 0 | T4: 0 | U4: 0.08318706 | V4: 0 | W4: 0 | X4: 0.63466923 | Y4: 0 | Z4: 0.00042337918 | AA4: 5.4947755e-05 | AB4: 0.0024369602 | AC4: 1.9932865e-08 | AD4: 0.0036442753 | AE4: -0.020683738 | AF4: 0.98301074 | AG4: 0.99723916 | AH4: 1 | AI4: 1 | AJ4: 1 | AK4: 1 | AL4: 1 | AM4: 0 | AN4: 0 | AO4: 07:-50--25 | AP4: =-50--25 -> -25 | AQ4: 2.4835959e+08 | AR4: 943 | AS4: 100 | AT4: 0 | AU4: 100 | AV4: 0 | AW4: 0 | AX4: 0
A5: 4.3 | B5: 0.98810675 | C5: 14.515411 | D5: 13.374372 | E5: 0.012984471 | F5: 0.01189325 | G5: 0 | H5: 4.0994748 | I5: 4.1233851 | J5: -40.112546 | K5: -8.5065994 | L5: 14.517274 | M5: 15.824699 | N5: 72.180941 | O5: 71.16733 | P5: 297035.51 | Q5: 273997.1 | R5: 782.74924 | S5: 0 | T5: 0 | U5: 0.16198165 | V5: 0 | W5: 0 | X5: 0.71326488 | Y5: 0 | Z5: 0.00037641719 | AA5: 6.1641507e-05 | AB5: 0.0025045364 | AC5: 1.1985382e-07 | AD5: 0.0089505203 | AE5: -0.015473879 | AF5: 0.95973186 | AG5: 0.99363686 | AH5: 0.99969863 | AI5: 1 | AJ5: 1 | AK5: 1 | AL5: 1 | AM5: 0 | AN5: 0 | AO5: 08:-25-0 | AP5: =-25-0 -> -25 | AQ5: 2.0251126e+09 | AR5: 7391 | AS5: 100 | AT5: 0 | AU5: 100 | AV5: 0 | AW5: 0 | AX5: 0
A6: 4.3 | B6: 0.98304592 | C6: 27.048998 | D6: 18.551023 | E6: 0.025939486 | F6: 0.016954085 | G6: 0 | H6: 4.1521468 | I6: 4.0348346 | J6: -30.391947 | K6: 15.744335 | L6: 14.364007 | M6: 15.776989 | N6: 68.038082 | O6: 65.942075 | P6: 298325.63 | Q6: 277825.05 | R6: 783.61193 | S6: 0 | T6: 0 | U6: 0.23317829 | V6: 0 | W6: 0 | X6: 0.8177067 | Y6: 0 | Z6: 0.00036976726 | AA6: 5.8793704e-05 | AB6: 0.0027739843 | AC6: 3.0262744e-06 | AD6: 0.013748499 | AE6: 0.0038239737 | AF6: 0.83514428 | AG6: 0.95178217 | AH6: 0.99513288 | AI6: 0.99904793 | AJ6: 1 | AK6: 1 | AL6: 1 | AM6: 0 | AN6: 0 | AO6: 09:0-25 | AP6: 0-25 | AQ6: 1.0989092e+10 | AR6: 39554 | AS6: 100 | AT6: 0 | AU6: 100 | AV6: 0 | AW6: 0 | AX6: 0
A7: 4.3 | B7: 0.97553016 | C7: 39.511307 | D7: 25.717173 | E7: 0.041027433 | F7: 0.024469838 | G7: 0 | H7: 4.1700427 | I7: 3.886904 | J7: -26.925548 | K7: 37.409975 | L7: 13.639154 | M7: 16.149073 | N7: 64.844231 | O7: 61.095981 | P7: 311881.57 | Q7: 292677.63 | R7: 783.83427 | S7: 0 | T7: 0 | U7: 0.2676584 | V7: 0 | W7: 0 | X7: 0.83998291 | Y7: 0 | Z7: 0.00036821089 | AA7: 5.7737956e-05 | AB7: 0.0030840132 | AC7: 1.0551737e-05 | AD7: 0.020949309 | AE7: 0.034424605 | AF7: 0.65979439 | AG7: 0.8965255 | AH7: 0.98913006 | AI7: 0.99836628 | AJ7: 1 | AK7: 1 | AL7: 1 | AM7: 0 | AN7: 0 | AO7: 10:25-50 | AP7: 25-50 | AQ7: 2.1924188e+10 | AR7: 74909 | AS7: 100 | AT7: 0 | AU7: 100 | AV7: 0 | AW7: 0 | AX7: 0
A8: 4.3 | B8: 0.96749363 | C8: 47.215946 | D8: 32.736821 | E8: 0.051853975 | F8: 0.032506367 | G8: 0 | H8: 4.4546713 | I8: 3.8939111 | J8: -17.636655 | K8: 62.476491 | L8: 14.232973 | M8: 17.622334 | N8: 67.200221 | O8: 63.714954 | P8: 300315.56 | Q8: 280510.29 | R8: 782.16221 | S8: 0 | T8: 0 | U8: 0.24509649 | V8: 0 | W8: 0 | X8: 0.76375298 | Y8: 0 | Z8: 0.00037146776 | AA8: 8.9448587e-05 | AB8: 0.0032444203 | AC8: 9.1333761e-06 | AD8: 0.028791883 | AE8: 0.02481458 | AF8: 0.68593791 | AG8: 0.94531389 | AH8: 0.99334833 | AI8: 0.99910374 | AJ8: 1 | AK8: 1 | AL8: 1 | AM8: 0 | AN8: 0 | AO8: 11:50-75 | AP8: 50-75 | AQ8: 1.7351525e+10 | AR8: 61857 | AS8: 100 | AT8: 0 | AU8: 100 | AV8: 0 | AW8: 0 | AX8: 0
A9: 4.3 | B9: 0.9616878 | C9: 45.770827 | D9: 37.423788 | E9: 0.049717463 | F9: 0.038312201 | G9: 0 | H9: 4.6792015 | I9: 3.8981509 | J9: -11.53115 | K9: 85.668971 | L9: 14.263814 | M9: 17.602014 | N9: 66.442911 | O9: 62.693089 | P9: 299859.64 | Q9: 279920.92 | R9: 780.85805 | S9: 0 | T9: 0 | U9: 0.28399373 | V9: 0 | W9: 0 | X9: 0.69290849 | Y9: 0 | Z9: 0.00037185965 | AA9: 0.00010535088 | AB9: 0.0033641167 | AC9: 1.8856207e-05 | AD9: 0.034452003 | AE9: 0.028319628 | AF9: 0.62658474 | AG9: 0.94565646 | AH9: 0.98872447 | AI9: 0.99818447 | AJ9: 1 | AK9: 1 | AL9: 1 | AM9: 0 | AN9: 0 | AO9: 12:75-100 | AP9: 75-100 | AQ9: 1.1137494e+10 | AR9: 39788 | AS9: 100 | AT9: 0 | AU9: 100 | AV9: 0 | AW9: 0 | AX9: 0
A10: 4.3 | B10: 0.95610776 | C10: 45.909203 | D10: 41.644457 | E10: 0.049919769 | F10: 0.04389224 | G10: 0 | H10: 4.8190174 | I10: 3.7827978 | J10: -7.033373 | K10: 111.76843 | L10: 14.851525 | M10: 18.573443 | N10: 70.047731 | O10: 64.517258 | P10: 288600.21 | Q10: 268853.2 | R10: 779.33271 | S10: 0 | T10: 0 | U10: 0.29515185 | V10: 0 | W10: 0 | X10: 0.61609329 | Y10: 0 | Z10: 0.00037279538 | AA10: 0.00014722462 | AB10: 0.0036961846 | AC10: 3.6742999e-05 | AD10: 0.039639278 | AE10: 0.052894394 | AF10: 0.44589189 | AG10: 0.9189403 | AH10: 0.98503593 | AI10: 0.99699297 | AJ10: 1 | AK10: 1 | AL10: 1 | AM10: 0 | AN10: 0 | AO10: 13:100-125 | AP10: 100-125 | AQ10: 5.7252288e+09 | AR10: 21295 | AS10: 100 | AT10: 0 | AU10: 100 | AV10: 0 | AW10: 0 | AX10: 0
A11: 4.3 | B11: 0.95139204 | C11: 46.476872 | D11: 45.006143 | E11: 0.050754696 | F11: 0.048607957 | G11: 0 | H11: 4.8761355 | I11: 3.6738705 | J11: -6.547352 | K11: 134.37324 | L11: 14.345575 | M11: 20.090596 | N11: 70.80133 | O11: 63.193322 | P11: 297212.06 | Q11: 278337.2 | R11: 778.25756 | S11: 0 | T11: 0 | U11: 0.29020541 | V11: 0 | W11: 0 | X11: 0.61283836 | Y11: 0 | Z11: 0.00037411096 | AA11: 0.00016841151 | AB11: 0.0036857396 | AC11: 8.5910415e-05 | AD11: 0.04429377 | AE11: 0.085370719 | AF11: 0.28253617 | AG11: 0.87003254 | AH11: 0.9662038 | AI11: 0.99610031 | AJ11: 1 | AK11: 1 | AL11: 1 | AM11: 0 | AN11: 0 | AO11: 14:125-150 | AP11: 125-150 | AQ11: 2.6208231e+09 | AR11: 9416 | AS11: 100 | AT11: 0 | AU11: 100 | AV11: 0 | AW11: 0 | AX11: 0
A12: 4.3 | B12: 0.94664668 | C12: 44.242836 | D12: 48.208917 | E12: 0.047514463 | F12: 0.05335332 | G12: 0 | H12: 5.0228991 | I12: 3.6711342 | J12: 6.8476451 | K12: 160.18516 | L12: 14.050936 | M12: 20.067577 | N12: 78.702585 | O12: 68.818309 | P12: 302497.45 | Q12: 284181.94 | R12: 777.14943 | S12: 0 | T12: 0 | U12: 0.23643044 | V12: 0 | W12: 0 | X12: 0.52204473 | Y12: 0 | Z12: 0.00037364661 | AA12: 0.00024360029 | AB12: 0.0038902341 | AC12: 0.00013030684 | AD12: 0.048715516 | AE12: 0.10704924 | AF12: 0.15712908 | AG12: 0.78788788 | AH12: 0.94414223 | AI12: 0.9898934 | AJ12: 1 | AK12: 1 | AL12: 1 | AM12: 0 | AN12: 0 | AO12: 15:150-175 | AP12: 150-175 | AQ12: 4.4019782e+08 | AR12: 1549 | AS12: 100 | AT12: 0 | AU12: 100 | AV12: 0 | AW12: 0 | AX12: 0
A13: 4.3 | B13: 0.94180872 | C13: 53.130436 | D13: 51.297364 | E13: 0.061197489 | F13: 0.058191283 | G13: 0 | H13: 5.046812 | I13: 3.6581714 | J13: 6.4300909 | K13: 183.9435 | L13: 13.884685 | M13: 20.486383 | N13: 85.498759 | O13: 72.57064 | P13: 305684.75 | Q13: 287591.9 | R13: 777.65331 | S13: 0 | T13: 0 | U13: 0.23252351 | V13: 0 | W13: 0 | X13: 0.40200049 | Y13: 0 | Z13: 0.00037498084 | AA13: 0.00032210145 | AB13: 0.0041021819 | AC13: 0.00035720284 | AD13: 0.0530348 | AE13: 0.13942807 | AF13: 0.035231054 | AG13: 0.62060278 | AH13: 0.85157551 | AI13: 0.98674363 | AJ13: 1 | AK13: 1 | AL13: 1 | AM13: 0 | AN13: 0 | AO13: 16:175-200 | AP13: 175-200 | AQ13: 96630878 | AR13: 336 | AS13: 100 | AT13: 0 | AU13: 100 | AV13: 0 | AW13: 0 | AX13: 0
A14: 4.3 | B14: 0.9407424 | C14: 47.495831 | D14: 51.954953 | E14: 0.052273955 | F14: 0.059257599 | G14: 0 | H14: 5.1962175 | I14: 3.6487088 | J14: 17.28872 | K14: 209.55229 | L14: 14.52586 | M14: 20.792683 | N14: 90.120235 | O14: 75.17575 | P14: 294450.4 | Q14: 274910.83 | R14: 775.39517 | S14: 0 | T14: 0 | U14: 0.083777428 | V14: 0 | W14: 0 | X14: 0.28831945 | Y14: 0 | Z14: 0.00037198764 | AA14: 0.00037985115 | AB14: 0.0043843365 | AC14: 0.0005945363 | AD14: 0.053526869 | AE14: 0.16459065 | AF14: 0 | AG14: 0.46714353 | AH14: 0.67606014 | AI14: 0.98161705 | AJ14: 1 | AK14: 1 | AL14: 1 | AM14: 0 | AN14: 0 | AO14: 17:200-225 | AP14: 200-225 | AQ14: 20893223 | AR14: 76 | AS14: 100 | AT14: 0 | AU14: 100 | AV14: 0 | AW14: 0 | AX14: 0
A15: 4.3 | B15: 0.94906051 | C15: 46.592588 | D15: 46.601772 | E15: 0.050925887 | F15: 0.050939488 | G15: 0 | H15: 5.321533 | I15: 3.665408 | J15: 30.474314 | K15: 232.6404 | L15: 17.927401 | M15: 20.850682 | N15: 92.695715 | O15: 75.691523 | P15: 246276.83 | Q15: 222772.75 | R15: 788.41159 | S15: 0 | T15: 0 | U15: 0 | V15: 0 | W15: 0 | X15: 0.34002479 | Y15: 0 | Z15: 0.00040339218 | AA15: 4.2794964e-05 | AB15: 0.004240869 | AC15: 0.00068165279 | AD15: 0.045570761 | AE15: 0.17333363 | AF15: 0 | AG15: 0.29883154 | AH15: 0.63135198 | AI15: 0.95367429 | AJ15: 1 | AK15: 1 | AL15: 1 | AM15: 0 | AN15: 0 | AO15: 18:225-250 | AP15: 225-250 | AQ15: 3787136.8 | AR15: 17 | AS15: 100 | AT15: 0 | AU15: 100 | AV15: 0 | AW15: 0 | AX15: 0
A19: WALA [12,24) | C19: CORRES
A20: modelId | B20: SFACTOR_PREPAY_TRACKING_CPR | C20: PREPAY_CPR1 | D20: PREPAY_TRACKING_CPR1 | E20: PREPAY_SMM1 | F20: PREPAY_TRACKING_SMM1 | G20: PCT_LOANTYPE | H20: _ORIGNOTERATE | I20: _ZEROSATO | J20: _SATO | K20: _REFI_INCENTIVE_Fixed | L20: _Fixed_cost | M20: _LOANAGE | N20: _LTV | O20: _CLTV | P20: _AVG_LOANSIZE_SCHAMBALANCE | Q20: _WACLS | R20: _FICO | S20: PCT_ISSECONDLIEN | T20: _OrigCombLTV | U20: PCT_SVC | V20: PCT_TPO | W20: PCT_GEO | X20: PCT_LOANPURPOSE | Y20: PCT_OCC | Z20: curtailsmm | AA20: defaultsmm | AB20: toverSmm | AC20: cashoutSmm | AD20: refiSmm | AE20: cumHPA | AF20: cumHPA05Pct | AG20: cumHPA15Pct | AH20: cumHPA20Pct | AI20: cumHPA25Pct | AJ20: cumHPA30Pct | AK20: cumHPA35Pct | AL20: cumHPA40Pct | AM20: adjtoverSmm | AN20: adjRefiSmm | AO20: groupByColumn | AP20: curve | AQ20: Balance | AR20: LoanCount | AS20: PCT_BROKER | AT20: PCT_CORRES | AU20: PCT_NonRETAIL | AV20: PCT_RETAIL | AW20: PCT_CashWindow | AX20: PCT_NonCashWindow
A21: 4.3 | B21: 0.9957006 | C21: 1.2100205e-05 | D21: 5.0390158 | E21: 1.0083505e-08 | F21: 0.0042994036 | G21: 0 | H21: 4.0264725 | I21: 4.1375376 | J21: -42.855524 | K21: -108.8538 | L21: 20.131193 | M21: 15.604363 | N21: 76.15288 | O21: 75.620604 | P21: 198516.22 | Q21: 198343.74 | R21: 760.45864 | S21: 0 | T21: 0 | U21: 0 | V21: 0 | W21: 0 | X21: 0.21177999 | Y21: 0 | Z21: 0.00035089724 | AA21: 5.1078517e-05 | AB21: 0.0028684717 | AC21: 0 | AD21: 0.0010289422 | AE21: -0.01596622 | AF21: 1 | AG21: 1 | AH21: 1 | AI21: 1 | AJ21: 1 | AK21: 1 | AL21: 1 | AM21: 0 | AN21: 0 | AO21: 04:-125--100 | AP21: =-125--100 -> -25 | AQ21: 991718.69 | AR21: 5 | AS21: 0 | AT21: 100 | AU21: 100 | AV21: 0 | AW21: 0 | AX21: 0
A22: 4.3 | B22: 0.99034254 | C22: 7.935874 | D22: 10.99278 | E22: 0.0068667181 | F22: 0.0096574553 | G22: 0 | H22: 4.1493576 | I22: 4.0940505 | J22: -33.386672 | K22: -83.205891 | L22: 15.783595 | M22: 15.690168 | N22: 76.749332 | O22: 75.908226 | P22: 298964.84 | Q22: 222085.04 | R22: 780.43588 | S22: 0 | T22: 0 | U22: 0 | V22: 0 | W22: 0 | X22: 0.37109602 | Y22: 0 | Z22: 0.00053542522 | AA22: 7.7502751e-05 | AB22: 0.0026030463 | AC22: 0 | AD22: 0.0064414668 | AE22: -0.026461015 | AF22: 1 | AG22: 1 | AH22: 1 | AI22: 1 | AJ22: 1 | AK22: 1 | AL22: 1 | AM22: 0 | AN22: 0 | AO22: 05:-100--75 | AP22: =-100--75 -> -25 | AQ22: 6218381 | AR22: 28 | AS22: 0 | AT22: 100 | AU22: 100 | AV22: 0 | AW22: 0 | AX22: 0
A23: 4.3 | B23: 0.99531194 | C23: 1.8301087 | D23: 5.4828571 | E23: 0.0015380347 | F23: 0.0046880567 | G23: 0 | H23: 3.8986259 | I23: 4.1473096 | J23: -59.670289 | K23: -56.905879 | L23: 17.18523 | M23: 15.245911 | N23: 77.854851 | O23: 76.716765 | P23: 263061.8 | Q23: 226873.4 | R23: 780.81197 | S23: 0 | T23: 0 | U23: 0.0025098134 | V23: 0 | W23: 0 | X23: 0.46038548 | Y23: 0 | Z23: 0.00047411809 | AA23: 6.1413376e-05 | AB23: 0.0024185358 | AC23: 0 | AD23: 0.0017339791 | AE23: -0.022969111 | AF23: 0.996552 | AG23: 1 | AH23: 1 | AI23: 1 | AJ23: 1 | AK23: 1 | AL23: 1 | AM23: 0 | AN23: 0 | AO23: 06:-75--50 | AP23: =-75--50 -> -25 | AQ23: 1.3952714e+08 | AR23: 615 | AS23: 0 | AT23: 100 | AU23: 100 | AV23: 0 | AW23: 0 | AX23: 0
A24: 4.3 | B24: 0.99386722 | C24: 3.4070807 | D24: 7.116109 | E24: 0.0028845605 | F24: 0.0061327803 | G24: 0 | H24: 3.8995117 | I24: 4.1447021 | J24: -60.114068 | K24: -33.387746 | L24: 15.955751 | M24: 15.468515 | N24: 73.341274 | O24: 71.959297 | P24: 273610.41 | Q24: 248811.56 | R24: 782.10208 | S24: 0 | T24: 0 | U24: 0.0013918239 | V24: 0 | W24: 0 | X24: 0.58737228 | Y24: 0 | Z24: 0.00039633253 | AA24: 5.7272475e-05 | AB24: 0.0025387935 | AC24: 2.1988534e-08 | AD24: 0.0031403457 | AE24: -0.015273165 | AF24: 0.98396189 | AG24: 0.99979739 | AH24: 0.99996869 | AI24: 0.99999042 | AJ24: 1 | AK24: 1 | AL24: 1 | AM24: 0 | AN24: 0 | AO24: 07:-50--25 | AP24: =-50--25 -> -25 | AQ24: 1.6254859e+09 | AR24: 6533 | AS24: 0 | AT24: 100 | AU24: 100 | AV24: 0 | AW24: 0 | AX24: 0
A25: 4.3 | B25: 0.9884728 | C25: 8.6868546 | D25: 12.988493 | E25: 0.0075443498 | F25: 0.011527198 | G25: 0 | H25: 4.097073 | I25: 4.1260145 | J25: -41.673293 | K25: -9.3602837 | L25: 15.303898 | M25: 16.096379 | N25: 72.187814 | O25: 71.033906 | P25: 281961.47 | Q25: 260269.92 | R25: 781.85441 | S25: 0 | T25: 0 | U25: 0.002782606 | V25: 0 | W25: 0 | X25: 0.6832404 | Y25: 0 | Z25: 0.00037474785 | AA25: 6.7008715e-05 | AB25: 0.0026069832 | AC25: 3.167863e-08 | AD25: 0.008478412 | AE25: -0.014262052 | AF25: 0.97210268 | AG25: 0.99863121 | AH25: 0.99987521 | AI25: 1 | AJ25: 1 | AK25: 1 | AL25: 1 | AM25: 0 | AN25: 0 | AO25: 08:-25-0 | AP25: =-25-0 -> -25 | AQ25: 9.6437813e+09 | AR25: 37053 | AS25: 0 | AT25: 100 | AU25: 100 | AV25: 0 | AW25: 0 | AX25: 0
A26: 4.3 | B26: 0.98339762 | C26: 18.623934 | D26: 18.20065 | E26: 0.017027448 | F26: 0.016602377 | G26: 0 | H26: 4.2061544 | I26: 4.0684698 | J26: -31.261201 | K26: 15.159426 | L26: 15.015325 | M26: 16.531355 | N26: 69.194667 | O26: 67.652827 | P26: 286199.29 | Q26: 265730.87 | R26: 782.34245 | S26: 0 | T26: 0 | U26: 0.0089632365 | V26: 0 | W26: 0 | X26: 0.76936148 | Y26: 0 | Z26: 0.00037298469 | AA26: 7.4133431e-05 | AB26: 0.0027640145 | AC26: 4.0375178e-07 | AD26: 0.013390826 | AE26: -0.0086907056 | AF26: 0.92529766 | AG26: 0.99384479 | AH26: 0.99955192 | AI26: 0.99983997 | AJ26: 1 | AK26: 1 | AL26: 1 | AM26: 0 | AN26: 0 | AO26: 09:0-25 | AP26: 0-25 | AQ26: 3.8876693e+10 | AR26: 146301 | AS26: 0 | AT26: 100 | AU26: 100 | AV26: 0 | AW26: 0 | AX26: 0
A27: 4.3 | B27: 0.97636692 | C27: 30.172729 | D27: 24.948964 | E27: 0.029485364 | F27: 0.023633078 | G27: 0 | H27: 4.2307505 | I27: 3.9141908 | J27: -26.990777 | K27: 37.381619 | L27: 14.422594 | M27: 17.06351 | N27: 67.386444 | O27: 64.475774 | P27: 297412.58 | Q27: 276705.53 | R27: 782.18971 | S27: 0 | T27: 0 | U27: 0.017089004 | V27: 0 | W27: 0 | X27: 0.75444376 | Y27: 0 | Z27: 0.00037191187 | AA27: 7.6173822e-05 | AB27: 0.0030566284 | AC27: 3.0381204e-06 | AD27: 0.020125312 | AE27: 0.014020201 | AF27: 0.79792715 | AG27: 0.97128841 | AH27: 0.99714665 | AI27: 0.99948034 | AJ27: 1 | AK27: 1 | AL27: 1 | AM27: 0 | AN27: 0 | AO27: 10:25-50 | AP27: 25-50 | AQ27: 6.1816015e+10 | AR27: 223400 | AS27: 0 | AT27: 100 | AU27: 100 | AV27: 0 | AW27: 0 | AX27: 0
A28: 4.3 | B28: 0.96874993 | C28: 38.013898 | D28: 31.6812 | E28: 0.039071235 | F28: 0.031250067 | G28: 0 | H28: 4.4691529 | I28: 3.8899297 | J28: -17.585481 | K28: 62.663639 | L28: 14.904888 | M28: 17.433619 | N28: 69.566621 | O28: 66.270424 | P28: 287889.79 | Q28: 267833.15 | R28: 780.90567 | S28: 0 | T28: 0 | U28: 0.012379923 | V28: 0 | W28: 0 | X28: 0.65513568 | Y28: 0 | Z28: 0.00037347868 | AA28: 0.00010165557 | AB28: 0.0031882111 | AC28: 6.1303928e-06 | AD28: 0.027580577 | AE28: 0.018520793 | AF28: 0.75933386 | AG28: 0.97296663 | AH28: 0.99568006 | AI28: 0.99918144 | AJ28: 1 | AK28: 1 | AL28: 1 | AM28: 0 | AN28: 0 | AO28: 11:50-75 | AP28: 50-75 | AQ28: 6.0848478e+10 | AR28: 227188 | AS28: 0 | AT28: 100 | AU28: 100 | AV28: 0 | AW28: 0 | AX28: 0
A29: 4.3 | B29: 0.96283573 | C29: 42.416214 | D29: 36.521539 | E29: 0.0449524 | F29: 0.037164268 | G29: 0 | H29: 4.669899 | I29: 3.8733774 | J29: -11.114419 | K29: 86.082824 | L29: 14.804271 | M29: 16.938335 | N29: 69.317804 | O29: 65.421495 | P29: 290106.53 | Q29: 269690.96 | R29: 780.16361 | S29: 0 | T29: 0 | U29: 0.014929732 | V29: 0 | W29: 0 | X29: 0.57816443 | Y29: 0 | Z29: 0.0003715959 | AA29: 0.00012118595 | AB29: 0.0033233774 | AC29: 1.1990445e-05 | AD29: 0.033336103 | AE29: 0.028739178 | AF29: 0.66722427 | AG29: 0.96394033 | AH29: 0.99288434 | AI29: 0.99892184 | AJ29: 1 | AK29: 1 | AL29: 1 | AM29: 0 | AN29: 0 | AO29: 12:75-100 | AP29: 75-100 | AQ29: 4.55179e+10 | AR29: 168778 | AS29: 0 | AT29: 100 | AU29: 100 | AV29: 0 | AW29: 0 | AX29: 0
A30: 4.3 | B30: 0.95762744 | C30: 42.856373 | D30: 40.521638 | E30: 0.045562891 | F30: 0.042372557 | G30: 0 | H30: 4.8031244 | I30: 3.7630665 | J30: -6.4548522 | K30: 111.90903 | L30: 15.277825 | M30: 18.004782 | N30: 72.048793 | O30: 66.634559 | P30: 281058.31 | Q30: 261352.89 | R30: 779.37482 | S30: 0 | T30: 0 | U30: 0.01546372 | V30: 0 | W30: 0 | X30: 0.50506534 | Y30: 0 | Z30: 0.00037175511 | AA30: 0.00016338236 | AB30: 0.0035742012 | AC30: 2.7048051e-05 | AD30: 0.038236155 | AE30: 0.049620894 | AF30: 0.5097601 | AG30: 0.94271147 | AH30: 0.98829344 | AI30: 0.99772965 | AJ30: 1 | AK30: 1 | AL30: 1 | AM30: 0 | AN30: 0 | AO30: 13:100-125 | AP30: 100-125 | AQ30: 2.802095e+10 | AR30: 107215 | AS30: 0 | AT30: 100 | AU30: 100 | AV30: 0 | AW30: 0 | AX30: 0
A31: 4.3 | B31: 0.95271962 | C31: 44.800986 | D31: 44.07818 | E31: 0.048312694 | F31: 0.047280382 | G31: 0 | H31: 4.8804013 | I31: 3.6765996 | J31: -4.9590254 | K31: 134.28061 | L31: 14.635412 | M31: 19.561149 | N31: 71.76419 | O31: 64.964183 | P31: 292491.52 | Q31: 272829.41 | R31: 778.75703 | S31: 0 | T31: 0 | U31: 0.017311252 | V31: 0 | W31: 0 | X31: 0.51891916 | Y31: 0 | Z31: 0.0003723305 | AA31: 0.00019811131 | AB31: 0.0035194468 | AC31: 6.8018786e-05 | AD31: 0.043122459 | AE31: 0.071315724 | AF31: 0.39506961 | AG31: 0.90346476 | AH31: 0.97245124 | AI31: 0.99591568 | AJ31: 1 | AK31: 1 | AL31: 1 | AM31: 0 | AN31: 0 | AO31: 14:125-150 | AP31: 125-150 | AQ31: 1.2692843e+10 | AR31: 46523 | AS31: 0 | AT31: 100 | AU31: 100 | AV31: 0 | AW31: 0 | AX31: 0
A32: 4.3 | B32: 0.9490703 | C32: 41.981394 | D32: 46.595165 | E32: 0.044353499 | F32: 0.050929704 | G32: 0 | H32: 5.0437272 | I32: 3.6813844 | J32: 9.9071253 | K32: 160.87385 | L32: 15.119569 | M32: 19.507703 | N32: 79.542842 | O32: 70.442227 | P32: 283310.92 | Q32: 264098.56 | R32: 776.92982 | S32: 0 | T32: 0 | U32: 0.016870534 | V32: 0 | W32: 0 | X32: 0.47603545 | Y32: 0 | Z32: 0.00037700592 | AA32: 0.00027635962 | AB32: 0.003803571 | AC32: 0.00014882352 | AD32: 0.046323928 | AE32: 0.092884957 | AF32: 0.28597376 | AG32: 0.80432464 | AH32: 0.93778902 | AI32: 0.99023488 | AJ32: 1 | AK32: 1 | AL32: 1 | AM32: 0 | AN32: 0 | AO32: 15:150-175 | AP32: 150-175 | AQ32: 2.58843e+09 | AR32: 9801 | AS32: 0 | AT32: 100 | AU32: 100 | AV32: 0 | AW32: 0 | AX32: 0
A33: 4.3 | B33: 0.94285433 | C33: 48.655806 | D33: 50.644539 | E33: 0.054036721 | F33: 0.057145668 | G33: 0 | H33: 5.0710696 | I33: 3.6599799 | J33: 12.2848 | K33: 183.22998 | L33: 14.003319 | M33: 19.98188 | N33: 83.336593 | O33: 71.286178 | P33: 302371.03 | Q33: 285150.39 | R33: 776.21487 | S33: 0 | T33: 0 | U33: 0.017358684 | V33: 0 | W33: 0 | X33: 0.46148792 | Y33: 0 | Z33: 0.00037680602 | AA33: 0.00032732859 | AB33: 0.0039005728 | AC33: 0.00043364357 | AD33: 0.0521073 | AE33: 0.12971425 | AF33: 0.16588024 | AG33: 0.61762235 | AH33: 0.80205726 | AI33: 0.96116652 | AJ33: 1 | AK33: 1 | AL33: 1 | AM33: 0 | AN33: 0 | AO33: 16:175-200 | AP33: 175-200 | AQ33: 6.8692728e+08 | AR33: 2409 | AS33: 0 | AT33: 100 | AU33: 100 | AV33: 0 | AW33: 0 | AX33: 0
A34: 4.3 | B34: 0.9407399 | C34: 38.318358 | D34: 51.956483 | E34: 0.039465443 | F34: 0.059260097 | G34: 0 | H34: 5.1605718 | I34: 3.6692646 | J34: 17.585612 | K34: 209.41141 | L34: 14.520526 | M34: 20.232747 | N34: 90.534831 | O34: 75.341532 | P34: 296660.31 | Q34: 274999.14 | R34: 775.31983 | S34: 0 | T34: 0 | U34: 0.015751738 | V34: 0 | W34: 0 | X34: 0.29437842 | Y34: 0 | Z34: 0.00037945678 | AA34: 0.00042470513 | AB34: 0.0042613109 | AC34: 0.00072566888 | AD34: 0.053468938 | AE34: 0.16225249 | AF34: 0.036592112 | AG34: 0.4165709 | AH34: 0.69329744 | AI34: 0.92631746 | AJ34: 1 | AK34: 1 | AL34: 1 | AM34: 0 | AN34: 0 | AO34: 17:200-225 | AP34: 200-225 | AQ34: 1.2347462e+08 | AR34: 449 | AS34: 0 | AT34: 100 | AU34: 100 | AV34: 0 | AW34: 0 | AX34: 0
A35: 4.3 | B35: 0.93891144 | C35: 22.828421 | D35: 53.065137 | E35: 0.021363411 | F35: 0.061088562 | G35: 0 | H35: 5.2641041 | I35: 3.6465013 | J35: 27.398546 | K35: 231.7946 | L35: 13.76739 | M35: 20.801174 | N35: 92.494129 | O35: 74.555659 | P35: 310947.98 | Q35: 290043.59 | R35: 776.17564 | S35: 0 | T35: 0 | U35: 0 | V35: 0 | W35: 0 | X35: 0.15312933 | Y35: 0 | Z35: 0.00038271758 | AA35: 0.00052407484 | AB35: 0.0044067446 | AC35: 0.0013321278 | AD35: 0.054442879 | AE35: 0.19808292 | AF35: 0 | AG35: 0.17645629 | AH35: 0.38832439 | AI35: 0.9097973 | AJ35: 1 | AK35: 1 | AL35: 1 | AM35: 0 | AN35: 0 | AO35: 18:225-250 | AP35: 225-250 | AQ35: 22913444 | AR35: 79 | AS35: 0 | AT35: 100 | AU35: 100 | AV35: 0 | AW35: 0 | AX35: 0
A38: WALA [12,24) | C38: CashWindow
A39: modelId | B39: SFACTOR_PREPAY_TRACKING_CPR | C39: PREPAY_CPR1 | D39: PREPAY_TRACKING_CPR1 | E39: PREPAY_SMM1 | F39: PREPAY_TRACKING_SMM1 | G39: PCT_LOANTYPE | H39: _ORIGNOTERATE | I39: _ZEROSATO | J39: _SATO | K39: _REFI_INCENTIVE_Fixed | L39: _Fixed_cost | M39: _LOANAGE | N39: _LTV | O39: _CLTV | P39: _AVG_LOANSIZE_SCHAMBALANCE | Q39: _WACLS | R39: _FICO | S39: PCT_ISSECONDLIEN | T39: _OrigCombLTV | U39: PCT_SVC | V39: PCT_TPO | W39: PCT_GEO | X39: PCT_LOANPURPOSE | Y39: PCT_OCC | Z39: curtailsmm | AA39: defaultsmm | AB39: toverSmm | AC39: cashoutSmm | AD39: refiSmm | AE39: cumHPA | AF39: cumHPA05Pct | AG39: cumHPA15Pct | AH39: cumHPA20Pct | AI39: cumHPA25Pct | AJ39: cumHPA30Pct | AK39: cumHPA35Pct | AL39: cumHPA40Pct | AM39: adjtoverSmm | AN39: adjRefiSmm | AO39: groupByColumn | AP39: curve | AQ39: Balance | AR39: LoanCount | AS39: PCT_BROKER | AT39: PCT_CORRES | AU39: PCT_NonRETAIL | AV39: PCT_RETAIL | AW39: PCT_CashWindow | AX39: PCT_NonCashWindow
A40: 4.3 | B40: 0.99661762 | C40: 0 | D40: 3.9841936 | E40: 0 | F40: 0.00338238 | G40: 0 | H40: 3.875 | I40: 4.118472 | J40: -64.0619 | K40: -131.95 | L40: 13.16 | M40: 17 | N40: 80 | O40: 77.08 | P40: 303250.44 | Q40: 303250.44 | R40: 773 | S40: 0 | T40: 0 | U40: 0 | V40: 1 | W40: 0 | X40: 1 | Y40: 0 | Z40: 0.00035183 | AA40: 7.792e-05 | AB40: 0.00295262 | AC40: 0 | AD40: 0 | AE40: 0.011207683 | AF40: 1 | AG40: 1 | AH40: 1 | AI40: 1 | AJ40: 1 | AK40: 1 | AL40: 1 | AM40: 0 | AN40: 0 | AO40: 03:-150--125 | AP40: =-150--125 -> -25 | AQ40: 303250.44 | AR40: 1 | AS40: 0 | AT40: 0 | AU40: 0 | AV40: 100 | AW40: 100 | AX40: 0
A41: 4.3 | B41: 0.99173453 | C41: 0 | D41: 9.4798618 | E41: 0 | F41: 0.0082654715 | G41: 0 | H41: 3.875 | I41: 3.8717773 | J41: -56.468943 | K41: -111.35086 | L41: 14.328815 | M41: 17.880294 | N41: 80 | O41: 75.620345 | P41: 284673.47 | Q41: 278674.78 | R41: 771.88117 | S41: 0 | T41: 0 | U41: 0 | V41: 1 | W41: 0 | X41: 1 | Y41: 0 | Z41: 0.00035334788 | AA41: 5.3605208e-05 | AB41: 0.0031742462 | AC41: 0 | AD41: 0.0046842576 | AE41: 0.029306717 | AF41: 1 | AG41: 1 | AH41: 1 | AI41: 1 | AJ41: 1 | AK41: 1 | AL41: 1 | AM41: 0 | AN41: 0 | AO41: 04:-125--100 | AP41: =-125--100 -> -25 | AQ41: 1114699.1 | AR41: 4 | AS41: 0 | AT41: 0 | AU41: 0 | AV41: 100 | AW41: 100 | AX41: 0
A42: 4.3 | B42: 0.98992819 | C42: 12.107777 | D42: 11.438635 | E42: 0.010697278 | F42: 0.01007181 | G42: 0 | H42: 4.2120764 | I42: 3.9473309 | J42: -23.140697 | K42: -83.452033 | L42: 19.208546 | M42: 17.333171 | N42: 79.615477 | O42: 76.037526 | P42: 239079.34 | Q42: 193572.8 | R42: 765.54682 | S42: 0 | T42: 0 | U42: 0 | V42: 1 | W42: 0 | X42: 0.97979815 | Y42: 0 | Z42: 0.00056887345 | AA42: 8.1948978e-05 | AB42: 0.0030977716 | AC42: 0 | AD42: 0.0063232008 | AE42: -0.0002056697 | AF42: 1 | AG42: 1 | AH42: 1 | AI42: 1 | AJ42: 1 | AK42: 1 | AL42: 1 | AM42: 0 | AN42: 0 | AO42: 05:-100--75 | AP42: =-100--75 -> -25 | AQ42: 2322873.6 | AR42: 12 | AS42: 0 | AT42: 0 | AU42: 0 | AV42: 100 | AW42: 100 | AX42: 0
A43: 4.3 | B43: 0.98934761 | C43: 27.432198 | D43: 12.059911 | E43: 0.026366898 | F43: 0.010652392 | G43: 0 | H43: 4.2156057 | I43: 4.0468354 | J43: -26.571952 | K43: -57.932898 | L43: 22.942908 | M43: 16.539877 | N43: 78.81004 | O43: 71.950413 | P43: 243355.1 | Q43: 154364.35 | R43: 774.26727 | S43: 0 | T43: 0 | U43: 0.08578669 | V43: 1 | W43: 0 | X43: 0.62733873 | Y43: 0 | Z43: 0.0010454839 | AA43: 8.0260524e-05 | AB43: 0.002838117 | AC43: 0 | AD43: 0.0066885165 | AE43: -0.01057977 | AF43: 0.95511436 | AG43: 0.99661868 | AH43: 1 | AI43: 1 | AJ43: 1 | AK43: 1 | AL43: 1 | AM43: 0 | AN43: 0 | AO43: 06:-75--50 | AP43: =-75--50 -> -25 | AQ43: 13275334 | AR43: 86 | AS43: 0 | AT43: 0 | AU43: 0 | AV43: 100 | AW43: 100 | AX43: 0
A44: 4.3 | B44: 0.99372916 | C44: 2.6972 | D44: 7.2708179 | E44: 0.0022759411 | F44: 0.0062708358 | G44: 0 | H44: 4.0130121 | I44: 4.124413 | J44: -49.480846 | K44: -32.313402 | L44: 17.404312 | M44: 15.583407 | N44: 77.145531 | O44: 74.947546 | P44: 263811.83 | Q44: 223674.18 | R44: 781.04806 | S44: 0 | T44: 0 | U44: 0.0047215107 | V44: 1 | W44: 0 | X44: 0.5513044 | Y44: 0 | Z44: 0.00047030754 | AA44: 5.2422737e-05 | AB44: 0.0026297805 | AC44: 3.0524064e-07 | AD44: 0.0031180062 | AE44: -0.014876592 | AF44: 0.97128747 | AG44: 0.99033606 | AH44: 0.99969298 | AI44: 0.99969298 | AJ44: 1 | AK44: 1 | AL44: 1 | AM44: 0 | AN44: 0 | AO44: 07:-50--25 | AP44: =-50--25 -> -25 | AQ44: 1.9616225e+08 | AR44: 877 | AS44: 0 | AT44: 0 | AU44: 0 | AV44: 100 | AW44: 100 | AX44: 0
A45: 4.3 | B45: 0.99009166 | C45: 10.272771 | D45: 11.262988 | E45: 0.0089923175 | F45: 0.0099083449 | G45: 0 | H45: 4.1238862 | I45: 4.1160383 | J45: -38.460418 | K45: -8.5277656 | L45: 16.482102 | M45: 15.981391 | N45: 74.178548 | O45: 72.813875 | P45: 262234.84 | Q45: 241347.2 | R45: 781.322 | S45: 0 | T45: 0 | U45: 0.019790794 | V45: 1 | W45: 0 | X45: 0.71355362 | Y45: 0 | Z45: 0.00038681295 | AA45: 5.6034209e-05 | AB45: 0.0026655013 | AC45: 1.5856603e-07 | AD45: 0.0067998237 | AE45: -0.013449962 | AF45: 0.9617047 | AG45: 0.99077334 | AH45: 0.999711 | AI45: 0.99996719 | AJ45: 1 | AK45: 1 | AL45: 1 | AM45: 0 | AN45: 0 | AO45: 08:-25-0 | AP45: =-25-0 -> -25 | AQ45: 2.0574849e+09 | AR45: 8525 | AS45: 0 | AT45: 0 | AU45: 0 | AV45: 100 | AW45: 100 | AX45: 0
A46: 4.3 | B46: 0.98630216 | C46: 18.568596 | D46: 15.253884 | E46: 0.016971762 | F46: 0.013697841 | G46: 0 | H46: 4.197132 | I46: 4.0368714 | J46: -27.530438 | K46: 15.60855 | L46: 16.293509 | M46: 16.097029 | N46: 70.91269 | O46: 68.870179 | P46: 263734.72 | Q46: 244852.35 | R46: 782.53188 | S46: 0 | T46: 0 | U46: 0.045171012 | V46: 1 | W46: 0 | X46: 0.80546192 | Y46: 0 | Z46: 0.00037783382 | AA46: 6.0192294e-05 | AB46: 0.0028370435 | AC46: 1.495745e-06 | AD46: 0.010421262 | AE46: -0.00041697403 | AF46: 0.88752184 | AG46: 0.97232014 | AH46: 0.99769674 | AI46: 0.99965008 | AJ46: 1 | AK46: 1 | AL46: 1 | AM46: 0 | AN46: 0 | AO46: 09:0-25 | AP46: 0-25 | AQ46: 1.1257087e+10 | AR46: 45975 | AS46: 0 | AT46: 0 | AU46: 0 | AV46: 100 | AW46: 100 | AX46: 0
A47: 4.3 | B47: 0.98060834 | C47: 30.159799 | D47: 20.941787 | E47: 0.02947039 | F47: 0.01939166 | G47: 0 | H47: 4.2299296 | I47: 3.9089805 | J47: -21.580224 | K47: 38.014005 | L47: 15.480645 | M47: 16.321129 | N47: 68.001822 | O47: 64.841484 | P47: 277166.09 | Q47: 257802.07 | R47: 783.21829 | S47: 0 | T47: 0 | U47: 0.045054977 | V47: 1 | W47: 0 | X47: 0.82871998 | Y47: 0 | Z47: 0.00037299548 | AA47: 6.2396994e-05 | AB47: 0.0030315717 | AC47: 5.0815919e-06 | AD47: 0.0159196 | AE47: 0.019986443 | AF47: 0.77431859 | AG47: 0.93880174 | AH47: 0.99518497 | AI47: 0.9992447 | AJ47: 1 | AK47: 1 | AL47: 1 | AM47: 0 | AN47: 0 | AO47: 10:25-50 | AP47: 25-50 | AQ47: 2.6377019e+10 | AR47: 102315 | AS47: 0 | AT47: 0 | AU47: 0 | AV47: 100 | AW47: 100 | AX47: 0
A48: 4.3 | B48: 0.97389312 | C48: 40.149087 | D48: 27.199293 | E48: 0.041874133 | F48: 0.026106875 | G48: 0 | H48: 4.4272407 | I48: 3.8675649 | J48: -11.88364 | K48: 61.818588 | L48: 15.319514 | M48: 17.356706 | N48: 67.606811 | O48: 64.383644 | P48: 280265.73 | Q48: 260583.52 | R48: 782.62838 | S48: 0 | T48: 0 | U48: 0.029567307 | V48: 1 | W48: 0 | X48: 0.78719709 | Y48: 0 | Z48: 0.00037399172 | AA48: 7.9844471e-05 | AB48: 0.0031769512 | AC48: 6.4092633e-06 | AD48: 0.022469664 | AE48: 0.0195067 | AF48: 0.77029743 | AG48: 0.9596833 | AH48: 0.99534206 | AI48: 0.9993421 | AJ48: 1 | AK48: 1 | AL48: 1 | AM48: 0 | AN48: 0 | AO48: 11:50-75 | AP48: 50-75 | AQ48: 2.2196504e+10 | AR48: 85180 | AS48: 0 | AT48: 0 | AU48: 0 | AV48: 100 | AW48: 100 | AX48: 0
A49: 4.3 | B49: 0.96868969 | C49: 42.720599 | D49: 31.732163 | E49: 0.045374116 | F49: 0.031310308 | G49: 0 | H49: 4.6748624 | I49: 3.876234 | J49: -4.757858 | K49: 86.11073 | L49: 15.269437 | M49: 17.80654 | N49: 67.682094 | O49: 64.283091 | P49: 281346.03 | Q49: 261471.15 | R49: 781.28007 | S49: 0 | T49: 0 | U49: 0.037970816 | V49: 1 | W49: 0 | X49: 0.70634876 | Y49: 0 | Z49: 0.00037464345 | AA49: 0.000101898 | AB49: 0.003284246 | AC49: 1.0011225e-05 | AD49: 0.027539494 | AE49: 0.020944397 | AF49: 0.7255838 | AG49: 0.96035673 | AH49: 0.9942031 | AI49: 0.99909325 | AJ49: 1 | AK49: 1 | AL49: 1 | AM49: 0 | AN49: 0 | AO49: 12:75-100 | AP49: 75-100 | AQ49: 1.3715731e+10 | AR49: 52456 | AS49: 0 | AT49: 0 | AU49: 0 | AV49: 100 | AW49: 100 | AX49: 0
A50: 4.3 | B50: 0.96474775 | C50: 43.681735 | D50: 34.992225 | E50: 0.046719362 | F50: 0.035252248 | G50: 0 | H50: 4.8434827 | I50: 3.807434 | J50: -1.3594117 | K50: 111.23674 | L50: 15.526546 | M50: 18.29082 | N50: 69.560573 | O50: 65.196329 | P50: 276553.64 | Q50: 257166.42 | R50: 780.71302 | S50: 0 | T50: 0 | U50: 0.039785194 | V50: 1 | W50: 0 | X50: 0.62199301 | Y50: 0 | Z50: 0.00037584798 | AA50: 0.0001336259 | AB50: 0.0034024579 | AC50: 1.6828302e-05 | AD50: 0.031323473 | AE50: 0.033325074 | AF50: 0.6266057 | AG50: 0.95634481 | AH50: 0.99256606 | AI50: 0.99872658 | AJ50: 1 | AK50: 1 | AL50: 1 | AM50: 0 | AN50: 0 | AO50: 13:100-125 | AP50: 100-125 | AQ50: 7.047903e+09 | AR50: 27406 | AS50: 0 | AT50: 0 | AU50: 0 | AV50: 100 | AW50: 100 | AX50: 0
A51: 4.3 | B51: 0.96091175 | C51: 42.096706 | D51: 38.027071 | E51: 0.044511922 | F51: 0.039088254 | G51: 0 | H51: 4.9315036 | I51: 3.6961975 | J51: 1.0148037 | K51: 134.98966 | L51: 15.352613 | M51: 19.417138 | N51: 70.84739 | O51: 64.873088 | P51: 279295.95 | Q51: 260089.7 | R51: 779.89281 | S51: 0 | T51: 0 | U51: 0.058809219 | V51: 1 | W51: 0 | X51: 0.64064484 | Y51: 0 | Z51: 0.00037431524 | AA51: 0.00014527289 | AB51: 0.0034345077 | AC51: 3.4003484e-05 | AD51: 0.03510014 | AE51: 0.058873943 | AF51: 0.4937243 | AG51: 0.92881813 | AH51: 0.98536312 | AI51: 0.99845284 | AJ51: 1 | AK51: 1 | AL51: 1 | AM51: 0 | AN51: 0 | AO51: 14:125-150 | AP51: 125-150 | AQ51: 2.983749e+09 | AR51: 11472 | AS51: 0 | AT51: 0 | AU51: 0 | AV51: 100 | AW51: 100 | AX51: 0
A52: 4.3 | B52: 0.95713534 | C52: 43.974174 | D52: 40.887378 | E52: 0.047132849 | F52: 0.04286466 | G52: 0 | H52: 5.0881617 | I52: 3.667939 | J52: 12.727544 | K52: 159.19145 | L52: 15.009271 | M52: 20.173603 | N52: 73.885734 | O52: 66.483514 | P52: 285506.84 | Q52: 266044.99 | R52: 778.89373 | S52: 0 | T52: 0 | U52: 0.018776664 | V52: 1 | W52: 0 | X52: 0.66670176 | Y52: 0 | Z52: 0.00037301546 | AA52: 0.00021407522 | AB52: 0.0034923012 | AC52: 6.0698153e-05 | AD52: 0.038724555 | AE52: 0.07629897 | AF52: 0.39665848 | AG52: 0.89240437 | AH52: 0.97360936 | AI52: 0.99656065 | AJ52: 1 | AK52: 1 | AL52: 1 | AM52: 0 | AN52: 0 | AO52: 15:150-175 | AP52: 150-175 | AQ52: 6.6245203e+08 | AR52: 2490 | AS52: 0 | AT52: 0 | AU52: 0 | AV52: 100 | AW52: 100 | AX52: 0
A53: 4.3 | B53: 0.95312325 | C53: 55.301 | D53: 43.793211 | E53: 0.064899799 | F53: 0.046876748 | G53: 0 | H53: 5.1828649 | I53: 3.6615472 | J53: 26.721662 | K53: 183.23274 | L53: 14.425865 | M53: 20.14771 | N53: 78.208501 | O53: 68.105276 | P53: 296805.85 | Q53: 276792.32 | R53: 779.56453 | S53: 0 | T53: 0 | U53: 0 | V53: 1 | W53: 0 | X53: 0.65481309 | Y53: 0 | Z53: 0.00039321549 | AA53: 0.00029980357 | AB53: 0.0036021195 | AC53: 0.00017322807 | AD53: 0.042408366 | AE53: 0.10048405 | AF53: 0.26675475 | AG53: 0.7917514 | AH53: 0.92892011 | AI53: 0.98513131 | AJ53: 1 | AK53: 1 | AL53: 1 | AM53: 0 | AN53: 0 | AO53: 16:175-200 | AP53: 175-200 | AQ53: 1.2012787e+08 | AR53: 434 | AS53: 0 | AT53: 0 | AU53: 0 | AV53: 100 | AW53: 100 | AX53: 0
A54: 4.3 | B54: 0.95413155 | C54: 53.736279 | D54: 43.075521 | E54: 0.062214788 | F54: 0.045868453 | G54: 0 | H54: 5.2404386 | I54: 3.6507389 | J54: 30.826975 | K54: 207.93763 | L54: 15.518872 | M54: 20.380193 | N54: 83.310511 | O54: 69.451672 | P54: 273149.38 | Q54: 257277.22 | R54: 776.7971 | S54: 0 | T54: 0 | U54: 0 | V54: 1 | W54: 0 | X54: 0.51070676 | Y54: 0 | Z54: 0.00043522976 | AA54: 0.00032085648 | AB54: 0.0039489034 | AC54: 0.00038778712 | AD54: 0.040775661 | AE54: 0.12908079 | AF54: 0.12918379 | AG54: 0.65268542 | AH54: 0.83717966 | AI54: 0.96337046 | AJ54: 1 | AK54: 1 | AL54: 1 | AM54: 0 | AN54: 0 | AO54: 17:200-225 | AP54: 200-225 | AQ54: 15951188 | AR54: 62 | AS54: 0 | AT54: 0 | AU54: 0 | AV54: 100 | AW54: 100 | AX54: 0
A55: 4.3 | B55: 0.95616787 | C55: 0 | D55: 41.600419 | E55: 0 | F55: 0.043832134 | G55: 0 | H55: 5.25 | I55: 3.6406663 | J55: 17.662921 | K55: 233.95346 | L55: 18.196645 | M55: 20.999142 | N55: 95 | O55: 75.144084 | P55: 219482.43 | Q55: 219482.19 | R55: 794 | S55: 0 | T55: 0 | U55: 0 | V55: 1 | W55: 0 | X55: 0 | Y55: 0 | Z55: 0.00035712854 | AA55: 0.00011713423 | AB55: 0.0048422815 | AC55: 0.0018443456 | AD55: 0.036671225 | AE55: 0.2325131 | AF55: 0 | AG55: 0 | AH55: 0 | AI55: 1 | AJ55: 1 | AK55: 1 | AL55: 1 | AM55: 0 | AN55: 0 | AO55: 18:225-250 | AP55: 225-250 | AQ55: 658446.57 | AR55: 3 | AS55: 0 | AT55: 0 | AU55: 0 | AV55: 100 | AW55: 100 | AX55: 0
A59: WALA [12,24) | C59: NonCashWindow
A60: modelId | B60: SFACTOR_PREPAY_TRACKING_CPR | C60: PREPAY_CPR1 | D60: PREPAY_TRACKING_CPR1 | E60: PREPAY_SMM1 | F60: PREPAY_TRACKING_SMM1 | G60: PCT_LOANTYPE | H60: _ORIGNOTERATE | I60: _ZEROSATO | J60: _SATO | K60: _REFI_INCENTIVE_Fixed | L60: _Fixed_cost | M60: _LOANAGE | N60: _LTV | O60: _CLTV | P60: _AVG_LOANSIZE_SCHAMBALANCE | Q60: _WACLS | R60: _FICO | S60: PCT_ISSECONDLIEN | T60: _OrigCombLTV | U60: PCT_SVC | V60: PCT_TPO | W60: PCT_GEO | X60: PCT_LOANPURPOSE | Y60: PCT_OCC | Z60: curtailsmm | AA60: defaultsmm | AB60: toverSmm | AC60: cashoutSmm | AD60: refiSmm | AE60: cumHPA | AF60: cumHPA05Pct | AG60: cumHPA15Pct | AH60: cumHPA20Pct | AI60: cumHPA25Pct | AJ60: cumHPA30Pct | AK60: cumHPA35Pct | AL60: cumHPA40Pct | AM60: adjtoverSmm | AN60: adjRefiSmm | AO60: groupByColumn | AP60: curve | AQ60: Balance | AR60: LoanCount | AS60: PCT_BROKER | AT60: PCT_CORRES | AU60: PCT_NonRETAIL | AV60: PCT_RETAIL | AW60: PCT_CashWindow | AX60: PCT_NonCashWindow
A61: 4.3 | B61: 0.99502774 | C61: 0 | D61: 5.8062099 | E61: 0 | F61: 0.004972258 | G61: 0 | H61: 4.125 | I61: 4.0914466 | J61: -39.2924 | K61: -107.58291 | L61: 22.464931 | M61: 18.498075 | N61: 80 | O61: 77.967109 | P61: 177738.07 | Q61: 177737.55 | R61: 782 | S61: 0 | T61: 0 | U61: 0 | V61: 1 | W61: 0 | X61: 0 | Y61: 0 | Z61: 0.00035354267 | AA61: 1.3394992e-05 | AB61: 0.0038048394 | AC61: 0 | AD61: 0.00080046846 | AE61: -0.0012605143 | AF61: 1 | AG61: 1 | AH61: 1 | AI61: 1 | AJ61: 1 | AK61: 1 | AL61: 1 | AM61: 0 | AN61: 0 | AO61: 04:-125--100 | AP61: =-125--100 -> -25 | AQ61: 710950.18 | AR61: 4 | AS61: 0 | AT61: 0 | AU61: 0 | AV61: 100 | AW61: 0 | AX61: 100
A62: 4.3 | B62: 0.99155722 | C62: 2.1576304 | D62: 9.6738777 | E62: 0.0018160553 | F62: 0.0084427815 | G62: 0 | H62: 4.1889411 | I62: 4.0657978 | J62: -27.8585 | K62: -83.219819 | L62: 18.879883 | M62: 17.169202 | N62: 76.77312 | O62: 76.563737 | P62: 225230.39 | Q62: 199055.97 | R62: 782.10614 | S62: 0 | T62: 0 | U62: 0 | V62: 1 | W62: 0 | X62: 0.13217823 | Y62: 0 | Z62: 0.00037752422 | AA62: 4.2870696e-05 | AB62: 0.0031142536 | AC62: 0 | AD62: 0.0049081176 | AE62: -0.024099846 | AF62: 1 | AG62: 1 | AH62: 1 | AI62: 1 | AJ62: 1 | AK62: 1 | AL62: 1 | AM62: 0 | AN62: 0 | AO62: 05:-100--75 | AP62: =-100--75 -> -25 | AQ62: 2985839.6 | AR62: 15 | AS62: 0 | AT62: 0 | AU62: 0 | AV62: 100 | AW62: 0 | AX62: 100
A63: 4.3 | B63: 0.99550634 | C63: 8.8452661 | D63: 5.2610892 | E63: 0.0076879413 | F63: 0.0044936552 | G63: 0 | H63: 3.8754078 | I63: 4.1426231 | J63: -62.065276 | K63: -58.362228 | L63: 20.533306 | M63: 15.317372 | N63: 78.746357 | O63: 74.733621 | P63: 253658.83 | Q63: 183215.2 | R63: 781.71532 | S63: 0 | T63: 0 | U63: 0 | V63: 1 | W63: 0 | X63: 0.15768331 | Y63: 0 | Z63: 0.00071264658 | AA63: 7.5896281e-05 | AB63: 0.0026374621 | AC63: 0 | AD63: 0.0010676405 | AE63: -0.021212522 | AF63: 0.99566702 | AG63: 1 | AH63: 1 | AI63: 1 | AJ63: 1 | AK63: 1 | AL63: 1 | AM63: 0 | AN63: 0 | AO63: 06:-75--50 | AP63: =-75--50 -> -25 | AQ63: 54598129 | AR63: 298 | AS63: 0 | AT63: 0 | AU63: 0 | AV63: 100 | AW63: 0 | AX63: 100
A64: 4.3 | B64: 0.99412404 | C64: 6.1091154 | D64: 6.8276779 | E64: 0.0052393001 | F64: 0.0058759588 | G64: 0 | H64: 3.9337332 | I64: 4.1358934 | J64: -57.987062 | K64: -33.504741 | L64: 16.96728 | M64: 15.448122 | N64: 74.279276 | O64: 72.186536 | P64: 264061.52 | Q64: 230524.08 | R64: 783.86911 | S64: 0 | T64: 0 | U64: 0.0022841412 | V64: 1 | W64: 0 | X64: 0.30870795 | Y64: 0 | Z64: 0.0004416903 | AA64: 6.3523872e-05 | AB64: 0.0027300309 | AC64: 7.7476567e-09 | AD64: 0.0026406919 | AE64: -0.012060826 | AF64: 0.97597851 | AG64: 0.99876642 | AH64: 1 | AI64: 1 | AJ64: 1 | AK64: 1 | AL64: 1 | AM64: 0 | AN64: 0 | AO64: 07:-50--25 | AP64: =-50--25 -> -25 | AQ64: 5.8691431e+08 | AR64: 2546 | AS64: 0 | AT64: 0 | AU64: 0 | AV64: 100 | AW64: 0 | AX64: 100
A65: 4.3 | B65: 0.98985186 | C65: 7.5476108 | D65: 11.520542 | E65: 0.0065183615 | F65: 0.010148138 | G65: 0 | H65: 4.1214877 | I65: 4.1334079 | J65: -40.061891 | K65: -8.3611912 | L65: 15.571414 | M65: 15.625428 | N65: 72.112709 | O65: 70.727766 | P65: 278786.73 | Q65: 255296.92 | R65: 783.58961 | S65: 0 | T65: 0 | U65: 0.002846396 | V65: 1 | W65: 0 | X65: 0.58850586 | Y65: 0 | Z65: 0.00038877256 | AA65: 6.7447233e-05 | AB65: 0.0026347468 | AC65: 1.1532695e-08 | AD65: 0.0070571457 | AE65: -0.015546707 | AF65: 0.97687925 | AG65: 0.99866327 | AH65: 0.99989613 | AI65: 1 | AJ65: 1 | AK65: 1 | AL65: 1 | AM65: 0 | AN65: 0 | AO65: 08:-25-0 | AP65: =-25-0 -> -25 | AQ65: 4.5335627e+09 | AR65: 17758 | AS65: 0 | AT65: 0 | AU65: 0 | AV65: 100 | AW65: 0 | AX65: 100
A66: 4.3 | B66: 0.98591472 | C66: 11.797693 | D66: 15.652506 | E66: 0.010406892 | F66: 0.014085285 | G66: 0 | H66: 4.2420115 | I66: 4.0979455 | J66: -27.984199 | K66: 15.32746 | L66: 15.34839 | M66: 16.027786 | N66: 67.860579 | O66: 66.32759 | P66: 279876.34 | Q66: 259921.55 | R66: 784.8208 | S66: 0 | T66: 0 | U66: 0.0093631669 | V66: 1 | W66: 0 | X66: 0.76846682 | Y66: 0 | Z66: 0.00037706139 | AA66: 7.1435677e-05 | AB66: 0.0027606002 | AC66: 4.1713309e-07 | AD66: 0.010875756 | AE66: -0.010170756 | AF66: 0.94085711 | AG66: 0.99349299 | AH66: 0.99919156 | AI66: 0.99978821 | AJ66: 1 | AK66: 1 | AL66: 1 | AM66: 0 | AN66: 0 | AO66: 09:0-25 | AP66: 0-25 | AQ66: 2.3068557e+10 | AR66: 88752 | AS66: 0 | AT66: 0 | AU66: 0 | AV66: 100 | AW66: 0 | AX66: 100
A67: 4.3 | B67: 0.98030231 | C67: 17.55991 | D67: 21.237349 | E67: 0.015962752 | F67: 0.019697688 | G67: 0 | H67: 4.3594907 | I67: 4.0141205 | J67: -17.69393 | K67: 38.111594 | L67: 15.143014 | M67: 17.022507 | N67: 65.665989 | O67: 63.523641 | P67: 283223.76 | Q67: 263596.7 | R67: 785.18895 | S67: 0 | T67: 0 | U67: 0.011352927 | V67: 1 | W67: 0 | X67: 0.83557602 | Y67: 0 | Z67: 0.00037495601 | AA67: 8.5276546e-05 | AB67: 0.0030262632 | AC67: 1.9782436e-06 | AD67: 0.016209199 | AE67: 0.00047233564 | AF67: 0.87196598 | AG67: 0.98161997 | AH67: 0.99805301 | AI67: 0.99951235 | AJ67: 1 | AK67: 1 | AL67: 1 | AM67: 0 | AN67: 0 | AO67: 10:25-50 | AP67: 25-50 | AQ67: 4.6900707e+10 | AR67: 177926 | AS67: 0 | AT67: 0 | AU67: 0 | AV67: 100 | AW67: 0 | AX67: 100
A68: 4.3 | B68: 0.97383997 | C68: 25.676066 | D68: 27.246962 | E68: 0.024424861 | F68: 0.026160032 | G68: 0 | H68: 4.5363795 | I68: 3.9428542 | J68: -8.837139 | K68: 62.97282 | L68: 15.52194 | M68: 17.988233 | N68: 66.904798 | O68: 64.127384 | P68: 276197.65 | Q68: 257200.95 | R68: 784.49164 | S68: 0 | T68: 0 | U68: 0.0091287563 | V68: 1 | W68: 0 | X68: 0.81147446 | Y68: 0 | Z68: 0.00037766527 | AA68: 0.00011707935 | AB68: 0.0032507888 | AC68: 4.6677129e-06 | AD68: 0.022409817 | AE68: 0.0092320769 | AF68: 0.80256162 | AG68: 0.97617681 | AH68: 0.99685625 | AI68: 0.99925923 | AJ68: 1 | AK68: 1 | AL68: 1 | AM68: 0 | AN68: 0 | AO68: 11:50-75 | AP68: 50-75 | AQ68: 5.9067741e+10 | AR68: 229656 | AS68: 0 | AT68: 0 | AU68: 0 | AV68: 100 | AW68: 0 | AX68: 100
A69: 4.3 | B69: 0.96838283 | C69: 31.506465 | D69: 31.991219 | E69: 0.031043832 | F69: 0.031617165 | G69: 0 | H69: 4.7068362 | I69: 3.8993735 | J69: -1.7327127 | K69: 86.340718 | L69: 15.316941 | M69: 17.929493 | N69: 66.053577 | O69: 62.805532 | P69: 279970.53 | Q69: 260672.83 | R69: 783.73187 | S69: 0 | T69: 0 | U69: 0.010820637 | V69: 1 | W69: 0 | X69: 0.80359528 | Y69: 0 | Z69: 0.00037747068 | AA69: 0.00014268261 | AB69: 0.0033466866 | AC69: 1.0009337e-05 | AD69: 0.027740301 | AE69: 0.018643281 | AF69: 0.71583084 | AG69: 0.9655081 | AH69: 0.99427538 | AI69: 0.99900877 | AJ69: 1 | AK69: 1 | AL69: 1 | AM69: 0 | AN69: 0 | AO69: 12:75-100 | AP69: 75-100 | AQ69: 5.2624892e+10 | AR69: 201881 | AS69: 0 | AT69: 0 | AU69: 0 | AV69: 100 | AW69: 0 | AX69: 100
A70: 4.3 | B70: 0.96402649 | C70: 35.202875 | D70: 35.573041 | E70: 0.035513149 | F70: 0.035973507 | G70: 0 | H70: 4.875273 | I70: 3.8240351 | J70: 2.8640941 | K70: 111.62061 | L70: 15.591368 | M70: 18.436838 | N70: 68.031409 | O70: 63.715734 | P70: 274819.08 | Q70: 256099.69 | R70: 782.14585 | S70: 0 | T70: 0 | U70: 0.010932085 | V70: 1 | W70: 0 | X70: 0.75570179 | Y70: 0 | Z70: 0.00037801051 | AA70: 0.00019942512 | AB70: 0.003518881 | AC70: 2.2498401e-05 | AD70: 0.031854677 | AE70: 0.034409915 | AF70: 0.58562118 | AG70: 0.94979627 | AH70: 0.99044619 | AI70: 0.99804399 | AJ70: 1 | AK70: 1 | AL70: 1 | AM70: 0 | AN70: 0 | AO70: 13:100-125 | AP70: 100-125 | AQ70: 3.0215665e+10 | AR70: 117984 | AS70: 0 | AT70: 0 | AU70: 0 | AV70: 100 | AW70: 0 | AX70: 100
A71: 4.3 | B71: 0.96002414 | C71: 35.292652 | D71: 38.710534 | E71: 0.035624578 | F71: 0.03997586 | G71: 0 | H71: 4.948392 | I71: 3.7110585 | J71: 4.1983428 | K71: 134.92879 | L71: 15.244953 | M71: 19.350509 | N71: 68.322934 | O71: 62.19156 | P71: 281087.83 | Q71: 261925.42 | R71: 781.44083 | S71: 0 | T71: 0 | U71: 0.012081384 | V71: 1 | W71: 0 | X71: 0.77661138 | Y71: 0 | Z71: 0.00037698949 | AA71: 0.00024306139 | AB71: 0.0035621478 | AC71: 5.029033e-05 | AD71: 0.035743357 | AE71: 0.064840859 | AF71: 0.42223724 | AG71: 0.90980069 | AH71: 0.9798565 | AI71: 0.99714418 | AJ71: 1 | AK71: 1 | AL71: 1 | AM71: 0 | AN71: 0 | AO71: 14:125-150 | AP71: 125-150 | AQ71: 1.4091588e+10 | AR71: 53800 | AS71: 0 | AT71: 0 | AU71: 0 | AV71: 100 | AW71: 0 | AX71: 100
A72: 4.3 | B72: 0.95692142 | C72: 34.084038 | D72: 41.045723 | E72: 0.034136214 | F72: 0.043078579 | G72: 0 | H72: 5.1459085 | I72: 3.6852227 | J72: 19.40902 | K72: 160.59319 | L72: 15.643636 | M72: 19.608128 | N72: 73.20453 | O72: 65.656036 | P72: 273651.28 | Q72: 255259.41 | R72: 779.35191 | S72: 0 | T72: 0 | U72: 0.0112626 | V72: 1 | W72: 0 | X72: 0.86951356 | Y72: 0 | Z72: 0.00038342289 | AA72: 0.00035448863 | AB72: 0.0036686535 | AC72: 6.9191811e-05 | AD72: 0.038602807 | AE72: 0.079609892 | AF72: 0.33058698 | AG72: 0.87412835 | AH72: 0.97213331 | AI72: 0.99550187 | AJ72: 1 | AK72: 1 | AL72: 1 | AM72: 0 | AN72: 0 | AO72: 15:150-175 | AP72: 150-175 | AQ72: 3.4406416e+09 | AR72: 13479 | AS72: 0 | AT72: 0 | AU72: 0 | AV72: 100 | AW72: 0 | AX72: 100
A73: 4.3 | B73: 0.9532454 | C73: 33.66536 | D73: 43.706713 | E73: 0.033626457 | F73: 0.046754602 | G73: 0 | H73: 5.2300295 | I73: 3.658819 | J73: 27.510522 | K73: 182.55438 | L73: 14.769761 | M73: 20.16457 | N73: 75.884241 | O73: 66.853702 | P73: 289325.66 | Q73: 270360.54 | R73: 778.1221 | S73: 0 | T73: 0 | U73: 0.01385278 | V73: 1 | W73: 0 | X73: 0.85221978 | Y73: 0 | Z73: 0.00038805999 | AA73: 0.00052770323 | AB73: 0.0036357914 | AC73: 0.00013058948 | AD73: 0.042072443 | AE73: 0.096594918 | AF73: 0.25503784 | AG73: 0.81629256 | AH73: 0.94230196 | AI73: 0.99203387 | AJ73: 1 | AK73: 1 | AL73: 1 | AM73: 0 | AN73: 0 | AO73: 16:175-200 | AP73: 175-200 | AQ73: 8.2784399e+08 | AR73: 3062 | AS73: 0 | AT73: 0 | AU73: 0 | AV73: 100 | AW73: 0 | AX73: 100
A74: 4.3 | B74: 0.95105383 | C74: 28.261047 | D74: 45.240284 | E74: 0.027298498 | F74: 0.04894617 | G74: 0 | H74: 5.2464187 | I74: 3.6917229 | J74: 34.717274 | K74: 210.09061 | L74: 15.062819 | M74: 19.593819 | N74: 85.791659 | O74: 73.984502 | P74: 285262.2 | Q74: 265099.5 | R74: 777.48058 | S74: 0 | T74: 0 | U74: 0.018733181 | V74: 1 | W74: 0 | X74: 0.76619444 | Y74: 0 | Z74: 0.00039355746 | AA74: 0.00055744886 | AB74: 0.0040135355 | AC74: 0.00029981246 | AD74: 0.0436818 | AE74: 0.12009367 | AF74: 0.14854477 | AG74: 0.6966005 | AH74: 0.85633043 | AI74: 0.97462642 | AJ74: 1 | AK74: 1 | AL74: 1 | AM74: 0 | AN74: 0 | AO74: 17:200-225 | AP74: 200-225 | AQ74: 1.0975119e+08 | AR74: 414 | AS74: 0 | AT74: 0 | AU74: 0 | AV74: 100 | AW74: 0 | AX74: 100
A75: 4.3 | B75: 0.95106712 | C75: 0.36622219 | D75: 45.231099 | E75: 0.00030569862 | F75: 0.048932877 | G75: 0 | H75: 5.3142705 | I75: 3.6726424 | J75: 37.399005 | K75: 234.92882 | L75: 14.685726 | M75: 20.006516 | N75: 88.220187 | O75: 75.44366 | P75: 291527.89 | Q75: 271913.73 | R75: 780.63111 | S75: 0 | T75: 0 | U75: 0.02801204 | V75: 1 | W75: 0 | X75: 0.75461687 | Y75: 0 | Z75: 0.00039629672 | AA75: 0.000556465 | AB75: 0.0039214945 | AC75: 0.0003853902 | AD75: 0.043673215 | AE75: 0.12704695 | AF75: 0.07035943 | AG75: 0.65337731 | AH75: 0.82154449 | AI75: 0.9827527 | AJ75: 1 | AK75: 1 | AL75: 1 | AM75: 0 | AN75: 0 | AO75: 18:225-250 | AP75: 225-250 | AQ75: 39971319 | AR75: 147 | AS75: 0 | AT75: 0 | AU75: 0 | AV75: 100 | AW75: 0 | AX75: 100
A76: 4.3 | B76: 0.95286035 | C76: 34.576458 | D76: 43.978976 | E76: 0.034739567 | F76: 0.047139654 | G76: 0 | H76: 5.483312 | I76: 3.6729403 | J76: 47.39144 | K76: 265.60645 | L76: 14.27703 | M76: 20.573626 | N76: 88.917568 | O76: 76.022172 | P76: 295376.62 | Q76: 279697.78 | R76: 783.97378 | S76: 0 | T76: 0 | U76: 0 | V76: 1 | W76: 0 | X76: 0.94361767 | Y76: 0 | Z76: 0.00039082394 | AA76: 0.00063181953 | AB76: 0.0040903139 | AC76: 0.00017462634 | AD76: 0.041852053 | AE76: 0.12851392 | AF76: 0.099460969 | AG76: 0.56324578 | AH76: 0.94738828 | AI76: 1 | AJ76: 1 | AK76: 1 | AL76: 1 | AM76: 0 | AN76: 0 | AO76: 999:>= 250 | AP76: >= 250 | AQ76: 15942774 | AR76: 57 | AS76: 0 | AT76: 0 | AU76: 0 | AV76: 100 | AW76: 0 | AX76: 100
