Workbook

Sheet Distribution of data
A1: count() | B1: bucket | I1: count() | J1: tag | K1: loansize | L1: fico | M1: lien | N1: invest | O1: cltv | P1: state | Q1: asOf | R1: Ticker | S1: Orig Date | T1: wala | U1: TPO | V1: burnout
A2: 1096925 | B2: 'Done' | C2: <= 417 >= 740 no lien no invest cltv <= 80 | I2: =SUM(Baseline!AR3:AR17) -> 1235646 | J2: Baseline | K2: (175,417] | L2: [740,860] | M2: no | N2: no | O2: (0,80] | P2: not in ('NY','PR') | Q2: [20120101,20130401] | R2: All 4 | S2: post HARP | T2: [12,24) | U2: CORRES, CASHWINDOW
A3: 466351 | B3: 'FICO' | I3: =SUM(Burnout!AR3:AR34) -> 1232986 | J3: Baseline | K3: (175,417] | L3: [740,860] | M3: no | N3: no | O3: (0,80] | P3: not in ('NY','PR') | Q3: [20120101,20130401] | R3: All 4 | S3: post HARP | U3: CORRES, CASHWINDOW | V3: [0,2000]
A4: 230769 | B4: '2nd Lien'
A5: 144409 | B5: 'INV'
A6: 124596 | B6: 'CLTV'
A7: 57525 | B7: 'Jumbo'
A8: 2 | B8: 'Not Done'
A10: =SUM(A2:A8) -> 2120577 | B10: total

Sheet Actual
A1: WALA [12,24) | C1: BROKER
A2: modelId | B2: SFACTOR_PREPAY_TRACKING_CPR | C2: PREPAY_CPR1 | D2: PREPAY_TRACKING_CPR1 | E2: PREPAY_SMM1 | F2: PREPAY_TRACKING_SMM1 | G2: PCT_LOANTYPE | H2: _ORIGNOTERATE | I2: _ZEROSATO | J2: _SATO | K2: _REFI_INCENTIVE_Fixed | L2: _Fixed_cost | M2: _LOANAGE | N2: _LTV | O2: _CLTV | P2: _AVG_LOANSIZE_SCHAMBALANCE | Q2: _WACLS | R2: _FICO | S2: PCT_ISSECONDLIEN | T2: _OrigCombLTV | U2: PCT_SVC | V2: PCT_TPO | W2: PCT_GEO | X2: PCT_LOANPURPOSE | Y2: PCT_OCC | Z2: curtailsmm | AA2: defaultsmm | AB2: toverSmm | AC2: cashoutSmm | AD2: refiSmm | AE2: cumHPA | AF2: cumHPA05Pct | AG2: cumHPA15Pct | AH2: cumHPA20Pct | AI2: cumHPA25Pct | AJ2: cumHPA30Pct | AK2: cumHPA35Pct | AL2: cumHPA40Pct | AM2: adjtoverSmm | AN2: adjRefiSmm | AO2: groupByColumn | AP2: curve | AQ2: Balance | AR2: LoanCount | AS2: PCT_BROKER | AT2: PCT_CORRES | AU2: PCT_NonRETAIL | AV2: PCT_RETAIL | AW2: PCT_CashWindow | AX2: PCT_NonCashWindow
A3: 4.3 | B3: 0.99354299 | C3: 3.4433222 | D3: 7.4790735 | E3: 0.0029157422 | F3: 0.0064570079 | G3: 0 | H3: 3.9622665 | I3: 4.1506701 | J3: -55.102824 | K3: -57.170377 | L3: 18.591369 | M3: 15.604608 | N3: 77.726934 | O3: 75.492093 | P3: 267072.12 | Q3: 193404.05 | R3: 774.87434 | S3: 0 | T3: 0 | U3: 0.089424414 | V3: 0 | W3: 0 | X3: 0.58543282 | Y3: 0 | Z3: 0.00067107958 | AA3: 7.5421688e-05 | AB3: 0.0025087098 | AC3: 2.9446125e-08 | AD3: 0.0032017562 | AE3: -0.025268185 | AF3: 0.99001879 | AG3: 0.99720024 | AH3: 1 | AI3: 1 | AJ3: 1 | AK3: 1 | AL3: 1 | AM3: 0 | AN3: 0 | AO3: 06:-75--50 | AP3: =-75--50 -> -25 | AQ3: 22048061 | AR3: 114 | AS3: 100 | AT3: 0 | AU3: 100 | AV3: 0 | AW3: 0 | AX3: 0
A4: 4.3 | B4: 0.9934404 | C4: 2.6756426 | D4: 7.5936475 | E4: 0.0022575225 | F4: 0.0065595963 | G4: 0 | H4: 3.91998 | I4: 4.1424648 | J4: -57.659948 | K4: -32.594271 | L4: 14.98906 | M4: 15.424298 | N4: 73.798811 | O4: 72.801415 | P4: 293064.03 | Q4: 263371.78 | R4: 784.82056 | S4: 0 | T4: 0 | U4: 0.08318706 | V4: 0 | W4: 0 | X4: 0.63466923 | Y4: 0 | Z4: 0.00042337918 | AA4: 5.4947755e-05 | AB4: 0.0024369602 | AC4: 1.9932865e-08 | AD4: 0.0036442753 | AE4: -0.020683738 | AF4: 0.98301074 | AG4: 0.99723916 | AH4: 1 | AI4: 1 | AJ4: 1 | AK4: 1 | AL4: 1 | AM4: 0 | AN4: 0 | AO4: 07:-50--25 | AP4: =-50--25 -> -25 | AQ4: 2.4835959e+08 | AR4: 943 | AS4: 100 | AT4: 0 | AU4: 100 | AV4: 0 | AW4: 0 | AX4: 0
A5: 4.3 | B5: 0.98810675 | C5: 14.515411 | D5: 13.374372 | E5: 0.012984471 | F5: 0.01189325 | G5: 0 | H5: 4.0994748 | I5: 4.1233851 | J5: -40.112546 | K5: -8.5065994 | L5: 14.517274 | M5: 15.824699 | N5: 72.180941 | O5: 71.16733 | P5: 297035.51 | Q5: 273997.1 | R5: 782.74924 | S5: 0 | T5: 0 | U5: 0.16198165 | V5: 0 | W5: 0 | X5: 0.71326488 | Y5: 0 | Z5: 0.00037641719 | AA5: 6.1641507e-05 | AB5: 0.0025045364 | AC5: 1.1985382e-07 | AD5: 0.0089505203 | AE5: -0.015473879 | AF5: 0.95973186 | AG5: 0.99363686 | AH5: 0.99969863 | AI5: 1 | AJ5: 1 | AK5: 1 | AL5: 1 | AM5: 0 | AN5: 0 | AO5: 08:-25-0 | AP5: =-25-0 -> -25 | AQ5: 2.0251126e+09 | AR5: 7391 | AS5: 100 | AT5: 0 | AU5: 100 | AV5: 0 | AW5: 0 | AX5: 0
A6: 4.3 | B6: 0.98304592 | C6: 27.048998 | D6: 18.551023 | E6: 0.025939486 | F6: 0.016954085 | G6: 0 | H6: 4.1521468 | I6: 4.0348346 | J6: -30.391947 | K6: 15.744335 | L6: 14.364007 | M6: 15.776989 | N6: 68.038082 | O6: 65.942075 | P6: 298325.63 | Q6: 277825.05 | R6: 783.61193 | S6: 0 | T6: 0 | U6: 0.23317829 | V6: 0 | W6: 0 | X6: 0.8177067 | Y6: 0 | Z6: 0.00036976726 | AA6: 5.8793704e-05 | AB6: 0.0027739843 | AC6: 3.0262744e-06 | AD6: 0.013748499 | AE6: 0.0038239737 | AF6: 0.83514428 | AG6: 0.95178217 | AH6: 0.99513288 | AI6: 0.99904793 | AJ6: 1 | AK6: 1 | AL6: 1 | AM6: 0 | AN6: 0 | AO6: 09:0-25 | AP6: 0-25 | AQ6: 1.0989092e+10 | AR6: 39554 | AS6: 100 | AT6: 0 | AU6: 100 | AV6: 0 | AW6: 0 | AX6: 0
A7: 4.3 | B7: 0.97553016 | C7: 39.511307 | D7: 25.717173 | E7: 0.041027433 | F7: 0.024469838 | G7: 0 | H7: 4.1700427 | I7: 3.886904 | J7: -26.925548 | K7: 37.409975 | L7: 13.639154 | M7: 16.149073 | N7: 64.844231 | O7: 61.095981 | P7: 311881.57 | Q7: 292677.63 | R7: 783.83427 | S7: 0 | T7: 0 | U7: 0.2676584 | V7: 0 | W7: 0 | X7: 0.83998291 | Y7: 0 | Z7: 0.00036821089 | AA7: 5.7737956e-05 | AB7: 0.0030840132 | AC7: 1.0551737e-05 | AD7: 0.020949309 | AE7: 0.034424605 | AF7: 0.65979439 | AG7: 0.8965255 | AH7: 0.98913006 | AI7: 0.99836628 | AJ7: 1 | AK7: 1 | AL7: 1 | AM7: 0 | AN7: 0 | AO7: 10:25-50 | AP7: 25-50 | AQ7: 2.1924188e+10 | AR7: 74909 | AS7: 100 | AT7: 0 | AU7: 100 | AV7: 0 | AW7: 0 | AX7: 0
A8: 4.3 | B8: 0.96749363 | C8: 47.215946 | D8: 32.736821 | E8: 0.051853975 | F8: 0.032506367 | G8: 0 | H8: 4.4546713 | I8: 3.8939111 | J8: -17.636655 | K8: 62.476491 | L8: 14.232973 | M8: 17.622334 | N8: 67.200221 | O8: 63.714954 | P8: 300315.56 | Q8: 280510.29 | R8: 782.16221 | S8: 0 | T8: 0 | U8: 0.24509649 | V8: 0 | W8: 0 | X8: 0.76375298 | Y8: 0 | Z8: 0.00037146776 | AA8: 8.9448587e-05 | AB8: 0.0032444203 | AC8: 9.1333761e-06 | AD8: 0.028791883 | AE8: 0.02481458 | AF8: 0.68593791 | AG8: 0.94531389 | AH8: 0.99334833 | AI8: 0.99910374 | AJ8: 1 | AK8: 1 | AL8: 1 | AM8: 0 | AN8: 0 | AO8: 11:50-75 | AP8: 50-75 | AQ8: 1.7351525e+10 | AR8: 61857 | AS8: 100 | AT8: 0 | AU8: 100 | AV8: 0 | AW8: 0 | AX8: 0
A9: 4.3 | B9: 0.9616878 | C9: 45.770827 | D9: 37.423788 | E9: 0.049717463 | F9: 0.038312201 | G9: 0 | H9: 4.6792015 | I9: 3.8981509 | J9: -11.53115 | K9: 85.668971 | L9: 14.263814 | M9: 17.602014 | N9: 66.442911 | O9: 62.693089 | P9: 299859.64 | Q9: 279920.92 | R9: 780.85805 | S9: 0 | T9: 0 | U9: 0.28399373 | V9: 0 | W9: 0 | X9: 0.69290849 | Y9: 0 | Z9: 0.00037185965 | AA9: 0.00010535088 | AB9: 0.0033641167 | AC9: 1.8856207e-05 | AD9: 0.034452003 | AE9: 0.028319628 | AF9: 0.62658474 | AG9: 0.94565646 | AH9: 0.98872447 | AI9: 0.99818447 | AJ9: 1 | AK9: 1 | AL9: 1 | AM9: 0 | AN9: 0 | AO9: 12:75-100 | AP9: 75-100 | AQ9: 1.1137494e+10 | AR9: 39788 | AS9: 100 | AT9: 0 | AU9: 100 | AV9: 0 | AW9: 0 | AX9: 0
A10: 4.3 | B10: 0.95610776 | C10: 45.909203 | D10: 41.644457 | E10: 0.049919769 | F10: 0.04389224 | G10: 0 | H10: 4.8190174 | I10: 3.7827978 | J10: -7.033373 | K10: 111.76843 | L10: 14.851525 | M10: 18.573443 | N10: 70.047731 | O10: 64.517258 | P10: 288600.21 | Q10: 268853.2 | R10: 779.33271 | S10: 0 | T10: 0 | U10: 0.29515185 | V10: 0 | W10: 0 | X10: 0.61609329 | Y10: 0 | Z10: 0.00037279538 | AA10: 0.00014722462 | AB10: 0.0036961846 | AC10: 3.6742999e-05 | AD10: 0.039639278 | AE10: 0.052894394 | AF10: 0.44589189 | AG10: 0.9189403 | AH10: 0.98503593 | AI10: 0.99699297 | AJ10: 1 | AK10: 1 | AL10: 1 | AM10: 0 | AN10: 0 | AO10: 13:100-125 | AP10: 100-125 | AQ10: 5.7252288e+09 | AR10: 21295 | AS10: 100 | AT10: 0 | AU10: 100 | AV10: 0 | AW10: 0 | AX10: 0
A11: 4.3 | B11: 0.95139204 | C11: 46.476872 | D11: 45.006143 | E11: 0.050754696 | F11: 0.048607957 | G11: 0 | H11: 4.8761355 | I11: 3.6738705 | J11: -6.547352 | K11: 134.37324 | L11: 14.345575 | M11: 20.090596 | N11: 70.80133 | O11: 63.193322 | P11: 297212.06 | Q11: 278337.2 | R11: 778.25756 | S11: 0 | T11: 0 | U11: 0.29020541 | V11: 0 | W11: 0 | X11: 0.61283836 | Y11: 0 | Z11: 0.00037411096 | AA11: 0.00016841151 | AB11: 0.0036857396 | AC11: 8.5910415e-05 | AD11: 0.04429377 | AE11: 0.085370719 | AF11: 0.28253617 | AG11: 0.87003254 | AH11: 0.9662038 | AI11: 0.99610031 | AJ11: 1 | AK11: 1 | AL11: 1 | AM11: 0 | AN11: 0 | AO11: 14:125-150 | AP11: 125-150 | AQ11: 2.6208231e+09 | AR11: 9416 | AS11: 100 | AT11: 0 | AU11: 100 | AV11: 0 | AW11: 0 | AX11: 0
A12: 4.3 | B12: 0.94664668 | C12: 44.242836 | D12: 48.208917 | E12: 0.047514463 | F12: 0.05335332 | G12: 0 | H12: 5.0228991 | I12: 3.6711342 | J12: 6.8476451 | K12: 160.18516 | L12: 14.050936 | M12: 20.067577 | N12: 78.702585 | O12: 68.818309 | P12: 302497.45 | Q12: 284181.94 | R12: 777.14943 | S12: 0 | T12: 0 | U12: 0.23643044 | V12: 0 | W12: 0 | X12: 0.52204473 | Y12: 0 | Z12: 0.00037364661 | AA12: 0.00024360029 | AB12: 0.0038902341 | AC12: 0.00013030684 | AD12: 0.048715516 | AE12: 0.10704924 | AF12: 0.15712908 | AG12: 0.78788788 | AH12: 0.94414223 | AI12: 0.9898934 | AJ12: 1 | AK12: 1 | AL12: 1 | AM12: 0 | AN12: 0 | AO12: 15:150-175 | AP12: 150-175 | AQ12: 4.4019782e+08 | AR12: 1549 | AS12: 100 | AT12: 0 | AU12: 100 | AV12: 0 | AW12: 0 | AX12: 0
A13: 4.3 | B13: 0.94180872 | C13: 53.130436 | D13: 51.297364 | E13: 0.061197489 | F13: 0.058191283 | G13: 0 | H13: 5.046812 | I13: 3.6581714 | J13: 6.4300909 | K13: 183.9435 | L13: 13.884685 | M13: 20.486383 | N13: 85.498759 | O13: 72.57064 | P13: 305684.75 | Q13: 287591.9 | R13: 777.65331 | S13: 0 | T13: 0 | U13: 0.23252351 | V13: 0 | W13: 0 | X13: 0.40200049 | Y13: 0 | Z13: 0.00037498084 | AA13: 0.00032210145 | AB13: 0.0041021819 | AC13: 0.00035720284 | AD13: 0.0530348 | AE13: 0.13942807 | AF13: 0.035231054 | AG13: 0.62060278 | AH13: 0.85157551 | AI13: 0.98674363 | AJ13: 1 | AK13: 1 | AL13: 1 | AM13: 0 | AN13: 0 | AO13: 16:175-200 | AP13: 175-200 | AQ13: 96630878 | AR13: 336 | AS13: 100 | AT13: 0 | AU13: 100 | AV13: 0 | AW13: 0 | AX13: 0
A14: 4.3 | B14: 0.9407424 | C14: 47.495831 | D14: 51.954953 | E14: 0.052273955 | F14: 0.059257599 | G14: 0 | H14: 5.1962175 | I14: 3.6487088 | J14: 17.28872 | K14: 209.55229 | L14: 14.52586 | M14: 20.792683 | N14: 90.120235 | O14: 75.17575 | P14: 294450.4 | Q14: 274910.83 | R14: 775.39517 | S14: 0 | T14: 0 | U14: 0.083777428 | V14: 0 | W14: 0 | X14: 0.28831945 | Y14: 0 | Z14: 0.00037198764 | AA14: 0.00037985115 | AB14: 0.0043843365 | AC14: 0.0005945363 | AD14: 0.053526869 | AE14: 0.16459065 | AF14: 0 | AG14: 0.46714353 | AH14: 0.67606014 | AI14: 0.98161705 | AJ14: 1 | AK14: 1 | AL14: 1 | AM14: 0 | AN14: 0 | AO14: 17:200-225 | AP14: 200-225 | AQ14: 20893223 | AR14: 76 | AS14: 100 | AT14: 0 | AU14: 100 | AV14: 0 | AW14: 0 | AX14: 0
A15: 4.3 | B15: 0.94906051 | C15: 46.592588 | D15: 46.601772 | E15: 0.050925887 | F15: 0.050939488 | G15: 0 | H15: 5.321533 | I15: 3.665408 | J15: 30.474314 | K15: 232.6404 | L15: 17.927401 | M15: 20.850682 | N15: 92.695715 | O15: 75.691523 | P15: 246276.83 | Q15: 222772.75 | R15: 788.41159 | S15: 0 | T15: 0 | U15: 0 | V15: 0 | W15: 0 | X15: 0.34002479 | Y15: 0 | Z15: 0.00040339218 | AA15: 4.2794964e-05 | AB15: 0.004240869 | AC15: 0.00068165279 | AD15: 0.045570761 | AE15: 0.17333363 | AF15: 0 | AG15: 0.29883154 | AH15: 0.63135198 | AI15: 0.95367429 | AJ15: 1 | AK15: 1 | AL15: 1 | AM15: 0 | AN15: 0 | AO15: 18:225-250 | AP15: 225-250 | AQ15: 3787136.8 | AR15: 17 | AS15: 100 | AT15: 0 | AU15: 100 | AV15: 0 | AW15: 0 | AX15: 0
A19: WALA [12,24) | C19: CORRES
A20: modelId | B20: SFACTOR_PREPAY_TRACKING_CPR | C20: PREPAY_CPR1 | D20: PREPAY_TRACKING_CPR1 | E20: PREPAY_SMM1 | F20: PREPAY_TRACKING_SMM1 | G20: PCT_LOANTYPE | H20: _ORIGNOTERATE | I20: _ZEROSATO | J20: _SATO | K20: _REFI_INCENTIVE_Fixed | L20: _Fixed_cost | M20: _LOANAGE | N20: _LTV | O20: _CLTV | P20: _AVG_LOANSIZE_SCHAMBALANCE | Q20: _WACLS | R20: _FICO | S20: PCT_ISSECONDLIEN | T20: _OrigCombLTV | U20: PCT_SVC | V20: PCT_TPO | W20: PCT_GEO | X20: PCT_LOANPURPOSE | Y20: PCT_OCC | Z20: curtailsmm | AA20: defaultsmm | AB20: toverSmm | AC20: cashoutSmm | AD20: refiSmm | AE20: cumHPA | AF20: cumHPA05Pct | AG20: cumHPA15Pct | AH20: cumHPA20Pct | AI20: cumHPA25Pct | AJ20: cumHPA30Pct | AK20: cumHPA35Pct | AL20: cumHPA40Pct | AM20: adjtoverSmm | AN20: adjRefiSmm | AO20: groupByColumn | AP20: curve | AQ20: Balance | AR20: LoanCount | AS20: PCT_BROKER | AT20: PCT_CORRES | AU20: PCT_NonRETAIL | AV20: PCT_RETAIL | AW20: PCT_CashWindow | AX20: PCT_NonCashWindow
A21: 4.3 | B21: 0.9957006 | C21: 1.2100205e-05 | D21: 5.0390158 | E21: 1.0083505e-08 | F21: 0.0042994036 | G21: 0 | H21: 4.0264725 | I21: 4.1375376 | J21: -42.855524 | K21: -108.8538 | L21: 20.131193 | M21: 15.604363 | N21: 76.15288 | O21: 75.620604 | P21: 198516.22 | Q21: 198343.74 | R21: 760.45864 | S21: 0 | T21: 0 | U21: 0 | V21: 0 | W21: 0 | X21: 0.21177999 | Y21: 0 | Z21: 0.00035089724 | AA21: 5.1078517e-05 | AB21: 0.0028684717 | AC21: 0 | AD21: 0.0010289422 | AE21: -0.01596622 | AF21: 1 | AG21: 1 | AH21: 1 | AI21: 1 | AJ21: 1 | AK21: 1 | AL21: 1 | AM21: 0 | AN21: 0 | AO21: 04:-125--100 | AP21: =-125--100 -> -25 | AQ21: 991718.69 | AR21: 5 | AS21: 0 | AT21: 100 | AU21: 100 | AV21: 0 | AW21: 0 | AX21: 0
A22: 4.3 | B22: 0.99034254 | C22: 7.935874 | D22: 10.99278 | E22: 0.0068667181 | F22: 0.0096574553 | G22: 0 | H22: 4.1493576 | I22: 4.0940505 | J22: -33.386672 | K22: -83.205891 | L22: 15.783595 | M22: 15.690168 | N22: 76.749332 | O22: 75.908226 | P22: 298964.84 | Q22: 222085.04 | R22: 780.43588 | S22: 0 | T22: 0 | U22: 0 | V22: 0 | W22: 0 | X22: 0.37109602 | Y22: 0 | Z22: 0.00053542522 | AA22: 7.7502751e-05 | AB22: 0.0026030463 | AC22: 0 | AD22: 0.0064414668 | AE22: -0.026461015 | AF22: 1 | AG22: 1 | AH22: 1 | AI22: 1 | AJ22: 1 | AK22: 1 | AL22: 1 | AM22: 0 | AN22: 0 | AO22: 05:-100--75 | AP22: =-100--75 -> -25 | AQ22: 6218381 | AR22: 28 | AS22: 0 | AT22: 100 | AU22: 100 | AV22: 0 | AW22: 0 | AX22: 0
A23: 4.3 | B23: 0.99531194 | C23: 1.8301087 | D23: 5.4828571 | E23: 0.0015380347 | F23: 0.0046880567 | G23: 0 | H23: 3.8986259 | I23: 4.1473096 | J23: -59.670289 | K23: -56.905879 | L23: 17.18523 | M23: 15.245911 | N23: 77.854851 | O23: 76.716765 | P23: 263061.8 | Q23: 226873.4 | R23: 780.81197 | S23: 0 | T23: 0 | U23: 0.0025098134 | V23: 0 | W23: 0 | X23: 0.46038548 | Y23: 0 | Z23: 0.00047411809 | AA23: 6.1413376e-05 | AB23: 0.0024185358 | AC23: 0 | AD23: 0.0017339791 | AE23: -0.022969111 | AF23: 0.996552 | AG23: 1 | AH23: 1 | AI23: 1 | AJ23: 1 | AK23: 1 | AL23: 1 | AM23: 0 | AN23: 0 | AO23: 06:-75--50 | AP23: =-75--50 -> -25 | AQ23: 1.3952714e+08 | AR23: 615 | AS23: 0 | AT23: 100 | AU23: 100 | AV23: 0 | AW23: 0 | AX23: 0
A24: 4.3 | B24: 0.99386722 | C24: 3.4070807 | D24: 7.116109 | E24: 0.0028845605 | F24: 0.0061327803 | G24: 0 | H24: 3.8995117 | I24: 4.1447021 | J24: -60.114068 | K24: -33.387746 | L24: 15.955751 | M24: 15.468515 | N24: 73.341274 | O24: 71.959297 | P24: 273610.41 | Q24: 248811.56 | R24: 782.10208 | S24: 0 | T24: 0 | U24: 0.0013918239 | V24: 0 | W24: 0 | X24: 0.58737228 | Y24: 0 | Z24: 0.00039633253 | AA24: 5.7272475e-05 | AB24: 0.0025387935 | AC24: 2.1988534e-08 | AD24: 0.0031403457 | AE24: -0.015273165 | AF24: 0.98396189 | AG24: 0.99979739 | AH24: 0.99996869 | AI24: 0.99999042 | AJ24: 1 | AK24: 1 | AL24: 1 | AM24: 0 | AN24: 0 | AO24: 07:-50--25 | AP24: =-50--25 -> -25 | AQ24: 1.6254859e+09 | AR24: 6533 | AS24: 0 | AT24: 100 | AU24: 100 | AV24: 0 | AW24: 0 | AX24: 0
A25: 4.3 | B25: 0.9884728 | C25: 8.6868546 | D25: 12.988493 | E25: 0.0075443498 | F25: 0.011527198 | G25: 0 | H25: 4.097073 | I25: 4.1260145 | J25: -41.673293 | K25: -9.3602837 | L25: 15.303898 | M25: 16.096379 | N25: 72.187814 | O25: 71.033906 | P25: 281961.47 | Q25: 260269.92 | R25: 781.85441 | S25: 0 | T25: 0 | U25: 0.002782606 | V25: 0 | W25: 0 | X25: 0.6832404 | Y25: 0 | Z25: 0.00037474785 | AA25: 6.7008715e-05 | AB25: 0.0026069832 | AC25: 3.167863e-08 | AD25: 0.008478412 | AE25: -0.014262052 | AF25: 0.97210268 | AG25: 0.99863121 | AH25: 0.99987521 | AI25: 1 | AJ25: 1 | AK25: 1 | AL25: 1 | AM25: 0 | AN25: 0 | AO25: 08:-25-0 | AP25: =-25-0 -> -25 | AQ25: 9.6437813e+09 | AR25: 37053 | AS25: 0 | AT25: 100 | AU25: 100 | AV25: 0 | AW25: 0 | AX25: 0
A26: 4.3 | B26: 0.98339762 | C26: 18.623934 | D26: 18.20065 | E26: 0.017027448 | F26: 0.016602377 | G26: 0 | H26: 4.2061544 | I26: 4.0684698 | J26: -31.261201 | K26: 15.159426 | L26: 15.015325 | M26: 16.531355 | N26: 69.194667 | O26: 67.652827 | P26: 286199.29 | Q26: 265730.87 | R26: 782.34245 | S26: 0 | T26: 0 | U26: 0.0089632365 | V26: 0 | W26: 0 | X26: 0.76936148 | Y26: 0 | Z26: 0.00037298469 | AA26: 7.4133431e-05 | AB26: 0.0027640145 | AC26: 4.0375178e-07 | AD26: 0.013390826 | AE26: -0.0086907056 | AF26: 0.92529766 | AG26: 0.99384479 | AH26: 0.99955192 | AI26: 0.99983997 | AJ26: 1 | AK26: 1 | AL26: 1 | AM26: 0 | AN26: 0 | AO26: 09:0-25 | AP26: 0-25 | AQ26: 3.8876693e+10 | AR26: 146301 | AS26: 0 | AT26: 100 | AU26: 100 | AV26: 0 | AW26: 0 | AX26: 0
A27: 4.3 | B27: 0.97636692 | C27: 30.172729 | D27: 24.948964 | E27: 0.029485364 | F27: 0.023633078 | G27: 0 | H27: 4.2307505 | I27: 3.9141908 | J27: -26.990777 | K27: 37.381619 | L27: 14.422594 | M27: 17.06351 | N27: 67.386444 | O27: 64.475774 | P27: 297412.58 | Q27: 276705.53 | R27: 782.18971 | S27: 0 | T27: 0 | U27: 0.017089004 | V27: 0 | W27: 0 | X27: 0.75444376 | Y27: 0 | Z27: 0.00037191187 | AA27: 7.6173822e-05 | AB27: 0.0030566284 | AC27: 3.0381204e-06 | AD27: 0.020125312 | AE27: 0.014020201 | AF27: 0.79792715 | AG27: 0.97128841 | AH27: 0.99714665 | AI27: 0.99948034 | AJ27: 1 | AK27: 1 | AL27: 1 | AM27: 0 | AN27: 0 | AO27: 10:25-50 | AP27: 25-50 | AQ27: 6.1816015e+10 | AR27: 223400 | AS27: 0 | AT27: 100 | AU27: 100 | AV27: 0 | AW27: 0 | AX27: 0
A28: 4.3 | B28: 0.96874993 | C28: 38.013898 | D28: 31.6812 | E28: 0.039071235 | F28: 0.031250067 | G28: 0 | H28: 4.4691529 | I28: 3.8899297 | J28: -17.585481 | K28: 62.663639 | L28: 14.904888 | M28: 17.433619 | N28: 69.566621 | O28: 66.270424 | P28: 287889.79 | Q28: 267833.15 | R28: 780.90567 | S28: 0 | T28: 0 | U28: 0.012379923 | V28: 0 | W28: 0 | X28: 0.65513568 | Y28: 0 | Z28: 0.00037347868 | AA28: 0.00010165557 | AB28: 0.0031882111 | AC28: 6.1303928e-06 | AD28: 0.027580577 | AE28: 0.018520793 | AF28: 0.75933386 | AG28: 0.97296663 | AH28: 0.99568006 | AI28: 0.99918144 | AJ28: 1 | AK28: 1 | AL28: 1 | AM28: 0 | AN28: 0 | AO28: 11:50-75 | AP28: 50-75 | AQ28: 6.0848478e+10 | AR28: 227188 | AS28: 0 | AT28: 100 | AU28: 100 | AV28: 0 | AW28: 0 | AX28: 0
A29: 4.3 | B29: 0.96283573 | C29: 42.416214 | D29: 36.521539 | E29: 0.0449524 | F29: 0.037164268 | G29: 0 | H29: 4.669899 | I29: 3.8733774 | J29: -11.114419 | K29: 86.082824 | L29: 14.804271 | M29: 16.938335 | N29: 69.317804 | O29: 65.421495 | P29: 290106.53 | Q29: 269690.96 | R29: 780.16361 | S29: 0 | T29: 0 | U29: 0.014929732 | V29: 0 | W29: 0 | X29: 0.57816443 | Y29: 0 | Z29: 0.0003715959 | AA29: 0.00012118595 | AB29: 0.0033233774 | AC29: 1.1990445e-05 | AD29: 0.033336103 | AE29: 0.028739178 | AF29: 0.66722427 | AG29: 0.96394033 | AH29: 0.99288434 | AI29: 0.99892184 | AJ29: 1 | AK29: 1 | AL29: 1 | AM29: 0 | AN29: 0 | AO29: 12:75-100 | AP29: 75-100 | AQ29: 4.55179e+10 | AR29: 168778 | AS29: 0 | AT29: 100 | AU29: 100 | AV29: 0 | AW29: 0 | AX29: 0
A30: 4.3 | B30: 0.95762744 | C30: 42.856373 | D30: 40.521638 | E30: 0.045562891 | F30: 0.042372557 | G30: 0 | H30: 4.8031244 | I30: 3.7630665 | J30: -6.4548522 | K30: 111.90903 | L30: 15.277825 | M30: 18.004782 | N30: 72.048793 | O30: 66.634559 | P30: 281058.31 | Q30: 261352.89 | R30: 779.37482 | S30: 0 | T30: 0 | U30: 0.01546372 | V30: 0 | W30: 0 | X30: 0.50506534 | Y30: 0 | Z30: 0.00037175511 | AA30: 0.00016338236 | AB30: 0.0035742012 | AC30: 2.7048051e-05 | AD30: 0.038236155 | AE30: 0.049620894 | AF30: 0.5097601 | AG30: 0.94271147 | AH30: 0.98829344 | AI30: 0.99772965 | AJ30: 1 | AK30: 1 | AL30: 1 | AM30: 0 | AN30: 0 | AO30: 13:100-125 | AP30: 100-125 | AQ30: 2.802095e+10 | AR30: 107215 | AS30: 0 | AT30: 100 | AU30: 100 | AV30: 0 | AW30: 0 | AX30: 0
A31: 4.3 | B31: 0.95271962 | C31: 44.800986 | D31: 44.07818 | E31: 0.048312694 | F31: 0.047280382 | G31: 0 | H31: 4.8804013 | I31: 3.6765996 | J31: -4.9590254 | K31: 134.28061 | L31: 14.635412 | M31: 19.561149 | N31: 71.76419 | O31: 64.964183 | P31: 292491.52 | Q31: 272829.41 | R31: 778.75703 | S31: 0 | T31: 0 | U31: 0.017311252 | V31: 0 | W31: 0 | X31: 0.51891916 | Y31: 0 | Z31: 0.0003723305 | AA31: 0.00019811131 | AB31: 0.0035194468 | AC31: 6.8018786e-05 | AD31: 0.043122459 | AE31: 0.071315724 | AF31: 0.39506961 | AG31: 0.90346476 | AH31: 0.97245124 | AI31: 0.99591568 | AJ31: 1 | AK31: 1 | AL31: 1 | AM31: 0 | AN31: 0 | AO31: 14:125-150 | AP31: 125-150 | AQ31: 1.2692843e+10 | AR31: 46523 | AS31: 0 | AT31: 100 | AU31: 100 | AV31: 0 | AW31: 0 | AX31: 0
A32: 4.3 | B32: 0.9490703 | C32: 41.981394 | D32: 46.595165 | E32: 0.044353499 | F32: 0.050929704 | G32: 0 | H32: 5.0437272 | I32: 3.6813844 | J32: 9.9071253 | K32: 160.87385 | L32: 15.119569 | M32: 19.507703 | N32: 79.542842 | O32: 70.442227 | P32: 283310.92 | Q32: 264098.56 | R32: 776.92982 | S32: 0 | T32: 0 | U32: 0.016870534 | V32: 0 | W32: 0 | X32: 0.47603545 | Y32: 0 | Z32: 0.00037700592 | AA32: 0.00027635962 | AB32: 0.003803571 | AC32: 0.00014882352 | AD32: 0.046323928 | AE32: 0.092884957 | AF32: 0.28597376 | AG32: 0.80432464 | AH32: 0.93778902 | AI32: 0.99023488 | AJ32: 1 | AK32: 1 | AL32: 1 | AM32: 0 | AN32: 0 | AO32: 15:150-175 | AP32: 150-175 | AQ32: 2.58843e+09 | AR32: 9801 | AS32: 0 | AT32: 100 | AU32: 100 | AV32: 0 | AW32: 0 | AX32: 0
A33: 4.3 | B33: 0.94285433 | C33: 48.655806 | D33: 50.644539 | E33: 0.054036721 | F33: 0.057145668 | G33: 0 | H33: 5.0710696 | I33: 3.6599799 | J33: 12.2848 | K33: 183.22998 | L33: 14.003319 | M33: 19.98188 | N33: 83.336593 | O33: 71.286178 | P33: 302371.03 | Q33: 285150.39 | R33: 776.21487 | S33: 0 | T33: 0 | U33: 0.017358684 | V33: 0 | W33: 0 | X33: 0.46148792 | Y33: 0 | Z33: 0.00037680602 | AA33: 0.00032732859 | AB33: 0.0039005728 | AC33: 0.00043364357 | AD33: 0.0521073 | AE33: 0.12971425 | AF33: 0.16588024 | AG33: 0.61762235 | AH33: 0.80205726 | AI33: 0.96116652 | AJ33: 1 | AK33: 1 | AL33: 1 | AM33: 0 | AN33: 0 | AO33: 16:175-200 | AP33: 175-200 | AQ33: 6.8692728e+08 | AR33: 2409 | AS33: 0 | AT33: 100 | AU33: 100 | AV33: 0 | AW33: 0 | AX33: 0
A34: 4.3 | B34: 0.9407399 | C34: 38.318358 | D34: 51.956483 | E34: 0.039465443 | F34: 0.059260097 | G34: 0 | H34: 5.1605718 | I34: 3.6692646 | J34: 17.585612 | K34: 209.41141 | L34: 14.520526 | M34: 20.232747 | N34: 90.534831 | O34: 75.341532 | P34: 296660.31 | Q34: 274999.14 | R34: 775.31983 | S34: 0 | T34: 0 | U34: 0.015751738 | V34: 0 | W34: 0 | X34: 0.29437842 | Y34: 0 | Z34: 0.00037945678 | AA34: 0.00042470513 | AB34: 0.0042613109 | AC34: 0.00072566888 | AD34: 0.053468938 | AE34: 0.16225249 | AF34: 0.036592112 | AG34: 0.4165709 | AH34: 0.69329744 | AI34: 0.92631746 | AJ34: 1 | AK34: 1 | AL34: 1 | AM34: 0 | AN34: 0 | AO34: 17:200-225 | AP34: 200-225 | AQ34: 1.2347462e+08 | AR34: 449 | AS34: 0 | AT34: 100 | AU34: 100 | AV34: 0 | AW34: 0 | AX34: 0
A35: 4.3 | B35: 0.93891144 | C35: 22.828421 | D35: 53.065137 | E35: 0.021363411 | F35: 0.061088562 | G35: 0 | H35: 5.2641041 | I35: 3.6465013 | J35: 27.398546 | K35: 231.7946 | L35: 13.76739 | M35: 20.801174 | N35: 92.494129 | O35: 74.555659 | P35: 310947.98 | Q35: 290043.59 | R35: 776.17564 | S35: 0 | T35: 0 | U35: 0 | V35: 0 | W35: 0 | X35: 0.15312933 | Y35: 0 | Z35: 0.00038271758 | AA35: 0.00052407484 | AB35: 0.0044067446 | AC35: 0.0013321278 | AD35: 0.054442879 | AE35: 0.19808292 | AF35: 0 | AG35: 0.17645629 | AH35: 0.38832439 | AI35: 0.9097973 | AJ35: 1 | AK35: 1 | AL35: 1 | AM35: 0 | AN35: 0 | AO35: 18:225-250 | AP35: 225-250 | AQ35: 22913444 | AR35: 79 | AS35: 0 | AT35: 100 | AU35: 100 | AV35: 0 | AW35: 0 | AX35: 0
A38: WALA [12,24) | C38: CashWindow
A39: modelId | B39: SFACTOR_PREPAY_TRACKING_CPR | C39: PREPAY_CPR1 | D39: PREPAY_TRACKING_CPR1 | E39: PREPAY_SMM1 | F39: PREPAY_TRACKING_SMM1 | G39: PCT_LOANTYPE | H39: _ORIGNOTERATE | I39: _ZEROSATO | J39: _SATO | K39: _REFI_INCENTIVE_Fixed | L39: _Fixed_cost | M39: _LOANAGE | N39: _LTV | O39: _CLTV | P39: _AVG_LOANSIZE_SCHAMBALANCE | Q39: _WACLS | R39: _FICO | S39: PCT_ISSECONDLIEN | T39: _OrigCombLTV | U39: PCT_SVC | V39: PCT_TPO | W39: PCT_GEO | X39: PCT_LOANPURPOSE | Y39: PCT_OCC | Z39: curtailsmm | AA39: defaultsmm | AB39: toverSmm | AC39: cashoutSmm | AD39: refiSmm | AE39: cumHPA | AF39: cumHPA05Pct | AG39: cumHPA15Pct | AH39: cumHPA20Pct | AI39: cumHPA25Pct | AJ39: cumHPA30Pct | AK39: cumHPA35Pct | AL39: cumHPA40Pct | AM39: adjtoverSmm | AN39: adjRefiSmm | AO39: groupByColumn | AP39: curve | AQ39: Balance | AR39: LoanCount | AS39: PCT_BROKER | AT39: PCT_CORRES | AU39: PCT_NonRETAIL | AV39: PCT_RETAIL | AW39: PCT_CashWindow | AX39: PCT_NonCashWindow
A40: 4.3 | B40: 0.99661762 | C40: 0 | D40: 3.9841936 | E40: 0 | F40: 0.00338238 | G40: 0 | H40: 3.875 | I40: 4.118472 | J40: -64.0619 | K40: -131.95 | L40: 13.16 | M40: 17 | N40: 80 | O40: 77.08 | P40: 303250.44 | Q40: 303250.44 | R40: 773 | S40: 0 | T40: 0 | U40: 0 | V40: 1 | W40: 0 | X40: 1 | Y40: 0 | Z40: 0.00035183 | AA40: 7.792e-05 | AB40: 0.00295262 | AC40: 0 | AD40: 0 | AE40: 0.011207683 | AF40: 1 | AG40: 1 | AH40: 1 | AI40: 1 | AJ40: 1 | AK40: 1 | AL40: 1 | AM40: 0 | AN40: 0 | AO40: 03:-150--125 | AP40: =-150--125 -> -25 | AQ40: 303250.44 | AR40: 1 | AS40: 0 | AT40: 0 | AU40: 0 | AV40: 100 | AW40: 100 | AX40: 0
A41: 4.3 | B41: 0.99173453 | C41: 0 | D41: 9.4798618 | E41: 0 | F41: 0.0082654715 | G41: 0 | H41: 3.875 | I41: 3.8717773 | J41: -56.468943 | K41: -111.35086 | L41: 14.328815 | M41: 17.880294 | N41: 80 | O41: 75.620345 | P41: 284673.47 | Q41: 278674.78 | R41: 771.88117 | S41: 0 | T41: 0 | U41: 0 | V41: 1 | W41: 0 | X41: 1 | Y41: 0 | Z41: 0.00035334788 | AA41: 5.3605208e-05 | AB41: 0.0031742462 | AC41: 0 | AD41: 0.0046842576 | AE41: 0.029306717 | AF41: 1 | AG41: 1 | AH41: 1 | AI41: 1 | AJ41: 1 | AK41: 1 | AL41: 1 | AM41: 0 | AN41: 0 | AO41: 04:-125--100 | AP41: =-125--100 -> -25 | AQ41: 1114699.1 | AR41: 4 | AS41: 0 | AT41: 0 | AU41: 0 | AV41: 100 | AW41: 100 | AX41: 0
A42: 4.3 | B42: 0.98992819 | C42: 12.107777 | D42: 11.438635 | E42: 0.010697278 | F42: 0.01007181 | G42: 0 | H42: 4.2120764 | I42: 3.9473309 | J42: -23.140697 | K42: -83.452033 | L42: 19.208546 | M42: 17.333171 | N42: 79.615477 | O42: 76.037526 | P42: 239079.34 | Q42: 193572.8 | R42: 765.54682 | S42: 0 | T42: 0 | U42: 0 | V42: 1 | W42: 0 | X42: 0.97979815 | Y42: 0 | Z42: 0.00056887345 | AA42: 8.1948978e-05 | AB42: 0.0030977716 | AC42: 0 | AD42: 0.0063232008 | AE42: -0.0002056697 | AF42: 1 | AG42: 1 | AH42: 1 | AI42: 1 | AJ42: 1 | AK42: 1 | AL42: 1 | AM42: 0 | AN42: 0 | AO42: 05:-100--75 | AP42: =-100--75 -> -25 | AQ42: 2322873.6 | AR42: 12 | AS42: 0 | AT42: 0 | AU42: 0 | AV42: 100 | AW42: 100 | AX42: 0
A43: 4.3 | B43: 0.98934761 | C43: 27.432198 | D43: 12.059911 | E43: 0.026366898 | F43: 0.010652392 | G43: 0 | H43: 4.2156057 | I43: 4.0468354 | J43: -26.571952 | K43: -57.932898 | L43: 22.942908 | M43: 16.539877 | N43: 78.81004 | O43: 71.950413 | P43: 243355.1 | Q43: 154364.35 | R43: 774.26727 | S43: 0 | T43: 0 | U43: 0.08578669 | V43: 1 | W43: 0 | X43: 0.62733873 | Y43: 0 | Z43: 0.0010454839 | AA43: 8.0260524e-05 | AB43: 0.002838117 | AC43: 0 | AD43: 0.0066885165 | AE43: -0.01057977 | AF43: 0.95511436 | AG43: 0.99661868 | AH43: 1 | AI43: 1 | AJ43: 1 | AK43: 1 | AL43: 1 | AM43: 0 | AN43: 0 | AO43: 06:-75--50 | AP43: =-75--50 -> -25 | AQ43: 13275334 | AR43: 86 | AS43: 0 | AT43: 0 | AU43: 0 | AV43: 100 | AW43: 100 | AX43: 0
A44: 4.3 | B44: 0.99372916 | C44: 2.6972 | D44: 7.2708179 | E44: 0.0022759411 | F44: 0.0062708358 | G44: 0 | H44: 4.0130121 | I44: 4.124413 | J44: -49.480846 | K44: -32.313402 | L44: 17.404312 | M44: 15.583407 | N44: 77.145531 | O44: 74.947546 | P44: 263811.83 | Q44: 223674.18 | R44: 781.04806 | S44: 0 | T44: 0 | U44: 0.0047215107 | V44: 1 | W44: 0 | X44: 0.5513044 | Y44: 0 | Z44: 0.00047030754 | AA44: 5.2422737e-05 | AB44: 0.0026297805 | AC44: 3.0524064e-07 | AD44: 0.0031180062 | AE44: -0.014876592 | AF44: 0.97128747 | AG44: 0.99033606 | AH44: 0.99969298 | AI44: 0.99969298 | AJ44: 1 | AK44: 1 | AL44: 1 | AM44: 0 | AN44: 0 | AO44: 07:-50--25 | AP44: =-50--25 -> -25 | AQ44: 1.9616225e+08 | AR44: 877 | AS44: 0 | AT44: 0 | AU44: 0 | AV44: 100 | AW44: 100 | AX44: 0
A45: 4.3 | B45: 0.99009166 | C45: 10.272771 | D45: 11.262988 | E45: 0.0089923175 | F45: 0.0099083449 | G45: 0 | H45: 4.1238862 | I45: 4.1160383 | J45: -38.460418 | K45: -8.5277656 | L45: 16.482102 | M45: 15.981391 | N45: 74.178548 | O45: 72.813875 | P45: 262234.84 | Q45: 241347.2 | R45: 781.322 | S45: 0 | T45: 0 | U45: 0.019790794 | V45: 1 | W45: 0 | X45: 0.71355362 | Y45: 0 | Z45: 0.00038681295 | AA45: 5.6034209e-05 | AB45: 0.0026655013 | AC45: 1.5856603e-07 | AD45: 0.0067998237 | AE45: -0.013449962 | AF45: 0.9617047 | AG45: 0.99077334 | AH45: 0.999711 | AI45: 0.99996719 | AJ45: 1 | AK45: 1 | AL45: 1 | AM45: 0 | AN45: 0 | AO45: 08:-25-0 | AP45: =-25-0 -> -25 | AQ45: 2.0574849e+09 | AR45: 8525 | AS45: 0 | AT45: 0 | AU45: 0 | AV45: 100 | AW45: 100 | AX45: 0
A46: 4.3 | B46: 0.98630216 | C46: 18.568596 | D46: 15.253884 | E46: 0.016971762 | F46: 0.013697841 | G46: 0 | H46: 4.197132 | I46: 4.0368714 | J46: -27.530438 | K46: 15.60855 | L46: 16.293509 | M46: 16.097029 | N46: 70.91269 | O46: 68.870179 | P46: 263734.72 | Q46: 244852.35 | R46: 782.53188 | S46: 0 | T46: 0 | U46: 0.045171012 | V46: 1 | W46: 0 | X46: 0.80546192 | Y46: 0 | Z46: 0.00037783382 | AA46: 6.0192294e-05 | AB46: 0.0028370435 | AC46: 1.495745e-06 | AD46: 0.010421262 | AE46: -0.00041697403 | AF46: 0.88752184 | AG46: 0.97232014 | AH46: 0.99769674 | AI46: 0.99965008 | AJ46: 1 | AK46: 1 | AL46: 1 | AM46: 0 | AN46: 0 | AO46: 09:0-25 | AP46: 0-25 | AQ46: 1.1257087e+10 | AR46: 45975 | AS46: 0 | AT46: 0 | AU46: 0 | AV46: 100 | AW46: 100 | AX46: 0
A47: 4.3 | B47: 0.98060834 | C47: 30.159799 | D47: 20.941787 | E47: 0.02947039 | F47: 0.01939166 | G47: 0 | H47: 4.2299296 | I47: 3.9089805 | J47: -21.580224 | K47: 38.014005 | L47: 15.480645 | M47: 16.321129 | N47: 68.001822 | O47: 64.841484 | P47: 277166.09 | Q47: 257802.07 | R47: 783.21829 | S47: 0 | T47: 0 | U47: 0.045054977 | V47: 1 | W47: 0 | X47: 0.82871998 | Y47: 0 | Z47: 0.00037299548 | AA47: 6.2396994e-05 | AB47: 0.0030315717 | AC47: 5.0815919e-06 | AD47: 0.0159196 | AE47: 0.019986443 | AF47: 0.77431859 | AG47: 0.93880174 | AH47: 0.99518497 | AI47: 0.9992447 | AJ47: 1 | AK47: 1 | AL47: 1 | AM47: 0 | AN47: 0 | AO47: 10:25-50 | AP47: 25-50 | AQ47: 2.6377019e+10 | AR47: 102315 | AS47: 0 | AT47: 0 | AU47: 0 | AV47: 100 | AW47: 100 | AX47: 0
A48: 4.3 | B48: 0.97389312 | C48: 40.149087 | D48: 27.199293 | E48: 0.041874133 | F48: 0.026106875 | G48: 0 | H48: 4.4272407 | I48: 3.8675649 | J48: -11.88364 | K48: 61.818588 | L48: 15.319514 | M48: 17.356706 | N48: 67.606811 | O48: 64.383644 | P48: 280265.73 | Q48: 260583.52 | R48: 782.62838 | S48: 0 | T48: 0 | U48: 0.029567307 | V48: 1 | W48: 0 | X48: 0.78719709 | Y48: 0 | Z48: 0.00037399172 | AA48: 7.9844471e-05 | AB48: 0.0031769512 | AC48: 6.4092633e-06 | AD48: 0.022469664 | AE48: 0.0195067 | AF48: 0.77029743 | AG48: 0.9596833 | AH48: 0.99534206 | AI48: 0.9993421 | AJ48: 1 | AK48: 1 | AL48: 1 | AM48: 0 | AN48: 0 | AO48: 11:50-75 | AP48: 50-75 | AQ48: 2.2196504e+10 | AR48: 85180 | AS48: 0 | AT48: 0 | AU48: 0 | AV48: 100 | AW48: 100 | AX48: 0
A49: 4.3 | B49: 0.96868969 | C49: 42.720599 | D49: 31.732163 | E49: 0.045374116 | F49: 0.031310308 | G49: 0 | H49: 4.6748624 | I49: 3.876234 | J49: -4.757858 | K49: 86.11073 | L49: 15.269437 | M49: 17.80654 | N49: 67.682094 | O49: 64.283091 | P49: 281346.03 | Q49: 261471.15 | R49: 781.28007 | S49: 0 | T49: 0 | U49: 0.037970816 | V49: 1 | W49: 0 | X49: 0.70634876 | Y49: 0 | Z49: 0.00037464345 | AA49: 0.000101898 | AB49: 0.003284246 | AC49: 1.0011225e-05 | AD49: 0.027539494 | AE49: 0.020944397 | AF49: 0.7255838 | AG49: 0.96035673 | AH49: 0.9942031 | AI49: 0.99909325 | AJ49: 1 | AK49: 1 | AL49: 1 | AM49: 0 | AN49: 0 | AO49: 12:75-100 | AP49: 75-100 | AQ49: 1.3715731e+10 | AR49: 52456 | AS49: 0 | AT49: 0 | AU49: 0 | AV49: 100 | AW49: 100 | AX49: 0
A50: 4.3 | B50: 0.96474775 | C50: 43.681735 | D50: 34.992225 | E50: 0.046719362 | F50: 0.035252248 | G50: 0 | H50: 4.8434827 | I50: 3.807434 | J50: -1.3594117 | K50: 111.23674 | L50: 15.526546 | M50: 18.29082 | N50: 69.560573 | O50: 65.196329 | P50: 276553.64 | Q50: 257166.42 | R50: 780.71302 | S50: 0 | T50: 0 | U50: 0.039785194 | V50: 1 | W50: 0 | X50: 0.62199301 | Y50: 0 | Z50: 0.00037584798 | AA50: 0.0001336259 | AB50: 0.0034024579 | AC50: 1.6828302e-05 | AD50: 0.031323473 | AE50: 0.033325074 | AF50: 0.6266057 | AG50: 0.95634481 | AH50: 0.99256606 | AI50: 0.99872658 | AJ50: 1 | AK50: 1 | AL50: 1 | AM50: 0 | AN50: 0 | AO50: 13:100-125 | AP50: 100-125 | AQ50: 7.047903e+09 | AR50: 27406 | AS50: 0 | AT50: 0 | AU50: 0 | AV50: 100 | AW50: 100 | AX50: 0
A51: 4.3 | B51: 0.96091175 | C51: 42.096706 | D51: 38.027071 | E51: 0.044511922 | F51: 0.039088254 | G51: 0 | H51: 4.9315036 | I51: 3.6961975 | J51: 1.0148037 | K51: 134.98966 | L51: 15.352613 | M51: 19.417138 | N51: 70.84739 | O51: 64.873088 | P51: 279295.95 | Q51: 260089.7 | R51: 779.89281 | S51: 0 | T51: 0 | U51: 0.058809219 | V51: 1 | W51: 0 | X51: 0.64064484 | Y51: 0 | Z51: 0.00037431524 | AA51: 0.00014527289 | AB51: 0.0034345077 | AC51: 3.4003484e-05 | AD51: 0.03510014 | AE51: 0.058873943 | AF51: 0.4937243 | AG51: 0.92881813 | AH51: 0.98536312 | AI51: 0.99845284 | AJ51: 1 | AK51: 1 | AL51: 1 | AM51: 0 | AN51: 0 | AO51: 14:125-150 | AP51: 125-150 | AQ51: 2.983749e+09 | AR51: 11472 | AS51: 0 | AT51: 0 | AU51: 0 | AV51: 100 | AW51: 100 | AX51: 0
A52: 4.3 | B52: 0.95713534 | C52: 43.974174 | D52: 40.887378 | E52: 0.047132849 | F52: 0.04286466 | G52: 0 | H52: 5.0881617 | I52: 3.667939 | J52: 12.727544 | K52: 159.19145 | L52: 15.009271 | M52: 20.173603 | N52: 73.885734 | O52: 66.483514 | P52: 285506.84 | Q52: 266044.99 | R52: 778.89373 | S52: 0 | T52: 0 | U52: 0.018776664 | V52: 1 | W52: 0 | X52: 0.66670176 | Y52: 0 | Z52: 0.00037301546 | AA52: 0.00021407522 | AB52: 0.0034923012 | AC52: 6.0698153e-05 | AD52: 0.038724555 | AE52: 0.07629897 | AF52: 0.39665848 | AG52: 0.89240437 | AH52: 0.97360936 | AI52: 0.99656065 | AJ52: 1 | AK52: 1 | AL52: 1 | AM52: 0 | AN52: 0 | AO52: 15:150-175 | AP52: 150-175 | AQ52: 6.6245203e+08 | AR52: 2490 | AS52: 0 | AT52: 0 | AU52: 0 | AV52: 100 | AW52: 100 | AX52: 0
A53: 4.3 | B53: 0.95312325 | C53: 55.301 | D53: 43.793211 | E53: 0.064899799 | F53: 0.046876748 | G53: 0 | H53: 5.1828649 | I53: 3.6615472 | J53: 26.721662 | K53: 183.23274 | L53: 14.425865 | M53: 20.14771 | N53: 78.208501 | O53: 68.105276 | P53: 296805.85 | Q53: 276792.32 | R53: 779.56453 | S53: 0 | T53: 0 | U53: 0 | V53: 1 | W53: 0 | X53: 0.65481309 | Y53: 0 | Z53: 0.00039321549 | AA53: 0.00029980357 | AB53: 0.0036021195 | AC53: 0.00017322807 | AD53: 0.042408366 | AE53: 0.10048405 | AF53: 0.26675475 | AG53: 0.7917514 | AH53: 0.92892011 | AI53: 0.98513131 | AJ53: 1 | AK53: 1 | AL53: 1 | AM53: 0 | AN53: 0 | AO53: 16:175-200 | AP53: 175-200 | AQ53: 1.2012787e+08 | AR53: 434 | AS53: 0 | AT53: 0 | AU53: 0 | AV53: 100 | AW53: 100 | AX53: 0
A54: 4.3 | B54: 0.95413155 | C54: 53.736279 | D54: 43.075521 | E54: 0.062214788 | F54: 0.045868453 | G54: 0 | H54: 5.2404386 | I54: 3.6507389 | J54: 30.826975 | K54: 207.93763 | L54: 15.518872 | M54: 20.380193 | N54: 83.310511 | O54: 69.451672 | P54: 273149.38 | Q54: 257277.22 | R54: 776.7971 | S54: 0 | T54: 0 | U54: 0 | V54: 1 | W54: 0 | X54: 0.51070676 | Y54: 0 | Z54: 0.00043522976 | AA54: 0.00032085648 | AB54: 0.0039489034 | AC54: 0.00038778712 | AD54: 0.040775661 | AE54: 0.12908079 | AF54: 0.12918379 | AG54: 0.65268542 | AH54: 0.83717966 | AI54: 0.96337046 | AJ54: 1 | AK54: 1 | AL54: 1 | AM54: 0 | AN54: 0 | AO54: 17:200-225 | AP54: 200-225 | AQ54: 15951188 | AR54: 62 | AS54: 0 | AT54: 0 | AU54: 0 | AV54: 100 | AW54: 100 | AX54: 0
A55: 4.3 | B55: 0.95616787 | C55: 0 | D55: 41.600419 | E55: 0 | F55: 0.043832134 | G55: 0 | H55: 5.25 | I55: 3.6406663 | J55: 17.662921 | K55: 233.95346 | L55: 18.196645 | M55: 20.999142 | N55: 95 | O55: 75.144084 | P55: 219482.43 | Q55: 219482.19 | R55: 794 | S55: 0 | T55: 0 | U55: 0 | V55: 1 | W55: 0 | X55: 0 | Y55: 0 | Z55: 0.00035712854 | AA55: 0.00011713423 | AB55: 0.0048422815 | AC55: 0.0018443456 | AD55: 0.036671225 | AE55: 0.2325131 | AF55: 0 | AG55: 0 | AH55: 0 | AI55: 1 | AJ55: 1 | AK55: 1 | AL55: 1 | AM55: 0 | AN55: 0 | AO55: 18:225-250 | AP55: 225-250 | AQ55: 658446.57 | AR55: 3 | AS55: 0 | AT55: 0 | AU55: 0 | AV55: 100 | AW55: 100 | AX55: 0
A59: WALA [12,24) | C59: NonCashWindow
A60: modelId | B60: SFACTOR_PREPAY_TRACKING_CPR | C60: PREPAY_CPR1 | D60: PREPAY_TRACKING_CPR1 | E60: PREPAY_SMM1 | F60: PREPAY_TRACKING_SMM1 | G60: PCT_LOANTYPE | H60: _ORIGNOTERATE | I60: _ZEROSATO | J60: _SATO | K60: _REFI_INCENTIVE_Fixed | L60: _Fixed_cost | M60: _LOANAGE | N60: _LTV | O60: _CLTV | P60: _AVG_LOANSIZE_SCHAMBALANCE | Q60: _WACLS | R60: _FICO | S60: PCT_ISSECONDLIEN | T60: _OrigCombLTV | U60: PCT_SVC | V60: PCT_TPO | W60: PCT_GEO | X60: PCT_LOANPURPOSE | Y60: PCT_OCC | Z60: curtailsmm | AA60: defaultsmm | AB60: toverSmm | AC60: cashoutSmm | AD60: refiSmm | AE60: cumHPA | AF60: cumHPA05Pct | AG60: cumHPA15Pct | AH60: cumHPA20Pct | AI60: cumHPA25Pct | AJ60: cumHPA30Pct | AK60: cumHPA35Pct | AL60: cumHPA40Pct | AM60: adjtoverSmm | AN60: adjRefiSmm | AO60: groupByColumn | AP60: curve | AQ60: Balance | AR60: LoanCount | AS60: PCT_BROKER | AT60: PCT_CORRES | AU60: PCT_NonRETAIL | AV60: PCT_RETAIL | AW60: PCT_CashWindow | AX60: PCT_NonCashWindow
A61: 4.3 | B61: 0.99502774 | C61: 0 | D61: 5.8062099 | E61: 0 | F61: 0.004972258 | G61: 0 | H61: 4.125 | I61: 4.0914466 | J61: -39.2924 | K61: -107.58291 | L61: 22.464931 | M61: 18.498075 | N61: 80 | O61: 77.967109 | P61: 177738.07 | Q61: 177737.55 | R61: 782 | S61: 0 | T61: 0 | U61: 0 | V61: 1 | W61: 0 | X61: 0 | Y61: 0 | Z61: 0.00035354267 | AA61: 1.3394992e-05 | AB61: 0.0038048394 | AC61: 0 | AD61: 0.00080046846 | AE61: -0.0012605143 | AF61: 1 | AG61: 1 | AH61: 1 | AI61: 1 | AJ61: 1 | AK61: 1 | AL61: 1 | AM61: 0 | AN61: 0 | AO61: 04:-125--100 | AP61: =-125--100 -> -25 | AQ61: 710950.18 | AR61: 4 | AS61: 0 | AT61: 0 | AU61: 0 | AV61: 100 | AW61: 0 | AX61: 100
A62: 4.3 | B62: 0.99155722 | C62: 2.1576304 | D62: 9.6738777 | E62: 0.0018160553 | F62: 0.0084427815 | G62: 0 | H62: 4.1889411 | I62: 4.0657978 | J62: -27.8585 | K62: -83.219819 | L62: 18.879883 | M62: 17.169202 | N62: 76.77312 | O62: 76.563737 | P62: 225230.39 | Q62: 199055.97 | R62: 782.10614 | S62: 0 | T62: 0 | U62: 0 | V62: 1 | W62: 0 | X62: 0.13217823 | Y62: 0 | Z62: 0.00037752422 | AA62: 4.2870696e-05 | AB62: 0.0031142536 | AC62: 0 | AD62: 0.0049081176 | AE62: -0.024099846 | AF62: 1 | AG62: 1 | AH62: 1 | AI62: 1 | AJ62: 1 | AK62: 1 | AL62: 1 | AM62: 0 | AN62: 0 | AO62: 05:-100--75 | AP62: =-100--75 -> -25 | AQ62: 2985839.6 | AR62: 15 | AS62: 0 | AT62: 0 | AU62: 0 | AV62: 100 | AW62: 0 | AX62: 100
A63: 4.3 | B63: 0.99550634 | C63: 8.8452661 | D63: 5.2610892 | E63: 0.0076879413 | F63: 0.0044936552 | G63: 0 | H63: 3.8754078 | I63: 4.1426231 | J63: -62.065276 | K63: -58.362228 | L63: 20.533306 | M63: 15.317372 | N63: 78.746357 | O63: 74.733621 | P63: 253658.83 | Q63: 183215.2 | R63: 781.71532 | S63: 0 | T63: 0 | U63: 0 | V63: 1 | W63: 0 | X63: 0.15768331 | Y63: 0 | Z63: 0.00071264658 | AA63: 7.5896281e-05 | AB63: 0.0026374621 | AC63: 0 | AD63: 0.0010676405 | AE63: -0.021212522 | AF63: 0.99566702 | AG63: 1 | AH63: 1 | AI63: 1 | AJ63: 1 | AK63: 1 | AL63: 1 | AM63: 0 | AN63: 0 | AO63: 06:-75--50 | AP63: =-75--50 -> -25 | AQ63: 54598129 | AR63: 298 | AS63: 0 | AT63: 0 | AU63: 0 | AV63: 100 | AW63: 0 | AX63: 100
A64: 4.3 | B64: 0.99412404 | C64: 6.1091154 | D64: 6.8276779 | E64: 0.0052393001 | F64: 0.0058759588 | G64: 0 | H64: 3.9337332 | I64: 4.1358934 | J64: -57.987062 | K64: -33.504741 | L64: 16.96728 | M64: 15.448122 | N64: 74.279276 | O64: 72.186536 | P64: 264061.52 | Q64: 230524.08 | R64: 783.86911 | S64: 0 | T64: 0 | U64: 0.0022841412 | V64: 1 | W64: 0 | X64: 0.30870795 | Y64: 0 | Z64: 0.0004416903 | AA64: 6.3523872e-05 | AB64: 0.0027300309 | AC64: 7.7476567e-09 | AD64: 0.0026406919 | AE64: -0.012060826 | AF64: 0.97597851 | AG64: 0.99876642 | AH64: 1 | AI64: 1 | AJ64: 1 | AK64: 1 | AL64: 1 | AM64: 0 | AN64: 0 | AO64: 07:-50--25 | AP64: =-50--25 -> -25 | AQ64: 5.8691431e+08 | AR64: 2546 | AS64: 0 | AT64: 0 | AU64: 0 | AV64: 100 | AW64: 0 | AX64: 100
A65: 4.3 | B65: 0.98985186 | C65: 7.5476108 | D65: 11.520542 | E65: 0.0065183615 | F65: 0.010148138 | G65: 0 | H65: 4.1214877 | I65: 4.1334079 | J65: -40.061891 | K65: -8.3611912 | L65: 15.571414 | M65: 15.625428 | N65: 72.112709 | O65: 70.727766 | P65: 278786.73 | Q65: 255296.92 | R65: 783.58961 | S65: 0 | T65: 0 | U65: 0.002846396 | V65: 1 | W65: 0 | X65: 0.58850586 | Y65: 0 | Z65: 0.00038877256 | AA65: 6.7447233e-05 | AB65: 0.0026347468 | AC65: 1.1532695e-08 | AD65: 0.0070571457 | AE65: -0.015546707 | AF65: 0.97687925 | AG65: 0.99866327 | AH65: 0.99989613 | AI65: 1 | AJ65: 1 | AK65: 1 | AL65: 1 | AM65: 0 | AN65: 0 | AO65: 08:-25-0 | AP65: =-25-0 -> -25 | AQ65: 4.5335627e+09 | AR65: 17758 | AS65: 0 | AT65: 0 | AU65: 0 | AV65: 100 | AW65: 0 | AX65: 100
A66: 4.3 | B66: 0.98591472 | C66: 11.797693 | D66: 15.652506 | E66: 0.010406892 | F66: 0.014085285 | G66: 0 | H66: 4.2420115 | I66: 4.0979455 | J66: -27.984199 | K66: 15.32746 | L66: 15.34839 | M66: 16.027786 | N66: 67.860579 | O66: 66.32759 | P66: 279876.34 | Q66: 259921.55 | R66: 784.8208 | S66: 0 | T66: 0 | U66: 0.0093631669 | V66: 1 | W66: 0 | X66: 0.76846682 | Y66: 0 | Z66: 0.00037706139 | AA66: 7.1435677e-05 | AB66: 0.0027606002 | AC66: 4.1713309e-07 | AD66: 0.010875756 | AE66: -0.010170756 | AF66: 0.94085711 | AG66: 0.99349299 | AH66: 0.99919156 | AI66: 0.99978821 | AJ66: 1 | AK66: 1 | AL66: 1 | AM66: 0 | AN66: 0 | AO66: 09:0-25 | AP66: 0-25 | AQ66: 2.3068557e+10 | AR66: 88752 | AS66: 0 | AT66: 0 | AU66: 0 | AV66: 100 | AW66: 0 | AX66: 100
A67: 4.3 | B67: 0.98030231 | C67: 17.55991 | D67: 21.237349 | E67: 0.015962752 | F67: 0.019697688 | G67: 0 | H67: 4.3594907 | I67: 4.0141205 | J67: -17.69393 | K67: 38.111594 | L67: 15.143014 | M67: 17.022507 | N67: 65.665989 | O67: 63.523641 | P67: 283223.76 | Q67: 263596.7 | R67: 785.18895 | S67: 0 | T67: 0 | U67: 0.011352927 | V67: 1 | W67: 0 | X67: 0.83557602 | Y67: 0 | Z67: 0.00037495601 | AA67: 8.5276546e-05 | AB67: 0.0030262632 | AC67: 1.9782436e-06 | AD67: 0.016209199 | AE67: 0.00047233564 | AF67: 0.87196598 | AG67: 0.98161997 | AH67: 0.99805301 | AI67: 0.99951235 | AJ67: 1 | AK67: 1 | AL67: 1 | AM67: 0 | AN67: 0 | AO67: 10:25-50 | AP67: 25-50 | AQ67: 4.6900707e+10 | AR67: 177926 | AS67: 0 | AT67: 0 | AU67: 0 | AV67: 100 | AW67: 0 | AX67: 100
A68: 4.3 | B68: 0.97383997 | C68: 25.676066 | D68: 27.246962 | E68: 0.024424861 | F68: 0.026160032 | G68: 0 | H68: 4.5363795 | I68: 3.9428542 | J68: -8.837139 | K68: 62.97282 | L68: 15.52194 | M68: 17.988233 | N68: 66.904798 | O68: 64.127384 | P68: 276197.65 | Q68: 257200.95 | R68: 784.49164 | S68: 0 | T68: 0 | U68: 0.0091287563 | V68: 1 | W68: 0 | X68: 0.81147446 | Y68: 0 | Z68: 0.00037766527 | AA68: 0.00011707935 | AB68: 0.0032507888 | AC68: 4.6677129e-06 | AD68: 0.022409817 | AE68: 0.0092320769 | AF68: 0.80256162 | AG68: 0.97617681 | AH68: 0.99685625 | AI68: 0.99925923 | AJ68: 1 | AK68: 1 | AL68: 1 | AM68: 0 | AN68: 0 | AO68: 11:50-75 | AP68: 50-75 | AQ68: 5.9067741e+10 | AR68: 229656 | AS68: 0 | AT68: 0 | AU68: 0 | AV68: 100 | AW68: 0 | AX68: 100
A69: 4.3 | B69: 0.96838283 | C69: 31.506465 | D69: 31.991219 | E69: 0.031043832 | F69: 0.031617165 | G69: 0 | H69: 4.7068362 | I69: 3.8993735 | J69: -1.7327127 | K69: 86.340718 | L69: 15.316941 | M69: 17.929493 | N69: 66.053577 | O69: 62.805532 | P69: 279970.53 | Q69: 260672.83 | R69: 783.73187 | S69: 0 | T69: 0 | U69: 0.010820637 | V69: 1 | W69: 0 | X69: 0.80359528 | Y69: 0 | Z69: 0.00037747068 | AA69: 0.00014268261 | AB69: 0.0033466866 | AC69: 1.0009337e-05 | AD69: 0.027740301 | AE69: 0.018643281 | AF69: 0.71583084 | AG69: 0.9655081 | AH69: 0.99427538 | AI69: 0.99900877 | AJ69: 1 | AK69: 1 | AL69: 1 | AM69: 0 | AN69: 0 | AO69: 12:75-100 | AP69: 75-100 | AQ69: 5.2624892e+10 | AR69: 201881 | AS69: 0 | AT69: 0 | AU69: 0 | AV69: 100 | AW69: 0 | AX69: 100
A70: 4.3 | B70: 0.96402649 | C70: 35.202875 | D70: 35.573041 | E70: 0.035513149 | F70: 0.035973507 | G70: 0 | H70: 4.875273 | I70: 3.8240351 | J70: 2.8640941 | K70: 111.62061 | L70: 15.591368 | M70: 18.436838 | N70: 68.031409 | O70: 63.715734 | P70: 274819.08 | Q70: 256099.69 | R70: 782.14585 | S70: 0 | T70: 0 | U70: 0.010932085 | V70: 1 | W70: 0 | X70: 0.75570179 | Y70: 0 | Z70: 0.00037801051 | AA70: 0.00019942512 | AB70: 0.003518881 | AC70: 2.2498401e-05 | AD70: 0.031854677 | AE70: 0.034409915 | AF70: 0.58562118 | AG70: 0.94979627 | AH70: 0.99044619 | AI70: 0.99804399 | AJ70: 1 | AK70: 1 | AL70: 1 | AM70: 0 | AN70: 0 | AO70: 13:100-125 | AP70: 100-125 | AQ70: 3.0215665e+10 | AR70: 117984 | AS70: 0 | AT70: 0 | AU70: 0 | AV70: 100 | AW70: 0 | AX70: 100
A71: 4.3 | B71: 0.96002414 | C71: 35.292652 | D71: 38.710534 | E71: 0.035624578 | F71: 0.03997586 | G71: 0 | H71: 4.948392 | I71: 3.7110585 | J71: 4.1983428 | K71: 134.92879 | L71: 15.244953 | M71: 19.350509 | N71: 68.322934 | O71: 62.19156 | P71: 281087.83 | Q71: 261925.42 | R71: 781.44083 | S71: 0 | T71: 0 | U71: 0.012081384 | V71: 1 | W71: 0 | X71: 0.77661138 | Y71: 0 | Z71: 0.00037698949 | AA71: 0.00024306139 | AB71: 0.0035621478 | AC71: 5.029033e-05 | AD71: 0.035743357 | AE71: 0.064840859 | AF71: 0.42223724 | AG71: 0.90980069 | AH71: 0.9798565 | AI71: 0.99714418 | AJ71: 1 | AK71: 1 | AL71: 1 | AM71: 0 | AN71: 0 | AO71: 14:125-150 | AP71: 125-150 | AQ71: 1.4091588e+10 | AR71: 53800 | AS71: 0 | AT71: 0 | AU71: 0 | AV71: 100 | AW71: 0 | AX71: 100
A72: 4.3 | B72: 0.95692142 | C72: 34.084038 | D72: 41.045723 | E72: 0.034136214 | F72: 0.043078579 | G72: 0 | H72: 5.1459085 | I72: 3.6852227 | J72: 19.40902 | K72: 160.59319 | L72: 15.643636 | M72: 19.608128 | N72: 73.20453 | O72: 65.656036 | P72: 273651.28 | Q72: 255259.41 | R72: 779.35191 | S72: 0 | T72: 0 | U72: 0.0112626 | V72: 1 | W72: 0 | X72: 0.86951356 | Y72: 0 | Z72: 0.00038342289 | AA72: 0.00035448863 | AB72: 0.0036686535 | AC72: 6.9191811e-05 | AD72: 0.038602807 | AE72: 0.079609892 | AF72: 0.33058698 | AG72: 0.87412835 | AH72: 0.97213331 | AI72: 0.99550187 | AJ72: 1 | AK72: 1 | AL72: 1 | AM72: 0 | AN72: 0 | AO72: 15:150-175 | AP72: 150-175 | AQ72: 3.4406416e+09 | AR72: 13479 | AS72: 0 | AT72: 0 | AU72: 0 | AV72: 100 | AW72: 0 | AX72: 100
A73: 4.3 | B73: 0.9532454 | C73: 33.66536 | D73: 43.706713 | E73: 0.033626457 | F73: 0.046754602 | G73: 0 | H73: 5.2300295 | I73: 3.658819 | J73: 27.510522 | K73: 182.55438 | L73: 14.769761 | M73: 20.16457 | N73: 75.884241 | O73: 66.853702 | P73: 289325.66 | Q73: 270360.54 | R73: 778.1221 | S73: 0 | T73: 0 | U73: 0.01385278 | V73: 1 | W73: 0 | X73: 0.85221978 | Y73: 0 | Z73: 0.00038805999 | AA73: 0.00052770323 | AB73: 0.0036357914 | AC73: 0.00013058948 | AD73: 0.042072443 | AE73: 0.096594918 | AF73: 0.25503784 | AG73: 0.81629256 | AH73: 0.94230196 | AI73: 0.99203387 | AJ73: 1 | AK73: 1 | AL73: 1 | AM73: 0 | AN73: 0 | AO73: 16:175-200 | AP73: 175-200 | AQ73: 8.2784399e+08 | AR73: 3062 | AS73: 0 | AT73: 0 | AU73: 0 | AV73: 100 | AW73: 0 | AX73: 100
A74: 4.3 | B74: 0.95105383 | C74: 28.261047 | D74: 45.240284 | E74: 0.027298498 | F74: 0.04894617 | G74: 0 | H74: 5.2464187 | I74: 3.6917229 | J74: 34.717274 | K74: 210.09061 | L74: 15.062819 | M74: 19.593819 | N74: 85.791659 | O74: 73.984502 | P74: 285262.2 | Q74: 265099.5 | R74: 777.48058 | S74: 0 | T74: 0 | U74: 0.018733181 | V74: 1 | W74: 0 | X74: 0.76619444 | Y74: 0 | Z74: 0.00039355746 | AA74: 0.00055744886 | AB74: 0.0040135355 | AC74: 0.00029981246 | AD74: 0.0436818 | AE74: 0.12009367 | AF74: 0.14854477 | AG74: 0.6966005 | AH74: 0.85633043 | AI74: 0.97462642 | AJ74: 1 | AK74: 1 | AL74: 1 | AM74: 0 | AN74: 0 | AO74: 17:200-225 | AP74: 200-225 | AQ74: 1.0975119e+08 | AR74: 414 | AS74: 0 | AT74: 0 | AU74: 0 | AV74: 100 | AW74: 0 | AX74: 100
A75: 4.3 | B75: 0.95106712 | C75: 0.36622219 | D75: 45.231099 | E75: 0.00030569862 | F75: 0.048932877 | G75: 0 | H75: 5.3142705 | I75: 3.6726424 | J75: 37.399005 | K75: 234.92882 | L75: 14.685726 | M75: 20.006516 | N75: 88.220187 | O75: 75.44366 | P75: 291527.89 | Q75: 271913.73 | R75: 780.63111 | S75: 0 | T75: 0 | U75: 0.02801204 | V75: 1 | W75: 0 | X75: 0.75461687 | Y75: 0 | Z75: 0.00039629672 | AA75: 0.000556465 | AB75: 0.0039214945 | AC75: 0.0003853902 | AD75: 0.043673215 | AE75: 0.12704695 | AF75: 0.07035943 | AG75: 0.65337731 | AH75: 0.82154449 | AI75: 0.9827527 | AJ75: 1 | AK75: 1 | AL75: 1 | AM75: 0 | AN75: 0 | AO75: 18:225-250 | AP75: 225-250 | AQ75: 39971319 | AR75: 147 | AS75: 0 | AT75: 0 | AU75: 0 | AV75: 100 | AW75: 0 | AX75: 100
A76: 4.3 | B76: 0.95286035 | C76: 34.576458 | D76: 43.978976 | E76: 0.034739567 | F76: 0.047139654 | G76: 0 | H76: 5.483312 | I76: 3.6729403 | J76: 47.39144 | K76: 265.60645 | L76: 14.27703 | M76: 20.573626 | N76: 88.917568 | O76: 76.022172 | P76: 295376.62 | Q76: 279697.78 | R76: 783.97378 | S76: 0 | T76: 0 | U76: 0 | V76: 1 | W76: 0 | X76: 0.94361767 | Y76: 0 | Z76: 0.00039082394 | AA76: 0.00063181953 | AB76: 0.0040903139 | AC76: 0.00017462634 | AD76: 0.041852053 | AE76: 0.12851392 | AF76: 0.099460969 | AG76: 0.56324578 | AH76: 0.94738828 | AI76: 1 | AJ76: 1 | AK76: 1 | AL76: 1 | AM76: 0 | AN76: 0 | AO76: 999:>= 250 | AP76: >= 250 | AQ76: 15942774 | AR76: 57 | AS76: 0 | AT76: 0 | AU76: 0 | AV76: 100 | AW76: 0 | AX76: 100
D80: =C1 -> BROKER | H80: =C19 -> CORRES | L80: =C38 -> CashWindow | P80: =C59 -> NonCashWindow
D81: =AO2 -> groupByColumn | E81: =E2 -> PREPAY_SMM1 | F81: CPR | H81: =AO20 -> groupByColumn | I81: =E20 -> PREPAY_SMM1 | J81: CPR | L81: =AO39 -> groupByColumn | M81: =E39 -> PREPAY_SMM1 | N81: CPR | P81: =AO60 -> groupByColumn | Q81: =E60 -> PREPAY_SMM1 | R81: CPR | U81: groupByColumn | V81: BROKER | W81: CORRES | X81: CashWindow | Y81: NonCashWindow
D82: =AO3 -> 06:-75--50 | E82: =E3 -> 0.0029157422 | F82: =100*(1-(1-E82)^12) -> 3.4433222 | H82: =AO21 -> 04:-125--100 | I82: =E21 -> 1.0083505e-08 | J82: =100*(1-(1-I82)^12) -> 1.2100205e-05 | L82: =AO40 -> 03:-150--125 | M82: =E40 -> 0 | N82: =100*(1-(1-M82)^12) -> 0 | P82: =AO61 -> 04:-125--100 | Q82: =E61 -> 0 | R82: =100*(1-(1-Q82)^12) -> 0 | U82: 03:-150--125 | V82: =VLOOKUP(U82,$D$81:$F$98,3,0) -> #N/A | W82: =VLOOKUP(U82,$H$81:$J$98,3,0) -> #N/A | X82: =VLOOKUP(U82,$L$81:$N$98,3,0) -> 0 | Y82: =VLOOKUP(U82,$P$81:$R$98,3,0) -> #N/A
D83: =AO4 -> 07:-50--25 | E83: =E4 -> 0.0022575225 | F83: =100*(1-(1-E83)^12) -> 2.6756426 | H83: =AO22 -> 05:-100--75 | I83: =E22 -> 0.0068667181 | J83: =100*(1-(1-I83)^12) -> 7.935874 | L83: =AO41 -> 04:-125--100 | M83: =E41 -> 0 | N83: =100*(1-(1-M83)^12) -> 0 | P83: =AO62 -> 05:-100--75 | Q83: =E62 -> 0.0018160553 | R83: =100*(1-(1-Q83)^12) -> 2.1576304 | U83: 04:-125--100 | V83: =VLOOKUP(U83,$D$81:$F$98,3,0) -> #N/A | W83: =VLOOKUP(U83,$H$81:$J$98,3,0) -> 1.2100205e-05 | X83: =VLOOKUP(U83,$L$81:$N$98,3,0) -> 0 | Y83: =VLOOKUP(U83,$P$81:$R$98,3,0) -> 0
D84: =AO5 -> 08:-25-0 | E84: =E5 -> 0.012984471 | F84: =100*(1-(1-E84)^12) -> 14.515411 | H84: =AO23 -> 06:-75--50 | I84: =E23 -> 0.0015380347 | J84: =100*(1-(1-I84)^12) -> 1.8301087 | L84: =AO42 -> 05:-100--75 | M84: =E42 -> 0.010697278 | N84: =100*(1-(1-M84)^12) -> 12.107777 | P84: =AO63 -> 06:-75--50 | Q84: =E63 -> 0.0076879413 | R84: =100*(1-(1-Q84)^12) -> 8.8452661 | U84: 05:-100--75 | V84: =VLOOKUP(U84,$D$81:$F$98,3,0) -> #N/A | W84: =VLOOKUP(U84,$H$81:$J$98,3,0) -> 7.935874 | X84: =VLOOKUP(U84,$L$81:$N$98,3,0) -> 12.107777 | Y84: =VLOOKUP(U84,$P$81:$R$98,3,0) -> 2.1576304
D85: =AO6 -> 09:0-25 | E85: =E6 -> 0.025939486 | F85: =100*(1-(1-E85)^12) -> 27.048998 | H85: =AO24 -> 07:-50--25 | I85: =E24 -> 0.0028845605 | J85: =100*(1-(1-I85)^12) -> 3.4070807 | L85: =AO43 -> 06:-75--50 | M85: =E43 -> 0.026366898 | N85: =100*(1-(1-M85)^12) -> 27.432198 | P85: =AO64 -> 07:-50--25 | Q85: =E64 -> 0.0052393001 | R85: =100*(1-(1-Q85)^12) -> 6.1091154 | U85: 06:-75--50 | V85: =VLOOKUP(U85,$D$81:$F$98,3,0) -> 3.4433222 | W85: =VLOOKUP(U85,$H$81:$J$98,3,0) -> 1.8301087 | X85: =VLOOKUP(U85,$L$81:$N$98,3,0) -> 27.432198 | Y85: =VLOOKUP(U85,$P$81:$R$98,3,0) -> 8.8452661
D86: =AO7 -> 10:25-50 | E86: =E7 -> 0.041027433 | F86: =100*(1-(1-E86)^12) -> 39.511307 | H86: =AO25 -> 08:-25-0 | I86: =E25 -> 0.0075443498 | J86: =100*(1-(1-I86)^12) -> 8.6868546 | L86: =AO44 -> 07:-50--25 | M86: =E44 -> 0.0022759411 | N86: =100*(1-(1-M86)^12) -> 2.6972 | P86: =AO65 -> 08:-25-0 | Q86: =E65 -> 0.0065183615 | R86: =100*(1-(1-Q86)^12) -> 7.5476108 | U86: 07:-50--25 | V86: =VLOOKUP(U86,$D$81:$F$98,3,0) -> 2.6756426 | W86: =VLOOKUP(U86,$H$81:$J$98,3,0) -> 3.4070807 | X86: =VLOOKUP(U86,$L$81:$N$98,3,0) -> 2.6972 | Y86: =VLOOKUP(U86,$P$81:$R$98,3,0) -> 6.1091154
D87: =AO8 -> 11:50-75 | E87: =E8 -> 0.051853975 | F87: =100*(1-(1-E87)^12) -> 47.215946 | H87: =AO26 -> 09:0-25 | I87: =E26 -> 0.017027448 | J87: =100*(1-(1-I87)^12) -> 18.623934 | L87: =AO45 -> 08:-25-0 | M87: =E45 -> 0.0089923175 | N87: =100*(1-(1-M87)^12) -> 10.272771 | P87: =AO66 -> 09:0-25 | Q87: =E66 -> 0.010406892 | R87: =100*(1-(1-Q87)^12) -> 11.797693 | U87: 08:-25-0 | V87: =VLOOKUP(U87,$D$81:$F$98,3,0) -> 14.515411 | W87: =VLOOKUP(U87,$H$81:$J$98,3,0) -> 8.6868546 | X87: =VLOOKUP(U87,$L$81:$N$98,3,0) -> 10.272771 | Y87: =VLOOKUP(U87,$P$81:$R$98,3,0) -> 7.5476108
D88: =AO9 -> 12:75-100 | E88: =E9 -> 0.049717463 | F88: =100*(1-(1-E88)^12) -> 45.770827 | H88: =AO27 -> 10:25-50 | I88: =E27 -> 0.029485364 | J88: =100*(1-(1-I88)^12) -> 30.172729 | L88: =AO46 -> 09:0-25 | M88: =E46 -> 0.016971762 | N88: =100*(1-(1-M88)^12) -> 18.568596 | P88: =AO67 -> 10:25-50 | Q88: =E67 -> 0.015962752 | R88: =100*(1-(1-Q88)^12) -> 17.55991 | U88: 09:0-25 | V88: =VLOOKUP(U88,$D$81:$F$98,3,0) -> 27.048998 | W88: =VLOOKUP(U88,$H$81:$J$98,3,0) -> 18.623934 | X88: =VLOOKUP(U88,$L$81:$N$98,3,0) -> 18.568596 | Y88: =VLOOKUP(U88,$P$81:$R$98,3,0) -> 11.797693
D89: =AO10 -> 13:100-125 | E89: =E10 -> 0.049919769 | F89: =100*(1-(1-E89)^12) -> 45.909203 | H89: =AO28 -> 11:50-75 | I89: =E28 -> 0.039071235 | J89: =100*(1-(1-I89)^12) -> 38.013898 | L89: =AO47 -> 10:25-50 | M89: =E47 -> 0.02947039 | N89: =100*(1-(1-M89)^12) -> 30.159799 | P89: =AO68 -> 11:50-75 | Q89: =E68 -> 0.024424861 | R89: =100*(1-(1-Q89)^12) -> 25.676066 | U89: 10:25-50 | V89: =VLOOKUP(U89,$D$81:$F$98,3,0) -> 39.511307 | W89: =VLOOKUP(U89,$H$81:$J$98,3,0) -> 30.172729 | X89: =VLOOKUP(U89,$L$81:$N$98,3,0) -> 30.159799 | Y89: =VLOOKUP(U89,$P$81:$R$98,3,0) -> 17.55991
D90: =AO11 -> 14:125-150 | E90: =E11 -> 0.050754696 | F90: =100*(1-(1-E90)^12) -> 46.476872 | H90: =AO29 -> 12:75-100 | I90: =E29 -> 0.0449524 | J90: =100*(1-(1-I90)^12) -> 42.416214 | L90: =AO48 -> 11:50-75 | M90: =E48 -> 0.041874133 | N90: =100*(1-(1-M90)^12) -> 40.149087 | P90: =AO69 -> 12:75-100 | Q90: =E69 -> 0.031043832 | R90: =100*(1-(1-Q90)^12) -> 31.506465 | U90: 11:50-75 | V90: =VLOOKUP(U90,$D$81:$F$98,3,0) -> 47.215946 | W90: =VLOOKUP(U90,$H$81:$J$98,3,0) -> 38.013898 | X90: =VLOOKUP(U90,$L$81:$N$98,3,0) -> 40.149087 | Y90: =VLOOKUP(U90,$P$81:$R$98,3,0) -> 25.676066
D91: =AO12 -> 15:150-175 | E91: =E12 -> 0.047514463 | F91: =100*(1-(1-E91)^12) -> 44.242836 | H91: =AO30 -> 13:100-125 | I91: =E30 -> 0.045562891 | J91: =100*(1-(1-I91)^12) -> 42.856373 | L91: =AO49 -> 12:75-100 | M91: =E49 -> 0.045374116 | N91: =100*(1-(1-M91)^12) -> 42.720599 | P91: =AO70 -> 13:100-125 | Q91: =E70 -> 0.035513149 | R91: =100*(1-(1-Q91)^12) -> 35.202875 | U91: 12:75-100 | V91: =VLOOKUP(U91,$D$81:$F$98,3,0) -> 45.770827 | W91: =VLOOKUP(U91,$H$81:$J$98,3,0) -> 42.416214 | X91: =VLOOKUP(U91,$L$81:$N$98,3,0) -> 42.720599 | Y91: =VLOOKUP(U91,$P$81:$R$98,3,0) -> 31.506465
D92: =AO13 -> 16:175-200 | E92: =E13 -> 0.061197489 | F92: =100*(1-(1-E92)^12) -> 53.130436 | H92: =AO31 -> 14:125-150 | I92: =E31 -> 0.048312694 | J92: =100*(1-(1-I92)^12) -> 44.800986 | L92: =AO50 -> 13:100-125 | M92: =E50 -> 0.046719362 | N92: =100*(1-(1-M92)^12) -> 43.681735 | P92: =AO71 -> 14:125-150 | Q92: =E71 -> 0.035624578 | R92: =100*(1-(1-Q92)^12) -> 35.292652 | U92: 13:100-125 | V92: =VLOOKUP(U92,$D$81:$F$98,3,0) -> 45.909203 | W92: =VLOOKUP(U92,$H$81:$J$98,3,0) -> 42.856373 | X92: =VLOOKUP(U92,$L$81:$N$98,3,0) -> 43.681735 | Y92: =VLOOKUP(U92,$P$81:$R$98,3,0) -> 35.202875
D93: =AO14 -> 17:200-225 | E93: =E14 -> 0.052273955 | F93: =100*(1-(1-E93)^12) -> 47.495831 | H93: =AO32 -> 15:150-175 | I93: =E32 -> 0.044353499 | J93: =100*(1-(1-I93)^12) -> 41.981394 | L93: =AO51 -> 14:125-150 | M93: =E51 -> 0.044511922 | N93: =100*(1-(1-M93)^12) -> 42.096706 | P93: =AO72 -> 15:150-175 | Q93: =E72 -> 0.034136214 | R93: =100*(1-(1-Q93)^12) -> 34.084038 | U93: 14:125-150 | V93: =VLOOKUP(U93,$D$81:$F$98,3,0) -> 46.476872 | W93: =VLOOKUP(U93,$H$81:$J$98,3,0) -> 44.800986 | X93: =VLOOKUP(U93,$L$81:$N$98,3,0) -> 42.096706 | Y93: =VLOOKUP(U93,$P$81:$R$98,3,0) -> 35.292652
D94: =AO15 -> 18:225-250 | E94: =E15 -> 0.050925887 | F94: =100*(1-(1-E94)^12) -> 46.592588 | H94: =AO33 -> 16:175-200 | I94: =E33 -> 0.054036721 | J94: =100*(1-(1-I94)^12) -> 48.655806 | L94: =AO52 -> 15:150-175 | M94: =E52 -> 0.047132849 | N94: =100*(1-(1-M94)^12) -> 43.974174 | P94: =AO73 -> 16:175-200 | Q94: =E73 -> 0.033626457 | R94: =100*(1-(1-Q94)^12) -> 33.66536 | U94: 15:150-175 | V94: =VLOOKUP(U94,$D$81:$F$98,3,0) -> 44.242836 | W94: =VLOOKUP(U94,$H$81:$J$98,3,0) -> 41.981394 | X94: =VLOOKUP(U94,$L$81:$N$98,3,0) -> 43.974174 | Y94: =VLOOKUP(U94,$P$81:$R$98,3,0) -> 34.084038
H95: =AO34 -> 17:200-225 | I95: =E34 -> 0.039465443 | J95: =100*(1-(1-I95)^12) -> 38.318358 | L95: =AO53 -> 16:175-200 | M95: =E53 -> 0.064899799 | N95: =100*(1-(1-M95)^12) -> 55.301 | P95: =AO74 -> 17:200-225 | Q95: =E74 -> 0.027298498 | R95: =100*(1-(1-Q95)^12) -> 28.261047 | U95: 16:175-200 | V95: =VLOOKUP(U95,$D$81:$F$98,3,0) -> 53.130436 | W95: =VLOOKUP(U95,$H$81:$J$98,3,0) -> 48.655806 | X95: =VLOOKUP(U95,$L$81:$N$98,3,0) -> 55.301 | Y95: =VLOOKUP(U95,$P$81:$R$98,3,0) -> 33.66536
H96: =AO35 -> 18:225-250 | I96: =E35 -> 0.021363411 | J96: =100*(1-(1-I96)^12) -> 22.828421 | L96: =AO54 -> 17:200-225 | M96: =E54 -> 0.062214788 | N96: =100*(1-(1-M96)^12) -> 53.736279 | P96: =AO75 -> 18:225-250 | Q96: =E75 -> 0.00030569862 | R96: =100*(1-(1-Q96)^12) -> 0.36622219 | U96: 17:200-225 | V96: =VLOOKUP(U96,$D$81:$F$98,3,0) -> 47.495831 | W96: =VLOOKUP(U96,$H$81:$J$98,3,0) -> 38.318358 | X96: =VLOOKUP(U96,$L$81:$N$98,3,0) -> 53.736279 | Y96: =VLOOKUP(U96,$P$81:$R$98,3,0) -> 28.261047
L97: =AO55 -> 18:225-250 | M97: =E55 -> 0 | N97: =100*(1-(1-M97)^12) -> 0 | U97: 18:225-250 | V97: =VLOOKUP(U97,$D$81:$F$98,3,0) -> 46.592588 | W97: =VLOOKUP(U97,$H$81:$J$98,3,0) -> 22.828421 | X97: =VLOOKUP(U97,$L$81:$N$98,3,0) -> 0 | Y97: =VLOOKUP(U97,$P$81:$R$98,3,0) -> 0.36622219

Sheet Baseline
A1: WALA [12,24) | C1: CORRES+CASHWINDOW | AS1: tover | AT1: cash | AW1: refi
A2: modelId | B2: SFACTOR_PREPAY_TRACKING_CPR | C2: PREPAY_CPR1 | D2: PREPAY_TRACKING_CPR1 | E2: PREPAY_SMM1 | F2: PREPAY_TRACKING_SMM1 | G2: PCT_LOANTYPE | H2: _ORIGNOTERATE | I2: _ZEROSATO | J2: _SATO | K2: _REFI_INCENTIVE_Fixed | L2: _Fixed_cost | M2: _LOANAGE | N2: _LTV | O2: _CLTV | P2: _AVG_LOANSIZE_SCHAMBALANCE | Q2: _WACLS | R2: _FICO | S2: PCT_ISSECONDLIEN | T2: _OrigCombLTV | U2: PCT_SVC | V2: PCT_TPO | W2: PCT_GEO | X2: PCT_LOANPURPOSE | Y2: PCT_OCC | Z2: curtailsmm | AA2: defaultsmm | AB2: toverSmm | AC2: cashoutSmm | AD2: refiSmm | AE2: cumHPA | AF2: cumHPA05Pct | AG2: cumHPA15Pct | AH2: cumHPA20Pct | AI2: cumHPA25Pct | AJ2: cumHPA30Pct | AK2: cumHPA35Pct | AL2: cumHPA40Pct | AM2: adjtoverSmm | AN2: adjRefiSmm | AO2: groupByColumn | AP2: curve | AQ2: Balance | AR2: LoanCount | AS2: PCT_BROKER | AT2: PCT_CORRES | AU2: PCT_NonRETAIL | AV2: PCT_RETAIL | AW2: PCT_CashWindow | AX2: PCT_NonCashWindow
A3: 96 | B3: 0.99661762 | C3: 0 | D3: 3.9841936 | E3: 0 | F3: 0.00338238 | G3: 0 | H3: 3.875 | I3: 4.118472 | J3: -64.0619 | K3: -131.95 | L3: 13.16 | M3: 17 | N3: 80 | O3: 77.08 | P3: 303250.44 | Q3: 303250.44 | R3: 773 | S3: 0 | T3: 0 | U3: 0 | V3: 1 | W3: 0 | X3: 1 | Y3: 0 | Z3: 0.00035183 | AA3: 7.792e-05 | AB3: 0.00295262 | AC3: 0 | AD3: 0 | AE3: 0.011207683 | AF3: 1 | AG3: 1 | AH3: 1 | AI3: 1 | AJ3: 1 | AK3: 1 | AL3: 1 | AM3: 0 | AN3: 0 | AO3: 03:-150--125 | AP3: =-150--125 -> -25 | AQ3: 303250.44 | AR3: 1 | AS3: 0 | AT3: 0 | AU3: 0 | AV3: 100 | AW3: 100 | AX3: 0
A4: 96 | B4: 0.99252822 | C4: 5.6968752e-06 | D4: 8.6066971 | E4: 4.7473962e-09 | F4: 0.0074717783 | G4: 0 | H4: 3.9463145 | I4: 3.9968994 | J4: -50.059634 | K4: -110.17523 | L4: 17.060622 | M4: 16.808767 | N4: 78.188745 | O4: 75.620467 | P4: 244109.93 | Q4: 234046.42 | R4: 766.50335 | S4: 0 | T4: 0 | U4: 0 | V4: 0.52919184 | W4: 0 | X4: 0.62889958 | Y4: 0 | Z4: 0.0003521941 | AA4: 5.2415621e-05 | AB4: 0.0030302851 | AC4: 0 | AD4: 0.0040368678 | AE4: 0.007991849 | AF4: 1 | AG4: 1 | AH4: 1 | AI4: 1 | AJ4: 1 | AK4: 1 | AL4: 1 | AM4: 0 | AN4: 0 | AO4: 04:-125--100 | AP4: =-125--100 -> -25 | AQ4: 2106417.8 | AR4: 9 | AS4: 0 | AT4: 47.080816 | AU4: 47.080816 | AV4: 52.919184 | AW4: 52.919184 | AX4: 0
A5: 96 | B5: 0.9854146 | C5: 6.7240517 | D5: 16.164509 | E5: 0.005783867 | F5: 0.0145854 | G5: 0 | H5: 4.2182657 | I5: 4.013573 | J5: -25.41889 | K5: -83.743459 | L5: 15.531015 | M5: 16.933544 | N5: 77.580947 | O5: 76.058289 | P5: 294714 | Q5: 232023.63 | R5: 776.08752 | S5: 0 | T5: 0 | U5: 0 | V5: 0.32998978 | W5: 0 | X5: 0.59746948 | Y5: 0 | Z5: 0.00049507274 | AA5: 8.312075e-05 | AB5: 0.0028162319 | AC5: 0 | AD5: 0.011190961 | AE5: -0.016614367 | AF5: 1 | AG5: 1 | AH5: 1 | AI5: 1 | AJ5: 1 | AK5: 1 | AL5: 1 | AM5: 0 | AN5: 0 | AO5: 05:-100--75 | AP5: =-100--75 -> -25 | AQ5: 6960708.8 | AR5: 30 | AS5: 0 | AT5: 67.001022 | AU5: 67.001022 | AV5: 32.998978 | AW5: 32.998978 | AX5: 0
A6: 96 | B6: 0.99302902 | C6: 5.2786397 | D6: 8.0517863 | E6: 0.0045090249 | F6: 0.0069709777 | G6: 0 | H6: 3.9477649 | I6: 4.1009703 | J6: -54.901747 | K6: -56.696947 | L6: 17.807148 | M6: 16.26908 | N6: 78.049954 | O6: 76.132956 | P6: 262092.09 | Q6: 215006.84 | R6: 779.43956 | S6: 0 | T6: 0 | U6: 0.01112109 | V6: 0.10269525 | W6: 0 | X6: 0.47395975 | Y6: 0 | Z6: 0.00054578086 | AA6: 7.3191027e-05 | AB6: 0.0025300283 | AC6: 0 | AD6: 0.0038219663 | AE6: -0.020708407 | AF6: 0.99013984 | AG6: 0.99958902 | AH6: 1 | AI6: 1 | AJ6: 1 | AK6: 1 | AL6: 1 | AM6: 0 | AN6: 0 | AO6: 06:-75--50 | AP6: =-75--50 -> -25 | AQ6: 1.0922347e+08 | AR6: 508 | AS6: 0 | AT6: 89.730475 | AU6: 89.730475 | AV6: 10.269525 | AW6: 10.269525 | AX6: 0
A7: 96 | B7: 0.99230135 | C7: 3.4916301 | D7: 8.8570662 | E7: 0.0029573223 | F7: 0.0076986466 | G7: 0 | H7: 3.8980515 | I7: 4.1131381 | J7: -60.5987 | K7: -33.134227 | L7: 16.339431 | M7: 16.249137 | N7: 74.492152 | O7: 72.612313 | P7: 269597.48 | Q7: 241873.07 | R7: 781.68626 | S7: 0 | T7: 0 | U7: 0.0015742685 | V7: 0.10414133 | W7: 0 | X7: 0.56299853 | Y7: 0 | Z7: 0.00041375709 | AA7: 6.3290386e-05 | AB7: 0.0026439115 | AC7: 6.9562929e-08 | AD7: 0.0045776036 | AE7: -0.011974575 | AF7: 0.97730546 | AG7: 0.99838128 | AH7: 0.99991916 | AI7: 0.99994485 | AJ7: 1 | AK7: 1 | AL7: 1 | AM7: 0 | AN7: 0 | AO7: 07:-50--25 | AP7: =-50--25 -> -25 | AQ7: 1.3745647e+09 | AR7: 5683 | AS7: 0 | AT7: 89.585867 | AU7: 89.585867 | AV7: 10.414133 | AW7: 10.414133 | AX7: 0
A8: 96 | B8: 0.98517734 | C8: 8.9858228 | D8: 16.406414 | E8: 0.0078155401 | F8: 0.014822662 | G8: 0 | H8: 4.0839912 | I8: 4.0992866 | J8: -42.802675 | K8: -9.077472 | L8: 15.562581 | M8: 16.684523 | N8: 72.801902 | O8: 71.302563 | P8: 277573.09 | Q8: 255801.73 | R8: 781.6394 | S8: 0 | T8: 0 | U8: 0.0055783667 | V8: 0.17335332 | W8: 0 | X8: 0.67387035 | Y8: 0 | Z8: 0.00037869677 | AA8: 6.7589305e-05 | AB8: 0.0027038749 | AC8: 6.6407159e-08 | AD8: 0.011672421 | AE8: -0.010937131 | AF8: 0.96415011 | AG8: 0.99661693 | AH8: 0.99981099 | AI8: 0.9999929 | AJ8: 1 | AK8: 1 | AL8: 1 | AM8: 0 | AN8: 0 | AO8: 08:-25-0 | AP8: =-25-0 -> -25 | AQ8: 9.5132663e+09 | AR8: 37190 | AS8: 0 | AT8: 82.664668 | AU8: 82.664668 | AV8: 17.335332 | AW8: 17.335332 | AX8: 0
A9: 96 | B9: 0.97895773 | C9: 18.38865 | D9: 22.52398 | E9: 0.016790921 | F9: 0.021042266 | G9: 0 | H9: 4.1856762 | I9: 4.0349491 | J9: -31.48218 | K9: 15.556412 | L9: 15.419536 | M9: 16.797045 | N9: 70.287528 | O9: 68.272532 | P9: 278926.35 | Q9: 258748.86 | R9: 782.30504 | S9: 0 | T9: 0 | U9: 0.018630946 | V9: 0.22529398 | W9: 0 | X9: 0.7659469 | Y9: 0 | Z9: 0.00037470468 | AA9: 7.2227262e-05 | AB9: 0.0028529876 | AC9: 7.4895964e-07 | AD9: 0.017741583 | AE9: -0.0021583667 | AF9: 0.90462044 | AG9: 0.98731819 | AH9: 0.9990021 | AI9: 0.9997661 | AJ9: 1 | AK9: 1 | AL9: 1 | AM9: 0 | AN9: 0 | AO9: 09:0-25 | AP9: 0-25 | AQ9: 4.3439276e+10 | AR9: 167882 | AS9: 0 | AT9: 77.470602 | AU9: 77.470602 | AV9: 22.529398 | AW9: 22.529398 | AX9: 0
A10: 96 | B10: 0.97148998 | C10: 30.040524 | D10: 29.325964 | E10: 0.029332373 | F10: 0.028510022 | G10: 0 | H10: 4.2143899 | I10: 3.8971895 | J10: -25.950779 | K10: 37.631504 | L10: 14.739426 | M10: 16.897771 | N10: 67.763986 | O10: 64.590286 | P10: 291283.19 | Q10: 270760.84 | R10: 782.49323 | S10: 0 | T10: 0 | U10: 0.026265113 | V10: 0.29598121 | W10: 0 | X10: 0.77482505 | Y10: 0 | Z10: 0.00037210515 | AA10: 7.1539095e-05 | AB10: 0.0030783518 | AC10: 3.8252828e-06 | AD10: 0.024984187 | AE10: 0.018675681 | AF10: 0.78093487 | AG10: 0.95971894 | AH10: 0.99639404 | AI10: 0.99938141 | AJ10: 1 | AK10: 1 | AL10: 1 | AM10: 0 | AN10: 0 | AO10: 10:25-50 | AP10: 25-50 | AQ10: 8.4135411e+10 | AR10: 310737 | AS10: 0 | AT10: 70.401879 | AU10: 70.401879 | AV10: 29.598121 | AW10: 29.598121 | AX10: 0
A11: 96 | B11: 0.96304728 | C11: 38.503459 | D11: 36.353973 | E11: 0.039705981 | F11: 0.036952722 | G11: 0 | H11: 4.4368642 | I11: 3.8641721 | J11: -16.151405 | K11: 62.402857 | L11: 15.006188 | M11: 17.333592 | N11: 69.32168 | O11: 65.791755 | P11: 285956.09 | Q11: 266022.72 | R11: 781.36518 | S11: 0 | T11: 0 | U11: 0.017246459 | V11: 0.26913712 | W11: 0 | X11: 0.68911647 | Y11: 0 | Z11: 0.00037305399 | AA11: 9.3431204e-05 | AB11: 0.0032090483 | AC11: 6.5567071e-06 | AD11: 0.033270617 | AE11: 0.022898189 | AF11: 0.74905845 | AG11: 0.96768233 | AH11: 0.99533969 | AI11: 0.99918041 | AJ11: 1 | AK11: 1 | AL11: 1 | AM11: 0 | AN11: 0 | AO11: 11:50-75 | AP11: 50-75 | AQ11: 7.8589496e+10 | AR11: 295424 | AS11: 0 | AT11: 73.086288 | AU11: 73.086288 | AV11: 26.913712 | AW11: 26.913712 | AX11: 0
A12: 96 | B12: 0.95601851 | C12: 42.321031 | D12: 41.70979 | E12: 0.044820945 | F12: 0.043981488 | G12: 0 | H12: 4.6559703 | I12: 3.8591563 | J12: -9.7638859 | K12: 86.123758 | L12: 14.913043 | M12: 17.0088 | N12: 69.232774 | O12: 65.248225 | P12: 287995.72 | Q12: 267721.99 | R12: 780.41619 | S12: 0 | T12: 0 | U12: 0.020502104 | V12: 0.22821933 | W12: 0 | X12: 0.60331037 | Y12: 0 | Z12: 0.00037169276 | AA12: 0.00011387914 | AB12: 0.0033322116 | AC12: 1.201048e-05 | AD12: 0.04015168 | AE12: 0.030369194 | AF12: 0.66788664 | AG12: 0.96158044 | AH12: 0.99290723 | AI12: 0.99891846 | AJ12: 1 | AK12: 1 | AL12: 1 | AM12: 0 | AN12: 0 | AO12: 12:75-100 | AP12: 75-100 | AQ12: 5.6874592e+10 | AR12: 212439 | AS12: 0 | AT12: 77.178067 | AU12: 77.178067 | AV12: 22.821933 | AW12: 22.821933 | AX12: 0
A13: 96 | B13: 0.95189661 | C13: 43.12208 | D13: 44.655134 | E13: 0.04593351 | F13: 0.048103395 | G13: 0 | H13: 4.8030413 | I13: 3.7634676 | J13: -5.7722298 | K13: 111.83503 | L13: 15.334443 | M13: 18.015841 | N13: 71.743211 | O13: 66.415984 | P13: 280024.33 | Q13: 260387.68 | R13: 779.64711 | S13: 0 | T13: 0 | U13: 0.020326776 | V13: 0.19832743 | W13: 0 | X13: 0.5239136 | Y13: 0 | Z13: 0.00037232537 | AA13: 0.00015299831 | AB13: 0.0035511637 | AC13: 2.5455984e-05 | AD13: 0.044001437 | AE13: 0.0483106 | AF13: 0.52474891 | AG13: 0.94444348 | AH13: 0.98895168 | AI13: 0.99789176 | AJ13: 1 | AK13: 1 | AL13: 1 | AM13: 0 | AN13: 0 | AO13: 13:100-125 | AP13: 100-125 | AQ13: 3.4432625e+10 | AR13: 132236 | AS13: 0 | AT13: 80.167257 | AU13: 80.167257 | AV13: 19.832743 | AW13: 19.832743 | AX13: 0
A14: 96 | B14: 0.94783045 | C14: 44.269541 | D14: 47.426383 | E14: 0.047552488 | F14: 0.052169555 | G14: 0 | H14: 4.8889524 | I14: 3.6792057 | J14: -3.8986406 | K14: 134.42076 | L14: 14.770577 | M14: 19.531062 | N14: 71.612656 | O14: 64.954466 | P14: 290001.43 | Q14: 270333.94 | R14: 778.9718 | S14: 0 | T14: 0 | U14: 0.02522111 | V14: 0.19016647 | W14: 0 | X14: 0.54162081 | Y14: 0 | Z14: 0.00037264217 | AA14: 0.00018728601 | AB14: 0.003504326 | AC14: 6.1669801e-05 | AD14: 0.048043616 | AE14: 0.069205256 | AF14: 0.41271197 | AG14: 0.90810374 | AH14: 0.97485773 | AI14: 0.99639125 | AJ14: 1 | AK14: 1 | AL14: 1 | AM14: 0 | AN14: 0 | AO14: 14:125-150 | AP14: 125-150 | AQ14: 1.5644766e+10 | AR14: 57872 | AS14: 0 | AT14: 80.983353 | AU14: 80.983353 | AV14: 19.016647 | AW14: 19.016647 | AX14: 0
A15: 96 | B15: 0.94467187 | C15: 42.416446 | D15: 49.490649 | E15: 0.04495272 | F15: 0.055328132 | G15: 0 | H15: 5.0523345 | I15: 3.6782356 | J15: 10.451198 | K15: 160.53489 | L15: 15.095943 | M15: 19.642718 | N15: 78.39791 | O15: 69.638817 | P15: 283783.99 | Q15: 264513.08 | R15: 777.32325 | S15: 0 | T15: 0 | U15: 0.017271692 | V15: 0.20360918 | W15: 0 | X15: 0.51465179 | Y15: 0 | Z15: 0.00037609829 | AA15: 0.00026329363 | AB15: 0.0037406843 | AC15: 0.00013096224 | AD15: 0.050817078 | AE15: 0.089601936 | AF15: 0.30801846 | AG15: 0.82214205 | AH15: 0.94504783 | AI15: 0.99151767 | AJ15: 1 | AK15: 1 | AL15: 1 | AM15: 0 | AN15: 0 | AO15: 15:150-175 | AP15: 150-175 | AQ15: 3.2484851e+09 | AR15: 12281 | AS15: 0 | AT15: 79.639082 | AU15: 79.639082 | AV15: 20.360918 | AW15: 20.360918 | AX15: 0
A16: 96 | B16: 0.93912402 | C16: 49.699111 | D16: 52.937456 | E16: 0.055653653 | F16: 0.060875978 | G16: 0 | H16: 5.08771 | I16: 3.6602132 | J16: 14.433686 | K16: 183.23039 | L16: 14.066214 | M16: 20.006563 | N16: 82.573291 | O16: 70.81271 | P16: 301542.67 | Q16: 283874.48 | R16: 776.71346 | S16: 0 | T16: 0 | U16: 0.014774893 | V16: 0.14884716 | W16: 0 | X16: 0.49026382 | Y16: 0 | Z16: 0.00037924852 | AA16: 0.00032323157 | AB16: 0.0038561489 | AC16: 0.00039488146 | AD16: 0.055922451 | AE16: 0.12536342 | AF16: 0.18089512 | AG16: 0.64354096 | AH16: 0.82094044 | AI16: 0.96473361 | AJ16: 1 | AK16: 1 | AL16: 1 | AM16: 0 | AN16: 0 | AO16: 16:175-200 | AP16: 175-200 | AQ16: 8.0705515e+08 | AR16: 2843 | AS16: 0 | AT16: 85.115284 | AU16: 85.115284 | AV16: 14.884716 | AW16: 14.884716 | AX16: 0
A17: 96 | B17: 0.93745664 | C17: 40.294314 | D17: 53.930419 | E17: 0.042068089 | F17: 0.062543363 | G17: 0 | H17: 5.1697091 | I17: 3.6671452 | J17: 19.100507 | K17: 209.2428 | L17: 14.634743 | M17: 20.249616 | N17: 89.708323 | O17: 74.667695 | P17: 293970.51 | Q17: 272848.93 | R17: 775.48884 | S17: 0 | T17: 0 | U17: 0.01394964 | V17: 0.11440628 | W17: 0 | X17: 0.31912774 | Y17: 0 | Z17: 0.00038583756 | AA17: 0.00041282419 | AB17: 0.0042255695 | AC17: 0.00068701308 | AD17: 0.056832102 | AE17: 0.15845744 | AF17: 0.047185182 | AG17: 0.44358389 | AH17: 0.70975847 | AI17: 0.93055656 | AJ17: 1 | AK17: 1 | AL17: 1 | AM17: 0 | AN17: 0 | AO17: 17:200-225 | AP17: 200-225 | AQ17: 1.394258e+08 | AR17: 511 | AS17: 0 | AT17: 88.559372 | AU17: 88.559372 | AV17: 11.440628 | AW17: 11.440628 | AX17: 0
A18: 96 | B18: 0.93452588 | C18: 22.261828 | D18: 55.629327 | E18: 0.020766655 | F18: 0.065474117 | G18: 0 | H18: 5.2637101 | I18: 3.6463383 | J18: 27.126595 | K18: 231.8549 | L18: 13.891115 | M18: 20.806704 | N18: 92.564127 | O18: 74.572096 | P18: 308393.03 | Q18: 287462.08 | R18: 776.67354 | S18: 0 | T18: 0 | U18: 0 | V18: 0.02793355 | W18: 0 | X18: 0.14885189 | Y18: 0 | Z18: 0.00038200278 | AA18: 0.00051270754 | AB18: 0.0044189107 | AC18: 0.0013464358 | AD18: 0.058814042 | AE18: 0.19904467 | AF18: 0 | AG18: 0.17152724 | AH18: 0.37747711 | AI18: 0.91231698 | AJ18: 1 | AK18: 1 | AL18: 1 | AM18: 0 | AN18: 0 | AO18: 18:225-250 | AP18: 225-250 | AQ18: 23571890 | AR18: 82 | AS18: 0 | AT18: 97.206645 | AU18: 97.206645 | AV18: 2.793355 | AW18: 2.793355 | AX18: 0
K25: turn | L25: cash | M25: refi | R25: turn | W25: cash | AB25: refi
A26: incentive | B26: =AQ2 -> Balance | C26: =AO2 -> groupByColumn | D26: =E2 -> PREPAY_SMM1 | E26: =F2 -> PREPAY_TRACKING_SMM1 | F26: ratio | G26: =C2 -> PREPAY_CPR1 | H26: =D2 -> PREPAY_TRACKING_CPR1 | K26: adj | L26: adj | M26: adj | N26: mdl_smm | O26: mdl_cpr | P26: ratio | R26: x | T26: Knot | U26: adj Knot | W26: x | X26: adj x | Y26: Knot | Z26: adj Knot | AB26: x | AC26: adj x | AD26: Knot | AE26: adj Knot
A27: =K3 -> -131.95 | B27: =AQ3/1000000000 -> 0.00030325044 | C27: =AO3 -> 03:-150--125 | D27: =E3 -> 0 | E27: =Z3+AA3+AB3+AC3+AD3 -> 0.00338237 | F27: =D27/E27 -> 0 | G27: =(1-(1-D27)^12)*100 -> 0 | H27: =(1-(1-E27)^12)*100 -> 3.984182 | K27: 1 | L27: 1 | M27: 1 | N27: =Z3+AA3+AB3*K27+AC3*L27+AD3*M27 -> 0.00338237 | O27: =100*(1-(1-N27)^12) -> 3.984182 | P27: =D27/N27 -> 0 | S27: =A27 -> -131.95 | T27: =VLOOKUP(ROUNDDOWN(S27,0),'Spline Pre-Adj'!A:B,2,0) -> 0.95832877 | U27: =T27*K27 -> 0.95832877
A28: =K4 -> -110.17523 | B28: =AQ4/1000000000 -> 0.0021064178 | C28: =AO4 -> 04:-125--100 | D28: =E4 -> 4.7473962e-09 | E28: =Z4+AA4+AB4+AC4+AD4 -> 0.0074717626 | F28: =D28/E28 -> 6.3537835e-07 | G28: =(1-(1-D28)^12)*100 -> 5.6968754e-06 | H28: =(1-(1-E28)^12)*100 -> 8.6066798 | K28: 1 | L28: 1 | M28: 1 | N28: =Z4+AA4+AB4*K28+AC4*L28+AD4*M28 -> 0.0074717626 | O28: =100*(1-(1-N28)^12) -> 8.6066798 | P28: =D28/N28 -> 6.3537835e-07 | S28: =A28 -> -110.17523 | T28: =VLOOKUP(ROUNDDOWN(S28,0),'Spline Pre-Adj'!A:B,2,0) -> 1.012994 | U28: =T28*K28 -> 1.012994 | X28: =A28 -> -110.17523 | Y28: =VLOOKUP(ROUNDDOWN(X28,0),'Spline Pre-Adj'!F:G,2,0) -> 0 | Z28: =Y28*L28 -> 0
A29: =K5 -> -83.743459 | B29: =AQ5/1000000000 -> 0.0069607088 | C29: =AO5 -> 05:-100--75 | D29: =E5 -> 0.005783867 | E29: =Z5+AA5+AB5+AC5+AD5 -> 0.014585386 | F29: =D29/E29 -> 0.3965522 | G29: =(1-(1-D29)^12)*100 -> 6.7240517 | H29: =(1-(1-E29)^12)*100 -> 16.164495 | K29: 1 | L29: 1 | M29: 1 | N29: =Z5+AA5+AB5*K29+AC5*L29+AD5*M29 -> 0.014585386 | O29: =100*(1-(1-N29)^12) -> 16.164495 | P29: =D29/N29 -> 0.3965522 | S29: =A29 -> -83.743459 | T29: =VLOOKUP(ROUNDDOWN(S29,0),'Spline Pre-Adj'!A:B,2,0) -> 1.1352282 | U29: =T29*K29 -> 1.1352282 | X29: =A29 -> -83.743459 | Y29: =VLOOKUP(ROUNDDOWN(X29,0),'Spline Pre-Adj'!F:G,2,0) -> 0.031256267 | Z29: =Y29*L29 -> 0.031256267
A30: =K6 -> -56.696947 | B30: =AQ6/1000000000 -> 0.10922347 | C30: =AO6 -> 06:-75--50 | D30: =E6 -> 0.0045090249 | E30: =Z6+AA6+AB6+AC6+AD6 -> 0.0069709665 | F30: =D30/E30 -> 0.64682922 | G30: =(1-(1-D30)^12)*100 -> 5.2786397 | H30: =(1-(1-E30)^12)*100 -> 8.0517738 | K30: 1 | L30: 1 | M30: 0.5 | N30: =Z6+AA6+AB6*K30+AC6*L30+AD6*M30 -> 0.0050599834 | O30: =100*(1-(1-N30)^12) -> 5.9058153 | P30: =D30/N30 -> 0.89111456 | S30: =A30 -> -56.696947 | T30: =VLOOKUP(ROUNDDOWN(S30,0),'Spline Pre-Adj'!A:B,2,0) -> 1.2795489 | U30: =T30*K30 -> 1.2795489 | X30: =A30 -> -56.696947 | Y30: =VLOOKUP(ROUNDDOWN(X30,0),'Spline Pre-Adj'!F:G,2,0) -> 0.18862313 | Z30: =Y30*L30 -> 0.18862313 | AC30: =A30 -> -56.696947 | AD30: =VLOOKUP(ROUNDDOWN(AC30,0),'Spline Pre-Adj'!K:L,2,0) -> 0 | AE30: =AD30*M30 -> 0
A31: =K7 -> -33.134227 | B31: =AQ7/1000000000 -> 1.3745647 | C31: =AO7 -> 07:-50--25 | D31: =E7 -> 0.0029573223 | E31: =Z7+AA7+AB7+AC7+AD7 -> 0.0076986322 | F31: =D31/E31 -> 0.38413608 | G31: =(1-(1-D31)^12)*100 -> 3.4916301 | H31: =(1-(1-E31)^12)*100 -> 8.8570502 | K31: 1 | L31: 1 | M31: 0.5 | N31: =Z7+AA7+AB7*K31+AC7*L31+AD7*M31 -> 0.0054098304 | O31: =100*(1-(1-N31)^12) -> 6.3020802 | P31: =D31/N31 -> 0.54665713 | S31: =A31 -> -33.134227 | T31: =VLOOKUP(ROUNDDOWN(S31,0),'Spline Pre-Adj'!A:B,2,0) -> 1.287 | U31: =T31*K31 -> 1.287 | X31: =A31 -> -33.134227 | Y31: =VLOOKUP(ROUNDDOWN(X31,0),'Spline Pre-Adj'!F:G,2,0) -> 0.30615061 | Z31: =Y31*L31 -> 0.30615061 | AC31: =A31 -> -33.134227 | AD31: =VLOOKUP(ROUNDDOWN(AC31,0),'Spline Pre-Adj'!K:L,2,0) -> 0.39387319 | AE31: =AD31*M31 -> 0.1969366
A32: =K8 -> -9.077472 | B32: =AQ8/1000000000 -> 9.5132663 | C32: =AO8 -> 08:-25-0 | D32: =E8 -> 0.0078155401 | E32: =Z8+AA8+AB8+AC8+AD8 -> 0.014822648 | F32: =D32/E32 -> 0.52727017 | G32: =(1-(1-D32)^12)*100 -> 8.9858228 | H32: =(1-(1-E32)^12)*100 -> 16.406399 | K32: 1 | L32: 1 | M32: 0.55 | N32: =Z8+AA8+AB8*K32+AC8*L32+AD8*M32 -> 0.0095700587 | O32: =100*(1-(1-N32)^12) -> 10.898476 | P32: =D32/N32 -> 0.81666585 | S32: =A32 -> -9.077472 | T32: =VLOOKUP(ROUNDDOWN(S32,0),'Spline Pre-Adj'!A:B,2,0) -> 1.287 | U32: =T32*K32 -> 1.287 | X32: =A32 -> -9.077472 | Y32: =VLOOKUP(ROUNDDOWN(X32,0),'Spline Pre-Adj'!F:G,2,0) -> 0.51930077 | Z32: =Y32*L32 -> 0.51930077 | AC32: =A32 -> -9.077472 | AD32: =VLOOKUP(ROUNDDOWN(AC32,0),'Spline Pre-Adj'!K:L,2,0) -> 1.1530058 | AE32: =AD32*M32 -> 0.6341532
A33: =K9 -> 15.556412 | B33: =AQ9/1000000000 -> 43.439276 | C33: =AO9 -> 09:0-25 | D33: =E9 -> 0.016790921 | E33: =Z9+AA9+AB9+AC9+AD9 -> 0.021042252 | F33: =D33/E33 -> 0.7979622 | G33: =(1-(1-D33)^12)*100 -> 18.38865 | H33: =(1-(1-E33)^12)*100 -> 22.523967 | K33: 1 | L33: 1 | M33: 0.8 | N33: =Z9+AA9+AB9*K33+AC9*L33+AD9*M33 -> 0.017493935 | O33: =100*(1-(1-N33)^12) -> 19.086147 | P33: =D33/N33 -> 0.95981386 | S33: =A33 -> 15.556412 | T33: =VLOOKUP(ROUNDDOWN(S33,0),'Spline Pre-Adj'!A:B,2,0) -> 1.287 | U33: =T33*K33 -> 1.287 | X33: =A33 -> 15.556412 | Y33: =VLOOKUP(ROUNDDOWN(X33,0),'Spline Pre-Adj'!F:G,2,0) -> 0.98856376 | Z33: =Y33*L33 -> 0.98856376 | AC33: =A33 -> 15.556412 | AD33: =VLOOKUP(ROUNDDOWN(AC33,0),'Spline Pre-Adj'!K:L,2,0) -> 1.7164152 | AE33: =AD33*M33 -> 1.3731322
A34: =K10 -> 37.631504 | B34: =AQ10/1000000000 -> 84.135411 | C34: =AO10 -> 10:25-50 | D34: =E10 -> 0.029332373 | E34: =Z10+AA10+AB10+AC10+AD10 -> 0.028510008 | F34: =D34/E34 -> 1.0288448 | G34: =(1-(1-D34)^12)*100 -> 30.040524 | H34: =(1-(1-E34)^12)*100 -> 29.325951 | K34: 1 | L34: 1 | M34: 1.05 | N34: =Z10+AA10+AB10*K34+AC10*L34+AD10*M34 -> 0.029759218 | O34: =100*(1-(1-N34)^12) -> 30.408803 | P34: =D34/N34 -> 0.98565673 | S34: =A34 -> 37.631504 | T34: =VLOOKUP(ROUNDDOWN(S34,0),'Spline Pre-Adj'!A:B,2,0) -> 1.287 | U34: =T34*K34 -> 1.287 | X34: =A34 -> 37.631504 | Y34: =VLOOKUP(ROUNDDOWN(X34,0),'Spline Pre-Adj'!F:G,2,0) -> 1.8953738 | Z34: =Y34*L34 -> 1.8953738 | AC34: =A34 -> 37.631504 | AD34: =VLOOKUP(ROUNDDOWN(AC34,0),'Spline Pre-Adj'!K:L,2,0) -> 2.4264029 | AE34: =AD34*M34 -> 2.5477231
A35: =K11 -> 62.402857 | B35: =AQ11/1000000000 -> 78.589496 | C35: =AO11 -> 11:50-75 | D35: =E11 -> 0.039705981 | E35: =Z11+AA11+AB11+AC11+AD11 -> 0.036952707 | F35: =D35/E35 -> 1.074508 | G35: =(1-(1-D35)^12)*100 -> 38.503459 | H35: =(1-(1-E35)^12)*100 -> 36.353962 | K35: 1 | L35: 1 | M35: 1.1 | N35: =Z11+AA11+AB11*K35+AC11*L35+AD11*M35 -> 0.040279769 | O35: =100*(1-(1-N35)^12) -> 38.942953 | P35: =D35/N35 -> 0.98575492 | S35: =A35 -> 62.402857 | T35: =VLOOKUP(ROUNDDOWN(S35,0),'Spline Pre-Adj'!A:B,2,0) -> 1.287 | U35: =T35*K35 -> 1.287 | X35: =A35 -> 62.402857 | Y35: =VLOOKUP(ROUNDDOWN(X35,0),'Spline Pre-Adj'!F:G,2,0) -> 3.3799458 | Z35: =Y35*L35 -> 3.3799458 | AC35: =A35 -> 62.402857 | AD35: =VLOOKUP(ROUNDDOWN(AC35,0),'Spline Pre-Adj'!K:L,2,0) -> 3.3536482 | AE35: =AD35*M35 -> 3.689013
A36: =K12 -> 86.123758 | B36: =AQ12/1000000000 -> 56.874592 | C36: =AO12 -> 12:75-100 | D36: =E12 -> 0.044820945 | E36: =Z12+AA12+AB12+AC12+AD12 -> 0.043981474 | F36: =D36/E36 -> 1.0190869 | G36: =(1-(1-D36)^12)*100 -> 42.321031 | H36: =(1-(1-E36)^12)*100 -> 41.709779 | K36: 1 | L36: 1 | M36: 1.02 | N36: =Z12+AA12+AB12*K36+AC12*L36+AD12*M36 -> 0.044784507 | O36: =100*(1-(1-N36)^12) -> 42.294622 | P36: =D36/N36 -> 1.0008136 | S36: =A36 -> 86.123758 | T36: =VLOOKUP(ROUNDDOWN(S36,0),'Spline Pre-Adj'!A:B,2,0) -> 1.287 | U36: =T36*K36 -> 1.287 | X36: =A36 -> 86.123758 | Y36: =VLOOKUP(ROUNDDOWN(X36,0),'Spline Pre-Adj'!F:G,2,0) -> 4.7646641 | Z36: =Y36*L36 -> 4.7646641 | AC36: =A36 -> 86.123758 | AD36: =VLOOKUP(ROUNDDOWN(AC36,0),'Spline Pre-Adj'!K:L,2,0) -> 4.1191353 | AE36: =AD36*M36 -> 4.201518
A37: =K13 -> 111.83503 | B37: =AQ13/1000000000 -> 34.432625 | C37: =AO13 -> 13:100-125 | D37: =E13 -> 0.04593351 | E37: =Z13+AA13+AB13+AC13+AD13 -> 0.04810338 | F37: =D37/E37 -> 0.95489152 | G37: =(1-(1-D37)^12)*100 -> 43.12208 | H37: =(1-(1-E37)^12)*100 -> 44.655124 | K37: 1 | L37: 1 | M37: 0.95 | N37: =Z13+AA13+AB13*K37+AC13*L37+AD13*M37 -> 0.045903308 | O37: =100*(1-(1-N37)^12) -> 43.10047 | P37: =D37/N37 -> 1.0006579 | X37: =A37 -> 111.83503 | Y37: =VLOOKUP(ROUNDDOWN(X37,0),'Spline Pre-Adj'!F:G,2,0) -> 6.2168085 | Z37: =Y37*L37 -> 6.2168085 | AC37: =A37 -> 111.83503 | AD37: =VLOOKUP(ROUNDDOWN(AC37,0),'Spline Pre-Adj'!K:L,2,0) -> 4.729914 | AE37: =AD37*M37 -> 4.4934183
A38: =K14 -> 134.42076 | B38: =AQ14/1000000000 -> 15.644766 | C38: =AO14 -> 14:125-150 | D38: =E14 -> 0.047552488 | E38: =Z14+AA14+AB14+AC14+AD14 -> 0.05216954 | F38: =D38/E38 -> 0.91149908 | G38: =(1-(1-D38)^12)*100 -> 44.269541 | H38: =(1-(1-E38)^12)*100 -> 47.426374 | K38: 1 | L38: 1 | M38: 0.92 | N38: =Z14+AA14+AB14*K38+AC14*L38+AD14*M38 -> 0.048326051 | O38: =100*(1-(1-N38)^12) -> 44.810282 | P38: =D38/N38 -> 0.98399284 | X38: =A38 -> 134.42076 | Y38: =VLOOKUP(ROUNDDOWN(X38,0),'Spline Pre-Adj'!F:G,2,0) -> 7.6066289 | Z38: =Y38*L38 -> 7.6066289 | AC38: =A38 -> 134.42076 | AD38: =VLOOKUP(ROUNDDOWN(AC38,0),'Spline Pre-Adj'!K:L,2,0) -> 5.205107 | AE38: =AD38*M38 -> 4.7886984
A39: =K15 -> 160.53489 | B39: =AQ15/1000000000 -> 3.2484851 | C39: =AO15 -> 15:150-175 | D39: =E15 -> 0.04495272 | E39: =Z15+AA15+AB15+AC15+AD15 -> 0.055328117 | F39: =D39/E39 -> 0.81247515 | G39: =(1-(1-D39)^12)*100 -> 42.416446 | H39: =(1-(1-E39)^12)*100 -> 49.490639 | K39: 1 | L39: 1 | M39: 0.9 | N39: =Z15+AA15+AB15*K39+AC15*L39+AD15*M39 -> 0.050246409 | O39: =100*(1-(1-N39)^12) -> 46.13194 | P39: =D39/N39 -> 0.89464542 | X39: =A39 -> 160.53489 | Y39: =VLOOKUP(ROUNDDOWN(X39,0),'Spline Pre-Adj'!F:G,2,0) -> 8.7434836 | Z39: =Y39*L39 -> 8.7434836 | AC39: =A39 -> 160.53489 | AD39: =VLOOKUP(ROUNDDOWN(AC39,0),'Spline Pre-Adj'!K:L,2,0) -> 5.6662697 | AE39: =AD39*M39 -> 5.0996428
A40: =K16 -> 183.23039 | B40: =AQ16/1000000000 -> 0.80705515 | C40: =AO16 -> 16:175-200 | D40: =E16 -> 0.055653653 | E40: =Z16+AA16+AB16+AC16+AD16 -> 0.060875962 | F40: =D40/E40 -> 0.91421394 | G40: =(1-(1-D40)^12)*100 -> 49.699111 | H40: =(1-(1-E40)^12)*100 -> 52.937447 | K40: 1 | L40: 1 | M40: 0.9 | N40: =Z16+AA16+AB16*K40+AC16*L40+AD16*M40 -> 0.055283716 | O40: =100*(1-(1-N40)^12) -> 49.462144 | P40: =D40/N40 -> 1.0066916 | X40: =A40 -> 183.23039 | Y40: =VLOOKUP(ROUNDDOWN(X40,0),'Spline Pre-Adj'!F:G,2,0) -> 8.8912891 | Z40: =Y40*L40 -> 8.8912891 | AC40: =A40 -> 183.23039 | AD40: =VLOOKUP(ROUNDDOWN(AC40,0),'Spline Pre-Adj'!K:L,2,0) -> 6.0276934 | AE40: =AD40*M40 -> 5.4249241
A41: =K17 -> 209.2428 | B41: =AQ17/1000000000 -> 0.1394258 | C41: =AO17 -> 17:200-225 | D41: =E17 -> 0.042068089 | E41: =Z17+AA17+AB17+AC17+AD17 -> 0.062543346 | F41: =D41/E41 -> 0.67262294 | G41: =(1-(1-D41)^12)*100 -> 40.294314 | H41: =(1-(1-E41)^12)*100 -> 53.930409 | K41: 1 | L41: 1 | M41: 1.05 | N41: =Z17+AA17+AB17*K41+AC17*L41+AD17*M41 -> 0.065384951 | O41: =100*(1-(1-N41)^12) -> 55.578498 | P41: =D41/N41 -> 0.643391 | X41: =A41 -> 209.2428 | Y41: =VLOOKUP(ROUNDDOWN(X41,0),'Spline Pre-Adj'!F:G,2,0) -> 8.9 | Z41: =Y41*L41 -> 8.9 | AC41: =A41 -> 209.2428 | AD41: =VLOOKUP(ROUNDDOWN(AC41,0),'Spline Pre-Adj'!K:L,2,0) -> 6.3657669 | AE41: =AD41*M41 -> 6.6840552
A67: WALA [12,24) | C67: BROKER | AS67: tover | AT67: cash | AW67: refi
A68: modelId | B68: SFACTOR_PREPAY_TRACKING_CPR | C68: PREPAY_CPR1 | D68: PREPAY_TRACKING_CPR1 | E68: PREPAY_SMM1 | F68: PREPAY_TRACKING_SMM1 | G68: PCT_LOANTYPE | H68: _ORIGNOTERATE | I68: _ZEROSATO | J68: _SATO | K68: _REFI_INCENTIVE_Fixed | L68: _Fixed_cost | M68: _LOANAGE | N68: _LTV | O68: _CLTV | P68: _AVG_LOANSIZE_SCHAMBALANCE | Q68: _WACLS | R68: _FICO | S68: PCT_ISSECONDLIEN | T68: _OrigCombLTV | U68: PCT_SVC | V68: PCT_TPO | W68: PCT_GEO | X68: PCT_LOANPURPOSE | Y68: PCT_OCC | Z68: curtailsmm | AA68: defaultsmm | AB68: toverSmm | AC68: cashoutSmm | AD68: refiSmm | AE68: cumHPA | AF68: cumHPA05Pct | AG68: cumHPA15Pct | AH68: cumHPA20Pct | AI68: cumHPA25Pct | AJ68: cumHPA30Pct | AK68: cumHPA35Pct | AL68: cumHPA40Pct | AM68: adjtoverSmm | AN68: adjRefiSmm | AO68: groupByColumn | AP68: curve | AQ68: Balance | AR68: LoanCount | AS68: PCT_BROKER | AT68: PCT_CORRES | AU68: PCT_NonRETAIL | AV68: PCT_RETAIL | AW68: PCT_CashWindow | AX68: PCT_NonCashWindow
A69: 96 | B69: 0.99182842 | C69: 3.8957922 | D69: 9.3769677 | E69: 0.003305947 | F69: 0.0081715784 | G69: 0 | H69: 3.9675065 | I69: 4.1283936 | J69: -54.678879 | K69: -56.682817 | L69: 18.767246 | M69: 16.274611 | N69: 77.853085 | O69: 75.207731 | P69: 267569.16 | Q69: 188541.3 | R69: 773.89744 | S69: 0 | T69: 0 | U69: 0.071689611 | V69: 0 | W69: 0 | X69: 0.5444671 | Y69: 0 | Z69: 0.0007036877 | AA69: 8.8031509e-05 | AB69: 0.0025907227 | AC69: 3.7428656e-08 | AD69: 0.0047890873 | AE69: -0.022818134 | AF69: 0.98731299 | AG69: 0.99644125 | AH69: 1 | AI69: 1 | AJ69: 1 | AK69: 1 | AL69: 1 | AM69: 0 | AN69: 0 | AO69: 06:-75--50 | AP69: =-75--50 -> -25 | AQ69: 17345800 | AR69: 92 | AS69: 100 | AT69: 0 | AU69: 100 | AV69: 0 | AW69: 0 | AX69: 0
A70: 96 | B70: 0.99146676 | C70: 2.5593301 | D70: 9.7727093 | E70: 0.00215821 | F70: 0.0085332374 | G70: 0 | H70: 3.8999139 | I70: 4.1100912 | J70: -59.796144 | K70: -32.151317 | L70: 15.206687 | M70: 16.277653 | N70: 74.240428 | O70: 72.758628 | P70: 291058.35 | Q70: 258641.71 | R70: 784.51618 | S70: 0 | T70: 0 | U70: 0.067353074 | V70: 0 | W70: 0 | X70: 0.6198173 | Y70: 0 | Z70: 0.00044165102 | AA70: 6.54869e-05 | AB70: 0.0025421345 | AC70: 2.7072769e-08 | AD70: 0.0054839232 | AE70: -0.017049304 | AF70: 0.97692522 | AG70: 0.99625024 | AH70: 1 | AI70: 1 | AJ70: 1 | AK70: 1 | AL70: 1 | AM70: 0 | AN70: 0 | AO70: 07:-50--25 | AP70: =-50--25 -> -25 | AQ70: 1.8285969e+08 | AR70: 707 | AS70: 100 | AT70: 0 | AU70: 100 | AV70: 0 | AW70: 0 | AX70: 0
A71: 96 | B71: 0.98853892 | C71: 9.4220487 | D71: 12.918625 | E71: 0.0082127038 | F71: 0.011461079 | G71: 0 | H71: 3.9787687 | I71: 4.11636 | J71: -52.192348 | K71: -22.234953 | L71: 15.058437 | M71: 16.143549 | N71: 73.258944 | O71: 71.898842 | P71: 289927.42 | Q71: 263943.27 | R71: 783.4957 | S71: 0 | T71: 0 | U71: 0.12846874 | V71: 0 | W71: 0 | X71: 0.65047953 | Y71: 0 | Z71: 0.00038934545 | AA71: 5.3528718e-05 | AB71: 0.0025274232 | AC71: 0 | AD71: 0.0084907668 | AE71: -0.013797444 | AF71: 0.98291916 | AG71: 1 | AH71: 1 | AI71: 1 | AJ71: 1 | AK71: 1 | AL71: 1 | AM71: 0 | AN71: 0 | AO71: 08-1:-25--20 | AP71: =-25--20 -> -5 | AQ71: 1.0425759e+08 | AR71: 395 | AS71: 100 | AT71: 0 | AU71: 100 | AV71: 0 | AW71: 0 | AX71: 0
A72: 96 | B72: 0.98664989 | C72: 10.8075 | D72: 14.894654 | E72: 0.0094858256 | F72: 0.013350114 | G72: 0 | H72: 4.0123687 | I72: 4.1022851 | J72: -48.675926 | K72: -17.320366 | L72: 14.771784 | M72: 16.461219 | N72: 73.185534 | O72: 71.808848 | P72: 293291.65 | Q72: 268021.91 | R72: 783.50073 | S72: 0 | T72: 0 | U72: 0.12902529 | V72: 0 | W72: 0 | X72: 0.6521736 | Y72: 0 | Z72: 0.00038242703 | AA72: 6.5931189e-05 | AB72: 0.0026124491 | AC72: 4.1997689e-08 | AD72: 0.01028925 | AE72: -0.012150854 | AF72: 0.95700419 | AG72: 0.99466206 | AH72: 1 | AI72: 1 | AJ72: 1 | AK72: 1 | AL72: 1 | AM72: 0 | AN72: 0 | AO72: 08-2:-20--15 | AP72: =-20--15 -> -5 | AQ72: 1.750183e+08 | AR72: 653 | AS72: 100 | AT72: 0 | AU72: 100 | AV72: 0 | AW72: 0 | AX72: 0
A73: 96 | B73: 0.98525239 | C73: 10.602841 | D73: 16.329962 | E73: 0.0092966237 | F73: 0.01474761 | G73: 0 | H73: 4.0594479 | I73: 4.1019476 | J73: -43.895944 | K73: -12.265261 | L73: 14.862993 | M73: 16.561958 | N73: 72.892803 | O73: 71.466897 | P73: 290133.71 | Q73: 267610.1 | R73: 782.54737 | S73: 0 | T73: 0 | U73: 0.14817147 | V73: 0 | W73: 0 | X73: 0.67536497 | Y73: 0 | Z73: 0.00038339238 | AA73: 6.8300586e-05 | AB73: 0.0026511847 | AC73: 1.093881e-07 | AD73: 0.011644608 | AE73: -0.011989605 | AF73: 0.95471591 | AG73: 0.99739985 | AH73: 0.99974737 | AI73: 1 | AJ73: 1 | AK73: 1 | AL73: 1 | AM73: 0 | AN73: 0 | AO73: 08-3:-15--10 | AP73: =-15--10 -> -5 | AQ73: 2.8393432e+08 | AR73: 1061 | AS73: 100 | AT73: 0 | AU73: 100 | AV73: 0 | AW73: 0 | AX73: 0
A74: 96 | B74: 0.98387571 | C74: 15.810679 | D74: 17.722159 | E74: 0.014239488 | F74: 0.016124286 | G74: 0 | H74: 4.1077354 | I74: 4.099816 | J74: -39.524502 | K74: -7.3224373 | L74: 14.493312 | M74: 16.391644 | N74: 73.64129 | O74: 72.295637 | P74: 297162.78 | Q74: 274503.54 | R74: 783.19252 | S74: 0 | T74: 0 | U74: 0.15411512 | V74: 0 | W74: 0 | X74: 0.69552451 | Y74: 0 | Z74: 0.00037708944 | AA74: 7.175416e-05 | AB74: 0.0025337216 | AC74: 1.6025797e-07 | AD74: 0.013141546 | AE74: -0.011378594 | AF74: 0.94440567 | AG74: 0.98798332 | AH74: 0.99955536 | AI74: 1 | AJ74: 1 | AK74: 1 | AL74: 1 | AM74: 0 | AN74: 0 | AO74: 08-4:-10--5 | AP74: =-10--5 -> -5 | AQ74: 4.2300995e+08 | AR74: 1541 | AS74: 100 | AT74: 0 | AU74: 100 | AV74: 0 | AW74: 0 | AX74: 0
A75: 96 | B75: 0.98253861 | C75: 14.323614 | D75: 19.053982 | E75: 0.012800118 | F75: 0.017461394 | G75: 0 | H75: 4.1116634 | I75: 4.0847326 | J75: -38.215918 | K75: -2.3387297 | L75: 14.464719 | M75: 16.5396 | N75: 71.790473 | O75: 70.257818 | P75: 297861.7 | Q75: 275125.01 | R75: 782.20967 | S75: 0 | T75: 0 | U75: 0.17400611 | V75: 0 | W75: 0 | X75: 0.71708806 | Y75: 0 | Z75: 0.00037544413 | AA75: 6.5077232e-05 | AB75: 0.0026184242 | AC75: 2.1687116e-07 | AD75: 0.014402217 | AE75: -0.0088282285 | AF75: 0.94302178 | AG75: 0.99026126 | AH75: 0.99944319 | AI75: 1 | AJ75: 1 | AK75: 1 | AL75: 1 | AM75: 0 | AN75: 0 | AO75: 08:-25-0 | AP75: =-25-0 -> -25 | AQ75: 6.2948602e+08 | AR75: 2288 | AS75: 100 | AT75: 0 | AU75: 100 | AV75: 0 | AW75: 0 | AX75: 0
A76: 96 | B76: 0.9812422 | C76: 19.451517 | D76: 20.326364 | E76: 0.017864415 | F76: 0.018757795 | G76: 0 | H76: 4.1335924 | I76: 4.0727535 | J76: -35.041675 | K76: 2.6535888 | L76: 14.474732 | M76: 16.462474 | N76: 71.886996 | O76: 70.234034 | P76: 297332.28 | Q76: 275510.89 | R76: 782.24488 | S76: 0 | T76: 0 | U76: 0.21882607 | V76: 0 | W76: 0 | X76: 0.7578272 | Y76: 0 | Z76: 0.00037073438 | AA76: 6.3384512e-05 | AB76: 0.0026459512 | AC76: 3.1561933e-07 | AD76: 0.015677395 | AE76: -0.0055919344 | AF76: 0.92268659 | AG76: 0.98776176 | AH76: 0.99886647 | AI76: 1 | AJ76: 1 | AK76: 1 | AL76: 1 | AM76: 0 | AN76: 0 | AO76: 09-1:0-5 | AP76: 0-5 | AQ76: 8.579409e+08 | AR76: 3114 | AS76: 100 | AT76: 0 | AU76: 100 | AV76: 0 | AW76: 0 | AX76: 0
A77: 96 | B77: 0.98008601 | C77: 23.94502 | D77: 21.445638 | E77: 0.022551304 | F77: 0.019913986 | G77: 0 | H77: 4.1410751 | I77: 4.048044 | J77: -33.144411 | K77: 7.6198853 | L77: 14.82869 | M77: 16.410128 | N77: 71.889857 | O77: 69.875992 | P77: 290487.27 | Q77: 268888.98 | R77: 782.61242 | S77: 0 | T77: 0 | U77: 0.2332186 | V77: 0 | W77: 0 | X77: 0.77023482 | Y77: 0 | Z77: 0.00037079632 | AA77: 6.9716105e-05 | AB77: 0.0027526028 | AC77: 1.5092874e-06 | AD77: 0.016719347 | AE77: 0.00031504853 | AF77: 0.88392053 | AG77: 0.97579615 | AH77: 0.99568268 | AI77: 0.99968544 | AJ77: 1 | AK77: 1 | AL77: 1 | AM77: 0 | AN77: 0 | AO77: 09-2:5-10 | AP77: 43230 | AQ77: 1.1519204e+09 | AR77: 4284 | AS77: 100 | AT77: 0 | AU77: 100 | AV77: 0 | AW77: 0 | AX77: 0
A78: 96 | B78: 0.97878733 | C78: 20.863987 | D78: 22.685659 | E78: 0.019311279 | F78: 0.021212672 | G78: 0 | H78: 4.1265253 | I78: 4.020329 | J78: -32.434444 | K78: 12.702784 | L78: 14.915967 | M78: 16.210359 | N78: 69.936325 | O78: 67.40952 | P78: 287560.37 | Q78: 267491.7 | R78: 783.4241 | S78: 0 | T78: 0 | U78: 0.24622891 | V78: 0 | W78: 0 | X78: 0.78940181 | Y78: 0 | Z78: 0.00037264348 | AA78: 6.1615366e-05 | AB78: 0.0028557815 | AC78: 1.6981223e-06 | AD78: 0.017920919 | AE78: 0.0072628806 | AF78: 0.83756179 | AG78: 0.9634191 | AH78: 0.99677143 | AI78: 0.99976356 | AJ78: 1 | AK78: 1 | AL78: 1 | AM78: 0 | AN78: 0 | AO78: 09-3:10-15 | AP78: 43388 | AQ78: 1.6116375e+09 | AR78: 6025 | AS78: 100 | AT78: 0 | AU78: 100 | AV78: 0 | AW78: 0 | AX78: 0
A79: 96 | B79: 0.9770496 | C79: 23.805678 | D79: 24.316823 | E79: 0.022402196 | F79: 0.022950396 | G79: 0 | H79: 4.1249627 | I79: 3.996877 | J79: -30.839618 | K79: 17.616236 | L79: 14.585152 | M79: 15.98221 | N79: 69.064701 | O79: 66.273359 | P79: 294113.95 | Q79: 273704.23 | R79: 783.7665 | S79: 0 | T79: 0 | U79: 0.25910044 | V79: 0 | W79: 0 | X79: 0.81223351 | Y79: 0 | Z79: 0.00036983754 | AA79: 6.0334906e-05 | AB79: 0.0028946161 | AC79: 3.991291e-06 | AD79: 0.019621602 | AE79: 0.013918083 | AF79: 0.79075428 | AG79: 0.93225234 | AH79: 0.99252337 | AI79: 0.99853656 | AJ79: 1 | AK79: 1 | AL79: 1 | AM79: 0 | AN79: 0 | AO79: 09-4:15-20 | AP79: 15-20 | AQ79: 2.4564955e+09 | AR79: 8975 | AS79: 100 | AT79: 0 | AU79: 100 | AV79: 0 | AW79: 0 | AX79: 0
A80: 96 | B80: 0.97500255 | C80: 30.879326 | D80: 26.197848 | E80: 0.030307589 | F80: 0.024997449 | G80: 0 | H80: 4.1179547 | I80: 3.9652869 | J80: -30.422156 | K80: 22.590179 | L80: 14.16522 | M80: 15.924105 | N80: 66.216865 | O80: 63.242575 | P80: 301198.07 | Q80: 281802.72 | R80: 784.11376 | S80: 0 | T80: 0 | U80: 0.26559685 | V80: 0 | W80: 0 | X80: 0.84041247 | Y80: 0 | Z80: 0.00036890884 | AA80: 5.481214e-05 | AB80: 0.0029440371 | AC80: 5.5388258e-06 | AD80: 0.021624138 | AE80: 0.019702368 | AF80: 0.75383705 | AG80: 0.92120141 | AH80: 0.99290227 | AI80: 0.99818661 | AJ80: 1 | AK80: 1 | AL80: 1 | AM80: 0 | AN80: 0 | AO80: 09:0-25 | AP80: 0-25 | AQ80: 3.3771238e+09 | AR80: 11984 | AS80: 100 | AT80: 0 | AU80: 100 | AV80: 0 | AW80: 0 | AX80: 0
A81: 96 | B81: 0.97309602 | C81: 35.002482 | D81: 27.91111 | E81: 0.035264934 | F81: 0.026903983 | G81: 0 | H81: 4.1320208 | I81: 3.9390589 | J81: -29.076316 | K81: 27.547268 | L81: 13.906361 | M81: 15.993033 | N81: 66.040052 | O81: 62.599358 | P81: 306080.2 | Q81: 287059.91 | R81: 783.65888 | S81: 0 | T81: 0 | U81: 0.25886295 | V81: 0 | W81: 0 | X81: 0.83429079 | Y81: 0 | Z81: 0.00036785539 | AA81: 5.6192523e-05 | AB81: 0.0030018129 | AC81: 8.3068484e-06 | AD81: 0.023469801 | AE81: 0.025956585 | AF81: 0.71356769 | AG81: 0.90914449 | AH81: 0.99017706 | AI81: 0.99715789 | AJ81: 1 | AK81: 1 | AL81: 1 | AM81: 0 | AN81: 0 | AO81: 10-1:25-30 | AP81: 25-30 | AQ81: 3.9548243e+09 | AR81: 13777 | AS81: 100 | AT81: 0 | AU81: 100 | AV81: 0 | AW81: 0 | AX81: 0
A82: 96 | B82: 0.97091667 | C82: 37.322085 | D82: 29.824829 | E82: 0.038182049 | F82: 0.029083332 | G82: 0 | H82: 4.1277907 | I82: 3.8973419 | J82: -28.48197 | K82: 32.542028 | L82: 13.669151 | M82: 16.000816 | N82: 65.147319 | O82: 61.460064 | P82: 311128.71 | Q82: 292033.55 | R82: 784.2264 | S82: 0 | T82: 0 | U82: 0.27340684 | V82: 0 | W82: 0 | X82: 0.84854343 | Y82: 0 | Z82: 0.00036784593 | AA82: 5.5420989e-05 | AB82: 0.0030536814 | AC82: 1.0630446e-05 | AD82: 0.025595739 | AE82: 0.034819176 | AF82: 0.67057978 | AG82: 0.87480962 | AH82: 0.99030351 | AI82: 0.99805259 | AJ82: 1 | AK82: 1 | AL82: 1 | AM82: 0 | AN82: 0 | AO82: 10-2:30-35 | AP82: 30-35 | AQ82: 4.3907244e+09 | AR82: 15035 | AS82: 100 | AT82: 0 | AU82: 100 | AV82: 0 | AW82: 0 | AX82: 0
A83: 96 | B83: 0.96906112 | C83: 39.012061 | D83: 31.41739 | E83: 0.040370339 | F83: 0.030938884 | G83: 0 | H83: 4.1407288 | I83: 3.8616035 | J83: -27.749282 | K83: 37.486494 | L83: 13.666565 | M83: 16.088478 | N83: 65.027498 | O83: 60.962342 | P83: 310640.52 | Q83: 292099.2 | R83: 783.91532 | S83: 0 | T83: 0 | U83: 0.2741301 | V83: 0 | W83: 0 | X83: 0.83728411 | Y83: 0 | Z83: 0.00036729239 | AA83: 5.4592609e-05 | AB83: 0.0031091513 | AC83: 1.1568735e-05 | AD83: 0.027396265 | AE83: 0.03772466 | AF83: 0.64459273 | AG83: 0.89988018 | AH83: 0.98723352 | AI83: 0.99853076 | AJ83: 1 | AK83: 1 | AL83: 1 | AM83: 0 | AN83: 0 | AO83: 10-3:35-40 | AP83: 35-40 | AQ83: 4.437571e+09 | AR83: 15192 | AS83: 100 | AT83: 0 | AU83: 100 | AV83: 0 | AW83: 0 | AX83: 0
A84: 96 | B84: 0.96673686 | C84: 42.22908 | D84: 33.365473 | E84: 0.044694143 | F84: 0.033263142 | G84: 0 | H84: 4.1633655 | I84: 3.8333468 | J84: -26.642684 | K84: 42.421648 | L84: 13.534384 | M84: 16.218482 | N84: 65.216204 | O84: 60.830955 | P84: 314000.99 | Q84: 294944.17 | R84: 783.87257 | S84: 0 | T84: 0 | U84: 0.28137819 | V84: 0 | W84: 0 | X84: 0.84062486 | Y84: 0 | Z84: 0.00036878211 | AA84: 5.6210012e-05 | AB84: 0.0031894474 | AC84: 1.2788838e-05 | AD84: 0.0296359 | AE84: 0.045297538 | AF84: 0.60042005 | AG84: 0.88244543 | AH84: 0.98714774 | AI84: 0.99890422 | AJ84: 1 | AK84: 1 | AL84: 1 | AM84: 0 | AN84: 0 | AO84: 10-4:40-45 | AP84: 40-45 | AQ84: 4.22655e+09 | AR84: 14330 | AS84: 100 | AT84: 0 | AU84: 100 | AV84: 0 | AW84: 0 | AX84: 0
A85: 96 | B85: 0.96427214 | C85: 42.385461 | D85: 35.375762 | E85: 0.044909905 | F85: 0.03572786 | G85: 0 | H85: 4.2053802 | I85: 3.8264175 | J85: -24.852095 | K85: 47.512004 | L85: 13.408458 | M85: 16.551013 | N85: 63.837087 | O85: 59.481399 | P85: 317484.72 | Q85: 297704.26 | R85: 783.68172 | S85: 0 | T85: 0 | U85: 0.26473142 | V85: 0 | W85: 0 | X85: 0.83669717 | Y85: 0 | Z85: 0.00036870671 | AA85: 6.3072e-05 | AB85: 0.0032262464 | AC85: 1.1692417e-05 | AD85: 0.032058128 | AE85: 0.048102621 | AF85: 0.59401179 | AG85: 0.894599 | AH85: 0.98843402 | AI85: 0.99877181 | AJ85: 1 | AK85: 1 | AL85: 1 | AM85: 0 | AN85: 0 | AO85: 10:25-50 | AP85: 25-50 | AQ85: 3.970184e+09 | AR85: 13336 | AS85: 100 | AT85: 0 | AU85: 100 | AV85: 0 | AW85: 0 | AX85: 0
A86: 96 | B86: 0.96322012 | C86: 45.94881 | D86: 36.216764 | E86: 0.049977761 | F86: 0.03677988 | G86: 0 | H86: 4.3069906 | I86: 3.8478541 | J86: -20.720569 | K86: 52.525414 | L86: 14.016152 | M86: 17.198522 | N86: 68.242989 | O86: 64.029642 | P86: 304170.72 | Q86: 284836.96 | R86: 782.53178 | S86: 0 | T86: 0 | U86: 0.23335837 | V86: 0 | W86: 0 | X86: 0.78723007 | Y86: 0 | Z86: 0.00036939263 | AA86: 7.320563e-05 | AB86: 0.003292512 | AC86: 9.5123652e-06 | AD86: 0.033035244 | AE86: 0.036502937 | AF86: 0.64151773 | AG86: 0.92290871 | AH86: 0.99178883 | AI86: 0.99919605 | AJ86: 1 | AK86: 1 | AL86: 1 | AM86: 0 | AN86: 0 | AO86: 11-1:50-55 | AP86: 50-55 | AQ86: 3.3368649e+09 | AR86: 11715 | AS86: 100 | AT86: 0 | AU86: 100 | AV86: 0 | AW86: 0 | AX86: 0
A87: 96 | B87: 0.96136775 | C87: 46.558381 | D87: 37.673235 | E87: 0.050875245 | F87: 0.03863225 | G87: 0 | H87: 4.3549524 | I87: 3.8473489 | J87: -19.564977 | K87: 57.496639 | L87: 14.11715 | M87: 17.497986 | N87: 67.040302 | O87: 63.041882 | P87: 301948.14 | Q87: 282804.23 | R87: 782.7508 | S87: 0 | T87: 0 | U87: 0.23700387 | V87: 0 | W87: 0 | X87: 0.7946447 | Y87: 0 | Z87: 0.00037049836 | AA87: 7.9962251e-05 | AB87: 0.0032937244 | AC87: 9.5781815e-06 | AD87: 0.034878473 | AE87: 0.035495696 | AF87: 0.64955835 | AG87: 0.92574536 | AH87: 0.99177366 | AI87: 0.99928007 | AJ87: 1 | AK87: 1 | AL87: 1 | AM87: 0 | AN87: 0 | AO87: 11-2:55-60 | AP87: 55-60 | AQ87: 3.2431989e+09 | AR87: 11468 | AS87: 100 | AT87: 0 | AU87: 100 | AV87: 0 | AW87: 0 | AX87: 0
A88: 96 | B88: 0.95957318 | C88: 48.369596 | D88: 39.055121 | E88: 0.053598413 | F88: 0.040426819 | G88: 0 | H88: 4.4317836 | I88: 3.8676266 | J88: -17.320993 | K88: 62.446297 | L88: 14.268627 | M88: 17.677067 | N88: 67.785288 | O88: 63.997449 | P88: 299854.45 | Q88: 279810.88 | R88: 782.07668 | S88: 0 | T88: 0 | U88: 0.24171011 | V88: 0 | W88: 0 | X88: 0.7615655 | Y88: 0 | Z88: 0.00037112525 | AA88: 8.7893186e-05 | AB88: 0.0032842944 | AC88: 9.3430351e-06 | AD88: 0.036674149 | AE88: 0.029339693 | AF88: 0.67731442 | AG88: 0.95454812 | AH88: 0.9935198 | AI88: 0.99882705 | AJ88: 1 | AK88: 1 | AL88: 1 | AM88: 0 | AN88: 0 | AO88: 11-3:60-65 | AP88: 60-65 | AQ88: 3.1971192e+09 | AR88: 11426 | AS88: 100 | AT88: 0 | AU88: 100 | AV88: 0 | AW88: 0 | AX88: 0
A89: 96 | B89: 0.95829379 | C89: 47.925493 | D89: 40.023093 | E89: 0.052922693 | F89: 0.041706214 | G89: 0 | H89: 4.5097981 | I89: 3.8948256 | J89: -15.446203 | K89: 67.445449 | L89: 14.416026 | M89: 17.656688 | N89: 68.110467 | O89: 64.532312 | P89: 297098.96 | Q89: 276954.95 | R89: 781.66658 | S89: 0 | T89: 0 | U89: 0.25422807 | V89: 0 | W89: 0 | X89: 0.73625999 | Y89: 0 | Z89: 0.00037198959 | AA89: 9.4553738e-05 | AB89: 0.0032602506 | AC89: 9.793879e-06 | AD89: 0.037969612 | AE89: 0.025062074 | AF89: 0.69109475 | AG89: 0.95240101 | AH89: 0.9939466 | AI89: 0.9989057 | AJ89: 1 | AK89: 1 | AL89: 1 | AM89: 0 | AN89: 0 | AO89: 11-4:65-70 | AP89: 65-70 | AQ89: 3.1955062e+09 | AR89: 11538 | AS89: 100 | AT89: 0 | AU89: 100 | AV89: 0 | AW89: 0 | AX89: 0
A90: 96 | B90: 0.95612858 | C90: 47.771931 | D90: 41.629205 | E90: 0.052690271 | F90: 0.043871419 | G90: 0 | H90: 4.5482527 | I90: 3.8964832 | J90: -14.674258 | K90: 72.47937 | L90: 14.154327 | M90: 17.524574 | N90: 66.514625 | O90: 62.894369 | P90: 301721.94 | Q90: 282076.09 | R90: 781.79005 | S90: 0 | T90: 0 | U90: 0.26510072 | V90: 0 | W90: 0 | X90: 0.73703351 | Y90: 0 | Z90: 0.00037079033 | AA90: 9.7058762e-05 | AB90: 0.0032567595 | AC90: 1.0567251e-05 | AD90: 0.040136228 | AE90: 0.027329153 | AF90: 0.66455656 | AG90: 0.95302023 | AH90: 0.9934843 | AI90: 0.99899335 | AJ90: 1 | AK90: 1 | AL90: 1 | AM90: 0 | AN90: 0 | AO90: 11:50-75 | AP90: 50-75 | AQ90: 3.2653128e+09 | AR90: 11576 | AS90: 100 | AT90: 0 | AU90: 100 | AV90: 0 | AW90: 0 | AX90: 0
... A96: 96 | B96: 0.93636927 | C96: 47.495831 | D96: 54.567584 | E96: 0.052273955 | F96: 0.06363073 | G96: 0 | H96: 5.1962175 | I96: 3.6487088 | J96: 17.28872 | K96: 209.55229 | L96: 14.52586 | M96: 20.792683 | N96: 90.120235 | O96: 75.17575 | P96: 294450.4 | Q96: 274910.83 | R96: 775.39517 | S96: 0 | T96: 0 | U96: 0.083777428 | V96: 0 | W96: 0 | X96: 0.28831945 | Y96: 0 | Z96: 0.00037198764 | AA96: 0.00037985115 | AB96: 0.0043843365 | AC96: 0.0005945363 | AD96: 0.057900001 | AE96: 0.16459065 | AF96: 0 | AG96: 0.46714353 | AH96: 0.67606014 | AI96: 0.98161705 | AJ96: 1 | AK96: 1 | AL96: 1 | AM96: 0 | AN96: 0 | AO96: 17:200-225 | AP96: 200-225 | AQ96: 20893223 | AR96: 76 | AS96: 100 | AT96: 0 | AU96: 100 | AV96: 0 | AW96: 0 | AX96: 0
L99: elbow | M99: 15bps earlier
L100: Channel Dial | M100: 1.05
K102: turn | L102: cash | M102: refi | R102: turn | W102: cash | AB102: refi
A103: incentive | B103: =AQ68 -> Balance | C103: =AO68 -> groupByColumn | D103: =E68 -> PREPAY_SMM1 | E103: =F68 -> PREPAY_TRACKING_SMM1 | F103: ratio | G103: =C68 -> PREPAY_CPR1 | H103: =D68 -> PREPAY_TRACKING_CPR1 | K103: adj | L103: adj | M103: adj | N103: mdl_smm | O103: mdl_cpr | P103: ratio | R103: x | T103: Knot | U103: adj Knot | W103: x | X103: adj x | Y103: Knot | Z103: adj Knot | AB103: x | AC103: adj x | AD103: Knot | AE103: adj Knot
A104: =K69 -> -56.682817 | B104: =AQ69/1000000000 -> 0.017345799 | C104: =AO69 -> 06:-75--50 | D104: =E69 -> 0.003305947 | E104: =Z69+AA69+AB69+AC69+AD69 -> 0.0081715667 | F104: =D104/E104 -> 0.4045671 | G104: =(1-(1-D104)^12)*100 -> 3.8957922 | H104: =(1-(1-E104)^12)*100 -> 9.3769548 | K104: =VLOOKUP(C104,$C$26:$M$44,9,0) -> 1 | L104: =VLOOKUP(C104,$C$26:$M$44,10,0) -> 1 | M104: =VLOOKUP(C104,$C$26:$M$44,11,0) -> 0.5 | N104: =Z69+AA69+AB69*K104+AC69*L104+AD69*M104*$M$100 -> 0.0058967502 | O104: =100*(1-(1-N104)^12) -> 6.8510589 | P104: =D104/N104 -> 0.56063881 | S104: =A104 -> -56.682817 | T104: =VLOOKUP(ROUNDDOWN(S104,0),'Spline Pre-Adj'!A:B,2,0) -> 1.2795489 | U104: =T104*K104 -> 1.2795489 | X104: =A104 -> -56.682817 | Y104: =VLOOKUP(ROUNDDOWN(X104,0),'Spline Pre-Adj'!F:G,2,0) -> 0.18862313 | Z104: =Y104*L104 -> 0.18862313 | AC104: =A104 -> -56.682817 | AD104: =VLOOKUP(ROUNDDOWN(AC104,0),'Spline Pre-Adj'!K:L,2,0) -> 0 | AE104: =AD104*M104 -> 0
A105: =K70 -> -32.151317 | B105: =AQ70/1000000000 -> 0.18285969 | C105: =AO70 -> 07:-50--25 | D105: =E70 -> 0.00215821 | E105: =Z70+AA70+AB70+AC70+AD70 -> 0.0085332227 | F105: =D105/E105 -> 0.25291851 | G105: =(1-(1-D105)^12)*100 -> 2.5593301 | H105: =(1-(1-E105)^12)*100 -> 9.7726932 | K105: =VLOOKUP(C105,$C$26:$M$44,9,0) -> 1 | L105: =VLOOKUP(C105,$C$26:$M$44,10,0) -> 1 | M105: =VLOOKUP(C105,$C$26:$M$44,11,0) -> 0.5 | N105: =Z70+AA70+AB70*K105+AC70*L105+AD70*M105*$M$100 -> 0.0059283592 | O105: =100*(1-(1-N105)^12) -> 6.8865943 | P105: =D105/N105 -> 0.36404845 | S105: =A105 -> -32.151317 | T105: =VLOOKUP(ROUNDDOWN(S105,0),'Spline Pre-Adj'!A:B,2,0) -> 1.287 | U105: =T105*K105 -> 1.287 | X105: =A105 -> -32.151317 | Y105: =VLOOKUP(ROUNDDOWN(X105,0),'Spline Pre-Adj'!F:G,2,0) -> 0.3115 | Z105: =Y105*L105 -> 0.3115 | AC105: =A105 -> -32.151317 | AD105: =VLOOKUP(ROUNDDOWN(AC105,0),'Spline Pre-Adj'!K:L,2,0) -> 0.43003694 | AE105: =AD105*M105 -> 0.21501847
A106: =K71 -> -22.234953 | B106: =AQ71/1000000000 -> 0.10425759 | C106: =AO71 -> 08-1:-25--20 | D106: =E71 -> 0.0082127038 | E106: =Z71+AA71+AB71+AC71+AD71 -> 0.011461064 | F106: =D106/E106 -> 0.71657428 | G106: =(1-(1-D106)^12)*100 -> 9.4220487 | H106: =(1-(1-E106)^12)*100 -> 12.918609 | J106: 1 | K106: =IF(ISNA(VLOOKUP(C106,$C$26:$M$44,9,0)),K107, VLOOKUP(C106,$C$26:$M$44,9,0)) -> 1 | L106: =IF(ISNA(VLOOKUP(C106,$C$26:$M$44,10,0)),L107, VLOOKUP(C106,$C$26:$M$44,10,0)) -> 1 | M106: =IF(ISNA(VLOOKUP(C106,$C$26:$M$44,11,0)),($M$111-$M$105)*J106/5+$M$105, VLOOKUP(C106,$C$26:$M$44,11,0)) -> 0.52 | N106: =Z71+AA71+AB71*K106+AC71*L106+AD74*M109*$M$100 -> 0.010973499 | O106: =100*(1-(1-N106)^12) -> 12.401807 | P106: =D106/N106 -> 0.74841252 | S106: =A106 -> -22.234953 | T106: =VLOOKUP(ROUNDDOWN(S106,0),'Spline Pre-Adj'!A:B,2,0) -> 1.287 | U106: =T106*K106 -> 1.287 | X106: =A106 -> -22.234953 | Y106: =VLOOKUP(ROUNDDOWN(X106,0),'Spline Pre-Adj'!F:G,2,0) -> 0.38089236 | Z106: =Y106*L106 -> 0.38089236 | AC106: =A106 -> -22.234953 | AD106: =VLOOKUP(ROUNDDOWN(AC106,0),'Spline Pre-Adj'!K:L,2,0) -> 0.79645948 | AE106: =AD106*M106 -> 0.41415893
A107: =K72 -> -17.320366 | B107: =AQ72/1000000000 -> 0.1750183 | C107: =AO72 -> 08-2:-20--15 | D107: =E72 -> 0.0094858256 | E107: =Z72+AA72+AB72+AC72+AD72 -> 0.013350099 | F107: =D107/E107 -> 0.71054346 | G107: =(1-(1-D107)^12)*100 -> 10.8075 | H107: =(1-(1-E107)^12)*100 -> 14.894639 | J107: 2 | K107: =IF(ISNA(VLOOKUP(C107,$C$26:$M$44,9,0)),K108, VLOOKUP(C107,$C$26:$M$44,9,0)) -> 1 | L107: =IF(ISNA(VLOOKUP(C107,$C$26:$M$44,10,0)),L108, VLOOKUP(C107,$C$26:$M$44,10,0)) -> 1 | M107: =IF(ISNA(VLOOKUP(C107,$C$26:$M$44,11,0)),($M$111-$M$105)*J107/5+$M$105, VLOOKUP(C107,$C$26:$M$44,11,0)) -> 0.54 | N107: =Z72+AA72+AB72*K107+AC72*L107+AD75*M110*$M$100 -> 0.01137813 | O107: =100*(1-(1-N107)^12) -> 12.830899 | P107: =D107/N107 -> 0.83368936 | S107: =A107 -> -17.320366 | T107: =VLOOKUP(ROUNDDOWN(S107,0),'Spline Pre-Adj'!A:B,2,0) -> 1.287 | U107: =T107*K107 -> 1.287 | X107: =A107 -> -17.320366 | Y107: =VLOOKUP(ROUNDDOWN(X107,0),'Spline Pre-Adj'!F:G,2,0) -> 0.43050425 | Z107: =Y107*L107 -> 0.43050425 | AC107: =A107 -> -17.320366 | AD107: =VLOOKUP(ROUNDDOWN(AC107,0),'Spline Pre-Adj'!K:L,2,0) -> 0.95362938 | AE107: =AD107*M107 -> 0.51495987
A108: =K73 -> -12.265261 | B108: =AQ73/1000000000 -> 0.28393432 | C108: =AO73 -> 08-3:-15--10 | D108: =E73 -> 0.0092966237 | E108: =Z73+AA73+AB73+AC73+AD73 -> 0.014747595 | F108: =D108/E108 -> 0.63038234 | G108: =(1-(1-D108)^12)*100 -> 10.602841 | H108: =(1-(1-E108)^12)*100 -> 16.329947 | J108: 3 | K108: =IF(ISNA(VLOOKUP(C108,$C$26:$M$44,9,0)),K109, VLOOKUP(C108,$C$26:$M$44,9,0)) -> 1 | L108: =IF(ISNA(VLOOKUP(C108,$C$26:$M$44,10,0)),L109, VLOOKUP(C108,$C$26:$M$44,10,0)) -> 1 | M108: =IF(ISNA(VLOOKUP(C108,$C$26:$M$44,11,0)),($M$111-$M$105)*J108/5+$M$105, VLOOKUP(C108,$C$26:$M$44,11,0)) -> 0.56 | N108: =Z73+AA73+AB73*K108+AC73*L108+AD76*M111*$M$100 -> 0.012979746 | O108: =100*(1-(1-N108)^12) -> 14.5105 | P108: =D108/N108 -> 0.71624081 | S108: =A108 -> -12.265261 | T108: =VLOOKUP(ROUNDDOWN(S108,0),'Spline Pre-Adj'!A:B,2,0) -> 1.287 | U108: =T108*K108 -> 1.287 | X108: =A108 -> -12.265261 | Y108: =VLOOKUP(ROUNDDOWN(X108,0),'Spline Pre-Adj'!F:G,2,0) -> 0.48396475 | Z108: =Y108*L108 -> 0.48396475 | AC108: =A108 -> -12.265261 | AD108: =VLOOKUP(ROUNDDOWN(AC108,0),'Spline Pre-Adj'!K:L,2,0) -> 1.0814264 | AE108: =AD108*M108 -> 0.60559876
A109: =K74 -> -7.3224373 | B109: =AQ74/1000000000 -> 0.42300995 | C109: =AO74 -> 08-4:-10--5 | D109: =E74 -> 0.014239488 | E109: =Z74+AA74+AB74+AC74+AD74 -> 0.016124271 | F109: =D109/E109 -> 0.88310892 | G109: =(1-(1-D109)^12)*100 -> 15.810679 | H109: =(1-(1-E109)^12)*100 -> 17.722144 | J109: 4 | K109: =IF(ISNA(VLOOKUP(C109,$C$26:$M$44,9,0)),K110, VLOOKUP(C109,$C$26:$M$44,9,0)) -> 1 | L109: =IF(ISNA(VLOOKUP(C109,$C$26:$M$44,10,0)),L110, VLOOKUP(C109,$C$26:$M$44,10,0)) -> 1 | M109: =IF(ISNA(VLOOKUP(C109,$C$26:$M$44,11,0)),($M$111-$M$105)*J109/5+$M$105, VLOOKUP(C109,$C$26:$M$44,11,0)) -> 0.58 | N109: =Z74+AA74+AB74*K109+AC74*L109+AD77*M112*$M$100 -> 0.01439368 | O109: =100*(1-(1-N109)^12) -> 15.968569 | P109: =D109/N109 -> 0.98928753 | S109: =A109 -> -7.3224373 | T109: =VLOOKUP(ROUNDDOWN(S109,0),'Spline Pre-Adj'!A:B,2,0) -> 1.287 | U109: =T109*K109 -> 1.287 | X109: =A109 -> -7.3224373 | Y109: =VLOOKUP(ROUNDDOWN(X109,0),'Spline Pre-Adj'!F:G,2,0) -> 0.54485561 | Z109: =Y109*L109 -> 0.54485561 | AC109: =A109 -> -7.3224373 | AD109: =VLOOKUP(ROUNDDOWN(AC109,0),'Spline Pre-Adj'!K:L,2,0) -> 1.1993278 | AE109: =AD109*M109 -> 0.69561011
A110: =K75 -> -2.3387297 | B110: =AQ75/1000000000 -> 0.62948602 | C110: =AO75 -> 08:-25-0 | D110: =E75 -> 0.012800118 | E110: =Z75+AA75+AB75+AC75+AD75 -> 0.017461379 | F110: =D110/E110 -> 0.73305309 | G110: =(1-(1-D110)^12)*100 -> 14.323614 | H110: =(1-(1-E110)^12)*100 -> 19.053968 | K110: =IF(ISNA(VLOOKUP(C110,$C$26:$M$44,9,0)),K111, VLOOKUP(C110,$C$26:$M$44,9,0)) -> 1 | L110: =IF(ISNA(VLOOKUP(C110,$C$26:$M$44,10,0)),L111, VLOOKUP(C110,$C$26:$M$44,10,0)) -> 1 | M110: =IF(ISNA(VLOOKUP(C110,$C$26:$M$44,11,0)),M111, VLOOKUP(C110,$C$26:$M$44,11,0)) -> 0.55 | N110: =Z75+AA75+AB75*K110+AC75*L110+AD78*M113*$M$100 -> 0.016231038 | O110: =100*(1-(1-N110)^12) -> 17.829223 | P110: =D110/N110 -> 0.7886198 | S110: =A110 -> -2.3387297 | T110: =VLOOKUP(ROUNDDOWN(S110,0),'Spline Pre-Adj'!A:B,2,0) -> 1.287 | U110: =T110*K110 -> 1.287 | X110: =A110 -> -2.3387297 | Y110: =VLOOKUP(ROUNDDOWN(X110,0),'Spline Pre-Adj'!F:G,2,0) -> 0.61797137 | Z110: =Y110*L110 -> 0.61797137 | AC110: =A110 -> -2.3387297 | AD110: =VLOOKUP(ROUNDDOWN(AC110,0),'Spline Pre-Adj'!K:L,2,0) -> 1.3122379 | AE110: =AD110*M110 -> 0.72173085
A111: =K76 -> 2.6535888 | B111: =AQ76/1000000000 -> 0.8579409 | C111: =AO76 -> 09-1:0-5 | D111: =E76 -> 0.017864415 | E111: =Z76+AA76+AB76+AC76+AD76 -> 0.018757781 | F111: =D111/E111 -> 0.95237357 | G111: =(1-(1-D111)^12)*100 -> 19.451517 | H111: =(1-(1-E111)^12)*100 -> 20.32635 | J111: 1 | K111: =IF(ISNA(VLOOKUP(C111,$C$26:$M$44,9,0)),K112, VLOOKUP(C111,$C$26:$M$44,9,0)) -> 1 | L111: =IF(ISNA(VLOOKUP(C111,$C$26:$M$44,10,0)),L112, VLOOKUP(C111,$C$26:$M$44,10,0)) -> 1 | M111: =IF(ISNA(VLOOKUP(C111,$C$26:$M$44,11,0)),($M$115-$M$110)*J111/5+$M$110, VLOOKUP(C111,$C$26:$M$44,11,0)) -> 0.6 | N111: =Z76+AA76+AB76*K111+AC76*L111+AD79*M114*$M$100 -> 0.018532397 | O111: =100*(1-(1-N111)^12) -> 20.106468 | P111: =D111/N111 -> 0.96395596 | S111: =A111 -> 2.6535888 | T111: =VLOOKUP(ROUNDDOWN(S111,0),'Spline Pre-Adj'!A:B,2,0) -> 1.287 | U111: =T111*K111 -> 1.287 | X111: =A111 -> 2.6535888 | Y111: =VLOOKUP(ROUNDDOWN(X111,0),'Spline Pre-Adj'!F:G,2,0) -> 0.68848781 | Z111: =Y111*L111 -> 0.68848781 | AC111: =A111 -> 2.6535888 | AD111: =VLOOKUP(ROUNDDOWN(AC111,0),'Spline Pre-Adj'!K:L,2,0) -> 1.401848 | AE111: =AD111*M111 -> 0.84110882
A112: =K77 -> 7.6198853 | B112: =AQ77/1000000000 -> 1.1519204 | C112: =AO77 -> 09-2:5-10 | D112: =E77 -> 0.022551304 | E112: =Z77+AA77+AB77+AC77+AD77 -> 0.019913971 | F112: =D112/E112 -> 1.1324363 | G112: =(1-(1-D112)^12)*100 -> 23.94502 | H112: =(1-(1-E112)^12)*100 -> 21.445625 | J112: 2 | K112: =IF(ISNA(VLOOKUP(C112,$C$26:$M$44,9,0)),K113, VLOOKUP(C112,$C$26:$M$44,9,0)) -> 1 | L112: =IF(ISNA(VLOOKUP(C112,$C$26:$M$44,10,0)),L113, VLOOKUP(C112,$C$26:$M$44,10,0)) -> 1 | M112: =IF(ISNA(VLOOKUP(C112,$C$26:$M$44,11,0)),($M$115-$M$110)*J112/5+$M$110, VLOOKUP(C112,$C$26:$M$44,11,0)) -> 0.65 | N112: =Z77+AA77+AB77*K112+AC77*L112+AD80*M115*$M$100 -> 0.0213589 | O112: =100*(1-(1-N112)^12) -> 22.824152 | P112: =D112/N112 -> 1.055827 | S112: =A112 -> 7.6198853 | T112: =VLOOKUP(ROUNDDOWN(S112,0),'Spline Pre-Adj'!A:B,2,0) -> 1.287 | U112: =T112*K112 -> 1.287 | X112: =A112 -> 7.6198853 | Y112: =VLOOKUP(ROUNDDOWN(X112,0),'Spline Pre-Adj'!F:G,2,0) -> 0.79418177 | Z112: =Y112*L112 -> 0.79418177 | AC112: =A112 -> 7.6198853 | AD112: =VLOOKUP(ROUNDDOWN(AC112,0),'Spline Pre-Adj'!K:L,2,0) -> 1.5165579 | AE112: =AD112*M112 -> 0.98576264
A113: =K78 -> 12.702784 | B113: =AQ78/1000000000 -> 1.6116375 | C113: =AO78 -> 09-3:10-15 | D113: =E78 -> 0.019311279 | E113: =Z78+AA78+AB78+AC78+AD78 -> 0.021212658 | F113: =D113/E113 -> 0.91036584 | G113: =(1-(1-D113)^12)*100 -> 20.863987 | H113: =(1-(1-E113)^12)*100 -> 22.685646 | J113: 3 | K113: =IF(ISNA(VLOOKUP(C113,$C$26:$M$44,9,0)),K114, VLOOKUP(C113,$C$26:$M$44,9,0)) -> 1 | L113: =IF(ISNA(VLOOKUP(C113,$C$26:$M$44,10,0)),L114, VLOOKUP(C113,$C$26:$M$44,10,0)) -> 1 | M113: =IF(ISNA(VLOOKUP(C113,$C$26:$M$44,11,0)),($M$115-$M$110)*J113/5+$M$110, VLOOKUP(C113,$C$26:$M$44,11,0)) -> 0.7 | N113: =Z78+AA78+AB78*K113+AC78*L113+AD81*M116*$M$100 -> 0.024238536 | O113: =100*(1-(1-N113)^12) -> 25.505545 | P113: =D113/N113 -> 0.79671805 | S113: =A113 -> 12.702784 | T113: =VLOOKUP(ROUNDDOWN(S113,0),'Spline Pre-Adj'!A:B,2,0) -> 1.287 | U113: =T113*K113 -> 1.287 | X113: =A113 -> 12.702784 | Y113: =VLOOKUP(ROUNDDOWN(X113,0),'Spline Pre-Adj'!F:G,2,0) -> 0.91120039 | Z113: =Y113*L113 -> 0.91120039 | AC113: =A113 -> 12.702784 | AD113: =VLOOKUP(ROUNDDOWN(AC113,0),'Spline Pre-Adj'!K:L,2,0) -> 1.6382588 | AE113: =AD113*M113 -> 1.1467811
A114: =K79 -> 17.616236 | B114: =AQ79/1000000000 -> 2.4564955 | C114: =AO79 -> 09-4:15-20 | D114: =E79 -> 0.022402196 | E114: =Z79+AA79+AB79+AC79+AD79 -> 0.022950382 | F114: =D114/E114 -> 0.97611431 | G114: =(1-(1-D114)^12)*100 -> 23.805678 | H114: =(1-(1-E114)^12)*100 -> 24.316809 | J114: 4 | K114: =IF(ISNA(VLOOKUP(C114,$C$26:$M$44,9,0)),K115, VLOOKUP(C114,$C$26:$M$44,9,0)) -> 1 | L114: =IF(ISNA(VLOOKUP(C114,$C$26:$M$44,10,0)),L115, VLOOKUP(C114,$C$26:$M$44,10,0)) -> 1 | M114: =IF(ISNA(VLOOKUP(C114,$C$26:$M$44,11,0)),($M$115-$M$110)*J114/5+$M$110, VLOOKUP(C114,$C$26:$M$44,11,0)) -> 0.75 | N114: =Z79+AA79+AB79*K114+AC79*L114+AD82*M117*$M$100 -> 0.027516754 | O114: =100*(1-(1-N114)^12) -> 28.45397 | P114: =D114/N114 -> 0.81412933 | X114: =A114 -> 17.616236 | Y114: =VLOOKUP(ROUNDDOWN(X114,0),'Spline Pre-Adj'!F:G,2,0) -> 1.044224 | Z114: =Y114*L114 -> 1.044224 | AC114: =A114 -> 17.616236 | AD114: =VLOOKUP(ROUNDDOWN(AC114,0),'Spline Pre-Adj'!K:L,2,0) -> 1.77123 | AE114: =AD114*M114 -> 1.3284225
A115: =K80 -> 22.590179 | B115: =AQ80/1000000000 -> 3.3771238 | C115: =AO80 -> 09:0-25 | D115: =E80 -> 0.030307589 | E115: =Z80+AA80+AB80+AC80+AD80 -> 0.024997435 | F115: =D115/E115 -> 1.212428 | G115: =(1-(1-D115)^12)*100 -> 30.879326 | H115: =(1-(1-E115)^12)*100 -> 26.197835 | K115: =IF(ISNA(VLOOKUP(C115,$C$26:$M$44,9,0)),K116, VLOOKUP(C115,$C$26:$M$44,9,0)) -> 1 | L115: =IF(ISNA(VLOOKUP(C115,$C$26:$M$44,10,0)),L116, VLOOKUP(C115,$C$26:$M$44,10,0)) -> 1 | M115: =IF(ISNA(VLOOKUP(C115,$C$26:$M$44,11,0)),M116, VLOOKUP(C115,$C$26:$M$44,11,0)) -> 0.8 | N115: =Z80+AA80+AB80*K115+AC80*L115+AD83*M118*$M$100 -> 0.030701071 | O115: =100*(1-(1-N115)^12) -> 31.21515 | P115: =D115/N115 -> 0.98718343 | X115: =A115 -> 22.590179 | Y115: =VLOOKUP(ROUNDDOWN(X115,0),'Spline Pre-Adj'!F:G,2,0) -> 1.2015373 | Z115: =Y115*L115 -> 1.2015373 | AC115: =A115 -> 22.590179 | AD115: =VLOOKUP(ROUNDDOWN(AC115,0),'Spline Pre-Adj'!K:L,2,0) -> 1.9188346 | AE115: =AD115*M115 -> 1.5350677
A116: =K81 -> 27.547268 | B116: =AQ81/1000000000 -> 3.9548243 | C116: =AO81 -> 10-1:25-30 | D116: =E81 -> 0.035264934 | E116: =Z81+AA81+AB81+AC81+AD81 -> 0.026903969 | F116: =D116/E116 -> 1.3107707 | G116: =(1-(1-D116)^12)*100 -> 35.002482 | H116: =(1-(1-E116)^12)*100 -> 27.911097 | J116: 1 | K116: =IF(ISNA(VLOOKUP(C116,$C$26:$M$44,9,0)),K117, VLOOKUP(C116,$C$26:$M$44,9,0)) -> 1 | L116: =IF(ISNA(VLOOKUP(C116,$C$26:$M$44,10,0)),L117, VLOOKUP(C116,$C$26:$M$44,10,0)) -> 1 | M116: =IF(ISNA(VLOOKUP(C116,$C$26:$M$44,11,0)),($M$120-$M$115)*J116/5+$M$115, VLOOKUP(C116,$C$26:$M$44,11,0)) -> 0.85 | N116: =Z81+AA81+AB81*K116+AC81*L116+AD84*M119*$M$100 -> 0.034551862 | O116: =100*(1-(1-N116)^12) -> 34.423627 | P116: =D116/N116 -> 1.0206377 | X116: =A116 -> 27.547268 | Y116: =VLOOKUP(ROUNDDOWN(X116,0),'Spline Pre-Adj'!F:G,2,0) -> 1.3914246 | Z116: =Y116*L116 -> 1.3914246 | AC116: =A116 -> 27.547268 | AD116: =VLOOKUP(ROUNDDOWN(AC116,0),'Spline Pre-Adj'!K:L,2,0) -> 2.0788177 | AE116: =AD116*M116 -> 1.7669951
A117: =K82 -> 32.542028 | B117: =AQ82/1000000000 -> 4.3907244 | C117: =AO82 -> 10-2:30-35 | D117: =E82 -> 0.038182049 | E117: =Z82+AA82+AB82+AC82+AD82 -> 0.029083318 | F117: =D117/E117 -> 1.3128505 | G117: =(1-(1-D117)^12)*100 -> 37.322085 | H117: =(1-(1-E117)^12)*100 -> 29.824817 | J117: 2 | K117: =IF(ISNA(VLOOKUP(C117,$C$26:$M$44,9,0)),K118, VLOOKUP(C117,$C$26:$M$44,9,0)) -> 1 | L117: =IF(ISNA(VLOOKUP(C117,$C$26:$M$44,10,0)),L118, VLOOKUP(C117,$C$26:$M$44,10,0)) -> 1 | M117: =IF(ISNA(VLOOKUP(C117,$C$26:$M$44,11,0)),($M$120-$M$115)*2/5+$M$115, VLOOKUP(C117,$C$26:$M$44,11,0)) -> 0.9 | N117: =Z82+AA82+AB82*K117+AC82*L117+AD85*M120*$M$100 -> 0.038831665 | O117: =100*(1-(1-N117)^12) -> 37.828197 | P117: =D117/N117 -> 0.98327099 | X117: =A117 -> 32.542028 | Y117: =VLOOKUP(ROUNDDOWN(X117,0),'Spline Pre-Adj'!F:G,2,0) -> 1.6233323 | Z117: =Y117*L117 -> 1.6233323 | AC117: =A117 -> 32.542028 | AD117: =VLOOKUP(ROUNDDOWN(AC117,0),'Spline Pre-Adj'!K:L,2,0) -> 2.2487417 | AE117: =AD117*M117 -> 2.0238675
A118: =K83 -> 37.486494 | B118: =AQ83/1000000000 -> 4.437571 | C118: =AO83 -> 10-3:35-40 | D118: =E83 -> 0.040370339 | E118: =Z83+AA83+AB83+AC83+AD83 -> 0.03093887 | F118: =D118/E118 -> 1.3048421 | G118: =(1-(1-D118)^12)*100 -> 39.012061 | H118: =(1-(1-E118)^12)*100 -> 31.417378 | J118: 3 | K118: =IF(ISNA(VLOOKUP(C118,$C$26:$M$44,9,0)),K119, VLOOKUP(C118,$C$26:$M$44,9,0)) -> 1 | L118: =IF(ISNA(VLOOKUP(C118,$C$26:$M$44,10,0)),L119, VLOOKUP(C118,$C$26:$M$44,10,0)) -> 1 | M118: =IF(ISNA(VLOOKUP(C118,$C$26:$M$44,11,0)),($M$120-$M$115)*3/5+$M$115, VLOOKUP(C118,$C$26:$M$44,11,0)) -> 0.95 | N118: =Z83+AA83+AB83*K118+AC83*L118+AD86*M121*$M$100 -> 0.041698311 | O118: =100*(1-(1-N118)^12) -> 40.017158 | P118: =D118/N118 -> 0.96815286 | X118: =A118 -> 37.486494 | Y118: =VLOOKUP(ROUNDDOWN(X118,0),'Spline Pre-Adj'!F:G,2,0) -> 1.8953738 | Z118: =Y118*L118 -> 1.8953738 | AC118: =A118 -> 37.486494 | AD118: =VLOOKUP(ROUNDDOWN(AC118,0),'Spline Pre-Adj'!K:L,2,0) -> 2.4264029 | AE118: =AD118*M118 -> 2.3050828
A119: =K84 -> 42.421648 | B119: =AQ84/1000000000 -> 4.22655 | C119: =AO84 -> 10-4:40-45 | D119: =E84 -> 0.044694143 | E119: =Z84+AA84+AB84+AC84+AD84 -> 0.033263128 | F119: =D119/E119 -> 1.3436542 | G119: =(1-(1-D119)^12)*100 -> 42.22908 | H119: =(1-(1-E119)^12)*100 -> 33.365461 | J119: 4 | K119: =IF(ISNA(VLOOKUP(C119,$C$26:$M$44,9,0)),K120, VLOOKUP(C119,$C$26:$M$44,9,0)) -> 1 | L119: =IF(ISNA(VLOOKUP(C119,$C$26:$M$44,10,0)),L120, VLOOKUP(C119,$C$26:$M$44,10,0)) -> 1 | M119: =IF(ISNA(VLOOKUP(C119,$C$26:$M$44,11,0)),($M$120-$M$115)*4/5+$M$115, VLOOKUP(C119,$C$26:$M$44,11,0)) -> 1 | N119: =Z84+AA84+AB84*K119+AC84*L119+AD87*M122*$M$100 -> 0.043911864 | O119: =100*(1-(1-N119)^12) -> 41.658828 | P119: =D119/N119 -> 1.0178147 | X119: =A119 -> 42.421648 | Y119: =VLOOKUP(ROUNDDOWN(X119,0),'Spline Pre-Adj'!F:G,2,0) -> 2.1927888 | Z119: =Y119*L119 -> 2.1927888 | AC119: =A119 -> 42.421648 | AD119: =VLOOKUP(ROUNDDOWN(AC119,0),'Spline Pre-Adj'!K:L,2,0) -> 2.609598 | AE119: =AD119*M119 -> 2.609598
A120: =K85 -> 47.512004 | B120: =AQ85/1000000000 -> 3.970184 | C120: =AO85 -> 10:25-50 | D120: =E85 -> 0.044909905 | E120: =Z85+AA85+AB85+AC85+AD85 -> 0.035727845 | F120: =D120/E120 -> 1.2570001 | G120: =(1-(1-D120)^12)*100 -> 42.385461 | H120: =(1-(1-E120)^12)*100 -> 35.375751 | K120: =IF(ISNA(VLOOKUP(C120,$C$26:$M$44,9,0)),K121, VLOOKUP(C120,$C$26:$M$44,9,0)) -> 1 | L120: =IF(ISNA(VLOOKUP(C120,$C$26:$M$44,10,0)),L121, VLOOKUP(C120,$C$26:$M$44,10,0)) -> 1 | M120: =IF(ISNA(VLOOKUP(C120,$C$26:$M$44,11,0)),M121, VLOOKUP(C120,$C$26:$M$44,11,0)) -> 1.05 | N120: =Z85+AA85+AB85*K120+AC85*L120+AD88*M123*$M$100 -> 0.046028359 | O120: =100*(1-(1-N120)^12) -> 43.189898 | P120: =D120/N120 -> 0.97570076 | X120: =A120 -> 47.512004 | Y120: =VLOOKUP(ROUNDDOWN(X120,0),'Spline Pre-Adj'!F:G,2,0) -> 2.5005892 | Z120: =Y120*L120 -> 2.5005892 | AC120: =A120 -> 47.512004 | AD120: =VLOOKUP(ROUNDDOWN(AC120,0),'Spline Pre-Adj'!K:L,2,0) -> 2.7961235 | AE120: =AD120*M120 -> 2.9359297
A121: =K86 -> 52.525414 | B121: =AQ86/1000000000 -> 3.3368649 | C121: =AO86 -> 11-1:50-55 | D121: =E86 -> 0.049977761 | E121: =Z86+AA86+AB86+AC86+AD86 -> 0.036779866 | F121: =D121/E121 -> 1.3588348 | G121: =(1-(1-D121)^12)*100 -> 45.94881 | H121: =(1-(1-E121)^12)*100 -> 36.216753 | K121: =IF(ISNA(VLOOKUP(C121,$C$26:$M$44,9,0)),K122, VLOOKUP(C121,$C$26:$M$44,9,0)) -> 1 | L121: =IF(ISNA(VLOOKUP(C121,$C$26:$M$44,10,0)),L122, VLOOKUP(C121,$C$26:$M$44,10,0)) -> 1 | M121: =IF(ISNA(VLOOKUP(C121,$C$26:$M$44,11,0)),M122, VLOOKUP(C121,$C$26:$M$44,11,0)) -> 1.1 | N121: =Z86+AA86+AB86*K121+AC86*L121+AD89*M124*$M$100 -> 0.047599524 | O121: =100*(1-(1-N121)^12) -> 44.302559 | P121: =D121/N121 -> 1.0499635 | X121: =A121 -> 52.525414 | Y121: =VLOOKUP(ROUNDDOWN(X121,0),'Spline Pre-Adj'!F:G,2,0) -> 2.8037869 | Z121: =Y121*L121 -> 2.8037869 | AC121: =A121 -> 52.525414 | AD121: =VLOOKUP(ROUNDDOWN(AC121,0),'Spline Pre-Adj'!K:L,2,0) -> 2.983776 | AE121: =AD121*M121 -> 3.2821536
A122: =K87 -> 57.496639 | B122: =AQ87/1000000000 -> 3.2431989 | C122: =AO87 -> 11-2:55-60 | D122: =E87 -> 0.050875245 | E122: =Z87+AA87+AB87+AC87+AD87 -> 0.038632236 | F122: =D122/E122 -> 1.3169117 | G122: =(1-(1-D122)^12)*100 -> 46.558381 | H122: =(1-(1-E122)^12)*100 -> 37.673223 | K122: =IF(ISNA(VLOOKUP(C122,$C$26:$M$44,9,0)),K123, VLOOKUP(C122,$C$26:$M$44,9,0)) -> 1 | L122: =IF(ISNA(VLOOKUP(C122,$C$26:$M$44,10,0)),L123, VLOOKUP(C122,$C$26:$M$44,10,0)) -> 1 | M122: =IF(ISNA(VLOOKUP(C122,$C$26:$M$44,11,0)),M123, VLOOKUP(C122,$C$26:$M$44,11,0)) -> 1.1 | N122: =Z87+AA87+AB87*K122+AC87*L122+AD90*M125*$M$100 -> 0.050111107 | O122: =100*(1-(1-N122)^12) -> 46.039779 | P122: =D122/N122 -> 1.0152489 | X122: =A122 -> 57.496639 | Y122: =VLOOKUP(ROUNDDOWN(X122,0),'Spline Pre-Adj'!F:G,2,0) -> 3.092616 | Z122: =Y122*L122 -> 3.092616 | AC122: =A122 -> 57.496639 | AD122: =VLOOKUP(ROUNDDOWN(AC122,0),'Spline Pre-Adj'!K:L,2,0) -> 3.1703521 | AE122: =AD122*M122 -> 3.4873873
A123: =K88 -> 62.446297 | B123: =AQ88/1000000000 -> 3.1971192 | C123: =AO88 -> 11-3:60-65 | D123: =E88 -> 0.053598413 | E123: =Z88+AA88+AB88+AC88+AD88 -> 0.040426805 | F123: =D123/E123 -> 1.3258137 | G123: =(1-(1-D123)^12)*100 -> 48.369596 | H123: =(1-(1-E123)^12)*100 -> 39.05511 | K123: =IF(ISNA(VLOOKUP(C123,$C$26:$M$44,9,0)),K124, VLOOKUP(C123,$C$26:$M$44,9,0)) -> 1 | L123: =IF(ISNA(VLOOKUP(C123,$C$26:$M$44,10,0)),L124, VLOOKUP(C123,$C$26:$M$44,10,0)) -> 1 | M123: =IF(ISNA(VLOOKUP(C123,$C$26:$M$44,11,0)),M124, VLOOKUP(C123,$C$26:$M$44,11,0)) -> 1.1 | N123: =Z88+AA88+AB88*K123+AC88*L123+AD91*M126*$M$100 -> 0.050196177 | O123: =100*(1-(1-N123)^12) -> 46.097742 | P123: =D123/N123 -> 1.0677788 | X123: =A123 -> 62.446297 | Y123: =VLOOKUP(ROUNDDOWN(X123,0),'Spline Pre-Adj'!F:G,2,0) -> 3.3799458 | Z123: =Y123*L123 -> 3.3799458 | AC123: =A123 -> 62.446297 | AD123: =VLOOKUP(ROUNDDOWN(AC123,0),'Spline Pre-Adj'!K:L,2,0) -> 3.3536482 | AE123: =AD123*M123 -> 3.689013
A124: =K89 -> 67.445449 | B124: =AQ89/1000000000 -> 3.1955062 | C124: =AO89 -> 11-4:65-70 | D124: =E89 -> 0.052922693 | E124: =Z89+AA89+AB89+AC89+AD89 -> 0.0417062 | F124: =D124/E124 -> 1.2689407 | G124: =(1-(1-D124)^12)*100 -> 47.925493 | H124: =(1-(1-E124)^12)*100 -> 40.023082 | K124: =IF(ISNA(VLOOKUP(C124,$C$26:$M$44,9,0)),K125, VLOOKUP(C124,$C$26:$M$44,9,0)) -> 1 | L124: =IF(ISNA(VLOOKUP(C124,$C$26:$M$44,10,0)),L125, VLOOKUP(C124,$C$26:$M$44,10,0)) -> 1 | M124: =IF(ISNA(VLOOKUP(C124,$C$26:$M$44,11,0)),M125, VLOOKUP(C124,$C$26:$M$44,11,0)) -> 1.1 | N124: =Z89+AA89+AB89*K124+AC89*L124+AD92*M127*$M$100 -> 0.050827192 | O124: =100*(1-(1-N124)^12) -> 46.525903 | P124: =D124/N124 -> 1.041228 | X124: =A124 -> 67.445449 | Y124: =VLOOKUP(ROUNDDOWN(X124,0),'Spline Pre-Adj'!F:G,2,0) -> 3.6676855 | Z124: =Y124*L124 -> 3.6676855 | AC124: =A124 -> 67.445449 | AD124: =VLOOKUP(ROUNDDOWN(AC124,0),'Spline Pre-Adj'!K:L,2,0) -> 3.531461 | AE124: =AD124*M124 -> 3.8846071
A125: =K90 -> 72.47937 | B125: =AQ90/1000000000 -> 3.2653128 | C125: =AO90 -> 11:50-75 | D125: =E90 -> 0.052690271 | E125: =Z90+AA90+AB90+AC90+AD90 -> 0.043871404 | F125: =D125/E125 -> 1.2010163 | G125: =(1-(1-D125)^12)*100 -> 47.771931 | H125: =(1-(1-E125)^12)*100 -> 41.629194 | K125: =IF(ISNA(VLOOKUP(C125,$C$26:$M$44,9,0)),K126, VLOOKUP(C125,$C$26:$M$44,9,0)) -> 1 | L125: =IF(ISNA(VLOOKUP(C125,$C$26:$M$44,10,0)),L126, VLOOKUP(C125,$C$26:$M$44,10,0)) -> 1 | M125: =IF(ISNA(VLOOKUP(C125,$C$26:$M$44,11,0)),M126, VLOOKUP(C125,$C$26:$M$44,11,0)) -> 1.1 | N125: =Z90+AA90+AB90*K125+AC90*L125+AD93*M128*$M$100 -> 0.052947387 | O125: =100*(1-(1-N125)^12) -> 47.941784 | P125: =D125/N125 -> 0.99514394 | X125: =A125 -> 72.47937 | Y125: =VLOOKUP(ROUNDDOWN(X125,0),'Spline Pre-Adj'!F:G,2,0) -> 3.9558229 | Z125: =Y125*L125 -> 3.9558229 | AC125: =A125 -> 72.47937 | AD125: =VLOOKUP(ROUNDDOWN(AC125,0),'Spline Pre-Adj'!K:L,2,0) -> 3.701587 | AE125: =AD125*M125 -> 4.0717457
A126: =K91 -> 85.725601 | B126: =AQ91/1000000000 -> 10.600686 | C126: =AO91 -> 12:75-100 | D126: =E91 -> 0.049369571 | E126: =Z91+AA91+AB91+AC91+AD91 -> 0.047249291 | F126: =D126/E126 -> 1.0448743 | G126: =(1-(1-D126)^12)*100 -> 45.532111 | H126: =(1-(1-E126)^12)*100 -> 44.056277 | K126: =IF(ISNA(VLOOKUP(C126,$C$26:$M$44,9,0)),K127, VLOOKUP(C126,$C$26:$M$44,9,0)) -> 1 | L126: =IF(ISNA(VLOOKUP(C126,$C$26:$M$44,10,0)),L127, VLOOKUP(C126,$C$26:$M$44,10,0)) -> 1 | M126: =IF(ISNA(VLOOKUP(C126,$C$26:$M$44,11,0)),M127, VLOOKUP(C126,$C$26:$M$44,11,0)) -> 1.02 | N126: =Z91+AA91+AB91*K126+AC91*L126+AD91*M126*$M$100 -> 0.05032818 | O126: =100*(1-(1-N126)^12) -> 46.187569 | P126: =D126/N126 -> 0.98095283 | X126: =A126 -> 85.725601 | Y126: =VLOOKUP(ROUNDDOWN(X126,0),'Spline Pre-Adj'!F:G,2,0) -> 4.706786 | Z126: =Y126*L126 -> 4.706786 | AC126: =A126 -> 85.725601 | AD126: =VLOOKUP(ROUNDDOWN(AC126,0),'Spline Pre-Adj'!K:L,2,0) -> 4.0923365 | AE126: =AD126*M126 -> 4.1741833
A127: =K92 -> 111.84113 | B127: =AQ92/1000000000 -> 5.6058508 | C127: =AO92 -> 13:100-125 | D127: =E92 -> 0.05001783 | E127: =Z92+AA92+AB92+AC92+AD92 -> 0.051473035 | F127: =D127/E127 -> 0.97172879 | G127: =(1-(1-D127)^12)*100 -> 45.97616 | H127: =(1-(1-E127)^12)*100 -> 46.960896 | K127: =IF(ISNA(VLOOKUP(C127,$C$26:$M$44,9,0)),K128, VLOOKUP(C127,$C$26:$M$44,9,0)) -> 1 | L127: =IF(ISNA(VLOOKUP(C127,$C$26:$M$44,10,0)),L128, VLOOKUP(C127,$C$26:$M$44,10,0)) -> 1 | M127: =IF(ISNA(VLOOKUP(C127,$C$26:$M$44,11,0)),M128, VLOOKUP(C127,$C$26:$M$44,11,0)) -> 0.95 | N127: =Z92+AA92+AB92*K127+AC92*L127+AD92*M127*$M$100 -> 0.051355013 | O127: =100*(1-(1-N127)^12) -> 46.881648 | P127: =D127/N127 -> 0.97396197 | X127: =A127 -> 111.84113 | Y127: =VLOOKUP(ROUNDDOWN(X127,0),'Spline Pre-Adj'!F:G,2,0) -> 6.2168085 | Z127: =Y127*L127 -> 6.2168085 | AC127: =A127 -> 111.84113 | AD127: =VLOOKUP(ROUNDDOWN(AC127,0),'Spline Pre-Adj'!K:L,2,0) -> 4.729914 | AE127: =AD127*M127 -> 4.4934183
A128: =K93 -> 134.38013 | B128: =AQ93/1000000000 -> 2.6160554 | C128: =AO93 -> 14:125-150 | D128: =E93 -> 0.050708829 | E128: =Z93+AA93+AB93+AC93+AD93 -> 0.055259575 | F128: =D128/E128 -> 0.91764783 | G128: =(1-(1-D128)^12)*100 -> 46.445829 | H128: =(1-(1-E128)^12)*100 -> 49.446644 | K128: =IF(ISNA(VLOOKUP(C128,$C$26:$M$44,9,0)),K129, VLOOKUP(C128,$C$26:$M$44,9,0)) -> 1 | L128: =IF(ISNA(VLOOKUP(C128,$C$26:$M$44,10,0)),L129, VLOOKUP(C128,$C$26:$M$44,10,0)) -> 1 | M128: =IF(ISNA(VLOOKUP(C128,$C$26:$M$44,11,0)),M129, VLOOKUP(C128,$C$26:$M$44,11,0)) -> 0.92 | N128: =Z93+AA93+AB93*K128+AC93*L128+AD93*M128*$M$100 -> 0.053527468 | O128: =100*(1-(1-N128)^12) -> 48.323133 | P128: =D128/N128 -> 0.94734219 | X128: =A128 -> 134.38013 | Y128: =VLOOKUP(ROUNDDOWN(X128,0),'Spline Pre-Adj'!F:G,2,0) -> 7.6066289 | Z128: =Y128*L128 -> 7.6066289 | AC128: =A128 -> 134.38013 | AD128: =VLOOKUP(ROUNDDOWN(AC128,0),'Spline Pre-Adj'!K:L,2,0) -> 5.205107 | AE128: =AD128*M128 -> 4.7886984
A129: =K94 -> 160.18516 | B129: =AQ94/1000000000 -> 0.44019782 | C129: =AO94 -> 15:150-175 | D129: =E94 -> 0.047514463 | E129: =Z94+AA94+AB94+AC94+AD94 -> 0.059732779 | F129: =D129/E129 -> 0.7954504 | G129: =(1-(1-D129)^12)*100 -> 44.242836 | H129: =(1-(1-E129)^12)*100 -> 52.245362 | K129: =IF(ISNA(VLOOKUP(C129,$C$26:$M$44,9,0)),K130, VLOOKUP(C129,$C$26:$M$44,9,0)) -> 1 | L129: =IF(ISNA(VLOOKUP(C129,$C$26:$M$44,10,0)),L130, VLOOKUP(C129,$C$26:$M$44,10,0)) -> 1 | M129: =IF(ISNA(VLOOKUP(C129,$C$26:$M$44,11,0)),M130, VLOOKUP(C129,$C$26:$M$44,11,0)) -> 0.9 | N129: =Z94+AA94+AB94*K129+AC94*L129+AD94*M129*$M$100 -> 0.056702555 | O129: =100*(1-(1-N129)^12) -> 50.365472 | P129: =D129/N129 -> 0.83795983 | X129: =A129 -> 160.18516 | Y129: =VLOOKUP(ROUNDDOWN(X129,0),'Spline Pre-Adj'!F:G,2,0) -> 8.7434836 | Z129: =Y129*L129 -> 8.7434836 | AC129: =A129 -> 160.18516 | AD129: =VLOOKUP(ROUNDDOWN(AC129,0),'Spline Pre-Adj'!K:L,2,0) -> 5.6662697 | AE129: =AD129*M129 -> 5.0996428
A130: =K95 -> 183.9435 | B130: =AQ95/1000000000 -> 0.096630878 | C130: =AO95 -> 16:175-200 | D130: =E95 -> 0.061197489 | E130: =Z95+AA95+AB95+AC95+AD95 -> 0.063330653 | F130: =D130/E130 -> 0.96631705 | G130: =(1-(1-D130)^12)*100 -> 53.130436 | H130: =(1-(1-E130)^12)*100 -> 54.39256 | K130: =IF(ISNA(VLOOKUP(C130,$C$26:$M$44,9,0)),K131, VLOOKUP(C130,$C$26:$M$44,9,0)) -> 1 | L130: =IF(ISNA(VLOOKUP(C130,$C$26:$M$44,10,0)),L131, VLOOKUP(C130,$C$26:$M$44,10,0)) -> 1 | M130: =IF(ISNA(VLOOKUP(C130,$C$26:$M$44,11,0)),M131, VLOOKUP(C130,$C$26:$M$44,11,0)) -> 0.9 | N130: =Z95+AA95+AB95*K130+AC95*L130+AD95*M130*$M$100 -> 0.060131073 | O130: =100*(1-(1-N130)^12) -> 52.487542 | P130: =D130/N130 -> 1.0177349 | X130: =A130 -> 183.9435 | Y130: =VLOOKUP(ROUNDDOWN(X130,0),'Spline Pre-Adj'!F:G,2,0) -> 8.8912891 | Z130: =Y130*L130 -> 8.8912891 | AC130: =A130 -> 183.9435 | AD130: =VLOOKUP(ROUNDDOWN(AC130,0),'Spline Pre-Adj'!K:L,2,0) -> 6.0276934 | AE130: =AD130*M130 -> 5.4249241
A131: =K96 -> 209.55229 | B131: =AQ96/1000000000 -> 0.020893223 | C131: =AO96 -> 17:200-225 | D131: =E96 -> 0.052273955 | E131: =Z96+AA96+AB96+AC96+AD96 -> 0.063630713 | F131: =D131/E131 -> 0.82152081 | G131: =(1-(1-D131)^12)*100 -> 47.495831 | H131: =(1-(1-E131)^12)*100 -> 54.567574 | K131: =IF(ISNA(VLOOKUP(C131,$C$26:$M$44,9,0)),K132, VLOOKUP(C131,$C$26:$M$44,9,0)) -> 1 | L131: =IF(ISNA(VLOOKUP(C131,$C$26:$M$44,10,0)),L132, VLOOKUP(C131,$C$26:$M$44,10,0)) -> 1 | M131: =IF(ISNA(VLOOKUP(C131,$C$26:$M$44,11,0)),M132, VLOOKUP(C131,$C$26:$M$44,11,0)) -> 1.05 | N131: =Z96+AA96+AB96*K131+AC96*L131+AD96*M131*$M$100 -> 0.069565463 | O131: =100*(1-(1-N131)^12) -> 57.905062 | P131: =D131/N131 -> 0.75143545 | X131: =A131 -> 209.55229 | Y131: =VLOOKUP(ROUNDDOWN(X131,0),'Spline Pre-Adj'!F:G,2,0) -> 8.9 | Z131: =Y131*L131 -> 8.9 | AC131: =A131 -> 209.55229 | AD131: =VLOOKUP(ROUNDDOWN(AC131,0),'Spline Pre-Adj'!K:L,2,0) -> 6.3657669 | AE131: =AD131*M131 -> 6.6840552
I136: Better fit for WALA<24 | K136: 0.75 | L136: 1 | M136: 1
K137: 0.75 | L137: 1 | M137: 1
K138: 0.75 | L138: 1 | M138: 1
K139: 0.64 | L139: 1 | M139: 1
K140: 0.64 | L140: 1 | M140: 0.32
K141: 0.75 | L141: 1 | M141: 0.67
K142: 0.75 | L142: 1 | M142: 1.11
K143: 0.75 | L143: 1 | M143: 1.32
...

Sheet Burnout
A1: WALA [12,24) | C1: CORRES+CASHWINDOW | F1: Burnout 0-2000 | AS1: tover | AT1: cash | AW1: refi
A2: modelId | B2: SFACTOR_PREPAY_TRACKING_CPR | C2: PREPAY_CPR1 | D2: PREPAY_TRACKING_CPR1 | E2: PREPAY_SMM1 | F2: PREPAY_TRACKING_SMM1 | G2: PCT_LOANTYPE | H2: _ORIGNOTERATE | I2: _ZEROSATO | J2: _SATO | K2: _REFI_INCENTIVE_Fixed | L2: _Fixed_cost | M2: _LOANAGE | N2: _LTV | O2: _CLTV | P2: _AVG_LOANSIZE_SCHAMBALANCE | Q2: _WACLS | R2: _FICO | S2: PCT_ISSECONDLIEN | T2: _OrigCombLTV | U2: PCT_SVC | V2: PCT_TPO | W2: PCT_GEO | X2: PCT_LOANPURPOSE | Y2: PCT_OCC | Z2: curtailsmm | AA2: defaultsmm | AB2: toverSmm | AC2: cashoutSmm | AD2: refiSmm | AE2: cumHPA | AF2: cumHPA05Pct | AG2: cumHPA15Pct | AH2: cumHPA20Pct | AI2: cumHPA25Pct | AJ2: cumHPA30Pct | AK2: cumHPA35Pct | AL2: cumHPA40Pct | AM2: adjtoverSmm | AN2: adjRefiSmm | AO2: groupByColumn | AP2: curve | AQ2: Balance | AR2: LoanCount | AS2: PCT_BROKER | AT2: PCT_CORRES | AU2: PCT_NonRETAIL | AV2: PCT_RETAIL | AW2: PCT_CashWindow | AX2: PCT_NonCashWindow | AY2: _Burnout_Fixed
A3: 96 | B3: 0.99661762 | C3: 0 | D3: 3.9841936 | E3: 0 | F3: 0.00338238 | G3: 0 | H3: 3.875 | I3: 4.118472 | J3: -64.0619 | K3: -131.95 | L3: 13.16 | M3: 17 | N3: 80 | O3: 77.08 | P3: 303250.44 | Q3: 303250.44 | R3: 773 | S3: 0 | T3: 0 | U3: 0 | V3: 1 | W3: 0 | X3: 1 | Y3: 0 | Z3: 0.00035183 | AA3: 7.792e-05 | AB3: 0.00295262 | AC3: 0 | AD3: 0 | AE3: 0.011207683 | AF3: 1 | AG3: 1 | AH3: 1 | AI3: 1 | AJ3: 1 | AK3: 1 | AL3: 1 | AM3: 0 | AN3: 0 | AO3: 03:-150--125 | AP3: =-150--125 -> -25 | AQ3: 303250.44 | AR3: 1 | AS3: 0 | AT3: 0 | AU3: 0 | AV3: 100 | AW3: 100 | AX3: 0 | AY3: 0
A4: 96 | B4: 0.99252822 | C4: 5.6968752e-06 | D4: 8.6066971 | E4: 4.7473962e-09 | F4: 0.0074717783 | G4: 0 | H4: 3.9463145 | I4: 3.9968994 | J4: -50.059634 | K4: -110.17523 | L4: 17.060622 | M4: 16.808767 | N4: 78.188745 | O4: 75.620467 | P4: 244109.93 | Q4: 234046.42 | R4: 766.50335 | S4: 0 | T4: 0 | U4: 0 | V4: 0.52919184 | W4: 0 | X4: 0.62889958 | Y4: 0 | Z4: 0.0003521941 | AA4: 5.2415621e-05 | AB4: 0.0030302851 | AC4: 0 | AD4: 0.0040368678 | AE4: 0.007991849 | AF4: 1 | AG4: 1 | AH4: 1 | AI4: 1 | AJ4: 1 | AK4: 1 | AL4: 1 | AM4: 0 | AN4: 0 | AO4: 04:-125--100 | AP4: =-125--100 -> -25 | AQ4: 2106417.8 | AR4: 9 | AS4: 0 | AT4: 47.080816 | AU4: 47.080816 | AV4: 52.919184 | AW4: 52.919184 | AX4: 0 | AY4: 0
A5: 96 | B5: 0.9854146 | C5: 6.7240517 | D5: 16.164509 | E5: 0.005783867 | F5: 0.0145854 | G5: 0 | H5: 4.2182657 | I5: 4.013573 | J5: -25.41889 | K5: -83.743459 | L5: 15.531015 | M5: 16.933544 | N5: 77.580947 | O5: 76.058289 | P5: 294714 | Q5: 232023.63 | R5: 776.08752 | S5: 0 | T5: 0 | U5: 0 | V5: 0.32998978 | W5: 0 | X5: 0.59746948 | Y5: 0 | Z5: 0.00049507274 | AA5: 8.312075e-05 | AB5: 0.0028162319 | AC5: 0 | AD5: 0.011190961 | AE5: -0.016614367 | AF5: 1 | AG5: 1 | AH5: 1 | AI5: 1 | AJ5: 1 | AK5: 1 | AL5: 1 | AM5: 0 | AN5: 0 | AO5: 05:-100--75 | AP5: =-100--75 -> -25 | AQ5: 6960708.8 | AR5: 30 | AS5: 0 | AT5: 67.001022 | AU5: 67.001022 | AV5: 32.998978 | AW5: 32.998978 | AX5: 0 | AY5: 0
A6: 96 | B6: 0.99302902 | C6: 5.2786397 | D6: 8.0517863 | E6: 0.0045090249 | F6: 0.0069709777 | G6: 0 | H6: 3.9477649 | I6: 4.1009703 | J6: -54.901747 | K6: -56.696947 | L6: 17.807148 | M6: 16.26908 | N6: 78.049954 | O6: 76.132956 | P6: 262092.09 | Q6: 215006.84 | R6: 779.43956 | S6: 0 | T6: 0 | U6: 0.01112109 | V6: 0.10269525 | W6: 0 | X6: 0.47395975 | Y6: 0 | Z6: 0.00054578086 | AA6: 7.3191027e-05 | AB6: 0.0025300283 | AC6: 0 | AD6: 0.0038219663 | AE6: -0.020708407 | AF6: 0.99013984 | AG6: 0.99958902 | AH6: 1 | AI6: 1 | AJ6: 1 | AK6: 1 | AL6: 1 | AM6: 0 | AN6: 0 | AO6: 06:-75--50 | AP6: =-75--50 -> -25 | AQ6: 1.0922347e+08 | AR6: 508 | AS6: 0 | AT6: 89.730475 | AU6: 89.730475 | AV6: 10.269525 | AW6: 10.269525 | AX6: 0 | AY6: 0.36724483
A7: 96 | B7: 0.99230135 | C7: 3.4916301 | D7: 8.8570662 | E7: 0.0029573223 | F7: 0.0076986466 | G7: 0 | H7: 3.8980515 | I7: 4.1131381 | J7: -60.5987 | K7: -33.134227 | L7: 16.339431 | M7: 16.249137 | N7: 74.492152 | O7: 72.612313 | P7: 269597.48 | Q7: 241873.07 | R7: 781.68626 | S7: 0 | T7: 0 | U7: 0.0015742685 | V7: 0.10414133 | W7: 0 | X7: 0.56299853 | Y7: 0 | Z7: 0.00041375709 | AA7: 6.3290386e-05 | AB7: 0.0026439115 | AC7: 6.9562929e-08 | AD7: 0.0045776036 | AE7: -0.011974575 | AF7: 0.97730546 | AG7: 0.99838128 | AH7: 0.99991916 | AI7: 0.99994485 | AJ7: 1 | AK7: 1 | AL7: 1 | AM7: 0 | AN7: 0 | AO7: 07:-50--25 | AP7: =-50--25 -> -25 | AQ7: 1.3745647e+09 | AR7: 5683 | AS7: 0 | AT7: 89.585867 | AU7: 89.585867 | AV7: 10.414133 | AW7: 10.414133 | AX7: 0 | AY7: 0.12526427
A8: 96 | B8: 0.98878451 | C8: 6.6623896 | D8: 12.658661 | E8: 0.0057291129 | F8: 0.011215491 | G8: 0 | H8: 3.9568729 | I8: 4.1092163 | J8: -54.589527 | K8: -22.352891 | L8: 15.718118 | M8: 16.506546 | N8: 71.855522 | O8: 70.237483 | P8: 276120.47 | Q8: 253281.98 | R8: 781.76954 | S8: 0 | T8: 0 | U8: 0.0037905842 | V8: 0.14317714 | W8: 0 | X8: 0.64851244 | Y8: 0 | Z8: 0.00038414882 | AA8: 5.7327614e-05 | AB8: 0.0027048945 | AC8: 8.5436358e-08 | AD8: 0.0080690199 | AE8: -0.01090598 | AF8: 0.97076008 | AG8: 0.99784321 | AH8: 0.99964418 | AI8: 1 | AJ8: 1 | AK8: 1 | AL8: 1 | AM8: 0 | AN8: 0 | AO8: 08-1:-25--20 | AP8: =-25--20 -> -5 | AQ8: 8.0771624e+08 | AR8: 3189 | AS8: 0 | AT8: 85.682286 | AU8: 85.682286 | AV8: 14.317714 | AW8: 14.317714 | AX8: 0 | AY8: 0.15044308
A9: 96 | B9: 0.98727315 | C9: 5.1089785 | D9: 14.247282 | E9: 0.0043605563 | F9: 0.012726854 | G9: 0 | H9: 4.0128716 | I9: 4.1072446 | J9: -49.551293 | K9: -17.273662 | L9: 15.967394 | M9: 16.495946 | N9: 72.569876 | O9: 70.951853 | P9: 272739.61 | Q9: 248738.71 | R9: 781.89197 | S9: 0 | T9: 0 | U9: 0.0051545806 | V9: 0.15004176 | W9: 0 | X9: 0.64325564 | Y9: 0 | Z9: 0.00038537961 | AA9: 6.1080902e-05 | AB9: 0.0026978917 | AC9: 6.7257932e-08 | AD9: 0.00958242 | AE9: -0.010756442 | AF9: 0.96667301 | AG9: 0.99780784 | AH9: 0.99962973 | AI9: 1 | AJ9: 1 | AK9: 1 | AL9: 1 | AM9: 0 | AN9: 0 | AO9: 08-2:-20--15 | AP9: =-20--15 -> -5 | AQ9: 1.1752904e+09 | AR9: 4725 | AS9: 0 | AT9: 84.995824 | AU9: 84.995824 | AV9: 15.004176 | AW9: 15.004176 | AX9: 0 | AY9: 0.27417563
A10: 96 | B10: 0.98596851 | C10: 7.3931326 | D10: 15.597264 | E10: 0.0063801337 | F10: 0.014031492 | G10: 0 | H10: 4.0622342 | I10: 4.1048272 | J10: -44.839479 | K10: -12.321954 | L10: 15.781596 | M10: 16.629436 | N10: 72.508354 | O10: 71.015891 | P10: 273438.55 | Q10: 252116.25 | R10: 781.66662 | S10: 0 | T10: 0 | U10: 0.0026982242 | V10: 0.17055764 | W10: 0 | X10: 0.66300266 | Y10: 0 | Z10: 0.00038045309 | AA10: 6.7120327e-05 | AB10: 0.0027136847 | AC10: 5.7859638e-08 | AD10: 0.010870162 | AE10: -0.011287361 | AF10: 0.96718736 | AG10: 0.99763981 | AH10: 0.99972538 | AI10: 1 | AJ10: 1 | AK10: 1 | AL10: 1 | AM10: 0 | AN10: 0 | AO10: 08-3:-15--10 | AP10: =-15--10 -> -5 | AQ10: 1.7789323e+09 | AR10: 7056 | AS10: 0 | AT10: 82.944236 | AU10: 82.944236 | AV10: 17.055764 | AW10: 17.055764 | AX10: 0 | AY10: 0.35121594
A11: 96 | B11: 0.98471013 | C11: 10.612968 | D11: 16.880894 | E11: 0.0093059766 | F11: 0.01528987 | G11: 0 | H11: 4.1080795 | I11: 4.1008715 | J11: -40.420924 | K11: -7.3847568 | L11: 15.461926 | M11: 16.671282 | N11: 73.30299 | O11: 71.85422 | P11: 279151.18 | Q11: 257733.1 | R11: 781.82462 | S11: 0 | T11: 0 | U11: 0.0053504584 | V11: 0.17142799 | W11: 0 | X11: 0.67540045 | Y11: 0 | Z11: 0.00037539892 | AA11: 6.9326727e-05 | AB11: 0.0026784442 | AC11: 6.7687265e-08 | AD11: 0.012166618 | AE11: -0.011297562 | AF11: 0.96169927 | AG11: 0.99673293 | AH11: 0.99987008 | AI11: 1 | AJ11: 1 | AK11: 1 | AL11: 1 | AM11: 0 | AN11: 0 | AO11: 08-4:-10--5 | AP11: =-10--5 -> -5 | AQ11: 2.490475e+09 | AR11: 9663 | AS11: 0 | AT11: 82.857201 | AU11: 82.857201 | AV11: 17.142799 | AW11: 17.142799 | AX11: 0 | AY11: 0.3769289
A12: 96 | B12: 0.98345367 | C12: 10.522405 | D12: 18.144688 | E12: 0.0092223714 | F12: 0.01654633 | G12: 0 | H12: 4.1345837 | I12: 4.0897255 | J12: -38.158592 | K12: -2.3578415 | L12: 15.335543 | M12: 16.836741 | N12: 72.897386 | O12: 71.427852 | P12: 280725.32 | Q12: 259684.03 | R12: 781.35981 | S12: 0 | T12: 0 | U12: 0.007919249 | V12: 0.19222567 | W12: 0 | X12: 0.695946 | Y12: 0 | Z12: 0.00037649823 | AA12: 7.1405814e-05 | AB12: 0.0027198499 | AC12: 6.5072321e-08 | AD12: 0.013378496 | AE12: -0.010543629 | AF12: 0.96181838 | AG12: 0.99523733 | AH12: 0.99991922 | AI12: 0.9999793 | AJ12: 1 | AK12: 1 | AL12: 1 | AM12: 0 | AN12: 0 | AO12: 08:-25-0 | AP12: =-25-0 -> -25 | AQ12: 3.2608523e+09 | AR12: 12557 | AS12: 0 | AT12: 80.777433 | AU12: 80.777433 | AV12: 19.222567 | AW12: 19.222567 | AX12: 0 | AY12: 1.2091977
A13: 96 | B13: 0.98234258 | C13: 12.754743 | D13: 19.247569 | E13: 0.011306181 | F13: 0.017657425 | G13: 0 | H13: 4.1628263 | I13: 4.0807088 | J13: -35.226232 | K13: 2.6131292 | L13: 15.429783 | M13: 16.938817 | N13: 72.581448 | O13: 70.945412 | P13: 280374.75 | Q13: 258474.51 | R13: 781.62572 | S13: 0 | T13: 0 | U13: 0.011187964 | V13: 0.20985741 | W13: 0 | X13: 0.71000911 | Y13: 0 | Z13: 0.0003765691 | AA13: 7.3983317e-05 | AB13: 0.0027538581 | AC13: 6.6610695e-08 | AD13: 0.014452933 | AE13: -0.0088857187 | AF13: 0.95336182 | AG13: 0.99544836 | AH13: 0.99988983 | AI13: 1 | AJ13: 1 | AK13: 1 | AL13: 1 | AM13: 0 | AN13: 0 | AO13: 09-1:0-5 | AP13: 0-5 | AQ13: 4.2927447e+09 | AR13: 16608 | AS13: 0 | AT13: 79.014259 | AU13: 79.014259 | AV13: 20.985741 | AW13: 20.985741 | AX13: 0 | AY13: 3.7828712
A14: 96 | B14: 0.98146619 | C14: 15.401938 | D14: 20.107848 | E14: 0.013841548 | F14: 0.01853381 | G14: 0 | H14: 4.1805802 | I14: 4.0649852 | J14: -33.302997 | K14: 7.6208417 | L14: 15.890939 | M14: 16.908032 | N14: 73.201799 | O14: 71.356822 | P14: 271742.56 | Q14: 250925.12 | R14: 781.8583 | S14: 0 | T14: 0 | U14: 0.011999135 | V14: 0.22121344 | W14: 0 | X14: 0.72554375 | Y14: 0 | Z14: 0.00037655785 | AA14: 7.4509212e-05 | AB14: 0.0028023688 | AC14: 1.7636512e-07 | AD14: 0.015280183 | AE14: -0.0062269186 | AF14: 0.936682 | AG14: 0.99379073 | AH14: 0.99966902 | AI14: 0.99993793 | AJ14: 1 | AK14: 1 | AL14: 1 | AM14: 0 | AN14: 0 | AO14: 09-2:5-10 | AP14: 43230 | AQ14: 5.5431869e+09 | AR14: 22091 | AS14: 0 | AT14: 77.878656 | AU14: 77.878656 | AV14: 22.121344 | AW14: 22.121344 | AX14: 0 | AY14: 10.81594
A15: 96 | B15: 0.98018092 | C15: 16.442332 | D15: 21.354312 | E15: 0.014857945 | F15: 0.019819083 | G15: 0 | H15: 4.1875187 | I15: 4.0509204 | J15: -31.967102 | K15: 12.667451 | L15: 15.837244 | M15: 16.815212 | N15: 71.493225 | O15: 69.573123 | P15: 270933.09 | Q15: 251919.43 | R15: 782.13665 | S15: 0 | T15: 0 | U15: 0.017577293 | V15: 0.21877122 | W15: 0 | X15: 0.75643771 | Y15: 0 | Z15: 0.00037476735 | AA15: 7.3934695e-05 | AB15: 0.0028339289 | AC15: 4.5990811e-07 | AD15: 0.016535978 | AE15: -0.0041864069 | AF15: 0.92243167 | AG15: 0.99177152 | AH15: 0.99905169 | AI15: 0.99978989 | AJ15: 1 | AK15: 1 | AL15: 1 | AM15: 0 | AN15: 0 | AO15: 09-3:10-15 | AP15: 43388 | AQ15: 8.0624295e+09 | AR15: 32004 | AS15: 0 | AT15: 78.122878 | AU15: 78.122878 | AV15: 21.877122 | AW15: 21.877122 | AX15: 0 | AY15: 24.243654
A16: 96 | B16: 0.97850393 | C16: 18.285414 | D16: 22.953862 | E16: 0.016687337 | F16: 0.021496073 | G16: 0 | H16: 4.1924203 | I16: 4.0335055 | J16: -30.754923 | K16: 17.609577 | L16: 15.456462 | M16: 16.719237 | N16: 69.869123 | O16: 67.866258 | P16: 278066.52 | Q16: 258212.17 | R16: 782.41299 | S16: 0 | T16: 0 | U16: 0.019426321 | V16: 0.21838488 | W16: 0 | X16: 0.7830235 | Y16: 0 | Z16: 0.00037496469 | AA16: 7.1991075e-05 | AB16: 0.0028495993 | AC16: 7.1193201e-07 | AD16: 0.018198792 | AE16: -0.0023829461 | AF16: 0.9013316 | AG16: 0.98690979 | AH16: 0.99902718 | AI16: 0.99980175 | AJ16: 1 | AK16: 1 | AL16: 1 | AM16: 0 | AN16: 0 | AO16: 09-4:15-20 | AP16: 15-20 | AQ16: 1.1349458e+10 | AR16: 43954 | AS16: 0 | AT16: 78.161512 | AU16: 78.161512 | AV16: 21.838488 | AW16: 21.838488 | AX16: 0 | AY16: 44.43304
A17: 96 | B17: 0.97662207 | C17: 22.277413 | D17: 24.713272 | E17: 0.020783017 | F17: 0.023377929 | G17: 0 | H17: 4.1881382 | I17: 4.001456 | J17: -29.944562 | K17: 22.570512 | L17: 14.965468 | M17: 16.762712 | N17: 68.104966 | O17: 65.845317 | P17: 286522.98 | Q17: 266631.42 | R17: 782.69437 | S17: 0 | T17: 0 | U17: 0.023435254 | V17: 0.24078838 | W17: 0 | X17: 0.79039443 | Y17: 0 | Z17: 0.00037317332 | AA17: 7.002361e-05 | AB17: 0.0029162821 | AC17: 1.3728455e-06 | AD17: 0.020017062 | AE17: 0.0027975256 | AF17: 0.86986483 | AG17: 0.98012732 | AH17: 0.99842485 | AI17: 0.99958619 | AJ17: 1 | AK17: 1 | AL17: 1 | AM17: 0 | AN17: 0 | AO17: 09:0-25 | AP17: 0-25 | AQ17: 1.4191457e+10 | AR17: 53225 | AS17: 0 | AT17: 75.921162 | AU17: 75.921162 | AV17: 24.078838 | AW17: 24.078838 | AX17: 0 | AY17: 68.122694
A18: 96 | B18: 0.97488157 | C18: 24.486386 | D18: 26.307668 | E18: 0.023133002 | F18: 0.025118434 | G18: 0 | H18: 4.188703 | I18: 3.9655937 | J18: -28.713058 | K18: 27.530456 | L18: 14.797287 | M18: 16.788894 | N18: 67.431069 | O18: 64.76307 | P18: 290761.16 | Q18: 269719.81 | R18: 782.48222 | S18: 0 | T18: 0 | U18: 0.025560263 | V18: 0.25777518 | W18: 0 | X18: 0.79426983 | Y18: 0 | Z18: 0.00037253834 | AA18: 6.964181e-05 | AB18: 0.00297816 | AC18: 1.9759146e-06 | AD18: 0.021696104 | AE18: 0.0093208967 | AF18: 0.83003463 | AG18: 0.96806173 | AH18: 0.99831 | AI18: 0.99940986 | AJ18: 1 | AK18: 1 | AL18: 1 | AM18: 0 | AN18: 0 | AO18: 10-1:25-30 | AP18: 25-30 | AQ18: 1.5991148e+10 | AR18: 59288 | AS18: 0 | AT18: 74.222482 | AU18: 74.222482 | AV18: 25.777518 | AW18: 25.777518 | AX18: 0 | AY18: 92.621794
A19: 96 | B19: 0.97338306 | C19: 26.780573 | D19: 27.655517 | E19: 0.025641315 | F19: 0.026616938 | G19: 0 | H19: 4.1910955 | I19: 3.9228204 | J19: -27.726625 | K19: 32.526474 | L19: 14.806896 | M19: 16.807832 | N19: 67.804178 | O19: 64.897532 | P19: 289439.72 | Q19: 269506.96 | R19: 782.66511 | S19: 0 | T19: 0 | U19: 0.029080957 | V19: 0.28643379 | W19: 0 | X19: 0.78955451 | Y19: 0 | Z19: 0.00037252461 | AA19: 7.0381464e-05 | AB19: 0.0030329288 | AC19: 3.3191714e-06 | AD19: 0.023137769 | AE19: 0.014600891 | AF19: 0.80224946 | AG19: 0.95796142 | AH19: 0.99691452 | AI19: 0.99933708 | AJ19: 1 | AK19: 1 | AL19: 1 | AM19: 0 | AN19: 0 | AO19: 10-2:30-35 | AP19: 30-35 | AQ19: 1.6730992e+10 | AR19: 62080 | AS19: 0 | AT19: 71.356621 | AU19: 71.356621 | AV19: 28.643379 | AW19: 28.643379 | AX19: 0 | AY19: 114.46711
A20: 96 | B20: 0.97160198 | C20: 29.650913 | D20: 29.228127 | E20: 0.028883041 | F20: 0.02839802 | G20: 0 | H20: 4.2023837 | I20: 3.8899202 | J20: -26.282971 | K20: 37.490679 | L20: 14.684922 | M20: 16.855369 | N20: 67.536391 | O20: 64.290187 | P20: 291894.02 | Q20: 271777.11 | R20: 782.54763 | S20: 0 | T20: 0 | U20: 0.02763465 | V20: 0.3017124 | W20: 0 | X20: 0.77721951 | Y20: 0 | Z20: 0.00037172198 | AA20: 7.0502529e-05 | AB20: 0.0030822348 | AC20: 3.72723e-06 | AD20: 0.02486982 | AE20: 0.019489362 | AF20: 0.77539906 | AG20: 0.95985568 | AH20: 0.99635305 | AI20: 0.9991725 | AJ20: 1 | AK20: 1 | AL20: 1 | AM20: 0 | AN20: 0 | AO20: 10-3:35-40 | AP20: 35-40 | AQ20: 1.7563596e+10 | AR20: 64625 | AS20: 0 | AT20: 69.82876 | AU20: 69.82876 | AV20: 30.17124 | AW20: 30.17124 | AX20: 0 | AY20: 135.82954
A21: 96 | B21: 0.96989109 | C21: 33.811491 | D21: 30.709188 | E21: 0.033804042 | F21: 0.030108907 | G21: 0 | H21: 4.2261171 | I21: 3.8631291 | J21: -24.508398 | K21: 42.445649 | L21: 14.754613 | M21: 16.903332 | N21: 68.159845 | O21: 64.656052 | P21: 291571.39 | Q21: 270480.18 | R21: 782.47171 | S21: 0 | T21: 0 | U21: 0.02642852 | V21: 0.31945948 | W21: 0 | X21: 0.76618658 | Y21: 0 | Z21: 0.00037218995 | AA21: 7.1639303e-05 | AB21: 0.0031279946 | AC21: 4.8245271e-06 | AD21: 0.026532245 | AE21: 0.024240609 | AF21: 0.75050976 | AG21: 0.95404854 | AH21: 0.99534452 | AI21: 0.99944528 | AJ21: 1 | AK21: 1 | AL21: 1 | AM21: 0 | AN21: 0 | AO21: 10-4:40-45 | AP21: 40-45 | AQ21: 1.6869038e+10 | AR21: 62367 | AS21: 0 | AT21: 68.054052 | AU21: 68.054052 | AV21: 31.945948 | AW21: 31.945948 | AX21: 0 | AY21: 160.24355
A22: 96 | B22: 0.9679033 | C22: 34.649792 | D22: 32.394249 | E22: 0.034829778 | F22: 0.032096702 | G22: 0 | H22: 4.2623003 | I22: 3.8488727 | J22: -22.689029 | K22: 47.537078 | L22: 14.659746 | M22: 17.127253 | N22: 67.880052 | O22: 64.369908 | P22: 292673.06 | Q22: 272225.94 | R22: 782.29936 | S22: 0 | T22: 0 | U22: 0.022575556 | V22: 0.31211605 | W22: 0 | X22: 0.74810549 | Y22: 0 | Z22: 0.00037159598 | AA22: 7.5439037e-05 | AB22: 0.0031641278 | AC22: 5.1742977e-06 | AD22: 0.02848035 | AE22: 0.025130258 | AF22: 0.749646 | AG22: 0.95908567 | AH22: 0.99516192 | AI22: 0.9995509 | AJ22: 1 | AK22: 1 | AL22: 1 | AM22: 0 | AN22: 0 | AO22: 10:25-50 | AP22: 25-50 | AQ22: 1.6980637e+10 | AR22: 62377 | AS22: 0 | AT22: 68.788395 | AU22: 68.788395 | AV22: 31.211605 | AW22: 31.211605 | AX22: 0 | AY22: 186.39755
A23: 96 | B23: 0.96643117 | C23: 35.102465 | D23: 33.617873 | E23: 0.035388689 | F23: 0.033568827 | G23: 0 | H23: 4.3239011 | I23: 3.8492956 | J23: -19.908963 | K23: 52.527592 | L23: 14.942229 | M23: 17.374517 | N23: 69.604906 | O23: 65.998659 | P23: 287444.7 | Q23: 267126.97 | R23: 781.86846 | S23: 0 | T23: 0 | U23: 0.017533301 | V23: 0.3024297 | W23: 0 | X23: 0.72429497 | Y23: 0 | Z23: 0.0003736279 | AA23: 8.221557e-05 | AB23: 0.0032006137 | AC23: 4.882112e-06 | AD23: 0.029907473 | AE23: 0.023159909 | AF23: 0.75402079 | AG23: 0.96399253 | AH23: 0.9958247 | AI23: 0.99957643 | AJ23: 1 | AK23: 1 | AL23: 1 | AM23: 0 | AN23: 0 | AO23: 11-1:50-55 | AP23: 50-55 | AQ23: 1.6104016e+10 | AR23: 60286 | AS23: 0 | AT23: 69.75703 | AU23: 69.75703 | AV23: 30.24297 | AW23: 30.24297 | AX23: 0 | AY23: 214.41358
A24: 96 | B24: 0.96469787 | C24: 38.093887 | D24: 35.032548 | E24: 0.03917463 | F24: 0.03530213 | G24: 0 | H24: 4.3722982 | I24: 3.8479664 | J24: -18.077082 | K24: 57.48813 | L24: 14.959449 | M24: 17.485138 | N24: 69.149612 | O24: 65.599926 | P24: 286599.54 | Q24: 266819.01 | R24: 781.65781 | S24: 0 | T24: 0 | U24: 0.016651952 | V24: 0.28527361 | W24: 0 | X24: 0.70960705 | Y24: 0 | Z24: 0.00037326347 | AA24: 8.7802542e-05 | AB24: 0.0032092901 | AC24: 5.9064308e-06 | AD24: 0.031625854 | AE24: 0.023763034 | AF24: 0.74997961 | AG24: 0.96513724 | AH24: 0.99553025 | AI24: 0.99910916 | AJ24: 1 | AK24: 1 | AL24: 1 | AM24: 0 | AN24: 0 | AO24: 11-2:55-60 | AP24: 55-60 | AQ24: 1.5768736e+10 | AR24: 59099 | AS24: 0 | AT24: 71.472639 | AU24: 71.472639 | AV24: 28.527361 | AW24: 28.527361 | AX24: 0 | AY24: 251.92832
A25: 96 | B25: 0.96278707 | C25: 39.617047 | D25: 36.56003 | E25: 0.041167243 | F25: 0.037212934 | G25: 0 | H25: 4.4371724 | I25: 3.8616982 | J25: -15.863396 | K25: 62.467222 | L25: 14.979527 | M25: 17.46552 | N25: 69.393148 | O25: 65.862825 | P25: 286480.47 | Q25: 266521.3 | R25: 781.30491 | S25: 0 | T25: 0 | U25: 0.016661951 | V25: 0.26601561 | W25: 0 | X25: 0.69248721 | Y25: 0 | Z25: 0.00037274987 | AA25: 9.4473643e-05 | AB25: 0.0032155764 | AC25: 6.023204e-06 | AD25: 0.033524096 | AE25: 0.022837393 | AF25: 0.75158123 | AG25: 0.97177414 | AH25: 0.99583254 | AI25: 0.99913459 | AJ25: 1 | AK25: 1 | AL25: 1 | AM25: 0 | AN25: 0 | AO25: 11-3:60-65 | AP25: 60-65 | AQ25: 1.5806312e+10 | AR25: 59306 | AS25: 0 | AT25: 73.398439 | AU25: 73.398439 | AV25: 26.601561 | AW25: 26.601561 | AX25: 0 | AY25: 296.5934
A26: 96 | B26: 0.96163609 | C26: 39.54037 | D26: 37.464153 | E26: 0.041065838 | F26: 0.038363912 | G26: 0 | H26: 4.5061568 | I26: 3.8794298 | J26: -13.888667 | K26: 67.469097 | L26: 15.238527 | M26: 17.279486 | N26: 69.679927 | O26: 66.245578 | P26: 281978.43 | Q26: 261990.2 | R26: 781.01539 | S26: 0 | T26: 0 | U26: 0.017466346 | V26: 0.25400472 | W26: 0 | X26: 0.66829004 | Y26: 0 | Z26: 0.00037305243 | AA26: 0.00010002593 | AB26: 0.0032007749 | AC26: 7.2855022e-06 | AD26: 0.034682759 | AE26: 0.021093981 | AF26: 0.75538425 | AG26: 0.97051408 | AH26: 0.99518829 | AI26: 0.99896052 | AJ26: 1 | AK26: 1 | AL26: 1 | AM26: 0 | AN26: 0 | AO26: 11-4:65-70 | AP26: 65-70 | AQ26: 1.5260405e+10 | AR26: 58248 | AS26: 0 | AT26: 74.599528 | AU26: 74.599528 | AV26: 25.400472 | AW26: 25.400472 | AX26: 0 | AY26: 348.62058
A27: 96 | B27: 0.95954098 | C27: 40.15501 | D27: 39.07966 | E27: 0.041882035 | F27: 0.040459022 | G27: 0 | H27: 4.5502812 | I27: 3.8834297 | J27: -12.841849 | K27: 72.511478 | L27: 14.91947 | M27: 17.0583 | N27: 68.782102 | O27: 65.257831 | P27: 287124.97 | Q27: 267590.43 | R27: 780.95439 | S27: 0 | T27: 0 | U27: 0.017926247 | V27: 0.23652822 | W27: 0 | X27: 0.64917503 | Y27: 0 | Z27: 0.00037256104 | AA27: 0.00010316016 | AB27: 0.003218958 | AC27: 8.7632689e-06 | AD27: 0.036755565 | AE27: 0.023578164 | AF27: 0.73430773 | AG27: 0.96714966 | AH27: 0.99429845 | AI27: 0.99910537 | AJ27: 1 | AK27: 1 | AL27: 1 | AM27: 0 | AN27: 0 | AO27: 11:50-75 | AP27: 50-75 | AQ27: 1.5650027e+10 | AR27: 58485 | AS27: 0 | AT27: 76.347178 | AU27: 76.347178 | AV27: 23.652822 | AW27: 23.652822 | AX27: 0 | AY27: 403.56446
... A34: 96 | B34: 0.93579989 | C34: 72.064022 | D34: 54.897995 | E34: 0.10081927 | F34: 0.064200115 | G34: 0 | H34: 5.246303 | I34: 3.6353262 | J34: 29.963975 | K34: 228.46734 | L34: 15.85931 | M34: 18.876273 | N34: 94.608967 | O34: 76.37676 | P34: 271524 | Q34: 251811.35 | R34: 773.36717 | S34: 0 | T34: 0 | U34: 0 | V34: 0 | W34: 0 | X34: 0 | Y34: 0 | Z34: 0.00035681576 | AA34: 0.00051280014 | AB34: 0.0053758672 | AC34: 0.0011187778 | AD34: 0.056835839 | AE34: 0.2087617 | AF34: 0 | AG34: 0 | AH34: 0.23427028 | AI34: 1 | AJ34: 1 | AK34: 1 | AL34: 1 | AM34: 0 | AN34: 0 | AO34: 18:225-250 | AP34: 225-250 | AQ34: 2769924.9 | AR34: 11 | AS34: 0 | AT34: 100 | AU34: 100 | AV34: 0 | AW34: 0 | AX34: 0 | AY34: 1892.0536
K40: burnout dial
K41: 1
K43: turn | L43: cash | M43: refi
A44: incentive | B44: =AQ2 -> Balance | C44: =AO2 -> groupByColumn | D44: =E2 -> PREPAY_SMM1 | E44: =F2 -> PREPAY_TRACKING_SMM1 | F44: ratio | G44: =C2 -> PREPAY_CPR1 | H44: =D2 -> PREPAY_TRACKING_CPR1 | K44: adj | L44: adj | M44: adj | N44: mdl_smm | O44: mdl_cpr | P44: ratio
A45: =K3 -> -131.95 | B45: =AQ3/1000000000 -> 0.00030325044 | C45: =AO3 -> 03:-150--125 | D45: =E3 -> 0 | E45: =Z3+AA3+AB3+AC3+AD3 -> 0.00338237 | F45: =D45/E45 -> 0 | G45: =(1-(1-D45)^12)*100 -> 0 | H45: =(1-(1-E45)^12)*100 -> 3.984182 | K45: 1 | L45: 1 | M45: =VLOOKUP($C45,'Refi Adj'!$B$2:$E$30,4,0) -> #N/A | N45: =Z3+AA3+AB3*K45+AC3*L45+AD3*M45*$K$41 -> #N/A | O45: =100*(1-(1-N45)^12) -> #N/A | P45: =D45/N45 -> #N/A
A46: =K4 -> -110.17523 | B46: =AQ4/1000000000 -> 0.0021064178 | C46: =AO4 -> 04:-125--100 | D46: =E4 -> 4.7473962e-09 | E46: =Z4+AA4+AB4+AC4+AD4 -> 0.0074717626 | F46: =D46/E46 -> 6.3537835e-07 | G46: =(1-(1-D46)^12)*100 -> 5.6968754e-06 | H46: =(1-(1-E46)^12)*100 -> 8.6066798 | K46: 1 | L46: 1 | M46: =VLOOKUP($C46,'Refi Adj'!$B$2:$E$30,4,0) -> 1 | N46: =Z4+AA4+AB4*K46+AC4*L46+AD4*M46*$K$41 -> 0.0074717626 | O46: =100*(1-(1-N46)^12) -> 8.6066798 | P46: =D46/N46 -> 6.3537835e-07
A47: =K5 -> -83.743459 | B47: =AQ5/1000000000 -> 0.0069607088 | C47: =AO5 -> 05:-100--75 | D47: =E5 -> 0.005783867 | E47: =Z5+AA5+AB5+AC5+AD5 -> 0.014585386 | F47: =D47/E47 -> 0.3965522 | G47: =(1-(1-D47)^12)*100 -> 6.7240517 | H47: =(1-(1-E47)^12)*100 -> 16.164495 | K47: 1 | L47: 1 | M47: =VLOOKUP($C47,'Refi Adj'!$B$2:$E$30,4,0) -> 1 | N47: =Z5+AA5+AB5*K47+AC5*L47+AD5*M47*$K$41 -> 0.014585386 | O47: =100*(1-(1-N47)^12) -> 16.164495 | P47: =D47/N47 -> 0.3965522
A48: =K6 -> -56.696947 | B48: =AQ6/1000000000 -> 0.10922347 | C48: =AO6 -> 06:-75--50 | D48: =E6 -> 0.0045090249 | E48: =Z6+AA6+AB6+AC6+AD6 -> 0.0069709665 | F48: =D48/E48 -> 0.64682922 | G48: =(1-(1-D48)^12)*100 -> 5.2786397 | H48: =(1-(1-E48)^12)*100 -> 8.0517738 | K48: 1 | L48: 1 | M48: =VLOOKUP($C48,'Refi Adj'!$B$2:$E$30,4,0) -> 0.5 | N48: =Z6+AA6+AB6*K48+AC6*L48+AD6*M48*$K$41 -> 0.0050599834 | O48: =100*(1-(1-N48)^12) -> 5.9058153 | P48: =D48/N48 -> 0.89111456
A49: =K7 -> -33.134227 | B49: =AQ7/1000000000 -> 1.3745647 | C49: =AO7 -> 07:-50--25 | D49: =E7 -> 0.0029573223 | E49: =Z7+AA7+AB7+AC7+AD7 -> 0.0076986322 | F49: =D49/E49 -> 0.38413608 | G49: =(1-(1-D49)^12)*100 -> 3.4916301 | H49: =(1-(1-E49)^12)*100 -> 8.8570502 | K49: 1 | L49: 1 | M49: =VLOOKUP($C49,'Refi Adj'!$B$2:$E$30,4,0) -> 0.5 | N49: =Z7+AA7+AB7*K49+AC7*L49+AD7*M49*$K$41 -> 0.0054098304 | O49: =100*(1-(1-N49)^12) -> 6.3020802 | P49: =D49/N49 -> 0.54665713
A50: =K8 -> -22.352891 | B50: =AQ8/1000000000 -> 0.80771624 | C50: =AO8 -> 08-1:-25--20 | D50: =E8 -> 0.0057291129 | E50: =Z8+AA8+AB8+AC8+AD8 -> 0.011215476 | F50: =D50/E50 -> 0.51082208 | G50: =(1-(1-D50)^12)*100 -> 6.6623896 | H50: =(1-(1-E50)^12)*100 -> 12.658645 | K50: 1 | L50: 1 | M50: =VLOOKUP($C50,'Refi Adj'!$B$2:$E$30,4,0) -> 0.51 | N50: =Z8+AA8+AB8*K50+AC8*L50+AD8*M50*$K$41 -> 0.0072616566 | O50: =100*(1-(1-N50)^12) -> 8.3742471 | P50: =D50/N50 -> 0.78895399
A51: =K9 -> -17.273662 | B51: =AQ9/1000000000 -> 1.1752904 | C51: =AO9 -> 08-2:-20--15 | D51: =E9 -> 0.0043605563 | E51: =Z9+AA9+AB9+AC9+AD9 -> 0.012726839 | F51: =D51/E51 -> 0.3426268 | G51: =(1-(1-D51)^12)*100 -> 5.1089785 | H51: =(1-(1-E51)^12)*100 -> 14.247267 | K51: 1 | L51: 1 | M51: =VLOOKUP($C51,'Refi Adj'!$B$2:$E$30,4,0) -> 0.52 | N51: =Z9+AA9+AB9*K51+AC9*L51+AD9*M51*$K$41 -> 0.0081272778 | O51: =100*(1-(1-N51)^12) -> 9.3283829 | P51: =D51/N51 -> 0.53653343
A52: =K10 -> -12.321954 | B52: =AQ10/1000000000 -> 1.7789323 | C52: =AO10 -> 08-3:-15--10 | D52: =E10 -> 0.0063801337 | E52: =Z10+AA10+AB10+AC10+AD10 -> 0.014031478 | F52: =D52/E52 -> 0.45470149 | G52: =(1-(1-D52)^12)*100 -> 7.3931326 | H52: =(1-(1-E52)^12)*100 -> 15.597249 | K52: 1 | L52: 1 | M52: =VLOOKUP($C52,'Refi Adj'!$B$2:$E$30,4,0) -> 0.53 | N52: =Z10+AA10+AB10*K52+AC10*L52+AD10*M52*$K$41 -> 0.0089225016 | O52: =100*(1-(1-N52)^12) -> 10.196887 | P52: =D52/N52 -> 0.71506109
A53: =K11 -> -7.3847568 | B53: =AQ11/1000000000 -> 2.490475 | C53: =AO11 -> 08-4:-10--5 | D53: =E11 -> 0.0093059766 | E53: =Z11+AA11+AB11+AC11+AD11 -> 0.015289856 | F53: =D53/E53 -> 0.6086373 | G53: =(1-(1-D53)^12)*100 -> 10.612968 | H53: =(1-(1-E53)^12)*100 -> 16.880879 | K53: 1 | L53: 1 | M53: =VLOOKUP($C53,'Refi Adj'!$B$2:$E$30,4,0) -> 0.54 | N53: =Z11+AA11+AB11*K53+AC11*L53+AD11*M53*$K$41 -> 0.0096932115 | O53: =100*(1-(1-N53)^12) -> 11.031335 | P53: =D53/N53 -> 0.96005092
A54: =K12 -> -2.3578415 | B54: =AQ12/1000000000 -> 3.2608523 | C54: =AO12 -> 08:-25-0 | D54: =E12 -> 0.0092223714 | E54: =Z12+AA12+AB12+AC12+AD12 -> 0.016546315 | F54: =D54/E54 -> 0.55736708 | G54: =(1-(1-D54)^12)*100 -> 10.522405 | H54: =(1-(1-E54)^12)*100 -> 18.144674 | K54: 1 | L54: 1 | M54: =VLOOKUP($C54,'Refi Adj'!$B$2:$E$30,4,0) -> 0.55 | N54: =Z12+AA12+AB12*K54+AC12*L54+AD12*M54*$K$41 -> 0.010525992 | O54: =100*(1-(1-N54)^12) -> 11.924993 | P54: =D54/N54 -> 0.87615224
A55: =K13 -> 2.6131292 | B55: =AQ13/1000000000 -> 4.2927447 | C55: =AO13 -> 09-1:0-5 | D55: =E13 -> 0.011306181 | E55: =Z13+AA13+AB13+AC13+AD13 -> 0.01765741 | F55: =D55/E55 -> 0.64030801 | G55: =(1-(1-D55)^12)*100 -> 12.754743 | H55: =(1-(1-E55)^12)*100 -> 19.247555 | K55: 1 | L55: 1 | M55: =VLOOKUP($C55,'Refi Adj'!$B$2:$E$30,4,0) -> 0.6 | N55: =Z13+AA13+AB13*K55+AC13*L55+AD13*M55*$K$41 -> 0.011876237 | O55: =100*(1-(1-N55)^12) -> 13.356473 | P55: =D55/N55 -> 0.9520003
A56: =K14 -> 7.6208417 | B56: =AQ14/1000000000 -> 5.5431869 | C56: =AO14 -> 09-2:5-10 | D56: =E14 -> 0.013841548 | E56: =Z14+AA14+AB14+AC14+AD14 -> 0.018533796 | F56: =D56/E56 -> 0.74682748 | G56: =(1-(1-D56)^12)*100 -> 15.401938 | H56: =(1-(1-E56)^12)*100 -> 20.107834 | K56: 1 | L56: 1 | M56: =VLOOKUP($C56,'Refi Adj'!$B$2:$E$30,4,0) -> 0.65 | N56: =Z14+AA14+AB14*K56+AC14*L56+AD14*M56*$K$41 -> 0.013185731 | O56: =100*(1-(1-N56)^12) -> 14.724349 | P56: =D56/N56 -> 1.0497368
... A73: =K31 -> 159.99643 | B73: =AQ31/1000000000 -> 2.9536473 | C73: =AO31 -> 15:150-175 | D73: =E31 -> 0.044546221 | E73: =Z31+AA31+AB31+AC31+AD31 -> 0.055851101 | F73: =D73/E73 -> 0.79758896 | G73: =(1-(1-D73)^12)*100 -> 42.121644 | H73: =(1-(1-E73)^12)*100 -> 49.825172 | K73: 1 | L73: 1 | M73: =VLOOKUP($C73,'Refi Adj'!$B$2:$E$30,4,0) -> 0.9 | N73: =Z31+AA31+AB31*K73+AC31*L73+AD31*M73*$K$41 -> 0.050718754 | O73: =100*(1-(1-N73)^12) -> 46.452548 | P73: =D73/N73 -> 0.87829881
A85: WALA [12,24) | C85: BROKER | AS85: tover | AT85: cash | AW85: refi
A86: modelId | B86: SFACTOR_PREPAY_TRACKING_CPR | C86: PREPAY_CPR1 | D86: PREPAY_TRACKING_CPR1 | E86: PREPAY_SMM1 | F86: PREPAY_TRACKING_SMM1 | G86: PCT_LOANTYPE | H86: _ORIGNOTERATE | I86: _ZEROSATO | J86: _SATO | K86: _REFI_INCENTIVE_Fixed | L86: _Fixed_cost | M86: _LOANAGE | N86: _LTV | O86: _CLTV | P86: _AVG_LOANSIZE_SCHAMBALANCE | Q86: _WACLS | R86: _FICO | S86: PCT_ISSECONDLIEN | T86: _OrigCombLTV | U86: PCT_SVC | V86: PCT_TPO | W86: PCT_GEO | X86: PCT_LOANPURPOSE | Y86: PCT_OCC | Z86: curtailsmm | AA86: defaultsmm | AB86: toverSmm | AC86: cashoutSmm | AD86: refiSmm | AE86: cumHPA | AF86: cumHPA05Pct | AG86: cumHPA15Pct | AH86: cumHPA20Pct | AI86: cumHPA25Pct | AJ86: cumHPA30Pct | AK86: cumHPA35Pct | AL86: cumHPA40Pct | AM86: adjtoverSmm | AN86: adjRefiSmm | AO86: groupByColumn | AP86: curve | AQ86: Balance | AR86: LoanCount | AS86: PCT_BROKER | AT86: PCT_CORRES | AU86: PCT_NonRETAIL | AV86: PCT_RETAIL | AW86: PCT_CashWindow | AX86: PCT_NonCashWindow
A87: 96 | B87: 0.99182842 | C87: 3.8957922 | D87: 9.3769677 | E87: 0.003305947 | F87: 0.0081715784 | G87: 0 | H87: 3.9675065 | I87: 4.1283936 | J87: -54.678879 | K87: -56.682817 | L87: 18.767246 | M87: 16.274611 | N87: 77.853085 | O87: 75.207731 | P87: 267569.16 | Q87: 188541.3 | R87: 773.89744 | S87: 0 | T87: 0 | U87: 0.071689611 | V87: 0 | W87: 0 | X87: 0.5444671 | Y87: 0 | Z87: 0.0007036877 | AA87: 8.8031509e-05 | AB87: 0.0025907227 | AC87: 3.7428656e-08 | AD87: 0.0047890873 | AE87: -0.022818134 | AF87: 0.98731299 | AG87: 0.99644125 | AH87: 1 | AI87: 1 | AJ87: 1 | AK87: 1 | AL87: 1 | AM87: 0 | AN87: 0 | AO87: 06:-75--50 | AP87: =-75--50 -> -25 | AQ87: 17345800 | AR87: 92 | AS87: 100 | AT87: 0 | AU87: 100 | AV87: 0 | AW87: 0 | AX87: 0
A88: 96 | B88: 0.99146676 | C88: 2.5593301 | D88: 9.7727093 | E88: 0.00215821 | F88: 0.0085332374 | G88: 0 | H88: 3.8999139 | I88: 4.1100912 | J88: -59.796144 | K88: -32.151317 | L88: 15.206687 | M88: 16.277653 | N88: 74.240428 | O88: 72.758628 | P88: 291058.35 | Q88: 258641.71 | R88: 784.51618 | S88: 0 | T88: 0 | U88: 0.067353074 | V88: 0 | W88: 0 | X88: 0.6198173 | Y88: 0 | Z88: 0.00044165102 | AA88: 6.54869e-05 | AB88: 0.0025421345 | AC88: 2.7072769e-08 | AD88: 0.0054839232 | AE88: -0.017049304 | AF88: 0.97692522 | AG88: 0.99625024 | AH88: 1 | AI88: 1 | AJ88: 1 | AK88: 1 | AL88: 1 | AM88: 0 | AN88: 0 | AO88: 07:-50--25 | AP88: =-50--25 -> -25 | AQ88: 1.8285969e+08 | AR88: 707 | AS88: 100 | AT88: 0 | AU88: 100 | AV88: 0 | AW88: 0 | AX88: 0
A89: 96 | B89: 0.98853892 | C89: 9.4220487 | D89: 12.918625 | E89: 0.0082127038 | F89: 0.011461079 | G89: 0 | H89: 3.9787687 | I89: 4.11636 | J89: -52.192348 | K89: -22.234953 | L89: 15.058437 | M89: 16.143549 | N89: 73.258944 | O89: 71.898842 | P89: 289927.42 | Q89: 263943.27 | R89: 783.4957 | S89: 0 | T89: 0 | U89: 0.12846874 | V89: 0 | W89: 0 | X89: 0.65047953 | Y89: 0 | Z89: 0.00038934545 | AA89: 5.3528718e-05 | AB89: 0.0025274232 | AC89: 0 | AD89: 0.0084907668 | AE89: -0.013797444 | AF89: 0.98291916 | AG89: 1 | AH89: 1 | AI89: 1 | AJ89: 1 | AK89: 1 | AL89: 1 | AM89: 0 | AN89: 0 | AO89: 08-1:-25--20 | AP89: =-25--20 -> -5 | AQ89: 1.0425759e+08 | AR89: 395 | AS89: 100 | AT89: 0 | AU89: 100 | AV89: 0 | AW89: 0 | AX89: 0
A90: 96 | B90: 0.98664989 | C90: 10.8075 | D90: 14.894654 | E90: 0.0094858256 | F90: 0.013350114 | G90: 0 | H90: 4.0123687 | I90: 4.1022851 | J90: -48.675926 | K90: -17.320366 | L90: 14.771784 | M90: 16.461219 | N90: 73.185534 | O90: 71.808848 | P90: 293291.65 | Q90: 268021.91 | R90: 783.50073 | S90: 0 | T90: 0 | U90: 0.12902529 | V90: 0 | W90: 0 | X90: 0.6521736 | Y90: 0 | Z90: 0.00038242703 | AA90: 6.5931189e-05 | AB90: 0.0026124491 | AC90: 4.1997689e-08 | AD90: 0.01028925 | AE90: -0.012150854 | AF90: 0.95700419 | AG90: 0.99466206 | AH90: 1 | AI90: 1 | AJ90: 1 | AK90: 1 | AL90: 1 | AM90: 0 | AN90: 0 | AO90: 08-2:-20--15 | AP90: =-20--15 -> -5 | AQ90: 1.750183e+08 | AR90: 653 | AS90: 100 | AT90: 0 | AU90: 100 | AV90: 0 | AW90: 0 | AX90: 0
A91: 96 | B91: 0.98525239 | C91: 10.602841 | D91: 16.329962 | E91: 0.0092966237 | F91: 0.01474761 | G91: 0 | H91: 4.0594479 | I91: 4.1019476 | J91: -43.895944 | K91: -12.265261 | L91: 14.862993 | M91: 16.561958 | N91: 72.892803 | O91: 71.466897 | P91: 290133.71 | Q91: 267610.1 | R91: 782.54737 | S91: 0 | T91: 0 | U91: 0.14817147 | V91: 0 | W91: 0 | X91: 0.67536497 | Y91: 0 | Z91: 0.00038339238 | AA91: 6.8300586e-05 | AB91: 0.0026511847 | AC91: 1.093881e-07 | AD91: 0.011644608 | AE91: -0.011989605 | AF91: 0.95471591 | AG91: 0.99739985 | AH91: 0.99974737 | AI91: 1 | AJ91: 1 | AK91: 1 | AL91: 1 | AM91: 0 | AN91: 0 | AO91: 08-3:-15--10 | AP91: =-15--10 -> -5 | AQ91: 2.8393432e+08 | AR91: 1061 | AS91: 100 | AT91: 0 | AU91: 100 | AV91: 0 | AW91: 0 | AX91: 0
A92: 96 | B92: 0.98387571 | C92: 15.810679 | D92: 17.722159 | E92: 0.014239488 | F92: 0.016124286 | G92: 0 | H92: 4.1077354 | I92: 4.099816 | J92: -39.524502 | K92: -7.3224373 | L92: 14.493312 | M92: 16.391644 | N92: 73.64129 | O92: 72.295637 | P92: 297162.78 | Q92: 274503.54 | R92: 783.19252 | S92: 0 | T92: 0 | U92: 0.15411512 | V92: 0 | W92: 0 | X92: 0.69552451 | Y92: 0 | Z92: 0.00037708944 | AA92: 7.175416e-05 | AB92: 0.0025337216 | AC92: 1.6025797e-07 | AD92: 0.013141546 | AE92: -0.011378594 | AF92: 0.94440567 | AG92: 0.98798332 | AH92: 0.99955536 | AI92: 1 | AJ92: 1 | AK92: 1 | AL92: 1 | AM92: 0 | AN92: 0 | AO92: 08-4:-10--5 | AP92: =-10--5 -> -5 | AQ92: 4.2300995e+08 | AR92: 1541 | AS92: 100 | AT92: 0 | AU92: 100 | AV92: 0 | AW92: 0 | AX92: 0
A93: 96 | B93: 0.98253861 | C93: 14.323614 | D93: 19.053982 | E93: 0.012800118 | F93: 0.017461394 | G93: 0 | H93: 4.1116634 | I93: 4.0847326 | J93: -38.215918 | K93: -2.3387297 | L93: 14.464719 | M93: 16.5396 | N93: 71.790473 | O93: 70.257818 | P93: 297861.7 | Q93: 275125.01 | R93: 782.20967 | S93: 0 | T93: 0 | U93: 0.17400611 | V93: 0 | W93: 0 | X93: 0.71708806 | Y93: 0 | Z93: 0.00037544413 | AA93: 6.5077232e-05 | AB93: 0.0026184242 | AC93: 2.1687116e-07 | AD93: 0.014402217 | AE93: -0.0088282285 | AF93: 0.94302178 | AG93: 0.99026126 | AH93: 0.99944319 | AI93: 1 | AJ93: 1 | AK93: 1 | AL93: 1 | AM93: 0 | AN93: 0 | AO93: 08:-25-0 | AP93: =-25-0 -> -25 | AQ93: 6.2948602e+08 | AR93: 2288 | AS93: 100 | AT93: 0 | AU93: 100 | AV93: 0 | AW93: 0 | AX93: 0
A94: 96 | B94: 0.9812422 | C94: 19.451517 | D94: 20.326364 | E94: 0.017864415 | F94: 0.018757795 | G94: 0 | H94: 4.1335924 | I94: 4.0727535 | J94: -35.041675 | K94: 2.6535888 | L94: 14.474732 | M94: 16.462474 | N94: 71.886996 | O94: 70.234034 | P94: 297332.28 | Q94: 275510.89 | R94: 782.24488 | S94: 0 | T94: 0 | U94: 0.21882607 | V94: 0 | W94: 0 | X94: 0.7578272 | Y94: 0 | Z94: 0.00037073438 | AA94: 6.3384512e-05 | AB94: 0.0026459512 | AC94: 3.1561933e-07 | AD94: 0.015677395 | AE94: -0.0055919344 | AF94: 0.92268659 | AG94: 0.98776176 | AH94: 0.99886647 | AI94: 1 | AJ94: 1 | AK94: 1 | AL94: 1 | AM94: 0 | AN94: 0 | AO94: 09-1:0-5 | AP94: 0-5 | AQ94: 8.579409e+08 | AR94: 3114 | AS94: 100 | AT94: 0 | AU94: 100 | AV94: 0 | AW94: 0 | AX94: 0
A95: 96 | B95: 0.98008601 | C95: 23.94502 | D95: 21.445638 | E95: 0.022551304 | F95: 0.019913986 | G95: 0 | H95: 4.1410751 | I95: 4.048044 | J95: -33.144411 | K95: 7.6198853 | L95: 14.82869 | M95: 16.410128 | N95: 71.889857 | O95: 69.875992 | P95: 290487.27 | Q95: 268888.98 | R95: 782.61242 | S95: 0 | T95: 0 | U95: 0.2332186 | V95: 0 | W95: 0 | X95: 0.77023482 | Y95: 0 | Z95: 0.00037079632 | AA95: 6.9716105e-05 | AB95: 0.0027526028 | AC95: 1.5092874e-06 | AD95: 0.016719347 | AE95: 0.00031504853 | AF95: 0.88392053 | AG95: 0.97579615 | AH95: 0.99568268 | AI95: 0.99968544 | AJ95: 1 | AK95: 1 | AL95: 1 | AM95: 0 | AN95: 0 | AO95: 09-2:5-10 | AP95: 43230 | AQ95: 1.1519204e+09 | AR95: 4284 | AS95: 100 | AT95: 0 | AU95: 100 | AV95: 0 | AW95: 0 | AX95: 0
A96: 96 | B96: 0.97878733 | C96: 20.863987 | D96: 22.685659 | E96: 0.019311279 | F96: 0.021212672 | G96: 0 | H96: 4.1265253 | I96: 4.020329 | J96: -32.434444 | K96: 12.702784 | L96: 14.915967 | M96: 16.210359 | N96: 69.936325 | O96: 67.40952 | P96: 287560.37 | Q96: 267491.7 | R96: 783.4241 | S96: 0 | T96: 0 | U96: 0.24622891 | V96: 0 | W96: 0 | X96: 0.78940181 | Y96: 0 | Z96: 0.00037264348 | AA96: 6.1615366e-05 | AB96: 0.0028557815 | AC96: 1.6981223e-06 | AD96: 0.017920919 | AE96: 0.0072628806 | AF96: 0.83756179 | AG96: 0.9634191 | AH96: 0.99677143 | AI96: 0.99976356 | AJ96: 1 | AK96: 1 | AL96: 1 | AM96: 0 | AN96: 0 | AO96: 09-3:10-15 | AP96: 43388 | AQ96: 1.6116375e+09 | AR96: 6025 | AS96: 100 | AT96: 0 | AU96: 100 | AV96: 0 | AW96: 0 | AX96: 0
A97: 96 | B97: 0.9770496 | C97: 23.805678 | D97: 24.316823 | E97: 0.022402196 | F97: 0.022950396 | G97: 0 | H97: 4.1249627 | I97: 3.996877 | J97: -30.839618 | K97: 17.616236 | L97: 14.585152 | M97: 15.98221 | N97: 69.064701 | O97: 66.273359 | P97: 294113.95 | Q97: 273704.23 | R97: 783.7665 | S97: 0 | T97: 0 | U97: 0.25910044 | V97: 0 | W97: 0 | X97: 0.81223351 | Y97: 0 | Z97: 0.00036983754 | AA97: 6.0334906e-05 | AB97: 0.0028946161 | AC97: 3.991291e-06 | AD97: 0.019621602 | AE97: 0.013918083 | AF97: 0.79075428 | AG97: 0.93225234 | AH97: 0.99252337 | AI97: 0.99853656 | AJ97: 1 | AK97: 1 | AL97: 1 | AM97: 0 | AN97: 0 | AO97: 09-4:15-20 | AP97: 15-20 | AQ97: 2.4564955e+09 | AR97: 8975 | AS97: 100 | AT97: 0 | AU97: 100 | AV97: 0 | AW97: 0 | AX97: 0
A98: 96 | B98: 0.97500255 | C98: 30.879326 | D98: 26.197848 | E98: 0.030307589 | F98: 0.024997449 | G98: 0 | H98: 4.1179547 | I98: 3.9652869 | J98: -30.422156 | K98: 22.590179 | L98: 14.16522 | M98: 15.924105 | N98: 66.216865 | O98: 63.242575 | P98: 301198.07 | Q98: 281802.72 | R98: 784.11376 | S98: 0 | T98: 0 | U98: 0.26559685 | V98: 0 | W98: 0 | X98: 0.84041247 | Y98: 0 | Z98: 0.00036890884 | AA98: 5.481214e-05 | AB98: 0.0029440371 | AC98: 5.5388258e-06 | AD98: 0.021624138 | AE98: 0.019702368 | AF98: 0.75383705 | AG98: 0.92120141 | AH98: 0.99290227 | AI98: 0.99818661 | AJ98: 1 | AK98: 1 | AL98: 1 | AM98: 0 | AN98: 0 | AO98: 09:0-25 | AP98: 0-25 | AQ98: 3.3771238e+09 | AR98: 11984 | AS98: 100 | AT98: 0 | AU98: 100 | AV98: 0 | AW98: 0 | AX98: 0
A99: 96 | B99: 0.97309602 | C99: 35.002482 | D99: 27.91111 | E99: 0.035264934 | F99: 0.026903983 | G99: 0 | H99: 4.1320208 | I99: 3.9390589 | J99: -29.076316 | K99: 27.547268 | L99: 13.906361 | M99: 15.993033 | N99: 66.040052 | O99: 62.599358 | P99: 306080.2 | Q99: 287059.91 | R99: 783.65888 | S99: 0 | T99: 0 | U99: 0.25886295 | V99: 0 | W99: 0 | X99: 0.83429079 | Y99: 0 | Z99: 0.00036785539 | AA99: 5.6192523e-05 | AB99: 0.0030018129 | AC99: 8.3068484e-06 | AD99: 0.023469801 | AE99: 0.025956585 | AF99: 0.71356769 | AG99: 0.90914449 | AH99: 0.99017706 | AI99: 0.99715789 | AJ99: 1 | AK99: 1 | AL99: 1 | AM99: 0 | AN99: 0 | AO99: 10-1:25-30 | AP99: 25-30 | AQ99: 3.9548243e+09 | AR99: 13777 | AS99: 100 | AT99: 0 | AU99: 100 | AV99: 0 | AW99: 0 | AX99: 0
A100: 96 | B100: 0.97091667 | C100: 37.322085 | D100: 29.824829 | E100: 0.038182049 | F100: 0.029083332 | G100: 0 | H100: 4.1277907 | I100: 3.8973419 | J100: -28.48197 | K100: 32.542028 | L100: 13.669151 | M100: 16.000816 | N100: 65.147319 | O100: 61.460064 | P100: 311128.71 | Q100: 292033.55 | R100: 784.2264 | S100: 0 | T100: 0 | U100: 0.27340684 | V100: 0 | W100: 0 | X100: 0.84854343 | Y100: 0 | Z100: 0.00036784593 | AA100: 5.5420989e-05 | AB100: 0.0030536814 | AC100: 1.0630446e-05 | AD100: 0.025595739 | AE100: 0.034819176 | AF100: 0.67057978 | AG100: 0.87480962 | AH100: 0.99030351 | AI100: 0.99805259 | AJ100: 1 | AK100: 1 | AL100: 1 | AM100: 0 | AN100: 0 | AO100: 10-2:30-35 | AP100: 30-35 | AQ100: 4.3907244e+09 | AR100: 15035 | AS100: 100 | AT100: 0 | AU100: 100 | AV100: 0 | AW100: 0 | AX100: 0
A101: 96 | B101: 0.96906112 | C101: 39.012061 | D101: 31.41739 | E101: 0.040370339 | F101: 0.030938884 | G101: 0 | H101: 4.1407288 | I101: 3.8616035 | J101: -27.749282 | K101: 37.486494 | L101: 13.666565 | M101: 16.088478 | N101: 65.027498 | O101: 60.962342 | P101: 310640.52 | Q101: 292099.2 | R101: 783.91532 | S101: 0 | T101: 0 | U101: 0.2741301 | V101: 0 | W101: 0 | X101: 0.83728411 | Y101: 0 | Z101: 0.00036729239 | AA101: 5.4592609e-05 | AB101: 0.0031091513 | AC101: 1.1568735e-05 | AD101: 0.027396265 | AE101: 0.03772466 | AF101: 0.64459273 | AG101: 0.89988018 | AH101: 0.98723352 | AI101: 0.99853076 | AJ101: 1 | AK101: 1 | AL101: 1 | AM101: 0 | AN101: 0 | AO101: 10-3:35-40 | AP101: 35-40 | AQ101: 4.437571e+09 | AR101: 15192 | AS101: 100 | AT101: 0 | AU101: 100 | AV101: 0 | AW101: 0 | AX101: 0
A102: 96 | B102: 0.96673686 | C102: 42.22908 | D102: 33.365473 | E102: 0.044694143 | F102: 0.033263142 | G102: 0 | H102: 4.1633655 | I102: 3.8333468 | J102: -26.642684 | K102: 42.421648 | L102: 13.534384 | M102: 16.218482 | N102: 65.216204 | O102: 60.830955 | P102: 314000.99 | Q102: 294944.17 | R102: 783.87257 | S102: 0 | T102: 0 | U102: 0.28137819 | V102: 0 | W102: 0 | X102: 0.84062486 | Y102: 0 | Z102: 0.00036878211 | AA102: 5.6210012e-05 | AB102: 0.0031894474 | AC102: 1.2788838e-05 | AD102: 0.0296359 | AE102: 0.045297538 | AF102: 0.60042005 | AG102: 0.88244543 | AH102: 0.98714774 | AI102: 0.99890422 | AJ102: 1 | AK102: 1 | AL102: 1 | AM102: 0 | AN102: 0 | AO102: 10-4:40-45 | AP102: 40-45 | AQ102: 4.22655e+09 | AR102: 14330 | AS102: 100 | AT102: 0 | AU102: 100 | AV102: 0 | AW102: 0 | AX102: 0
A103: 96 | B103: 0.96427214 | C103: 42.385461 | D103: 35.375762 | E103: 0.044909905 | F103: 0.03572786 | G103: 0 | H103: 4.2053802 | I103: 3.8264175 | J103: -24.852095 | K103: 47.512004 | L103: 13.408458 | M103: 16.551013 | N103: 63.837087 | O103: 59.481399 | P103: 317484.72 | Q103: 297704.26 | R103: 783.68172 | S103: 0 | T103: 0 | U103: 0.26473142 | V103: 0 | W103: 0 | X103: 0.83669717 | Y103: 0 | Z103: 0.00036870671 | AA103: 6.3072e-05 | AB103: 0.0032262464 | AC103: 1.1692417e-05 | AD103: 0.032058128 | AE103: 0.048102621 | AF103: 0.59401179 | AG103: 0.894599 | AH103: 0.98843402 | AI103: 0.99877181 | AJ103: 1 | AK103: 1 | AL103: 1 | AM103: 0 | AN103: 0 | AO103: 10:25-50 | AP103: 25-50 | AQ103: 3.970184e+09 | AR103: 13336 | AS103: 100 | AT103: 0 | AU103: 100 | AV103: 0 | AW103: 0 | AX103: 0
A104: 96 | B104: 0.96322012 | C104: 45.94881 | D104: 36.216764 | E104: 0.049977761 | F104: 0.03677988 | G104: 0 | H104: 4.3069906 | I104: 3.8478541 | J104: -20.720569 | K104: 52.525414 | L104: 14.016152 | M104: 17.198522 | N104: 68.242989 | O104: 64.029642 | P104: 304170.72 | Q104: 284836.96 | R104: 782.53178 | S104: 0 | T104: 0 | U104: 0.23335837 | V104: 0 | W104: 0 | X104: 0.78723007 | Y104: 0 | Z104: 0.00036939263 | AA104: 7.320563e-05 | AB104: 0.003292512 | AC104: 9.5123652e-06 | AD104: 0.033035244 | AE104: 0.036502937 | AF104: 0.64151773 | AG104: 0.92290871 | AH104: 0.99178883 | AI104: 0.99919605 | AJ104: 1 | AK104: 1 | AL104: 1 | AM104: 0 | AN104: 0 | AO104: 11-1:50-55 | AP104: 50-55 | AQ104: 3.3368649e+09 | AR104: 11715 | AS104: 100 | AT104: 0 | AU104: 100 | AV104: 0 | AW104: 0 | AX104: 0
A105: 96 | B105: 0.96136775 | C105: 46.558381 | D105: 37.673235 | E105: 0.050875245 | F105: 0.03863225 | G105: 0 | H105: 4.3549524 | I105: 3.8473489 | J105: -19.564977 | K105: 57.496639 | L105: 14.11715 | M105: 17.497986 | N105: 67.040302 | O105: 63.041882 | P105: 301948.14 | Q105: 282804.23 | R105: 782.7508 | S105: 0 | T105: 0 | U105: 0.23700387 | V105: 0 | W105: 0 | X105: 0.7946447 | Y105: 0 | Z105: 0.00037049836 | AA105: 7.9962251e-05 | AB105: 0.0032937244 | AC105: 9.5781815e-06 | AD105: 0.034878473 | AE105: 0.035495696 | AF105: 0.64955835 | AG105: 0.92574536 | AH105: 0.99177366 | AI105: 0.99928007 | AJ105: 1 | AK105: 1 | AL105: 1 | AM105: 0 | AN105: 0 | AO105: 11-2:55-60 | AP105: 55-60 | AQ105: 3.2431989e+09 | AR105: 11468 | AS105: 100 | AT105: 0 | AU105: 100 | AV105: 0 | AW105: 0 | AX105: 0
A106: 96 | B106: 0.95957318 | C106: 48.369596 | D106: 39.055121 | E106: 0.053598413 | F106: 0.040426819 | G106: 0 | H106: 4.4317836 | I106: 3.8676266 | J106: -17.320993 | K106: 62.446297 | L106: 14.268627 | M106: 17.677067 | N106: 67.785288 | O106: 63.997449 | P106: 299854.45 | Q106: 279810.88 | R106: 782.07668 | S106: 0 | T106: 0 | U106: 0.24171011 | V106: 0 | W106: 0 | X106: 0.7615655 | Y106: 0 | Z106: 0.00037112525 | AA106: 8.7893186e-05 | AB106: 0.0032842944 | AC106: 9.3430351e-06 | AD106: 0.036674149 | AE106: 0.029339693 | AF106: 0.67731442 | AG106: 0.95454812 | AH106: 0.9935198 | AI106: 0.99882705 | AJ106: 1 | AK106: 1 | AL106: 1 | AM106: 0 | AN106: 0 | AO106: 11-3:60-65 | AP106: 60-65 | AQ106: 3.1971192e+09 | AR106: 11426 | AS106: 100 | AT106: 0 | AU106: 100 | AV106: 0 | AW106: 0 | AX106: 0
A107: 96 | B107: 0.95829379 | C107: 47.925493 | D107: 40.023093 | E107: 0.052922693 | F107: 0.041706214 | G107: 0 | H107: 4.5097981 | I107: 3.8948256 | J107: -15.446203 | K107: 67.445449 | L107: 14.416026 | M107: 17.656688 | N107: 68.110467 | O107: 64.532312 | P107: 297098.96 | Q107: 276954.95 | R107: 781.66658 | S107: 0 | T107: 0 | U107: 0.25422807 | V107: 0 | W107: 0 | X107: 0.73625999 | Y107: 0 | Z107: 0.00037198959 | AA107: 9.4553738e-05 | AB107: 0.0032602506 | AC107: 9.793879e-06 | AD107: 0.037969612 | AE107: 0.025062074 | AF107: 0.69109475 | AG107: 0.95240101 | AH107: 0.9939466 | AI107: 0.9989057 | AJ107: 1 | AK107: 1 | AL107: 1 | AM107: 0 | AN107: 0 | AO107: 11-4:65-70 | AP107: 65-70 | AQ107: 3.1955062e+09 | AR107: 11538 | AS107: 100 | AT107: 0 | AU107: 100 | AV107: 0 | AW107: 0 | AX107: 0
A108: 96 | B108: 0.95612858 | C108: 47.771931 | D108: 41.629205 | E108: 0.052690271 | F108: 0.043871419 | G108: 0 | H108: 4.5482527 | I108: 3.8964832 | J108: -14.674258 | K108: 72.47937 | L108: 14.154327 | M108: 17.524574 | N108: 66.514625 | O108: 62.894369 | P108: 301721.94 | Q108: 282076.09 | R108: 781.79005 | S108: 0 | T108: 0 | U108: 0.26510072 | V108: 0 | W108: 0 | X108: 0.73703351 | Y108: 0 | Z108: 0.00037079033 | AA108: 9.7058762e-05 | AB108: 0.0032567595 | AC108: 1.0567251e-05 | AD108: 0.040136228 | AE108: 0.027329153 | AF108: 0.66455656 | AG108: 0.95302023 | AH108: 0.9934843 | AI108: 0.99899335 | AJ108: 1 | AK108: 1 | AL108: 1 | AM108: 0 | AN108: 0 | AO108: 11:50-75 | AP108: 50-75 | AQ108: 3.2653128e+09 | AR108: 11576 | AS108: 100 | AT108: 0 | AU108: 100 | AV108: 0 | AW108: 0 | AX108: 0
... A114: 96 | B114: 0.93636927 | C114: 47.495831 | D114: 54.567584 | E114: 0.052273955 | F114: 0.06363073 | G114: 0 | H114: 5.1962175 | I114: 3.6487088 | J114: 17.28872 | K114: 209.55229 | L114: 14.52586 | M114: 20.792683 | N114: 90.120235 | O114: 75.17575 | P114: 294450.4 | Q114: 274910.83 | R114: 775.39517 | S114: 0 | T114: 0 | U114: 0.083777428 | V114: 0 | W114: 0 | X114: 0.28831945 | Y114: 0 | Z114: 0.00037198764 | AA114: 0.00037985115 | AB114: 0.0043843365 | AC114: 0.0005945363 | AD114: 0.057900001 | AE114: 0.16459065 | AF114: 0 | AG114: 0.46714353 | AH114: 0.67606014 | AI114: 0.98161705 | AJ114: 1 | AK114: 1 | AL114: 1 | AM114: 0 | AN114: 0 | AO114: 17:200-225 | AP114: 200-225 | AQ114: 20893223 | AR114: 76 | AS114: 100 | AT114: 0 | AU114: 100 | AV114: 0 | AW114: 0 | AX114: 0
L117: elbow | M117: 15bps earlier
L118: Channel Dial | M118: 1.05
K120: turn | L120: cash | M120: refi | R120: turn | W120: cash | AB120: refi
A121: incentive | B121: =AQ86 -> Balance | C121: =AO86 -> groupByColumn | D121: =E86 -> PREPAY_SMM1 | E121: =F86 -> PREPAY_TRACKING_SMM1 | F121: ratio | G121: =C86 -> PREPAY_CPR1 | H121: =D86 -> PREPAY_TRACKING_CPR1 | K121: adj | L121: adj | M121: adj | N121: mdl_smm | O121: mdl_cpr | P121: ratio | R121: x | T121: Knot | U121: adj Knot | W121: x | X121: adj x | Y121: Knot | Z121: adj Knot | AB121: x | AC121: adj x | AD121: Knot | AE121: adj Knot
A122: =K87 -> -56.682817 | B122: =AQ87/1000000000 -> 0.017345799 | C122: =AO87 -> 06:-75--50 | D122: =E87 -> 0.003305947 | E122: =Z87+AA87+AB87+AC87+AD87 -> 0.0081715667 | F122: =D122/E122 -> 0.4045671 | G122: =(1-(1-D122)^12)*100 -> 3.8957922 | H122: =(1-(1-E122)^12)*100 -> 9.3769548 | K122: =VLOOKUP(C122,$C$44:$M$62,9,0) -> 1 | L122: =VLOOKUP(C122,$C$44:$M$62,10,0) -> 1 | M122: =VLOOKUP(C122,$C$44:$M$62,11,0) -> 0.5 | N122: =Z87+AA87+AB87*K122+AC87*L122+AD87*M122*$M$118 -> 0.0058967502 | O122: =100*(1-(1-N122)^12) -> 6.8510589 | P122: =D122/N122 -> 0.56063881 | S122: =A122 -> -56.682817 | T122: =VLOOKUP(ROUNDDOWN(S122,0),'Spline Pre-Adj'!A:B,2,0) -> 1.2795489 | U122: =T122*K122 -> 1.2795489 | X122: =A122 -> -56.682817 | Y122: =VLOOKUP(ROUNDDOWN(X122,0),'Spline Pre-Adj'!F:G,2,0) -> 0.18862313 | Z122: =Y122*L122 -> 0.18862313 | AC122: =A122 -> -56.682817 | AD122: =VLOOKUP(ROUNDDOWN(AC122,0),'Spline Pre-Adj'!K:L,2,0) -> 0 | AE122: =AD122*M122 -> 0
A123: =K88 -> -32.151317 | B123: =AQ88/1000000000 -> 0.18285969 | C123: =AO88 -> 07:-50--25 | D123: =E88 -> 0.00215821 | E123: =Z88+AA88+AB88+AC88+AD88 -> 0.0085332227 | F123: =D123/E123 -> 0.25291851 | G123: =(1-(1-D123)^12)*100 -> 2.5593301 | H123: =(1-(1-E123)^12)*100 -> 9.7726932 | K123: =VLOOKUP(C123,$C$44:$M$62,9,0) -> 1 | L123: =VLOOKUP(C123,$C$44:$M$62,10,0) -> 1 | M123: =VLOOKUP(C123,$C$44:$M$62,11,0) -> 0.5 | N123: =Z88+AA88+AB88*K123+AC88*L123+AD88*M123*$M$118 -> 0.0059283592 | O123: =100*(1-(1-N123)^12) -> 6.8865943 | P123: =D123/N123 -> 0.36404845 | S123: =A123 -> -32.151317 | T123: =VLOOKUP(ROUNDDOWN(S123,0),'Spline Pre-Adj'!A:B,2,0) -> 1.287 | U123: =T123*K123 -> 1.287 | X123: =A123 -> -32.151317 | Y123: =VLOOKUP(ROUNDDOWN(X123,0),'Spline Pre-Adj'!F:G,2,0) -> 0.3115 | Z123: =Y123*L123 -> 0.3115 | AC123: =A123 -> -32.151317 | AD123: =VLOOKUP(ROUNDDOWN(AC123,0),'Spline Pre-Adj'!K:L,2,0) -> 0.43003694 | AE123: =AD123*M123 -> 0.21501847
A124: =K89 -> -22.234953 | B124: =AQ89/1000000000 -> 0.10425759 | C124: =AO89 -> 08-1:-25--20 | D124: =E89 -> 0.0082127038 | E124: =Z89+AA89+AB89+AC89+AD89 -> 0.011461064 | F124: =D124/E124 -> 0.71657428 | G124: =(1-(1-D124)^12)*100 -> 9.4220487 | H124: =(1-(1-E124)^12)*100 -> 12.918609 | J124: 1 | K124: =IF(ISNA(VLOOKUP(C124,$C$44:$M$62,9,0)),K125, VLOOKUP(C124,$C$44:$M$62,9,0)) -> 1 | L124: =IF(ISNA(VLOOKUP(C124,$C$44:$M$62,10,0)),L125, VLOOKUP(C124,$C$44:$M$62,10,0)) -> 1 | M124: =IF(ISNA(VLOOKUP(C124,$C$44:$M$62,11,0)),($M$129-$M$123)*J124/5+$M$123, VLOOKUP(C124,$C$44:$M$62,11,0)) -> 0.51 | N124: =Z89+AA89+AB89*K124+AC89*L124+AD92*M127*$M$118 -> 0.010421554 | O124: =100*(1-(1-N124)^12) -> 11.813374 | P124: =D124/N124 -> 0.78804984 | S124: =A124 -> -22.234953 | T124: =VLOOKUP(ROUNDDOWN(S124,0),'Spline Pre-Adj'!A:B,2,0) -> 1.287 | U124: =T124*K124 -> 1.287 | X124: =A124 -> -22.234953 | Y124: =VLOOKUP(ROUNDDOWN(X124,0),'Spline Pre-Adj'!F:G,2,0) -> 0.38089236 | Z124: =Y124*L124 -> 0.38089236 | AC124: =A124 -> -22.234953 | AD124: =VLOOKUP(ROUNDDOWN(AC124,0),'Spline Pre-Adj'!K:L,2,0) -> 0.79645948 | AE124: =AD124*M124 -> 0.40619434
A125: =K90 -> -17.320366 | B125: =AQ90/1000000000 -> 0.1750183 | C125: =AO90 -> 08-2:-20--15 | D125: =E90 -> 0.0094858256 | E125: =Z90+AA90+AB90+AC90+AD90 -> 0.013350099 | F125: =D125/E125 -> 0.71054346 | G125: =(1-(1-D125)^12)*100 -> 10.8075 | H125: =(1-(1-E125)^12)*100 -> 14.894639 | J125: 2 | K125: =IF(ISNA(VLOOKUP(C125,$C$44:$M$62,9,0)),K126, VLOOKUP(C125,$C$44:$M$62,9,0)) -> 1 | L125: =IF(ISNA(VLOOKUP(C125,$C$44:$M$62,10,0)),L126, VLOOKUP(C125,$C$44:$M$62,10,0)) -> 1 | M125: =IF(ISNA(VLOOKUP(C125,$C$44:$M$62,11,0)),($M$129-$M$123)*J125/5+$M$123, VLOOKUP(C125,$C$44:$M$62,11,0)) -> 0.52 | N125: =Z90+AA90+AB90*K125+AC90*L125+AD93*M128*$M$118 -> 0.01137813 | O125: =100*(1-(1-N125)^12) -> 12.830899 | P125: =D125/N125 -> 0.83368936 | S125: =A125 -> -17.320366 | T125: =VLOOKUP(ROUNDDOWN(S125,0),'Spline Pre-Adj'!A:B,2,0) -> 1.287 | U125: =T125*K125 -> 1.287 | X125: =A125 -> -17.320366 | Y125: =VLOOKUP(ROUNDDOWN(X125,0),'Spline Pre-Adj'!F:G,2,0) -> 0.43050425 | Z125: =Y125*L125 -> 0.43050425 | AC125: =A125 -> -17.320366 | AD125: =VLOOKUP(ROUNDDOWN(AC125,0),'Spline Pre-Adj'!K:L,2,0) -> 0.95362938 | AE125: =AD125*M125 -> 0.49588728
A126: =K91 -> -12.265261 | B126: =AQ91/1000000000 -> 0.28393432 | C126: =AO91 -> 08-3:-15--10 | D126: =E91 -> 0.0092966237 | E126: =Z91+AA91+AB91+AC91+AD91 -> 0.014747595 | F126: =D126/E126 -> 0.63038234 | G126: =(1-(1-D126)^12)*100 -> 10.602841 | H126: =(1-(1-E126)^12)*100 -> 16.329947 | J126: 3 | K126: =IF(ISNA(VLOOKUP(C126,$C$44:$M$62,9,0)),K127, VLOOKUP(C126,$C$44:$M$62,9,0)) -> 1 | L126: =IF(ISNA(VLOOKUP(C126,$C$44:$M$62,10,0)),L127, VLOOKUP(C126,$C$44:$M$62,10,0)) -> 1 | M126: =IF(ISNA(VLOOKUP(C126,$C$44:$M$62,11,0)),($M$129-$M$123)*J126/5+$M$123, VLOOKUP(C126,$C$44:$M$62,11,0)) -> 0.53 | N126: =Z91+AA91+AB91*K126+AC91*L126+AD94*M129*$M$118 -> 0.012979746 | O126: =100*(1-(1-N126)^12) -> 14.5105 | P126: =D126/N126 -> 0.71624081 | S126: =A126 -> -12.265261 | T126: =VLOOKUP(ROUNDDOWN(S126,0),'Spline Pre-Adj'!A:B,2,0) -> 1.287 | U126: =T126*K126 -> 1.287 | X126: =A126 -> -12.265261 | Y126: =VLOOKUP(ROUNDDOWN(X126,0),'Spline Pre-Adj'!F:G,2,0) -> 0.48396475 | Z126: =Y126*L126 -> 0.48396475 | AC126: =A126 -> -12.265261 | AD126: =VLOOKUP(ROUNDDOWN(AC126,0),'Spline Pre-Adj'!K:L,2,0) -> 1.0814264 | AE126: =AD126*M126 -> 0.57315597
A127: =K92 -> -7.3224373 | B127: =AQ92/1000000000 -> 0.42300995 | C127: =AO92 -> 08-4:-10--5 | D127: =E92 -> 0.014239488 | E127: =Z92+AA92+AB92+AC92+AD92 -> 0.016124271 | F127: =D127/E127 -> 0.88310892 | G127: =(1-(1-D127)^12)*100 -> 15.810679 | H127: =(1-(1-E127)^12)*100 -> 17.722144 | J127: 4 | K127: =IF(ISNA(VLOOKUP(C127,$C$44:$M$62,9,0)),K128, VLOOKUP(C127,$C$44:$M$62,9,0)) -> 1 | L127: =IF(ISNA(VLOOKUP(C127,$C$44:$M$62,10,0)),L128, VLOOKUP(C127,$C$44:$M$62,10,0)) -> 1 | M127: =IF(ISNA(VLOOKUP(C127,$C$44:$M$62,11,0)),($M$129-$M$123)*J127/5+$M$123, VLOOKUP(C127,$C$44:$M$62,11,0)) -> 0.54 | N127: =Z92+AA92+AB92*K127+AC92*L127+AD95*M130*$M$118 -> 0.01439368 | O127: =100*(1-(1-N127)^12) -> 15.968569 | P127: =D127/N127 -> 0.98928753 | S127: =A127 -> -7.3224373 | T127: =VLOOKUP(ROUNDDOWN(S127,0),'Spline Pre-Adj'!A:B,2,0) -> 1.287 | U127: =T127*K127 -> 1.287 | X127: =A127 -> -7.3224373 | Y127: =VLOOKUP(ROUNDDOWN(X127,0),'Spline Pre-Adj'!F:G,2,0) -> 0.54485561 | Z127: =Y127*L127 -> 0.54485561 | AC127: =A127 -> -7.3224373 | AD127: =VLOOKUP(ROUNDDOWN(AC127,0),'Spline Pre-Adj'!K:L,2,0) -> 1.1993278 | AE127: =AD127*M127 -> 0.647637
A128: =K93 -> -2.3387297 | B128: =AQ93/1000000000 -> 0.62948602 | C128: =AO93 -> 08:-25-0 | D128: =E93 -> 0.012800118 | E128: =Z93+AA93+AB93+AC93+AD93 -> 0.017461379 | F128: =D128/E128 -> 0.73305309 | G128: =(1-(1-D128)^12)*100 -> 14.323614 | H128: =(1-(1-E128)^12)*100 -> 19.053968 | K128: =IF(ISNA(VLOOKUP(C128,$C$44:$M$62,9,0)),K129, VLOOKUP(C128,$C$44:$M$62,9,0)) -> 1 | L128: =IF(ISNA(VLOOKUP(C128,$C$44:$M$62,10,0)),L129, VLOOKUP(C128,$C$44:$M$62,10,0)) -> 1 | M128: =IF(ISNA(VLOOKUP(C128,$C$44:$M$62,11,0)),M129, VLOOKUP(C128,$C$44:$M$62,11,0)) -> 0.55 | N128: =Z93+AA93+AB93*K128+AC93*L128+AD96*M131*$M$118 -> 0.016231038 | O128: =100*(1-(1-N128)^12) -> 17.829223 | P128: =D128/N128 -> 0.7886198 | S128: =A128 -> -2.3387297 | T128: =VLOOKUP(ROUNDDOWN(S128,0),'Spline Pre-Adj'!A:B,2,0) -> 1.287 | U128: =T128*K128 -> 1.287 | X128: =A128 -> -2.3387297 | Y128: =VLOOKUP(ROUNDDOWN(X128,0),'Spline Pre-Adj'!F:G,2,0) -> 0.61797137 | Z128: =Y128*L128 -> 0.61797137 | AC128: =A128 -> -2.3387297 | AD128: =VLOOKUP(ROUNDDOWN(AC128,0),'Spline Pre-Adj'!K:L,2,0) -> 1.3122379 | AE128: =AD128*M128 -> 0.72173085
A129: =K94 -> 2.6535888 | B129: =AQ94/1000000000 -> 0.8579409 | C129: =AO94 -> 09-1:0-5 | D129: =E94 -> 0.017864415 | E129: =Z94+AA94+AB94+AC94+AD94 -> 0.018757781 | F129: =D129/E129 -> 0.95237357 | G129: =(1-(1-D129)^12)*100 -> 19.451517 | H129: =(1-(1-E129)^12)*100 -> 20.32635 | J129: 1 | K129: =IF(ISNA(VLOOKUP(C129,$C$44:$M$62,9,0)),K130, VLOOKUP(C129,$C$44:$M$62,9,0)) -> 1 | L129: =IF(ISNA(VLOOKUP(C129,$C$44:$M$62,10,0)),L130, VLOOKUP(C129,$C$44:$M$62,10,0)) -> 1 | M129: =IF(ISNA(VLOOKUP(C129,$C$44:$M$62,11,0)),($M$133-$M$128)*J129/5+$M$128, VLOOKUP(C129,$C$44:$M$62,11,0)) -> 0.6 | N129: =Z94+AA94+AB94*K129+AC94*L129+AD97*M132*$M$118 -> 0.018532397 | O129: =100*(1-(1-N129)^12) -> 20.106468 | P129: =D129/N129 -> 0.96395596 | S129: =A129 -> 2.6535888 | T129: =VLOOKUP(ROUNDDOWN(S129,0),'Spline Pre-Adj'!A:B,2,0) -> 1.287 | U129: =T129*K129 -> 1.287 | X129: =A129 -> 2.6535888 | Y129: =VLOOKUP(ROUNDDOWN(X129,0),'Spline Pre-Adj'!F:G,2,0) -> 0.68848781 | Z129: =Y129*L129 -> 0.68848781 | AC129: =A129 -> 2.6535888 | AD129: =VLOOKUP(ROUNDDOWN(AC129,0),'Spline Pre-Adj'!K:L,2,0) -> 1.401848 | AE129: =AD129*M129 -> 0.84110882
A130: =K95 -> 7.6198853 | B130: =AQ95/1000000000 -> 1.1519204 | C130: =AO95 -> 09-2:5-10 | D130: =E95 -> 0.022551304 | E130: =Z95+AA95+AB95+AC95+AD95 -> 0.019913971 | F130: =D130/E130 -> 1.1324363 | G130: =(1-(1-D130)^12)*100 -> 23.94502 | H130: =(1-(1-E130)^12)*100 -> 21.445625 | J130: 2 | K130: =IF(ISNA(VLOOKUP(C130,$C$44:$M$62,9,0)),K131, VLOOKUP(C130,$C$44:$M$62,9,0)) -> 1 | L130: =IF(ISNA(VLOOKUP(C130,$C$44:$M$62,10,0)),L131, VLOOKUP(C130,$C$44:$M$62,10,0)) -> 1 | M130: =IF(ISNA(VLOOKUP(C130,$C$44:$M$62,11,0)),($M$133-$M$128)*J130/5+$M$128, VLOOKUP(C130,$C$44:$M$62,11,0)) -> 0.65 | N130: =Z95+AA95+AB95*K130+AC95*L130+AD98*M133*$M$118 -> 0.0213589 | O130: =100*(1-(1-N130)^12) -> 22.824152 | P130: =D130/N130 -> 1.055827 | S130: =A130 -> 7.6198853 | T130: =VLOOKUP(ROUNDDOWN(S130,0),'Spline Pre-Adj'!A:B,2,0) -> 1.287 | U130: =T130*K130 -> 1.287 | X130: =A130 -> 7.6198853 | Y130: =VLOOKUP(ROUNDDOWN(X130,0),'Spline Pre-Adj'!F:G,2,0) -> 0.79418177 | Z130: =Y130*L130 -> 0.79418177 | AC130: =A130 -> 7.6198853 | AD130: =VLOOKUP(ROUNDDOWN(AC130,0),'Spline Pre-Adj'!K:L,2,0) -> 1.5165579 | AE130: =AD130*M130 -> 0.98576264
A131: =K96 -> 12.702784 | B131: =AQ96/1000000000 -> 1.6116375 | C131: =AO96 -> 09-3:10-15 | D131: =E96 -> 0.019311279 | E131: =Z96+AA96+AB96+AC96+AD96 -> 0.021212658 | F131: =D131/E131 -> 0.91036584 | G131: =(1-(1-D131)^12)*100 -> 20.863987 | H131: =(1-(1-E131)^12)*100 -> 22.685646 | J131: 3 | K131: =IF(ISNA(VLOOKUP(C131,$C$44:$M$62,9,0)),K132, VLOOKUP(C131,$C$44:$M$62,9,0)) -> 1 | L131: =IF(ISNA(VLOOKUP(C131,$C$44:$M$62,10,0)),L132, VLOOKUP(C131,$C$44:$M$62,10,0)) -> 1 | M131: =IF(ISNA(VLOOKUP(C131,$C$44:$M$62,11,0)),($M$133-$M$128)*J131/5+$M$128, VLOOKUP(C131,$C$44:$M$62,11,0)) -> 0.7 | N131: =Z96+AA96+AB96*K131+AC96*L131+AD99*M134*$M$118 -> 0.024238536 | O131: =100*(1-(1-N131)^12) -> 25.505545 | P131: =D131/N131 -> 0.79671805 | S131: =A131 -> 12.702784 | T131: =VLOOKUP(ROUNDDOWN(S131,0),'Spline Pre-Adj'!A:B,2,0) -> 1.287 | U131: =T131*K131 -> 1.287 | X131: =A131 -> 12.702784 | Y131: =VLOOKUP(ROUNDDOWN(X131,0),'Spline Pre-Adj'!F:G,2,0) -> 0.91120039 | Z131: =Y131*L131 -> 0.91120039 | AC131: =A131 -> 12.702784 | AD131: =VLOOKUP(ROUNDDOWN(AC131,0),'Spline Pre-Adj'!K:L,2,0) -> 1.6382588 | AE131: =AD131*M131 -> 1.1467811
A132: =K97 -> 17.616236 | B132: =AQ97/1000000000 -> 2.4564955 | C132: =AO97 -> 09-4:15-20 | D132: =E97 -> 0.022402196 | E132: =Z97+AA97+AB97+AC97+AD97 -> 0.022950382 | F132: =D132/E132 -> 0.97611431 | G132: =(1-(1-D132)^12)*100 -> 23.805678 | H132: =(1-(1-E132)^12)*100 -> 24.316809 | J132: 4 | K132: =IF(ISNA(VLOOKUP(C132,$C$44:$M$62,9,0)),K133, VLOOKUP(C132,$C$44:$M$62,9,0)) -> 1 | L132: =IF(ISNA(VLOOKUP(C132,$C$44:$M$62,10,0)),L133, VLOOKUP(C132,$C$44:$M$62,10,0)) -> 1 | M132: =IF(ISNA(VLOOKUP(C132,$C$44:$M$62,11,0)),($M$133-$M$128)*J132/5+$M$128, VLOOKUP(C132,$C$44:$M$62,11,0)) -> 0.75 | N132: =Z97+AA97+AB97*K132+AC97*L132+AD100*M135*$M$118 -> 0.027516754 | O132: =100*(1-(1-N132)^12) -> 28.45397 | P132: =D132/N132 -> 0.81412933 | X132: =A132 -> 17.616236 | Y132: =VLOOKUP(ROUNDDOWN(X132,0),'Spline Pre-Adj'!F:G,2,0) -> 1.044224 | Z132: =Y132*L132 -> 1.044224 | AC132: =A132 -> 17.616236 | AD132: =VLOOKUP(ROUNDDOWN(AC132,0),'Spline Pre-Adj'!K:L,2,0) -> 1.77123 | AE132: =AD132*M132 -> 1.3284225
A133: =K98 -> 22.590179 | B133: =AQ98/1000000000 -> 3.3771238 | C133: =AO98 -> 09:0-25 | D133: =E98 -> 0.030307589 | E133: =Z98+AA98+AB98+AC98+AD98 -> 0.024997435 | F133: =D133/E133 -> 1.212428 | G133: =(1-(1-D133)^12)*100 -> 30.879326 | H133: =(1-(1-E133)^12)*100 -> 26.197835 | K133: =IF(ISNA(VLOOKUP(C133,$C$44:$M$62,9,0)),K134, VLOOKUP(C133,$C$44:$M$62,9,0)) -> 1 | L133: =IF(ISNA(VLOOKUP(C133,$C$44:$M$62,10,0)),L134, VLOOKUP(C133,$C$44:$M$62,10,0)) -> 1 | M133: =IF(ISNA(VLOOKUP(C133,$C$44:$M$62,11,0)),M134, VLOOKUP(C133,$C$44:$M$62,11,0)) -> 0.8 | N133: =Z98+AA98+AB98*K133+AC98*L133+AD101*M136*$M$118 -> 0.030701071 | O133: =100*(1-(1-N133)^12) -> 31.21515 | P133: =D133/N133 -> 0.98718343 | X133: =A133 -> 22.590179 | Y133: =VLOOKUP(ROUNDDOWN(X133,0),'Spline Pre-Adj'!F:G,2,0) -> 1.2015373 | Z133: =Y133*L133 -> 1.2015373 | AC133: =A133 -> 22.590179 | AD133: =VLOOKUP(ROUNDDOWN(AC133,0),'Spline Pre-Adj'!K:L,2,0) -> 1.9188346 | AE133: =AD133*M133 -> 1.5350677
A134: =K99 -> 27.547268 | B134: =AQ99/1000000000 -> 3.9548243 | C134: =AO99 -> 10-1:25-30 | D134: =E99 -> 0.035264934 | E134: =Z99+AA99+AB99+AC99+AD99 -> 0.026903969 | F134: =D134/E134 -> 1.3107707 | G134: =(1-(1-D134)^12)*100 -> 35.002482 | H134: =(1-(1-E134)^12)*100 -> 27.911097 | J134: 1 | K134: =IF(ISNA(VLOOKUP(C134,$C$44:$M$62,9,0)),K135, VLOOKUP(C134,$C$44:$M$62,9,0)) -> 1 | L134: =IF(ISNA(VLOOKUP(C134,$C$44:$M$62,10,0)),L135, VLOOKUP(C134,$C$44:$M$62,10,0)) -> 1 | M134: =IF(ISNA(VLOOKUP(C134,$C$44:$M$62,11,0)),($M$138-$M$133)*J134/5+$M$133, VLOOKUP(C134,$C$44:$M$62,11,0)) -> 0.85 | N134: =Z99+AA99+AB99*K134+AC99*L134+AD102*M137*$M$118 -> 0.0084129988 | O134: =100*(1-(1-N134)^12) -> 9.6413155 | P134: =D134/N134 -> 4.1917199 | X134: =A134 -> 27.547268 | Y134: =VLOOKUP(ROUNDDOWN(X134,0),'Spline Pre-Adj'!F:G,2,0) -> 1.3914246 | Z134: =Y134*L134 -> 1.3914246 | AC134: =A134 -> 27.547268 | AD134: =VLOOKUP(ROUNDDOWN(AC134,0),'Spline Pre-Adj'!K:L,2,0) -> 2.0788177 | AE134: =AD134*M134 -> 1.7669951
A135: =K100 -> 32.542028 | B135: =AQ100/1000000000 -> 4.3907244 | C135: =AO100 -> 10-2:30-35 | D135: =E100 -> 0.038182049 | E135: =Z100+AA100+AB100+AC100+AD100 -> 0.029083318 | F135: =D135/E135 -> 1.3128505 | G135: =(1-(1-D135)^12)*100 -> 37.322085 | H135: =(1-(1-E135)^12)*100 -> 29.824817 | J135: 2 | K135: =IF(ISNA(VLOOKUP(C135,$C$44:$M$62,9,0)),K136, VLOOKUP(C135,$C$44:$M$62,9,0)) -> 1 | L135: =IF(ISNA(VLOOKUP(C135,$C$44:$M$62,10,0)),L136, VLOOKUP(C135,$C$44:$M$62,10,0)) -> 1 | M135: =IF(ISNA(VLOOKUP(C135,$C$44:$M$62,11,0)),($M$138-$M$133)*2/5+$M$133, VLOOKUP(C135,$C$44:$M$62,11,0)) -> 0.9 | N135: =Z100+AA100+AB100*K135+AC100*L135+AD103*M138*$M$118 -> 0.0034875787 | O135: =100*(1-(1-N135)^12) -> 4.1057433 | P135: =D135/N135 -> 10.948011 | X135: =A135 -> 32.542028 | Y135: =VLOOKUP(ROUNDDOWN(X135,0),'Spline Pre-Adj'!F:G,2,0) -> 1.6233323 | Z135: =Y135*L135 -> 1.6233323 | AC135: =A135 -> 32.542028 | AD135: =VLOOKUP(ROUNDDOWN(AC135,0),'Spline Pre-Adj'!K:L,2,0) -> 2.2487417 | AE135: =AD135*M135 -> 2.0238675
A136: =K101 -> 37.486494 | B136: =AQ101/1000000000 -> 4.437571 | C136: =AO101 -> 10-3:35-40 | D136: =E101 -> 0.040370339 | E136: =Z101+AA101+AB101+AC101+AD101 -> 0.03093887 | F136: =D136/E136 -> 1.3048421 | G136: =(1-(1-D136)^12)*100 -> 39.012061 | H136: =(1-(1-E136)^12)*100 -> 31.417378 | J136: 3 | K136: =IF(ISNA(VLOOKUP(C136,$C$44:$M$62,9,0)),K137, VLOOKUP(C136,$C$44:$M$62,9,0)) -> 1 | L136: =IF(ISNA(VLOOKUP(C136,$C$44:$M$62,10,0)),L137, VLOOKUP(C136,$C$44:$M$62,10,0)) -> 1 | M136: =IF(ISNA(VLOOKUP(C136,$C$44:$M$62,11,0)),($M$138-$M$133)*3/5+$M$133, VLOOKUP(C136,$C$44:$M$62,11,0)) -> 0.95 | N136: =Z101+AA101+AB101*K136+AC101*L136+AD104*M139*$M$118 -> 0.003542605 | O136: =100*(1-(1-N136)^12) -> 4.169266 | P136: =D136/N136 -> 11.395665 | X136: =A136 -> 37.486494 | Y136: =VLOOKUP(ROUNDDOWN(X136,0),'Spline Pre-Adj'!F:G,2,0) -> 1.8953738 | Z136: =Y136*L136 -> 1.8953738 | AC136: =A136 -> 37.486494 | AD136: =VLOOKUP(ROUNDDOWN(AC136,0),'Spline Pre-Adj'!K:L,2,0) -> 2.4264029 | AE136: =AD136*M136 -> 2.3050828
A137: =K102 -> 42.421648 | B137: =AQ102/1000000000 -> 4.22655 | C137: =AO102 -> 10-4:40-45 | D137: =E102 -> 0.044694143 | E137: =Z102+AA102+AB102+AC102+AD102 -> 0.033263128 | F137: =D137/E137 -> 1.3436542 | G137: =(1-(1-D137)^12)*100 -> 42.22908 | H137: =(1-(1-E137)^12)*100 -> 33.365461 | J137: 4 | K137: =IF(ISNA(VLOOKUP(C137,$C$44:$M$62,9,0)),K138, VLOOKUP(C137,$C$44:$M$62,9,0)) -> 0 | L137: =IF(ISNA(VLOOKUP(C137,$C$44:$M$62,10,0)),L138, VLOOKUP(C137,$C$44:$M$62,10,0)) -> 0 | M137: =IF(ISNA(VLOOKUP(C137,$C$44:$M$62,11,0)),($M$138-$M$133)*4/5+$M$133, VLOOKUP(C137,$C$44:$M$62,11,0)) -> 0.16 | N137: =Z102+AA102+AB102*K137+AC102*L137+AD105*M140*$M$118 -> 0.00042499212 | O137: =100*(1-(1-N137)^12) -> 0.50880016 | P137: =D137/N137 -> 105.16464 | X137: =A137 -> 42.421648 | Y137: =VLOOKUP(ROUNDDOWN(X137,0),'Spline Pre-Adj'!F:G,2,0) -> 2.1927888 | Z137: =Y137*L137 -> 0 | AC137: =A137 -> 42.421648 | AD137: =VLOOKUP(ROUNDDOWN(AC137,0),'Spline Pre-Adj'!K:L,2,0) -> 2.609598 | AE137: =AD137*M137 -> 0.41753568
A138: =K103 -> 47.512004 | B138: =AQ103/1000000000 -> 3.970184 | C138: =AO103 -> 10:25-50 | D138: =E103 -> 0.044909905 | E138: =Z103+AA103+AB103+AC103+AD103 -> 0.035727845 | F138: =D138/E138 -> 1.2570001 | G138: =(1-(1-D138)^12)*100 -> 42.385461 | H138: =(1-(1-E138)^12)*100 -> 35.375751 | K138: =IF(ISNA(VLOOKUP(C138,$C$44:$M$62,9,0)),K139, VLOOKUP(C138,$C$44:$M$62,9,0)) -> 0 | L138: =IF(ISNA(VLOOKUP(C138,$C$44:$M$62,10,0)),L139, VLOOKUP(C138,$C$44:$M$62,10,0)) -> 0 | M138: =IF(ISNA(VLOOKUP(C138,$C$44:$M$62,11,0)),M139, VLOOKUP(C138,$C$44:$M$62,11,0)) -> 0 | N138: =Z103+AA103+AB103*K138+AC103*L138+AD106*M141*$M$118 -> 0.00043177871 | O138: =100*(1-(1-N138)^12) -> 0.51690576 | P138: =D138/N138 -> 104.01139 | X138: =A138 -> 47.512004 | Y138: =VLOOKUP(ROUNDDOWN(X138,0),'Spline Pre-Adj'!F:G,2,0) -> 2.5005892 | Z138: =Y138*L138 -> 0 | AC138: =A138 -> 47.512004 | AD138: =VLOOKUP(ROUNDDOWN(AC138,0),'Spline Pre-Adj'!K:L,2,0) -> 2.7961235 | AE138: =AD138*M138 -> 0
A139: =K104 -> 52.525414 | B139: =AQ104/1000000000 -> 3.3368649 | C139: =AO104 -> 11-1:50-55 | D139: =E104 -> 0.049977761 | E139: =Z104+AA104+AB104+AC104+AD104 -> 0.036779866 | F139: =D139/E139 -> 1.3588348 | G139: =(1-(1-D139)^12)*100 -> 45.94881 | H139: =(1-(1-E139)^12)*100 -> 36.216753 | K139: =IF(ISNA(VLOOKUP(C139,$C$44:$M$62,9,0)),K140, VLOOKUP(C139,$C$44:$M$62,9,0)) -> 0 | L139: =IF(ISNA(VLOOKUP(C139,$C$44:$M$62,10,0)),L140, VLOOKUP(C139,$C$44:$M$62,10,0)) -> 0 | M139: =IF(ISNA(VLOOKUP(C139,$C$44:$M$62,11,0)),M140, VLOOKUP(C139,$C$44:$M$62,11,0)) -> 0 | N139: =Z104+AA104+AB104*K139+AC104*L139+AD107*M142*$M$118 -> 0.00044259826 | O139: =100*(1-(1-N139)^12) -> 0.52982692 | P139: =D139/N139 -> 112.91902 | X139: =A139 -> 52.525414 | Y139: =VLOOKUP(ROUNDDOWN(X139,0),'Spline Pre-Adj'!F:G,2,0) -> 2.8037869 | Z139: =Y139*L139 -> 0 | AC139: =A139 -> 52.525414 | AD139: =VLOOKUP(ROUNDDOWN(AC139,0),'Spline Pre-Adj'!K:L,2,0) -> 2.983776 | AE139: =AD139*M139 -> 0
A140: =K105 -> 57.496639 | B140: =AQ105/1000000000 -> 3.2431989 | C140: =AO105 -> 11-2:55-60 | D140: =E105 -> 0.050875245 | E140: =Z105+AA105+AB105+AC105+AD105 -> 0.038632236 | F140: =D140/E140 -> 1.3169117 | G140: =(1-(1-D140)^12)*100 -> 46.558381 | H140: =(1-(1-E140)^12)*100 -> 37.673223 | K140: =IF(ISNA(VLOOKUP(C140,$C$44:$M$62,9,0)),K141, VLOOKUP(C140,$C$44:$M$62,9,0)) -> 0 | L140: =IF(ISNA(VLOOKUP(C140,$C$44:$M$62,10,0)),L141, VLOOKUP(C140,$C$44:$M$62,10,0)) -> 0 | M140: =IF(ISNA(VLOOKUP(C140,$C$44:$M$62,11,0)),M141, VLOOKUP(C140,$C$44:$M$62,11,0)) -> 0 | N140: =Z105+AA105+AB105*K140+AC105*L140+AD108*M143*$M$118 -> 0.00045046061 | O140: =100*(1-(1-N140)^12) -> 0.5392155 | P140: =D140/N140 -> 112.9405 | X140: =A140 -> 57.496639 | Y140: =VLOOKUP(ROUNDDOWN(X140,0),'Spline Pre-Adj'!F:G,2,0) -> 3.092616 | Z140: =Y140*L140 -> 0 | AC140: =A140 -> 57.496639 | AD140: =VLOOKUP(ROUNDDOWN(AC140,0),'Spline Pre-Adj'!K:L,2,0) -> 3.1703521 | AE140: =AD140*M140 -> 0
A141: =K106 -> 62.446297 | B141: =AQ106/1000000000 -> 3.1971192 | C141: =AO106 -> 11-3:60-65 | D141: =E106 -> 0.053598413 | E141: =Z106+AA106+AB106+AC106+AD106 -> 0.040426805 | F141: =D141/E141 -> 1.3258137 | G141: =(1-(1-D141)^12)*100 -> 48.369596 | H141: =(1-(1-E141)^12)*100 -> 39.05511 | K141: =IF(ISNA(VLOOKUP(C141,$C$44:$M$62,9,0)),K142, VLOOKUP(C141,$C$44:$M$62,9,0)) -> 0 | L141: =IF(ISNA(VLOOKUP(C141,$C$44:$M$62,10,0)),L142, VLOOKUP(C141,$C$44:$M$62,10,0)) -> 0 | M141: =IF(ISNA(VLOOKUP(C141,$C$44:$M$62,11,0)),M142, VLOOKUP(C141,$C$44:$M$62,11,0)) -> 0 | N141: =Z106+AA106+AB106*K141+AC106*L141+AD109*M144*$M$118 -> 0.00045901843 | O141: =100*(1-(1-N141)^12) -> 0.54943364 | P141: =D141/N141 -> 116.76745 | X141: =A141 -> 62.446297 | Y141: =VLOOKUP(ROUNDDOWN(X141,0),'Spline Pre-Adj'!F:G,2,0) -> 3.3799458 | Z141: =Y141*L141 -> 0 | AC141: =A141 -> 62.446297 | AD141: =VLOOKUP(ROUNDDOWN(AC141,0),'Spline Pre-Adj'!K:L,2,0) -> 3.3536482 | AE141: =AD141*M141 -> 0
