Workbook

Sheet Distribution of data
A1: count() | B1: bucket | I1: count() | J1: tag | K1: loansize | L1: fico | M1: lien | N1: invest | O1: cltv | P1: state | Q1: asOf | R1: Ticker | S1: Orig Date | T1: wala | U1: TPO
A2: 1096925 | B2: 'Done' | C2: <= 417 >= 740 no lien no invest cltv <= 80 | I2: =SUM(Baseline!AR3:AR17) -> 1313593 | J2: Baseline | K2: (175,417] | L2: [740,860] | M2: no | N2: no | O2: (0,80] | P2: not in ('NY','PR') | Q2: [20120101,20130401] | R2: All 4 | S2: post HARP | T2: [12,24) | U2: CORRES, CASHWINDOW
A3: 466351 | B3: 'FICO'
A4: 230769 | B4: '2nd Lien'
A5: 144409 | B5: 'INV'
A6: 124596 | B6: 'CLTV'
A7: 57525 | B7: 'Jumbo'
A8: 2 | B8: 'Not Done'
A10: =SUM(A2:A8) -> 2120577 | B10: total

Sheet Actual
A1: WALA [12,24) | C1: BROKER
A2: modelId | B2: SFACTOR_PREPAY_TRACKING_CPR | C2: PREPAY_CPR1 | D2: PREPAY_TRACKING_CPR1 | E2: PREPAY_SMM1 | F2: PREPAY_TRACKING_SMM1 | G2: PCT_LOANTYPE | H2: _ORIGNOTERATE | I2: _ZEROSATO | J2: _SATO | K2: _REFI_INCENTIVE_Fixed | L2: _Fixed_cost | M2: _LOANAGE | N2: _LTV | O2: _CLTV | P2: _AVG_LOANSIZE_SCHAMBALANCE | Q2: _WACLS | R2: _FICO | S2: PCT_ISSECONDLIEN | T2: _OrigCombLTV | U2: PCT_SVC | V2: PCT_TPO | W2: PCT_GEO | X2: PCT_LOANPURPOSE | Y2: PCT_OCC | Z2: curtailsmm | AA2: defaultsmm | AB2: toverSmm | AC2: cashoutSmm | AD2: refiSmm | AE2: cumHPA | AF2: cumHPA05Pct | AG2: cumHPA15Pct | AH2: cumHPA20Pct | AI2: cumHPA25Pct | AJ2: cumHPA30Pct | AK2: cumHPA35Pct | AL2: cumHPA40Pct | AM2: adjtoverSmm | AN2: adjRefiSmm | AO2: groupByColumn | AP2: curve | AQ2: Balance | AR2: LoanCount | AS2: PCT_BROKER | AT2: PCT_CORRES | AU2: PCT_NonRETAIL | AV2: PCT_RETAIL | AW2: PCT_CashWindow | AX2: PCT_NonCashWindow
A3: 4.3 | B3: 0.99354299 | C3: 3.4433222 | D3: 7.4790735 | E3: 0.0029157422 | F3: 0.0064570079 | G3: 0 | H3: 3.9622665 | I3: 4.1506701 | J3: -55.102824 | K3: -57.170377 | L3: 18.591369 | M3: 15.604608 | N3: 77.726934 | O3: 75.492093 | P3: 267072.12 | Q3: 193404.05 | R3: 774.87434 | S3: 0 | T3: 0 | U3: 0.089424414 | V3: 0 | W3: 0 | X3: 0.58543282 | Y3: 0 | Z3: 0.00067107958 | AA3: 7.5421688e-05 | AB3: 0.0025087098 | AC3: 2.9446125e-08 | AD3: 0.0032017562 | AE3: -0.025268185 | AF3: 0.99001879 | AG3: 0.99720024 | AH3: 1 | AI3: 1 | AJ3: 1 | AK3: 1 | AL3: 1 | AM3: 0 | AN3: 0 | AO3: 06:-75--50 | AP3: =-75--50 -> -25 | AQ3: 22048061 | AR3: 114 | AS3: 100 | AT3: 0 | AU3: 100 | AV3: 0 | AW3: 0 | AX3: 0
A4: 4.3 | B4: 0.9934404 | C4: 2.6756426 | D4: 7.5936475 | E4: 0.0022575225 | F4: 0.0065595963 | G4: 0 | H4: 3.91998 | I4: 4.1424648 | J4: -57.659948 | K4: -32.594271 | L4: 14.98906 | M4: 15.424298 | N4: 73.798811 | O4: 72.801415 | P4: 293064.03 | Q4: 263371.78 | R4: 784.82056 | S4: 0 | T4: 0 | U4: 0.08318706 | V4: 0 | W4: 0 | X4: 0.63466923 | Y4: 0 | Z4: 0.00042337918 | AA4: 5.4947755e-05 | AB4: 0.0024369602 | AC4: 1.9932865e-08 | AD4: 0.0036442753 | AE4: -0.020683738 | AF4: 0.98301074 | AG4: 0.99723916 | AH4: 1 | AI4: 1 | AJ4: 1 | AK4: 1 | AL4: 1 | AM4: 0 | AN4: 0 | AO4: 07:-50--25 | AP4: =-50--25 -> -25 | AQ4: 2.4835959e+08 | AR4: 943 | AS4: 100 | AT4: 0 | AU4: 100 | AV4: 0 | AW4: 0 | AX4: 0
A5: 4.3 | B5: 0.98810675 | C5: 14.515411 | D5: 13.374372 | E5: 0.012984471 | F5: 0.01189325 | G5: 0 | H5: 4.0994748 | I5: 4.1233851 | J5: -40.112546 | K5: -8.5065994 | L5: 14.517274 | M5: 15.824699 | N5: 72.180941 | O5: 71.16733 | P5: 297035.51 | Q5: 273997.1 | R5: 782.74924 | S5: 0 | T5: 0 | U5: 0.16198165 | V5: 0 | W5: 0 | X5: 0.71326488 | Y5: 0 | Z5: 0.00037641719 | AA5: 6.1641507e-05 | AB5: 0.0025045364 | AC5: 1.1985382e-07 | AD5: 0.0089505203 | AE5: -0.015473879 | AF5: 0.95973186 | AG5: 0.99363686 | AH5: 0.99969863 | AI5: 1 | AJ5: 1 | AK5: 1 | AL5: 1 | AM5: 0 | AN5: 0 | AO5: 08:-25-0 | AP5: =-25-0 -> -25 | AQ5: 2.0251126e+09 | AR5: 7391 | AS5: 100 | AT5: 0 | AU5: 100 | AV5: 0 | AW5: 0 | AX5: 0
A6: 4.3 | B6: 0.98304592 | C6: 27.048998 | D6: 18.551023 | E6: 0.025939486 | F6: 0.016954085 | G6: 0 | H6: 4.1521468 | I6: 4.0348346 | J6: -30.391947 | K6: 15.744335 | L6: 14.364007 | M6: 15.776989 | N6: 68.038082 | O6: 65.942075 | P6: 298325.63 | Q6: 277825.05 | R6: 783.61193 | S6: 0 | T6: 0 | U6: 0.23317829 | V6: 0 | W6: 0 | X6: 0.8177067 | Y6: 0 | Z6: 0.00036976726 | AA6: 5.8793704e-05 | AB6: 0.0027739843 | AC6: 3.0262744e-06 | AD6: 0.013748499 | AE6: 0.0038239737 | AF6: 0.83514428 | AG6: 0.95178217 | AH6: 0.99513288 | AI6: 0.99904793 | AJ6: 1 | AK6: 1 | AL6: 1 | AM6: 0 | AN6: 0 | AO6: 09:0-25 | AP6: 0-25 | AQ6: 1.0989092e+10 | AR6: 39554 | AS6: 100 | AT6: 0 | AU6: 100 | AV6: 0 | AW6: 0 | AX6: 0
A7: 4.3 | B7: 0.97553016 | C7: 39.511307 | D7: 25.717173 | E7: 0.041027433 | F7: 0.024469838 | G7: 0 | H7: 4.1700427 | I7: 3.886904 | J7: -26.925548 | K7: 37.409975 | L7: 13.639154 | M7: 16.149073 | N7: 64.844231 | O7: 61.095981 | P7: 311881.57 | Q7: 292677.63 | R7: 783.83427 | S7: 0 | T7: 0 | U7: 0.2676584 | V7: 0 | W7: 0 | X7: 0.83998291 | Y7: 0 | Z7: 0.00036821089 | AA7: 5.7737956e-05 | AB7: 0.0030840132 | AC7: 1.0551737e-05 | AD7: 0.020949309 | AE7: 0.034424605 | AF7: 0.65979439 | AG7: 0.8965255 | AH7: 0.98913006 | AI7: 0.99836628 | AJ7: 1 | AK7: 1 | AL7: 1 | AM7: 0 | AN7: 0 | AO7: 10:25-50 | AP7: 25-50 | AQ7: 2.1924188e+10 | AR7: 74909 | AS7: 100 | AT7: 0 | AU7: 100 | AV7: 0 | AW7: 0 | AX7: 0
A8: 4.3 | B8: 0.96749363 | C8: 47.215946 | D8: 32.736821 | E8: 0.051853975 | F8: 0.032506367 | G8: 0 | H8: 4.4546713 | I8: 3.8939111 | J8: -17.636655 | K8: 62.476491 | L8: 14.232973 | M8: 17.622334 | N8: 67.200221 | O8: 63.714954 | P8: 300315.56 | Q8: 280510.29 | R8: 782.16221 | S8: 0 | T8: 0 | U8: 0.24509649 | V8: 0 | W8: 0 | X8: 0.76375298 | Y8: 0 | Z8: 0.00037146776 | AA8: 8.9448587e-05 | AB8: 0.0032444203 | AC8: 9.1333761e-06 | AD8: 0.028791883 | AE8: 0.02481458 | AF8: 0.68593791 | AG8: 0.94531389 | AH8: 0.99334833 | AI8: 0.99910374 | AJ8: 1 | AK8: 1 | AL8: 1 | AM8: 0 | AN8: 0 | AO8: 11:50-75 | AP8: 50-75 | AQ8: 1.7351525e+10 | AR8: 61857 | AS8: 100 | AT8: 0 | AU8: 100 | AV8: 0 | AW8: 0 | AX8: 0
A9: 4.3 | B9: 0.9616878 | C9: 45.770827 | D9: 37.423788 | E9: 0.049717463 | F9: 0.038312201 | G9: 0 | H9: 4.6792015 | I9: 3.8981509 | J9: -11.53115 | K9: 85.668971 | L9: 14.263814 | M9: 17.602014 | N9: 66.442911 | O9: 62.693089 | P9: 299859.64 | Q9: 279920.92 | R9: 780.85805 | S9: 0 | T9: 0 | U9: 0.28399373 | V9: 0 | W9: 0 | X9: 0.69290849 | Y9: 0 | Z9: 0.00037185965 | AA9: 0.00010535088 | AB9: 0.0033641167 | AC9: 1.8856207e-05 | AD9: 0.034452003 | AE9: 0.028319628 | AF9: 0.62658474 | AG9: 0.94565646 | AH9: 0.98872447 | AI9: 0.99818447 | AJ9: 1 | AK9: 1 | AL9: 1 | AM9: 0 | AN9: 0 | AO9: 12:75-100 | AP9: 75-100 | AQ9: 1.1137494e+10 | AR9: 39788 | AS9: 100 | AT9: 0 | AU9: 100 | AV9: 0 | AW9: 0 | AX9: 0
A10: 4.3 | B10: 0.95610776 | C10: 45.909203 | D10: 41.644457 | E10: 0.049919769 | F10: 0.04389224 | G10: 0 | H10: 4.8190174 | I10: 3.7827978 | J10: -7.033373 | K10: 111.76843 | L10: 14.851525 | M10: 18.573443 | N10: 70.047731 | O10: 64.517258 | P10: 288600.21 | Q10: 268853.2 | R10: 779.33271 | S10: 0 | T10: 0 | U10: 0.29515185 | V10: 0 | W10: 0 | X10: 0.61609329 | Y10: 0 | Z10: 0.00037279538 | AA10: 0.00014722462 | AB10: 0.0036961846 | AC10: 3.6742999e-05 | AD10: 0.039639278 | AE10: 0.052894394 | AF10: 0.44589189 | AG10: 0.9189403 | AH10: 0.98503593 | AI10: 0.99699297 | AJ10: 1 | AK10: 1 | AL10: 1 | AM10: 0 | AN10: 0 | AO10: 13:100-125 | AP10: 100-125 | AQ10: 5.7252288e+09 | AR10: 21295 | AS10: 100 | AT10: 0 | AU10: 100 | AV10: 0 | AW10: 0 | AX10: 0
A11: 4.3 | B11: 0.95139204 | C11: 46.476872 | D11: 45.006143 | E11: 0.050754696 | F11: 0.048607957 | G11: 0 | H11: 4.8761355 | I11: 3.6738705 | J11: -6.547352 | K11: 134.37324 | L11: 14.345575 | M11: 20.090596 | N11: 70.80133 | O11: 63.193322 | P11: 297212.06 | Q11: 278337.2 | R11: 778.25756 | S11: 0 | T11: 0 | U11: 0.29020541 | V11: 0 | W11: 0 | X11: 0.61283836 | Y11: 0 | Z11: 0.00037411096 | AA11: 0.00016841151 | AB11: 0.0036857396 | AC11: 8.5910415e-05 | AD11: 0.04429377 | AE11: 0.085370719 | AF11: 0.28253617 | AG11: 0.87003254 | AH11: 0.9662038 | AI11: 0.99610031 | AJ11: 1 | AK11: 1 | AL11: 1 | AM11: 0 | AN11: 0 | AO11: 14:125-150 | AP11: 125-150 | AQ11: 2.6208231e+09 | AR11: 9416 | AS11: 100 | AT11: 0 | AU11: 100 | AV11: 0 | AW11: 0 | AX11: 0
A12: 4.3 | B12: 0.94664668 | C12: 44.242836 | D12: 48.208917 | E12: 0.047514463 | F12: 0.05335332 | G12: 0 | H12: 5.0228991 | I12: 3.6711342 | J12: 6.8476451 | K12: 160.18516 | L12: 14.050936 | M12: 20.067577 | N12: 78.702585 | O12: 68.818309 | P12: 302497.45 | Q12: 284181.94 | R12: 777.14943 | S12: 0 | T12: 0 | U12: 0.23643044 | V12: 0 | W12: 0 | X12: 0.52204473 | Y12: 0 | Z12: 0.00037364661 | AA12: 0.00024360029 | AB12: 0.0038902341 | AC12: 0.00013030684 | AD12: 0.048715516 | AE12: 0.10704924 | AF12: 0.15712908 | AG12: 0.78788788 | AH12: 0.94414223 | AI12: 0.9898934 | AJ12: 1 | AK12: 1 | AL12: 1 | AM12: 0 | AN12: 0 | AO12: 15:150-175 | AP12: 150-175 | AQ12: 4.4019782e+08 | AR12: 1549 | AS12: 100 | AT12: 0 | AU12: 100 | AV12: 0 | AW12: 0 | AX12: 0
A13: 4.3 | B13: 0.94180872 | C13: 53.130436 | D13: 51.297364 | E13: 0.061197489 | F13: 0.058191283 | G13: 0 | H13: 5.046812 | I13: 3.6581714 | J13: 6.4300909 | K13: 183.9435 | L13: 13.884685 | M13: 20.486383 | N13: 85.498759 | O13: 72.57064 | P13: 305684.75 | Q13: 287591.9 | R13: 777.65331 | S13: 0 | T13: 0 | U13: 0.23252351 | V13: 0 | W13: 0 | X13: 0.40200049 | Y13: 0 | Z13: 0.00037498084 | AA13: 0.00032210145 | AB13: 0.0041021819 | AC13: 0.00035720284 | AD13: 0.0530348 | AE13: 0.13942807 | AF13: 0.035231054 | AG13: 0.62060278 | AH13: 0.85157551 | AI13: 0.98674363 | AJ13: 1 | AK13: 1 | AL13: 1 | AM13: 0 | AN13: 0 | AO13: 16:175-200 | AP13: 175-200 | AQ13: 96630878 | AR13: 336 | AS13: 100 | AT13: 0 | AU13: 100 | AV13: 0 | AW13: 0 | AX13: 0
A14: 4.3 | B14: 0.9407424 | C14: 47.495831 | D14: 51.954953 | E14: 0.052273955 | F14: 0.059257599 | G14: 0 | H14: 5.1962175 | I14: 3.6487088 | J14: 17.28872 | K14: 209.55229 | L14: 14.52586 | M14: 20.792683 | N14: 90.120235 | O14: 75.17575 | P14: 294450.4 | Q14: 274910.83 | R14: 775.39517 | S14: 0 | T14: 0 | U14: 0.083777428 | V14: 0 | W14: 0 | X14: 0.28831945 | Y14: 0 | Z14: 0.00037198764 | AA14: 0.00037985115 | AB14: 0.0043843365 | AC14: 0.0005945363 | AD14: 0.053526869 | AE14: 0.16459065 | AF14: 0 | AG14: 0.46714353 | AH14: 0.67606014 | AI14: 0.98161705 | AJ14: 1 | AK14: 1 | AL14: 1 | AM14: 0 | AN14: 0 | AO14: 17:200-225 | AP14: 200-225 | AQ14: 20893223 | AR14: 76 | AS14: 100 | AT14: 0 | AU14: 100 | AV14: 0 | AW14: 0 | AX14: 0
A15: 4.3 | B15: 0.94906051 | C15: 46.592588 | D15: 46.601772 | E15: 0.050925887 | F15: 0.050939488 | G15: 0 | H15: 5.321533 | I15: 3.665408 | J15: 30.474314 | K15: 232.6404 | L15: 17.927401 | M15: 20.850682 | N15: 92.695715 | O15: 75.691523 | P15: 246276.83 | Q15: 222772.75 | R15: 788.41159 | S15: 0 | T15: 0 | U15: 0 | V15: 0 | W15: 0 | X15: 0.34002479 | Y15: 0 | Z15: 0.00040339218 | AA15: 4.2794964e-05 | AB15: 0.004240869 | AC15: 0.00068165279 | AD15: 0.045570761 | AE15: 0.17333363 | AF15: 0 | AG15: 0.29883154 | AH15: 0.63135198 | AI15: 0.95367429 | AJ15: 1 | AK15: 1 | AL15: 1 | AM15: 0 | AN15: 0 | AO15: 18:225-250 | AP15: 225-250 | AQ15: 3787136.8 | AR15: 17 | AS15: 100 | AT15: 0 | AU15: 100 | AV15: 0 | AW15: 0 | AX15: 0
A19: WALA [12,24) | C19: CORRES
A20: modelId | B20: SFACTOR_PREPAY_TRACKING_CPR | C20: PREPAY_CPR1 | D20: PREPAY_TRACKING_CPR1 | E20: PREPAY_SMM1 | F20: PREPAY_TRACKING_SMM1 | G20: PCT_LOANTYPE | H20: _ORIGNOTERATE | I20: _ZEROSATO | J20: _SATO | K20: _REFI_INCENTIVE_Fixed | L20: _Fixed_cost | M20: _LOANAGE | N20: _LTV | O20: _CLTV | P20: _AVG_LOANSIZE_SCHAMBALANCE | Q20: _WACLS | R20: _FICO | S20: PCT_ISSECONDLIEN | T20: _OrigCombLTV | U20: PCT_SVC | V20: PCT_TPO | W20: PCT_GEO | X20: PCT_LOANPURPOSE | Y20: PCT_OCC | Z20: curtailsmm | AA20: defaultsmm | AB20: toverSmm | AC20: cashoutSmm | AD20: refiSmm | AE20: cumHPA | AF20: cumHPA05Pct | AG20: cumHPA15Pct | AH20: cumHPA20Pct | AI20: cumHPA25Pct | AJ20: cumHPA30Pct | AK20: cumHPA35Pct | AL20: cumHPA40Pct | AM20: adjtoverSmm | AN20: adjRefiSmm | AO20: groupByColumn | AP20: curve | AQ20: Balance | AR20: LoanCount | AS20: PCT_BROKER | AT20: PCT_CORRES | AU20: PCT_NonRETAIL | AV20: PCT_RETAIL | AW20: PCT_CashWindow | AX20: PCT_NonCashWindow
A21: 4.3 | B21: 0.9957006 | C21: 1.2100205e-05 | D21: 5.0390158 | E21: 1.0083505e-08 | F21: 0.0042994036 | G21: 0 | H21: 4.0264725 | I21: 4.1375376 | J21: -42.855524 | K21: -108.8538 | L21: 20.131193 | M21: 15.604363 | N21: 76.15288 | O21: 75.620604 | P21: 198516.22 | Q21: 198343.74 | R21: 760.45864 | S21: 0 | T21: 0 | U21: 0 | V21: 0 | W21: 0 | X21: 0.21177999 | Y21: 0 | Z21: 0.00035089724 | AA21: 5.1078517e-05 | AB21: 0.0028684717 | AC21: 0 | AD21: 0.0010289422 | AE21: -0.01596622 | AF21: 1 | AG21: 1 | AH21: 1 | AI21: 1 | AJ21: 1 | AK21: 1 | AL21: 1 | AM21: 0 | AN21: 0 | AO21: 04:-125--100 | AP21: =-125--100 -> -25 | AQ21: 991718.69 | AR21: 5 | AS21: 0 | AT21: 100 | AU21: 100 | AV21: 0 | AW21: 0 | AX21: 0
A22: 4.3 | B22: 0.99034254 | C22: 7.935874 | D22: 10.99278 | E22: 0.0068667181 | F22: 0.0096574553 | G22: 0 | H22: 4.1493576 | I22: 4.0940505 | J22: -33.386672 | K22: -83.205891 | L22: 15.783595 | M22: 15.690168 | N22: 76.749332 | O22: 75.908226 | P22: 298964.84 | Q22: 222085.04 | R22: 780.43588 | S22: 0 | T22: 0 | U22: 0 | V22: 0 | W22: 0 | X22: 0.37109602 | Y22: 0 | Z22: 0.00053542522 | AA22: 7.7502751e-05 | AB22: 0.0026030463 | AC22: 0 | AD22: 0.0064414668 | AE22: -0.026461015 | AF22: 1 | AG22: 1 | AH22: 1 | AI22: 1 | AJ22: 1 | AK22: 1 | AL22: 1 | AM22: 0 | AN22: 0 | AO22: 05:-100--75 | AP22: =-100--75 -> -25 | AQ22: 6218381 | AR22: 28 | AS22: 0 | AT22: 100 | AU22: 100 | AV22: 0 | AW22: 0 | AX22: 0
A23: 4.3 | B23: 0.99531194 | C23: 1.8301087 | D23: 5.4828571 | E23: 0.0015380347 | F23: 0.0046880567 | G23: 0 | H23: 3.8986259 | I23: 4.1473096 | J23: -59.670289 | K23: -56.905879 | L23: 17.18523 | M23: 15.245911 | N23: 77.854851 | O23: 76.716765 | P23: 263061.8 | Q23: 226873.4 | R23: 780.81197 | S23: 0 | T23: 0 | U23: 0.0025098134 | V23: 0 | W23: 0 | X23: 0.46038548 | Y23: 0 | Z23: 0.00047411809 | AA23: 6.1413376e-05 | AB23: 0.0024185358 | AC23: 0 | AD23: 0.0017339791 | AE23: -0.022969111 | AF23: 0.996552 | AG23: 1 | AH23: 1 | AI23: 1 | AJ23: 1 | AK23: 1 | AL23: 1 | AM23: 0 | AN23: 0 | AO23: 06:-75--50 | AP23: =-75--50 -> -25 | AQ23: 1.3952714e+08 | AR23: 615 | AS23: 0 | AT23: 100 | AU23: 100 | AV23: 0 | AW23: 0 | AX23: 0
A24: 4.3 | B24: 0.99386722 | C24: 3.4070807 | D24: 7.116109 | E24: 0.0028845605 | F24: 0.0061327803 | G24: 0 | H24: 3.8995117 | I24: 4.1447021 | J24: -60.114068 | K24: -33.387746 | L24: 15.955751 | M24: 15.468515 | N24: 73.341274 | O24: 71.959297 | P24: 273610.41 | Q24: 248811.56 | R24: 782.10208 | S24: 0 | T24: 0 | U24: 0.0013918239 | V24: 0 | W24: 0 | X24: 0.58737228 | Y24: 0 | Z24: 0.00039633253 | AA24: 5.7272475e-05 | AB24: 0.0025387935 | AC24: 2.1988534e-08 | AD24: 0.0031403457 | AE24: -0.015273165 | AF24: 0.98396189 | AG24: 0.99979739 | AH24: 0.99996869 | AI24: 0.99999042 | AJ24: 1 | AK24: 1 | AL24: 1 | AM24: 0 | AN24: 0 | AO24: 07:-50--25 | AP24: =-50--25 -> -25 | AQ24: 1.6254859e+09 | AR24: 6533 | AS24: 0 | AT24: 100 | AU24: 100 | AV24: 0 | AW24: 0 | AX24: 0
A25: 4.3 | B25: 0.9884728 | C25: 8.6868546 | D25: 12.988493 | E25: 0.0075443498 | F25: 0.011527198 | G25: 0 | H25: 4.097073 | I25: 4.1260145 | J25: -41.673293 | K25: -9.3602837 | L25: 15.303898 | M25: 16.096379 | N25: 72.187814 | O25: 71.033906 | P25: 281961.47 | Q25: 260269.92 | R25: 781.85441 | S25: 0 | T25: 0 | U25: 0.002782606 | V25: 0 | W25: 0 | X25: 0.6832404 | Y25: 0 | Z25: 0.00037474785 | AA25: 6.7008715e-05 | AB25: 0.0026069832 | AC25: 3.167863e-08 | AD25: 0.008478412 | AE25: -0.014262052 | AF25: 0.97210268 | AG25: 0.99863121 | AH25: 0.99987521 | AI25: 1 | AJ25: 1 | AK25: 1 | AL25: 1 | AM25: 0 | AN25: 0 | AO25: 08:-25-0 | AP25: =-25-0 -> -25 | AQ25: 9.6437813e+09 | AR25: 37053 | AS25: 0 | AT25: 100 | AU25: 100 | AV25: 0 | AW25: 0 | AX25: 0
A26: 4.3 | B26: 0.98339762 | C26: 18.623934 | D26: 18.20065 | E26: 0.017027448 | F26: 0.016602377 | G26: 0 | H26: 4.2061544 | I26: 4.0684698 | J26: -31.261201 | K26: 15.159426 | L26: 15.015325 | M26: 16.531355 | N26: 69.194667 | O26: 67.652827 | P26: 286199.29 | Q26: 265730.87 | R26: 782.34245 | S26: 0 | T26: 0 | U26: 0.0089632365 | V26: 0 | W26: 0 | X26: 0.76936148 | Y26: 0 | Z26: 0.00037298469 | AA26: 7.4133431e-05 | AB26: 0.0027640145 | AC26: 4.0375178e-07 | AD26: 0.013390826 | AE26: -0.0086907056 | AF26: 0.92529766 | AG26: 0.99384479 | AH26: 0.99955192 | AI26: 0.99983997 | AJ26: 1 | AK26: 1 | AL26: 1 | AM26: 0 | AN26: 0 | AO26: 09:0-25 | AP26: 0-25 | AQ26: 3.8876693e+10 | AR26: 146301 | AS26: 0 | AT26: 100 | AU26: 100 | AV26: 0 | AW26: 0 | AX26: 0
A27: 4.3 | B27: 0.97636692 | C27: 30.172729 | D27: 24.948964 | E27: 0.029485364 | F27: 0.023633078 | G27: 0 | H27: 4.2307505 | I27: 3.9141908 | J27: -26.990777 | K27: 37.381619 | L27: 14.422594 | M27: 17.06351 | N27: 67.386444 | O27: 64.475774 | P27: 297412.58 | Q27: 276705.53 | R27: 782.18971 | S27: 0 | T27: 0 | U27: 0.017089004 | V27: 0 | W27: 0 | X27: 0.75444376 | Y27: 0 | Z27: 0.00037191187 | AA27: 7.6173822e-05 | AB27: 0.0030566284 | AC27: 3.0381204e-06 | AD27: 0.020125312 | AE27: 0.014020201 | AF27: 0.79792715 | AG27: 0.97128841 | AH27: 0.99714665 | AI27: 0.99948034 | AJ27: 1 | AK27: 1 | AL27: 1 | AM27: 0 | AN27: 0 | AO27: 10:25-50 | AP27: 25-50 | AQ27: 6.1816015e+10 | AR27: 223400 | AS27: 0 | AT27: 100 | AU27: 100 | AV27: 0 | AW27: 0 | AX27: 0
A28: 4.3 | B28: 0.96874993 | C28: 38.013898 | D28: 31.6812 | E28: 0.039071235 | F28: 0.031250067 | G28: 0 | H28: 4.4691529 | I28: 3.8899297 | J28: -17.585481 | K28: 62.663639 | L28: 14.904888 | M28: 17.433619 | N28: 69.566621 | O28: 66.270424 | P28: 287889.79 | Q28: 267833.15 | R28: 780.90567 | S28: 0 | T28: 0 | U28: 0.012379923 | V28: 0 | W28: 0 | X28: 0.65513568 | Y28: 0 | Z28: 0.00037347868 | AA28: 0.00010165557 | AB28: 0.0031882111 | AC28: 6.1303928e-06 | AD28: 0.027580577 | AE28: 0.018520793 | AF28: 0.75933386 | AG28: 0.97296663 | AH28: 0.99568006 | AI28: 0.99918144 | AJ28: 1 | AK28: 1 | AL28: 1 | AM28: 0 | AN28: 0 | AO28: 11:50-75 | AP28: 50-75 | AQ28: 6.0848478e+10 | AR28: 227188 | AS28: 0 | AT28: 100 | AU28: 100 | AV28: 0 | AW28: 0 | AX28: 0
A29: 4.3 | B29: 0.96283573 | C29: 42.416214 | D29: 36.521539 | E29: 0.0449524 | F29: 0.037164268 | G29: 0 | H29: 4.669899 | I29: 3.8733774 | J29: -11.114419 | K29: 86.082824 | L29: 14.804271 | M29: 16.938335 | N29: 69.317804 | O29: 65.421495 | P29: 290106.53 | Q29: 269690.96 | R29: 780.16361 | S29: 0 | T29: 0 | U29: 0.014929732 | V29: 0 | W29: 0 | X29: 0.57816443 | Y29: 0 | Z29: 0.0003715959 | AA29: 0.00012118595 | AB29: 0.0033233774 | AC29: 1.1990445e-05 | AD29: 0.033336103 | AE29: 0.028739178 | AF29: 0.66722427 | AG29: 0.96394033 | AH29: 0.99288434 | AI29: 0.99892184 | AJ29: 1 | AK29: 1 | AL29: 1 | AM29: 0 | AN29: 0 | AO29: 12:75-100 | AP29: 75-100 | AQ29: 4.55179e+10 | AR29: 168778 | AS29: 0 | AT29: 100 | AU29: 100 | AV29: 0 | AW29: 0 | AX29: 0
A30: 4.3 | B30: 0.95762744 | C30: 42.856373 | D30: 40.521638 | E30: 0.045562891 | F30: 0.042372557 | G30: 0 | H30: 4.8031244 | I30: 3.7630665 | J30: -6.4548522 | K30: 111.90903 | L30: 15.277825 | M30: 18.004782 | N30: 72.048793 | O30: 66.634559 | P30: 281058.31 | Q30: 261352.89 | R30: 779.37482 | S30: 0 | T30: 0 | U30: 0.01546372 | V30: 0 | W30: 0 | X30: 0.50506534 | Y30: 0 | Z30: 0.00037175511 | AA30: 0.00016338236 | AB30: 0.0035742012 | AC30: 2.7048051e-05 | AD30: 0.038236155 | AE30: 0.049620894 | AF30: 0.5097601 | AG30: 0.94271147 | AH30: 0.98829344 | AI30: 0.99772965 | AJ30: 1 | AK30: 1 | AL30: 1 | AM30: 0 | AN30: 0 | AO30: 13:100-125 | AP30: 100-125 | AQ30: 2.802095e+10 | AR30: 107215 | AS30: 0 | AT30: 100 | AU30: 100 | AV30: 0 | AW30: 0 | AX30: 0
A31: 4.3 | B31: 0.95271962 | C31: 44.800986 | D31: 44.07818 | E31: 0.048312694 | F31: 0.047280382 | G31: 0 | H31: 4.8804013 | I31: 3.6765996 | J31: -4.9590254 | K31: 134.28061 | L31: 14.635412 | M31: 19.561149 | N31: 71.76419 | O31: 64.964183 | P31: 292491.52 | Q31: 272829.41 | R31: 778.75703 | S31: 0 | T31: 0 | U31: 0.017311252 | V31: 0 | W31: 0 | X31: 0.51891916 | Y31: 0 | Z31: 0.0003723305 | AA31: 0.00019811131 | AB31: 0.0035194468 | AC31: 6.8018786e-05 | AD31: 0.043122459 | AE31: 0.071315724 | AF31: 0.39506961 | AG31: 0.90346476 | AH31: 0.97245124 | AI31: 0.99591568 | AJ31: 1 | AK31: 1 | AL31: 1 | AM31: 0 | AN31: 0 | AO31: 14:125-150 | AP31: 125-150 | AQ31: 1.2692843e+10 | AR31: 46523 | AS31: 0 | AT31: 100 | AU31: 100 | AV31: 0 | AW31: 0 | AX31: 0
A32: 4.3 | B32: 0.9490703 | C32: 41.981394 | D32: 46.595165 | E32: 0.044353499 | F32: 0.050929704 | G32: 0 | H32: 5.0437272 | I32: 3.6813844 | J32: 9.9071253 | K32: 160.87385 | L32: 15.119569 | M32: 19.507703 | N32: 79.542842 | O32: 70.442227 | P32: 283310.92 | Q32: 264098.56 | R32: 776.92982 | S32: 0 | T32: 0 | U32: 0.016870534 | V32: 0 | W32: 0 | X32: 0.47603545 | Y32: 0 | Z32: 0.00037700592 | AA32: 0.00027635962 | AB32: 0.003803571 | AC32: 0.00014882352 | AD32: 0.046323928 | AE32: 0.092884957 | AF32: 0.28597376 | AG32: 0.80432464 | AH32: 0.93778902 | AI32: 0.99023488 | AJ32: 1 | AK32: 1 | AL32: 1 | AM32: 0 | AN32: 0 | AO32: 15:150-175 | AP32: 150-175 | AQ32: 2.58843e+09 | AR32: 9801 | AS32: 0 | AT32: 100 | AU32: 100 | AV32: 0 | AW32: 0 | AX32: 0
A33: 4.3 | B33: 0.94285433 | C33: 48.655806 | D33: 50.644539 | E33: 0.054036721 | F33: 0.057145668 | G33: 0 | H33: 5.0710696 | I33: 3.6599799 | J33: 12.2848 | K33: 183.22998 | L33: 14.003319 | M33: 19.98188 | N33: 83.336593 | O33: 71.286178 | P33: 302371.03 | Q33: 285150.39 | R33: 776.21487 | S33: 0 | T33: 0 | U33: 0.017358684 | V33: 0 | W33: 0 | X33: 0.46148792 | Y33: 0 | Z33: 0.00037680602 | AA33: 0.00032732859 | AB33: 0.0039005728 | AC33: 0.00043364357 | AD33: 0.0521073 | AE33: 0.12971425 | AF33: 0.16588024 | AG33: 0.61762235 | AH33: 0.80205726 | AI33: 0.96116652 | AJ33: 1 | AK33: 1 | AL33: 1 | AM33: 0 | AN33: 0 | AO33: 16:175-200 | AP33: 175-200 | AQ33: 6.8692728e+08 | AR33: 2409 | AS33: 0 | AT33: 100 | AU33: 100 | AV33: 0 | AW33: 0 | AX33: 0
A34: 4.3 | B34: 0.9407399 | C34: 38.318358 | D34: 51.956483 | E34: 0.039465443 | F34: 0.059260097 | G34: 0 | H34: 5.1605718 | I34: 3.6692646 | J34: 17.585612 | K34: 209.41141 | L34: 14.520526 | M34: 20.232747 | N34: 90.534831 | O34: 75.341532 | P34: 296660.31 | Q34: 274999.14 | R34: 775.31983 | S34: 0 | T34: 0 | U34: 0.015751738 | V34: 0 | W34: 0 | X34: 0.29437842 | Y34: 0 | Z34: 0.00037945678 | AA34: 0.00042470513 | AB34: 0.0042613109 | AC34: 0.00072566888 | AD34: 0.053468938 | AE34: 0.16225249 | AF34: 0.036592112 | AG34: 0.4165709 | AH34: 0.69329744 | AI34: 0.92631746 | AJ34: 1 | AK34: 1 | AL34: 1 | AM34: 0 | AN34: 0 | AO34: 17:200-225 | AP34: 200-225 | AQ34: 1.2347462e+08 | AR34: 449 | AS34: 0 | AT34: 100 | AU34: 100 | AV34: 0 | AW34: 0 | AX34: 0
A35: 4.3 | B35: 0.93891144 | C35: 22.828421 | D35: 53.065137 | E35: 0.021363411 | F35: 0.061088562 | G35: 0 | H35: 5.2641041 | I35: 3.6465013 | J35: 27.398546 | K35: 231.7946 | L35: 13.76739 | M35: 20.801174 | N35: 92.494129 | O35: 74.555659 | P35: 310947.98 | Q35: 290043.59 | R35: 776.17564 | S35: 0 | T35: 0 | U35: 0 | V35: 0 | W35: 0 | X35: 0.15312933 | Y35: 0 | Z35: 0.00038271758 | AA35: 0.00052407484 | AB35: 0.0044067446 | AC35: 0.0013321278 | AD35: 0.054442879 | AE35: 0.19808292 | AF35: 0 | AG35: 0.17645629 | AH35: 0.38832439 | AI35: 0.9097973 | AJ35: 1 | AK35: 1 | AL35: 1 | AM35: 0 | AN35: 0 | AO35: 18:225-250 | AP35: 225-250 | AQ35: 22913444 | AR35: 79 | AS35: 0 | AT35: 100 | AU35: 100 | AV35: 0 | AW35: 0 | AX35: 0
A38: WALA [12,24) | C38: CashWindow
A39: modelId | B39: SFACTOR_PREPAY_TRACKING_CPR | C39: PREPAY_CPR1 | D39: PREPAY_TRACKING_CPR1 | E39: PREPAY_SMM1 | F39: PREPAY_TRACKING_SMM1 | G39: PCT_LOANTYPE | H39: _ORIGNOTERATE | I39: _ZEROSATO | J39: _SATO | K39: _REFI_INCENTIVE_Fixed | L39: _Fixed_cost | M39: _LOANAGE | N39: _LTV | O39: _CLTV | P39: _AVG_LOANSIZE_SCHAMBALANCE | Q39: _WACLS | R39: _FICO | S39: PCT_ISSECONDLIEN | T39: _OrigCombLTV | U39: PCT_SVC | V39: PCT_TPO | W39: PCT_GEO | X39: PCT_LOANPURPOSE | Y39: PCT_OCC | Z39: curtailsmm | AA39: defaultsmm | AB39: toverSmm | AC39: cashoutSmm | AD39: refiSmm | AE39: cumHPA | AF39: cumHPA05Pct | AG39: cumHPA15Pct | AH39: cumHPA20Pct | AI39: cumHPA25Pct | AJ39: cumHPA30Pct | AK39: cumHPA35Pct | AL39: cumHPA40Pct | AM39: adjtoverSmm | AN39: adjRefiSmm | AO39: groupByColumn | AP39: curve | AQ39: Balance | AR39: LoanCount | AS39: PCT_BROKER | AT39: PCT_CORRES | AU39: PCT_NonRETAIL | AV39: PCT_RETAIL | AW39: PCT_CashWindow | AX39: PCT_NonCashWindow
A40: 4.3 | B40: 0.99661762 | C40: 0 | D40: 3.9841936 | E40: 0 | F40: 0.00338238 | G40: 0 | H40: 3.875 | I40: 4.118472 | J40: -64.0619 | K40: -131.95 | L40: 13.16 | M40: 17 | N40: 80 | O40: 77.08 | P40: 303250.44 | Q40: 303250.44 | R40: 773 | S40: 0 | T40: 0 | U40: 0 | V40: 1 | W40: 0 | X40: 1 | Y40: 0 | Z40: 0.00035183 | AA40: 7.792e-05 | AB40: 0.00295262 | AC40: 0 | AD40: 0 | AE40: 0.011207683 | AF40: 1 | AG40: 1 | AH40: 1 | AI40: 1 | AJ40: 1 | AK40: 1 | AL40: 1 | AM40: 0 | AN40: 0 | AO40: 03:-150--125 | AP40: =-150--125 -> -25 | AQ40: 303250.44 | AR40: 1 | AS40: 0 | AT40: 0 | AU40: 0 | AV40: 100 | AW40: 100 | AX40: 0
A41: 4.3 | B41: 0.99173453 | C41: 0 | D41: 9.4798618 | E41: 0 | F41: 0.0082654715 | G41: 0 | H41: 3.875 | I41: 3.8717773 | J41: -56.468943 | K41: -111.35086 | L41: 14.328815 | M41: 17.880294 | N41: 80 | O41: 75.620345 | P41: 284673.47 | Q41: 278674.78 | R41: 771.88117 | S41: 0 | T41: 0 | U41: 0 | V41: 1 | W41: 0 | X41: 1 | Y41: 0 | Z41: 0.00035334788 | AA41: 5.3605208e-05 | AB41: 0.0031742462 | AC41: 0 | AD41: 0.0046842576 | AE41: 0.029306717 | AF41: 1 | AG41: 1 | AH41: 1 | AI41: 1 | AJ41: 1 | AK41: 1 | AL41: 1 | AM41: 0 | AN41: 0 | AO41: 04:-125--100 | AP41: =-125--100 -> -25 | AQ41: 1114699.1 | AR41: 4 | AS41: 0 | AT41: 0 | AU41: 0 | AV41: 100 | AW41: 100 | AX41: 0
A42: 4.3 | B42: 0.98992819 | C42: 12.107777 | D42: 11.438635 | E42: 0.010697278 | F42: 0.01007181 | G42: 0 | H42: 4.2120764 | I42: 3.9473309 | J42: -23.140697 | K42: -83.452033 | L42: 19.208546 | M42: 17.333171 | N42: 79.615477 | O42: 76.037526 | P42: 239079.34 | Q42: 193572.8 | R42: 765.54682 | S42: 0 | T42: 0 | U42: 0 | V42: 1 | W42: 0 | X42: 0.97979815 | Y42: 0 | Z42: 0.00056887345 | AA42: 8.1948978e-05 | AB42: 0.0030977716 | AC42: 0 | AD42: 0.0063232008 | AE42: -0.0002056697 | AF42: 1 | AG42: 1 | AH42: 1 | AI42: 1 | AJ42: 1 | AK42: 1 | AL42: 1 | AM42: 0 | AN42: 0 | AO42: 05:-100--75 | AP42: =-100--75 -> -25 | AQ42: 2322873.6 | AR42: 12 | AS42: 0 | AT42: 0 | AU42: 0 | AV42: 100 | AW42: 100 | AX42: 0
A43: 4.3 | B43: 0.98934761 | C43: 27.432198 | D43: 12.059911 | E43: 0.026366898 | F43: 0.010652392 | G43: 0 | H43: 4.2156057 | I43: 4.0468354 | J43: -26.571952 | K43: -57.932898 | L43: 22.942908 | M43: 16.539877 | N43: 78.81004 | O43: 71.950413 | P43: 243355.1 | Q43: 154364.35 | R43: 774.26727 | S43: 0 | T43: 0 | U43: 0.08578669 | V43: 1 | W43: 0 | X43: 0.62733873 | Y43: 0 | Z43: 0.0010454839 | AA43: 8.0260524e-05 | AB43: 0.002838117 | AC43: 0 | AD43: 0.0066885165 | AE43: -0.01057977 | AF43: 0.95511436 | AG43: 0.99661868 | AH43: 1 | AI43: 1 | AJ43: 1 | AK43: 1 | AL43: 1 | AM43: 0 | AN43: 0 | AO43: 06:-75--50 | AP43: =-75--50 -> -25 | AQ43: 13275334 | AR43: 86 | AS43: 0 | AT43: 0 | AU43: 0 | AV43: 100 | AW43: 100 | AX43: 0
A44: 4.3 | B44: 0.99372916 | C44: 2.6972 | D44: 7.2708179 | E44: 0.0022759411 | F44: 0.0062708358 | G44: 0 | H44: 4.0130121 | I44: 4.124413 | J44: -49.480846 | K44: -32.313402 | L44: 17.404312 | M44: 15.583407 | N44: 77.145531 | O44: 74.947546 | P44: 263811.83 | Q44: 223674.18 | R44: 781.04806 | S44: 0 | T44: 0 | U44: 0.0047215107 | V44: 1 | W44: 0 | X44: 0.5513044 | Y44: 0 | Z44: 0.00047030754 | AA44: 5.2422737e-05 | AB44: 0.0026297805 | AC44: 3.0524064e-07 | AD44: 0.0031180062 | AE44: -0.014876592 | AF44: 0.97128747 | AG44: 0.99033606 | AH44: 0.99969298 | AI44: 0.99969298 | AJ44: 1 | AK44: 1 | AL44: 1 | AM44: 0 | AN44: 0 | AO44: 07:-50--25 | AP44: =-50--25 -> -25 | AQ44: 1.9616225e+08 | AR44: 877 | AS44: 0 | AT44: 0 | AU44: 0 | AV44: 100 | AW44: 100 | AX44: 0
A45: 4.3 | B45: 0.99009166 | C45: 10.272771 | D45: 11.262988 | E45: 0.0089923175 | F45: 0.0099083449 | G45: 0 | H45: 4.1238862 | I45: 4.1160383 | J45: -38.460418 | K45: -8.5277656 | L45: 16.482102 | M45: 15.981391 | N45: 74.178548 | O45: 72.813875 | P45: 262234.84 | Q45: 241347.2 | R45: 781.322 | S45: 0 | T45: 0 | U45: 0.019790794 | V45: 1 | W45: 0 | X45: 0.71355362 | Y45: 0 | Z45: 0.00038681295 | AA45: 5.6034209e-05 | AB45: 0.0026655013 | AC45: 1.5856603e-07 | AD45: 0.0067998237 | AE45: -0.013449962 | AF45: 0.9617047 | AG45: 0.99077334 | AH45: 0.999711 | AI45: 0.99996719 | AJ45: 1 | AK45: 1 | AL45: 1 | AM45: 0 | AN45: 0 | AO45: 08:-25-0 | AP45: =-25-0 -> -25 | AQ45: 2.0574849e+09 | AR45: 8525 | AS45: 0 | AT45: 0 | AU45: 0 | AV45: 100 | AW45: 100 | AX45: 0
A46: 4.3 | B46: 0.98630216 | C46: 18.568596 | D46: 15.253884 | E46: 0.016971762 | F46: 0.013697841 | G46: 0 | H46: 4.197132 | I46: 4.0368714 | J46: -27.530438 | K46: 15.60855 | L46: 16.293509 | M46: 16.097029 | N46: 70.91269 | O46: 68.870179 | P46: 263734.72 | Q46: 244852.35 | R46: 782.53188 | S46: 0 | T46: 0 | U46: 0.045171012 | V46: 1 | W46: 0 | X46: 0.80546192 | Y46: 0 | Z46: 0.00037783382 | AA46: 6.0192294e-05 | AB46: 0.0028370435 | AC46: 1.495745e-06 | AD46: 0.010421262 | AE46: -0.00041697403 | AF46: 0.88752184 | AG46: 0.97232014 | AH46: 0.99769674 | AI46: 0.99965008 | AJ46: 1 | AK46: 1 | AL46: 1 | AM46: 0 | AN46: 0 | AO46: 09:0-25 | AP46: 0-25 | AQ46: 1.1257087e+10 | AR46: 45975 | AS46: 0 | AT46: 0 | AU46: 0 | AV46: 100 | AW46: 100 | AX46: 0
A47: 4.3 | B47: 0.98060834 | C47: 30.159799 | D47: 20.941787 | E47: 0.02947039 | F47: 0.01939166 | G47: 0 | H47: 4.2299296 | I47: 3.9089805 | J47: -21.580224 | K47: 38.014005 | L47: 15.480645 | M47: 16.321129 | N47: 68.001822 | O47: 64.841484 | P47: 277166.09 | Q47: 257802.07 | R47: 783.21829 | S47: 0 | T47: 0 | U47: 0.045054977 | V47: 1 | W47: 0 | X47: 0.82871998 | Y47: 0 | Z47: 0.00037299548 | AA47: 6.2396994e-05 | AB47: 0.0030315717 | AC47: 5.0815919e-06 | AD47: 0.0159196 | AE47: 0.019986443 | AF47: 0.77431859 | AG47: 0.93880174 | AH47: 0.99518497 | AI47: 0.9992447 | AJ47: 1 | AK47: 1 | AL47: 1 | AM47: 0 | AN47: 0 | AO47: 10:25-50 | AP47: 25-50 | AQ47: 2.6377019e+10 | AR47: 102315 | AS47: 0 | AT47: 0 | AU47: 0 | AV47: 100 | AW47: 100 | AX47: 0
A48: 4.3 | B48: 0.97389312 | C48: 40.149087 | D48: 27.199293 | E48: 0.041874133 | F48: 0.026106875 | G48: 0 | H48: 4.4272407 | I48: 3.8675649 | J48: -11.88364 | K48: 61.818588 | L48: 15.319514 | M48: 17.356706 | N48: 67.606811 | O48: 64.383644 | P48: 280265.73 | Q48: 260583.52 | R48: 782.62838 | S48: 0 | T48: 0 | U48: 0.029567307 | V48: 1 | W48: 0 | X48: 0.78719709 | Y48: 0 | Z48: 0.00037399172 | AA48: 7.9844471e-05 | AB48: 0.0031769512 | AC48: 6.4092633e-06 | AD48: 0.022469664 | AE48: 0.0195067 | AF48: 0.77029743 | AG48: 0.9596833 | AH48: 0.99534206 | AI48: 0.9993421 | AJ48: 1 | AK48: 1 | AL48: 1 | AM48: 0 | AN48: 0 | AO48: 11:50-75 | AP48: 50-75 | AQ48: 2.2196504e+10 | AR48: 85180 | AS48: 0 | AT48: 0 | AU48: 0 | AV48: 100 | AW48: 100 | AX48: 0
A49: 4.3 | B49: 0.96868969 | C49: 42.720599 | D49: 31.732163 | E49: 0.045374116 | F49: 0.031310308 | G49: 0 | H49: 4.6748624 | I49: 3.876234 | J49: -4.757858 | K49: 86.11073 | L49: 15.269437 | M49: 17.80654 | N49: 67.682094 | O49: 64.283091 | P49: 281346.03 | Q49: 261471.15 | R49: 781.28007 | S49: 0 | T49: 0 | U49: 0.037970816 | V49: 1 | W49: 0 | X49: 0.70634876 | Y49: 0 | Z49: 0.00037464345 | AA49: 0.000101898 | AB49: 0.003284246 | AC49: 1.0011225e-05 | AD49: 0.027539494 | AE49: 0.020944397 | AF49: 0.7255838 | AG49: 0.96035673 | AH49: 0.9942031 | AI49: 0.99909325 | AJ49: 1 | AK49: 1 | AL49: 1 | AM49: 0 | AN49: 0 | AO49: 12:75-100 | AP49: 75-100 | AQ49: 1.3715731e+10 | AR49: 52456 | AS49: 0 | AT49: 0 | AU49: 0 | AV49: 100 | AW49: 100 | AX49: 0
A50: 4.3 | B50: 0.96474775 | C50: 43.681735 | D50: 34.992225 | E50: 0.046719362 | F50: 0.035252248 | G50: 0 | H50: 4.8434827 | I50: 3.807434 | J50: -1.3594117 | K50: 111.23674 | L50: 15.526546 | M50: 18.29082 | N50: 69.560573 | O50: 65.196329 | P50: 276553.64 | Q50: 257166.42 | R50: 780.71302 | S50: 0 | T50: 0 | U50: 0.039785194 | V50: 1 | W50: 0 | X50: 0.62199301 | Y50: 0 | Z50: 0.00037584798 | AA50: 0.0001336259 | AB50: 0.0034024579 | AC50: 1.6828302e-05 | AD50: 0.031323473 | AE50: 0.033325074 | AF50: 0.6266057 | AG50: 0.95634481 | AH50: 0.99256606 | AI50: 0.99872658 | AJ50: 1 | AK50: 1 | AL50: 1 | AM50: 0 | AN50: 0 | AO50: 13:100-125 | AP50: 100-125 | AQ50: 7.047903e+09 | AR50: 27406 | AS50: 0 | AT50: 0 | AU50: 0 | AV50: 100 | AW50: 100 | AX50: 0
A51: 4.3 | B51: 0.96091175 | C51: 42.096706 | D51: 38.027071 | E51: 0.044511922 | F51: 0.039088254 | G51: 0 | H51: 4.9315036 | I51: 3.6961975 | J51: 1.0148037 | K51: 134.98966 | L51: 15.352613 | M51: 19.417138 | N51: 70.84739 | O51: 64.873088 | P51: 279295.95 | Q51: 260089.7 | R51: 779.89281 | S51: 0 | T51: 0 | U51: 0.058809219 | V51: 1 | W51: 0 | X51: 0.64064484 | Y51: 0 | Z51: 0.00037431524 | AA51: 0.00014527289 | AB51: 0.0034345077 | AC51: 3.4003484e-05 | AD51: 0.03510014 | AE51: 0.058873943 | AF51: 0.4937243 | AG51: 0.92881813 | AH51: 0.98536312 | AI51: 0.99845284 | AJ51: 1 | AK51: 1 | AL51: 1 | AM51: 0 | AN51: 0 | AO51: 14:125-150 | AP51: 125-150 | AQ51: 2.983749e+09 | AR51: 11472 | AS51: 0 | AT51: 0 | AU51: 0 | AV51: 100 | AW51: 100 | AX51: 0
A52: 4.3 | B52: 0.95713534 | C52: 43.974174 | D52: 40.887378 | E52: 0.047132849 | F52: 0.04286466 | G52: 0 | H52: 5.0881617 | I52: 3.667939 | J52: 12.727544 | K52: 159.19145 | L52: 15.009271 | M52: 20.173603 | N52: 73.885734 | O52: 66.483514 | P52: 285506.84 | Q52: 266044.99 | R52: 778.89373 | S52: 0 | T52: 0 | U52: 0.018776664 | V52: 1 | W52: 0 | X52: 0.66670176 | Y52: 0 | Z52: 0.00037301546 | AA52: 0.00021407522 | AB52: 0.0034923012 | AC52: 6.0698153e-05 | AD52: 0.038724555 | AE52: 0.07629897 | AF52: 0.39665848 | AG52: 0.89240437 | AH52: 0.97360936 | AI52: 0.99656065 | AJ52: 1 | AK52: 1 | AL52: 1 | AM52: 0 | AN52: 0 | AO52: 15:150-175 | AP52: 150-175 | AQ52: 6.6245203e+08 | AR52: 2490 | AS52: 0 | AT52: 0 | AU52: 0 | AV52: 100 | AW52: 100 | AX52: 0
A53: 4.3 | B53: 0.95312325 | C53: 55.301 | D53: 43.793211 | E53: 0.064899799 | F53: 0.046876748 | G53: 0 | H53: 5.1828649 | I53: 3.6615472 | J53: 26.721662 | K53: 183.23274 | L53: 14.425865 | M53: 20.14771 | N53: 78.208501 | O53: 68.105276 | P53: 296805.85 | Q53: 276792.32 | R53: 779.56453 | S53: 0 | T53: 0 | U53: 0 | V53: 1 | W53: 0 | X53: 0.65481309 | Y53: 0 | Z53: 0.00039321549 | AA53: 0.00029980357 | AB53: 0.0036021195 | AC53: 0.00017322807 | AD53: 0.042408366 | AE53: 0.10048405 | AF53: 0.26675475 | AG53: 0.7917514 | AH53: 0.92892011 | AI53: 0.98513131 | AJ53: 1 | AK53: 1 | AL53: 1 | AM53: 0 | AN53: 0 | AO53: 16:175-200 | AP53: 175-200 | AQ53: 1.2012787e+08 | AR53: 434 | AS53: 0 | AT53: 0 | AU53: 0 | AV53: 100 | AW53: 100 | AX53: 0
A54: 4.3 | B54: 0.95413155 | C54: 53.736279 | D54: 43.075521 | E54: 0.062214788 | F54: 0.045868453 | G54: 0 | H54: 5.2404386 | I54: 3.6507389 | J54: 30.826975 | K54: 207.93763 | L54: 15.518872 | M54: 20.380193 | N54: 83.310511 | O54: 69.451672 | P54: 273149.38 | Q54: 257277.22 | R54: 776.7971 | S54: 0 | T54: 0 | U54: 0 | V54: 1 | W54: 0 | X54: 0.51070676 | Y54: 0 | Z54: 0.00043522976 | AA54: 0.00032085648 | AB54: 0.0039489034 | AC54: 0.00038778712 | AD54: 0.040775661 | AE54: 0.12908079 | AF54: 0.12918379 | AG54: 0.65268542 | AH54: 0.83717966 | AI54: 0.96337046 | AJ54: 1 | AK54: 1 | AL54: 1 | AM54: 0 | AN54: 0 | AO54: 17:200-225 | AP54: 200-225 | AQ54: 15951188 | AR54: 62 | AS54: 0 | AT54: 0 | AU54: 0 | AV54: 100 | AW54: 100 | AX54: 0
A55: 4.3 | B55: 0.95616787 | C55: 0 | D55: 41.600419 | E55: 0 | F55: 0.043832134 | G55: 0 | H55: 5.25 | I55: 3.6406663 | J55: 17.662921 | K55: 233.95346 | L55: 18.196645 | M55: 20.999142 | N55: 95 | O55: 75.144084 | P55: 219482.43 | Q55: 219482.19 | R55: 794 | S55: 0 | T55: 0 | U55: 0 | V55: 1 | W55: 0 | X55: 0 | Y55: 0 | Z55: 0.00035712854 | AA55: 0.00011713423 | AB55: 0.0048422815 | AC55: 0.0018443456 | AD55: 0.036671225 | AE55: 0.2325131 | AF55: 0 | AG55: 0 | AH55: 0 | AI55: 1 | AJ55: 1 | AK55: 1 | AL55: 1 | AM55: 0 | AN55: 0 | AO55: 18:225-250 | AP55: 225-250 | AQ55: 658446.57 | AR55: 3 | AS55: 0 | AT55: 0 | AU55: 0 | AV55: 100 | AW55: 100 | AX55: 0
A59: WALA [12,24) | C59: NonCashWindow
A60: modelId | B60: SFACTOR_PREPAY_TRACKING_CPR | C60: PREPAY_CPR1 | D60: PREPAY_TRACKING_CPR1 | E60: PREPAY_SMM1 | F60: PREPAY_TRACKING_SMM1 | G60: PCT_LOANTYPE | H60: _ORIGNOTERATE | I60: _ZEROSATO | J60: _SATO | K60: _REFI_INCENTIVE_Fixed | L60: _Fixed_cost | M60: _LOANAGE | N60: _LTV | O60: _CLTV | P60: _AVG_LOANSIZE_SCHAMBALANCE | Q60: _WACLS | R60: _FICO | S60: PCT_ISSECONDLIEN | T60: _OrigCombLTV | U60: PCT_SVC | V60: PCT_TPO | W60: PCT_GEO | X60: PCT_LOANPURPOSE | Y60: PCT_OCC | Z60: curtailsmm | AA60: defaultsmm | AB60: toverSmm | AC60: cashoutSmm | AD60: refiSmm | AE60: cumHPA | AF60: cumHPA05Pct | AG60: cumHPA15Pct | AH60: cumHPA20Pct | AI60: cumHPA25Pct | AJ60: cumHPA30Pct | AK60: cumHPA35Pct | AL60: cumHPA40Pct | AM60: adjtoverSmm | AN60: adjRefiSmm | AO60: groupByColumn | AP60: curve | AQ60: Balance | AR60: LoanCount | AS60: PCT_BROKER | AT60: PCT_CORRES | AU60: PCT_NonRETAIL | AV60: PCT_RETAIL | AW60: PCT_CashWindow | AX60: PCT_NonCashWindow
A61: 4.3 | B61: 0.99502774 | C61: 0 | D61: 5.8062099 | E61: 0 | F61: 0.004972258 | G61: 0 | H61: 4.125 | I61: 4.0914466 | J61: -39.2924 | K61: -107.58291 | L61: 22.464931 | M61: 18.498075 | N61: 80 | O61: 77.967109 | P61: 177738.07 | Q61: 177737.55 | R61: 782 | S61: 0 | T61: 0 | U61: 0 | V61: 1 | W61: 0 | X61: 0 | Y61: 0 | Z61: 0.00035354267 | AA61: 1.3394992e-05 | AB61: 0.0038048394 | AC61: 0 | AD61: 0.00080046846 | AE61: -0.0012605143 | AF61: 1 | AG61: 1 | AH61: 1 | AI61: 1 | AJ61: 1 | AK61: 1 | AL61: 1 | AM61: 0 | AN61: 0 | AO61: 04:-125--100 | AP61: =-125--100 -> -25 | AQ61: 710950.18 | AR61: 4 | AS61: 0 | AT61: 0 | AU61: 0 | AV61: 100 | AW61: 0 | AX61: 100
A62: 4.3 | B62: 0.99155722 | C62: 2.1576304 | D62: 9.6738777 | E62: 0.0018160553 | F62: 0.0084427815 | G62: 0 | H62: 4.1889411 | I62: 4.0657978 | J62: -27.8585 | K62: -83.219819 | L62: 18.879883 | M62: 17.169202 | N62: 76.77312 | O62: 76.563737 | P62: 225230.39 | Q62: 199055.97 | R62: 782.10614 | S62: 0 | T62: 0 | U62: 0 | V62: 1 | W62: 0 | X62: 0.13217823 | Y62: 0 | Z62: 0.00037752422 | AA62: 4.2870696e-05 | AB62: 0.0031142536 | AC62: 0 | AD62: 0.0049081176 | AE62: -0.024099846 | AF62: 1 | AG62: 1 | AH62: 1 | AI62: 1 | AJ62: 1 | AK62: 1 | AL62: 1 | AM62: 0 | AN62: 0 | AO62: 05:-100--75 | AP62: =-100--75 -> -25 | AQ62: 2985839.6 | AR62: 15 | AS62: 0 | AT62: 0 | AU62: 0 | AV62: 100 | AW62: 0 | AX62: 100
A63: 4.3 | B63: 0.99550634 | C63: 8.8452661 | D63: 5.2610892 | E63: 0.0076879413 | F63: 0.0044936552 | G63: 0 | H63: 3.8754078 | I63: 4.1426231 | J63: -62.065276 | K63: -58.362228 | L63: 20.533306 | M63: 15.317372 | N63: 78.746357 | O63: 74.733621 | P63: 253658.83 | Q63: 183215.2 | R63: 781.71532 | S63: 0 | T63: 0 | U63: 0 | V63: 1 | W63: 0 | X63: 0.15768331 | Y63: 0 | Z63: 0.00071264658 | AA63: 7.5896281e-05 | AB63: 0.0026374621 | AC63: 0 | AD63: 0.0010676405 | AE63: -0.021212522 | AF63: 0.99566702 | AG63: 1 | AH63: 1 | AI63: 1 | AJ63: 1 | AK63: 1 | AL63: 1 | AM63: 0 | AN63: 0 | AO63: 06:-75--50 | AP63: =-75--50 -> -25 | AQ63: 54598129 | AR63: 298 | AS63: 0 | AT63: 0 | AU63: 0 | AV63: 100 | AW63: 0 | AX63: 100
A64: 4.3 | B64: 0.99412404 | C64: 6.1091154 | D64: 6.8276779 | E64: 0.0052393001 | F64: 0.0058759588 | G64: 0 | H64: 3.9337332 | I64: 4.1358934 | J64: -57.987062 | K64: -33.504741 | L64: 16.96728 | M64: 15.448122 | N64: 74.279276 | O64: 72.186536 | P64: 264061.52 | Q64: 230524.08 | R64: 783.86911 | S64: 0 | T64: 0 | U64: 0.0022841412 | V64: 1 | W64: 0 | X64: 0.30870795 | Y64: 0 | Z64: 0.0004416903 | AA64: 6.3523872e-05 | AB64: 0.0027300309 | AC64: 7.7476567e-09 | AD64: 0.0026406919 | AE64: -0.012060826 | AF64: 0.97597851 | AG64: 0.99876642 | AH64: 1 | AI64: 1 | AJ64: 1 | AK64: 1 | AL64: 1 | AM64: 0 | AN64: 0 | AO64: 07:-50--25 | AP64: =-50--25 -> -25 | AQ64: 5.8691431e+08 | AR64: 2546 | AS64: 0 | AT64: 0 | AU64: 0 | AV64: 100 | AW64: 0 | AX64: 100
A65: 4.3 | B65: 0.98985186 | C65: 7.5476108 | D65: 11.520542 | E65: 0.0065183615 | F65: 0.010148138 | G65: 0 | H65: 4.1214877 | I65: 4.1334079 | J65: -40.061891 | K65: -8.3611912 | L65: 15.571414 | M65: 15.625428 | N65: 72.112709 | O65: 70.727766 | P65: 278786.73 | Q65: 255296.92 | R65: 783.58961 | S65: 0 | T65: 0 | U65: 0.002846396 | V65: 1 | W65: 0 | X65: 0.58850586 | Y65: 0 | Z65: 0.00038877256 | AA65: 6.7447233e-05 | AB65: 0.0026347468 | AC65: 1.1532695e-08 | AD65: 0.0070571457 | AE65: -0.015546707 | AF65: 0.97687925 | AG65: 0.99866327 | AH65: 0.99989613 | AI65: 1 | AJ65: 1 | AK65: 1 | AL65: 1 | AM65: 0 | AN65: 0 | AO65: 08:-25-0 | AP65: =-25-0 -> -25 | AQ65: 4.5335627e+09 | AR65: 17758 | AS65: 0 | AT65: 0 | AU65: 0 | AV65: 100 | AW65: 0 | AX65: 100
A66: 4.3 | B66: 0.98591472 | C66: 11.797693 | D66: 15.652506 | E66: 0.010406892 | F66: 0.014085285 | G66: 0 | H66: 4.2420115 | I66: 4.0979455 | J66: -27.984199 | K66: 15.32746 | L66: 15.34839 | M66: 16.027786 | N66: 67.860579 | O66: 66.32759 | P66: 279876.34 | Q66: 259921.55 | R66: 784.8208 | S66: 0 | T66: 0 | U66: 0.0093631669 | V66: 1 | W66: 0 | X66: 0.76846682 | Y66: 0 | Z66: 0.00037706139 | AA66: 7.1435677e-05 | AB66: 0.0027606002 | AC66: 4.1713309e-07 | AD66: 0.010875756 | AE66: -0.010170756 | AF66: 0.94085711 | AG66: 0.99349299 | AH66: 0.99919156 | AI66: 0.99978821 | AJ66: 1 | AK66: 1 | AL66: 1 | AM66: 0 | AN66: 0 | AO66: 09:0-25 | AP66: 0-25 | AQ66: 2.3068557e+10 | AR66: 88752 | AS66: 0 | AT66: 0 | AU66: 0 | AV66: 100 | AW66: 0 | AX66: 100
A67: 4.3 | B67: 0.98030231 | C67: 17.55991 | D67: 21.237349 | E67: 0.015962752 | F67: 0.019697688 | G67: 0 | H67: 4.3594907 | I67: 4.0141205 | J67: -17.69393 | K67: 38.111594 | L67: 15.143014 | M67: 17.022507 | N67: 65.665989 | O67: 63.523641 | P67: 283223.76 | Q67: 263596.7 | R67: 785.18895 | S67: 0 | T67: 0 | U67: 0.011352927 | V67: 1 | W67: 0 | X67: 0.83557602 | Y67: 0 | Z67: 0.00037495601 | AA67: 8.5276546e-05 | AB67: 0.0030262632 | AC67: 1.9782436e-06 | AD67: 0.016209199 | AE67: 0.00047233564 | AF67: 0.87196598 | AG67: 0.98161997 | AH67: 0.99805301 | AI67: 0.99951235 | AJ67: 1 | AK67: 1 | AL67: 1 | AM67: 0 | AN67: 0 | AO67: 10:25-50 | AP67: 25-50 | AQ67: 4.6900707e+10 | AR67: 177926 | AS67: 0 | AT67: 0 | AU67: 0 | AV67: 100 | AW67: 0 | AX67: 100
A68: 4.3 | B68: 0.97383997 | C68: 25.676066 | D68: 27.246962 | E68: 0.024424861 | F68: 0.026160032 | G68: 0 | H68: 4.5363795 | I68: 3.9428542 | J68: -8.837139 | K68: 62.97282 | L68: 15.52194 | M68: 17.988233 | N68: 66.904798 | O68: 64.127384 | P68: 276197.65 | Q68: 257200.95 | R68: 784.49164 | S68: 0 | T68: 0 | U68: 0.0091287563 | V68: 1 | W68: 0 | X68: 0.81147446 | Y68: 0 | Z68: 0.00037766527 | AA68: 0.00011707935 | AB68: 0.0032507888 | AC68: 4.6677129e-06 | AD68: 0.022409817 | AE68: 0.0092320769 | AF68: 0.80256162 | AG68: 0.97617681 | AH68: 0.99685625 | AI68: 0.99925923 | AJ68: 1 | AK68: 1 | AL68: 1 | AM68: 0 | AN68: 0 | AO68: 11:50-75 | AP68: 50-75 | AQ68: 5.9067741e+10 | AR68: 229656 | AS68: 0 | AT68: 0 | AU68: 0 | AV68: 100 | AW68: 0 | AX68: 100
A69: 4.3 | B69: 0.96838283 | C69: 31.506465 | D69: 31.991219 | E69: 0.031043832 | F69: 0.031617165 | G69: 0 | H69: 4.7068362 | I69: 3.8993735 | J69: -1.7327127 | K69: 86.340718 | L69: 15.316941 | M69: 17.929493 | N69: 66.053577 | O69: 62.805532 | P69: 279970.53 | Q69: 260672.83 | R69: 783.73187 | S69: 0 | T69: 0 | U69: 0.010820637 | V69: 1 | W69: 0 | X69: 0.80359528 | Y69: 0 | Z69: 0.00037747068 | AA69: 0.00014268261 | AB69: 0.0033466866 | AC69: 1.0009337e-05 | AD69: 0.027740301 | AE69: 0.018643281 | AF69: 0.71583084 | AG69: 0.9655081 | AH69: 0.99427538 | AI69: 0.99900877 | AJ69: 1 | AK69: 1 | AL69: 1 | AM69: 0 | AN69: 0 | AO69: 12:75-100 | AP69: 75-100 | AQ69: 5.2624892e+10 | AR69: 201881 | AS69: 0 | AT69: 0 | AU69: 0 | AV69: 100 | AW69: 0 | AX69: 100
A70: 4.3 | B70: 0.96402649 | C70: 35.202875 | D70: 35.573041 | E70: 0.035513149 | F70: 0.035973507 | G70: 0 | H70: 4.875273 | I70: 3.8240351 | J70: 2.8640941 | K70: 111.62061 | L70: 15.591368 | M70: 18.436838 | N70: 68.031409 | O70: 63.715734 | P70: 274819.08 | Q70: 256099.69 | R70: 782.14585 | S70: 0 | T70: 0 | U70: 0.010932085 | V70: 1 | W70: 0 | X70: 0.75570179 | Y70: 0 | Z70: 0.00037801051 | AA70: 0.00019942512 | AB70: 0.003518881 | AC70: 2.2498401e-05 | AD70: 0.031854677 | AE70: 0.034409915 | AF70: 0.58562118 | AG70: 0.94979627 | AH70: 0.99044619 | AI70: 0.99804399 | AJ70: 1 | AK70: 1 | AL70: 1 | AM70: 0 | AN70: 0 | AO70: 13:100-125 | AP70: 100-125 | AQ70: 3.0215665e+10 | AR70: 117984 | AS70: 0 | AT70: 0 | AU70: 0 | AV70: 100 | AW70: 0 | AX70: 100
A71: 4.3 | B71: 0.96002414 | C71: 35.292652 | D71: 38.710534 | E71: 0.035624578 | F71: 0.03997586 | G71: 0 | H71: 4.948392 | I71: 3.7110585 | J71: 4.1983428 | K71: 134.92879 | L71: 15.244953 | M71: 19.350509 | N71: 68.322934 | O71: 62.19156 | P71: 281087.83 | Q71: 261925.42 | R71: 781.44083 | S71: 0 | T71: 0 | U71: 0.012081384 | V71: 1 | W71: 0 | X71: 0.77661138 | Y71: 0 | Z71: 0.00037698949 | AA71: 0.00024306139 | AB71: 0.0035621478 | AC71: 5.029033e-05 | AD71: 0.035743357 | AE71: 0.064840859 | AF71: 0.42223724 | AG71: 0.90980069 | AH71: 0.9798565 | AI71: 0.99714418 | AJ71: 1 | AK71: 1 | AL71: 1 | AM71: 0 | AN71: 0 | AO71: 14:125-150 | AP71: 125-150 | AQ71: 1.4091588e+10 | AR71: 53800 | AS71: 0 | AT71: 0 | AU71: 0 | AV71: 100 | AW71: 0 | AX71: 100
A72: 4.3 | B72: 0.95692142 | C72: 34.084038 | D72: 41.045723 | E72: 0.034136214 | F72: 0.043078579 | G72: 0 | H72: 5.1459085 | I72: 3.6852227 | J72: 19.40902 | K72: 160.59319 | L72: 15.643636 | M72: 19.608128 | N72: 73.20453 | O72: 65.656036 | P72: 273651.28 | Q72: 255259.41 | R72: 779.35191 | S72: 0 | T72: 0 | U72: 0.0112626 | V72: 1 | W72: 0 | X72: 0.86951356 | Y72: 0 | Z72: 0.00038342289 | AA72: 0.00035448863 | AB72: 0.0036686535 | AC72: 6.9191811e-05 | AD72: 0.038602807 | AE72: 0.079609892 | AF72: 0.33058698 | AG72: 0.87412835 | AH72: 0.97213331 | AI72: 0.99550187 | AJ72: 1 | AK72: 1 | AL72: 1 | AM72: 0 | AN72: 0 | AO72: 15:150-175 | AP72: 150-175 | AQ72: 3.4406416e+09 | AR72: 13479 | AS72: 0 | AT72: 0 | AU72: 0 | AV72: 100 | AW72: 0 | AX72: 100
A73: 4.3 | B73: 0.9532454 | C73: 33.66536 | D73: 43.706713 | E73: 0.033626457 | F73: 0.046754602 | G73: 0 | H73: 5.2300295 | I73: 3.658819 | J73: 27.510522 | K73: 182.55438 | L73: 14.769761 | M73: 20.16457 | N73: 75.884241 | O73: 66.853702 | P73: 289325.66 | Q73: 270360.54 | R73: 778.1221 | S73: 0 | T73: 0 | U73: 0.01385278 | V73: 1 | W73: 0 | X73: 0.85221978 | Y73: 0 | Z73: 0.00038805999 | AA73: 0.00052770323 | AB73: 0.0036357914 | AC73: 0.00013058948 | AD73: 0.042072443 | AE73: 0.096594918 | AF73: 0.25503784 | AG73: 0.81629256 | AH73: 0.94230196 | AI73: 0.99203387 | AJ73: 1 | AK73: 1 | AL73: 1 | AM73: 0 | AN73: 0 | AO73: 16:175-200 | AP73: 175-200 | AQ73: 8.2784399e+08 | AR73: 3062 | AS73: 0 | AT73: 0 | AU73: 0 | AV73: 100 | AW73: 0 | AX73: 100
A74: 4.3 | B74: 0.95105383 | C74: 28.261047 | D74: 45.240284 | E74: 0.027298498 | F74: 0.04894617 | G74: 0 | H74: 5.2464187 | I74: 3.6917229 | J74: 34.717274 | K74: 210.09061 | L74: 15.062819 | M74: 19.593819 | N74: 85.791659 | O74: 73.984502 | P74: 285262.2 | Q74: 265099.5 | R74: 777.48058 | S74: 0 | T74: 0 | U74: 0.018733181 | V74: 1 | W74: 0 | X74: 0.76619444 | Y74: 0 | Z74: 0.00039355746 | AA74: 0.00055744886 | AB74: 0.0040135355 | AC74: 0.00029981246 | AD74: 0.0436818 | AE74: 0.12009367 | AF74: 0.14854477 | AG74: 0.6966005 | AH74: 0.85633043 | AI74: 0.97462642 | AJ74: 1 | AK74: 1 | AL74: 1 | AM74: 0 | AN74: 0 | AO74: 17:200-225 | AP74: 200-225 | AQ74: 1.0975119e+08 | AR74: 414 | AS74: 0 | AT74: 0 | AU74: 0 | AV74: 100 | AW74: 0 | AX74: 100
A75: 4.3 | B75: 0.95106712 | C75: 0.36622219 | D75: 45.231099 | E75: 0.00030569862 | F75: 0.048932877 | G75: 0 | H75: 5.3142705 | I75: 3.6726424 | J75: 37.399005 | K75: 234.92882 | L75: 14.685726 | M75: 20.006516 | N75: 88.220187 | O75: 75.44366 | P75: 291527.89 | Q75: 271913.73 | R75: 780.63111 | S75: 0 | T75: 0 | U75: 0.02801204 | V75: 1 | W75: 0 | X75: 0.75461687 | Y75: 0 | Z75: 0.00039629672 | AA75: 0.000556465 | AB75: 0.0039214945 | AC75: 0.0003853902 | AD75: 0.043673215 | AE75: 0.12704695 | AF75: 0.07035943 | AG75: 0.65337731 | AH75: 0.82154449 | AI75: 0.9827527 | AJ75: 1 | AK75: 1 | AL75: 1 | AM75: 0 | AN75: 0 | AO75: 18:225-250 | AP75: 225-250 | AQ75: 39971319 | AR75: 147 | AS75: 0 | AT75: 0 | AU75: 0 | AV75: 100 | AW75: 0 | AX75: 100
A76: 4.3 | B76: 0.95286035 | C76: 34.576458 | D76: 43.978976 | E76: 0.034739567 | F76: 0.047139654 | G76: 0 | H76: 5.483312 | I76: 3.6729403 | J76: 47.39144 | K76: 265.60645 | L76: 14.27703 | M76: 20.573626 | N76: 88.917568 | O76: 76.022172 | P76: 295376.62 | Q76: 279697.78 | R76: 783.97378 | S76: 0 | T76: 0 | U76: 0 | V76: 1 | W76: 0 | X76: 0.94361767 | Y76: 0 | Z76: 0.00039082394 | AA76: 0.00063181953 | AB76: 0.0040903139 | AC76: 0.00017462634 | AD76: 0.041852053 | AE76: 0.12851392 | AF76: 0.099460969 | AG76: 0.56324578 | AH76: 0.94738828 | AI76: 1 | AJ76: 1 | AK76: 1 | AL76: 1 | AM76: 0 | AN76: 0 | AO76: 999:>= 250 | AP76: >= 250 | AQ76: 15942774 | AR76: 57 | AS76: 0 | AT76: 0 | AU76: 0 | AV76: 100 | AW76: 0 | AX76: 100
D80: =C1 -> BROKER | H80: =C19 -> CORRES | L80: =C38 -> CashWindow | P80: =C59 -> NonCashWindow
D81: =AO2 -> groupByColumn | E81: =E2 -> PREPAY_SMM1 | F81: CPR | H81: =AO20 -> groupByColumn | I81: =E20 -> PREPAY_SMM1 | J81: CPR | L81: =AO39 -> groupByColumn | M81: =E39 -> PREPAY_SMM1 | N81: CPR | P81: =AO60 -> groupByColumn | Q81: =E60 -> PREPAY_SMM1 | R81: CPR | U81: groupByColumn | V81: BROKER | W81: CORRES | X81: CashWindow | Y81: NonCashWindow
D82: =AO3 -> 06:-75--50 | E82: =E3 -> 0.0029157422 | F82: =100*(1-(1-E82)^12) -> 3.4433222 | H82: =AO21 -> 04:-125--100 | I82: =E21 -> 1.0083505e-08 | J82: =100*(1-(1-I82)^12) -> 1.2100205e-05 | L82: =AO40 -> 03:-150--125 | M82: =E40 -> 0 | N82: =100*(1-(1-M82)^12) -> 0 | P82: =AO61 -> 04:-125--100 | Q82: =E61 -> 0 | R82: =100*(1-(1-Q82)^12) -> 0 | U82: 03:-150--125 | V82: =VLOOKUP(U82,$D$81:$F$98,3,0) -> #N/A | W82: =VLOOKUP(U82,$H$81:$J$98,3,0) -> #N/A | X82: =VLOOKUP(U82,$L$81:$N$98,3,0) -> 0 | Y82: =VLOOKUP(U82,$P$81:$R$98,3,0) -> #N/A
D83: =AO4 -> 07:-50--25 | E83: =E4 -> 0.0022575225 | F83: =100*(1-(1-E83)^12) -> 2.6756426 | H83: =AO22 -> 05:-100--75 | I83: =E22 -> 0.0068667181 | J83: =100*(1-(1-I83)^12) -> 7.935874 | L83: =AO41 -> 04:-125--100 | M83: =E41 -> 0 | N83: =100*(1-(1-M83)^12) -> 0 | P83: =AO62 -> 05:-100--75 | Q83: =E62 -> 0.0018160553 | R83: =100*(1-(1-Q83)^12) -> 2.1576304 | U83: 04:-125--100 | V83: =VLOOKUP(U83,$D$81:$F$98,3,0) -> #N/A | W83: =VLOOKUP(U83,$H$81:$J$98,3,0) -> 1.2100205e-05 | X83: =VLOOKUP(U83,$L$81:$N$98,3,0) -> 0 | Y83: =VLOOKUP(U83,$P$81:$R$98,3,0) -> 0
D84: =AO5 -> 08:-25-0 | E84: =E5 -> 0.012984471 | F84: =100*(1-(1-E84)^12) -> 14.515411 | H84: =AO23 -> 06:-75--50 | I84: =E23 -> 0.0015380347 | J84: =100*(1-(1-I84)^12) -> 1.8301087 | L84: =AO42 -> 05:-100--75 | M84: =E42 -> 0.010697278 | N84: =100*(1-(1-M84)^12) -> 12.107777 | P84: =AO63 -> 06:-75--50 | Q84: =E63 -> 0.0076879413 | R84: =100*(1-(1-Q84)^12) -> 8.8452661 | U84: 05:-100--75 | V84: =VLOOKUP(U84,$D$81:$F$98,3,0) -> #N/A | W84: =VLOOKUP(U84,$H$81:$J$98,3,0) -> 7.935874 | X84: =VLOOKUP(U84,$L$81:$N$98,3,0) -> 12.107777 | Y84: =VLOOKUP(U84,$P$81:$R$98,3,0) -> 2.1576304
D85: =AO6 -> 09:0-25 | E85: =E6 -> 0.025939486 | F85: =100*(1-(1-E85)^12) -> 27.048998 | H85: =AO24 -> 07:-50--25 | I85: =E24 -> 0.0028845605 | J85: =100*(1-(1-I85)^12) -> 3.4070807 | L85: =AO43 -> 06:-75--50 | M85: =E43 -> 0.026366898 | N85: =100*(1-(1-M85)^12) -> 27.432198 | P85: =AO64 -> 07:-50--25 | Q85: =E64 -> 0.0052393001 | R85: =100*(1-(1-Q85)^12) -> 6.1091154 | U85: 06:-75--50 | V85: =VLOOKUP(U85,$D$81:$F$98,3,0) -> 3.4433222 | W85: =VLOOKUP(U85,$H$81:$J$98,3,0) -> 1.8301087 | X85: =VLOOKUP(U85,$L$81:$N$98,3,0) -> 27.432198 | Y85: =VLOOKUP(U85,$P$81:$R$98,3,0) -> 8.8452661
D86: =AO7 -> 10:25-50 | E86: =E7 -> 0.041027433 | F86: =100*(1-(1-E86)^12) -> 39.511307 | H86: =AO25 -> 08:-25-0 | I86: =E25 -> 0.0075443498 | J86: =100*(1-(1-I86)^12) -> 8.6868546 | L86: =AO44 -> 07:-50--25 | M86: =E44 -> 0.0022759411 | N86: =100*(1-(1-M86)^12) -> 2.6972 | P86: =AO65 -> 08:-25-0 | Q86: =E65 -> 0.0065183615 | R86: =100*(1-(1-Q86)^12) -> 7.5476108 | U86: 07:-50--25 | V86: =VLOOKUP(U86,$D$81:$F$98,3,0) -> 2.6756426 | W86: =VLOOKUP(U86,$H$81:$J$98,3,0) -> 3.4070807 | X86: =VLOOKUP(U86,$L$81:$N$98,3,0) -> 2.6972 | Y86: =VLOOKUP(U86,$P$81:$R$98,3,0) -> 6.1091154
D87: =AO8 -> 11:50-75 | E87: =E8 -> 0.051853975 | F87: =100*(1-(1-E87)^12) -> 47.215946 | H87: =AO26 -> 09:0-25 | I87: =E26 -> 0.017027448 | J87: =100*(1-(1-I87)^12) -> 18.623934 | L87: =AO45 -> 08:-25-0 | M87: =E45 -> 0.0089923175 | N87: =100*(1-(1-M87)^12) -> 10.272771 | P87: =AO66 -> 09:0-25 | Q87: =E66 -> 0.010406892 | R87: =100*(1-(1-Q87)^12) -> 11.797693 | U87: 08:-25-0 | V87: =VLOOKUP(U87,$D$81:$F$98,3,0) -> 14.515411 | W87: =VLOOKUP(U87,$H$81:$J$98,3,0) -> 8.6868546 | X87: =VLOOKUP(U87,$L$81:$N$98,3,0) -> 10.272771 | Y87: =VLOOKUP(U87,$P$81:$R$98,3,0) -> 7.5476108
D88: =AO9 -> 12:75-100 | E88: =E9 -> 0.049717463 | F88: =100*(1-(1-E88)^12) -> 45.770827 | H88: =AO27 -> 10:25-50 | I88: =E27 -> 0.029485364 | J88: =100*(1-(1-I88)^12) -> 30.172729 | L88: =AO46 -> 09:0-25 | M88: =E46 -> 0.016971762 | N88: =100*(1-(1-M88)^12) -> 18.568596 | P88: =AO67 -> 10:25-50 | Q88: =E67 -> 0.015962752 | R88: =100*(1-(1-Q88)^12) -> 17.55991 | U88: 09:0-25 | V88: =VLOOKUP(U88,$D$81:$F$98,3,0) -> 27.048998 | W88: =VLOOKUP(U88,$H$81:$J$98,3,0) -> 18.623934 | X88: =VLOOKUP(U88,$L$81:$N$98,3,0) -> 18.568596 | Y88: =VLOOKUP(U88,$P$81:$R$98,3,0) -> 11.797693
D89: =AO10 -> 13:100-125 | E89: =E10 -> 0.049919769 | F89: =100*(1-(1-E89)^12) -> 45.909203 | H89: =AO28 -> 11:50-75 | I89: =E28 -> 0.039071235 | J89: =100*(1-(1-I89)^12) -> 38.013898 | L89: =AO47 -> 10:25-50 | M89: =E47 -> 0.02947039 | N89: =100*(1-(1-M89)^12) -> 30.159799 | P89: =AO68 -> 11:50-75 | Q89: =E68 -> 0.024424861 | R89: =100*(1-(1-Q89)^12) -> 25.676066 | U89: 10:25-50 | V89: =VLOOKUP(U89,$D$81:$F$98,3,0) -> 39.511307 | W89: =VLOOKUP(U89,$H$81:$J$98,3,0) -> 30.172729 | X89: =VLOOKUP(U89,$L$81:$N$98,3,0) -> 30.159799 | Y89: =VLOOKUP(U89,$P$81:$R$98,3,0) -> 17.55991
D90: =AO11 -> 14:125-150 | E90: =E11 -> 0.050754696 | F90: =100*(1-(1-E90)^12) -> 46.476872 | H90: =AO29 -> 12:75-100 | I90: =E29 -> 0.0449524 | J90: =100*(1-(1-I90)^12) -> 42.416214 | L90: =AO48 -> 11:50-75 | M90: =E48 -> 0.041874133 | N90: =100*(1-(1-M90)^12) -> 40.149087 | P90: =AO69 -> 12:75-100 | Q90: =E69 -> 0.031043832 | R90: =100*(1-(1-Q90)^12) -> 31.506465 | U90: 11:50-75 | V90: =VLOOKUP(U90,$D$81:$F$98,3,0) -> 47.215946 | W90: =VLOOKUP(U90,$H$81:$J$98,3,0) -> 38.013898 | X90: =VLOOKUP(U90,$L$81:$N$98,3,0) -> 40.149087 | Y90: =VLOOKUP(U90,$P$81:$R$98,3,0) -> 25.676066
D91: =AO12 -> 15:150-175 | E91: =E12 -> 0.047514463 | F91: =100*(1-(1-E91)^12) -> 44.242836 | H91: =AO30 -> 13:100-125 | I91: =E30 -> 0.045562891 | J91: =100*(1-(1-I91)^12) -> 42.856373 | L91: =AO49 -> 12:75-100 | M91: =E49 -> 0.045374116 | N91: =100*(1-(1-M91)^12) -> 42.720599 | P91: =AO70 -> 13:100-125 | Q91: =E70 -> 0.035513149 | R91: =100*(1-(1-Q91)^12) -> 35.202875 | U91: 12:75-100 | V91: =VLOOKUP(U91,$D$81:$F$98,3,0) -> 45.770827 | W91: =VLOOKUP(U91,$H$81:$J$98,3,0) -> 42.416214 | X91: =VLOOKUP(U91,$L$81:$N$98,3,0) -> 42.720599 | Y91: =VLOOKUP(U91,$P$81:$R$98,3,0) -> 31.506465
D92: =AO13 -> 16:175-200 | E92: =E13 -> 0.061197489 | F92: =100*(1-(1-E92)^12) -> 53.130436 | H92: =AO31 -> 14:125-150 | I92: =E31 -> 0.048312694 | J92: =100*(1-(1-I92)^12) -> 44.800986 | L92: =AO50 -> 13:100-125 | M92: =E50 -> 0.046719362 | N92: =100*(1-(1-M92)^12) -> 43.681735 | P92: =AO71 -> 14:125-150 | Q92: =E71 -> 0.035624578 | R92: =100*(1-(1-Q92)^12) -> 35.292652 | U92: 13:100-125 | V92: =VLOOKUP(U92,$D$81:$F$98,3,0) -> 45.909203 | W92: =VLOOKUP(U92,$H$81:$J$98,3,0) -> 42.856373 | X92: =VLOOKUP(U92,$L$81:$N$98,3,0) -> 43.681735 | Y92: =VLOOKUP(U92,$P$81:$R$98,3,0) -> 35.202875
D93: =AO14 -> 17:200-225 | E93: =E14 -> 0.052273955 | F93: =100*(1-(1-E93)^12) -> 47.495831 | H93: =AO32 -> 15:150-175 | I93: =E32 -> 0.044353499 | J93: =100*(1-(1-I93)^12) -> 41.981394 | L93: =AO51 -> 14:125-150 | M93: =E51 -> 0.044511922 | N93: =100*(1-(1-M93)^12) -> 42.096706 | P93: =AO72 -> 15:150-175 | Q93: =E72 -> 0.034136214 | R93: =100*(1-(1-Q93)^12) -> 34.084038 | U93: 14:125-150 | V93: =VLOOKUP(U93,$D$81:$F$98,3,0) -> 46.476872 | W93: =VLOOKUP(U93,$H$81:$J$98,3,0) -> 44.800986 | X93: =VLOOKUP(U93,$L$81:$N$98,3,0) -> 42.096706 | Y93: =VLOOKUP(U93,$P$81:$R$98,3,0) -> 35.292652
D94: =AO15 -> 18:225-250 | E94: =E15 -> 0.050925887 | F94: =100*(1-(1-E94)^12) -> 46.592588 | H94: =AO33 -> 16:175-200 | I94: =E33 -> 0.054036721 | J94: =100*(1-(1-I94)^12) -> 48.655806 | L94: =AO52 -> 15:150-175 | M94: =E52 -> 0.047132849 | N94: =100*(1-(1-M94)^12) -> 43.974174 | P94: =AO73 -> 16:175-200 | Q94: =E73 -> 0.033626457 | R94: =100*(1-(1-Q94)^12) -> 33.66536 | U94: 15:150-175 | V94: =VLOOKUP(U94,$D$81:$F$98,3,0) -> 44.242836 | W94: =VLOOKUP(U94,$H$81:$J$98,3,0) -> 41.981394 | X94: =VLOOKUP(U94,$L$81:$N$98,3,0) -> 43.974174 | Y94: =VLOOKUP(U94,$P$81:$R$98,3,0) -> 34.084038
H95: =AO34 -> 17:200-225 | I95: =E34 -> 0.039465443 | J95: =100*(1-(1-I95)^12) -> 38.318358 | L95: =AO53 -> 16:175-200 | M95: =E53 -> 0.064899799 | N95: =100*(1-(1-M95)^12) -> 55.301 | P95: =AO74 -> 17:200-225 | Q95: =E74 -> 0.027298498 | R95: =100*(1-(1-Q95)^12) -> 28.261047 | U95: 16:175-200 | V95: =VLOOKUP(U95,$D$81:$F$98,3,0) -> 53.130436 | W95: =VLOOKUP(U95,$H$81:$J$98,3,0) -> 48.655806 | X95: =VLOOKUP(U95,$L$81:$N$98,3,0) -> 55.301 | Y95: =VLOOKUP(U95,$P$81:$R$98,3,0) -> 33.66536
H96: =AO35 -> 18:225-250 | I96: =E35 -> 0.021363411 | J96: =100*(1-(1-I96)^12) -> 22.828421 | L96: =AO54 -> 17:200-225 | M96: =E54 -> 0.062214788 | N96: =100*(1-(1-M96)^12) -> 53.736279 | P96: =AO75 -> 18:225-250 | Q96: =E75 -> 0.00030569862 | R96: =100*(1-(1-Q96)^12) -> 0.36622219 | U96: 17:200-225 | V96: =VLOOKUP(U96,$D$81:$F$98,3,0) -> 47.495831 | W96: =VLOOKUP(U96,$H$81:$J$98,3,0) -> 38.318358 | X96: =VLOOKUP(U96,$L$81:$N$98,3,0) -> 53.736279 | Y96: =VLOOKUP(U96,$P$81:$R$98,3,0) -> 28.261047
L97: =AO55 -> 18:225-250 | M97: =E55 -> 0 | N97: =100*(1-(1-M97)^12) -> 0 | U97: 18:225-250 | V97: =VLOOKUP(U97,$D$81:$F$98,3,0) -> 46.592588 | W97: =VLOOKUP(U97,$H$81:$J$98,3,0) -> 22.828421 | X97: =VLOOKUP(U97,$L$81:$N$98,3,0) -> 0 | Y97: =VLOOKUP(U97,$P$81:$R$98,3,0) -> 0.36622219

Sheet Baseline
A1: WALA [12,24) | C1: CORRES+CASHWINDOW | AS1: tover | AT1: cash | AW1: refi
A2: modelId | B2: SFACTOR_PREPAY_TRACKING_CPR | C2: PREPAY_CPR1 | D2: PREPAY_TRACKING_CPR1 | E2: PREPAY_SMM1 | F2: PREPAY_TRACKING_SMM1 | G2: PCT_LOANTYPE | H2: _ORIGNOTERATE | I2: _ZEROSATO | J2: _SATO | K2: _REFI_INCENTIVE_Fixed | L2: _Fixed_cost | M2: _LOANAGE | N2: _LTV | O2: _CLTV | P2: _AVG_LOANSIZE_SCHAMBALANCE | Q2: _WACLS | R2: _FICO | S2: PCT_ISSECONDLIEN | T2: _OrigCombLTV | U2: PCT_SVC | V2: PCT_TPO | W2: PCT_GEO | X2: PCT_LOANPURPOSE | Y2: PCT_OCC | Z2: curtailsmm | AA2: defaultsmm | AB2: toverSmm | AC2: cashoutSmm | AD2: refiSmm | AE2: cumHPA | AF2: cumHPA05Pct | AG2: cumHPA15Pct | AH2: cumHPA20Pct | AI2: cumHPA25Pct | AJ2: cumHPA30Pct | AK2: cumHPA35Pct | AL2: cumHPA40Pct | AM2: adjtoverSmm | AN2: adjRefiSmm | AO2: groupByColumn | AP2: curve | AQ2: Balance | AR2: LoanCount | AS2: PCT_BROKER | AT2: PCT_CORRES | AU2: PCT_NonRETAIL | AV2: PCT_RETAIL | AW2: PCT_CashWindow | AX2: PCT_NonCashWindow
A3: 4.3 | B3: 0.99661762 | C3: 0 | D3: 3.9841936 | E3: 0 | F3: 0.00338238 | G3: 0 | H3: 3.875 | I3: 4.118472 | J3: -64.0619 | K3: -131.95 | L3: 13.16 | M3: 17 | N3: 80 | O3: 77.08 | P3: 303250.44 | Q3: 303250.44 | R3: 773 | S3: 0 | T3: 0 | U3: 0 | V3: 1 | W3: 0 | X3: 1 | Y3: 0 | Z3: 0.00035183 | AA3: 7.792e-05 | AB3: 0.00295262 | AC3: 0 | AD3: 0 | AE3: 0.011207683 | AF3: 1 | AG3: 1 | AH3: 1 | AI3: 1 | AJ3: 1 | AK3: 1 | AL3: 1 | AM3: 0 | AN3: 0 | AO3: 03:-150--125 | AP3: =-150--125 -> -25 | AQ3: 303250.44 | AR3: 1 | AS3: 0 | AT3: 0 | AU3: 0 | AV3: 100 | AW3: 100 | AX3: 0
A4: 4.3 | B4: 0.99360179 | C4: 5.6968752e-06 | D4: 7.4133523 | E4: 4.7473962e-09 | F4: 0.0063982143 | G4: 0 | H4: 3.9463145 | I4: 3.9968994 | J4: -50.059634 | K4: -110.17523 | L4: 17.060622 | M4: 16.808767 | N4: 78.188745 | O4: 75.620467 | P4: 244109.93 | Q4: 234046.42 | R4: 766.50335 | S4: 0 | T4: 0 | U4: 0 | V4: 0.52919184 | W4: 0 | X4: 0.62889958 | Y4: 0 | Z4: 0.0003521941 | AA4: 5.2415621e-05 | AB4: 0.0030302851 | AC4: 0 | AD4: 0.0029633053 | AE4: 0.007991849 | AF4: 1 | AG4: 1 | AH4: 1 | AI4: 1 | AJ4: 1 | AK4: 1 | AL4: 1 | AM4: 0 | AN4: 0 | AO4: 04:-125--100 | AP4: =-125--100 -> -25 | AQ4: 2106417.8 | AR4: 9 | AS4: 0 | AT4: 47.080816 | AU4: 47.080816 | AV4: 52.919184 | AW4: 52.919184 | AX4: 0
A5: 4.3 | B5: 0.99022986 | C5: 9.0882947 | D5: 11.114237 | E5: 0.0079086791 | F5: 0.0097701429 | G5: 0 | H5: 4.1664145 | I5: 4.0541488 | J5: -30.600184 | K5: -83.272832 | L5: 16.715042 | M5: 16.136998 | N5: 77.528807 | O5: 75.943391 | P5: 282678.42 | Q5: 213531.37 | R5: 776.38666 | S5: 0 | T5: 0 | U5: 0 | V5: 0.2719593 | W5: 0 | X5: 0.53663822 | Y5: 0 | Z5: 0.00054452178 | AA5: 7.8711944e-05 | AB5: 0.0027375914 | AC5: 0 | AD5: 0.0064093033 | AE5: -0.01932063 | AF5: 1 | AG5: 1 | AH5: 1 | AI5: 1 | AJ5: 1 | AK5: 1 | AL5: 1 | AM5: 0 | AN5: 0 | AO5: 05:-100--75 | AP5: =-100--75 -> -25 | AQ5: 8541254.6 | AR5: 40 | AS5: 0 | AT5: 72.80407 | AU5: 72.80407 | AV5: 27.19593 | AW5: 27.19593 | AX5: 0
A6: 4.3 | B6: 0.99479377 | C6: 4.3452105 | D6: 6.0716553 | E6: 0.0036951907 | F6: 0.0052062325 | G6: 0 | H6: 3.9261648 | I6: 4.1385805 | J6: -56.794737 | K6: -56.995105 | L6: 17.685452 | M6: 15.35833 | N6: 77.937837 | O6: 76.302669 | P6: 261349.7 | Q6: 217977.85 | R6: 780.24337 | S6: 0 | T6: 0 | U6: 0.0097448293 | V6: 0.08687905 | W6: 0 | X6: 0.47489022 | Y6: 0 | Z6: 0.00052375781 | AA6: 6.3050798e-05 | AB6: 0.0024549886 | AC6: 0 | AD6: 0.0021644246 | AE6: -0.021892737 | AF6: 0.99295194 | AG6: 0.99970623 | AH6: 1 | AI6: 1 | AJ6: 1 | AK6: 1 | AL6: 1 | AM6: 0 | AN6: 0 | AO6: 06:-75--50 | AP6: =-75--50 -> -25 | AQ6: 1.5280248e+08 | AR6: 701 | AS6: 0 | AT6: 91.312095 | AU6: 91.312095 | AV6: 8.687905 | AW6: 8.687905 | AX6: 0
A7: 4.3 | B7: 0.99385235 | C7: 3.3308667 | D7: 7.13278 | E7: 0.002819022 | F7: 0.0061476467 | G7: 0 | H7: 3.9117338 | I7: 4.1425173 | J7: -58.969041 | K7: -33.272057 | L7: 16.111738 | M7: 15.480887 | N7: 73.750931 | O7: 72.281083 | P7: 272555.26 | Q7: 245836.46 | R7: 781.98858 | S7: 0 | T7: 0 | U7: 0.0017503777 | V7: 0.10768394 | W7: 0 | X7: 0.58348835 | Y7: 0 | Z7: 0.00040429845 | AA7: 5.6750236e-05 | AB7: 0.0025485914 | AC7: 5.2490237e-08 | AD7: 0.0031379401 | AE7: -0.015230461 | AF7: 0.98259706 | AG7: 0.99877856 | AH7: 0.999939 | AI7: 0.99995839 | AJ7: 1 | AK7: 1 | AL7: 1 | AM7: 0 | AN7: 0 | AO7: 07:-50--25 | AP7: =-50--25 -> -25 | AQ7: 1.8216482e+09 | AR7: 7410 | AS7: 0 | AT7: 89.231606 | AU7: 89.231606 | AV7: 10.768394 | AW7: 10.768394 | AX7: 0
A8: 4.3 | B8: 0.98875745 | C8: 8.9675625 | D8: 12.687336 | E8: 0.007798953 | F8: 0.011242548 | G8: 0 | H8: 4.1017876 | I8: 4.1242603 | J8: -41.108359 | K8: -9.2138984 | L8: 15.511066 | M8: 16.07616 | N8: 72.537854 | O8: 71.346886 | P8: 278492.85 | Q8: 256730.58 | R8: 781.7608 | S8: 0 | T8: 0 | U8: 0.0057732302 | V8: 0.17583438 | W8: 0 | X8: 0.68857051 | Y8: 0 | Z8: 0.00037686931 | AA8: 6.5079019e-05 | AB8: 0.0026172727 | AC8: 5.3989797e-08 | AD8: 0.0081832585 | AE8: -0.014119258 | AF8: 0.97027436 | AG8: 0.99724952 | AH8: 0.99984633 | AI8: 0.99999423 | AJ8: 1 | AK8: 1 | AL8: 1 | AM8: 0 | AN8: 0 | AO8: 08:-25-0 | AP8: =-25-0 -> -25 | AQ8: 1.1701266e+10 | AR8: 45578 | AS8: 0 | AT8: 82.416562 | AU8: 82.416562 | AV8: 17.583438 | AW8: 17.583438 | AX8: 0
A9: 4.3 | B9: 0.98404981 | C9: 18.611512 | D9: 17.54728 | E9: 0.017014944 | F9: 0.01595019 | G9: 0 | H9: 4.2041285 | I9: 4.0613746 | J9: -30.423492 | K9: 15.260273 | L9: 15.30233 | M9: 16.433831 | N9: 69.580433 | O9: 67.926172 | P9: 281155.07 | Q9: 260738.62 | R9: 782.38498 | S9: 0 | T9: 0 | U9: 0.017093365 | V9: 0.22454096 | W9: 0 | X9: 0.7774675 | Y9: 0 | Z9: 0.00037407352 | AA9: 7.1003075e-05 | AB9: 0.0027804125 | AC9: 6.4894898e-07 | AD9: 0.012724037 | AE9: -0.006832914 | AF9: 0.91681544 | AG9: 0.98901162 | AH9: 0.99913535 | AI9: 0.99979733 | AJ9: 1 | AK9: 1 | AL9: 1 | AM9: 0 | AN9: 0 | AO9: 09:0-25 | AP9: 0-25 | AQ9: 5.0133779e+10 | AR9: 192276 | AS9: 0 | AT9: 77.545904 | AU9: 77.545904 | AV9: 22.454096 | AW9: 22.454096 | AX9: 0
A10: 4.3 | B10: 0.97763546 | C10: 30.168862 | D10: 23.770455 | E10: 0.029480886 | F10: 0.022364543 | G10: 0 | H10: 4.230505 | I10: 3.9126325 | J10: -25.372574 | K10: 37.570755 | L10: 14.739039 | M10: 16.841476 | N10: 67.570493 | O10: 64.585151 | P10: 291357.21 | Q10: 270767.49 | R10: 782.49734 | S10: 0 | T10: 0 | U10: 0.025453145 | V10: 0.29908279 | W10: 0 | X10: 0.7766585 | Y10: 0 | Z10: 0.00037223596 | AA10: 7.205341e-05 | AB10: 0.0030491343 | AC10: 3.6492875e-06 | AD10: 0.018867456 | AE10: 0.015804602 | AF10: 0.79086624 | AG10: 0.9615722 | AH10: 0.99655995 | AI10: 0.99940987 | AJ10: 1 | AK10: 1 | AL10: 1 | AM10: 0 | AN10: 0 | AO10: 10:25-50 | AP10: 25-50 | AQ10: 8.8193033e+10 | AR10: 325715 | AS10: 0 | AT10: 70.091721 | AU10: 70.091721 | AV10: 29.908279 | AW10: 29.908279 | AX10: 0
A11: 4.3 | B11: 0.97012462 | C11: 38.59133 | D11: 30.508719 | E11: 0.0398204 | F11: 0.02987538 | G11: 0 | H11: 4.4579505 | I11: 3.883952 | J11: -16.061477 | K11: 62.437772 | L11: 15.01571 | M11: 17.413062 | N11: 69.042798 | O11: 65.76612 | P11: 285852.01 | Q11: 265856.24 | R11: 781.36612 | S11: 0 | T11: 0 | U11: 0.016973817 | V11: 0.26728291 | W11: 0 | X11: 0.69043344 | Y11: 0 | Z11: 0.00037361581 | AA11: 9.5825835e-05 | AB11: 0.0031852015 | AC11: 6.2049301e-06 | AD11: 0.026214517 | AE11: 0.018784309 | AF11: 0.76226423 | AG11: 0.96941622 | AH11: 0.99558972 | AI11: 0.99922438 | AJ11: 1 | AK11: 1 | AL11: 1 | AM11: 0 | AN11: 0 | AO11: 11:50-75 | AP11: 50-75 | AQ11: 8.3044982e+10 | AR11: 312368 | AS11: 0 | AT11: 73.271709 | AU11: 73.271709 | AV11: 26.728291 | AW11: 26.728291 | AX11: 0
A12: 4.3 | B12: 0.96419123 | C12: 42.486827 | D12: 35.440799 | E12: 0.045050049 | F12: 0.035808765 | G12: 0 | H12: 4.6710483 | I12: 3.8740388 | J12: -9.6425377 | K12: 86.089286 | L12: 14.911982 | M12: 17.139371 | N12: 68.93905 | O12: 65.157894 | P12: 288078.01 | Q12: 267741.99 | R12: 780.42213 | S12: 0 | T12: 0 | U12: 0.020264966 | V12: 0.23155309 | W12: 0 | X12: 0.60784591 | Y12: 0 | Z12: 0.00037230157 | AA12: 0.00011671977 | AB12: 0.0033143164 | AC12: 1.1532151e-05 | AD12: 0.031993881 | AE12: 0.026934272 | AF12: 0.6807376 | AG12: 0.96311053 | AH12: 0.99318971 | AI12: 0.99896153 | AJ12: 1 | AK12: 1 | AL12: 1 | AM12: 0 | AN12: 0 | AO12: 12:75-100 | AP12: 75-100 | AQ12: 5.9233631e+10 | AR12: 221234 | AS12: 0 | AT12: 76.844691 | AU12: 76.844691 | AV12: 23.155309 | AW12: 23.155309 | AX12: 0
A13: 4.3 | B13: 0.95905844 | C13: 43.023134 | D13: 39.446279 | E13: 0.04579531 | F13: 0.040941565 | G13: 0 | H13: 4.8112353 | I13: 3.7719832 | J13: -5.4308048 | K13: 111.77392 | L13: 15.327811 | M13: 18.062268 | N13: 71.548727 | O13: 66.345513 | P13: 280152.99 | Q13: 260500.62 | R13: 779.64376 | S13: 0 | T13: 0 | U13: 0.020351686 | V13: 0.20097329 | W13: 0 | X13: 0.52856468 | Y13: 0 | Z13: 0.00037257767 | AA13: 0.0001574021 | AB13: 0.0035396854 | AC13: 2.4994155e-05 | AD13: 0.036846891 | AE13: 0.04634587 | AF13: 0.53324294 | AG13: 0.9454514 | AH13: 0.98915212 | AI13: 0.99793001 | AJ13: 1 | AK13: 1 | AL13: 1 | AM13: 0 | AN13: 0 | AO13: 13:100-125 | AP13: 100-125 | AQ13: 3.5068853e+10 | AR13: 134621 | AS13: 0 | AT13: 79.902671 | AU13: 79.902671 | AV13: 20.097329 | AW13: 20.097329 | AX13: 0
A14: 4.3 | B14: 0.95427884 | C14: 44.295375 | D14: 42.969981 | E14: 0.047589288 | F14: 0.045721162 | G14: 0 | H14: 4.8901277 | I14: 3.6803297 | J14: -3.8220176 | K14: 134.41557 | L14: 14.771918 | M14: 19.533739 | N14: 71.589694 | O14: 64.946845 | P14: 289979.98 | Q14: 270309.36 | R14: 778.9732 | S14: 0 | T14: 0 | U14: 0.025209621 | V14: 0.19033149 | W14: 0 | X14: 0.54208739 | Y14: 0 | Z14: 0.00037270826 | AA14: 0.00018805449 | AB14: 0.0035032802 | AC14: 6.1544603e-05 | AD14: 0.041595559 | AE14: 0.068947661 | AF14: 0.4138467 | AG14: 0.9082903 | AH14: 0.97490878 | AI14: 0.99639858 | AJ14: 1 | AK14: 1 | AL14: 1 | AM14: 0 | AN14: 0 | AO14: 14:125-150 | AP14: 125-150 | AQ14: 1.5676592e+10 | AR14: 57995 | AS14: 0 | AT14: 80.966851 | AU14: 80.966851 | AV14: 19.033149 | AW14: 19.033149 | AX14: 0
A15: 4.3 | B15: 0.95071376 | C15: 42.392669 | D15: 45.474789 | E15: 0.044919863 | F15: 0.049286241 | G15: 0 | H15: 5.0527819 | I15: 3.6786445 | J15: 10.481859 | K15: 160.53102 | L15: 15.097093 | M15: 19.643398 | N15: 78.390058 | O15: 69.635536 | P15: 283758.4 | Q15: 264492.88 | R15: 777.33002 | S15: 0 | T15: 0 | U15: 0.017258958 | V15: 0.20377609 | W15: 0 | X15: 0.51488869 | Y15: 0 | Z15: 0.00037619276 | AA15: 0.00026366755 | AB15: 0.0037401417 | AC15: 0.00013086568 | AD15: 0.044775358 | AE15: 0.08950513 | AF15: 0.30852866 | AG15: 0.82227318 | AH15: 0.94508835 | AI15: 0.99152392 | AJ15: 1 | AK15: 1 | AL15: 1 | AM15: 0 | AN15: 0 | AO15: 15:150-175 | AP15: 150-175 | AQ15: 3.250882e+09 | AR15: 12291 | AS15: 0 | AT15: 79.622391 | AU15: 79.622391 | AV15: 20.377609 | AW15: 20.377609 | AX15: 0
A16: 4.3 | B16: 0.94438283 | C16: 49.699111 | D16: 49.675786 | E16: 0.055653653 | F16: 0.055617168 | G16: 0 | H16: 5.08771 | I16: 3.6602132 | J16: 14.433686 | K16: 183.23039 | L16: 14.066214 | M16: 20.006563 | N16: 82.573291 | O16: 70.81271 | P16: 301542.67 | Q16: 283874.48 | R16: 776.71346 | S16: 0 | T16: 0 | U16: 0.014774893 | V16: 0.14884716 | W16: 0 | X16: 0.49026382 | Y16: 0 | Z16: 0.00037924852 | AA16: 0.00032323157 | AB16: 0.0038561489 | AC16: 0.00039488146 | AD16: 0.050663642 | AE16: 0.12536342 | AF16: 0.18089512 | AG16: 0.64354096 | AH16: 0.82094044 | AI16: 0.96473361 | AJ16: 1 | AK16: 1 | AL16: 1 | AM16: 0 | AN16: 0 | AO16: 16:175-200 | AP16: 175-200 | AQ16: 8.0705515e+08 | AR16: 2843 | AS16: 0 | AT16: 85.115284 | AU16: 85.115284 | AV16: 14.884716 | AW16: 14.884716 | AX16: 0
A17: 4.3 | B17: 0.94227199 | C17: 40.294314 | D17: 51.009104 | E17: 0.042068089 | F17: 0.057728008 | G17: 0 | H17: 5.1697091 | I17: 3.6671452 | J17: 19.100507 | K17: 209.2428 | L17: 14.634743 | M17: 20.249616 | N17: 89.708323 | O17: 74.667695 | P17: 293970.51 | Q17: 272848.93 | R17: 775.48884 | S17: 0 | T17: 0 | U17: 0.01394964 | V17: 0.11440628 | W17: 0 | X17: 0.31912774 | Y17: 0 | Z17: 0.00038583756 | AA17: 0.00041282419 | AB17: 0.0042255695 | AC17: 0.00068701308 | AD17: 0.052016747 | AE17: 0.15845744 | AF17: 0.047185182 | AG17: 0.44358389 | AH17: 0.70975847 | AI17: 0.93055656 | AJ17: 1 | AK17: 1 | AL17: 1 | AM17: 0 | AN17: 0 | AO17: 17:200-225 | AP17: 200-225 | AQ17: 1.394258e+08 | AR17: 511 | AS17: 0 | AT17: 88.559372 | AU17: 88.559372 | AV17: 11.440628 | AW17: 11.440628 | AX17: 0
A18: 4.3 | B18: 0.93939347 | C18: 22.261828 | D18: 52.775165 | E18: 0.020766655 | F18: 0.060606529 | G18: 0 | H18: 5.2637101 | I18: 3.6463383 | J18: 27.126595 | K18: 231.8549 | L18: 13.891115 | M18: 20.806704 | N18: 92.564127 | O18: 74.572096 | P18: 308393.03 | Q18: 287462.08 | R18: 776.67354 | S18: 0 | T18: 0 | U18: 0 | V18: 0.02793355 | W18: 0 | X18: 0.14885189 | Y18: 0 | Z18: 0.00038200278 | AA18: 0.00051270754 | AB18: 0.0044189107 | AC18: 0.0013464358 | AD18: 0.053946453 | AE18: 0.19904467 | AF18: 0 | AG18: 0.17152724 | AH18: 0.37747711 | AI18: 0.91231698 | AJ18: 1 | AK18: 1 | AL18: 1 | AM18: 0 | AN18: 0 | AO18: 18:225-250 | AP18: 225-250 | AQ18: 23571890 | AR18: 82 | AS18: 0 | AT18: 97.206645 | AU18: 97.206645 | AV18: 2.793355 | AW18: 2.793355 | AX18: 0
K25: turn | L25: cash | M25: refi | R25: turn | W25: cash | AB25: refi
A26: incentive | B26: =AQ2 -> Balance | C26: =AO2 -> groupByColumn | D26: =E2 -> PREPAY_SMM1 | E26: =F2 -> PREPAY_TRACKING_SMM1 | F26: ratio | G26: =C2 -> PREPAY_CPR1 | H26: =D2 -> PREPAY_TRACKING_CPR1 | K26: adj | L26: adj | M26: adj | N26: mdl_smm | O26: mdl_cpr | P26: ratio | R26: x | T26: Knot | U26: adj Knot | W26: x | X26: adj x | Y26: Knot | Z26: adj Knot | AB26: x | AC26: adj x | AD26: Knot | AE26: adj Knot
A27: =K3 -> -131.95 | B27: =AQ3/1000000000 -> 0.00030325044 | C27: =AO3 -> 03:-150--125 | D27: =E3 -> 0 | E27: =Z3+AA3+AB3+AC3+AD3 -> 0.00338237 | F27: =D27/E27 -> 0 | G27: =(1-(1-D27)^12)*100 -> 0 | H27: =(1-(1-E27)^12)*100 -> 3.984182 | K27: 1 | L27: 1 | M27: 1 | N27: =Z3+AA3+AB3*K27+AC3*L27+AD3*M27 -> 0.00338237 | O27: =100*(1-(1-N27)^12) -> 3.984182 | P27: =D27/N27 -> 0 | S27: =A27 -> -131.95 | T27: =VLOOKUP(ROUNDDOWN(S27,0),'Spline Pre-Adj'!A:B,2,0) -> 0.95832877 | U27: =T27*K27 -> 0.95832877
A28: =K4 -> -110.17523 | B28: =AQ4/1000000000 -> 0.0021064178 | C28: =AO4 -> 04:-125--100 | D28: =E4 -> 4.7473962e-09 | E28: =Z4+AA4+AB4+AC4+AD4 -> 0.0063982001 | F28: =D28/E28 -> 7.4198933e-07 | G28: =(1-(1-D28)^12)*100 -> 5.6968754e-06 | H28: =(1-(1-E28)^12)*100 -> 7.4133363 | K28: 1 | L28: 1 | M28: 1 | N28: =Z4+AA4+AB4*K28+AC4*L28+AD4*M28 -> 0.0063982001 | O28: =100*(1-(1-N28)^12) -> 7.4133363 | P28: =D28/N28 -> 7.4198933e-07 | S28: =A28 -> -110.17523 | T28: =VLOOKUP(ROUNDDOWN(S28,0),'Spline Pre-Adj'!A:B,2,0) -> 1.012994 | U28: =T28*K28 -> 1.012994 | X28: =A28 -> -110.17523 | Y28: =VLOOKUP(ROUNDDOWN(X28,0),'Spline Pre-Adj'!F:G,2,0) -> 0 | Z28: =Y28*L28 -> 0
A29: =K5 -> -83.272832 | B29: =AQ5/1000000000 -> 0.0085412546 | C29: =AO5 -> 05:-100--75 | D29: =E5 -> 0.0079086791 | E29: =Z5+AA5+AB5+AC5+AD5 -> 0.0097701284 | F29: =D29/E29 -> 0.80947544 | G29: =(1-(1-D29)^12)*100 -> 9.0882947 | H29: =(1-(1-E29)^12)*100 -> 11.114222 | K29: 1 | L29: 1 | M29: 1 | N29: =Z5+AA5+AB5*K29+AC5*L29+AD5*M29 -> 0.0097701284 | O29: =100*(1-(1-N29)^12) -> 11.114222 | P29: =D29/N29 -> 0.80947544 | S29: =A29 -> -83.272832 | T29: =VLOOKUP(ROUNDDOWN(S29,0),'Spline Pre-Adj'!A:B,2,0) -> 1.1352282 | U29: =T29*K29 -> 1.1352282 | X29: =A29 -> -83.272832 | Y29: =VLOOKUP(ROUNDDOWN(X29,0),'Spline Pre-Adj'!F:G,2,0) -> 0.031256267 | Z29: =Y29*L29 -> 0.031256267
A30: =K6 -> -56.995105 | B30: =AQ6/1000000000 -> 0.15280248 | C30: =AO6 -> 06:-75--50 | D30: =E6 -> 0.0036951907 | E30: =Z6+AA6+AB6+AC6+AD6 -> 0.0052062219 | F30: =D30/E30 -> 0.70976436 | G30: =(1-(1-D30)^12)*100 -> 4.3452105 | H30: =(1-(1-E30)^12)*100 -> 6.0716433 | K30: 1 | L30: 1 | M30: 1 | N30: =Z6+AA6+AB6*K30+AC6*L30+AD6*M30 -> 0.0052062219 | O30: =100*(1-(1-N30)^12) -> 6.0716433 | P30: =D30/N30 -> 0.70976436 | S30: =A30 -> -56.995105 | T30: =VLOOKUP(ROUNDDOWN(S30,0),'Spline Pre-Adj'!A:B,2,0) -> 1.2795489 | U30: =T30*K30 -> 1.2795489 | X30: =A30 -> -56.995105 | Y30: =VLOOKUP(ROUNDDOWN(X30,0),'Spline Pre-Adj'!F:G,2,0) -> 0.18862313 | Z30: =Y30*L30 -> 0.18862313 | AC30: =A30 -> -56.995105 | AD30: =VLOOKUP(ROUNDDOWN(AC30,0),'Spline Pre-Adj'!K:L,2,0) -> 0 | AE30: =AD30*M30 -> 0
A31: =K7 -> -33.272057 | B31: =AQ7/1000000000 -> 1.8216482 | C31: =AO7 -> 07:-50--25 | D31: =E7 -> 0.002819022 | E31: =Z7+AA7+AB7+AC7+AD7 -> 0.0061476326 | F31: =D31/E31 -> 0.45855407 | G31: =(1-(1-D31)^12)*100 -> 3.3308667 | H31: =(1-(1-E31)^12)*100 -> 7.1327642 | K31: 1 | L31: 1 | M31: 1 | N31: =Z7+AA7+AB7*K31+AC7*L31+AD7*M31 -> 0.0061476326 | O31: =100*(1-(1-N31)^12) -> 7.1327642 | P31: =D31/N31 -> 0.45855407 | S31: =A31 -> -33.272057 | T31: =VLOOKUP(ROUNDDOWN(S31,0),'Spline Pre-Adj'!A:B,2,0) -> 1.287 | U31: =T31*K31 -> 1.287 | X31: =A31 -> -33.272057 | Y31: =VLOOKUP(ROUNDDOWN(X31,0),'Spline Pre-Adj'!F:G,2,0) -> 0.30615061 | Z31: =Y31*L31 -> 0.30615061 | AC31: =A31 -> -33.272057 | AD31: =VLOOKUP(ROUNDDOWN(AC31,0),'Spline Pre-Adj'!K:L,2,0) -> 0.39387319 | AE31: =AD31*M31 -> 0.39387319
A32: =K8 -> -9.2138984 | B32: =AQ8/1000000000 -> 11.701266 | C32: =AO8 -> 08:-25-0 | D32: =E8 -> 0.007798953 | E32: =Z8+AA8+AB8+AC8+AD8 -> 0.011242534 | F32: =D32/E32 -> 0.69370067 | G32: =(1-(1-D32)^12)*100 -> 8.9675625 | H32: =(1-(1-E32)^12)*100 -> 12.687321 | K32: 1 | L32: 1 | M32: 1 | N32: =Z8+AA8+AB8*K32+AC8*L32+AD8*M32 -> 0.011242534 | O32: =100*(1-(1-N32)^12) -> 12.687321 | P32: =D32/N32 -> 0.69370067 | S32: =A32 -> -9.2138984 | T32: =VLOOKUP(ROUNDDOWN(S32,0),'Spline Pre-Adj'!A:B,2,0) -> 1.287 | U32: =T32*K32 -> 1.287 | X32: =A32 -> -9.2138984 | Y32: =VLOOKUP(ROUNDDOWN(X32,0),'Spline Pre-Adj'!F:G,2,0) -> 0.51930077 | Z32: =Y32*L32 -> 0.51930077 | AC32: =A32 -> -9.2138984 | AD32: =VLOOKUP(ROUNDDOWN(AC32,0),'Spline Pre-Adj'!K:L,2,0) -> 1.1530058 | AE32: =AD32*M32 -> 1.1530058
A33: =K9 -> 15.260273 | B33: =AQ9/1000000000 -> 50.133779 | C33: =AO9 -> 09:0-25 | D33: =E9 -> 0.017014944 | E33: =Z9+AA9+AB9+AC9+AD9 -> 0.015950175 | F33: =D33/E33 -> 1.066756 | G33: =(1-(1-D33)^12)*100 -> 18.611512 | H33: =(1-(1-E33)^12)*100 -> 17.547266 | K33: 1 | L33: 1 | M33: 1.08 | N33: =Z9+AA9+AB9*K33+AC9*L33+AD9*M33 -> 0.016968098 | O33: =100*(1-(1-N33)^12) -> 18.564954 | P33: =D33/N33 -> 1.0027608 | S33: =A33 -> 15.260273 | T33: =VLOOKUP(ROUNDDOWN(S33,0),'Spline Pre-Adj'!A:B,2,0) -> 1.287 | U33: =T33*K33 -> 1.287 | X33: =A33 -> 15.260273 | Y33: =VLOOKUP(ROUNDDOWN(X33,0),'Spline Pre-Adj'!F:G,2,0) -> 0.98856376 | Z33: =Y33*L33 -> 0.98856376 | AC33: =A33 -> 15.260273 | AD33: =VLOOKUP(ROUNDDOWN(AC33,0),'Spline Pre-Adj'!K:L,2,0) -> 1.7164152 | AE33: =AD33*M33 -> 1.8537284
A34: =K10 -> 37.570755 | B34: =AQ10/1000000000 -> 88.193033 | C34: =AO10 -> 10:25-50 | D34: =E10 -> 0.029480886 | E34: =Z10+AA10+AB10+AC10+AD10 -> 0.022364529 | F34: =D34/E34 -> 1.3181984 | G34: =(1-(1-D34)^12)*100 -> 30.168862 | H34: =(1-(1-E34)^12)*100 -> 23.770441 | K34: 1 | L34: 1 | M34: 1.37 | N34: =Z10+AA10+AB10*K34+AC10*L34+AD10*M34 -> 0.029345488 | O34: =100*(1-(1-N34)^12) -> 30.051866 | P34: =D34/N34 -> 1.0046139 | S34: =A34 -> 37.570755 | T34: =VLOOKUP(ROUNDDOWN(S34,0),'Spline Pre-Adj'!A:B,2,0) -> 1.287 | U34: =T34*K34 -> 1.287 | X34: =A34 -> 37.570755 | Y34: =VLOOKUP(ROUNDDOWN(X34,0),'Spline Pre-Adj'!F:G,2,0) -> 1.8953738 | Z34: =Y34*L34 -> 1.8953738 | AC34: =A34 -> 37.570755 | AD34: =VLOOKUP(ROUNDDOWN(AC34,0),'Spline Pre-Adj'!K:L,2,0) -> 2.4264029 | AE34: =AD34*M34 -> 3.324172
A35: =K11 -> 62.437772 | B35: =AQ11/1000000000 -> 83.044982 | C35: =AO11 -> 11:50-75 | D35: =E11 -> 0.0398204 | E35: =Z11+AA11+AB11+AC11+AD11 -> 0.029875365 | F35: =D35/E35 -> 1.3328841 | G35: =(1-(1-D35)^12)*100 -> 38.59133 | H35: =(1-(1-E35)^12)*100 -> 30.508707 | K35: 1 | L35: 1 | M35: 1.38 | N35: =Z11+AA11+AB11*K35+AC11*L35+AD11*M35 -> 0.039836882 | O35: =100*(1-(1-N35)^12) -> 38.603977 | P35: =D35/N35 -> 0.99958628 | S35: =A35 -> 62.437772 | T35: =VLOOKUP(ROUNDDOWN(S35,0),'Spline Pre-Adj'!A:B,2,0) -> 1.287 | U35: =T35*K35 -> 1.287 | X35: =A35 -> 62.437772 | Y35: =VLOOKUP(ROUNDDOWN(X35,0),'Spline Pre-Adj'!F:G,2,0) -> 3.3799458 | Z35: =Y35*L35 -> 3.3799458 | AC35: =A35 -> 62.437772 | AD35: =VLOOKUP(ROUNDDOWN(AC35,0),'Spline Pre-Adj'!K:L,2,0) -> 3.3536482 | AE35: =AD35*M35 -> 4.6280345
A36: =K12 -> 86.089286 | B36: =AQ12/1000000000 -> 59.233631 | C36: =AO12 -> 12:75-100 | D36: =E12 -> 0.045050049 | E36: =Z12+AA12+AB12+AC12+AD12 -> 0.035808751 | F36: =D36/E36 -> 1.2580738 | G36: =(1-(1-D36)^12)*100 -> 42.486827 | H36: =(1-(1-E36)^12)*100 -> 35.440787 | K36: 1 | L36: 1 | M36: 1.29 | N36: =Z12+AA12+AB12*K36+AC12*L36+AD12*M36 -> 0.045086976 | O36: =100*(1-(1-N36)^12) -> 42.513509 | P36: =D36/N36 -> 0.99918099 | S36: =A36 -> 86.089286 | T36: =VLOOKUP(ROUNDDOWN(S36,0),'Spline Pre-Adj'!A:B,2,0) -> 1.287 | U36: =T36*K36 -> 1.287 | X36: =A36 -> 86.089286 | Y36: =VLOOKUP(ROUNDDOWN(X36,0),'Spline Pre-Adj'!F:G,2,0) -> 4.7646641 | Z36: =Y36*L36 -> 4.7646641 | AC36: =A36 -> 86.089286 | AD36: =VLOOKUP(ROUNDDOWN(AC36,0),'Spline Pre-Adj'!K:L,2,0) -> 4.1191353 | AE36: =AD36*M36 -> 5.3136845
A37: =K13 -> 111.77392 | B37: =AQ13/1000000000 -> 35.068853 | C37: =AO13 -> 13:100-125 | D37: =E13 -> 0.04579531 | E37: =Z13+AA13+AB13+AC13+AD13 -> 0.04094155 | F37: =D37/E37 -> 1.1185534 | G37: =(1-(1-D37)^12)*100 -> 43.023134 | H37: =(1-(1-E37)^12)*100 -> 39.446268 | K37: 1 | L37: 1 | M37: 1.13 | N37: =Z13+AA13+AB13*K37+AC13*L37+AD13*M37 -> 0.045731646 | O37: =100*(1-(1-N37)^12) -> 42.977499 | P37: =D37/N37 -> 1.0013921 | X37: =A37 -> 111.77392 | Y37: =VLOOKUP(ROUNDDOWN(X37,0),'Spline Pre-Adj'!F:G,2,0) -> 6.2168085 | Z37: =Y37*L37 -> 6.2168085 | AC37: =A37 -> 111.77392 | AD37: =VLOOKUP(ROUNDDOWN(AC37,0),'Spline Pre-Adj'!K:L,2,0) -> 4.729914 | AE37: =AD37*M37 -> 5.3448028
A38: =K14 -> 134.41557 | B38: =AQ14/1000000000 -> 15.676592 | C38: =AO14 -> 14:125-150 | D38: =E14 -> 0.047589288 | E38: =Z14+AA14+AB14+AC14+AD14 -> 0.045721147 | F38: =D38/E38 -> 1.0408595 | G38: =(1-(1-D38)^12)*100 -> 44.295375 | H38: =(1-(1-E38)^12)*100 -> 42.96997 | K38: 1 | L38: 1 | M38: 1.05 | N38: =Z14+AA14+AB14*K38+AC14*L38+AD14*M38 -> 0.047800925 | O38: =100*(1-(1-N38)^12) -> 44.443732 | P38: =D38/N38 -> 0.99557254 | X38: =A38 -> 134.41557 | Y38: =VLOOKUP(ROUNDDOWN(X38,0),'Spline Pre-Adj'!F:G,2,0) -> 7.6066289 | Z38: =Y38*L38 -> 7.6066289 | AC38: =A38 -> 134.41557 | AD38: =VLOOKUP(ROUNDDOWN(AC38,0),'Spline Pre-Adj'!K:L,2,0) -> 5.205107 | AE38: =AD38*M38 -> 5.4653623
A39: =K15 -> 160.53102 | B39: =AQ15/1000000000 -> 3.250882 | C39: =AO15 -> 15:150-175 | D39: =E15 -> 0.044919863 | E39: =Z15+AA15+AB15+AC15+AD15 -> 0.049286226 | F39: =D39/E39 -> 0.91140806 | G39: =(1-(1-D39)^12)*100 -> 42.392669 | H39: =(1-(1-E39)^12)*100 -> 45.474779 | K39: 1 | L39: 1 | M39: 1 | N39: =Z15+AA15+AB15*K39+AC15*L39+AD15*M39 -> 0.049286226 | O39: =100*(1-(1-N39)^12) -> 45.474779 | P39: =D39/N39 -> 0.91140806 | X39: =A39 -> 160.53102 | Y39: =VLOOKUP(ROUNDDOWN(X39,0),'Spline Pre-Adj'!F:G,2,0) -> 8.7434836 | Z39: =Y39*L39 -> 8.7434836 | AC39: =A39 -> 160.53102 | AD39: =VLOOKUP(ROUNDDOWN(AC39,0),'Spline Pre-Adj'!K:L,2,0) -> 5.6662697 | AE39: =AD39*M39 -> 5.6662697
A40: =K16 -> 183.23039 | B40: =AQ16/1000000000 -> 0.80705515 | C40: =AO16 -> 16:175-200 | D40: =E16 -> 0.055653653 | E40: =Z16+AA16+AB16+AC16+AD16 -> 0.055617152 | F40: =D40/E40 -> 1.0006563 | G40: =(1-(1-D40)^12)*100 -> 49.699111 | H40: =(1-(1-E40)^12)*100 -> 49.675776 | K40: 1 | L40: 1 | M40: 1 | N40: =Z16+AA16+AB16*K40+AC16*L40+AD16*M40 -> 0.055617152 | O40: =100*(1-(1-N40)^12) -> 49.675776 | P40: =D40/N40 -> 1.0006563 | X40: =A40 -> 183.23039 | Y40: =VLOOKUP(ROUNDDOWN(X40,0),'Spline Pre-Adj'!F:G,2,0) -> 8.8912891 | Z40: =Y40*L40 -> 8.8912891 | AC40: =A40 -> 183.23039 | AD40: =VLOOKUP(ROUNDDOWN(AC40,0),'Spline Pre-Adj'!K:L,2,0) -> 6.0276934 | AE40: =AD40*M40 -> 6.0276934
A41: =K17 -> 209.2428 | B41: =AQ17/1000000000 -> 0.1394258 | C41: =AO17 -> 17:200-225 | D41: =E17 -> 0.042068089 | E41: =Z17+AA17+AB17+AC17+AD17 -> 0.057727992 | F41: =D41/E41 -> 0.72872948 | G41: =(1-(1-D41)^12)*100 -> 40.294314 | H41: =(1-(1-E41)^12)*100 -> 51.009093 | K41: 1 | L41: 1 | M41: 1.05 | N41: =Z17+AA17+AB17*K41+AC17*L41+AD17*M41 -> 0.060328829 | O41: =100*(1-(1-N41)^12) -> 52.607367 | P41: =D41/N41 -> 0.69731321 | X41: =A41 -> 209.2428 | Y41: =VLOOKUP(ROUNDDOWN(X41,0),'Spline Pre-Adj'!F:G,2,0) -> 8.9 | Z41: =Y41*L41 -> 8.9 | AC41: =A41 -> 209.2428 | AD41: =VLOOKUP(ROUNDDOWN(AC41,0),'Spline Pre-Adj'!K:L,2,0) -> 6.3657669 | AE41: =AD41*M41 -> 6.6840552
A67: WALA [12,24) | C67: BROKER | AS67: tover | AT67: cash | AW67: refi
A68: modelId | B68: SFACTOR_PREPAY_TRACKING_CPR | C68: PREPAY_CPR1 | D68: PREPAY_TRACKING_CPR1 | E68: PREPAY_SMM1 | F68: PREPAY_TRACKING_SMM1 | G68: PCT_LOANTYPE | H68: _ORIGNOTERATE | I68: _ZEROSATO | J68: _SATO | K68: _REFI_INCENTIVE_Fixed | L68: _Fixed_cost | M68: _LOANAGE | N68: _LTV | O68: _CLTV | P68: _AVG_LOANSIZE_SCHAMBALANCE | Q68: _WACLS | R68: _FICO | S68: PCT_ISSECONDLIEN | T68: _OrigCombLTV | U68: PCT_SVC | V68: PCT_TPO | W68: PCT_GEO | X68: PCT_LOANPURPOSE | Y68: PCT_OCC | Z68: curtailsmm | AA68: defaultsmm | AB68: toverSmm | AC68: cashoutSmm | AD68: refiSmm | AE68: cumHPA | AF68: cumHPA05Pct | AG68: cumHPA15Pct | AH68: cumHPA20Pct | AI68: cumHPA25Pct | AJ68: cumHPA30Pct | AK68: cumHPA35Pct | AL68: cumHPA40Pct | AM68: adjtoverSmm | AN68: adjRefiSmm | AO68: groupByColumn | AP68: curve | AQ68: Balance | AR68: LoanCount | AS68: PCT_BROKER | AT68: PCT_CORRES | AU68: PCT_NonRETAIL | AV68: PCT_RETAIL | AW68: PCT_CashWindow | AX68: PCT_NonCashWindow
A69: 4.3 | B69: 0.99354299 | C69: 3.4433222 | D69: 7.4790735 | E69: 0.0029157422 | F69: 0.0064570079 | G69: 0 | H69: 3.9622665 | I69: 4.1506701 | J69: -55.102824 | K69: -57.170377 | L69: 18.591369 | M69: 15.604608 | N69: 77.726934 | O69: 75.492093 | P69: 267072.12 | Q69: 193404.05 | R69: 774.87434 | S69: 0 | T69: 0 | U69: 0.089424414 | V69: 0 | W69: 0 | X69: 0.58543282 | Y69: 0 | Z69: 0.00067107958 | AA69: 7.5421688e-05 | AB69: 0.0025087098 | AC69: 2.9446125e-08 | AD69: 0.0032017562 | AE69: -0.025268185 | AF69: 0.99001879 | AG69: 0.99720024 | AH69: 1 | AI69: 1 | AJ69: 1 | AK69: 1 | AL69: 1 | AM69: 0 | AN69: 0 | AO69: 06:-75--50 | AP69: =-75--50 -> -25 | AQ69: 22048061 | AR69: 114 | AS69: 100 | AT69: 0 | AU69: 100 | AV69: 0 | AW69: 0 | AX69: 0
A70: 4.3 | B70: 0.9934404 | C70: 2.6756426 | D70: 7.5936475 | E70: 0.0022575225 | F70: 0.0065595963 | G70: 0 | H70: 3.91998 | I70: 4.1424648 | J70: -57.659948 | K70: -32.594271 | L70: 14.98906 | M70: 15.424298 | N70: 73.798811 | O70: 72.801415 | P70: 293064.03 | Q70: 263371.78 | R70: 784.82056 | S70: 0 | T70: 0 | U70: 0.08318706 | V70: 0 | W70: 0 | X70: 0.63466923 | Y70: 0 | Z70: 0.00042337918 | AA70: 5.4947755e-05 | AB70: 0.0024369602 | AC70: 1.9932865e-08 | AD70: 0.0036442753 | AE70: -0.020683738 | AF70: 0.98301074 | AG70: 0.99723916 | AH70: 1 | AI70: 1 | AJ70: 1 | AK70: 1 | AL70: 1 | AM70: 0 | AN70: 0 | AO70: 07:-50--25 | AP70: =-50--25 -> -25 | AQ70: 2.4835959e+08 | AR70: 943 | AS70: 100 | AT70: 0 | AU70: 100 | AV70: 0 | AW70: 0 | AX70: 0
A71: 4.3 | B71: 0.99114739 | C71: 10.4129 | D71: 10.120865 | E71: 0.009121383 | F71: 0.0088526127 | G71: 0 | H71: 4.0056311 | I71: 4.1464708 | J71: -49.381152 | K71: -22.225236 | L71: 15.001395 | M71: 15.369031 | N71: 72.626371 | O71: 71.694031 | P71: 289969.09 | Q71: 264789.1 | R71: 783.23381 | S71: 0 | T71: 0 | U71: 0.13071171 | V71: 0 | W71: 0 | X71: 0.67358073 | Y71: 0 | Z71: 0.00038794505 | AA71: 4.9048207e-05 | AB71: 0.0024405504 | AC71: 0 | AD71: 0.0059750552 | AE71: -0.018393852 | AF71: 0.9873345 | AG71: 1 | AH71: 1 | AI71: 1 | AJ71: 1 | AK71: 1 | AL71: 1 | AM71: 0 | AN71: 0 | AO71: 08-1:-25--20 | AP71: =-25--20 -> -5 | AQ71: 1.4060301e+08 | AR71: 531 | AS71: 100 | AT71: 0 | AU71: 100 | AV71: 0 | AW71: 0 | AX71: 0
A72: 4.3 | B72: 0.98979274 | C72: 16.327212 | D72: 11.583934 | E72: 0.014744912 | F72: 0.010207256 | G72: 0 | H72: 4.0383236 | I72: 4.1330423 | J72: -46.267664 | K72: -17.313489 | L72: 14.569381 | M72: 15.678942 | N72: 73.0143 | O72: 72.085273 | P72: 296555.33 | Q72: 272242.23 | R72: 783.43081 | S72: 0 | T72: 0 | U72: 0.134467 | V72: 0 | W72: 0 | X72: 0.66383613 | Y72: 0 | Z72: 0.0003778521 | AA72: 5.8955725e-05 | AB72: 0.0024977375 | AC72: 3.2103869e-08 | AD72: 0.0072726643 | AE72: -0.016843218 | AF72: 0.96713315 | AG72: 0.99591957 | AH72: 1 | AI72: 1 | AJ72: 1 | AK72: 1 | AL72: 1 | AM72: 0 | AN72: 0 | AO72: 08-2:-20--15 | AP72: =-20--15 -> -5 | AQ72: 2.2895571e+08 | AR72: 841 | AS72: 100 | AT72: 0 | AU72: 100 | AV72: 0 | AW72: 0 | AX72: 0
A73: 4.3 | B73: 0.98884467 | C73: 9.7157195 | D73: 12.594869 | E73: 0.0084810662 | F73: 0.011155329 | G73: 0 | H73: 4.0757363 | I73: 4.1303029 | J73: -42.500846 | K73: -12.328418 | L73: 14.682354 | M73: 15.838804 | N73: 72.147826 | O73: 71.155493 | P73: 293625.38 | Q73: 271091.4 | R73: 782.50929 | S73: 0 | T73: 0 | U73: 0.15588411 | V73: 0 | W73: 0 | X73: 0.69472941 | Y73: 0 | Z73: 0.00037919395 | AA73: 6.1978133e-05 | AB73: 0.0025449369 | AC73: 8.5692111e-08 | AD73: 0.0081691196 | AE73: -0.01640918 | AF73: 0.96452549 | AG73: 0.9979631 | AH73: 0.9998021 | AI73: 1 | AJ73: 1 | AK73: 1 | AL73: 1 | AM73: 0 | AN73: 0 | AO73: 08-3:-15--10 | AP73: =-15--10 -> -5 | AQ73: 3.624492e+08 | AR73: 1337 | AS73: 100 | AT73: 0 | AU73: 100 | AV73: 0 | AW73: 0 | AX73: 0
A74: 4.3 | B74: 0.98779298 | C74: 15.287748 | D74: 13.703891 | E74: 0.013730691 | F74: 0.012207022 | G74: 0 | H74: 4.1210596 | I74: 4.127226 | J74: -38.363445 | K74: -7.3315214 | L74: 14.347284 | M74: 15.740577 | N74: 72.613089 | O74: 71.694586 | P74: 300052.43 | Q74: 277205.63 | R74: 783.22406 | S74: 0 | T74: 0 | U74: 0.16411247 | V74: 0 | W74: 0 | X74: 0.72120807 | Y74: 0 | Z74: 0.00037482514 | AA74: 6.5203385e-05 | AB74: 0.0024447642 | AC74: 1.272374e-07 | AD74: 0.009322088 | AE74: -0.016271324 | AF74: 0.95586068 | AG74: 0.99045932 | AH74: 0.99964698 | AI74: 1 | AJ74: 1 | AK74: 1 | AL74: 1 | AM74: 0 | AN74: 0 | AO74: 08-4:-10--5 | AP74: =-10--5 -> -5 | AQ74: 5.3278923e+08 | AR74: 1922 | AS74: 100 | AT74: 0 | AU74: 100 | AV74: 0 | AW74: 0 | AX74: 0
A75: 4.3 | B75: 0.98690485 | C75: 16.375859 | D75: 14.630372 | E75: 0.014792659 | F75: 0.013095151 | G75: 0 | H75: 4.1314347 | I75: 4.1102186 | J75: -36.632177 | K75: -2.3191468 | L75: 14.452482 | M75: 16.00508 | N75: 71.560578 | O75: 70.429676 | P75: 297998.43 | Q75: 275476.6 | R75: 782.23605 | S75: 0 | T75: 0 | U75: 0.17746345 | V75: 0 | W75: 0 | X75: 0.73875801 | Y75: 0 | Z75: 0.00037364519 | AA75: 6.2122678e-05 | AB75: 0.0025410424 | AC75: 1.7955359e-07 | AD75: 0.010118147 | AE75: -0.013516869 | AF75: 0.95282617 | AG75: 0.99193703 | AH75: 0.99953901 | AI75: 1 | AJ75: 1 | AK75: 1 | AL75: 1 | AM75: 0 | AN75: 0 | AO75: 08:-25-0 | AP75: =-25-0 -> -25 | AQ75: 7.6031541e+08 | AR75: 2760 | AS75: 100 | AT75: 0 | AU75: 100 | AV75: 0 | AW75: 0 | AX75: 0
A76: 4.3 | B76: 0.98607597 | C76: 19.687584 | D76: 15.486804 | E76: 0.018104603 | F76: 0.013924026 | G76: 0 | H76: 4.1517844 | I76: 4.0977448 | J76: -33.812386 | K76: 2.6430066 | L76: 14.54813 | M76: 16.001209 | N76: 71.288535 | O76: 69.986831 | P76: 295420.67 | Q76: 274102.53 | R76: 782.29454 | S76: 0 | T76: 0 | U76: 0.21018906 | V76: 0 | W76: 0 | X76: 0.7699831 | Y76: 0 | Z76: 0.00037109638 | AA76: 6.0870482e-05 | AB76: 0.002586356 | AC76: 2.6634901e-07 | AD76: 0.010905422 | AE76: -0.010435831 | AF76: 0.93427976 | AG76: 0.98967223 | AH76: 0.99904342 | AI76: 1 | AJ76: 1 | AK76: 1 | AL76: 1 | AM76: 0 | AN76: 0 | AO76: 09-1:0-5 | AP76: 0-5 | AQ76: 1.0166463e+09 | AR76: 3709 | AS76: 100 | AT76: 0 | AU76: 100 | AV76: 0 | AW76: 0 | AX76: 0
A77: 4.3 | B77: 0.98509336 | C77: 25.482693 | D77: 16.491878 | E77: 0.024213596 | F77: 0.014906637 | G77: 0 | H77: 4.1660401 | I77: 4.0831096 | J77: -31.684568 | K77: 7.6035452 | L77: 14.719348 | M77: 15.871484 | N77: 70.830485 | O77: 69.390702 | P77: 292401.82 | Q77: 270951.32 | R77: 782.93256 | S77: 0 | T77: 0 | U77: 0.21637457 | V77: 0 | W77: 0 | X77: 0.79015276 | Y77: 0 | Z77: 0.00036986603 | AA77: 6.5498002e-05 | AB77: 0.002650548 | AC77: 1.2229032e-06 | AD77: 0.011819488 | AE77: -0.0074182861 | AF77: 0.90573507 | AG77: 0.98038878 | AH77: 0.99650189 | AI77: 0.99974512 | AJ77: 1 | AK77: 1 | AL77: 1 | AM77: 0 | AN77: 0 | AO77: 09-2:5-10 | AP77: 43230 | AQ77: 1.4216816e+09 | AR77: 5247 | AS77: 100 | AT77: 0 | AU77: 100 | AV77: 0 | AW77: 0 | AX77: 0
A78: 4.3 | B78: 0.98402391 | C78: 23.497805 | D78: 17.573316 | E78: 0.022073628 | F78: 0.015976087 | G78: 0 | H78: 4.1562696 | I78: 4.0588919 | J78: -30.989792 | K78: 12.65754 | L78: 14.63845 | M78: 15.747708 | N78: 68.698019 | O78: 66.822244 | P78: 293042.97 | Q78: 272589.53 | R78: 783.73442 | S78: 0 | T78: 0 | U78: 0.22099417 | V78: 0 | W78: 0 | X78: 0.8029593 | Y78: 0 | Z78: 0.0003718002 | AA78: 5.8591214e-05 | AB78: 0.0027388251 | AC78: 1.3899832e-06 | AD78: 0.012805466 | AE78: -0.0018176758 | AF78: 0.86679245 | AG78: 0.97005702 | AH78: 0.99735728 | AI78: 0.99980647 | AJ78: 1 | AK78: 1 | AL78: 1 | AM78: 0 | AN78: 0 | AO78: 09-3:10-15 | AP78: 43388 | AQ78: 1.9689142e+09 | AR78: 7223 | AS78: 100 | AT78: 0 | AU78: 100 | AV78: 0 | AW78: 0 | AX78: 0
A79: 4.3 | B79: 0.98271495 | C79: 26.524161 | D79: 18.879477 | E79: 0.025357423 | F79: 0.017285053 | G79: 0 | H79: 4.1530601 | I79: 4.029587 | J79: -29.603562 | K79: 17.627773 | L79: 14.345931 | M79: 15.681866 | N79: 67.641646 | O79: 65.389675 | P79: 299018.7 | Q79: 278252.99 | R79: 783.70556 | S79: 0 | T79: 0 | U79: 0.23738472 | V79: 0 | W79: 0 | X79: 0.82353725 | Y79: 0 | Z79: 0.00036940555 | AA79: 5.9284044e-05 | AB79: 0.0027942855 | AC79: 3.438017e-06 | AD79: 0.014058626 | AE79: 0.0059045285 | AF79: 0.81933774 | AG79: 0.94164354 | AH79: 0.99355979 | AI79: 0.99873942 | AJ79: 1 | AK79: 1 | AL79: 1 | AM79: 0 | AN79: 0 | AO79: 09-4:15-20 | AP79: 15-20 | AQ79: 2.8518149e+09 | AR79: 10249 | AS79: 100 | AT79: 0 | AU79: 100 | AV79: 0 | AW79: 0 | AX79: 0
A80: 4.3 | B80: 0.98117648 | C80: 31.654387 | D80: 20.390378 | E80: 0.031218389 | F80: 0.018823518 | G80: 0 | H80: 4.1440758 | I80: 3.9906015 | J80: -29.254195 | K80: 22.607392 | L80: 14.04734 | M80: 15.768042 | N80: 66.042586 | O80: 63.482964 | P80: 303633.81 | Q80: 284171.51 | R80: 784.09369 | S80: 0 | T80: 0 | U80: 0.24906418 | V80: 0 | W80: 0 | X80: 0.84454282 | Y80: 0 | Z80: 0.0003685708 | AA80: 5.5404351e-05 | AB80: 0.0028752081 | AC80: 5.0147786e-06 | AD80: 0.015519305 | AE80: 0.013382773 | AF80: 0.77659831 | AG80: 0.92865681 | AH80: 0.99357381 | AI80: 0.99835818 | AJ80: 1 | AK80: 1 | AL80: 1 | AM80: 0 | AN80: 0 | AO80: 09:0-25 | AP80: 0-25 | AQ80: 3.7300352e+09 | AR80: 13126 | AS80: 100 | AT80: 0 | AU80: 100 | AV80: 0 | AW80: 0 | AX80: 0
A81: 4.3 | B81: 0.97958559 | C81: 35.607025 | D81: 21.9256 | E81: 0.036015892 | F81: 0.02041441 | G81: 0 | H81: 4.1488824 | I81: 3.9558327 | J81: -28.41872 | K81: 27.551558 | L81: 13.875966 | M81: 15.91216 | N81: 65.451313 | O81: 62.276792 | P81: 306524.88 | Q81: 287674.79 | R81: 783.74499 | S81: 0 | T81: 0 | U81: 0.25128253 | V81: 0 | W81: 0 | X81: 0.83761005 | Y81: 0 | Z81: 0.00036798501 | AA81: 5.6429608e-05 | AB81: 0.0029631966 | AC81: 7.8325676e-06 | AD81: 0.017018952 | AE81: 0.021637976 | AF81: 0.72985208 | AG81: 0.9143319 | AH81: 0.9907379 | AI81: 0.99732016 | AJ81: 1 | AK81: 1 | AL81: 1 | AM81: 0 | AN81: 0 | AO81: 10-1:25-30 | AP81: 25-30 | AQ81: 4.1942984e+09 | AR81: 14580 | AS81: 100 | AT81: 0 | AU81: 100 | AV81: 0 | AW81: 0 | AX81: 0
A82: 4.3 | B82: 0.97762089 | C82: 37.323822 | D82: 23.784084 | E82: 0.03818427 | F82: 0.022379111 | G82: 0 | H82: 4.1449306 | I82: 3.9132314 | J82: -27.955655 | K82: 32.507572 | L82: 13.642876 | M82: 15.962654 | N82: 64.847443 | O82: 61.414253 | P82: 311923.5 | Q82: 292598.31 | R82: 784.15694 | S82: 0 | T82: 0 | U82: 0.26742243 | V82: 0 | W82: 0 | X82: 0.84908746 | Y82: 0 | Z82: 0.00036773544 | AA82: 5.5855843e-05 | AB82: 0.0030163828 | AC82: 1.0126984e-05 | AD82: 0.018928996 | AE82: 0.03067424 | AF82: 0.68618123 | AG82: 0.88073868 | AH82: 0.99076274 | AI82: 0.99814482 | AJ82: 1 | AK82: 1 | AL82: 1 | AM82: 0 | AN82: 0 | AO82: 10-2:30-35 | AP82: 30-35 | AQ82: 4.6090086e+09 | AR82: 15752 | AS82: 100 | AT82: 0 | AU82: 100 | AV82: 0 | AW82: 0 | AX82: 0
A83: 4.3 | B83: 0.97562859 | C83: 39.422265 | D83: 25.627189 | E83: 0.040909876 | F83: 0.024371415 | G83: 0 | H83: 4.1575 | I83: 3.8758481 | J83: -27.282079 | K83: 37.485856 | L83: 13.675113 | M83: 16.087235 | N83: 64.96033 | O83: 61.114395 | P83: 310538.01 | Q83: 291917.76 | R83: 783.83983 | S83: 0 | T83: 0 | U83: 0.27334866 | V83: 0 | W83: 0 | X83: 0.83771013 | Y83: 0 | Z83: 0.00036763567 | AA83: 5.5545911e-05 | AB83: 0.0030822935 | AC83: 1.112484e-05 | AD83: 0.0208548 | AE83: 0.034185625 | AF83: 0.65812777 | AG83: 0.90372181 | AH83: 0.98772338 | AI83: 0.99858713 | AJ83: 1 | AK83: 1 | AL83: 1 | AM83: 0 | AN83: 0 | AO83: 10-3:35-40 | AP83: 35-40 | AQ83: 4.6146359e+09 | AR83: 15808 | AS83: 100 | AT83: 0 | AU83: 100 | AV83: 0 | AW83: 0 | AX83: 0
A84: 4.3 | B84: 0.97335776 | C84: 42.85163 | D84: 27.678076 | E84: 0.045556289 | F84: 0.026642235 | G84: 0 | H84: 4.1804969 | I84: 3.8486214 | J84: -26.294688 | K84: 42.427567 | L84: 13.529293 | M84: 16.230831 | N84: 65.010229 | O84: 60.85364 | P84: 314224.05 | Q84: 295056.64 | R84: 783.80426 | S84: 0 | T84: 0 | U84: 0.27995379 | V84: 0 | W84: 0 | X84: 0.83995941 | Y84: 0 | Z84: 0.00036887805 | AA84: 5.7180759e-05 | AB84: 0.0031595858 | AC84: 1.2299865e-05 | AD84: 0.023044277 | AE84: 0.041430168 | AF84: 0.61560436 | AG84: 0.88694006 | AH84: 0.98763913 | AI84: 0.99894611 | AJ84: 1 | AK84: 1 | AL84: 1 | AM84: 0 | AN84: 0 | AO84: 10-4:40-45 | AP84: 40-45 | AQ84: 4.3945736e+09 | AR84: 14894 | AS84: 100 | AT84: 0 | AU84: 100 | AV84: 0 | AW84: 0 | AX84: 0
A85: 4.3 | B85: 0.97126103 | C85: 42.173965 | D85: 29.525572 | E85: 0.044618228 | F85: 0.028738971 | G85: 0 | H85: 4.2226815 | I85: 3.8404032 | J85: -24.521783 | K85: 47.513898 | L85: 13.470474 | M85: 16.581736 | N85: 63.91363 | O85: 59.773021 | P85: 316303.18 | Q85: 296336.7 | R85: 783.58946 | S85: 0 | T85: 0 | U85: 0.26510018 | V85: 0 | W85: 0 | X85: 0.83477354 | Y85: 0 | Z85: 0.0003689068 | AA85: 6.4238087e-05 | AB85: 0.0032042264 | AC85: 1.1290066e-05 | AD85: 0.025090295 | AE85: 0.044452823 | AF85: 0.60785132 | AG85: 0.89822598 | AH85: 0.98883202 | AI85: 0.99881407 | AJ85: 1 | AK85: 1 | AL85: 1 | AM85: 0 | AN85: 0 | AO85: 10:25-50 | AP85: 25-50 | AQ85: 4.1116717e+09 | AR85: 13875 | AS85: 100 | AT85: 0 | AU85: 100 | AV85: 0 | AW85: 0 | AX85: 0
A86: 4.3 | B86: 0.97029305 | C86: 45.416321 | D86: 30.363807 | E86: 0.049201326 | F86: 0.029706955 | G86: 0 | H86: 4.3267142 | I86: 3.8649364 | J86: -20.628806 | K86: 52.530043 | L86: 14.08948 | M86: 17.252689 | N86: 68.131359 | O86: 64.176219 | P86: 302729.6 | Q86: 283356.21 | R86: 782.48628 | S86: 0 | T86: 0 | U86: 0.23333304 | V86: 0 | W86: 0 | X86: 0.7870467 | Y86: 0 | Z86: 0.00037000114 | AA86: 7.5091657e-05 | AB86: 0.0032668174 | AC86: 9.0902946e-06 | AD86: 0.02598594 | AE86: 0.032244581 | AF86: 0.65735949 | AG86: 0.92632931 | AH86: 0.99215317 | AI86: 0.99923172 | AJ86: 1 | AK86: 1 | AL86: 1 | AM86: 0 | AN86: 0 | AO86: 11-1:50-55 | AP86: 50-55 | AQ86: 3.4917986e+09 | AR86: 12323 | AS86: 100 | AT86: 0 | AU86: 100 | AV86: 0 | AW86: 0 | AX86: 0
A87: 4.3 | B87: 0.96871222 | C87: 46.399305 | D87: 31.713113 | E87: 0.050640133 | F87: 0.031287784 | G87: 0 | H87: 4.382941 | I87: 3.8727884 | J87: -19.498244 | K87: 57.490347 | L87: 14.197381 | M87: 17.577599 | N87: 66.816573 | O87: 63.192341 | P87: 300595.3 | Q87: 281207.08 | R87: 782.67167 | S87: 0 | T87: 0 | U87: 0.23698634 | V87: 0 | W87: 0 | X87: 0.79252906 | Y87: 0 | Z87: 0.0003711292 | AA87: 8.3364331e-05 | AB87: 0.0032570608 | AC87: 8.9461004e-06 | AD87: 0.02756727 | AE87: 0.029179085 | AF87: 0.6723862 | AG87: 0.93064555 | AH87: 0.99231653 | AI87: 0.99932758 | AJ87: 1 | AK87: 1 | AL87: 1 | AM87: 0 | AN87: 0 | AO87: 11-2:55-60 | AP87: 55-60 | AQ87: 3.4723451e+09 | AR87: 12348 | AS87: 100 | AT87: 0 | AU87: 100 | AV87: 0 | AW87: 0 | AX87: 0
A88: 4.3 | B88: 0.96725828 | C88: 48.031872 | D88: 32.932909 | E88: 0.05308407 | F88: 0.032741721 | G88: 0 | H88: 4.4581157 | I88: 3.8934248 | J88: -17.466896 | K88: 62.445765 | L88: 14.300568 | M88: 17.781663 | N88: 67.385529 | O88: 63.98751 | P88: 299369.62 | Q88: 279185.33 | R88: 782.15544 | S88: 0 | T88: 0 | U88: 0.24019832 | V88: 0 | W88: 0 | X88: 0.76128986 | Y88: 0 | Z88: 0.00037200654 | AA88: 9.0873366e-05 | AB88: 0.0032466414 | AC88: 8.683064e-06 | AD88: 0.029023502 | AE88: 0.022881954 | AF88: 0.69989846 | AG88: 0.95775874 | AH88: 0.99397754 | AI88: 0.9989099 | AJ88: 1 | AK88: 1 | AL88: 1 | AM88: 0 | AN88: 0 | AO88: 11-3:60-65 | AP88: 60-65 | AQ88: 3.4401217e+09 | AR88: 12322 | AS88: 100 | AT88: 0 | AU88: 100 | AV88: 0 | AW88: 0 | AX88: 0
A89: 4.3 | B89: 0.96641777 | C89: 48.254009 | D89: 33.628921 | E89: 0.053422031 | F89: 0.033582231 | G89: 0 | H89: 4.5355861 | I89: 3.9208721 | J89: -15.801698 | K89: 67.457834 | L89: 14.413448 | M89: 17.825331 | N89: 67.423102 | O89: 64.252074 | P89: 297328.19 | Q89: 277005.98 | R89: 781.66757 | S89: 0 | T89: 0 | U89: 0.25027157 | V89: 0 | W89: 0 | X89: 0.73971916 | Y89: 0 | Z89: 0.00037256355 | AA89: 9.7906782e-05 | AB89: 0.0032233661 | AC89: 9.0391997e-06 | AD89: 0.029879341 | AE89: 0.018237857 | AF89: 0.71472042 | AG89: 0.9560688 | AH89: 0.99441305 | AI89: 0.99899003 | AJ89: 1 | AK89: 1 | AL89: 1 | AM89: 0 | AN89: 0 | AO89: 11-4:65-70 | AP89: 65-70 | AQ89: 3.4622977e+09 | AR89: 12499 | AS89: 100 | AT89: 0 | AU89: 100 | AV89: 0 | AW89: 0 | AX89: 0
A90: 4.3 | B90: 0.96477575 | C90: 47.942948 | D90: 34.969582 | E90: 0.052949152 | F90: 0.03522425 | G90: 0 | H90: 4.5705614 | I90: 3.9176833 | J90: -14.774382 | K90: 72.491928 | L90: 14.166186 | M90: 17.678323 | N90: 66.24516 | O90: 62.97083 | P90: 301519.77 | Q90: 281840.82 | R90: 781.82802 | S90: 0 | T90: 0 | U90: 0.26465755 | V90: 0 | W90: 0 | X90: 0.73805059 | Y90: 0 | Z90: 0.00037165407 | AA90: 0.00010008628 | AB90: 0.0032281092 | AC90: 9.9012219e-06 | AD90: 0.031514485 | AE90: 0.021463011 | AF90: 0.68569878 | AG90: 0.95598126 | AH90: 0.99389497 | AI90: 0.9990568 | AJ90: 1 | AK90: 1 | AL90: 1 | AM90: 0 | AN90: 0 | AO90: 11:50-75 | AP90: 50-75 | AQ90: 3.4849618e+09 | AR90: 12365 | AS90: 100 | AT90: 0 | AU90: 100 | AV90: 0 | AW90: 0 | AX90: 0
... A97: 4.3 | B97: 0.94906051 | C97: 46.592588 | D97: 46.601772 | E97: 0.050925887 | F97: 0.050939488 | G97: 0 | H97: 5.321533 | I97: 3.665408 | J97: 30.474314 | K97: 232.6404 | L97: 17.927401 | M97: 20.850682 | N97: 92.695715 | O97: 75.691523 | P97: 246276.83 | Q97: 222772.75 | R97: 788.41159 | S97: 0 | T97: 0 | U97: 0 | V97: 0 | W97: 0 | X97: 0.34002479 | Y97: 0 | Z97: 0.00040339218 | AA97: 4.2794964e-05 | AB97: 0.004240869 | AC97: 0.00068165279 | AD97: 0.045570761 | AE97: 0.17333363 | AF97: 0 | AG97: 0.29883154 | AH97: 0.63135198 | AI97: 0.95367429 | AJ97: 1 | AK97: 1 | AL97: 1 | AM97: 0 | AN97: 0 | AO97: 18:225-250 | AP97: 225-250 | AQ97: 3787136.8 | AR97: 17 | AS97: 100 | AT97: 0 | AU97: 100 | AV97: 0 | AW97: 0 | AX97: 0
L99: elbow | M99: 15bps earlier
L100: Channel Dial | M100: 1.05
K102: turn | L102: cash | M102: refi | R102: turn | W102: cash | AB102: refi
A103: incentive | B103: =AQ68 -> Balance | C103: =AO68 -> groupByColumn | D103: =E68 -> PREPAY_SMM1 | E103: =F68 -> PREPAY_TRACKING_SMM1 | F103: ratio | G103: =C68 -> PREPAY_CPR1 | H103: =D68 -> PREPAY_TRACKING_CPR1 | K103: adj | L103: adj | M103: adj | N103: mdl_smm | O103: mdl_cpr | P103: ratio | R103: x | T103: Knot | U103: adj Knot | W103: x | X103: adj x | Y103: Knot | Z103: adj Knot | AB103: x | AC103: adj x | AD103: Knot | AE103: adj Knot
A104: =K69 -> -57.170377 | B104: =AQ69/1000000000 -> 0.022048061 | C104: =AO69 -> 06:-75--50 | D104: =E69 -> 0.0029157422 | E104: =Z69+AA69+AB69+AC69+AD69 -> 0.0064569967 | F104: =D104/E104 -> 0.45156322 | G104: =(1-(1-D104)^12)*100 -> 3.4433222 | H104: =(1-(1-E104)^12)*100 -> 7.479061 | K104: =VLOOKUP(C104,$C$26:$M$44,9,0) -> 1 | L104: =VLOOKUP(C104,$C$26:$M$44,10,0) -> 1 | M104: =VLOOKUP(C104,$C$26:$M$44,11,0) -> 1 | N104: =Z69+AA69+AB69*K104+AC69*L104+AD69*M104*$M$100 -> 0.0066170845 | O104: =100*(1-(1-N104)^12) -> 7.6577954 | P104: =D104/N104 -> 0.4406385 | S104: =A104 -> -57.170377 | T104: =VLOOKUP(ROUNDDOWN(S104,0),'Spline Pre-Adj'!A:B,2,0) -> 1.2769809 | U104: =T104*K104 -> 1.2769809 | X104: =A104 -> -57.170377 | Y104: =VLOOKUP(ROUNDDOWN(X104,0),'Spline Pre-Adj'!F:G,2,0) -> 0.18383339 | Z104: =Y104*L104 -> 0.18383339 | AC104: =A104 -> -57.170377 | AD104: =VLOOKUP(ROUNDDOWN(AC104,0),'Spline Pre-Adj'!K:L,2,0) -> 0 | AE104: =AD104*M104 -> 0
A105: =K70 -> -32.594271 | B105: =AQ70/1000000000 -> 0.24835959 | C105: =AO70 -> 07:-50--25 | D105: =E70 -> 0.0022575225 | E105: =Z70+AA70+AB70+AC70+AD70 -> 0.0065595824 | F105: =D105/E105 -> 0.34415644 | G105: =(1-(1-D105)^12)*100 -> 2.6756426 | H105: =(1-(1-E105)^12)*100 -> 7.593632 | K105: =VLOOKUP(C105,$C$26:$M$44,9,0) -> 1 | L105: =VLOOKUP(C105,$C$26:$M$44,10,0) -> 1 | M105: =VLOOKUP(C105,$C$26:$M$44,11,0) -> 1 | N105: =Z70+AA70+AB70*K105+AC70*L105+AD70*M105*$M$100 -> 0.0067417961 | O105: =100*(1-(1-N105)^12) -> 7.7968136 | P105: =D105/N105 -> 0.33485476 | S105: =A105 -> -32.594271 | T105: =VLOOKUP(ROUNDDOWN(S105,0),'Spline Pre-Adj'!A:B,2,0) -> 1.287 | U105: =T105*K105 -> 1.287 | X105: =A105 -> -32.594271 | Y105: =VLOOKUP(ROUNDDOWN(X105,0),'Spline Pre-Adj'!F:G,2,0) -> 0.3115 | Z105: =Y105*L105 -> 0.3115 | AC105: =A105 -> -32.594271 | AD105: =VLOOKUP(ROUNDDOWN(AC105,0),'Spline Pre-Adj'!K:L,2,0) -> 0.43003694 | AE105: =AD105*M105 -> 0.43003694
A106: =K71 -> -22.225236 | B106: =AQ71/1000000000 -> 0.14060301 | C106: =AO71 -> 08-1:-25--20 | D106: =E71 -> 0.009121383 | E106: =Z71+AA71+AB71+AC71+AD71 -> 0.0088525988 | F106: =D106/E106 -> 1.0303622 | G106: =(1-(1-D106)^12)*100 -> 10.4129 | H106: =(1-(1-E106)^12)*100 -> 10.12085 | J106: 1 | K106: =IF(ISNA(VLOOKUP(C106,$C$26:$M$44,9,0)),K107, VLOOKUP(C106,$C$26:$M$44,9,0)) -> 1 | L106: =IF(ISNA(VLOOKUP(C106,$C$26:$M$44,10,0)),L107, VLOOKUP(C106,$C$26:$M$44,10,0)) -> 1 | M106: =IF(ISNA(VLOOKUP(C106,$C$26:$M$44,11,0)),($M$111-$M$105)*J106/5+$M$105, VLOOKUP(C106,$C$26:$M$44,11,0)) -> 1.0032 | N106: =Z71+AA71+AB71*K106+AC71*L106+AD74*M109*$M$100 -> 0.012791025 | O106: =100*(1-(1-N106)^12) -> 14.314144 | P106: =D106/N106 -> 0.71310806 | S106: =A106 -> -22.225236 | T106: =VLOOKUP(ROUNDDOWN(S106,0),'Spline Pre-Adj'!A:B,2,0) -> 1.287 | U106: =T106*K106 -> 1.287 | X106: =A106 -> -22.225236 | Y106: =VLOOKUP(ROUNDDOWN(X106,0),'Spline Pre-Adj'!F:G,2,0) -> 0.38089236 | Z106: =Y106*L106 -> 0.38089236 | AC106: =A106 -> -22.225236 | AD106: =VLOOKUP(ROUNDDOWN(AC106,0),'Spline Pre-Adj'!K:L,2,0) -> 0.79645948 | AE106: =AD106*M106 -> 0.79900815
A107: =K72 -> -17.313489 | B107: =AQ72/1000000000 -> 0.22895571 | C107: =AO72 -> 08-2:-20--15 | D107: =E72 -> 0.014744912 | E107: =Z72+AA72+AB72+AC72+AD72 -> 0.010207242 | F107: =D107/E107 -> 1.444554 | G107: =(1-(1-D107)^12)*100 -> 16.327212 | H107: =(1-(1-E107)^12)*100 -> 11.583918 | J107: 2 | K107: =IF(ISNA(VLOOKUP(C107,$C$26:$M$44,9,0)),K108, VLOOKUP(C107,$C$26:$M$44,9,0)) -> 1 | L107: =IF(ISNA(VLOOKUP(C107,$C$26:$M$44,10,0)),L108, VLOOKUP(C107,$C$26:$M$44,10,0)) -> 1 | M107: =IF(ISNA(VLOOKUP(C107,$C$26:$M$44,11,0)),($M$111-$M$105)*J107/5+$M$105, VLOOKUP(C107,$C$26:$M$44,11,0)) -> 1.0064 | N107: =Z72+AA72+AB72*K107+AC72*L107+AD75*M110*$M$100 -> 0.013558632 | O107: =100*(1-(1-N107)^12) -> 15.110237 | P107: =D107/N107 -> 1.0874926 | S107: =A107 -> -17.313489 | T107: =VLOOKUP(ROUNDDOWN(S107,0),'Spline Pre-Adj'!A:B,2,0) -> 1.287 | U107: =T107*K107 -> 1.287 | X107: =A107 -> -17.313489 | Y107: =VLOOKUP(ROUNDDOWN(X107,0),'Spline Pre-Adj'!F:G,2,0) -> 0.43050425 | Z107: =Y107*L107 -> 0.43050425 | AC107: =A107 -> -17.313489 | AD107: =VLOOKUP(ROUNDDOWN(AC107,0),'Spline Pre-Adj'!K:L,2,0) -> 0.95362938 | AE107: =AD107*M107 -> 0.95973261
A108: =K73 -> -12.328418 | B108: =AQ73/1000000000 -> 0.3624492 | C108: =AO73 -> 08-3:-15--10 | D108: =E73 -> 0.0084810662 | E108: =Z73+AA73+AB73+AC73+AD73 -> 0.011155314 | F108: =D108/E108 -> 0.76027138 | G108: =(1-(1-D108)^12)*100 -> 9.7157195 | H108: =(1-(1-E108)^12)*100 -> 12.594853 | J108: 3 | K108: =IF(ISNA(VLOOKUP(C108,$C$26:$M$44,9,0)),K109, VLOOKUP(C108,$C$26:$M$44,9,0)) -> 1 | L108: =IF(ISNA(VLOOKUP(C108,$C$26:$M$44,10,0)),L109, VLOOKUP(C108,$C$26:$M$44,10,0)) -> 1 | M108: =IF(ISNA(VLOOKUP(C108,$C$26:$M$44,11,0)),($M$111-$M$105)*J108/5+$M$105, VLOOKUP(C108,$C$26:$M$44,11,0)) -> 1.0096 | N108: =Z73+AA73+AB73*K108+AC73*L108+AD76*M111*$M$100 -> 0.014620099 | O108: =100*(1-(1-N108)^12) -> 16.199927 | P108: =D108/N108 -> 0.58009635 | S108: =A108 -> -12.328418 | T108: =VLOOKUP(ROUNDDOWN(S108,0),'Spline Pre-Adj'!A:B,2,0) -> 1.287 | U108: =T108*K108 -> 1.287 | X108: =A108 -> -12.328418 | Y108: =VLOOKUP(ROUNDDOWN(X108,0),'Spline Pre-Adj'!F:G,2,0) -> 0.48396475 | Z108: =Y108*L108 -> 0.48396475 | AC108: =A108 -> -12.328418 | AD108: =VLOOKUP(ROUNDDOWN(AC108,0),'Spline Pre-Adj'!K:L,2,0) -> 1.0814264 | AE108: =AD108*M108 -> 1.0918081
A109: =K74 -> -7.3315214 | B109: =AQ74/1000000000 -> 0.53278923 | C109: =AO74 -> 08-4:-10--5 | D109: =E74 -> 0.013730691 | E109: =Z74+AA74+AB74+AC74+AD74 -> 0.012207008 | F109: =D109/E109 -> 1.1248203 | G109: =(1-(1-D109)^12)*100 -> 15.287748 | H109: =(1-(1-E109)^12)*100 -> 13.703876 | J109: 4 | K109: =IF(ISNA(VLOOKUP(C109,$C$26:$M$44,9,0)),K110, VLOOKUP(C109,$C$26:$M$44,9,0)) -> 1 | L109: =IF(ISNA(VLOOKUP(C109,$C$26:$M$44,10,0)),L110, VLOOKUP(C109,$C$26:$M$44,10,0)) -> 1 | M109: =IF(ISNA(VLOOKUP(C109,$C$26:$M$44,11,0)),($M$111-$M$105)*J109/5+$M$105, VLOOKUP(C109,$C$26:$M$44,11,0)) -> 1.0128 | N109: =Z74+AA74+AB74*K109+AC74*L109+AD77*M112*$M$100 -> 0.015692517 | O109: =100*(1-(1-N109)^12) -> 17.287825 | P109: =D109/N109 -> 0.87498333 | S109: =A109 -> -7.3315214 | T109: =VLOOKUP(ROUNDDOWN(S109,0),'Spline Pre-Adj'!A:B,2,0) -> 1.287 | U109: =T109*K109 -> 1.287 | X109: =A109 -> -7.3315214 | Y109: =VLOOKUP(ROUNDDOWN(X109,0),'Spline Pre-Adj'!F:G,2,0) -> 0.54485561 | Z109: =Y109*L109 -> 0.54485561 | AC109: =A109 -> -7.3315214 | AD109: =VLOOKUP(ROUNDDOWN(AC109,0),'Spline Pre-Adj'!K:L,2,0) -> 1.1993278 | AE109: =AD109*M109 -> 1.2146792
A110: =K75 -> -2.3191468 | B110: =AQ75/1000000000 -> 0.76031541 | C110: =AO75 -> 08:-25-0 | D110: =E75 -> 0.014792659 | E110: =Z75+AA75+AB75+AC75+AD75 -> 0.013095137 | F110: =D110/E110 -> 1.1296299 | G110: =(1-(1-D110)^12)*100 -> 16.375859 | H110: =(1-(1-E110)^12)*100 -> 14.630357 | K110: =IF(ISNA(VLOOKUP(C110,$C$26:$M$44,9,0)),K111, VLOOKUP(C110,$C$26:$M$44,9,0)) -> 1 | L110: =IF(ISNA(VLOOKUP(C110,$C$26:$M$44,10,0)),L111, VLOOKUP(C110,$C$26:$M$44,10,0)) -> 1 | M110: =IF(ISNA(VLOOKUP(C110,$C$26:$M$44,11,0)),M111, VLOOKUP(C110,$C$26:$M$44,11,0)) -> 1 | N110: =Z75+AA75+AB75*K110+AC75*L110+AD78*M113*$M$100 -> 0.017068125 | O110: =100*(1-(1-N110)^12) -> 18.664334 | P110: =D110/N110 -> 0.8666833 | S110: =A110 -> -2.3191468 | T110: =VLOOKUP(ROUNDDOWN(S110,0),'Spline Pre-Adj'!A:B,2,0) -> 1.287 | U110: =T110*K110 -> 1.287 | X110: =A110 -> -2.3191468 | Y110: =VLOOKUP(ROUNDDOWN(X110,0),'Spline Pre-Adj'!F:G,2,0) -> 0.61797137 | Z110: =Y110*L110 -> 0.61797137 | AC110: =A110 -> -2.3191468 | AD110: =VLOOKUP(ROUNDDOWN(AC110,0),'Spline Pre-Adj'!K:L,2,0) -> 1.3122379 | AE110: =AD110*M110 -> 1.3122379
A111: =K76 -> 2.6430066 | B111: =AQ76/1000000000 -> 1.0166463 | C111: =AO76 -> 09-1:0-5 | D111: =E76 -> 0.018104603 | E111: =Z76+AA76+AB76+AC76+AD76 -> 0.013924011 | F111: =D111/E111 -> 1.3002433 | G111: =(1-(1-D111)^12)*100 -> 19.687584 | H111: =(1-(1-E111)^12)*100 -> 15.486789 | J111: 1 | K111: =IF(ISNA(VLOOKUP(C111,$C$26:$M$44,9,0)),K112, VLOOKUP(C111,$C$26:$M$44,9,0)) -> 1 | L111: =IF(ISNA(VLOOKUP(C111,$C$26:$M$44,10,0)),L112, VLOOKUP(C111,$C$26:$M$44,10,0)) -> 1 | M111: =IF(ISNA(VLOOKUP(C111,$C$26:$M$44,11,0)),($M$115-$M$110)*J111/5+$M$110, VLOOKUP(C111,$C$26:$M$44,11,0)) -> 1.016 | N111: =Z76+AA76+AB76*K111+AC76*L111+AD79*M114*$M$100 -> 0.018724886 | O111: =100*(1-(1-N111)^12) -> 20.294293 | P111: =D111/N111 -> 0.9668739 | S111: =A111 -> 2.6430066 | T111: =VLOOKUP(ROUNDDOWN(S111,0),'Spline Pre-Adj'!A:B,2,0) -> 1.287 | U111: =T111*K111 -> 1.287 | X111: =A111 -> 2.6430066 | Y111: =VLOOKUP(ROUNDDOWN(X111,0),'Spline Pre-Adj'!F:G,2,0) -> 0.68848781 | Z111: =Y111*L111 -> 0.68848781 | AC111: =A111 -> 2.6430066 | AD111: =VLOOKUP(ROUNDDOWN(AC111,0),'Spline Pre-Adj'!K:L,2,0) -> 1.401848 | AE111: =AD111*M111 -> 1.4242776
A112: =K77 -> 7.6035452 | B112: =AQ77/1000000000 -> 1.4216816 | C112: =AO77 -> 09-2:5-10 | D112: =E77 -> 0.024213596 | E112: =Z77+AA77+AB77+AC77+AD77 -> 0.014906623 | F112: =D112/E112 -> 1.6243515 | G112: =(1-(1-D112)^12)*100 -> 25.482693 | H112: =(1-(1-E112)^12)*100 -> 16.491864 | J112: 2 | K112: =IF(ISNA(VLOOKUP(C112,$C$26:$M$44,9,0)),K113, VLOOKUP(C112,$C$26:$M$44,9,0)) -> 1 | L112: =IF(ISNA(VLOOKUP(C112,$C$26:$M$44,10,0)),L113, VLOOKUP(C112,$C$26:$M$44,10,0)) -> 1 | M112: =IF(ISNA(VLOOKUP(C112,$C$26:$M$44,11,0)),($M$115-$M$110)*J112/5+$M$110, VLOOKUP(C112,$C$26:$M$44,11,0)) -> 1.032 | N112: =Z77+AA77+AB77*K112+AC77*L112+AD80*M115*$M$100 -> 0.020686027 | O112: =100*(1-(1-N112)^12) -> 22.184984 | P112: =D112/N112 -> 1.170529 | S112: =A112 -> 7.6035452 | T112: =VLOOKUP(ROUNDDOWN(S112,0),'Spline Pre-Adj'!A:B,2,0) -> 1.287 | U112: =T112*K112 -> 1.287 | X112: =A112 -> 7.6035452 | Y112: =VLOOKUP(ROUNDDOWN(X112,0),'Spline Pre-Adj'!F:G,2,0) -> 0.79418177 | Z112: =Y112*L112 -> 0.79418177 | AC112: =A112 -> 7.6035452 | AD112: =VLOOKUP(ROUNDDOWN(AC112,0),'Spline Pre-Adj'!K:L,2,0) -> 1.5165579 | AE112: =AD112*M112 -> 1.5650878
A113: =K78 -> 12.65754 | B113: =AQ78/1000000000 -> 1.9689142 | C113: =AO78 -> 09-3:10-15 | D113: =E78 -> 0.022073628 | E113: =Z78+AA78+AB78+AC78+AD78 -> 0.015976073 | F113: =D113/E113 -> 1.381668 | G113: =(1-(1-D113)^12)*100 -> 23.497805 | H113: =(1-(1-E113)^12)*100 -> 17.573301 | J113: 3 | K113: =IF(ISNA(VLOOKUP(C113,$C$26:$M$44,9,0)),K114, VLOOKUP(C113,$C$26:$M$44,9,0)) -> 1 | L113: =IF(ISNA(VLOOKUP(C113,$C$26:$M$44,10,0)),L114, VLOOKUP(C113,$C$26:$M$44,10,0)) -> 1 | M113: =IF(ISNA(VLOOKUP(C113,$C$26:$M$44,11,0)),($M$115-$M$110)*J113/5+$M$110, VLOOKUP(C113,$C$26:$M$44,11,0)) -> 1.048 | N113: =Z78+AA78+AB78*K113+AC78*L113+AD81*M116*$M$100 -> 0.023506552 | O113: =100*(1-(1-N113)^12) -> 24.832171 | P113: =D113/N113 -> 0.93904154 | S113: =A113 -> 12.65754 | T113: =VLOOKUP(ROUNDDOWN(S113,0),'Spline Pre-Adj'!A:B,2,0) -> 1.287 | U113: =T113*K113 -> 1.287 | X113: =A113 -> 12.65754 | Y113: =VLOOKUP(ROUNDDOWN(X113,0),'Spline Pre-Adj'!F:G,2,0) -> 0.91120039 | Z113: =Y113*L113 -> 0.91120039 | AC113: =A113 -> 12.65754 | AD113: =VLOOKUP(ROUNDDOWN(AC113,0),'Spline Pre-Adj'!K:L,2,0) -> 1.6382588 | AE113: =AD113*M113 -> 1.7168952
A114: =K79 -> 17.627773 | B114: =AQ79/1000000000 -> 2.8518149 | C114: =AO79 -> 09-4:15-20 | D114: =E79 -> 0.025357423 | E114: =Z79+AA79+AB79+AC79+AD79 -> 0.017285039 | F114: =D114/E114 -> 1.4670157 | G114: =(1-(1-D114)^12)*100 -> 26.524161 | H114: =(1-(1-E114)^12)*100 -> 18.879463 | J114: 4 | K114: =IF(ISNA(VLOOKUP(C114,$C$26:$M$44,9,0)),K115, VLOOKUP(C114,$C$26:$M$44,9,0)) -> 1 | L114: =IF(ISNA(VLOOKUP(C114,$C$26:$M$44,10,0)),L115, VLOOKUP(C114,$C$26:$M$44,10,0)) -> 1 | M114: =IF(ISNA(VLOOKUP(C114,$C$26:$M$44,11,0)),($M$115-$M$110)*J114/5+$M$110, VLOOKUP(C114,$C$26:$M$44,11,0)) -> 1.064 | N114: =Z79+AA79+AB79*K114+AC79*L114+AD82*M117*$M$100 -> 0.026997446 | O114: =100*(1-(1-N114)^12) -> 27.994153 | P114: =D114/N114 -> 0.93925266 | X114: =A114 -> 17.627773 | Y114: =VLOOKUP(ROUNDDOWN(X114,0),'Spline Pre-Adj'!F:G,2,0) -> 1.044224 | Z114: =Y114*L114 -> 1.044224 | AC114: =A114 -> 17.627773 | AD114: =VLOOKUP(ROUNDDOWN(AC114,0),'Spline Pre-Adj'!K:L,2,0) -> 1.77123 | AE114: =AD114*M114 -> 1.8845888
A115: =K80 -> 22.607392 | B115: =AQ80/1000000000 -> 3.7300352 | C115: =AO80 -> 09:0-25 | D115: =E80 -> 0.031218389 | E115: =Z80+AA80+AB80+AC80+AD80 -> 0.018823503 | F115: =D115/E115 -> 1.6584792 | G115: =(1-(1-D115)^12)*100 -> 31.654387 | H115: =(1-(1-E115)^12)*100 -> 20.390364 | K115: =IF(ISNA(VLOOKUP(C115,$C$26:$M$44,9,0)),K116, VLOOKUP(C115,$C$26:$M$44,9,0)) -> 1 | L115: =IF(ISNA(VLOOKUP(C115,$C$26:$M$44,10,0)),L116, VLOOKUP(C115,$C$26:$M$44,10,0)) -> 1 | M115: =IF(ISNA(VLOOKUP(C115,$C$26:$M$44,11,0)),M116, VLOOKUP(C115,$C$26:$M$44,11,0)) -> 1.08 | N115: =Z80+AA80+AB80*K115+AC80*L115+AD83*M118*$M$100 -> 0.030763714 | O115: =100*(1-(1-N115)^12) -> 31.268475 | P115: =D115/N115 -> 1.0147796 | X115: =A115 -> 22.607392 | Y115: =VLOOKUP(ROUNDDOWN(X115,0),'Spline Pre-Adj'!F:G,2,0) -> 1.2015373 | Z115: =Y115*L115 -> 1.2015373 | AC115: =A115 -> 22.607392 | AD115: =VLOOKUP(ROUNDDOWN(AC115,0),'Spline Pre-Adj'!K:L,2,0) -> 1.9188346 | AE115: =AD115*M115 -> 2.0723413
A116: =K81 -> 27.551558 | B116: =AQ81/1000000000 -> 4.1942984 | C116: =AO81 -> 10-1:25-30 | D116: =E81 -> 0.036015892 | E116: =Z81+AA81+AB81+AC81+AD81 -> 0.020414395 | F116: =D116/E116 -> 1.76424 | G116: =(1-(1-D116)^12)*100 -> 35.607025 | H116: =(1-(1-E116)^12)*100 -> 21.925586 | J116: 1 | K116: =IF(ISNA(VLOOKUP(C116,$C$26:$M$44,9,0)),K117, VLOOKUP(C116,$C$26:$M$44,9,0)) -> 1 | L116: =IF(ISNA(VLOOKUP(C116,$C$26:$M$44,10,0)),L117, VLOOKUP(C116,$C$26:$M$44,10,0)) -> 1 | M116: =IF(ISNA(VLOOKUP(C116,$C$26:$M$44,11,0)),($M$120-$M$115)*J116/5+$M$115, VLOOKUP(C116,$C$26:$M$44,11,0)) -> 1.138 | N116: =Z81+AA81+AB81*K116+AC81*L116+AD84*M119*$M$100 -> 0.035141239 | O116: =100*(1-(1-N116)^12) -> 34.902406 | P116: =D116/N116 -> 1.0248896 | X116: =A116 -> 27.551558 | Y116: =VLOOKUP(ROUNDDOWN(X116,0),'Spline Pre-Adj'!F:G,2,0) -> 1.3914246 | Z116: =Y116*L116 -> 1.3914246 | AC116: =A116 -> 27.551558 | AD116: =VLOOKUP(ROUNDDOWN(AC116,0),'Spline Pre-Adj'!K:L,2,0) -> 2.0788177 | AE116: =AD116*M116 -> 2.3656946
A117: =K82 -> 32.507572 | B117: =AQ82/1000000000 -> 4.6090086 | C117: =AO82 -> 10-2:30-35 | D117: =E82 -> 0.03818427 | E117: =Z82+AA82+AB82+AC82+AD82 -> 0.022379097 | F117: =D117/E117 -> 1.7062472 | G117: =(1-(1-D117)^12)*100 -> 37.323822 | H117: =(1-(1-E117)^12)*100 -> 23.784071 | J117: 2 | K117: =IF(ISNA(VLOOKUP(C117,$C$26:$M$44,9,0)),K118, VLOOKUP(C117,$C$26:$M$44,9,0)) -> 1 | L117: =IF(ISNA(VLOOKUP(C117,$C$26:$M$44,10,0)),L118, VLOOKUP(C117,$C$26:$M$44,10,0)) -> 1 | M117: =IF(ISNA(VLOOKUP(C117,$C$26:$M$44,11,0)),($M$120-$M$115)*2/5+$M$115, VLOOKUP(C117,$C$26:$M$44,11,0)) -> 1.196 | N117: =Z82+AA82+AB82*K117+AC82*L117+AD85*M120*$M$100 -> 0.039542491 | O117: =100*(1-(1-N117)^12) -> 38.377704 | P117: =D117/N117 -> 0.96565162 | X117: =A117 -> 32.507572 | Y117: =VLOOKUP(ROUNDDOWN(X117,0),'Spline Pre-Adj'!F:G,2,0) -> 1.6233323 | Z117: =Y117*L117 -> 1.6233323 | AC117: =A117 -> 32.507572 | AD117: =VLOOKUP(ROUNDDOWN(AC117,0),'Spline Pre-Adj'!K:L,2,0) -> 2.2487417 | AE117: =AD117*M117 -> 2.689495
A118: =K83 -> 37.485856 | B118: =AQ83/1000000000 -> 4.6146359 | C118: =AO83 -> 10-3:35-40 | D118: =E83 -> 0.040909876 | E118: =Z83+AA83+AB83+AC83+AD83 -> 0.0243714 | F118: =D118/E118 -> 1.6786018 | G118: =(1-(1-D118)^12)*100 -> 39.422265 | H118: =(1-(1-E118)^12)*100 -> 25.627176 | J118: 3 | K118: =IF(ISNA(VLOOKUP(C118,$C$26:$M$44,9,0)),K119, VLOOKUP(C118,$C$26:$M$44,9,0)) -> 1 | L118: =IF(ISNA(VLOOKUP(C118,$C$26:$M$44,10,0)),L119, VLOOKUP(C118,$C$26:$M$44,10,0)) -> 1 | M118: =IF(ISNA(VLOOKUP(C118,$C$26:$M$44,11,0)),($M$120-$M$115)*3/5+$M$115, VLOOKUP(C118,$C$26:$M$44,11,0)) -> 1.254 | N118: =Z83+AA83+AB83*K118+AC83*L118+AD86*M121*$M$100 -> 0.041170227 | O118: =100*(1-(1-N118)^12) -> 39.619301 | P118: =D118/N118 -> 0.99367623 | X118: =A118 -> 37.485856 | Y118: =VLOOKUP(ROUNDDOWN(X118,0),'Spline Pre-Adj'!F:G,2,0) -> 1.8953738 | Z118: =Y118*L118 -> 1.8953738 | AC118: =A118 -> 37.485856 | AD118: =VLOOKUP(ROUNDDOWN(AC118,0),'Spline Pre-Adj'!K:L,2,0) -> 2.4264029 | AE118: =AD118*M118 -> 3.0427093
A119: =K84 -> 42.427567 | B119: =AQ84/1000000000 -> 4.3945736 | C119: =AO84 -> 10-4:40-45 | D119: =E84 -> 0.045556289 | E119: =Z84+AA84+AB84+AC84+AD84 -> 0.026642221 | F119: =D119/E119 -> 1.7099283 | G119: =(1-(1-D119)^12)*100 -> 42.85163 | H119: =(1-(1-E119)^12)*100 -> 27.678063 | J119: 4 | K119: =IF(ISNA(VLOOKUP(C119,$C$26:$M$44,9,0)),K120, VLOOKUP(C119,$C$26:$M$44,9,0)) -> 1 | L119: =IF(ISNA(VLOOKUP(C119,$C$26:$M$44,10,0)),L120, VLOOKUP(C119,$C$26:$M$44,10,0)) -> 1 | M119: =IF(ISNA(VLOOKUP(C119,$C$26:$M$44,11,0)),($M$120-$M$115)*4/5+$M$115, VLOOKUP(C119,$C$26:$M$44,11,0)) -> 1.312 | N119: =Z84+AA84+AB84*K119+AC84*L119+AD87*M122*$M$100 -> 0.043542918 | O119: =100*(1-(1-N119)^12) -> 41.388094 | P119: =D119/N119 -> 1.0462388 | X119: =A119 -> 42.427567 | Y119: =VLOOKUP(ROUNDDOWN(X119,0),'Spline Pre-Adj'!F:G,2,0) -> 2.1927888 | Z119: =Y119*L119 -> 2.1927888 | AC119: =A119 -> 42.427567 | AD119: =VLOOKUP(ROUNDDOWN(AC119,0),'Spline Pre-Adj'!K:L,2,0) -> 2.609598 | AE119: =AD119*M119 -> 3.4237926
A120: =K85 -> 47.513898 | B120: =AQ85/1000000000 -> 4.1116717 | C120: =AO85 -> 10:25-50 | D120: =E85 -> 0.044618228 | E120: =Z85+AA85+AB85+AC85+AD85 -> 0.028738957 | F120: =D120/E120 -> 1.5525347 | G120: =(1-(1-D120)^12)*100 -> 42.173965 | H120: =(1-(1-E120)^12)*100 -> 29.525559 | K120: =IF(ISNA(VLOOKUP(C120,$C$26:$M$44,9,0)),K121, VLOOKUP(C120,$C$26:$M$44,9,0)) -> 1 | L120: =IF(ISNA(VLOOKUP(C120,$C$26:$M$44,10,0)),L121, VLOOKUP(C120,$C$26:$M$44,10,0)) -> 1 | M120: =IF(ISNA(VLOOKUP(C120,$C$26:$M$44,11,0)),M121, VLOOKUP(C120,$C$26:$M$44,11,0)) -> 1.37 | N120: =Z85+AA85+AB85*K120+AC85*L120+AD88*M123*$M$100 -> 0.045703715 | O120: =100*(1-(1-N120)^12) -> 42.957468 | P120: =D120/N120 -> 0.97624947 | X120: =A120 -> 47.513898 | Y120: =VLOOKUP(ROUNDDOWN(X120,0),'Spline Pre-Adj'!F:G,2,0) -> 2.5005892 | Z120: =Y120*L120 -> 2.5005892 | AC120: =A120 -> 47.513898 | AD120: =VLOOKUP(ROUNDDOWN(AC120,0),'Spline Pre-Adj'!K:L,2,0) -> 2.7961235 | AE120: =AD120*M120 -> 3.8306892
A121: =K86 -> 52.530043 | B121: =AQ86/1000000000 -> 3.4917986 | C121: =AO86 -> 11-1:50-55 | D121: =E86 -> 0.049201326 | E121: =Z86+AA86+AB86+AC86+AD86 -> 0.02970694 | F121: =D121/E121 -> 1.6562233 | G121: =(1-(1-D121)^12)*100 -> 45.416321 | H121: =(1-(1-E121)^12)*100 -> 30.363794 | K121: =IF(ISNA(VLOOKUP(C121,$C$26:$M$44,9,0)),K122, VLOOKUP(C121,$C$26:$M$44,9,0)) -> 1 | L121: =IF(ISNA(VLOOKUP(C121,$C$26:$M$44,10,0)),L122, VLOOKUP(C121,$C$26:$M$44,10,0)) -> 1 | M121: =IF(ISNA(VLOOKUP(C121,$C$26:$M$44,11,0)),M122, VLOOKUP(C121,$C$26:$M$44,11,0)) -> 1.38 | N121: =Z86+AA86+AB86*K121+AC86*L121+AD89*M124*$M$100 -> 0.047016165 | O121: =100*(1-(1-N121)^12) -> 43.891791 | P121: =D121/N121 -> 1.0464768 | X121: =A121 -> 52.530043 | Y121: =VLOOKUP(ROUNDDOWN(X121,0),'Spline Pre-Adj'!F:G,2,0) -> 2.8037869 | Z121: =Y121*L121 -> 2.8037869 | AC121: =A121 -> 52.530043 | AD121: =VLOOKUP(ROUNDDOWN(AC121,0),'Spline Pre-Adj'!K:L,2,0) -> 2.983776 | AE121: =AD121*M121 -> 4.1176109
A122: =K87 -> 57.490347 | B122: =AQ87/1000000000 -> 3.4723451 | C122: =AO87 -> 11-2:55-60 | D122: =E87 -> 0.050640133 | E122: =Z87+AA87+AB87+AC87+AD87 -> 0.03128777 | F122: =D122/E122 -> 1.6185281 | G122: =(1-(1-D122)^12)*100 -> 46.399305 | H122: =(1-(1-E122)^12)*100 -> 31.713101 | K122: =IF(ISNA(VLOOKUP(C122,$C$26:$M$44,9,0)),K123, VLOOKUP(C122,$C$26:$M$44,9,0)) -> 1 | L122: =IF(ISNA(VLOOKUP(C122,$C$26:$M$44,10,0)),L123, VLOOKUP(C122,$C$26:$M$44,10,0)) -> 1 | M122: =IF(ISNA(VLOOKUP(C122,$C$26:$M$44,11,0)),M123, VLOOKUP(C122,$C$26:$M$44,11,0)) -> 1.38 | N122: =Z87+AA87+AB87*K122+AC87*L122+AD90*M125*$M$100 -> 0.049384989 | O122: =100*(1-(1-N122)^12) -> 45.542711 | P122: =D122/N122 -> 1.0254155 | X122: =A122 -> 57.490347 | Y122: =VLOOKUP(ROUNDDOWN(X122,0),'Spline Pre-Adj'!F:G,2,0) -> 3.092616 | Z122: =Y122*L122 -> 3.092616 | AC122: =A122 -> 57.490347 | AD122: =VLOOKUP(ROUNDDOWN(AC122,0),'Spline Pre-Adj'!K:L,2,0) -> 3.1703521 | AE122: =AD122*M122 -> 4.3750859
A123: =K88 -> 62.445765 | B123: =AQ88/1000000000 -> 3.4401217 | C123: =AO88 -> 11-3:60-65 | D123: =E88 -> 0.05308407 | E123: =Z88+AA88+AB88+AC88+AD88 -> 0.032741706 | F123: =D123/E123 -> 1.6212982 | G123: =(1-(1-D123)^12)*100 -> 48.031872 | H123: =(1-(1-E123)^12)*100 -> 32.932897 | K123: =IF(ISNA(VLOOKUP(C123,$C$26:$M$44,9,0)),K124, VLOOKUP(C123,$C$26:$M$44,9,0)) -> 1 | L123: =IF(ISNA(VLOOKUP(C123,$C$26:$M$44,10,0)),L124, VLOOKUP(C123,$C$26:$M$44,10,0)) -> 1 | M123: =IF(ISNA(VLOOKUP(C123,$C$26:$M$44,11,0)),M124, VLOOKUP(C123,$C$26:$M$44,11,0)) -> 1.38 | N123: =Z88+AA88+AB88*K123+AC88*L123+AD91*M126*$M$100 -> 0.050383443 | O123: =100*(1-(1-N123)^12) -> 46.225134 | P123: =D123/N123 -> 1.0536015 | X123: =A123 -> 62.445765 | Y123: =VLOOKUP(ROUNDDOWN(X123,0),'Spline Pre-Adj'!F:G,2,0) -> 3.3799458 | Z123: =Y123*L123 -> 3.3799458 | AC123: =A123 -> 62.445765 | AD123: =VLOOKUP(ROUNDDOWN(AC123,0),'Spline Pre-Adj'!K:L,2,0) -> 3.3536482 | AE123: =AD123*M123 -> 4.6280345
A124: =K89 -> 67.457834 | B124: =AQ89/1000000000 -> 3.4622977 | C124: =AO89 -> 11-4:65-70 | D124: =E89 -> 0.053422031 | E124: =Z89+AA89+AB89+AC89+AD89 -> 0.033582216 | F124: =D124/E124 -> 1.5907834 | G124: =(1-(1-D124)^12)*100 -> 48.254009 | H124: =(1-(1-E124)^12)*100 -> 33.628909 | K124: =IF(ISNA(VLOOKUP(C124,$C$26:$M$44,9,0)),K125, VLOOKUP(C124,$C$26:$M$44,9,0)) -> 1 | L124: =IF(ISNA(VLOOKUP(C124,$C$26:$M$44,10,0)),L125, VLOOKUP(C124,$C$26:$M$44,10,0)) -> 1 | M124: =IF(ISNA(VLOOKUP(C124,$C$26:$M$44,11,0)),M125, VLOOKUP(C124,$C$26:$M$44,11,0)) -> 1.38 | N124: =Z89+AA89+AB89*K124+AC89*L124+AD92*M127*$M$100 -> 0.050734878 | O124: =100*(1-(1-N124)^12) -> 46.463461 | P124: =D124/N124 -> 1.0529646 | X124: =A124 -> 67.457834 | Y124: =VLOOKUP(ROUNDDOWN(X124,0),'Spline Pre-Adj'!F:G,2,0) -> 3.6676855 | Z124: =Y124*L124 -> 3.6676855 | AC124: =A124 -> 67.457834 | AD124: =VLOOKUP(ROUNDDOWN(AC124,0),'Spline Pre-Adj'!K:L,2,0) -> 3.531461 | AE124: =AD124*M124 -> 4.8734162
A125: =K90 -> 72.491928 | B125: =AQ90/1000000000 -> 3.4849618 | C125: =AO90 -> 11:50-75 | D125: =E90 -> 0.052949152 | E125: =Z90+AA90+AB90+AC90+AD90 -> 0.035224235 | F125: =D125/E125 -> 1.5032023 | G125: =(1-(1-D125)^12)*100 -> 47.942948 | H125: =(1-(1-E125)^12)*100 -> 34.96957 | K125: =IF(ISNA(VLOOKUP(C125,$C$26:$M$44,9,0)),K126, VLOOKUP(C125,$C$26:$M$44,9,0)) -> 1 | L125: =IF(ISNA(VLOOKUP(C125,$C$26:$M$44,10,0)),L126, VLOOKUP(C125,$C$26:$M$44,10,0)) -> 1 | M125: =IF(ISNA(VLOOKUP(C125,$C$26:$M$44,11,0)),M126, VLOOKUP(C125,$C$26:$M$44,11,0)) -> 1.38 | N125: =Z90+AA90+AB90*K125+AC90*L125+AD93*M128*$M$100 -> 0.052543632 | O125: =100*(1-(1-N125)^12) -> 47.674832 | P125: =D125/N125 -> 1.0077178 | X125: =A125 -> 72.491928 | Y125: =VLOOKUP(ROUNDDOWN(X125,0),'Spline Pre-Adj'!F:G,2,0) -> 3.9558229 | Z125: =Y125*L125 -> 3.9558229 | AC125: =A125 -> 72.491928 | AD125: =VLOOKUP(ROUNDDOWN(AC125,0),'Spline Pre-Adj'!K:L,2,0) -> 3.701587 | AE125: =AD125*M125 -> 5.10819
A126: =K91 -> 85.668971 | B126: =AQ91/1000000000 -> 11.137494 | C126: =AO91 -> 12:75-100 | D126: =E91 -> 0.049717463 | E126: =Z91+AA91+AB91+AC91+AD91 -> 0.038312187 | F126: =D126/E126 -> 1.2976932 | G126: =(1-(1-D126)^12)*100 -> 45.770827 | H126: =(1-(1-E126)^12)*100 -> 37.423776 | K126: =IF(ISNA(VLOOKUP(C126,$C$26:$M$44,9,0)),K127, VLOOKUP(C126,$C$26:$M$44,9,0)) -> 1 | L126: =IF(ISNA(VLOOKUP(C126,$C$26:$M$44,10,0)),L127, VLOOKUP(C126,$C$26:$M$44,10,0)) -> 1 | M126: =IF(ISNA(VLOOKUP(C126,$C$26:$M$44,11,0)),M127, VLOOKUP(C126,$C$26:$M$44,11,0)) -> 1.29 | N126: =Z91+AA91+AB91*K126+AC91*L126+AD91*M126*$M$100 -> 0.050525422 | O126: =100*(1-(1-N126)^12) -> 46.321534 | P126: =D126/N126 -> 0.98400887 | X126: =A126 -> 85.668971 | Y126: =VLOOKUP(ROUNDDOWN(X126,0),'Spline Pre-Adj'!F:G,2,0) -> 4.706786 | Z126: =Y126*L126 -> 4.706786 | AC126: =A126 -> 85.668971 | AD126: =VLOOKUP(ROUNDDOWN(AC126,0),'Spline Pre-Adj'!K:L,2,0) -> 4.0923365 | AE126: =AD126*M126 -> 5.2791141
A127: =K92 -> 111.76843 | B127: =AQ92/1000000000 -> 5.7252288 | C127: =AO92 -> 13:100-125 | D127: =E92 -> 0.049919769 | E127: =Z92+AA92+AB92+AC92+AD92 -> 0.043892225 | F127: =D127/E127 -> 1.137326 | G127: =(1-(1-D127)^12)*100 -> 45.909203 | H127: =(1-(1-E127)^12)*100 -> 41.644446 | K127: =IF(ISNA(VLOOKUP(C127,$C$26:$M$44,9,0)),K128, VLOOKUP(C127,$C$26:$M$44,9,0)) -> 1 | L127: =IF(ISNA(VLOOKUP(C127,$C$26:$M$44,10,0)),L128, VLOOKUP(C127,$C$26:$M$44,10,0)) -> 1 | M127: =IF(ISNA(VLOOKUP(C127,$C$26:$M$44,11,0)),M128, VLOOKUP(C127,$C$26:$M$44,11,0)) -> 1.13 | N127: =Z92+AA92+AB92*K127+AC92*L127+AD92*M127*$M$100 -> 0.05128495 | O127: =100*(1-(1-N127)^12) -> 46.834552 | P127: =D127/N127 -> 0.97338046 | X127: =A127 -> 111.76843 | Y127: =VLOOKUP(ROUNDDOWN(X127,0),'Spline Pre-Adj'!F:G,2,0) -> 6.2168085 | Z127: =Y127*L127 -> 6.2168085 | AC127: =A127 -> 111.76843 | AD127: =VLOOKUP(ROUNDDOWN(AC127,0),'Spline Pre-Adj'!K:L,2,0) -> 4.729914 | AE127: =AD127*M127 -> 5.3448028
A128: =K93 -> 134.37324 | B128: =AQ93/1000000000 -> 2.6208231 | C128: =AO93 -> 14:125-150 | D128: =E93 -> 0.050754696 | E128: =Z93+AA93+AB93+AC93+AD93 -> 0.048607942 | F128: =D128/E128 -> 1.0441647 | G128: =(1-(1-D128)^12)*100 -> 46.476872 | H128: =(1-(1-E128)^12)*100 -> 45.006133 | K128: =IF(ISNA(VLOOKUP(C128,$C$26:$M$44,9,0)),K129, VLOOKUP(C128,$C$26:$M$44,9,0)) -> 1 | L128: =IF(ISNA(VLOOKUP(C128,$C$26:$M$44,10,0)),L129, VLOOKUP(C128,$C$26:$M$44,10,0)) -> 1 | M128: =IF(ISNA(VLOOKUP(C128,$C$26:$M$44,11,0)),M129, VLOOKUP(C128,$C$26:$M$44,11,0)) -> 1.05 | N128: =Z93+AA93+AB93*K128+AC93*L128+AD93*M128*$M$100 -> 0.053148054 | O128: =100*(1-(1-N128)^12) -> 48.073994 | P128: =D128/N128 -> 0.95496811 | X128: =A128 -> 134.37324 | Y128: =VLOOKUP(ROUNDDOWN(X128,0),'Spline Pre-Adj'!F:G,2,0) -> 7.6066289 | Z128: =Y128*L128 -> 7.6066289 | AC128: =A128 -> 134.37324 | AD128: =VLOOKUP(ROUNDDOWN(AC128,0),'Spline Pre-Adj'!K:L,2,0) -> 5.205107 | AE128: =AD128*M128 -> 5.4653623
A129: =K94 -> 160.18516 | B129: =AQ94/1000000000 -> 0.44019782 | C129: =AO94 -> 15:150-175 | D129: =E94 -> 0.047514463 | E129: =Z94+AA94+AB94+AC94+AD94 -> 0.053353304 | F129: =D129/E129 -> 0.89056271 | G129: =(1-(1-D129)^12)*100 -> 44.242836 | H129: =(1-(1-E129)^12)*100 -> 48.208907 | K129: =IF(ISNA(VLOOKUP(C129,$C$26:$M$44,9,0)),K130, VLOOKUP(C129,$C$26:$M$44,9,0)) -> 1 | L129: =IF(ISNA(VLOOKUP(C129,$C$26:$M$44,10,0)),L130, VLOOKUP(C129,$C$26:$M$44,10,0)) -> 1 | M129: =IF(ISNA(VLOOKUP(C129,$C$26:$M$44,11,0)),M130, VLOOKUP(C129,$C$26:$M$44,11,0)) -> 1 | N129: =Z94+AA94+AB94*K129+AC94*L129+AD94*M129*$M$100 -> 0.05578908 | O129: =100*(1-(1-N129)^12) -> 49.785606 | P129: =D129/N129 -> 0.85168035 | X129: =A129 -> 160.18516 | Y129: =VLOOKUP(ROUNDDOWN(X129,0),'Spline Pre-Adj'!F:G,2,0) -> 8.7434836 | Z129: =Y129*L129 -> 8.7434836 | AC129: =A129 -> 160.18516 | AD129: =VLOOKUP(ROUNDDOWN(AC129,0),'Spline Pre-Adj'!K:L,2,0) -> 5.6662697 | AE129: =AD129*M129 -> 5.6662697
A130: =K95 -> 183.9435 | B130: =AQ95/1000000000 -> 0.096630878 | C130: =AO95 -> 16:175-200 | D130: =E95 -> 0.061197489 | E130: =Z95+AA95+AB95+AC95+AD95 -> 0.058191267 | F130: =D130/E130 -> 1.0516611 | G130: =(1-(1-D130)^12)*100 -> 53.130436 | H130: =(1-(1-E130)^12)*100 -> 51.297354 | K130: =IF(ISNA(VLOOKUP(C130,$C$26:$M$44,9,0)),K131, VLOOKUP(C130,$C$26:$M$44,9,0)) -> 1 | L130: =IF(ISNA(VLOOKUP(C130,$C$26:$M$44,10,0)),L131, VLOOKUP(C130,$C$26:$M$44,10,0)) -> 1 | M130: =IF(ISNA(VLOOKUP(C130,$C$26:$M$44,11,0)),M131, VLOOKUP(C130,$C$26:$M$44,11,0)) -> 1 | N130: =Z95+AA95+AB95*K130+AC95*L130+AD95*M130*$M$100 -> 0.060843007 | O130: =100*(1-(1-N130)^12) -> 52.917625 | P130: =D130/N130 -> 1.0058262 | X130: =A130 -> 183.9435 | Y130: =VLOOKUP(ROUNDDOWN(X130,0),'Spline Pre-Adj'!F:G,2,0) -> 8.8912891 | Z130: =Y130*L130 -> 8.8912891 | AC130: =A130 -> 183.9435 | AD130: =VLOOKUP(ROUNDDOWN(AC130,0),'Spline Pre-Adj'!K:L,2,0) -> 6.0276934 | AE130: =AD130*M130 -> 6.0276934
A131: =K96 -> 209.55229 | B131: =AQ96/1000000000 -> 0.020893223 | C131: =AO96 -> 17:200-225 | D131: =E96 -> 0.052273955 | E131: =Z96+AA96+AB96+AC96+AD96 -> 0.05925758 | F131: =D131/E131 -> 0.88214798 | G131: =(1-(1-D131)^12)*100 -> 47.495831 | H131: =(1-(1-E131)^12)*100 -> 51.954941 | K131: =IF(ISNA(VLOOKUP(C131,$C$26:$M$44,9,0)),K132, VLOOKUP(C131,$C$26:$M$44,9,0)) -> 1 | L131: =IF(ISNA(VLOOKUP(C131,$C$26:$M$44,10,0)),L132, VLOOKUP(C131,$C$26:$M$44,10,0)) -> 1 | M131: =IF(ISNA(VLOOKUP(C131,$C$26:$M$44,11,0)),M132, VLOOKUP(C131,$C$26:$M$44,11,0)) -> 1.05 | N131: =Z96+AA96+AB96*K131+AC96*L131+AD96*M131*$M$100 -> 0.064744084 | O131: =100*(1-(1-N131)^12) -> 55.211598 | P131: =D131/N131 -> 0.80739353 | X131: =A131 -> 209.55229 | Y131: =VLOOKUP(ROUNDDOWN(X131,0),'Spline Pre-Adj'!F:G,2,0) -> 8.9 | Z131: =Y131*L131 -> 8.9 | AC131: =A131 -> 209.55229 | AD131: =VLOOKUP(ROUNDDOWN(AC131,0),'Spline Pre-Adj'!K:L,2,0) -> 6.3657669 | AE131: =AD131*M131 -> 6.6840552
I136: Better fit for WALA<24 | K136: 0.75 | L136: 1 | M136: 1
K137: 0.75 | L137: 1 | M137: 1
K138: 0.75 | L138: 1 | M138: 1
K139: 0.64 | L139: 1 | M139: 1
K140: 0.64 | L140: 1 | M140: 0.32
K141: 0.75 | L141: 1 | M141: 0.67
K142: 0.75 | L142: 1 | M142: 1.11
K143: 0.75 | L143: 1 | M143: 1.32
...

Sheet Spline Pre-Adj
A1: spline | B1: conventional_turnover_incentive | F1: spline | G1: conventional_cashout_incentive | K1: spline | L1: conventional_refinance_himedia_incentive
A3: Row Labels | B3: Average of knotValues | F3: Row Labels | G3: Average of knotValues | K3: Row Labels | L3: Average of knotValues
A4: -730 | B4: 0.7314 | F4: -404 | G4: 0 | K4: -196 | L4: 0
A5: -729 | B5: 0.73142 | F5: -403 | G5: 0 | K5: -195 | L5: 0
A6: -728 | B6: 0.73144 | F6: -402 | G6: 0 | K6: -194 | L6: 0
A7: -727 | B7: 0.73146 | F7: -401 | G7: 0 | K7: -193 | L7: 0
A8: -726 | B8: 0.73148 | F8: -400 | G8: 0 | K8: -192 | L8: 0
A9: -725 | B9: 0.7315 | F9: -399 | G9: 0 | K9: -191 | L9: 0
A10: -724 | B10: 0.73152 | F10: -398 | G10: 0 | K10: -190 | L10: 0
A11: -723 | B11: 0.73154 | F11: -397 | G11: 0 | K11: -189 | L11: 0
A12: -722 | B12: 0.73156 | F12: -396 | G12: 0 | K12: -188 | L12: 0
A13: -721 | B13: 0.73158 | F13: -395 | G13: 0 | K13: -187 | L13: 0
A14: -720 | B14: 0.7316 | F14: -394 | G14: 0 | K14: -186 | L14: 0
A15: -719 | B15: 0.73162 | F15: -393 | G15: 0 | K15: -185 | L15: 0
... A564: -170 | B564: 0.887822 | F564: 156 | G564: 8.687382 | K564: 364 | L564: 7.8860159
A565: -169 | B565: 0.88931903 | F565: 157 | G565: 8.7024887 | K565: Grand Total | L565: 3.6232454
A566: -168 | B566: 0.89082605 | F566: 158 | G566: 8.7168624
A567: -167 | B567: 0.89234358 | F567: 159 | G567: 8.7305213
A568: -166 | B568: 0.89387214 | F568: 160 | G568: 8.7434836
A569: -165 | B569: 0.89541225 | F569: 161 | G569: 8.7557675
A570: -164 | B570: 0.89696442 | F570: 162 | G570: 8.7673913
A571: -163 | B571: 0.89852916 | F571: 163 | G571: 8.7783732
A572: -162 | B572: 0.90010699 | F572: 164 | G572: 8.7887314
A573: -161 | B573: 0.90169843 | F573: 165 | G573: 8.7984842
A574: -160 | B574: 0.903304 | F574: 166 | G574: 8.8076498
A575: -159 | B575: 0.90492421 | F575: 167 | G575: 8.8162464
A576: -158 | B576: 0.90655957 | F576: 168 | G576: 8.8242923
A577: -157 | B577: 0.9082106 | F577: 169 | G577: 8.8318057
... A728: -6 | B728: 1.287 | F728: 320 | G728: 8.9
A729: -5 | B729: 1.287 | F729: Grand Total | G729: 2.9928788
A730: -4 | B730: 1.287
A731: -3 | B731: 1.287
A732: -2 | B732: 1.287
A733: -1 | B733: 1.287
A734: 0 | B734: 1.287
A735: 1 | B735: 1.287
A736: 2 | B736: 1.287
A737: 3 | B737: 1.287
A738: 4 | B738: 1.287
A739: 5 | B739: 1.287
A740: 6 | B740: 1.287
A741: 7 | B741: 1.287
... A914: 180 | B914: 1.287
A915: Grand Total | B915: 0.92777098
